Workbook

Sheet Sheet3
A1: 4488
A2: 4714
A3: 432.25
A4: 3669
A5: 4519
A6: 2451.25
A7: 472
A8: 1325
A9: 4235.25
A10: 4879
A11: 4984
A12: 4364.25
... A52: 1892

Sheet Chapter 1
B2: Personal Financial Statement | I2: Liquid Assets | L2: Investable Assets | O2: Savings Rate
B3: 1. Assets | O3: 3 Images from Savings Rate Table
B4: 2. Liabilities | O4: Income
B5: 3. Full PFS | O5: Expenses
O6: Total
B7: PERSONAL FINANCIAL STATEMENT: John Robinson
B8: As of December 31, 2022
B10: Assets | E10: Liabilities | I10: LIQUID ASSETS: John Robinson | L10: INVESTABLE ASSETS: John Robinson | O10: SAVINGS RATE: John Robinson
I11: As of December 31, 2022 | L11: As of December 31, 2022 | O11: As of December 31, 2022
C12: Estimated Value | F12: Estimated Value | I12: Cash or Cash Equivalent
B13: Cash or Cash Equivalent | E13: Loans | I13: Cash on Hand | J13: =C14 -> 200 | L13: Monthly Income | M13: =S26 -> 4000 | O13: Income | R13: Expenses
B14: Cash on Hand | C14: 200 | E14: Mortgage - Personal Residence | F14: 138200 | I14: Bank - Checking Account | J14: =C15 -> 20000 | L14: Desired Reserve (months) | M14: 3
B15: Bank - Checking Account | C15: 20000 | E15: School Loan | F15: 26300 | L15: Required Reserve ($) | M15: =M14*S26 -> 12000 | P15: Estimated Value | S15: Estimated Value
B16: Money Owed from Bill Jones | C16: 5000 | E16: Car Loan | F16: 3200 | I16: Investments | O16: Cash or Cash Equivalent | R16: Expenses
I17: Stocks | J17: =C22 -> 3200 | L17: Liquid Assets | M17: =J20 -> 24200 | O17: Monthly Salary | P17: 4500 | R17: Tax Withholdings | S17: =P17*0.3 -> 1350
B18: Retirement Accounts | E18: Revolving Debt | I18: Bonds | J18: =C23 -> 800 | L18: Required Reserves | M18: =-M15 -> -12000 | O18: Ridesharing Income | P18: 500 | R18: Mortgage Payments | S18: 1150
B19: Self-Directed IRA | C19: 54500 | E19: Credit Cards | F19: 6800 | R19: Student Loan Payments | S19: 200
I20: Total Liquid Assets | J20: =SUM(J13:J18) -> 24200 | L20: Investable Assets | M20: =M17-M15 -> 12200 | R20: Food & Groceries | S20: 400
B21: Investments | E21: Other | R21: Entertainment | S21: 300
B22: Stocks | C22: 3200 | E22: Estimated Taxes Owed on April 15 | F22: 18000 | R22: Car Loan payments | S22: 200
B23: Bonds | C23: 800 | R23: Gas | S23: 100
R24: Misc. | S24: 300
B25: Business Interests
B26: ABC Properties, LLC | C26: 65000 | I26: LIQUID ASSETS: John Robinson | O26: Total Income | P26: =SUM(P17:P23) -> 5000 | R26: Total Expenses | S26: =SUM(S17:S24) -> 4000
I27: As of December 31, 2022
B28: Real/Personal Property Owned | R28: Savings Rate | S28: =P26-S26 -> 1000
B29: Personal Residence | C29: 185000 | I29: Starting Liquid Assets | J29: 24200
B30: 2013 Honda CRV | C30: 7000 | I30: Investment Amount | J30: 20000
B31: Furniture and Household Goods | C31: 5000 | I31: Ending Liquid Assets | J31: =J29-J30 -> 4200 | R31: VARIABLE INCOME: John Robinson
B32: Jewelry | C32: 2000
R33: Rideshare Income May | S33: 350
B34: Assets Total | C34: =SUM(C14:C33) -> 347700 | E34: Liabilities Total | F34: =SUM(F14:F33) -> 192500 | R34: Rideshare Income June | S34: 475
R35: Rideshare Income July | S35: 675
E36: Estimated Net Worth: | F36: =C34-F34 -> 155200 | R36: Average Income | S36: =AVERAGE(S33:S35) -> 500
R39: VARIABLE EXPENSES: John Robinson
R41: May Expenses | S41: 3100
R42: June Expenses | S42: 3450
R43: July Expenses | S43: 3050
R44: Average Expenses | S44: =AVERAGE(S41:S43) -> 3200
R47: Month | S47: Savings Rate | T47: Investment(s) | U47: Liquid Assets
R48: Month 0 | S48: -1000 | T48: 0 | U48: 24200
R49: Month 1 | S49: -700 | T49: 20000 | U49: =U48-T49 -> 4200
R50: Month 2 | S50: -700 | T50: 0 | U50: =U49+S49 -> 3500
R51: Month 3 | S51: -700 | T51: 0 | U51: =U50+S50 -> 2800
R52: Month 4 | S52: -700 | T52: 0 | U52: =U51+S51 -> 2100
R53: Month 5 | S53: -700 | T53: 0 | U53: =U52+S52 -> 1400
R54: Month 6 | S54: -700 | T54: 0 | U54: =U53+S53 -> 700
R55: Month 7 | S55: -700 | T55: 0 | U55: =U54+S54 -> 0
R56: Month 8 | S56: -700 | T56: 0 | U56: =U55+S55 -> -700
R57: Month 9 | S57: -700 | T57: 0 | U57: =U56+S56 -> -1400
R58: Month 10 | S58: -700 | T58: 0 | U58: =U57+S57 -> -2100
R59: Month 11 | S59: -700 | T59: 0 | U59: =U58+S58 -> -2800
R60: Month 12 | S60: -700 | T60: 0 | U60: =U59+S59 -> -3500

Sheet IP Examples
C2: 457 Main St. | D2: 38 Holland Dr. | E2: 845 Chestnut Rd.
C3: Rental | D3: STR | E3: House Hack | J3: * different down payment amounts for House hack
B4: Price | C4: 122000 | D4: 175000 | E4: 165000 | J4: * interest only vs fully amortized for STR
B5: Expected Down Payment | C5: =C4*0.25 -> 30500 | D5: =D4*0.25 -> 43750 | E5: =E4*0.1 -> 16500 | J5: * Two interest rates
B6: Closing Costs | C6: 6000 | D6: 6000 | E6: 4500 | J6: * play our scenarios and explain pros/cons of each
B7: Reserve Funds | C7: =C4*0.05 -> 6100 | D7: =D4*0.08 -> 14000 | E7: =E4*0.05 -> 8250 | J7: * should we model an equity partner scenario? Maybe we do this in the flipping section?
B8: Cash Needed | C8: =SUM(C5:C7) -> 42600 | D8: =SUM(D5:D7) -> 63750 | E8: =SUM(E5:E7) -> 29250
B9: Cash on Hand | C9: ='Example PFS'!J47 -> 12200 | D9: =C9 -> 12200 | E9: =D9 -> 12200
B10: Cash Remaining | C10: =C9-C8 -> -30400 | D10: =D9-D8 -> -51550 | E10: =E9-E8 -> -17050
B11: Time to Afford (Months) | C11: =IF(C10>0, "Now", C10/'Example PFS'!$F$55) -> -30.4 | D11: =IF(D10>0, "Now", -D10/'Example PFS'!$F$55) -> 51.55 | E11: =IF(E10>0, "Now", E10/'Example PFS'!$F$55) -> -17.05
B16: Loan Option 1 | C16: 457 Main St. | D16: 457 Main St. | E16: 38 Holland Dr. | F16: 38 Holland Dr. | G16: 845 Chestnut Rd. | H16: 845 Chestnut Rd. | L16: Same property, different strategies?
B17: Purchase Price | C17: 122000 | D17: 122000 | E17: 175000 | F17: 175000 | G17: 165000 | H17: 165000 | L17: 3 different properties?
B18: Down Payment (%) | C18: 0.25 | D18: 0.25 | E18: 0.25 | F18: 0.25 | G18: 0.05 | H18: 0.2 | L18: * bonus videos of doing this analysis
B19: Loan Amount (Principal) | C19: 91500 | D19: 91500 | E19: =(1-E18)*E17 -> 131250 | F19: 131250 | G19: 156750 | H19: 132000 | L19: *
B20: Annual Interest Rate | C20: 0.04 | D20: 0.035 | E20: 0.0425 | F20: 0.035 | G20: 0.035 | H20: 0.035
B21: Term (Years) | C21: 30 | D21: 30 | E21: 30 | F21: 30 | G21: 30 | H21: 30
B22: Payments/year | C22: 12 | D22: 12 | E22: 12 | F22: 12 | G22: 12 | H22: 12
B23: Total Payments | C23: 360 | D23: 360 | E23: =E22*E21 -> 360 | F23: 360 | G23: 360 | H23: 360
B24: Payment per Period | C24: 436.835 | D24: 410.87589 | E24: =-PMT(E20/E22, E23, E19, 0) -> 645.67111 | F24: 589.37115 | G24: 703.87755 | H24: 592.73899
B25: PMI per Period | C25: 0 | D25: 0 | E25: 0 | F25: 0 | G25: 82 | H25: 0
B26: Sum of Payments | C26: 157260.6 | D26: 147915.32 | E26: =E24*E23 -> 232441.6 | F26: 212173.61 | G26: =253395.91733052+(G25*G23) -> 282915.92 | H26: 213386.04
B27: Interest Cost + PMI | C27: 65760.598 | D27: 56415.32 | E27: =E26-E19 -> 101191.6 | F27: 80923.615 | G27: =96645.9173305196+G25*G23 -> 126165.92 | H27: 81386.036
B28: Estimated Closing Costs | C28: 6000 | D28: 6000 | E28: 6000 | F28: 6000 | G28: 4500 | H28: 4500
B30: Loan Constant | C30: =((SUM(C24:C25)*12)/C19) -> 0.057289835 | D30: =((SUM(D24:D25)*12)/D19) -> 0.053885363 | E30: =((SUM(E24:E25)*12)/E19) -> 0.059032787 | F30: =((SUM(F24:F25)*12)/F19) -> 0.053885363 | G30: =((SUM(G24:G25)*12)/G19) -> 0.060162874 | H30: =((SUM(H24:H25)*12)/H19) -> 0.053885363
B31: Cap Rate
B32: Breakeven loan value
B35: Income Property Pro Forma

Sheet Chapter 2
B2: All images in Chapter 2 derived from this table
B5: BALANCE SHEET
B6: For Year Ending December 31, 2022
B8: ASSETS
B9: Investment in 123 Main Street
B10: Land | C10: 75462
B11: Buildings/Improvements | C11: =281559-7021 -> 274538
B12: Furniture & Fixtures | C12: 8254
B13: Accumulated Depreciation | C13: =-27115+7021 -> -20094
C14: =SUM(C10:C13) -> 338160
B16: Other Assets
B17: Cash in Operating Account | C17: 16581
B18: Replacement Reserves | C18: 14000
B19: Rents Receivable | C19: 2220
C20: =SUM(C17:C19) -> 32801
B22: TOTAL ASSETS | C22: =C14+C20 -> 370961
B24: LIABILITIES & OWNER EQUITY
B25: Liabilities
B26: Mortgage Principal Balance | C26: 276841
B27: Accounts Payable | C27: 16875
B28: Taxes Payable | C28: 12254
B29: Tenant Security Deposits | C29: 8450
B30: TOTAL LIABILITIES | C30: =SUM(C26:C29) -> 314420
B32: Owner Equity
B33: Initial Contributions | C33: 40000
B34: Retained Earnings | C34: =C22-C30-C33 -> 16541
B35: TOTAL OWNER EQUITY | C35: =SUM(C31:C34) -> 56541
B37: TOTAL LIABILITIES & OWNER EQUITY | C37: =C30+C35 -> 370961

Sheet Chapter 3
B2: All images in Chapter 3 derived from these 2 tables
B5: PROFIT & LOSS STATEMENT - GREAT FLIPS, LLC | E5: PROFIT & LOSS STATEMENT - GREAT FLIPS, LLC
B6: For the Fiscal Year 2022 (Jan. 1–Dec. 31, 2022) | E6: For the Fiscal Year 2022 (Jan. 1–Dec. 31, 2022)
B8: INCOME | E8: INCOME
B9: Revenue Source #1 | C9: 0 | E9: Revenue from Sale of Properties | F9: 375000
B10: Revenue Source #2 | C10: 0 | E10: Revenue from Commissions | F10: 25000
B11: … | E11: …
B12: TOTAL INCOME: | C12: 0 | E12: TOTAL INCOME | F12: =F9+F10 -> 400000
B14: Cost of Goods Sold (COGS) #1 | C14: 0 | E14: Property Purchase Costs | F14: 120000
B15: Cost of Goods Sold (COGS) #2 | C15: 0 | E15: Rehab Labor | F15: 75000
B16: … | E16: Rehab Materials | F16: 30000
B17: TOTAL COGS: | C17: 0 | E17: Closing Costs | F17: 6000
E18: TOTAL COGS | F18: =SUM(F14:F17) -> 231000
B19: GROSS PROFIT: | C19: 0
E20: GROSS PROFIT | F20: =F12-F18 -> 169000
B21: EXPENSES
B22: Expense Source #1 | C22: 0 | E22: EXPENSES
B23: Expense Source #2 | C23: 0 | E23: Rent | F23: 7200
B24: … | E24: Owner Salary | F24: 50000
B25: TOTAL OPERATING EXPENSES: | C25: 0 | E25: Insurance | F25: 2500
E26: Office Supplies | F26: 300
B27: OPERATING INCOME: | C27: 0
E28: Tools | F28: 2200
E30: Utilities | F30: 1800
E31: TOTAL OPERATING EXPENSES: | F31: =SUM(F23:F30) -> 64000
E33: OPERATING INCOME: | F33: =F20-F31 -> 105000
E35: 2022 Taxes | F35: 21000
E37: NET INCOME: | F37: =F33-F35 -> 84000
E39: Gross Profit Margin | F39: =F20/F12 -> 0.4225
E40: Operating Profit Margin | F40: =F33/F12 -> 0.2625
E41: Net Profit Margin | F41: =F37/F12 -> 0.21

Sheet Chapter 4
B2: All images in Chapter 4 derived from these 2 tables
E6: PROFIT & LOSS STATEMENT - Catherine Corp.
E7: For the Fiscal Year 2022 (Jan. 1 - Dec. 31, 2022)
B8: INCOME | E8: INCOME
B9: Gross Potential Rent | C9: - | E9: Gross Potential Rent | F9: 120000
B10: Rent Loss | C10: - | E10: Rent Loss | F10: -12000
B11: Other Income | C11: - | E11: Other Income | F11: 3000
B12: GROSS OPERATING INCOME: | C12: - | E12: GROSS OPERATING INCOME: | F12: 111000
E13: EXPENSES
E14: Property Taxes | F14: 5250
B15: EXPENSES | E15: Insurance | F15: 2810
B16: Property Taxes | C16: - | E16: Property Management | F16: 8640
B17: Insurance | C17: - | E17: Turnover | F17: 4800
B18: Property Management | C18: - | E18: Repairs & Maintenance | F18: 10000
B19: Turnover | C19: - | E19: Utilities | F19: 400
B20: Repairs & Maintenance | C20: - | E20: Lawn Care | F20: 3600
B21: Utilities | C21: - | E21: Snow Removal | F21: 0
B22: Lawn Care | C22: - | E22: Dumpster/Trash Removal | F22: 0
B23: Snow Removal | C23: - | E23: Grounds Cleanup | F23: 3000
B24: Dumpster/Trash Removal | C24: - | E24: Office Costs | F24: 0
B25: Grounds Cleanup | C25: - | E25: Legal | F25: 0
B26: Office Costs | C26: - | E26: Accounting | F26: 1500
B27: Legal | C27: - | E27: OPERATING EXPENSES: | F27: 40000
B28: Accounting | C28: - | E28: NET OPERATING INCOME: | F28: 71000
E29: Debt Service | F29: -40200
E30: Capital Expenses | F30: -5000
E31: CASH FLOW BEFORE TAX | F31: =SUM(F28:F30) -> 25800

Sheet Chapter 6
C6: Year-End Balance | D6: Interest Rate | E6: Annual Profit
B7: Year 1 | C7: 10000 | D7: 0.05 | E7: =D7*C7 -> 500
B8: Year 2 | C8: 10000 | D8: 0.05 | E8: =D8*C8 -> 500
B9: Year 3 | C9: 10000 | D9: 0.05 | E9: =D9*C9 -> 500
B10: Year 4 | C10: 10000 | D10: 0.05 | E10: =D10*C10 -> 500
B11: Year 5 | C11: 10000 | D11: 0.05 | E11: =D11*C11 -> 500
C14: Year-End Balance | D14: Interest Rate | E14: Annual Profit
B15: Year 1 | C15: 10000 | D15: 0.05 | E15: =D15*C15 -> 500
B16: Year 2 | C16: =C15+E15 -> 10500 | D16: 0.05 | E16: =D16*C16 -> 525
B17: Year 3 | C17: =C16+E16 -> 11025 | D17: 0.05 | E17: =D17*C17 -> 551.25
B18: Year 4 | C18: =C17+E17 -> 11576.25 | D18: 0.05 | E18: =D18*C18 -> 578.8125
B19: Year 5 | C19: =C18+E18 -> 12155.062 | D19: 0.05 | E19: =D19*C19 -> 607.75313
B27: Compounding
B28: Year | C28: Compounding Interest | D28: Simple Interest | E28: Interest Rate | F28: Compounding vs. Simple % Difference
B29: 0 | C29: 10000 | D29: 10000 | E29: 0.08
B30: 1 | C30: =C29*(1+E29) -> 10800 | D30: =D29+(C$29*E30) -> 10800 | E30: 0.08 | F30: =C30/D30-1 -> 0
B31: 2 | C31: =C30*(1+E30) -> 11664 | D31: =D30+(C$29*E31) -> 11600 | E31: 0.08 | F31: =C31/D31-1 -> 0.0055172414
B32: 3 | C32: =C31*(1+E31) -> 12597.12 | D32: =D31+(C$29*E32) -> 12400 | E32: 0.08 | F32: =C32/D32-1 -> 0.015896774
B33: 4 | C33: =C32*(1+E32) -> 13604.89 | D33: =D32+(C$29*E33) -> 13200 | E33: 0.08 | F33: =C33/D33-1 -> 0.030673455
B34: 5 | C34: =C33*(1+E33) -> 14693.281 | D34: =D33+(C$29*E34) -> 14000 | E34: 0.08 | F34: =C34/D34-1 -> 0.049520055
B35: 6 | C35: =C34*(1+E34) -> 15868.743 | D35: =D34+(C$29*E35) -> 14800 | E35: 0.08 | F35: =C35/D35-1 -> 0.07221238
B36: 7 | C36: =C35*(1+E35) -> 17138.243 | D36: =D35+(C$29*E36) -> 15600 | E36: 0.08 | F36: =C36/D36-1 -> 0.0986053
B37: 8 | C37: =C36*(1+E36) -> 18509.302 | D37: =D36+(C$29*E37) -> 16400 | E37: 0.08 | F37: =C37/D37-1 -> 0.12861598
B38: 9 | C38: =C37*(1+E37) -> 19990.046 | D38: =D37+(C$29*E38) -> 17200 | E38: 0.08 | F38: =C38/D38-1 -> 0.16221199
B39: 10 | C39: =C38*(1+E38) -> 21589.25 | D39: =D38+(C$29*E39) -> 18000 | E39: 0.08 | F39: =C39/D39-1 -> 0.19940278
B40: 11 | C40: =C39*(1+E39) -> 23316.39 | D40: =D39+(C$29*E40) -> 18800 | E40: 0.08 | F40: =C40/D40-1 -> 0.24023351
B41: 12 | C41: =C40*(1+E40) -> 25181.701 | D41: =D40+(C$29*E41) -> 19600 | E41: 0.08 | F41: =C41/D41-1 -> 0.28478067
... B59: 30 | C59: =C58*(1+E58) -> 100626.57 | D59: =D58+(C$29*E59) -> 34000 | E59: 0.08 | F59: =C59/D59-1 -> 1.959605

Sheet Chapter 8
B5: Month | C5: Principal | D5: ROR | E5: Return | H5: Month | I5: FV | J5: Discount Rate | K5: PV
B6: January | C6: 1000 | D6: 0.01 | E6: 10 | H6: December | I6: 1000 | J6: 0.01 | K6: 990.1
B7: February | C7: =C6+E6 -> 1010 | D7: 0.01 | E7: 10.1 | H7: November | I7: 990.1 | J7: 0.01 | K7: 980.3
B8: March | C8: =C7+E7 -> 1020.1 | D8: 0.01 | E8: 10.2 | H8: October | I8: 980.3 | J8: 0.01 | K8: 970.59
B9: April | C9: =C8+E8 -> 1030.3 | D9: 0.01 | E9: 10.3 | H9: September | I9: 970.59 | J9: 0.01 | K9: 960.98
B10: May | C10: =C9+E9 -> 1040.6 | D10: 0.01 | E10: 10.41 | H10: August | I10: 960.98 | J10: 0.01 | K10: 951.47
B11: June | C11: =C10+E10 -> 1051.01 | D11: 0.01 | E11: 10.51 | H11: July | I11: 951.47 | J11: 0.01 | K11: 942.05
B12: July | C12: =C11+E11 -> 1061.52 | D12: 0.01 | E12: 10.62 | H12: June | I12: 942.05 | J12: 0.01 | K12: 932.72
B13: August | C13: =C12+E12 -> 1072.14 | D13: 0.01 | E13: 10.72 | H13: May | I13: 932.72 | J13: 0.01 | K13: 923.48
B14: September | C14: =C13+E13 -> 1082.86 | D14: 0.01 | E14: 10.83 | H14: April | I14: 923.48 | J14: 0.01 | K14: 914.34
B15: October | C15: =C14+E14 -> 1093.69 | D15: 0.01 | E15: 10.94 | H15: March | I15: 914.34 | J15: 0.01 | K15: 905.29
B16: November | C16: =C15+E15 -> 1104.63 | D16: 0.01 | E16: 11.05 | H16: February | I16: 905.29 | J16: 0.01 | K16: 896.32
B17: December | C17: =C16+E16 -> 1115.68 | D17: 0.01 | E17: 11.16 | H17: January | I17: 896.32 | J17: 0.01 | K17: 887.45
B18: End of Year | C18: 1126.83 | J18: Present Value = | K18: 887.45

Sheet Chapter 9
B4: Year | C4: Property #1 | D4: Property #2 | F4: Discount Rate | G4: 0.08
B5: 1 | C5: 5000 | D5: 15000
B6: 2 | C6: 8000 | D6: 15000 | F6: Year | G6: Cash Flow | H6: Present Value | I6: Equation
B7: 3 | C7: 12000 | D7: 15000 | F7: 1 | G7: 200000 | H7: =G7/(1+$G$4)^F7 -> 185185.19 | I7: $200,000 ¸ ((1 + 0.08) ^ 1)
B8: 4 | C8: 125000 | D8: 105000 | F8: 2 | G8: 200000 | H8: =G8/(1+$G$4)^F8 -> 171467.76 | I8: $200,000 ¸ ((1 + 0.08) ^ 2)
B9: Totals: | C9: 150000 | D9: 150000 | F9: 3 | G9: 200000 | H9: =G9/(1+$G$4)^F9 -> 158766.45 | I9: $200,000 ¸ ((1 + 0.08) ^ 3)
F10: 4 | G10: 200000 | H10: =G10/(1+$G$4)^F10 -> 147005.97 | I10: $200,000 ¸ ((1 + 0.08) ^ 4)
F11: 5 | G11: 200000 | H11: =G11/(1+$G$4)^F11 -> 136116.64 | I11: $200,000 ¸ ((1 + 0.08) ^ 5)
F12: 6 | G12: 200000 | H12: =G12/(1+$G$4)^F12 -> 126033.93 | I12: $200,000 ¸ ((1 + 0.08) ^ 6)
B13: Property 1 | F13: 7 | G13: 200000 | H13: =G13/(1+$G$4)^F13 -> 116698.08 | I13: $200,000 ¸ ((1 + 0.08) ^ 7)
B14: Discount Rate | C14: 0.08 | F14: 8 | G14: 200000 | H14: =G14/(1+$G$4)^F14 -> 108053.78 | I14: $200,000 ¸ ((1 + 0.08) ^ 8)
F15: 9 | G15: 200000 | H15: =G15/(1+$G$4)^F15 -> 100049.79 | I15: $200,000 ¸ ((1 + 0.08) ^ 9)
B16: Year | C16: Cash Flow | D16: Present Value | F16: 10 | G16: 200000 | H16: =G16/(1+$G$4)^F16 -> 92638.698 | I16: $200,000 ¸ ((1 + 0.08) ^ 10)
B17: 1 | C17: 5000 | D17: =C17/(1+$C$14)^B17 -> 4629.6296 | F17: 11 | G17: 200000 | H17: =G17/(1+$G$4)^F17 -> 85776.572 | I17: $200,000 ¸ ((1 + 0.08) ^ 11)
B18: 2 | C18: 8000 | D18: =C18/(1+$C$14)^B18 -> 6858.7106 | F18: 12 | G18: 200000 | H18: =G18/(1+$G$4)^F18 -> 79422.752 | I18: $200,000 ¸ ((1 + 0.08) ^ 12)
B19: 3 | C19: 12000 | D19: =C19/(1+$C$14)^B19 -> 9525.9869 | F19: 13 | G19: 200000 | H19: =G19/(1+$G$4)^F19 -> 73539.585 | I19: $200,000 ¸ ((1 + 0.08) ^ 13)
B20: 4 | C20: 125000 | D20: =C20/(1+$C$14)^B20 -> 91878.732 | F20: 14 | G20: 200000 | H20: =G20/(1+$G$4)^F20 -> 68092.208 | I20: $200,000 ¸ ((1 + 0.08) ^ 14)
B21: Totals: | C21: 150000 | D21: =SUM(D17:D20) -> 112893.06 | F21: 15 | G21: 200000 | H21: =G21/(1+$G$4)^F21 -> 63048.341 | I21: $200,000 ¸ ((1 + 0.08) ^ 15)
F22: 16 | G22: 200000 | H22: =G22/(1+$G$4)^F22 -> 58378.094 | I22: $200,000 ¸ ((1 + 0.08) ^ 16)
F23: 17 | G23: 200000 | H23: =G23/(1+$G$4)^F23 -> 54053.79 | I23: $200,000 ¸ ((1 + 0.08) ^ 17)
B24: Property 2 | F24: 18 | G24: 200000 | H24: =G24/(1+$G$4)^F24 -> 50049.806 | I24: $200,000 ¸ ((1 + 0.08) ^ 18)
B25: Discount Rate | C25: 0.08 | F25: 19 | G25: 200000 | H25: =G25/(1+$G$4)^F25 -> 46342.413 | I25: $200,000 ¸ ((1 + 0.08) ^ 19)
F26: 20 | G26: 200000 | H26: =G26/(1+$G$4)^F26 -> 42909.641 | I26: $200,000 ¸ ((1 + 0.08) ^ 20)
B27: Year | C27: Cash Flow | D27: Present Value | F27: 21 | G27: 200000 | H27: =G27/(1+$G$4)^F27 -> 39731.15 | I27: $200,000 ¸ ((1 + 0.08) ^ 21)
B28: 1 | C28: 15000 | D28: =C28/(1+$C$25)^B28 -> 13888.889 | F28: 22 | G28: 200000 | H28: =G28/(1+$G$4)^F28 -> 36788.101 | I28: $200,000 ¸ ((1 + 0.08) ^ 22)
B29: 2 | C29: 15000 | D29: =C29/(1+$C$25)^B29 -> 12860.082 | F29: 23 | G29: 200000 | H29: =G29/(1+$G$4)^F29 -> 34063.057 | I29: $200,000 ¸ ((1 + 0.08) ^ 23)
B30: 3 | C30: 15000 | D30: =C30/(1+$C$25)^B30 -> 11907.484 | F30: 24 | G30: 200000 | H30: =G30/(1+$G$4)^F30 -> 31539.867 | I30: $200,000 ¸ ((1 + 0.08) ^ 24)
B31: 4 | C31: 105000 | D31: =C31/(1+$C$25)^B31 -> 77178.135 | F31: 25 | G31: 200000 | H31: =G31/(1+$G$4)^F31 -> 29203.581 | I31: $200,000 ¸ ((1 + 0.08) ^ 25)
B32: Totals: | C32: 150000 | D32: =SUM(D28:D31) -> 115834.59 | F32: Totals: | H32: =SUM(H7:H31) -> 2134955.2

Sheet Chapter 10
B2: Discount Rate | C2: 0.12
B3: Initial Cost | C3: 77000
C5: Year | D5: Cash Flow | E5: Present Value | F5: Formula
B6: 43831 | C6: 0 | D6: =-C3 -> -77000 | E6: =-C3 -> -77000
B7: 44197 | C7: 1 | D7: 9600 | E7: =D7/(1+C$2)^C7 -> 8571.4286 | F7: PV = (9,600 ÷ (1+.12)1
B8: 44562 | C8: 2 | D8: 9600 | E8: =D8/(1+C$2)^C8 -> 7653.0612 | F8: PV = (9,600 ÷ (1+.12)2
B9: 44927 | C9: 3 | D9: 9600 | E9: =D9/(1+C$2)^C9 -> 6833.0904 | F9: PV = (9,600 ÷ (1+.12)3
B10: 45292 | C10: 4 | D10: 9600 | E10: =D10/(1+C$2)^C10 -> 6100.9736 | F10: PV = (9,600 ÷ (1+.12)4
B11: 45658 | C11: 5 | D11: 9600 | E11: =D11/(1+C$2)^C11 -> 5447.2978 | F11: PV = (9,600 ÷ (1+.12)5
B12: 46023 | C12: 6 | D12: 9600 | E12: =D12/(1+C$2)^C12 -> 4863.6588 | F12: PV = (9,600 ÷ (1+.12)6
B13: 46388 | C13: 7 | D13: 9600 | E13: =D13/(1+C$2)^C13 -> 4342.5525 | F13: PV = (9,600 ÷ (1+.12)7
B14: 46753 | C14: 8 | D14: 9600 | E14: =D14/(1+C$2)^C14 -> 3877.279 | F14: PV = (9,600 ÷ (1+.12)8
B15: 47119 | C15: 9 | D15: 9600 | E15: =D15/(1+C$2)^C15 -> 3461.8562 | F15: PV = (9,600 ÷ (1+.12)9
B16: 47484 | C16: 10 | D16: 9600 | E16: =D16/(1+C$2)^C16 -> 3090.9431 | F16: PV = (9,600 ÷ (1+.12)10
C17: Net Present Value | E17: =SUM(E6:E16) -> -22757.859
C18: IRR | E18: =XIRR(D6:D16,B6:B16) -> 0.042209962
B22: Discount Rate | C22: 0.12
B23: Initial Cost | C23: 54242
C25: Year | D25: Cash Flow | E25: Present Value
B26: 43831 | C26: 0 | D26: =-C23 -> -54242 | E26: =-C23 -> -54242
B27: 44197 | C27: 1 | D27: 9600 | E27: =D27/(1+C$22)^C27 -> 8571.4286
B28: 44562 | C28: 2 | D28: 9600 | E28: =D28/(1+C$22)^C28 -> 7653.0612
B29: 44927 | C29: 3 | D29: 9600 | E29: =D29/(1+C$22)^C29 -> 6833.0904
B30: 45292 | C30: 4 | D30: 9600 | E30: =D30/(1+C$22)^C30 -> 6100.9736
B31: 45658 | C31: 5 | D31: 9600 | E31: =D31/(1+C$22)^C31 -> 5447.2978
B32: 46023 | C32: 6 | D32: 9600 | E32: =D32/(1+C$22)^C32 -> 4863.6588
B33: 46388 | C33: 7 | D33: 9600 | E33: =D33/(1+C$22)^C33 -> 4342.5525
B34: 46753 | C34: 8 | D34: 9600 | E34: =D34/(1+C$22)^C34 -> 3877.279
B35: 47119 | C35: 9 | D35: 9600 | E35: =D35/(1+C$22)^C35 -> 3461.8562
B36: 47484 | C36: 10 | D36: 9600 | E36: =D36/(1+C$22)^C36 -> 3090.9431
C37: Net Present Value | D37: =ROUND(NPV(C22, D27:D36)+D26,0) -> 0 | E37: =ROUND(SUM(E26:E36),0) -> 0 | G37: Added rounding functions here
C38: IRR | E38: =ROUND(XIRR(D26:D36,B26:B36),2) -> 0.12 | G38: Added rounding functions here
B42: Discount Rate | C42: 0.07
B43: Initial Cost | C43: 100000
C45: Year | D45: Cashflow | E45: Present Value
B46: 43831 | C46: 0 | D46: 50000 | E46: -100000
B47: 44197 | C47: 1 | D47: 1500 | E47: =D47/(1+$C$42)^C47 -> 1401.8692
B48: 44562 | C48: 2 | D48: 1500 | E48: =D48/(1+$C$42)^C48 -> 1310.1581
B49: 44927 | C49: 3 | D49: 1500 | E49: =D49/(1+$C$42)^C49 -> 1224.4468
B50: 45292 | C50: 4 | D50: 1500 | E50: =D50/(1+$C$42)^C50 -> 1144.3428
B51: 45658 | C51: 5 | D51: 92000 | E51: =D51/(1+$C$42)^C51 -> 65594.729
C52: Net Present Value | E52: =SUM(E46:E51) -> -29324.455
B57: Discount Rate | C57: 0.05
B58: Initial Cost | C58: 100000
C60: Year | D60: Cash Flow | E60: Present Value
B61: 43831 | C61: 0 | D61: -100000 | E61: -100000
B62: 44197 | C62: 1 | D62: 2000 | E62: 1905
B63: 44562 | C63: 2 | D63: 2000 | E63: 1814
B64: 44927 | C64: 3 | D64: 2000 | E64: 1728
B65: 45292 | C65: 4 | D65: 2000 | E65: 1645
B66: 45658 | C66: 5 | D66: 130000 | E66: 101858
D67: Net Present Value | E67: 8950.3

Sheet Chapter 11
B9: Discount Rate | C9: 0.05
B10: Initial Cost | C10: 100000
C12: Year | D12: Cashflow | E12: Present Value
B13: 43831 | C13: 0 | D13: -100000 | E13: -100000
B14: 44197 | C14: 1 | D14: 2000 | E14: =D14/(1+$C$9)^C14 -> 1904.7619
B15: 44562 | C15: 2 | D15: 2000 | E15: =D15/(1+$C$9)^C15 -> 1814.059
B16: 44927 | C16: 3 | D16: 2000 | E16: =D16/(1+$C$9)^C16 -> 1727.6752
B17: 45292 | C17: 4 | D17: 2000 | E17: =D17/(1+$C$9)^C17 -> 1645.4049
B18: 45658 | C18: 5 | D18: 130000 | E18: =D18/(1+$C$9)^C18 -> 101858.4
C19: Net Present Value | E19: =SUM(E13:E18) -> 8950.3026
B23: Discount Rate | C23: =D44 -> 0.068727639
B24: Initial Cost | C24: 100000
C26: Year | D26: Cashflow | E26: Present Value
B27: 43831 | C27: 0 | D27: -100000 | E27: -100000
B28: 44197 | C28: 1 | D28: 2000 | E28: =D28/(1+$C$23)^C28 -> 1871.3842
B29: 44562 | C29: 2 | D29: 2000 | E29: =D29/(1+$C$23)^C29 -> 1751.0394
B30: 44927 | C30: 3 | D30: 2000 | E30: =D30/(1+$C$23)^C30 -> 1638.4337
B31: 45292 | C31: 4 | D31: 2000 | E31: =D31/(1+$C$23)^C31 -> 1533.0695
B32: 45658 | C32: 5 | D32: 130000 | E32: =D32/(1+$C$23)^C32 -> 93241.263
C33: Net Present Value | E33: =ROUND(SUM(E27:E32),-2) -> 0
C37: Year | D37: Cashflow
B38: 43831 | C38: 0 | D38: -100000
B39: 44197 | C39: 1 | D39: 2000
B40: 44562 | C40: 2 | D40: 2000
B41: 44927 | C41: 3 | D41: 2000
B42: 45292 | C42: 4 | D42: 2000
B43: 45658 | C43: 5 | D43: 130000
C44: IRR | D44: =XIRR(D38:D43, B38:B43) -> 0.068727639

Sheet Chapter 12
B3: NOI | C3: 61428
B5: Interest Paid | C5: 32817
B7: Purchase Price | C7: 1000000
B8: Structure Value (%) | C8: 0.73
B9: Structure Cost ($) | C9: =C8*C7 -> 730000
B10: Depreciation Period (Years) | C10: 27.5
B11: Depreciation ($) | C11: =C9/C10 -> 26545.455
B13: Mortgage "Points" | C13: 13000
B14: Amortization Period (Years) | C14: 25
B15: Amortization ($) | C15: =C13/C14 -> 520
B16: Taxable Income | C16: =C3-C5-C11-C15 -> 1545.5455
B17: Tax Rate | C17: 0.24
B18: Taxes Owed | C18: =C17*C16 -> 370.93091
B22: Purchase Price | C22: 250000
B23: Closing Costs | C23: 5000
B24: Basis | C24: =SUM(C22:C23) -> 255000
B26: Purchase Price | C26: 250000
B27: Purchase Costs | C27: 5000
B28: Capital Expenditures | C28: 45000
B29: Sellings Costs | C29: 35000
B30: Depreciation ($) | C30: -30000
B31: Adjusted Basis | C31: =SUM(C26:C30) -> 305000
B36: Sale Price | C36: 400000
B37: Adjusted Basis | C37: 305000
B38: Taxable Gain | C38: =C36-C37 -> 95000
B40: Depreciation Recapture | C40: 30000
B41: Depreciation Recapture Rate | C41: 0.24
B42: Depreciation Recapture Owed | C42: =C40*C41 -> 7200
B44: Capital Gains | C44: 65000
B45: Capital Gains Tax Rate | C45: =15% -> 0.15
B46: Capital Gains Tax Owed | C46: =C45*C44 -> 9750
B47: Total Tax Owed | C47: =C42+C46 -> 16950

Sheet Chapter 14
B8: Return Metric | C8: Answers Q1 | D8: Answers Q2 | E8: Answers Q3 | F8: Answers Q4
B9: Profit | C9: X
B10: Net Operating Income (NOI) | C10: X
B11: Cash Flow (CF) | C11: X
B12: Return on Investment (ROI) | D12: X
B13: Equity Multiplier (EM) | D13: X
B14: Capitalization Rate (Cap Rate) | E14: X
B15: Cash-on-Cash Return (COC) | E15: X
B16: Average Annual Return (AAR) | E16: X
B17: Compound Annual Growth Rate (CAGR) | F17: X
B18: Internal Rate of Return (IRR) | F18: X

Sheet Chapter 15
B5: PROFIT & LOSS STATEMENT - Catherine Corp
B6: For the Fiscal Year 2022 (Jan. 1–Dec. 31, 2022)
B7: INCOME
B8: Gross Potential Rent | C8: 120000
B9: Rent Loss | C9: -12000
B10: Other Income | C10: 3000
B11: GROSS OPERATING INCOME: | C11: 111000
B12: EXPENSES
B13: Property Taxes | C13: 5250
B14: Insurance | C14: 2810
B15: Property Management | C15: 8640
B16: Turnover | C16: 4800
B17: Repairs & Maintenance | C17: 10000
B18: Utilities | C18: 400
B19: Lawn Care | C19: 3600
B20: Snow Removal | C20: 0
B21: Dumpster/Trash Removal | C21: 0
B22: Grounds Cleanup | C22: 3000
B23: Office Costs | C23: 0
B24: Legal | C24: 0
... B29: Capital Expenses | C29: -5000
B30: CASH FLOW BEFORE TAX | C30: =SUM(C27:C29) -> 25800
B31: Tax Rate | C31: 0.35
B32: Taxes Owed | C32: =-C31*C30 -> -9030
B33: Cash Flow After Taxes | C33: =C30+C32 -> 16770

Sheet Chapter 17
C2: Year | D2: Cash Flow
C3: Year 1 | D3: 5000
C4: Year 2 | D4: 8000
C5: Year 3 | D5: 12000
C6: Year 4 | D6: 200000
C7: Ending Value | D7: =SUM(D3:D6) -> 225000

Sheet Chapter 18
C4: Deal #1 | D4: Deal #2 | E4: Deal #3
B5: NOI | C5: 1058000 | D5: 2157000 | E5: 1165000
B6: Value (Asking Price) | C6: 22000000 | D6: 36000000 | E6: 30000000
B7: Cap Rate (NOI ÷ Value) | C7: 0.048 | D7: 0.06 | E7: 0.039

Sheet Chapter 20
B5: Year | C5: Portfolio Value | D5: Annual Growth Rate
B6: Year 0 | C6: 10000
B7: Year 1 | C7: =C6*(1+D7) -> 11500 | D7: 0.15
B8: Year 2 | C8: =C7*(1+D8) -> 13570 | D8: 0.18
B9: Year 3 | C9: =C8*(1+D9) -> 11941.6 | D9: -0.12
B10: Year 4 | C10: =C9*(1+D10) -> 10866.856 | D10: -0.09
B11: Year 5 | C11: =C10*(1+D11) -> 10323.513 | D11: -0.05
B12: Year 6 | C12: =C11*(1+D12) -> 9084.6916 | D12: -0.12
B13: Year 7 | C13: =C12*(1+D13) -> 10901.63 | D13: 0.2
B14: Year 8 | C14: =C13*(1+D14) -> 12536.874 | D14: 0.15
B15: Year 9 | C15: =C14*(1+D15) -> 14041.299 | D15: 0.12
B16: ROI | C16: =C15/C6-1 -> 0.40412994
B17: AAR | C17: =SUM(D7:D15)/9 -> 0.046666667
B18: CAGR | C18: =_xlfn.RRI(9, C6, C15) -> 0.038433258
C22: Portfolio Value | D22: % Change
B23: Year 0 | C23: 10000
B24: Year 1 | C24: =C23*(1+D24) -> 12000 | D24: 0.2
B25: Year 2 | C25: =C24*(1+D25) -> 9600 | D25: -0.2
C44: SCENARIO #1 | E44: SCENARIO #2 | G44: SCENARIO #3 | I44: SCENARIO #4
B45: Year | C45: ROI | D45: Balance | E45: ROI | F45: Balance | G45: ROI | H45: Balance | I45: ROI | J45: Balance
B46: 0 | D46: 100000 | F46: 100000 | H46: 100000 | J46: 100000
B47: 1 | C47: 0.1 | D47: 110000 | E47: 0.15 | F47: 115000 | G47: 0.2 | H47: 120000 | I47: 0.3 | J47: 130000
B48: 2 | C48: 0.1 | D48: 121000 | E48: 0.1 | F48: 126500 | G48: 0.1 | H48: 132000 | I48: 0 | J48: 130000
B49: 3 | C49: 0.1 | D49: 133100 | E49: 0.05 | F49: 132825 | G49: 0 | H49: 132000 | I49: 0 | J49: 130000
C50: AAR = 10% | E50: AAR = 10% | G50: AAR = 10% | I50: AAR = 10%

Sheet Chapter 21
B5: Year | C5: Annual Growth Rate | D5: Portfolio Value
B6: Year 0 | D6: 10000
B7: Year 1 | C7: 0.15 | D7: =D6*(1+C7) -> 11500
B8: Year 2 | C8: 0.18 | D8: =D7*(1+C8) -> 13570
B9: Year 3 | C9: -0.12 | D9: =D8*(1+C9) -> 11941.6
B10: Year 4 | C10: -0.09 | D10: =D9*(1+C10) -> 10866.856
B11: Year 5 | C11: -0.05 | D11: =D10*(1+C11) -> 10323.513
B12: Year 6 | C12: -0.12 | D12: =D11*(1+C12) -> 9084.6916
B13: Year 7 | C13: 0.2 | D13: =D12*(1+C13) -> 10901.63
B14: Year 8 | C14: 0.15 | D14: =D13*(1+C14) -> 12536.874 | F14: CAGR
B15: Year 9 | C15: 0.12 | D15: =D14*(1+C15) -> 14041.299 | F15: =_xlfn.RRI(9,D6,D15) -> 0.038433258
C18: Annual Growth Rate | D18: Portfolio Value
B19: Year 0 | D19: 10000
B20: Year 1 | C20: =F15 -> 0.038433258 | D20: =D19*(1+C20) -> 10384.333
B21: Year 2 | C21: =C20 -> 0.038433258 | D21: =D20*(1+C21) -> 10783.436
B22: Year 3 | C22: =C21 -> 0.038433258 | D22: =D21*(1+C22) -> 11197.879
B23: Year 4 | C23: =C22 -> 0.038433258 | D23: =D22*(1+C23) -> 11628.25
B24: Year 5 | C24: =C23 -> 0.038433258 | D24: =D23*(1+C24) -> 12075.161
B25: Year 6 | C25: =C24 -> 0.038433258 | D25: =D24*(1+C25) -> 12539.249
B26: Year 7 | C26: =C25 -> 0.038433258 | D26: =D25*(1+C26) -> 13021.173
B27: Year 8 | C27: =C26 -> 0.038433258 | D27: =D26*(1+C27) -> 13521.619
B28: Year 9 | C28: =C27 -> 0.038433258 | D28: =D27*(1+C28) -> 14041.299
C32: Purchase Price | D32: Current Value | E32: Hold Period (Years) | F32: CAGR | I32: =D33/C33 -> 1.7866667 | J32: =1/12 -> 0.083333333 | K32: =I32^J32 -> 1.0495512
B33: Property 1 | C33: 150000 | D33: 268000 | E33: 12 | F33: =_xlfn.RRI(E33,C33,D33) -> 0.049551196 | I33: =D34/C34 -> 1.7045455 | J33: =1/12 -> 0.083333333 | K33: =I33^J33 -> 1.0454439
B34: Property 2 | C34: 220000 | D34: 375000 | E34: 12 | F34: =_xlfn.RRI(E34,C34,D34) -> 0.045443858

Sheet Chapter 22
B3: Date | C3: Month # | D3: Cashflows
B4: 39661 | C4: 0 | D4: -63500
B5: 39692 | C5: 1 | D5: -17000
B6: 39722 | C6: 2 | D6: -17000
B7: 39753 | C7: 3 | D7: 0
B8: 39783 | C8: 4 | D8: 0
B9: 39814 | C9: 5 | D9: 0
B10: 39845 | C10: 6 | D10: 0
B11: 39873 | C11: 7 | D11: 0
B12: 39904 | C12: 8 | D12: 0
B13: 39934 | C13: 9 | D13: 1000
B14: 39965 | C14: 10 | D14: 1000
B15: 39995 | C15: 11 | D15: 1000
B16: 40026 | C16: 12 | D16: =1000-1400 -> -400
B17: 40057 | C17: 13 | D17: 1000
B18: 40087 | C18: 14 | D18: 1000
B19: 40118 | C19: 15 | D19: 1000
B20: 40148 | C20: 16 | D20: 1000
B21: 40179 | C21: 17 | D21: 1000
B22: 40210 | C22: 18 | D22: 1000
B23: 40238 | C23: 19 | D23: 1000
B24: 40269 | C24: 20 | D24: 1000
B25: 40299 | C25: 21 | D25: 1000
B26: 40330 | C26: 22 | D26: 1000
B27: 40360 | C27: 23 | D27: 1000
B28: 40391 | C28: 24 | D28: =66320+100-2300-1200 -> 62920
B29: 40422 | C29: 25 | D29: 1000
B30: 40452 | C30: 26 | D30: 1000
B31: 40483 | C31: 27 | D31: 1000
B32: 40513 | C32: 28 | D32: 1000
B33: 40544 | C33: 29 | D33: 1000
B34: 40575 | C34: 30 | D34: 1000
B35: 40603 | C35: 31 | D35: 1000
B36: 40634 | C36: 32 | D36: 1000
B37: 40664 | C37: 33 | D37: 1000
B38: 40695 | C38: 34 | D38: 1000
B39: 40725 | C39: 35 | D39: 50000
B40: IRR | D40: =XIRR(D4:D39, B4:B39) -> 0.1621164

Sheet Chapter 23
B2: Investment 1
B3: Year | C3: Account Balance | D3: ROI
B4: Year 0 | C4: 1000
B5: Year 1 | C5: 1200 | D5: =C5/C4-1 -> 0.2
B6: Year 2 | C6: 1250 | D6: =C6/C5-1 -> 0.041666667
B7: Year 3 | C7: 1400 | D7: =C7/C6-1 -> 0.12
B8: Year 4 | C8: 1300 | D8: =C8/C7-1 -> -0.071428571
B9: Year 5 | C9: 1150 | D9: =C9/C8-1 -> -0.11538462
B10: Year 6 | C10: 1600 | D10: =C10/C9-1 -> 0.39130435
B11: Year 7 | C11: 1800 | D11: =C11/C10-1 -> 0.125
B12: Year 8 | C12: 2000 | D12: =C12/C11-1 -> 0.11111111
B13: Year 9 | C13: 2100 | D13: =C13/C12-1 -> 0.05
B14: Year 10 | C14: 2400 | D14: =C14/C13-1 -> 0.14285714
B15: ROI | C15: =C14/C4-1 -> 1.4
B16: AAR | C16: =SUM(D5:D14)/COUNT(D5:D14) -> 0.099512608
B17: CAGR | C17: =_xlfn.RRI(10, C4, C14) -> 0.091493426
B21: Investment 2
B22: Year | C22: Account Balance | D22: ROI
B23: Year 0 | C23: 1000
B24: Year 1 | C24: 1200 | D24: =C24/C23-1 -> 0.2
B25: Year 2 | C25: 1250 | D25: =C25/C24-1 -> 0.041666667
B26: Year 3 | C26: 1400 | D26: =C26/C25-1 -> 0.12
B27: Year 4 | C27: 1300 | D27: =C27/C26-1 -> -0.071428571
B28: Year 5 | C28: 1450 | D28: =C28/C27-1 -> 0.11538462
B29: Year 6 | C29: 1600 | D29: =C29/C28-1 -> 0.10344828
B30: Year 7 | C30: 1900 | D30: =C30/C29-1 -> 0.1875
B31: ROI | C31: =C30/C23-1 -> 0.9
B32: AAR | C32: =SUM(D24:D30)/COUNT(D24:D30) -> 0.099510141
B33: CAGR | C33: =_xlfn.RRI(7, C23, C30) -> 0.096028742
A36: S | B36: Scenario 1 | G36: Scenario 2
B37: Purchase Price | C37: 480000 | G37: Purchase Price | H37: 480000
B38: Financing | C38: 0.8 | G38: Financing | H38: 0.8
B39: Down Payment | C39: =(1-C38)*C37 -> 96000 | G39: Down Payment | H39: =(1-H38)*H37 -> 96000
B40: Rehab & CapEx | C40: 120000 | G40: Rehab & CapEx | H40: 10000
B41: Total Initial Investment | C41: =SUM(C39:C40) -> 216000 | G41: Total Initial Investment | H41: =SUM(H39:H40) -> 106000
B43: Rehab Time Frame | C43: 6 Months | G43: Rehab Time Frame | H43: N/A
B44: Current Rent | C44: 2200 | G44: Current Rent | H44: =C44 -> 2200
B45: Post-Rehab Rent | C45: 3600 | G45: Post-Rehab Rent | H45: =H44 -> 2200
B46: Rent Growth | C46: 0.03 | G46: Rent Growth | H46: 0.01
B47: Property Appreciation | C47: 0.03 | G47: Property Appreciation | H47: 0.01
B48: Annual Expenses | C48: 7500 | G48: Annual Expenses | H48: 10000
B49: Sale Price | C49: =C37*(1+C47)^B62 -> 645079.86 | G49: Sale Price | H49: =H37*(1+H47)^G62 -> 530218.62
B51: Year | C51: Cash Flows | G51: Year | H51: Cash Flows
A52: 44562 | B52: 0 | C52: =-C41+(C45*6)-C48 -> -201900 | F52: 44562 | G52: 0 | H52: =-H41+(H45*6)-H48 -> -102800
A53: 44927 | B53: 1 | C53: =((C$45*12)*((1+$C$46)^B53))-C$48 -> 36996 | F53: 44927 | G53: 1 | H53: =((H$45*12)*((1+$C$46)^G53))-H$48 -> 17192
A54: 45292 | B54: 2 | C54: =((C$45*12)*((1+$C$46)^B54))-C$48 -> 38330.88 | F54: 45292 | G54: 2 | H54: =((H$45*12)*((1+$C$46)^G54))-H$48 -> 18007.76
A55: 45658 | B55: 3 | C55: =((C$45*12)*((1+$C$46)^B55))-C$48 -> 39705.806 | F55: 45658 | G55: 3 | H55: =((H$45*12)*((1+$C$46)^G55))-H$48 -> 18847.993
A56: 46023 | B56: 4 | C56: =((C$45*12)*((1+$C$46)^B56))-C$48 -> 41121.981 | F56: 46023 | G56: 4 | H56: =((H$45*12)*((1+$C$46)^G56))-H$48 -> 19713.433
A57: 46388 | B57: 5 | C57: =((C$45*12)*((1+$C$46)^B57))-C$48 -> 42580.64 | F57: 46388 | G57: 5 | H57: =((H$45*12)*((1+$C$46)^G57))-H$48 -> 20604.836
A58: 46753 | B58: 6 | C58: =((C$45*12)*((1+$C$46)^B58))-C$48 -> 44083.059 | F58: 46753 | G58: 6 | H58: =((H$45*12)*((1+$C$46)^G58))-H$48 -> 21522.981
A59: 47119 | B59: 7 | C59: =((C$45*12)*((1+$C$46)^B59))-C$48 -> 45630.551 | F59: 47119 | G59: 7 | H59: =((H$45*12)*((1+$C$46)^G59))-H$48 -> 22468.67
A60: 47484 | B60: 8 | C60: =((C$45*12)*((1+$C$46)^B60))-C$48 -> 47224.468 | F60: 47484 | G60: 8 | H60: =((H$45*12)*((1+$C$46)^G60))-H$48 -> 23442.73
A61: 47849 | B61: 9 | C61: =((C$45*12)*((1+$C$46)^B61))-C$48 -> 48866.202 | F61: 47849 | G61: 9 | H61: =((H$45*12)*((1+$C$46)^G61))-H$48 -> 24446.012
A62: 48214 | B62: 10 | C62: =C49 -> 645079.86 | F62: 48214 | G62: 10 | H62: =H49 -> 530218.62
B63: IRR | C63: =XIRR(C52:C62, A52:A62) -> 0.25847262 | G63: IRR | H63: =XIRR(H52:H62, F52:F62) -> 0.28689176
B67: Year | C67: Cash Flows
A68: 44562 | B68: 0 | C68: -212800
A69: 44927 | B69: 1 | C69: 28192
A70: 45292 | B70: 2 | C70: 29008
A71: 45658 | B71: 3 | C71: 29848
A72: 46023 | B72: 4 | C72: 30713
A73: 46388 | B73: 5 | C73: 31605
A74: 46753 | B74: 6 | C74: 32523
A75: 47119 | B75: 7 | C75: 33469
A76: 47484 | B76: 8 | C76: 34443
A77: 47849 | B77: 9 | C77: 35446
A78: 48214 | B78: 10 | C78: 1080219
B79: IRR | C79: =XIRR(C68:C78, A68:A78) -> 0.25694445

Sheet Chapter 24
B5: Discount Rate | C5: 0.075
B7: Year | C7: Cashflow | D7: Property Sale | E7: Present Value | G7: Math Check
B8: 1 | C8: 115000 | E8: 106977 | G8: =PV($C$5, B8, 0, C8) -> -106976.74
B9: 2 | C9: 122000 | E9: 105571 | G9: =PV($C$5, B9, 0, C9) -> -105570.58
B10: 3 | C10: 173000 | E10: 139258 | G10: =PV($C$5, B10, 0, C10) -> -139258.18
B11: 4 | C11: 154000 | E11: 115315 | G11: =PV($C$5, B11, 0, C11) -> -115315.28
B12: 5 | C12: 160000 | D12: 2380000 | E12: 1769259 | G12: =PV($C$5, B12, 0, C12+D12) -> -1769258.9
B13: Totals: | E13: 2236380 | G13: =SUM(G8:G12) -> -2236379.7

Sheet Chapter 25
B2: 200 Post Rd.
B3: Expense | C3: Amount | F3: Capital Source | G3: Financing Type | H3: Capital Type | I3: Capital Contribution
B4: Purchase Price | C4: 250000 | F4: Equity | G4: None (Sponsor) | H4: Common Equity | I4: 285000
B5: Closing Costs | C5: 5000 | F5: Total | I5: =I4 -> 285000
B6: Rehab Costs | C6: 20000
B7: Operating Reserve | C7: 10000 | F7: Capital Source | G7: Financing Type | H7: Capital Type | I7: Capital Contribution
B8: Total | C8: =SUM(C4:C7) -> 285000 | F8: Equity | G8: None (Sponsor) | H8: Common Equity | I8: 85000
F9: Debt | G9: Debt | H9: Debt | I9: 200000
F10: Total | I10: =SUM(I8:I9) -> 285000
F12: Capital Source | G12: Financing Type | H12: Capital Type | I12: Capital Contribution
F13: Common Equity | G13: None (Sponsor) | H13: Common Equity | I13: 250000
B14: Deal Proceeds | C14: 300000 | F14: Preferred Equity | G14: Equity Financing | H14: Preferred Equity | I14: 500000
B15: Loan Balance | C15: 190000 | F15: Mezzanine Debt | G15: Debt | H15: Debt | I15: 500000
B16: Owner Equity | C16: =C14-C15 -> 110000 | F16: Senior Debt | I16: 1000000
F17: Total | I17: =SUM(I13:I16) -> 2250000
B18: Initial Investment | C18: 85000
B19: ROI | C19: =C16/C18-1 -> 0.29411765
B20: Annualized ROI | C20: =C19/2 -> 0.14705882
B24: Deal Proceeds | C24: 260000
B25: Loan Balance | C25: 190000
B26: Owner Equity | C26: =C24-C25 -> 70000
B28: Initial Investment | C28: 85000
B29: ROI | C29: =C26/C28-1 -> -0.17647059
B30: Annualized ROI | C30: =C29/2 -> -0.088235294

Sheet Chapter 26
C3: Capital Source | D3: Financing Type | E3: Capital Type | F3: Capital Contribution
C4: Equity | D4: None (Sponsor) | E4: Common Equity | F4: 285000
C5: Total | F5: =F4 -> 285000
C8: Capital Source | D8: Financing Type | E8: Capital Type | F8: Capital Contribution
C9: Equity(Brian) | D9: None (Sponsor) | E9: Equity | F9: =285000/2 -> 142500
C10: Equity (Melissa) | D10: Equity Financing | E10: Equity | F10: =285000/2 -> 142500
C11: Total | F11: =SUM(F9:F10) -> 285000
C77: Expense | D77: Amount | E77: Senior Debt | F77: Mezzanine Debt | G77: Common Equity
C78: Purchase Price | D78: 250000 | E78: =D78*0.75 -> 187500 | F78: 0 | G78: =D78-E78 -> 62500
C79: Closing Costs | D79: 5000 | E79: 0 | F79: 0 | G79: =D79 -> 5000
C80: Rehab Costs | D80: 20000 | E80: 0 | F80: 20000 | G80: 0
C81: Operating Reserve | D81: 10000 | E81: 0 | F81: 10000 | G81: 0
C82: Total | D82: =SUM(D78:D81) -> 285000 | E82: =SUM(E78:E81) -> 187500 | F82: =SUM(F78:F81) -> 30000 | G82: =SUM(G78:G81) -> 67500

Sheet Chapter 28
D7: Capital Source | E7: Financing Type | F7: Capital Type | G7: Capital Contribution
D8: Equity | E8: None (Sponsor) | F8: Common Equity | G8: 85000
D9: Debt | E9: Debt | F9: Debt | G9: 200000
D10: Total | G10: =SUM(G8:G9) -> 285000
D14: Capital Source | E14: Financing Type | F14: Capital Type | G14: Capital Contribution
D15: Debt (Mortgage Company) | E15: None (Sponsor) | F15: Common Equity | G15: 285000
D16: Total | G16: =G15 -> 285000
D19: Capital Source | E19: Financing Type | F19: Capital Type | G19: Capital Contribution
D20: Common Equity | E20: None (Sponsor) | F20: Common Equity | G20: =285000-G21 -> 97500
D21: Senior Debt | E21: Debt | F21: Debt | G21: =0.75*250000 -> 187500
D22: Total | G22: =SUM(G20:G21) -> 285000
D26: Expense | E26: Amount | F26: Debt | G26: Equity
D27: Purchase Price | E27: 250000 | F27: =E27*0.75 -> 187500 | G27: =E27-F27 -> 62500
D28: Closing Costs | E28: 5000 | F28: 0 | G28: =E28 -> 5000
D29: Rehab Costs | E29: 20000 | F29: 0 | G29: =E29 -> 20000
D30: Operating Reserve | E30: 10000 | F30: 0 | G30: =E30 -> 10000
D31: Total | E31: =SUM(E27:E30) -> 285000 | F31: =SUM(F27:F30) -> 187500 | G31: =SUM(G27:G30) -> 97500
D35: Capital Source | E35: Financing Type | F35: Capital Type | G35: Capital Contribution
D36: Equity | E36: None (Sponsor) | F36: Common Equity | G36: 67500
D37: Debt 2 | G37: 30000
D38: Debt 1 | E38: Debt | F38: Debt | G38: =0.75*250000 -> 187500
D39: Total | G39: =SUM(G36:G38) -> 285000
D42: Expense | E42: Amount | F42: Senior Debt | G42: Mezzanine Debt | H42: Common Equity
D43: Purchase Price | E43: 250000 | F43: =E43*0.75 -> 187500 | G43: 0 | H43: =E43-F43 -> 62500
D44: Closing Costs | E44: 5000 | F44: 0 | G44: 0 | H44: =E44 -> 5000
D45: Rehab Costs | E45: 20000 | F45: 0 | G45: 20000 | H45: 0
D46: Operating Reserve | E46: 10000 | F46: 0 | G46: 10000 | H46: 0
D47: Total | E47: =SUM(E43:E46) -> 285000 | F47: =SUM(F43:F46) -> 187500 | G47: =SUM(G43:G46) -> 30000 | H47: =SUM(H43:H46) -> 67500

Sheet Finance Other
A2: 200 Post Rd.
A3: Expense | B3: Amount | E3: Capital Source | F3: Financing Type | G3: Capital Type | H3: Capital Contribution
A4: Purchase Price | B4: 250000 | E4: Common Equity | F4: None (Sponsor) | G4: Common Equity | H4: 285000
A5: Closing Costs | B5: 5000 | E5: Total | H5: =H4 -> 285000
A6: Rehab Costs | B6: 20000
A7: Operating Reserve | B7: 10000 | E7: Capital Source | F7: Financing Type | G7: Capital Type | H7: Capital Contribution
A8: Total | B8: =SUM(B4:B7) -> 285000 | E8: Equity | F8: None (Sponsor) | G8: Common Equity | H8: 85000
E9: Debt | F9: Debt | G9: Debt | H9: 200000
E10: Total | H10: =SUM(H8:H9) -> 285000
E12: Capital Source | F12: Financing Type | G12: Capital Type | H12: Capital Contribution
E13: Common Equity | F13: None (Sponsor) | G13: Common Equity | H13: 250000
E14: Preferred Equity | F14: Equity Financing | G14: Preferred Equity | H14: 500000
E15: Mezzanine Debt | F15: Debt | G15: Debt | H15: 500000
E16: Senior Debt | H16: 1000000
E17: Total | H17: =SUM(H13:H16) -> 2250000
E19: Capital Source | F19: Financing Type | G19: Capital Type | H19: Capital Contribution
E20: Common Equity (Brian) | F20: None (Sponsor) | G20: Equity | H20: =285000/2 -> 142500
A21: Deal Proceeds | B21: 300000 | E21: Preferred Equity (Melissa) | F21: Equity Financing | G21: Equity | H21: =285000/2 -> 142500
A22: Loan Balance | B22: 190000 | E22: Total | H22: =SUM(H20:H21) -> 285000
A23: Owner Equity | B23: =B21-B22 -> 110000
A25: Initial Investment | B25: 85000
A26: ROI | B26: =B23/B25-1 -> 0.29411765 | E26: Capital Source | F26: Financing Type | G26: Capital Type | H26: Capital Contribution
A27: AAROI | B27: =B26/2 -> 0.14705882 | E27: Senior Debt (Mortgage Company) | F27: None (Sponsor) | G27: Common Equity | H27: 285000
E28: Total | H28: =H27 -> 285000
E31: Capital Source | F31: Financing Type | G31: Capital Type | H31: Capital Contribution
E32: Common Equity | F32: None (Sponsor) | G32: Common Equity | H32: =285000-H33 -> 97500
E33: Senior Debt | F33: Debt | G33: Debt | H33: =0.75*250000 -> 187500
E34: Total | H34: =SUM(H32:H33) -> 285000
A36: Deal Proceeds | B36: 260000
A37: Loan Balance | B37: 190000
A38: Owner Equity | B38: =B36-B37 -> 70000 | E38: Expense | F38: Amount | G38: Debt | H38: Equity
E39: Purchase Price | F39: 250000 | G39: =F39*0.75 -> 187500 | H39: =F39-G39 -> 62500
A40: Initial Investment | B40: 85000 | E40: Closing Costs | F40: 5000 | G40: 0 | H40: =F40 -> 5000
A41: ROI | B41: =B38/B40-1 -> -0.17647059 | E41: Rehab Costs | F41: 20000 | G41: 0 | H41: =F41 -> 20000
A42: AAROI | B42: =B41/2 -> -0.088235294 | E42: Operating Reserve | F42: 10000 | G42: 0 | H42: =F42 -> 10000
E43: Total | F43: =SUM(F39:F42) -> 285000 | G43: =SUM(G39:G42) -> 187500 | H43: =SUM(H39:H42) -> 97500
E47: Capital Source | F47: Financing Type | G47: Capital Type | H47: Capital Contribution
E48: Common Equity | F48: None (Sponsor) | G48: Common Equity | H48: 67500
E49: Mezzanine Debt | H49: 30000
E50: Senior Debt | F50: Debt | G50: Debt | H50: =0.75*250000 -> 187500
E51: Total | H51: =SUM(H48:H50) -> 285000
E77: Expense | F77: Amount | G77: Senior Debt | H77: Mezzanine Debt | I77: Common Equity
E78: Purchase Price | F78: 250000 | G78: =F78*0.75 -> 187500 | H78: 0 | I78: =F78-G78 -> 62500
E79: Closing Costs | F79: 5000 | G79: 0 | H79: 0 | I79: =F79 -> 5000
E80: Rehab Costs | F80: 20000 | G80: 0 | H80: 20000 | I80: 0
E81: Operating Reserve | F81: 10000 | G81: 0 | H81: 10000 | I81: 0
E82: Total | F82: =SUM(F78:F81) -> 285000 | G82: =SUM(G78:G81) -> 187500 | H82: =SUM(H78:H81) -> 30000 | I82: =SUM(I78:I81) -> 67500

Sheet Financing Intro
B3: Expenses | E3: Capital Source | F3: Financing Type | G3: Capital Type | H3: Capital Contribution
A4: Purchase Price | B4: 250000 | E4: Primary Owner (Sponsor) | F4: None (self-financed) | G4: Equity Capital | H4: 285000
A5: Closing Costs | B5: 5000 | E5: Total | H5: =H4 -> 285000
A6: Rehab Costs | B6: 20000
A7: Operating Reserve | B7: 10000 | E7: Capital Source | F7: Financing Type | G7: Capital Type | H7: Capital Contribution
A8: Total | B8: =SUM(B4:B7) -> 285000 | E8: Primary Owner | F8: None (self-financed) | G8: Equity Capital | H8: 85000
E9: Mortgage Company | F9: Debt | G9: Debt | H9: 200000
E10: Total | H10: =SUM(H8:H9) -> 285000
E12: Capital Source | F12: Financing Type | G12: Capital Type | H12: Capital Contribution
E13: Primary Owner (Sponsor) | F13: None (self-financed) | G13: Equity Capital | H13: 50000
E14: Investor Partner | F14: Equity Financing | G14: Equity Capital | H14: 35000
E15: Mortgage Company | F15: Debt | G15: Debt | H15: 200000
E16: Total | H16: =SUM(H13:H15) -> 285000

Sheet Chapter 30 - Balloon
A1: Purchase Price | B1: 400000 | E1: Payment Number | F1: Payment ($) | G1: Interest Paid | H1: Prinicpal Paid | I1: Total Interest Paid | J1: Total Principal Paid | K1: Principal Balance | L1: Sale Price | M1: Profit
A2: Down Payment (%) | B2: 0.2 | E2: 0 | F2: =B8 -> 1717.8292 | G2: =(B$4/B$6)*K2 -> 1333.3333 | H2: =F2-G2 -> 384.49586 | I2: =G2 -> 1333.3333 | J2: =H2 -> 384.49586 | K2: =B3 -> 320000 | L2: 400000 | M2: =L2-K2 -> 80000
A3: Loan Amount (Principal) | B3: =(1-B2)*B1 -> 320000 | E3: 1 | F3: =F2 -> 1717.8292 | G3: =(B$4/B$6)*K3 -> 1331.7313 | H3: =F3-G3 -> 386.09793 | I3: =I2+G3 -> 2665.0646 | J3: =J2+H3 -> 770.59379 | K3: =K2-H2 -> 319615.5 | L3: 400000 | M3: =L3-K3 -> 80384.496
A4: Annual Interest Rate | B4: 0.05 | E4: 2 | F4: =F3 -> 1717.8292 | G4: =(B$4/B$6)*K4 -> 1330.1225 | H4: =F4-G4 -> 387.70667 | I4: =I3+G4 -> 3995.1871 | J4: =J3+H4 -> 1158.3005 | K4: =K3-H3 -> 319229.41 | L4: 400000 | M4: =L4-K4 -> 80770.594
A5: Term (Years) | B5: 30 | E5: 3 | F5: =F4 -> 1717.8292 | G5: =(B$4/B$6)*K5 -> 1328.5071 | H5: =F5-G5 -> 389.32211 | I5: =I4+G5 -> 5323.6942 | J5: =J4+H5 -> 1547.6226 | K5: =K4-H4 -> 318841.7 | L5: 400000 | M5: =L5-K5 -> 81158.3
A6: Payments/year | B6: 12 | E6: 4 | F6: =F5 -> 1717.8292 | G6: =(B$4/B$6)*K6 -> 1326.8849 | H6: =F6-G6 -> 390.94429 | I6: =I5+G6 -> 6650.5791 | J6: =J5+H6 -> 1938.5669 | K6: =K5-H5 -> 318452.38 | L6: 400000 | M6: =L6-K6 -> 81547.623 | R6: =320000*(0.05/12) -> 1333.3333
A7: Total Payments | B7: =B6*B5 -> 360 | E7: 5 | F7: =F6 -> 1717.8292 | G7: =(B$4/B$6)*K7 -> 1325.256 | H7: =F7-G7 -> 392.57322 | I7: =I6+G7 -> 7975.8351 | J7: =J6+H7 -> 2331.1401 | K7: =K6-H6 -> 318061.43 | L7: 400000 | M7: =L7-K7 -> 81938.567
A8: Payment per Period | B8: =-PMT(B4/B6, B7, B3, 0) -> 1717.8292 | E8: 6 | F8: =F7 -> 1717.8292 | G8: =(B$4/B$6)*K8 -> 1323.6202 | H8: =F8-G8 -> 394.20894 | I8: =I7+G8 -> 9299.4553 | J8: =J7+H8 -> 2725.349 | K8: =K7-H7 -> 317668.86 | L8: 400000 | M8: =L8-K8 -> 82331.14
A9: Sum of Payments | B9: =B8*B7 -> 618418.51 | E9: 7 | F9: =F8 -> 1717.8292 | G9: =(B$4/B$6)*K9 -> 1321.9777 | H9: =F9-G9 -> 395.85148 | I9: =I8+G9 -> 10621.433 | J9: =J8+H9 -> 3121.2005 | K9: =K8-H8 -> 317274.65 | L9: 400000 | M9: =L9-K9 -> 82725.349
A10: Interest Cost | B10: =B9-B3 -> 298418.51 | E10: 8 | F10: =F9 -> 1717.8292 | G10: =(B$4/B$6)*K10 -> 1320.3283 | H10: =F10-G10 -> 397.50086 | I10: =I9+G10 -> 11941.761 | J10: =J9+H10 -> 3518.7014 | K10: =K9-H9 -> 316878.8 | L10: 400000 | M10: =L10-K10 -> 83121.201
E11: 9 | F11: =F10 -> 1717.8292 | G11: =(B$4/B$6)*K11 -> 1318.6721 | H11: =F11-G11 -> 399.15712 | I11: =I10+G11 -> 13260.433 | J11: =J10+H11 -> 3917.8585 | K11: =K10-H10 -> 316481.3 | L11: 400000 | M11: =L11-K11 -> 83518.701
E12: 10 | F12: =F11 -> 1717.8292 | G12: =(B$4/B$6)*K12 -> 1317.0089 | H12: =F12-G12 -> 400.82027 | I12: =I11+G12 -> 14577.442 | J12: =J11+H12 -> 4318.6788 | K12: =K11-H11 -> 316082.14 | L12: 400000 | M12: =L12-K12 -> 83917.858
E13: 11 | F13: =F12 -> 1717.8292 | G13: =(B$4/B$6)*K13 -> 1315.3388 | H13: =F13-G13 -> 402.49036 | I13: =I12+G13 -> 15892.781 | J13: =J12+H13 -> 4721.1691 | K13: =K12-H12 -> 315681.32 | L13: 400000 | M13: =L13-K13 -> 84318.679 | O13: Year | P13: Payment ($) | Q13: Interest Paid | R13: Principal Paid | S13: Total Interest Paid | T13: Total Principal Paid | U13: Principal Balance
E14: 12 | F14: =F13 -> 1717.8292 | G14: =(B$4/B$6)*K14 -> 1313.6618 | H14: =F14-G14 -> 404.1674 | I14: =I13+G14 -> 17206.443 | J14: =J13+H14 -> 5125.3365 | K14: =K13-H13 -> 315278.83 | L14: 400000 | M14: =L14-K14 -> 84721.169 | O14: 1 | P14: =F13 -> 1717.8292 | Q14: =G13 -> 1315.3388 | R14: =H13 -> 402.49036 | S14: =I13 -> 15892.781 | T14: =J13 -> 4721.1691 | U14: =K13 -> 315681.32
E15: 13 | F15: =F14 -> 1717.8292 | G15: =(B$4/B$6)*K15 -> 1311.9778 | H15: =F15-G15 -> 405.85143 | I15: =I14+G15 -> 18518.421 | J15: =J14+H15 -> 5531.1879 | K15: =K14-H14 -> 314874.66 | L15: 400000 | M15: =L15-K15 -> 85125.337 | O15: 2 | P15: =F25 -> 1717.8292 | Q15: =G25 -> 1294.7467 | R15: =H25 -> 423.08253 | S15: =I25 -> 31544.018 | T15: =J25 -> 9683.8822 | U15: =K25 -> 310739.2
E16: 14 | F16: =F15 -> 1717.8292 | G16: =(B$4/B$6)*K16 -> 1310.2867 | H16: =F16-G16 -> 407.54248 | I16: =I15+G16 -> 19828.707 | J16: =J15+H16 -> 5938.7304 | K16: =K15-H15 -> 314468.81 | L16: 400000 | M16: =L16-K16 -> 85531.188 | O16: 3 | P16: =F37 -> 1717.8292 | Q16: =G37 -> 1273.101 | R16: =H37 -> 444.72823 | S16: =I37 -> 46941.354 | T16: =J37 -> 14900.497 | U16: =K37 -> 305544.23
E17: 15 | F17: =F16 -> 1717.8292 | G17: =(B$4/B$6)*K17 -> 1308.5886 | H17: =F17-G17 -> 409.24057 | I17: =I16+G17 -> 21137.296 | J17: =J16+H17 -> 6347.971 | K17: =K16-H16 -> 314061.27 | L17: 400000 | M17: =L17-K17 -> 85938.73 | O17: 4 | P17: =F49 -> 1717.8292 | Q17: =G49 -> 1250.3478 | R17: =H49 -> 467.48137 | S17: =I49 -> 62071.797 | T17: =J49 -> 20384.004 | U17: =K49 -> 300083.48
A18: =B4/12 -> 0.0041666667 | E18: 16 | F18: =F17 -> 1717.8292 | G18: =(B$4/B$6)*K18 -> 1306.8835 | H18: =F18-G18 -> 410.94574 | I18: =I17+G18 -> 22444.18 | J18: =J17+H18 -> 6758.9167 | K18: =K17-H17 -> 313652.03 | L18: 400000 | M18: =L18-K18 -> 86347.971 | O18: 5 | P18: =F61 -> 1717.8292 | Q18: =G61 -> 1226.4306 | R18: =H61 -> 491.3986 | S18: =I61 -> 76921.694 | T18: =J61 -> 26148.057 | U18: =K61 -> 294343.34
B19: =319615.33*A18 -> 1331.7305 | E19: 17 | F19: =F18 -> 1717.8292 | G19: =(B$4/B$6)*K19 -> 1305.1712 | H19: =F19-G19 -> 412.65801 | I19: =I18+G19 -> 23749.351 | J19: =J18+H19 -> 7171.5747 | K19: =K18-H18 -> 313241.08 | L19: 400000 | M19: =L19-K19 -> 86758.917 | O19: 6 | P19: =F73 -> 1717.8292 | Q19: =G73 -> 1201.2897 | R19: =H73 -> 516.53949 | S19: =I73 -> 91476.691 | T19: =J73 -> 32207.011 | U19: =K73 -> 288309.53
B20: =A18*B3 -> 1333.3333 | E20: 18 | F20: =F19 -> 1717.8292 | G20: =(B$4/B$6)*K20 -> 1303.4518 | H20: =F20-G20 -> 414.37742 | I20: =I19+G20 -> 25052.803 | J20: =J19+H20 -> 7585.9522 | K20: =K19-H19 -> 312828.43 | L20: 400000 | M20: =L20-K20 -> 87171.575 | O20: 7 | P20: =F85 -> 1717.8292 | Q20: =G85 -> 1174.8626 | R20: =H85 -> 542.96663 | S20: =I85 -> 105721.7 | T20: =J85 -> 38575.952 | U20: =K85 -> 281967.02
E21: 19 | F21: =F20 -> 1717.8292 | G21: =(B$4/B$6)*K21 -> 1301.7252 | H21: =F21-G21 -> 416.10399 | I21: =I20+G21 -> 26354.528 | J21: =J20+H21 -> 8002.0561 | K21: =K20-H20 -> 312414.05 | L21: 400000 | M21: =L21-K21 -> 87585.952 | O21: 8 | P21: =F97 -> 1717.8292 | Q21: =G97 -> 1147.0834 | R21: =H97 -> 570.74583 | S21: =I97 -> 119640.86 | T21: =J97 -> 45270.74 | U21: =K97 -> 275300.01
E22: 20 | F22: =F21 -> 1717.8292 | G22: =(B$4/B$6)*K22 -> 1299.9914 | H22: =F22-G22 -> 417.83776 | I22: =I21+G22 -> 27654.519 | J22: =J21+H22 -> 8419.8939 | K22: =K21-H21 -> 311997.94 | L22: 400000 | M22: =L22-K22 -> 88002.056 | O22: 9 | P22: =F109 -> 1717.8292 | Q22: =G109 -> 1117.8829 | R22: =H109 -> 599.94627 | S22: =I109 -> 133217.51 | T22: =J109 -> 52308.046 | U22: =K109 -> 268291.9
E23: 21 | F23: =F22 -> 1717.8292 | G23: =(B$4/B$6)*K23 -> 1298.2504 | H23: =F23-G23 -> 419.57875 | I23: =I22+G23 -> 28952.77 | J23: =J22+H23 -> 8839.4727 | K23: =K22-H22 -> 311580.11 | L23: 400000 | M23: =L23-K23 -> 88419.894 | O23: 10 | P23: =U22 -> 268291.9 | Q23: 0 | R23: =P23 -> 268291.9 | S23: =S22 -> 133217.51 | T23: =800000 -> 800000 | U23: 0
E24: 22 | F24: =F23 -> 1717.8292 | G24: =(B$4/B$6)*K24 -> 1296.5022 | H24: =F24-G24 -> 421.327 | I24: =I23+G24 -> 30249.272 | J24: =J23+H24 -> 9260.7997 | K24: =K23-H23 -> 311160.53 | L24: 400000 | M24: =L24-K24 -> 88839.473 | O24: 11 | P24: =F133 -> 1717.8292 | Q24: =G133 -> 1054.9238 | R24: =H133 -> 662.90544 | S24: =I133 -> 159272.25 | T24: =J133 -> 67481.204 | U24: =K133 -> 253181.7
E25: 23 | F25: =F24 -> 1717.8292 | G25: =(B$4/B$6)*K25 -> 1294.7467 | H25: =F25-G25 -> 423.08253 | I25: =I24+G25 -> 31544.018 | J25: =J24+H25 -> 9683.8822 | K25: =K24-H24 -> 310739.2 | L25: 400000 | M25: =L25-K25 -> 89260.8 | O25: 12 | P25: =F145 -> 1717.8292 | Q25: =G145 -> 1021.0083 | R25: =H145 -> 696.82094 | S25: =I145 -> 171712.56 | T25: =J145 -> 75654.84 | U25: =K145 -> 245041.98
E26: 24 | F26: =F25 -> 1717.8292 | G26: =(B$4/B$6)*K26 -> 1292.9838 | H26: =F26-G26 -> 424.84537 | I26: =I25+G26 -> 32837.002 | J26: =J25+H26 -> 10108.728 | K26: =K25-H25 -> 310316.12 | L26: 400000 | M26: =L26-K26 -> 89683.882 | O26: 13 | P26: =F157 -> 1717.8292 | Q26: =G157 -> 985.35757 | R26: =H157 -> 732.47162 | S26: =I157 -> 183734.7 | T26: =J157 -> 84246.654 | U26: =K157 -> 236485.82
E27: 25 | F27: =F26 -> 1717.8292 | G27: =(B$4/B$6)*K27 -> 1291.2136 | H27: =F27-G27 -> 426.61556 | I27: =I26+G27 -> 34128.216 | J27: =J26+H27 -> 10535.343 | K27: =K26-H26 -> 309891.27 | L27: 400000 | M27: =L27-K27 -> 90108.728 | O27: 14 | P27: =F169 -> 1717.8292 | Q27: =G169 -> 947.88294 | R27: =H169 -> 769.94626 | S27: =I169 -> 195317.26 | T27: =J169 -> 93278.042 | U27: =K169 -> 227491.9
E28: 26 | F28: =F27 -> 1717.8292 | G28: =(B$4/B$6)*K28 -> 1289.4361 | H28: =F28-G28 -> 428.39312 | I28: =I27+G28 -> 35417.652 | J28: =J27+H28 -> 10963.736 | K28: =K27-H27 -> 309464.66 | L28: 400000 | M28: =L28-K28 -> 90535.343 | O28: 15 | P28: =F181 -> 1717.8292 | Q28: =G181 -> 908.49102 | R28: =H181 -> 809.33817 | S28: =I181 -> 206437.76 | T28: =J181 -> 102771.49 | U28: =K181 -> 218037.85
E29: 27 | F29: =F28 -> 1717.8292 | G29: =(B$4/B$6)*K29 -> 1287.6511 | H29: =F29-G29 -> 430.17809 | I29: =I28+G29 -> 36705.303 | J29: =J28+H29 -> 11393.914 | K29: =K28-H28 -> 309036.26 | L29: 400000 | M29: =L29-K29 -> 90963.736 | O29: 16 | P29: =F193 -> 1717.8292 | Q29: =G193 -> 867.08375 | R29: =H193 -> 850.74545 | S29: =I193 -> 217072.56 | T29: =J193 -> 112750.65 | U29: =K193 -> 208100.1
E30: 28 | F30: =F29 -> 1717.8292 | G30: =(B$4/B$6)*K30 -> 1285.8587 | H30: =F30-G30 -> 431.9705 | I30: =I29+G30 -> 37991.162 | J30: =J29+H30 -> 11825.885 | K30: =K29-H29 -> 308606.09 | L30: 400000 | M30: =L30-K30 -> 91393.914 | O30: 17 | P30: =F205 -> 1717.8292 | Q30: =G205 -> 823.558 | R30: =H205 -> 894.2712 | S30: =I205 -> 227196.8 | T30: =J205 -> 123240.35 | U30: =K205 -> 197653.92
E31: 29 | F31: =F30 -> 1717.8292 | G31: =(B$4/B$6)*K31 -> 1284.0588 | H31: =F31-G31 -> 433.77038 | I31: =I30+G31 -> 39275.221 | J31: =J30+H31 -> 12259.655 | K31: =K30-H30 -> 308174.12 | L31: 400000 | M31: =L31-K31 -> 91825.885 | O31: 18 | P31: =F217 -> 1717.8292 | Q31: =G217 -> 777.80538 | R31: =H217 -> 940.02381 | S31: =I217 -> 236784.37 | T31: =J217 -> 134266.73 | U31: =K217 -> 186673.29
E32: 30 | F32: =F31 -> 1717.8292 | G32: =(B$4/B$6)*K32 -> 1282.2514 | H32: =F32-G32 -> 435.57776 | I32: =I31+G32 -> 40557.472 | J32: =J31+H32 -> 12695.233 | K32: =K31-H31 -> 307740.34 | L32: 400000 | M32: =L32-K32 -> 92259.655 | O32: 19 | P32: =F229 -> 1717.8292 | Q32: =G229 -> 729.71198 | R32: =H229 -> 988.11721 | S32: =I229 -> 245807.81 | T32: =J229 -> 145857.24 | U32: =K229 -> 175130.88
E33: 31 | F33: =F32 -> 1717.8292 | G33: =(B$4/B$6)*K33 -> 1280.4365 | H33: =F33-G33 -> 437.39266 | I33: =I32+G33 -> 41837.909 | J33: =J32+H33 -> 13132.626 | K33: =K32-H32 -> 307304.77 | L33: 400000 | M33: =L33-K33 -> 92695.233 | O33: 20 | P33: =F241 -> 1717.8292 | Q33: =G241 -> 679.15803 | R33: =H241 -> 1038.6712 | S33: =I241 -> 254238.26 | T33: =J241 -> 158040.74 | U33: =K241 -> 162997.93
E34: 32 | F34: =F33 -> 1717.8292 | G34: =(B$4/B$6)*K34 -> 1278.6141 | H34: =F34-G34 -> 439.21513 | I34: =I33+G34 -> 43116.523 | J34: =J33+H34 -> 13571.841 | K34: =K33-H33 -> 306867.37 | L34: 400000 | M34: =L34-K34 -> 93132.626 | O34: 21 | P34: =F253 -> 1717.8292 | Q34: =G253 -> 626.01764 | R34: =H253 -> 1091.8116 | S34: =I253 -> 262045.38 | T34: =J253 -> 170847.58 | U34: =K253 -> 150244.23
E35: 33 | F35: =F34 -> 1717.8292 | G35: =(B$4/B$6)*K35 -> 1276.784 | H35: =F35-G35 -> 441.0452 | I35: =I34+G35 -> 44393.307 | J35: =J34+H35 -> 14012.886 | K35: =K34-H34 -> 306428.16 | L35: 400000 | M35: =L35-K35 -> 93571.841 | O35: 22 | P35: =F265 -> 1717.8292 | Q35: =G265 -> 570.15849 | R35: =H265 -> 1147.6707 | S35: =I265 -> 269197.27 | T35: =J265 -> 184309.63 | U35: =K265 -> 136838.04
E36: 34 | F36: =F35 -> 1717.8292 | G36: =(B$4/B$6)*K36 -> 1274.9463 | H36: =F36-G36 -> 442.88289 | I36: =I35+G36 -> 45668.253 | J36: =J35+H36 -> 14455.769 | K36: =K35-H35 -> 305987.11 | L36: 400000 | M36: =L36-K36 -> 94012.886 | O36: 23 | P36: =F277 -> 1717.8292 | Q36: =G277 -> 511.44148 | R36: =H277 -> 1206.3877 | S36: =I277 -> 275660.42 | T36: =J277 -> 198460.43 | U36: =K277 -> 122745.96
E37: 35 | F37: =F36 -> 1717.8292 | G37: =(B$4/B$6)*K37 -> 1273.101 | H37: =F37-G37 -> 444.72823 | I37: =I36+G37 -> 46941.354 | J37: =J36+H37 -> 14900.497 | K37: =K36-H36 -> 305544.23 | L37: 400000 | M37: =L37-K37 -> 94455.769 | O37: 24 | P37: =F289 -> 1717.8292 | Q37: =G289 -> 449.72039 | R37: =H289 -> 1268.1088 | S37: =I289 -> 281399.59 | T37: =J289 -> 213335.21 | U37: =K289 -> 107932.89
E38: 36 | F38: =F37 -> 1717.8292 | G38: =(B$4/B$6)*K38 -> 1271.2479 | H38: =F38-G38 -> 446.58126 | I38: =I37+G38 -> 48212.602 | J38: =J37+H38 -> 15347.078 | K38: =K37-H37 -> 305099.5 | L38: 400000 | M38: =L38-K38 -> 94900.497 | O38: 25 | P38: =F301 -> 1717.8292 | Q38: =G301 -> 384.84154 | R38: =H301 -> 1332.9877 | S38: =I301 -> 286377.74 | T38: =J301 -> 228971.02 | U38: =K301 -> 92361.97
E39: 37 | F39: =F38 -> 1717.8292 | G39: =(B$4/B$6)*K39 -> 1269.3872 | H39: =F39-G39 -> 448.44202 | I39: =I38+G39 -> 49481.989 | J39: =J38+H39 -> 15795.52 | K39: =K38-H38 -> 304652.92 | L39: 400000 | M39: =L39-K39 -> 95347.078 | O39: 26 | P39: =F313 -> 1717.8292 | Q39: =G313 -> 316.64336 | R39: =H313 -> 1401.1858 | S39: =I313 -> 290555.93 | T39: =J313 -> 245406.78 | U39: =K313 -> 75994.407 | AH39: =320000*(0.591^360)/((1.417^360)-1) -> 6.0743108e-132 | AI39: =1.417^360 -> 3.1127632e+54
E40: 38 | F40: =F39 -> 1717.8292 | G40: =(B$4/B$6)*K40 -> 1267.5187 | H40: =F40-G40 -> 450.31053 | I40: =I39+G40 -> 50749.508 | J40: =J39+H40 -> 16245.831 | K40: =K39-H39 -> 304204.48 | L40: 400000 | M40: =L40-K40 -> 95795.52 | O40: 27 | P40: =F325 -> 1717.8292 | Q40: =G325 -> 244.95604 | R40: =H325 -> 1472.8732 | S40: =I325 -> 293893.23 | T40: =J325 -> 262683.42 | U40: =K325 -> 58789.449
E41: 39 | F41: =F40 -> 1717.8292 | G41: =(B$4/B$6)*K41 -> 1265.6424 | H41: =F41-G41 -> 452.18682 | I41: =I40+G41 -> 52015.15 | J41: =J40+H41 -> 16698.018 | K41: =K40-H40 -> 303754.17 | L41: 400000 | M41: =L41-K41 -> 96245.831 | O41: 28 | P41: =F337 -> 1717.8292 | Q41: =G337 -> 169.60105 | R41: =H337 -> 1548.2281 | S41: =I337 -> 296346.63 | T41: =J337 -> 280843.98 | U41: =K337 -> 40704.252
E42: 40 | F42: =F41 -> 1717.8292 | G42: =(B$4/B$6)*K42 -> 1263.7583 | H42: =F42-G42 -> 454.07093 | I42: =I41+G42 -> 53278.908 | J42: =J41+H42 -> 17152.089 | K42: =K41-H41 -> 303301.98 | L42: 400000 | M42: =L42-K42 -> 96698.018 | O42: 29 | P42: =F349 -> 1717.8292 | Q42: =G349 -> 90.390761 | R42: =H349 -> 1627.4384 | S42: =I349 -> 297870.9 | T42: =J349 -> 299933.66 | U42: =K349 -> 21693.783 | AI42: =0.591^360 -> 5.908716e-83
E43: 41 | F43: =F42 -> 1717.8292 | G43: =(B$4/B$6)*K43 -> 1261.8663 | H43: =F43-G43 -> 455.9629 | I43: =I42+G43 -> 54540.775 | J43: =J42+H43 -> 17608.052 | K43: =K42-H42 -> 302847.91 | L43: 400000 | M43: =L43-K43 -> 97152.089 | O43: 30 | P43: =F361 -> 1717.8292 | Q43: =G361 -> 7.127922 | R43: =H361 -> 1710.7013 | S43: =I361 -> 298418.51 | T43: =J361 -> 320000 | U43: =K361 -> 1710.7013
E44: 42 | F44: =F43 -> 1717.8292 | G44: =(B$4/B$6)*K44 -> 1259.9665 | H44: =F44-G44 -> 457.86274 | I44: =I43+G44 -> 55800.741 | J44: =J43+H44 -> 18065.914 | K44: =K43-H43 -> 302391.95 | L44: 400000 | M44: =L44-K44 -> 97608.052
E45: 43 | F45: =F44 -> 1717.8292 | G45: =(B$4/B$6)*K45 -> 1258.0587 | H45: =F45-G45 -> 459.7705 | I45: =I44+G45 -> 57058.8 | J45: =J44+H45 -> 18525.685 | K45: =K44-H44 -> 301934.09 | L45: 400000 | M45: =L45-K45 -> 98065.914
E46: 44 | F46: =F45 -> 1717.8292 | G46: =(B$4/B$6)*K46 -> 1256.143 | H46: =F46-G46 -> 461.68621 | I46: =I45+G46 -> 58314.943 | J46: =J45+H46 -> 18987.371 | K46: =K45-H45 -> 301474.32 | L46: 400000 | M46: =L46-K46 -> 98525.685
E47: 45 | F47: =F46 -> 1717.8292 | G47: =(B$4/B$6)*K47 -> 1254.2193 | H47: =F47-G47 -> 463.60991 | I47: =I46+G47 -> 59569.162 | J47: =J46+H47 -> 19450.981 | K47: =K46-H46 -> 301012.63 | L47: 400000 | M47: =L47-K47 -> 98987.371
E48: 46 | F48: =F47 -> 1717.8292 | G48: =(B$4/B$6)*K48 -> 1252.2876 | H48: =F48-G48 -> 465.54161 | I48: =I47+G48 -> 60821.45 | J48: =J47+H48 -> 19916.523 | K48: =K47-H47 -> 300549.02 | L48: 400000 | M48: =L48-K48 -> 99450.981
E49: 47 | F49: =F48 -> 1717.8292 | G49: =(B$4/B$6)*K49 -> 1250.3478 | H49: =F49-G49 -> 467.48137 | I49: =I48+G49 -> 62071.797 | J49: =J48+H49 -> 20384.004 | K49: =K48-H48 -> 300083.48 | L49: 400000 | M49: =L49-K49 -> 99916.523
E50: 48 | F50: =F49 -> 1717.8292 | G50: =(B$4/B$6)*K50 -> 1248.4 | H50: =F50-G50 -> 469.42921 | I50: =I49+G50 -> 63320.197 | J50: =J49+H50 -> 20853.433 | K50: =K49-H49 -> 299616 | L50: 400000 | M50: =L50-K50 -> 100384
E51: 49 | F51: =F50 -> 1717.8292 | G51: =(B$4/B$6)*K51 -> 1246.444 | H51: =F51-G51 -> 471.38516 | I51: =I50+G51 -> 64566.641 | J51: =J50+H51 -> 21324.818 | K51: =K50-H50 -> 299146.57 | L51: 400000 | M51: =L51-K51 -> 100853.43 | Q51: Full
E52: 50 | F52: =F51 -> 1717.8292 | G52: =(B$4/B$6)*K52 -> 1244.4799 | H52: =F52-G52 -> 473.34927 | I52: =I51+G52 -> 65811.121 | J52: =J51+H52 -> 21798.168 | K52: =K51-H51 -> 298675.18 | L52: 400000 | M52: =L52-K52 -> 101324.82 | Q52: Total Interest | R52: 574956
E53: 51 | F53: =F52 -> 1717.8292 | G53: =(B$4/B$6)*K53 -> 1242.5076 | H53: =F53-G53 -> 475.32156 | I53: =I52+G53 -> 67053.629 | J53: =J52+H53 -> 22273.489 | K53: =K52-H52 -> 298201.83 | L53: 400000 | M53: =L53-K53 -> 101798.17
E54: 52 | F54: =F53 -> 1717.8292 | G54: =(B$4/B$6)*K54 -> 1240.5271 | H54: =F54-G54 -> 477.30206 | I54: =I53+G54 -> 68294.156 | J54: =J53+H54 -> 22750.791 | K54: =K53-H53 -> 297726.51 | L54: 400000 | M54: =L54-K54 -> 102273.49
E55: 53 | F55: =F54 -> 1717.8292 | G55: =(B$4/B$6)*K55 -> 1238.5384 | H55: =F55-G55 -> 479.29082 | I55: =I54+G55 -> 69532.694 | J55: =J54+H55 -> 23230.082 | K55: =K54-H54 -> 297249.21 | L55: 400000 | M55: =L55-K55 -> 102750.79
E56: 54 | F56: =F55 -> 1717.8292 | G56: =(B$4/B$6)*K56 -> 1236.5413 | H56: =F56-G56 -> 481.28787 | I56: =I55+G56 -> 70769.236 | J56: =J55+H56 -> 23711.37 | K56: =K55-H55 -> 296769.92 | L56: 400000 | M56: =L56-K56 -> 103230.08
E57: 55 | F57: =F56 -> 1717.8292 | G57: =(B$4/B$6)*K57 -> 1234.536 | H57: =F57-G57 -> 483.29323 | I57: =I56+G57 -> 72003.772 | J57: =J56+H57 -> 24194.663 | K57: =K56-H56 -> 296288.63 | L57: 400000 | M57: =L57-K57 -> 103711.37
E58: 56 | F58: =F57 -> 1717.8292 | G58: =(B$4/B$6)*K58 -> 1232.5222 | H58: =F58-G58 -> 485.30696 | I58: =I57+G58 -> 73236.294 | J58: =J57+H58 -> 24679.97 | K58: =K57-H57 -> 295805.34 | L58: 400000 | M58: =L58-K58 -> 104194.66
E59: 57 | F59: =F58 -> 1717.8292 | G59: =(B$4/B$6)*K59 -> 1230.5001 | H59: =F59-G59 -> 487.32907 | I59: =I58+G59 -> 74466.794 | J59: =J58+H59 -> 25167.299 | K59: =K58-H58 -> 295320.03 | L59: 400000 | M59: =L59-K59 -> 104679.97
E60: 58 | F60: =F59 -> 1717.8292 | G60: =(B$4/B$6)*K60 -> 1228.4696 | H60: =F60-G60 -> 489.35961 | I60: =I59+G60 -> 75695.264 | J60: =J59+H60 -> 25656.659 | K60: =K59-H59 -> 294832.7 | L60: 400000 | M60: =L60-K60 -> 105167.3
E61: 59 | F61: =F60 -> 1717.8292 | G61: =(B$4/B$6)*K61 -> 1226.4306 | H61: =F61-G61 -> 491.3986 | I61: =I60+G61 -> 76921.694 | J61: =J60+H61 -> 26148.057 | K61: =K60-H60 -> 294343.34 | L61: 400000 | M61: =L61-K61 -> 105656.66
E62: 60 | F62: =F61 -> 1717.8292 | G62: =(B$4/B$6)*K62 -> 1224.3831 | H62: =F62-G62 -> 493.4461 | I62: =I61+G62 -> 78146.077 | J62: =J61+H62 -> 26641.503 | K62: =K61-H61 -> 293851.94 | L62: 400000 | M62: =L62-K62 -> 106148.06
E63: 61 | F63: =F62 -> 1717.8292 | G63: =(B$4/B$6)*K63 -> 1222.3271 | H63: =F63-G63 -> 495.50212 | I63: =I62+G63 -> 79368.404 | J63: =J62+H63 -> 27137.006 | K63: =K62-H62 -> 293358.5 | L63: 400000 | M63: =L63-K63 -> 106641.5
E64: 62 | F64: =F63 -> 1717.8292 | G64: =(B$4/B$6)*K64 -> 1220.2625 | H64: =F64-G64 -> 497.56672 | I64: =I63+G64 -> 80588.667 | J64: =J63+H64 -> 27634.572 | K64: =K63-H63 -> 292862.99 | L64: 400000 | M64: =L64-K64 -> 107137.01
... E362: 360 | F362: =F361 -> 1717.8292 | G362: =(B$4/B$6)*K362 -> -4.6838977e-12 | H362: =F362-G362 -> 1717.8292 | I362: =I361+G362 -> 298418.51 | J362: =J361+H362 -> 321717.83 | K362: =K361-H361 -> -1.1241355e-09 | L362: 400000 | M362: =L362-K362 -> 400000

Sheet Chapter 30 - Full
A1: Do Not Delete
A2: Purchase Price | B2: 400000 | E2: Payment Number | F2: Payment ($) | G2: Interest Paid | H2: Prinicipal Paid | I2: Total Interest Paid | J2: Total Principal Paid | K2: Principal Balance | L2: Sale Price | M2: Profit
A3: Down Payment (%) | B3: 0.2 | E3: 0 | F3: =B9 -> 1717.8292 | G3: =(B$5/B$7)*K3 -> 1333.3333 | H3: =F3-G3 -> 384.49586 | I3: =G3 -> 1333.3333 | J3: =H3 -> 384.49586 | K3: =B4 -> 320000 | L3: 400000 | M3: =L3-K3 -> 80000
A4: Loan Amount (Principal) | B4: =(1-B3)*B2 -> 320000 | E4: 1 | F4: =F3 -> 1717.8292 | G4: =(B$5/B$7)*K4 -> 1331.7313 | H4: =F4-G4 -> 386.09793 | I4: =I3+G4 -> 2665.0646 | J4: =J3+H4 -> 770.59379 | K4: =K3-H3 -> 319615.5 | L4: 400000 | M4: =L4-K4 -> 80384.496
A5: Annual Interest Rate | B5: =0.05 -> 0.05 | E5: 2 | F5: =F4 -> 1717.8292 | G5: =(B$5/B$7)*K5 -> 1330.1225 | H5: =F5-G5 -> 387.70667 | I5: =I4+G5 -> 3995.1871 | J5: =J4+H5 -> 1158.3005 | K5: =K4-H4 -> 319229.41 | L5: 400000 | M5: =L5-K5 -> 80770.594
A6: Term (Years) | B6: 30 | E6: 3 | F6: =F5 -> 1717.8292 | G6: =(B$5/B$7)*K6 -> 1328.5071 | H6: =F6-G6 -> 389.32211 | I6: =I5+G6 -> 5323.6942 | J6: =J5+H6 -> 1547.6226 | K6: =K5-H5 -> 318841.7 | L6: 400000 | M6: =L6-K6 -> 81158.3
A7: Payments/year | B7: 12 | E7: 4 | F7: =F6 -> 1717.8292 | G7: =(B$5/B$7)*K7 -> 1326.8849 | H7: =F7-G7 -> 390.94429 | I7: =I6+G7 -> 6650.5791 | J7: =J6+H7 -> 1938.5669 | K7: =K6-H6 -> 318452.38 | L7: 400000 | M7: =L7-K7 -> 81547.623
A8: Total Payments | B8: =B7*B6 -> 360 | E8: 5 | F8: =F7 -> 1717.8292 | G8: =(B$5/B$7)*K8 -> 1325.256 | H8: =F8-G8 -> 392.57322 | I8: =I7+G8 -> 7975.8351 | J8: =J7+H8 -> 2331.1401 | K8: =K7-H7 -> 318061.43 | L8: 400000 | M8: =L8-K8 -> 81938.567
A9: Payment per Period | B9: =-PMT(B5/B7, B8, B4, 0) -> 1717.8292 | E9: 6 | F9: =F8 -> 1717.8292 | G9: =(B$5/B$7)*K9 -> 1323.6202 | H9: =F9-G9 -> 394.20894 | I9: =I8+G9 -> 9299.4553 | J9: =J8+H9 -> 2725.349 | K9: =K8-H8 -> 317668.86 | L9: 400000 | M9: =L9-K9 -> 82331.14
A10: Sum of Payments | B10: =B9*B8 -> 618418.51 | E10: 7 | F10: =F9 -> 1717.8292 | G10: =(B$5/B$7)*K10 -> 1321.9777 | H10: =F10-G10 -> 395.85148 | I10: =I9+G10 -> 10621.433 | J10: =J9+H10 -> 3121.2005 | K10: =K9-H9 -> 317274.65 | L10: 400000 | M10: =L10-K10 -> 82725.349
A11: Interest Cost | B11: =B10-B4 -> 298418.51 | E11: 8 | F11: =F10 -> 1717.8292 | G11: =(B$5/B$7)*K11 -> 1320.3283 | H11: =F11-G11 -> 397.50086 | I11: =I10+G11 -> 11941.761 | J11: =J10+H11 -> 3518.7014 | K11: =K10-H10 -> 316878.8 | L11: 400000 | M11: =L11-K11 -> 83121.201
E12: 9 | F12: =F11 -> 1717.8292 | G12: =(B$5/B$7)*K12 -> 1318.6721 | H12: =F12-G12 -> 399.15712 | I12: =I11+G12 -> 13260.433 | J12: =J11+H12 -> 3917.8585 | K12: =K11-H11 -> 316481.3 | L12: 400000 | M12: =L12-K12 -> 83518.701
E13: 10 | F13: =F12 -> 1717.8292 | G13: =(B$5/B$7)*K13 -> 1317.0089 | H13: =F13-G13 -> 400.82027 | I13: =I12+G13 -> 14577.442 | J13: =J12+H13 -> 4318.6788 | K13: =K12-H12 -> 316082.14 | L13: 400000 | M13: =L13-K13 -> 83917.858
E14: 11 | F14: =F13 -> 1717.8292 | G14: =(B$5/B$7)*K14 -> 1315.3388 | H14: =F14-G14 -> 402.49036 | I14: =I13+G14 -> 15892.781 | J14: =J13+H14 -> 4721.1691 | K14: =K13-H13 -> 315681.32 | L14: 400000 | M14: =L14-K14 -> 84318.679 | O14: Year | Q14: Total Principal Paid | R14: Principal/Year
E15: 12 | F15: =F14 -> 1717.8292 | G15: =(B$5/B$7)*K15 -> 1313.6618 | H15: =F15-G15 -> 404.1674 | I15: =I14+G15 -> 17206.443 | J15: =J14+H15 -> 5125.3365 | K15: =K14-H14 -> 315278.83 | L15: 400000 | M15: =L15-K15 -> 84721.169 | O15: 1 | P15: =I14 -> 15892.781 | Q15: =J14 -> 4721.1691 | R15: =Q15 -> 4721.1691
E16: 13 | F16: =F15 -> 1717.8292 | G16: =(B$5/B$7)*K16 -> 1311.9778 | H16: =F16-G16 -> 405.85143 | I16: =I15+G16 -> 18518.421 | J16: =J15+H16 -> 5531.1879 | K16: =K15-H15 -> 314874.66 | L16: 400000 | M16: =L16-K16 -> 85125.337 | O16: 2 | P16: =I26 -> 31544.018 | Q16: =J26 -> 9683.8822 | R16: =Q16-Q15 -> 4962.7131
E17: 14 | F17: =F16 -> 1717.8292 | G17: =(B$5/B$7)*K17 -> 1310.2867 | H17: =F17-G17 -> 407.54248 | I17: =I16+G17 -> 19828.707 | J17: =J16+H17 -> 5938.7304 | K17: =K16-H16 -> 314468.81 | L17: 400000 | M17: =L17-K17 -> 85531.188 | O17: 3 | P17: =I38 -> 46941.354 | Q17: =J38 -> 14900.497 | R17: =Q17-Q16 -> 5216.6149
E18: 15 | F18: =F17 -> 1717.8292 | G18: =(B$5/B$7)*K18 -> 1308.5886 | H18: =F18-G18 -> 409.24057 | I18: =I17+G18 -> 21137.296 | J18: =J17+H18 -> 6347.971 | K18: =K17-H17 -> 314061.27 | L18: 400000 | M18: =L18-K18 -> 85938.73 | O18: 4 | P18: =I50 -> 62071.797 | Q18: =J50 -> 20384.004 | R18: =Q18-Q17 -> 5483.5068
E19: 16 | F19: =F18 -> 1717.8292 | G19: =(B$5/B$7)*K19 -> 1306.8835 | H19: =F19-G19 -> 410.94574 | I19: =I18+G19 -> 22444.18 | J19: =J18+H19 -> 6758.9167 | K19: =K18-H18 -> 313652.03 | L19: 400000 | M19: =L19-K19 -> 86347.971 | O19: 5 | P19: =I62 -> 76921.694 | Q19: =J62 -> 26148.057 | R19: =Q19-Q18 -> 5764.0534
E20: 17 | F20: =F19 -> 1717.8292 | G20: =(B$5/B$7)*K20 -> 1305.1712 | H20: =F20-G20 -> 412.65801 | I20: =I19+G20 -> 23749.351 | J20: =J19+H20 -> 7171.5747 | K20: =K19-H19 -> 313241.08 | L20: 400000 | M20: =L20-K20 -> 86758.917 | O20: 6 | P20: =I74 -> 91476.691 | Q20: =J74 -> 32207.011 | R20: =Q20-Q19 -> 6058.9533
E21: 18 | F21: =F20 -> 1717.8292 | G21: =(B$5/B$7)*K21 -> 1303.4518 | H21: =F21-G21 -> 414.37742 | I21: =I20+G21 -> 25052.803 | J21: =J20+H21 -> 7585.9522 | K21: =K20-H20 -> 312828.43 | L21: 400000 | M21: =L21-K21 -> 87171.575 | O21: 7 | P21: =I86 -> 105721.7 | Q21: =J86 -> 38575.952 | R21: =Q21-Q20 -> 6368.9409
E22: 19 | F22: =F21 -> 1717.8292 | G22: =(B$5/B$7)*K22 -> 1301.7252 | H22: =F22-G22 -> 416.10399 | I22: =I21+G22 -> 26354.528 | J22: =J21+H22 -> 8002.0561 | K22: =K21-H21 -> 312414.05 | L22: 400000 | M22: =L22-K22 -> 87585.952 | O22: 8 | P22: =I98 -> 119640.86 | Q22: =J98 -> 45270.74 | R22: =Q22-Q21 -> 6694.788
E23: 20 | F23: =F22 -> 1717.8292 | G23: =(B$5/B$7)*K23 -> 1299.9914 | H23: =F23-G23 -> 417.83776 | I23: =I22+G23 -> 27654.519 | J23: =J22+H23 -> 8419.8939 | K23: =K22-H22 -> 311997.94 | L23: 400000 | M23: =L23-K23 -> 88002.056 | O23: 9 | P23: =I110 -> 133217.51 | Q23: =J110 -> 52308.046 | R23: =Q23-Q22 -> 7037.3061
E24: 21 | F24: =F23 -> 1717.8292 | G24: =(B$5/B$7)*K24 -> 1298.2504 | H24: =F24-G24 -> 419.57875 | I24: =I23+G24 -> 28952.77 | J24: =J23+H24 -> 8839.4727 | K24: =K23-H23 -> 311580.11 | L24: 400000 | M24: =L24-K24 -> 88419.894 | O24: 10 | P24: =I122 -> 146434.11 | Q24: =J122 -> 59705.394 | R24: =Q24-Q23 -> 7397.348
E25: 22 | F25: =F24 -> 1717.8292 | G25: =(B$5/B$7)*K25 -> 1296.5022 | H25: =F25-G25 -> 421.327 | I25: =I24+G25 -> 30249.272 | J25: =J24+H25 -> 9260.7997 | K25: =K24-H24 -> 311160.53 | L25: 400000 | M25: =L25-K25 -> 88839.473 | O25: 11 | P25: =I134 -> 159272.25 | Q25: =J134 -> 67481.204 | R25: =Q25-Q24 -> 7775.8104
E26: 23 | F26: =F25 -> 1717.8292 | G26: =(B$5/B$7)*K26 -> 1294.7467 | H26: =F26-G26 -> 423.08253 | I26: =I25+G26 -> 31544.018 | J26: =J25+H26 -> 9683.8822 | K26: =K25-H25 -> 310739.2 | L26: 400000 | M26: =L26-K26 -> 89260.8 | O26: 12 | P26: =I146 -> 171712.56 | Q26: =J146 -> 75654.84 | R26: =Q26-Q25 -> 8173.6356
E27: 24 | F27: =F26 -> 1717.8292 | G27: =(B$5/B$7)*K27 -> 1292.9838 | H27: =F27-G27 -> 424.84537 | I27: =I26+G27 -> 32837.002 | J27: =J26+H27 -> 10108.728 | K27: =K26-H26 -> 310316.12 | L27: 400000 | M27: =L27-K27 -> 89683.882 | O27: 13 | P27: =I158 -> 183734.7 | Q27: =J158 -> 84246.654 | R27: =Q27-Q26 -> 8591.8143
E28: 25 | F28: =F27 -> 1717.8292 | G28: =(B$5/B$7)*K28 -> 1291.2136 | H28: =F28-G28 -> 426.61556 | I28: =I27+G28 -> 34128.216 | J28: =J27+H28 -> 10535.343 | K28: =K27-H27 -> 309891.27 | L28: 400000 | M28: =L28-K28 -> 90108.728 | O28: 14 | P28: =I170 -> 195317.26 | Q28: =J170 -> 93278.042 | R28: =Q28-Q27 -> 9031.3878
E29: 26 | F29: =F28 -> 1717.8292 | G29: =(B$5/B$7)*K29 -> 1289.4361 | H29: =F29-G29 -> 428.39312 | I29: =I28+G29 -> 35417.652 | J29: =J28+H29 -> 10963.736 | K29: =K28-H28 -> 309464.66 | L29: 400000 | M29: =L29-K29 -> 90535.343 | O29: 15 | P29: =I182 -> 206437.76 | Q29: =J182 -> 102771.49 | R29: =Q29-Q28 -> 9493.4507
E30: 27 | F30: =F29 -> 1717.8292 | G30: =(B$5/B$7)*K30 -> 1287.6511 | H30: =F30-G30 -> 430.17809 | I30: =I29+G30 -> 36705.303 | J30: =J29+H30 -> 11393.914 | K30: =K29-H29 -> 309036.26 | L30: 400000 | M30: =L30-K30 -> 90963.736 | O30: 16 | P30: =I194 -> 217072.56 | Q30: =J194 -> 112750.65 | R30: =Q30-Q29 -> 9979.1537
E31: 28 | F31: =F30 -> 1717.8292 | G31: =(B$5/B$7)*K31 -> 1285.8587 | H31: =F31-G31 -> 431.9705 | I31: =I30+G31 -> 37991.162 | J31: =J30+H31 -> 11825.885 | K31: =K30-H30 -> 308606.09 | L31: 400000 | M31: =L31-K31 -> 91393.914 | O31: 17 | P31: =I206 -> 227196.8 | Q31: =J206 -> 123240.35 | R31: =Q31-Q30 -> 10489.706
E32: 29 | F32: =F31 -> 1717.8292 | G32: =(B$5/B$7)*K32 -> 1284.0588 | H32: =F32-G32 -> 433.77038 | I32: =I31+G32 -> 39275.221 | J32: =J31+H32 -> 12259.655 | K32: =K31-H31 -> 308174.12 | L32: 400000 | M32: =L32-K32 -> 91825.885 | O32: 18 | P32: =I218 -> 236784.37 | Q32: =J218 -> 134266.73 | R32: =Q32-Q31 -> 11026.379
E33: 30 | F33: =F32 -> 1717.8292 | G33: =(B$5/B$7)*K33 -> 1282.2514 | H33: =F33-G33 -> 435.57776 | I33: =I32+G33 -> 40557.472 | J33: =J32+H33 -> 12695.233 | K33: =K32-H32 -> 307740.34 | L33: 400000 | M33: =L33-K33 -> 92259.655 | O33: 19 | P33: =I230 -> 245807.81 | Q33: =J230 -> 145857.24 | R33: =Q33-Q32 -> 11590.51
E34: 31 | F34: =F33 -> 1717.8292 | G34: =(B$5/B$7)*K34 -> 1280.4365 | H34: =F34-G34 -> 437.39266 | I34: =I33+G34 -> 41837.909 | J34: =J33+H34 -> 13132.626 | K34: =K33-H33 -> 307304.77 | L34: 400000 | M34: =L34-K34 -> 92695.233 | O34: 20 | P34: =I242 -> 254238.26 | Q34: =J242 -> 158040.74 | R34: =Q34-Q33 -> 12183.502
E35: 32 | F35: =F34 -> 1717.8292 | G35: =(B$5/B$7)*K35 -> 1278.6141 | H35: =F35-G35 -> 439.21513 | I35: =I34+G35 -> 43116.523 | J35: =J34+H35 -> 13571.841 | K35: =K34-H34 -> 306867.37 | L35: 400000 | M35: =L35-K35 -> 93132.626 | O35: 21 | P35: =I254 -> 262045.38 | Q35: =J254 -> 170847.58 | R35: =Q35-Q34 -> 12806.834
E36: 33 | F36: =F35 -> 1717.8292 | G36: =(B$5/B$7)*K36 -> 1276.784 | H36: =F36-G36 -> 441.0452 | I36: =I35+G36 -> 44393.307 | J36: =J35+H36 -> 14012.886 | K36: =K35-H35 -> 306428.16 | L36: 400000 | M36: =L36-K36 -> 93571.841 | O36: 22 | P36: =I266 -> 269197.27 | Q36: =J266 -> 184309.63 | R36: =Q36-Q35 -> 13462.055
E37: 34 | F37: =F36 -> 1717.8292 | G37: =(B$5/B$7)*K37 -> 1274.9463 | H37: =F37-G37 -> 442.88289 | I37: =I36+G37 -> 45668.253 | J37: =J36+H37 -> 14455.769 | K37: =K36-H36 -> 305987.11 | L37: 400000 | M37: =L37-K37 -> 94012.886 | O37: 23 | P37: =I278 -> 275660.42 | Q37: =J278 -> 198460.43 | R37: =Q37-Q36 -> 14150.8
E38: 35 | F38: =F37 -> 1717.8292 | G38: =(B$5/B$7)*K38 -> 1273.101 | H38: =F38-G38 -> 444.72823 | I38: =I37+G38 -> 46941.354 | J38: =J37+H38 -> 14900.497 | K38: =K37-H37 -> 305544.23 | L38: 400000 | M38: =L38-K38 -> 94455.769 | O38: 24 | P38: =I290 -> 281399.59 | Q38: =J290 -> 213335.21 | R38: =Q38-Q37 -> 14874.781
E39: 36 | F39: =F38 -> 1717.8292 | G39: =(B$5/B$7)*K39 -> 1271.2479 | H39: =F39-G39 -> 446.58126 | I39: =I38+G39 -> 48212.602 | J39: =J38+H39 -> 15347.078 | K39: =K38-H38 -> 305099.5 | L39: 400000 | M39: =L39-K39 -> 94900.497 | O39: 25 | P39: =I302 -> 286377.74 | Q39: =J302 -> 228971.02 | R39: =Q39-Q38 -> 15635.804
E40: 37 | F40: =F39 -> 1717.8292 | G40: =(B$5/B$7)*K40 -> 1269.3872 | H40: =F40-G40 -> 448.44202 | I40: =I39+G40 -> 49481.989 | J40: =J39+H40 -> 15795.52 | K40: =K39-H39 -> 304652.92 | L40: 400000 | M40: =L40-K40 -> 95347.078 | O40: 26 | P40: =I314 -> 290555.93 | Q40: =J314 -> 245406.78 | R40: =Q40-Q39 -> 16435.761
E41: 38 | F41: =F40 -> 1717.8292 | G41: =(B$5/B$7)*K41 -> 1267.5187 | H41: =F41-G41 -> 450.31053 | I41: =I40+G41 -> 50749.508 | J41: =J40+H41 -> 16245.831 | K41: =K40-H40 -> 304204.48 | L41: 400000 | M41: =L41-K41 -> 95795.52 | O41: 27 | P41: =I326 -> 293893.23 | Q41: =J326 -> 262683.42 | R41: =Q41-Q40 -> 17276.646
E42: 39 | F42: =F41 -> 1717.8292 | G42: =(B$5/B$7)*K42 -> 1265.6424 | H42: =F42-G42 -> 452.18682 | I42: =I41+G42 -> 52015.15 | J42: =J41+H42 -> 16698.018 | K42: =K41-H41 -> 303754.17 | L42: 400000 | M42: =L42-K42 -> 96245.831 | O42: 28 | P42: =I338 -> 296346.63 | Q42: =J338 -> 280843.98 | R42: =Q42-Q41 -> 18160.552
E43: 40 | F43: =F42 -> 1717.8292 | G43: =(B$5/B$7)*K43 -> 1263.7583 | H43: =F43-G43 -> 454.07093 | I43: =I42+G43 -> 53278.908 | J43: =J42+H43 -> 17152.089 | K43: =K42-H42 -> 303301.98 | L43: 400000 | M43: =L43-K43 -> 96698.018 | O43: 29 | P43: =I350 -> 297870.9 | Q43: =J350 -> 299933.66 | R43: =Q43-Q42 -> 19089.68
E44: 41 | F44: =F43 -> 1717.8292 | G44: =(B$5/B$7)*K44 -> 1261.8663 | H44: =F44-G44 -> 455.9629 | I44: =I43+G44 -> 54540.775 | J44: =J43+H44 -> 17608.052 | K44: =K43-H43 -> 302847.91 | L44: 400000 | M44: =L44-K44 -> 97152.089 | O44: 30 | P44: =I362 -> 298418.51 | Q44: =J362 -> 320000 | R44: =Q44-Q43 -> 20066.344
E45: 42 | F45: =F44 -> 1717.8292 | G45: =(B$5/B$7)*K45 -> 1259.9665 | H45: =F45-G45 -> 457.86274 | I45: =I44+G45 -> 55800.741 | J45: =J44+H45 -> 18065.914 | K45: =K44-H44 -> 302391.95 | L45: 400000 | M45: =L45-K45 -> 97608.052
E46: 43 | F46: =F45 -> 1717.8292 | G46: =(B$5/B$7)*K46 -> 1258.0587 | H46: =F46-G46 -> 459.7705 | I46: =I45+G46 -> 57058.8 | J46: =J45+H46 -> 18525.685 | K46: =K45-H45 -> 301934.09 | L46: 400000 | M46: =L46-K46 -> 98065.914
E47: 44 | F47: =F46 -> 1717.8292 | G47: =(B$5/B$7)*K47 -> 1256.143 | H47: =F47-G47 -> 461.68621 | I47: =I46+G47 -> 58314.943 | J47: =J46+H47 -> 18987.371 | K47: =K46-H46 -> 301474.32 | L47: 400000 | M47: =L47-K47 -> 98525.685
E48: 45 | F48: =F47 -> 1717.8292 | G48: =(B$5/B$7)*K48 -> 1254.2193 | H48: =F48-G48 -> 463.60991 | I48: =I47+G48 -> 59569.162 | J48: =J47+H48 -> 19450.981 | K48: =K47-H47 -> 301012.63 | L48: 400000 | M48: =L48-K48 -> 98987.371
E49: 46 | F49: =F48 -> 1717.8292 | G49: =(B$5/B$7)*K49 -> 1252.2876 | H49: =F49-G49 -> 465.54161 | I49: =I48+G49 -> 60821.45 | J49: =J48+H49 -> 19916.523 | K49: =K48-H48 -> 300549.02 | L49: 400000 | M49: =L49-K49 -> 99450.981
E50: 47 | F50: =F49 -> 1717.8292 | G50: =(B$5/B$7)*K50 -> 1250.3478 | H50: =F50-G50 -> 467.48137 | I50: =I49+G50 -> 62071.797 | J50: =J49+H50 -> 20384.004 | K50: =K49-H49 -> 300083.48 | L50: 400000 | M50: =L50-K50 -> 99916.523
E51: 48 | F51: =F50 -> 1717.8292 | G51: =(B$5/B$7)*K51 -> 1248.4 | H51: =F51-G51 -> 469.42921 | I51: =I50+G51 -> 63320.197 | J51: =J50+H51 -> 20853.433 | K51: =K50-H50 -> 299616 | L51: 400000 | M51: =L51-K51 -> 100384
E52: 49 | F52: =F51 -> 1717.8292 | G52: =(B$5/B$7)*K52 -> 1246.444 | H52: =F52-G52 -> 471.38516 | I52: =I51+G52 -> 64566.641 | J52: =J51+H52 -> 21324.818 | K52: =K51-H51 -> 299146.57 | L52: 400000 | M52: =L52-K52 -> 100853.43
E53: 50 | F53: =F52 -> 1717.8292 | G53: =(B$5/B$7)*K53 -> 1244.4799 | H53: =F53-G53 -> 473.34927 | I53: =I52+G53 -> 65811.121 | J53: =J52+H53 -> 21798.168 | K53: =K52-H52 -> 298675.18 | L53: 400000 | M53: =L53-K53 -> 101324.82
E54: 51 | F54: =F53 -> 1717.8292 | G54: =(B$5/B$7)*K54 -> 1242.5076 | H54: =F54-G54 -> 475.32156 | I54: =I53+G54 -> 67053.629 | J54: =J53+H54 -> 22273.489 | K54: =K53-H53 -> 298201.83 | L54: 400000 | M54: =L54-K54 -> 101798.17
E55: 52 | F55: =F54 -> 1717.8292 | G55: =(B$5/B$7)*K55 -> 1240.5271 | H55: =F55-G55 -> 477.30206 | I55: =I54+G55 -> 68294.156 | J55: =J54+H55 -> 22750.791 | K55: =K54-H54 -> 297726.51 | L55: 400000 | M55: =L55-K55 -> 102273.49
E56: 53 | F56: =F55 -> 1717.8292 | G56: =(B$5/B$7)*K56 -> 1238.5384 | H56: =F56-G56 -> 479.29082 | I56: =I55+G56 -> 69532.694 | J56: =J55+H56 -> 23230.082 | K56: =K55-H55 -> 297249.21 | L56: 400000 | M56: =L56-K56 -> 102750.79
... E363: 360 | F363: =F362 -> 1717.8292 | G363: =(B$5/B$7)*K363 -> -4.6838977e-12 | H363: =F363-G363 -> 1717.8292 | I363: =I362+G363 -> 298418.51 | J363: =J362+H363 -> 321717.83 | K363: =K362-H362 -> -1.1241355e-09 | L363: 400000 | M363: =L363-K363 -> 400000

Sheet Chapter 31
C3: NOI | D3: TDS | E3: DSCR
B4: Property 1 | C4: 25000 | D4: 21000 | E4: =C4/D4 -> 1.1904762
B5: Property 2 | C5: 22000 | D5: 15000 | E5: =C5/D5 -> 1.4666667

Sheet Chapter 34
C2: Monthly | D2: Annual
B3: Rental Income | C3: 1200 | D3: =C3*12 -> 14400
B4: Expenses | C4: 600 | D4: =C4*12 -> 7200
B5: Net Operating Income | C5: 600 | D5: =C5*12 -> 7200
B6: Debt Service | C6: 0 | D6: =C6*12 -> 0
B7: Cash Flow | C7: 600 | D7: =C7*12 -> 7200
C10: Monthly | D10: Annual
B11: Rental Income | C11: 1200 | D11: =C11*12 -> 14400
B12: Expenses | C12: 600 | D12: =C12*12 -> 7200
B13: Net Operating Income | C13: 600 | D13: =C13*12 -> 7200
B14: Debt Service | C14: 405 | D14: =C14*12 -> 4860
B15: Cash Flow | C15: =C13-C14 -> 195 | D15: =C15*12 -> 2340
C18: Monthly | D18: Annual
B19: Rental Income | C19: 1200 | D19: =C19*12 -> 14400
B20: Expenses | C20: 600 | D20: =C20*12 -> 7200
B21: Net Operating Income | C21: 600 | D21: =C21*12 -> 7200
B22: Debt Service | C22: 532 | D22: =C22*12 -> 6384
B23: Cash Flow | C23: =C21-C22 -> 68 | D23: =C23*12 -> 816
C28: No Loan | D28: Loan @ 4.5% | E28: Loan @ 7%
B29: Purchase Price | C29: 100000 | D29: 100000 | E29: 100000
B30: Loan Amount | C30: 0 | D30: 80000 | E30: 80000
B31: Down Payment (DP) | C31: =C29 -> 100000 | D31: =D29-D30 -> 20000 | E31: =E29-E30 -> 20000
B32: Interest Rate | C32: N/A | D32: 0.045 | E32: 0.07
B33: Cash Flow | C33: 7200 | D33: 2340 | E33: 816
B34: ROI (Cash Flow/DP) | C34: 0.072 | D34: 0.117 | E34: 0.041

Sheet Chapter 27 (16)

Sheet Chapter 27 (2)

Sheet Chapter 27 (3)

Sheet Chapter 27 (4)

Sheet Chapter 27 (5)

Sheet Chapter 27 (6)

Sheet Chapter 27 (7)

Sheet Chapter 27 (8)

Sheet Chapter 27

Sheet Compounding and CAGR
C5: Year-End Balance | D5: Return | E5: Annual ROI | K5: Portfolio Value | L5: Annual Growth Rate
B6: Year 0 | C6: 60000 | J6: Year 0 | K6: 10000 | Q6: Year-End Balance | R6: Interest Rate | S6: Annual Profit
B7: Year 1 | C7: 60000 | D7: =C7*E7 -> 3000 | E7: 0.05 | J7: Year 1 | K7: =K6*(1+L7) -> 11500 | L7: 0.15 | P7: Year 1 | Q7: 10000
B8: Year 2 | C8: 60000 | D8: =C8*E8 -> 3000 | E8: 0.05 | J8: Year 2 | K8: =K7*(1+L8) -> 13570 | L8: 0.18 | P8: Year 2 | Q8: 10000 | R8: 0.05 | S8: =Q8*R8 -> 500
B9: Year 3 | C9: 60000 | D9: =C9*E9 -> 3000 | E9: 0.05 | J9: Year 3 | K9: =K8*(1+L9) -> 11941.6 | L9: -0.12 | P9: year 3 | Q9: 10000 | R9: 0.05 | S9: =Q9*R9 -> 500
B10: Year 4 | C10: 60000 | D10: =C10*E10 -> 3000 | E10: 0.05 | J10: Year 4 | K10: =K9*(1+L10) -> 10866.856 | L10: -0.09 | P10: Year 4 | Q10: 10000 | R10: 0.05 | S10: =Q10*R10 -> 500
J11: Year 5 | K11: =K10*(1+L11) -> 10323.513 | L11: -0.05 | P11: Year 5 | Q11: 10000 | R11: 0.05 | S11: =Q11*R11 -> 500
J12: Year 6 | K12: =K11*(1+L12) -> 9084.6916 | L12: -0.12
J13: Year 7 | K13: =K12*(1+L13) -> 10901.63 | L13: 0.2
C14: Year-End Balance | D14: Return | E14: Annual ROI | J14: Year 8 | K14: =K13*(1+L14) -> 12536.874 | L14: 0.15
B15: Year 0 | C15: 10000 | D15: 500 | J15: Year 9 | K15: =K14*(1+L15) -> 14041.299 | L15: 0.12
B16: Year 1 | C16: =C15+D15 -> 10500 | D16: =C16*E16 -> 525 | E16: 0.05 | J16: ROI | K16: =K15/K6-1 -> 0.40412994
B17: Year 2 | C17: =C16+D16 -> 11025 | D17: =C17*E17 -> 551.25 | E17: 0.05 | J17: AAGR | K17: =SUM(L7:L15)/9 -> 0.046666667
B18: Year 3 | C18: =C17+D17 -> 11576.25 | D18: =C18*E18 -> 578.8125 | E18: 0.05 | J18: CAGR | K18: =_xlfn.RRI(9, K6, K15) -> 0.038433258 | M18: {=SUM(L7:L15/9)} -> 0.046666667
B19: Year 4 | C19: =C18+D18 -> 12155.062 | D19: =C19*E19 -> 607.75313 | E19: 0.05
J20: Year | K20: Appreciation | M20: =10000*K17*9 -> 4200
J21: Year 0 | K21: 0.09 | M21: =10000*(1+K18)^9 -> 14041.299
J22: Year 1 | K22: 0.12
J23: Year 2 | K23: -0.06
J24: Year 3 | K24: 0.01
J25: Year 4 | K25: -0.04
J26: Year 5 | K26: -0.08
J27: Year 6 | K27: 0.08
J28: Year 7 | K28: 0.1
J29: Year 8 | K29: 0.07
J30: Year 9 | K30: N/A (Sold)
B33: Investment 1 | G33: Investment 1
B34: Year | C34: Account Balance | G34: Year | H34: Account Balance | I34: ROI
B35: Year 0 | C35: 1000 | G35: Year 0 | H35: 1000
B36: Year 1 | C36: 1200 | G36: Year 1 | H36: 1200 | I36: =H36/H35-1 -> 0.2
B37: Year 2 | C37: 1250 | G37: Year 2 | H37: 1250 | I37: =H37/H36-1 -> 0.041666667
B38: Year 3 | C38: 1400 | G38: Year 3 | H38: 1400 | I38: =H38/H37-1 -> 0.12
B39: Year 4 | C39: 1300 | G39: Year 4 | H39: 1300 | I39: =H39/H38-1 -> -0.071428571
B40: Year 5 | C40: 1150 | G40: Year 5 | H40: 1150 | I40: =H40/H39-1 -> -0.11538462
B41: Year 6 | C41: 1600 | G41: Year 6 | H41: 1600 | I41: =H41/H40-1 -> 0.39130435
B42: Year 7 | C42: 1800 | G42: Year 7 | H42: 1800 | I42: =H42/H41-1 -> 0.125
B43: Year 8 | C43: 2000 | G43: Year 8 | H43: 2000 | I43: =H43/H42-1 -> 0.11111111
B44: Year 9 | C44: 2100 | G44: Year 9 | H44: 2100 | I44: =H44/H43-1 -> 0.05
B45: Year 10 | C45: 2400 | G45: Year 10 | H45: 2400 | I45: =H45/H44-1 -> 0.14285714
G46: ROI | H46: =H45/H35-1 -> 1.4
G47: AAGR | H47: =SUM(I36:I45)/COUNT(I36:I45) -> 0.099512608
G48: CAGR | H48: =_xlfn.RRI(10, H35, H45) -> 0.091493426
B52: Investment 2 | G52: Investment 2
B53: Year | C53: Account Balance | G53: Year | H53: Account Balance | I53: ROI
B54: Year 0 | C54: 1000 | G54: Year 0 | H54: 1000
B55: Year 1 | C55: 1200 | G55: Year 1 | H55: 1200 | I55: =H55/H54-1 -> 0.2
B56: Year 2 | C56: 1250 | G56: Year 2 | H56: 1250 | I56: =H56/H55-1 -> 0.041666667
B57: Year 3 | C57: 1400 | G57: Year 3 | H57: 1400 | I57: =H57/H56-1 -> 0.12
B58: Year 4 | C58: 1300 | G58: Year 4 | H58: 1300 | I58: =H58/H57-1 -> -0.071428571
B59: Year 5 | C59: 1450 | G59: Year 5 | H59: 1450 | I59: =H59/H58-1 -> 0.11538462
B60: Year 6 | C60: 1600 | G60: Year 6 | H60: 1600 | I60: =H60/H59-1 -> 0.10344828
B61: Year 7 | C61: 1900 | G61: Year 7 | H61: 1900 | I61: =H61/H60-1 -> 0.1875
G62: ROI | H62: =H61/H54-1 -> 0.9
G63: AAGR | H63: =SUM(I55:I61)/COUNT(I55:I61) -> 0.099510141
G64: CAGR | H64: =_xlfn.RRI(7, H54, H61) -> 0.096028742

Sheet Final Proforma
B3: Assumptions | C3: 457 Main St. | E3: Financing Details | F3: =C3 -> 457 Main St. | H3: Outputs | I3: =F3 -> 457 Main St.
B4: Starting Income (Annual | C4: 28800 | E4: Purchase Price | F4: 400000 | H4: Total Invested | I4: =F4*F5+F16 -> 106000
B5: Other Income (Annual) | C5: 0 | E5: Down Payment (%) | F5: 0.25 | H5: PV | I5: =AG58/(1+C12)^AG23 -> 73760.018
B6: Income Growth Rate | C6: 0.02 | E6: Loan Amount (Principal) | F6: 91500 | H6: NPV | I6: =SUM(C45:AG45) -> -11520.216
B7: Expense Growth Rate | C7: 0.01 | E7: Annual Interest Rate | F7: 0.04 | H7: IRR | I7: =XIRR(C44:AG44, C22:AG22) -> 0.071210399
B8: Property Management Fee | C8: 0 | E8: Term (Years) | F8: 30 | H8: CAGR | I8: =_xlfn.RRI(F8, I4,AG58) -> 0.067024178
B9: Repairs and Maintenance Reserve (%) | C9: 0.05 | E9: Payments/year | F9: 12
B10: Capex Reserve (%) | C10: 0.05 | E10: Total Payments | F10: 360
B11: Income Tax (%) | C11: 0.33 | E11: P&I Per Period | F11: ='Mortgage Calculator_IP'!B8 -> 1432.2459
B12: Discount Rate | C12: 0.08 | E12: PMI per Period | F12: 0
B13: Property Appreciation | C13: 0.01 | E13: Total payment per period | F13: =SUM(F11:F12) -> 1432.2459
B14: Commission Paid at Sale | C14: =5.8% -> 0.058 | E14: Sum of Payments | F14: =F13*F10 -> 515608.52
B15: ARV | C15: 122000 | E15: Interest Cost + PMI | F15: =F14-F6 -> 424108.52
B16: Vacancy Rate | C16: 0.09 | E16: Estimated Closing Costs | F16: 6000
E17: Loan Constant | F17: =((SUM(F11:F12)*12)/F6) -> 0.18783553
E18: Est Cap Rate | F18: =C38/F4 -> 0.053494
E19: Breakeven loan value | F19: =C38/F17 -> 113916.68
B22: Year (for XIRR) | C22: 44562 | D22: 44927 | E22: 45292 | F22: 45658 | G22: 46023 | H22: 46388 | I22: 46753 | J22: 47119 | K22: 47484 | L22: 47849 | M22: 48214 | N22: 48580 | O22: 48945 | P22: 49310 | Q22: 49675 | R22: 50041 | S22: 50406 | T22: 50771 | U22: 51136 | V22: 51502 | W22: 51867 | X22: 52232 | Y22: 52597 | Z22: 52963 | AA22: 53328 | AB22: 53693 | AC22: 54058 | AD22: 54424 | AE22: 54789 | AF22: 55154 | AG22: 55519
B23: Income | C23: 0 | D23: 1 | E23: 2 | F23: 3 | G23: 4 | H23: 5 | I23: 6 | J23: 7 | K23: 8 | L23: 9 | M23: 10 | N23: 11 | O23: 12 | P23: 13 | Q23: 14 | R23: 15 | S23: 16 | T23: 17 | U23: 18 | V23: 19 | W23: 20 | X23: 21 | Y23: 22 | Z23: 23 | AA23: 24 | AB23: 25 | AC23: 26 | AD23: 27 | AE23: 28 | AF23: 29 | AG23: 30
B24: Potential Gross Income | C24: =C4 -> 28800 | D24: =$C24*(1+$C$6)^D$23 -> 29376 | E24: =$C24*(1+$C$6)^E23 -> 29963.52 | F24: =$C24*(1+$C$6)^F23 -> 30562.79 | G24: =$C24*(1+$C$6)^G23 -> 31174.046 | H24: =$C24*(1+$C$6)^H23 -> 31797.527 | I24: =$C24*(1+$C$6)^I23 -> 32433.478 | J24: =$C24*(1+$C$6)^J23 -> 33082.147 | K24: =$C24*(1+$C$6)^K23 -> 33743.79 | L24: =$C24*(1+$C$6)^L23 -> 34418.666 | ... AG24: =$C24*(1+$C$6)^AG23 -> 52167.214
B25: Other Income | C25: =C5 -> 0 | D25: =$C25*(1+$C$6)^D$23 -> 0 | E25: =$C25*(1+$C$6)^E$23 -> 0 | F25: =$C25*(1+$C$6)^F$23 -> 0 | G25: =$C25*(1+$C$6)^G$23 -> 0 | H25: =$C25*(1+$C$6)^H$23 -> 0 | I25: =$C25*(1+$C$6)^I$23 -> 0 | J25: =$C25*(1+$C$6)^J$23 -> 0 | K25: =$C25*(1+$C$6)^K$23 -> 0 | ... AG25: =$C25*(1+$C$6)^AG$23 -> 0
B26: Rent Loss | C26: =-(C24*$C$16) -> -2592 | D26: =-(D24*$C$16) -> -2643.84 | E26: =-(E24*$C$16) -> -2696.7168 | F26: =-(F24*$C$16) -> -2750.6511 | G26: =-(G24*$C$16) -> -2805.6642 | H26: =-(H24*$C$16) -> -2861.7774 | I26: =-(I24*$C$16) -> -2919.013 | J26: =-(J24*$C$16) -> -2977.3933 | ... AG26: =-(AG24*$C$16) -> -4695.0492
B27: Effective Gross Income | C27: =SUM(C24:C26) -> 26208 | D27: =SUM(D24:D26) -> 26732.16 | E27: =SUM(E24:E26) -> 27266.803 | F27: =SUM(F24:F26) -> 27812.139 | G27: =SUM(G24:G26) -> 28368.382 | H27: =SUM(H24:H26) -> 28935.75 | I27: =SUM(I24:I26) -> 29514.465 | J27: =SUM(J24:J26) -> 30104.754 | ... AG27: =SUM(AG24:AG26) -> 47472.164
B29: Expenses
B30: Property Management | C30: =C27*$C8 -> 0 | D30: =D27*$C8 -> 0 | E30: =E27*$C8 -> 0 | F30: =F27*$C8 -> 0 | G30: =G27*$C8 -> 0 | H30: =H27*$C8 -> 0 | I30: =I27*$C8 -> 0 | J30: =J27*$C8 -> 0 | ... AG30: =AG27*$C8 -> 0
B31: Repairs & Maintenance | C31: =C$27*$C9 -> 1310.4 | D31: =D$27*$C9 -> 1336.608 | E31: =E$27*$C9 -> 1363.3402 | F31: =F$27*$C9 -> 1390.607 | G31: =G$27*$C9 -> 1418.4191 | H31: =H$27*$C9 -> 1446.7875 | I31: =I$27*$C9 -> 1475.7232 | J31: =J$27*$C9 -> 1505.2377 | ... AG31: =AG$27*$C9 -> 2373.6082
B32: Professional Fees (Accounting & Lawyers) | C32: 800 | D32: =$C32*(1+$C$7)^D$23 -> 808 | E32: =$C32*(1+$C$7)^E$23 -> 816.08 | F32: =$C32*(1+$C$7)^F$23 -> 824.2408 | G32: =$C32*(1+$C$7)^G$23 -> 832.48321 | H32: =$C32*(1+$C$7)^H$23 -> 840.80804 | I32: =$C32*(1+$C$7)^I$23 -> 849.21612 | J32: =$C32*(1+$C$7)^J$23 -> 857.70828 | K32: =$C32*(1+$C$7)^K$23 -> 866.28536 | ... AG32: =$C32*(1+$C$7)^AG$23 -> 1078.2791
B33: Utilities | C33: 0 | D33: =$C33*(1+$C$7)^D$23 -> 0 | E33: =$C33*(1+$C$7)^E$23 -> 0 | F33: =$C33*(1+$C$7)^F$23 -> 0 | G33: =$C33*(1+$C$7)^G$23 -> 0 | H33: =$C33*(1+$C$7)^H$23 -> 0 | I33: =$C33*(1+$C$7)^I$23 -> 0 | J33: =$C33*(1+$C$7)^J$23 -> 0 | K33: =$C33*(1+$C$7)^K$23 -> 0 | ... AG33: =$C33*(1+$C$7)^AG$23 -> 0
B34: Property Tax | C34: 1500 | D34: =$C34*(1+$C$7)^D$23 -> 1515 | E34: =$C34*(1+$C$7)^E$23 -> 1530.15 | F34: =$C34*(1+$C$7)^F$23 -> 1545.4515 | G34: =$C34*(1+$C$7)^G$23 -> 1560.906 | H34: =$C34*(1+$C$7)^H$23 -> 1576.5151 | I34: =$C34*(1+$C$7)^I$23 -> 1592.2802 | J34: =$C34*(1+$C$7)^J$23 -> 1608.203 | K34: =$C34*(1+$C$7)^K$23 -> 1624.2851 | ... AG34: =$C34*(1+$C$7)^AG$23 -> 2021.7734
B35: Insurance | C35: 1200 | D35: =$C35*(1+$C$7)^D$23 -> 1212 | E35: =$C35*(1+$C$7)^E$23 -> 1224.12 | F35: =$C35*(1+$C$7)^F$23 -> 1236.3612 | G35: =$C35*(1+$C$7)^G$23 -> 1248.7248 | H35: =$C35*(1+$C$7)^H$23 -> 1261.2121 | I35: =$C35*(1+$C$7)^I$23 -> 1273.8242 | J35: =$C35*(1+$C$7)^J$23 -> 1286.5624 | K35: =$C35*(1+$C$7)^K$23 -> 1299.428 | ... AG35: =$C35*(1+$C$7)^AG$23 -> 1617.4187
B36: Total Operating Expenses | C36: =SUM(C30:C35) -> 4810.4 | D36: =SUM(D30:D35) -> 4871.608 | E36: =SUM(E30:E35) -> 4933.6902 | F36: =SUM(F30:F35) -> 4996.6605 | G36: =SUM(G30:G35) -> 5060.5331 | H36: =SUM(H30:H35) -> 5125.3227 | I36: =SUM(I30:I35) -> 5191.0438 | J36: =SUM(J30:J35) -> 5257.7114 | ... AG36: =SUM(AG30:AG35) -> 7091.0794
B38: Net Operating Income | C38: =C27-C36 -> 21397.6 | D38: =D27-D36 -> 21860.552 | E38: =E27-E36 -> 22333.113 | F38: =F27-F36 -> 22815.479 | G38: =G27-G36 -> 23307.849 | H38: =H27-H36 -> 23810.427 | I38: =I27-I36 -> 24323.421 | J38: =J27-J36 -> 24847.043 | ... AG38: =AG27-AG36 -> 40381.085
B40: Down Payment + Closing Costs | C40: =(F4*F5)+F16 -> 106000
B41: Debt Service | C41: =($F$13*$F$9) -> 17186.951 | D41: =($F$13*$F$9) -> 17186.951 | E41: =($F$13*$F$9) -> 17186.951 | F41: =($F$13*$F$9) -> 17186.951 | G41: =($F$13*$F$9) -> 17186.951 | H41: =($F$13*$F$9) -> 17186.951 | I41: =($F$13*$F$9) -> 17186.951 | J41: =($F$13*$F$9) -> 17186.951 | ... AG41: =($F$13*$F$9) -> 17186.951
B42: Capital Expenditures | C42: =C27*$C10 -> 1310.4 | D42: =D27*$C10 -> 1336.608 | E42: =E27*$C10 -> 1363.3402 | F42: =F27*$C10 -> 1390.607 | G42: =G27*$C10 -> 1418.4191 | H42: =H27*$C10 -> 1446.7875 | I42: =I27*$C10 -> 1475.7232 | J42: =J27*$C10 -> 1505.2377 | ... AG42: =AG27*$C10 -> 2373.6082
B44: Cash Flow Before Taxes | C44: =C38-SUM(C40:C42) -> -103099.75 | D44: =D38-SUM(D40:D42) -> 3336.9934 | E44: =E38-SUM(E40:E42) -> 3782.8222 | F44: =F38-SUM(F40:F42) -> 4237.9212 | G44: =G38-SUM(G40:G42) -> 4702.4792 | H44: =H38-SUM(H40:H42) -> 5176.6889 | I44: =I38-SUM(I40:I42) -> 5660.7471 | J44: =J38-SUM(J40:J42) -> 6154.8542 | ... AG44: =AG38-SUM(AG40:AG42) -> 20820.526
B45: Present Value | C45: =C44/(1+$C$12)^C23 -> -103099.75 | D45: =D44/(1+$C$12)^D23 -> 3089.8087 | E45: =E44/(1+$C$12)^E23 -> 3243.1604 | F45: =F44/(1+$C$12)^F23 -> 3364.1985 | G45: =G44/(1+$C$12)^G23 -> 3456.4626 | H45: =H44/(1+$C$12)^H23 -> 3523.1675 | I45: =I44/(1+$C$12)^I23 -> 3567.2309 | J45: =J44/(1+$C$12)^J23 -> 3591.2983 | ... AG45: =AG44/(1+$C$12)^AG23 -> 2069.0883
B47: Income Taxes | C47: =C44*$C$11 -> -34022.918 | D47: =D44*$C$11 -> 1101.2078 | E47: =E44*$C$11 -> 1248.3313 | F47: =F44*$C$11 -> 1398.514 | G47: =G44*$C$11 -> 1551.8181 | H47: =H44*$C$11 -> 1708.3073 | I47: =I44*$C$11 -> 1868.0465 | J47: =J44*$C$11 -> 2031.1019 | ... AG47: =AG44*$C$11 -> 6870.7736
B49: Cash Flow After Taxes | C49: =C44-C47 -> -69076.833 | D49: =D44-D47 -> 2235.7856 | E49: =E44-E47 -> 2534.4909 | F49: =F44-F47 -> 2839.4072 | G49: =G44-G47 -> 3150.661 | H49: =H44-H47 -> 3468.3816 | I49: =I44-I47 -> 3792.7005 | J49: =J44-J47 -> 4123.7523 | ... AG49: =AG44-AG47 -> 13949.752
B51: Estimated Property Value | C51: =IF(C15>F4, C15, F4) -> 400000 | D51: =$C51*(1+$C$13)^D$23 -> 404000 | E51: =$C51*(1+$C$13)^E$23 -> 408040 | F51: =$C51*(1+$C$13)^F$23 -> 412120.4 | G51: =$C51*(1+$C$13)^G$23 -> 416241.6 | H51: =$C51*(1+$C$13)^H$23 -> 420404.02 | I51: =$C51*(1+$C$13)^I$23 -> 424608.06 | J51: =$C51*(1+$C$13)^J$23 -> 428854.14 | K51: =$C51*(1+$C$13)^K$23 -> 433142.68 | ... AG51: =$C51*(1+$C$13)^AG$23 -> 539139.57
B52: Principle Remaining on Loan | C52: ='Mortgage Calculator_IP'!P8 -> 295165.25 | D52: ='Mortgage Calculator_IP'!Q8 -> 289685.17 | E52: ='Mortgage Calculator_IP'!R8 -> 283981.82 | F52: ='Mortgage Calculator_IP'!S8 -> 278046.1 | G52: ='Mortgage Calculator_IP'!T8 -> 271868.56 | H52: ='Mortgage Calculator_IP'!U8 -> 265439.33 | I52: ='Mortgage Calculator_IP'!V8 -> 258748.16 | J52: ='Mortgage Calculator_IP'!W8 -> 251784.39 | ... AG52: ='Mortgage Calculator_IP'!AT8 -> 0
B53: Equity | C53: =C51-C52 -> 104834.75 | D53: =D51-D52 -> 114314.83 | E53: =E51-E52 -> 124058.18 | F53: =F51-F52 -> 134074.3 | G53: =G51-G52 -> 144373.05 | H53: =H51-H52 -> 154964.69 | I53: =I51-I52 -> 165859.9 | J53: =J51-J52 -> 177069.75 | ... AG53: =AG51-AG52 -> 539139.57
B54: Equity minus invested cash | C54: =C53-$I$4 -> -1165.2524 | D54: =D53-$I$4 -> 8314.832 | E54: =E53-$I$4 -> 18058.183 | F54: =F53-$I$4 -> 28074.298 | G54: =G53-$I$4 -> 38373.047 | H54: =H53-$I$4 -> 48964.691 | I54: =I53-$I$4 -> 59859.896 | J54: =J53-$I$4 -> 71069.749 | ... AG54: =AG53-$I$4 -> 433139.57
B56: Cumulative Cashflow | C56: =C44 -> -103099.75 | D56: =C56+D44 -> -99762.757 | E56: =D56+E44 -> -95979.935 | F56: =E56+F44 -> -91742.014 | G56: =F56+G44 -> -87039.535 | H56: =G56+H44 -> -81862.846 | I56: =H56+I44 -> -76202.099 | J56: =I56+J44 -> -70047.244 | K56: =J56+K44 -> -63388.029 | ... AG56: =AF56+AG44 -> 234352.28
B57: Proceeds at Sale | C57: =(C51-C52) - (C51*$C$14) -> 81634.748 | D57: =(D51-D52) - (D51*$C$14) -> 90882.832 | E57: =(E51-E52) - (E51*$C$14) -> 100391.86 | F57: =(F51-F52) - (F51*$C$14) -> 110171.32 | G57: =(G51-G52) - (G51*$C$14) -> 120231.03 | H57: =(H51-H52) - (H51*$C$14) -> 130581.26 | I57: =(I51-I52) - (I51*$C$14) -> 141232.63 | J57: =(J51-J52) - (J51*$C$14) -> 152196.21 | ... AG57: =(AG51-AG52) - (AG51*$C$14) -> 507869.47
B58: Profit at Sale (Total Return) | C58: =SUM(C56:C57) -> -21465.003 | D58: =SUM(D56:D57) -> -8879.9253 | E58: =SUM(E56:E57) -> 4411.9284 | F58: =SUM(F56:F57) -> 18429.301 | G58: =SUM(G56:G57) -> 33191.5 | H58: =SUM(H56:H57) -> 48718.412 | I58: =SUM(I56:I57) -> 65030.529 | J58: =SUM(J56:J57) -> 82148.964 | ... AG58: =SUM(AG56:AG57) -> 742221.76
B60: Cash-on-Cash Return | C60: =(C44+C40)/$C$40 -> 0.027360843 | D60: =(D44+D40)/$C$40 -> 0.031481069 | E60: =(E44+E40)/$C$40 -> 0.035687002 | F60: =(F44+F40)/$C$40 -> 0.039980389 | G60: =(G44+G40)/$C$40 -> 0.044363011 | H60: =(H44+H40)/$C$40 -> 0.048836688 | I60: =(I44+I40)/$C$40 -> 0.053403274 | J60: =(J44+J40)/$C$40 -> 0.058064662 | ... AG60: =(AG44+AG40)/$C$40 -> 0.19642006
B61: Simple ROI | C61: =C58/$I$4 -> -0.20250003 | D61: =D58/$I$4 -> -0.08377288 | E61: =E58/$I$4 -> 0.041621966 | F61: =F58/$I$4 -> 0.17386133 | G61: =G58/$I$4 -> 0.31312735 | H61: =H58/$I$4 -> 0.45960766 | I61: =I58/$I$4 -> 0.61349556 | J61: =J58/$I$4 -> 0.77499023 | ... AG61: =AG58/$I$4 -> 7.002092
B62: AAROI | D62: =D61/D23 -> -0.08377288 | E62: =E61/E23 -> 0.020810983 | F62: =F61/F23 -> 0.057953777 | G62: =G61/G23 -> 0.078281839 | H62: =H61/H23 -> 0.091921532 | I62: =I61/I23 -> 0.10224926 | J62: =J61/J23 -> 0.11071289 | K62: =K61/K23 -> 0.11803711 | ... AG62: =AG61/AG23 -> 0.23340307

Sheet Spare Mort Calc
A1: Purchase Price | B1: 200000 | E1: Payment Number | F1: Payment ($) | G1: Interest Paid | H1: Prinicipal Paid | I1: Total Interest Paid | J1: Total Principal Paid | K1: Principal Balance | L1: Sale Price | M1: Profit
A2: Down Payment (%) | B2: 0.2 | E2: 0 | F2: =B8 -> 763.86447 | G2: =(B$4/B$6)*K2 -> 533.33333 | H2: =F2-G2 -> 230.53114 | I2: =G2 -> 533.33333 | J2: =H2 -> 230.53114 | K2: =B3 -> 160000 | L2: 400000 | M2: =L2-K2 -> 240000
A3: Loan Amount (Principal) | B3: =(1-B2)*B1 -> 160000 | E3: 1 | F3: =F2 -> 763.86447 | G3: =(B$4/B$6)*K3 -> 532.5649 | H3: =F3-G3 -> 231.29958 | I3: =I2+G3 -> 1065.8982 | J3: =J2+H3 -> 461.83072 | K3: =K2-H2 -> 159769.47 | L3: 400000 | M3: =L3-K3 -> 240230.53
A4: Annual Interest Rate | B4: ='Final Proforma'!F7 -> 0.04 | E4: 2 | F4: =F3 -> 763.86447 | G4: =(B$4/B$6)*K4 -> 531.7939 | H4: =F4-G4 -> 232.07058 | I4: =I3+G4 -> 1597.6921 | J4: =J3+H4 -> 693.90129 | K4: =K3-H3 -> 159538.17 | L4: 400000 | M4: =L4-K4 -> 240461.83 | O4: Annual | P4: 1 | Q4: 2 | R4: 3 | S4: 4 | T4: 5 | U4: 6 | V4: 7 | W4: 8 | X4: 9 | Y4: 10 | Z4: 11 | AA4: 12 | AB4: 13 | AC4: 14 | AD4: 15 | AE4: 16 | AF4: 17 | AG4: 18 | AH4: 19 | AI4: 20 | AJ4: 21 | AK4: 22 | AL4: 23 | AM4: 24 | AN4: 25 | AO4: 26 | AP4: 27 | AQ4: 28 | AR4: 29 | AS4: 30
A5: Term (Years) | B5: ='Final Proforma'!F8 -> 30 | E5: 3 | F5: =F4 -> 763.86447 | G5: =(B$4/B$6)*K5 -> 531.02033 | H5: =F5-G5 -> 232.84414 | I5: =I4+G5 -> 2128.7125 | J5: =J4+H5 -> 926.74543 | K5: =K4-H4 -> 159306.1 | L5: 400000 | M5: =L5-K5 -> 240693.9 | O5: Total Interest Paid | P5: =P14 -> 6348.7154 | Q5: =P15 -> 12582.635 | R5: =P16 -> 18697.082 | S5: =P17 -> 24687.189 | T5: =P18 -> 30547.889 | U5: =P19 -> 36273.912 | V5: =P20 -> 41859.769 | W5: =P21 -> 47299.751 | X5: =P22 -> 52587.913 | Y5: =P23 -> 57718.071 | Z5: =P24 -> 62683.788 | AA5: =P25 -> 67478.363 | AB5: =P26 -> 72094.825 | AC5: =P27 -> 76525.916 | AD5: =P28 -> 80764.084 | AE5: =P29 -> 84801.47 | AF5: =P30 -> 88629.893 | AG5: =P31 -> 92240.839 | AH5: =P32 -> 95625.449 | AI5: =P33 -> 98774.501 | AJ5: =P34 -> 101678.4 | AK5: =P35 -> 104327.15 | AL5: =P36 -> 106710.37 | AM5: =P37 -> 108817.23 | AN5: =P38 -> 110636.47 | AO5: =P39 -> 112156.38 | AP5: =P40 -> 113364.76 | AQ5: =P41 -> 114248.93 | AR5: =P42 -> 114795.66 | AS5: =P43 -> 114991.21
A6: Payments/year | B6: ='Final Proforma'!F9 -> 12 | E6: 4 | F6: =F5 -> 763.86447 | G6: =(B$4/B$6)*K6 -> 530.24418 | H6: =F6-G6 -> 233.62029 | I6: =I5+G6 -> 2658.9566 | J6: =J5+H6 -> 1160.3657 | K6: =K5-H5 -> 159073.25 | L6: 400000 | M6: =L6-K6 -> 240926.75 | O6: Total Principal Paid | P6: =Q14 -> 2817.6583 | Q6: =Q15 -> 5750.1123 | R6: =Q16 -> 8802.0391 | S6: =Q17 -> 11978.306 | T6: =Q18 -> 15283.979 | U6: =Q19 -> 18724.33 | V6: =Q20 -> 22304.847 | W6: =Q21 -> 26031.239 | X6: =Q22 -> 29909.45 | Y6: =Q23 -> 33945.665 | Z6: =Q24 -> 38146.322 | AA6: =Q25 -> 42518.121 | AB6: =Q26 -> 47068.033 | AC6: =Q27 -> 51803.315 | AD6: =Q28 -> 56731.521 | AE6: =Q29 -> 61860.509 | AF6: =Q30 -> 67198.459 | AG6: =Q31 -> 72753.887 | AH6: =Q32 -> 78535.651 | AI6: =Q33 -> 84552.972 | AJ6: =Q34 -> 90815.449 | AK6: =Q35 -> 97333.069 | AL6: =Q36 -> 104116.23 | AM6: =Q37 -> 111175.74 | AN6: =Q38 -> 118522.87 | AO6: =Q39 -> 126169.33 | AP6: =Q40 -> 134127.32 | AQ6: =Q41 -> 142409.54 | AR6: =Q42 -> 151029.18 | AS6: =Q43 -> 160000
A7: Total Payments | B7: =B6*B5 -> 360 | E7: 5 | F7: =F6 -> 763.86447 | G7: =(B$4/B$6)*K7 -> 529.46545 | H7: =F7-G7 -> 234.39903 | I7: =I6+G7 -> 3188.4221 | J7: =J6+H7 -> 1394.7648 | K7: =K6-H6 -> 158839.63 | L7: 400000 | M7: =L7-K7 -> 241160.37 | O7: Principal/Year | P7: =S14 -> 2817.6583 | Q7: =Q6-P6 -> 2932.454 | R7: =R6-Q6 -> 3051.9267 | S7: =S6-R6 -> 3176.2669 | T7: =T6-S6 -> 3305.673 | U7: =U6-T6 -> 3440.3512 | V7: =V6-U6 -> 3580.5164 | W7: =W6-V6 -> 3726.3922 | X7: =X6-W6 -> 3878.2111 | ... AS7: =AS6-AR6 -> 8970.8201
A8: Payment per Period | B8: =-PMT(B4/B6, B7, B3, 0) -> 763.86447 | E8: 6 | F8: =F7 -> 763.86447 | G8: =(B$4/B$6)*K8 -> 528.68412 | H8: =F8-G8 -> 235.18036 | I8: =I7+G8 -> 3717.1062 | J8: =J7+H8 -> 1629.9451 | K8: =K7-H7 -> 158605.24 | L8: 400000 | M8: =L8-K8 -> 241394.76 | O8: Principal Balance | P8: =R14 -> 157421.47 | Q8: =R15 -> 154498.76 | R8: =R16 -> 151456.97 | S8: =R17 -> 148291.25 | T8: =R18 -> 144996.56 | U8: =R19 -> 141567.64 | V8: =R20 -> 137999.02 | W8: =R21 -> 134285.01 | X8: =R22 -> 130419.68 | Y8: =R23 -> 126396.88 | Z8: =R24 -> 122210.17 | AA8: =R25 -> 117852.9 | AB8: =R26 -> 113318.1 | AC8: =R27 -> 108598.55 | AD8: =R28 -> 103686.72 | AE8: =R29 -> 98574.773 | AF8: =R30 -> 93254.556 | AG8: =R31 -> 87717.586 | AH8: =R32 -> 81955.03 | AI8: =R33 -> 75957.7 | AJ8: =R34 -> 69716.028 | AK8: =R35 -> 63220.062 | AL8: =R36 -> 56459.44 | AM8: =R37 -> 49423.379 | AN8: =R38 -> 42100.659 | AO8: =R39 -> 34479.599 | AP8: =R40 -> 26548.046 | AQ8: =R41 -> 18293.349 | AR8: =R42 -> 9702.3434 | AS8: =R43 -> 761.32672
A9: Sum of Payments | B9: =B8*B7 -> 274991.21 | E9: 7 | F9: =F8 -> 763.86447 | G9: =(B$4/B$6)*K9 -> 527.90018 | H9: =F9-G9 -> 235.96429 | I9: =I8+G9 -> 4245.0064 | J9: =J8+H9 -> 1865.9094 | K9: =K8-H8 -> 158370.05 | L9: 400000 | M9: =L9-K9 -> 241629.95
A10: Interest Cost | B10: =B9-B3 -> 114991.21 | E10: 8 | F10: =F9 -> 763.86447 | G10: =(B$4/B$6)*K10 -> 527.11364 | H10: =F10-G10 -> 236.75084 | I10: =I9+G10 -> 4772.12 | J10: =J9+H10 -> 2102.6602 | K10: =K9-H9 -> 158134.09 | L10: 400000 | M10: =L10-K10 -> 241865.91
E11: 9 | F11: =F10 -> 763.86447 | G11: =(B$4/B$6)*K11 -> 526.32447 | H11: =F11-G11 -> 237.54001 | I11: =I10+G11 -> 5298.4445 | J11: =J10+H11 -> 2340.2002 | K11: =K10-H10 -> 157897.34 | L11: 400000 | M11: =L11-K11 -> 242102.66
E12: 10 | F12: =F11 -> 763.86447 | G12: =(B$4/B$6)*K12 -> 525.53267 | H12: =F12-G12 -> 238.33181 | I12: =I11+G12 -> 5823.9772 | J12: =J11+H12 -> 2578.532 | K12: =K11-H11 -> 157659.8 | L12: 400000 | M12: =L12-K12 -> 242340.2
E13: 11 | F13: =F12 -> 763.86447 | G13: =(B$4/B$6)*K13 -> 524.73823 | H13: =F13-G13 -> 239.12625 | I13: =I12+G13 -> 6348.7154 | J13: =J12+H13 -> 2817.6583 | K13: =K12-H12 -> 157421.47 | L13: 400000 | M13: =L13-K13 -> 242578.53 | O13: Year | P13: Total Interest Paid | Q13: Total Principal Paid | R13: Total Principal Paid | S13: Principal/Year
E14: 12 | F14: =F13 -> 763.86447 | G14: =(B$4/B$6)*K14 -> 523.94114 | H14: =F14-G14 -> 239.92333 | I14: =I13+G14 -> 6872.6565 | J14: =J13+H14 -> 3057.5816 | K14: =K13-H13 -> 157182.34 | L14: 400000 | M14: =L14-K14 -> 242817.66 | O14: 1 | P14: =I13 -> 6348.7154 | Q14: =J13 -> 2817.6583 | R14: =K13 -> 157421.47 | S14: =Q14 -> 2817.6583
E15: 13 | F15: =F14 -> 763.86447 | G15: =(B$4/B$6)*K15 -> 523.14139 | H15: =F15-G15 -> 240.72308 | I15: =I14+G15 -> 7395.7979 | J15: =J14+H15 -> 3298.3047 | K15: =K14-H14 -> 156942.42 | L15: 400000 | M15: =L15-K15 -> 243057.58 | O15: 2 | P15: =I25 -> 12582.635 | Q15: =J25 -> 5750.1123 | R15: =K25 -> 154498.76 | S15: =Q15-Q14 -> 2932.454
E16: 14 | F16: =F15 -> 763.86447 | G16: =(B$4/B$6)*K16 -> 522.33898 | H16: =F16-G16 -> 241.52549 | I16: =I15+G16 -> 7918.1369 | J16: =J15+H16 -> 3539.8302 | K16: =K15-H15 -> 156701.7 | L16: 400000 | M16: =L16-K16 -> 243298.3 | O16: 3 | P16: =I37 -> 18697.082 | Q16: =J37 -> 8802.0391 | R16: =K37 -> 151456.97 | S16: =Q16-Q15 -> 3051.9267
E17: 15 | F17: =F16 -> 763.86447 | G17: =(B$4/B$6)*K17 -> 521.5339 | H17: =F17-G17 -> 242.33057 | I17: =I16+G17 -> 8439.6708 | J17: =J16+H17 -> 3782.1608 | K17: =K16-H16 -> 156460.17 | L17: 400000 | M17: =L17-K17 -> 243539.83 | O17: 4 | P17: =I49 -> 24687.189 | Q17: =J49 -> 11978.306 | R17: =K49 -> 148291.25 | S17: =Q17-Q16 -> 3176.2669
A18: =B4/12 -> 0.0033333333 | E18: 16 | F18: =F17 -> 763.86447 | G18: =(B$4/B$6)*K18 -> 520.72613 | H18: =F18-G18 -> 243.13834 | I18: =I17+G18 -> 8960.3969 | J18: =J17+H18 -> 4025.2991 | K18: =K17-H17 -> 156217.84 | L18: 400000 | M18: =L18-K18 -> 243782.16 | O18: 5 | P18: =I61 -> 30547.889 | Q18: =J61 -> 15283.979 | R18: =K61 -> 144996.56 | S18: =Q18-Q17 -> 3305.673
B19: =319615.33*A18 -> 1065.3844 | E19: 17 | F19: =F18 -> 763.86447 | G19: =(B$4/B$6)*K19 -> 519.91567 | H19: =F19-G19 -> 243.9488 | I19: =I18+G19 -> 9480.3126 | J19: =J18+H19 -> 4269.2479 | K19: =K18-H18 -> 155974.7 | L19: 400000 | M19: =L19-K19 -> 244025.3 | O19: 6 | P19: =I73 -> 36273.912 | Q19: =J73 -> 18724.33 | R19: =K73 -> 141567.64 | S19: =Q19-Q18 -> 3440.3512
B20: =A18*B3 -> 533.33333 | E20: 18 | F20: =F19 -> 763.86447 | G20: =(B$4/B$6)*K20 -> 519.10251 | H20: =F20-G20 -> 244.76197 | I20: =I19+G20 -> 9999.4151 | J20: =J19+H20 -> 4514.0099 | K20: =K19-H19 -> 155730.75 | L20: 400000 | M20: =L20-K20 -> 244269.25 | O20: 7 | P20: =I85 -> 41859.769 | Q20: =J85 -> 22304.847 | R20: =K85 -> 137999.02 | S20: =Q20-Q19 -> 3580.5164
E21: 19 | F21: =F20 -> 763.86447 | G21: =(B$4/B$6)*K21 -> 518.28663 | H21: =F21-G21 -> 245.57784 | I21: =I20+G21 -> 10517.702 | J21: =J20+H21 -> 4759.5877 | K21: =K20-H20 -> 155485.99 | L21: 400000 | M21: =L21-K21 -> 244514.01 | O21: 8 | P21: =I97 -> 47299.751 | Q21: =J97 -> 26031.239 | R21: =K97 -> 134285.01 | S21: =Q21-Q20 -> 3726.3922
E22: 20 | F22: =F21 -> 763.86447 | G22: =(B$4/B$6)*K22 -> 517.46804 | H22: =F22-G22 -> 246.39643 | I22: =I21+G22 -> 11035.17 | J22: =J21+H22 -> 5005.9841 | K22: =K21-H21 -> 155240.41 | L22: 400000 | M22: =L22-K22 -> 244759.59 | O22: 9 | P22: =I109 -> 52587.913 | Q22: =J109 -> 29909.45 | R22: =K109 -> 130419.68 | S22: =Q22-Q21 -> 3878.2111
E23: 21 | F23: =F22 -> 763.86447 | G23: =(B$4/B$6)*K23 -> 516.64672 | H23: =F23-G23 -> 247.21775 | I23: =I22+G23 -> 11551.816 | J23: =J22+H23 -> 5253.2019 | K23: =K22-H22 -> 154994.02 | L23: 400000 | M23: =L23-K23 -> 245005.98 | O23: 10 | P23: =I121 -> 57718.071 | Q23: =J121 -> 33945.665 | R23: =K121 -> 126396.88 | S23: =Q23-Q22 -> 4036.2154
E24: 22 | F24: =F23 -> 763.86447 | G24: =(B$4/B$6)*K24 -> 515.82266 | H24: =F24-G24 -> 248.04181 | I24: =I23+G24 -> 12067.639 | J24: =J23+H24 -> 5501.2437 | K24: =K23-H23 -> 154746.8 | L24: 400000 | M24: =L24-K24 -> 245253.2 | O24: 11 | P24: =I133 -> 62683.788 | Q24: =J133 -> 38146.322 | R24: =K133 -> 122210.17 | S24: =Q24-Q23 -> 4200.6571
A25: 1719 | E25: 23 | F25: =F24 -> 763.86447 | G25: =(B$4/B$6)*K25 -> 514.99585 | H25: =F25-G25 -> 248.86862 | I25: =I24+G25 -> 12582.635 | J25: =J24+H25 -> 5750.1123 | K25: =K24-H24 -> 154498.76 | L25: 400000 | M25: =L25-K25 -> 245501.24 | O25: 12 | P25: =I145 -> 67478.363 | Q25: =J145 -> 42518.121 | R25: =K145 -> 117852.9 | S25: =Q25-Q24 -> 4371.7983
A26: 1528 | E26: 24 | F26: =F25 -> 763.86447 | G26: =(B$4/B$6)*K26 -> 514.16629 | H26: =F26-G26 -> 249.69818 | I26: =I25+G26 -> 13096.801 | J26: =J25+H26 -> 5999.8105 | K26: =K25-H25 -> 154249.89 | L26: 400000 | M26: =L26-K26 -> 245750.11 | O26: 13 | P26: =I157 -> 72094.825 | Q26: =J157 -> 47068.033 | R26: =K157 -> 113318.1 | S26: =Q26-Q25 -> 4549.9121
A27: =A25-A26 -> 191 | B27: e | E27: 25 | F27: =F26 -> 763.86447 | G27: =(B$4/B$6)*K27 -> 513.33396 | H27: =F27-G27 -> 250.53051 | I27: =I26+G27 -> 13610.135 | J27: =J26+H27 -> 6250.341 | K27: =K26-H26 -> 154000.19 | L27: 400000 | M27: =L27-K27 -> 245999.81 | O27: 14 | P27: =I169 -> 76525.916 | Q27: =J169 -> 51803.315 | R27: =K169 -> 108598.55 | S27: =Q27-Q26 -> 4735.2826
E28: 26 | F28: =F27 -> 763.86447 | G28: =(B$4/B$6)*K28 -> 512.49886 | H28: =F28-G28 -> 251.36561 | I28: =I27+G28 -> 14122.634 | J28: =J27+H28 -> 6501.7066 | K28: =K27-H27 -> 153749.66 | L28: 400000 | M28: =L28-K28 -> 246250.34 | O28: 15 | P28: =I181 -> 80764.084 | Q28: =J181 -> 56731.521 | R28: =K181 -> 103686.72 | S28: =Q28-Q27 -> 4928.2053
E29: 27 | F29: =F28 -> 763.86447 | G29: =(B$4/B$6)*K29 -> 511.66098 | H29: =F29-G29 -> 252.20349 | I29: =I28+G29 -> 14634.295 | J29: =J28+H29 -> 6753.9101 | K29: =K28-H28 -> 153498.29 | L29: 400000 | M29: =L29-K29 -> 246501.71 | O29: 16 | P29: =I193 -> 84801.47 | Q29: =J193 -> 61860.509 | R29: =K193 -> 98574.773 | S29: =Q29-Q28 -> 5128.988
E30: 28 | F30: =F29 -> 763.86447 | G30: =(B$4/B$6)*K30 -> 510.8203 | H30: =F30-G30 -> 253.04417 | I30: =I29+G30 -> 15145.115 | J30: =J29+H30 -> 7006.9543 | K30: =K29-H29 -> 153246.09 | L30: 400000 | M30: =L30-K30 -> 246753.91 | O30: 17 | P30: =I205 -> 88629.893 | Q30: =J205 -> 67198.459 | R30: =K205 -> 93254.556 | S30: =Q30-Q29 -> 5337.9509
E31: 29 | F31: =F30 -> 763.86447 | G31: =(B$4/B$6)*K31 -> 509.97682 | H31: =F31-G31 -> 253.88765 | I31: =I30+G31 -> 15655.092 | J31: =J30+H31 -> 7260.842 | K31: =K30-H30 -> 152993.05 | L31: 400000 | M31: =L31-K31 -> 247006.95 | O31: 18 | P31: =I217 -> 92240.839 | Q31: =J217 -> 72753.887 | R31: =K217 -> 87717.586 | S31: =Q31-Q30 -> 5555.4272 | U31: 400000
E32: 30 | F32: =F31 -> 763.86447 | G32: =(B$4/B$6)*K32 -> 509.13053 | H32: =F32-G32 -> 254.73395 | I32: =I31+G32 -> 16164.223 | J32: =J31+H32 -> 7515.5759 | K32: =K31-H31 -> 152739.16 | L32: 400000 | M32: =L32-K32 -> 247260.84 | O32: 19 | P32: =I229 -> 95625.449 | Q32: =J229 -> 78535.651 | R32: =K229 -> 81955.03 | S32: =Q32-Q31 -> 5781.7639 | U32: 290000
E33: 31 | F33: =F32 -> 763.86447 | G33: =(B$4/B$6)*K33 -> 508.28141 | H33: =F33-G33 -> 255.58306 | I33: =I32+G33 -> 16672.504 | J33: =J32+H33 -> 7771.159 | K33: =K32-H32 -> 152484.42 | L33: 400000 | M33: =L33-K33 -> 247515.58 | O33: 20 | P33: =I241 -> 98774.501 | Q33: =J241 -> 84552.972 | R33: =K241 -> 75957.7 | S33: =Q33-Q32 -> 6017.3219 | U33: =U32/U31 -> 0.725
E34: 32 | F34: =F33 -> 763.86447 | G34: =(B$4/B$6)*K34 -> 507.42947 | H34: =F34-G34 -> 256.435 | I34: =I33+G34 -> 17179.934 | J34: =J33+H34 -> 8027.594 | K34: =K33-H33 -> 152228.84 | L34: 400000 | M34: =L34-K34 -> 247771.16 | O34: 21 | P34: =I253 -> 101678.4 | Q34: =J253 -> 90815.449 | R34: =K253 -> 69716.028 | S34: =Q34-Q33 -> 6262.4768
E35: 33 | F35: =F34 -> 763.86447 | G35: =(B$4/B$6)*K35 -> 506.57469 | H35: =F35-G35 -> 257.28979 | I35: =I34+G35 -> 17686.508 | J35: =J34+H35 -> 8284.8837 | K35: =K34-H34 -> 151972.41 | L35: 400000 | M35: =L35-K35 -> 248027.59 | O35: 22 | P35: =I265 -> 104327.15 | Q35: =J265 -> 97333.069 | R35: =K265 -> 63220.062 | S35: =Q35-Q34 -> 6517.6198
E36: 34 | F36: =F35 -> 763.86447 | G36: =(B$4/B$6)*K36 -> 505.71705 | H36: =F36-G36 -> 258.14742 | I36: =I35+G36 -> 18192.225 | J36: =J35+H36 -> 8543.0312 | K36: =K35-H35 -> 151715.12 | L36: 400000 | M36: =L36-K36 -> 248284.88 | O36: 23 | P36: =I277 -> 106710.37 | Q36: =J277 -> 104116.23 | R36: =K277 -> 56459.44 | S36: =Q36-Q35 -> 6783.1577
E37: 35 | F37: =F36 -> 763.86447 | G37: =(B$4/B$6)*K37 -> 504.85656 | H37: =F37-G37 -> 259.00791 | I37: =I36+G37 -> 18697.082 | J37: =J36+H37 -> 8802.0391 | K37: =K36-H36 -> 151456.97 | L37: 400000 | M37: =L37-K37 -> 248543.03 | O37: 24 | P37: =I289 -> 108817.23 | Q37: =J289 -> 111175.74 | R37: =K289 -> 49423.379 | S37: =Q37-Q36 -> 7059.514
E38: 36 | F38: =F37 -> 763.86447 | G38: =(B$4/B$6)*K38 -> 503.9932 | H38: =F38-G38 -> 259.87127 | I38: =I37+G38 -> 19201.075 | J38: =J37+H38 -> 9061.9103 | K38: =K37-H37 -> 151197.96 | L38: 400000 | M38: =L38-K38 -> 248802.04 | O38: 25 | P38: =I301 -> 110636.47 | Q38: =J301 -> 118522.87 | R38: =K301 -> 42100.659 | S38: =Q38-Q37 -> 7347.1295
E39: 37 | F39: =F38 -> 763.86447 | G39: =(B$4/B$6)*K39 -> 503.12697 | H39: =F39-G39 -> 260.73751 | I39: =I38+G39 -> 19704.202 | J39: =J38+H39 -> 9322.6479 | K39: =K38-H38 -> 150938.09 | L39: 400000 | M39: =L39-K39 -> 249061.91 | O39: 26 | P39: =I313 -> 112156.38 | Q39: =J313 -> 126169.33 | R39: =K313 -> 34479.599 | S39: =Q39-Q38 -> 7646.4629
E40: 38 | F40: =F39 -> 763.86447 | G40: =(B$4/B$6)*K40 -> 502.25784 | H40: =F40-G40 -> 261.60663 | I40: =I39+G40 -> 20206.46 | J40: =J39+H40 -> 9584.2545 | K40: =K39-H39 -> 150677.35 | L40: 400000 | M40: =L40-K40 -> 249322.65 | O40: 27 | P40: =I325 -> 113364.76 | Q40: =J325 -> 134127.32 | R40: =K325 -> 26548.046 | S40: =Q40-Q39 -> 7957.9916
E41: 39 | F41: =F40 -> 763.86447 | G41: =(B$4/B$6)*K41 -> 501.38582 | H41: =F41-G41 -> 262.47865 | I41: =I40+G41 -> 20707.846 | J41: =J40+H41 -> 9846.7331 | K41: =K40-H40 -> 150415.75 | L41: 400000 | M41: =L41-K41 -> 249584.25 | O41: 28 | P41: =I337 -> 114248.93 | Q41: =J337 -> 142409.54 | R41: =K337 -> 18293.349 | S41: =Q41-Q40 -> 8282.2125
E42: 40 | F42: =F41 -> 763.86447 | G42: =(B$4/B$6)*K42 -> 500.51089 | H42: =F42-G42 -> 263.35358 | I42: =I41+G42 -> 21208.357 | J42: =J41+H42 -> 10110.087 | K42: =K41-H41 -> 150153.27 | L42: 400000 | M42: =L42-K42 -> 249846.73 | O42: 29 | P42: =I349 -> 114795.66 | Q42: =J349 -> 151029.18 | R42: =K349 -> 9702.3434 | S42: =Q42-Q41 -> 8619.6426
E43: 41 | F43: =F42 -> 763.86447 | G43: =(B$4/B$6)*K43 -> 499.63304 | H43: =F43-G43 -> 264.23143 | I43: =I42+G43 -> 21707.99 | J43: =J42+H43 -> 10374.318 | K43: =K42-H42 -> 149889.91 | L43: 400000 | M43: =L43-K43 -> 250110.09 | O43: 30 | P43: =I361 -> 114991.21 | Q43: =J361 -> 160000 | R43: =K361 -> 761.32672 | S43: =Q43-Q42 -> 8970.8201
E44: 42 | F44: =F43 -> 763.86447 | G44: =(B$4/B$6)*K44 -> 498.75227 | H44: =F44-G44 -> 265.1122 | I44: =I43+G44 -> 22206.742 | J44: =J43+H44 -> 10639.43 | K44: =K43-H43 -> 149625.68 | L44: 400000 | M44: =L44-K44 -> 250374.32
E45: 43 | F45: =F44 -> 763.86447 | G45: =(B$4/B$6)*K45 -> 497.86857 | H45: =F45-G45 -> 265.99591 | I45: =I44+G45 -> 22704.611 | J45: =J44+H45 -> 10905.426 | K45: =K44-H44 -> 149360.57 | L45: 400000 | M45: =L45-K45 -> 250639.43
E46: 44 | F46: =F45 -> 763.86447 | G46: =(B$4/B$6)*K46 -> 496.98191 | H46: =F46-G46 -> 266.88256 | I46: =I45+G46 -> 23201.592 | J46: =J45+H46 -> 11172.309 | K46: =K45-H45 -> 149094.57 | L46: 400000 | M46: =L46-K46 -> 250905.43
E47: 45 | F47: =F46 -> 763.86447 | G47: =(B$4/B$6)*K47 -> 496.0923 | H47: =F47-G47 -> 267.77217 | I47: =I46+G47 -> 23697.685 | J47: =J46+H47 -> 11440.081 | K47: =K46-H46 -> 148827.69 | L47: 400000 | M47: =L47-K47 -> 251172.31
E48: 46 | F48: =F47 -> 763.86447 | G48: =(B$4/B$6)*K48 -> 495.19973 | H48: =F48-G48 -> 268.66474 | I48: =I47+G48 -> 24192.884 | J48: =J47+H48 -> 11708.746 | K48: =K47-H47 -> 148559.92 | L48: 400000 | M48: =L48-K48 -> 251440.08
E49: 47 | F49: =F48 -> 763.86447 | G49: =(B$4/B$6)*K49 -> 494.30418 | H49: =F49-G49 -> 269.56029 | I49: =I48+G49 -> 24687.189 | J49: =J48+H49 -> 11978.306 | K49: =K48-H48 -> 148291.25 | L49: 400000 | M49: =L49-K49 -> 251708.75
E50: 48 | F50: =F49 -> 763.86447 | G50: =(B$4/B$6)*K50 -> 493.40565 | H50: =F50-G50 -> 270.45883 | I50: =I49+G50 -> 25180.594 | J50: =J49+H50 -> 12248.765 | K50: =K49-H49 -> 148021.69 | L50: 400000 | M50: =L50-K50 -> 251978.31
E51: 49 | F51: =F50 -> 763.86447 | G51: =(B$4/B$6)*K51 -> 492.50412 | H51: =F51-G51 -> 271.36036 | I51: =I50+G51 -> 25673.098 | J51: =J50+H51 -> 12520.125 | K51: =K50-H50 -> 147751.24 | L51: 400000 | M51: =L51-K51 -> 252248.76
E52: 50 | F52: =F51 -> 763.86447 | G52: =(B$4/B$6)*K52 -> 491.59958 | H52: =F52-G52 -> 272.26489 | I52: =I51+G52 -> 26164.698 | J52: =J51+H52 -> 12792.39 | K52: =K51-H51 -> 147479.87 | L52: 400000 | M52: =L52-K52 -> 252520.13
E53: 51 | F53: =F52 -> 763.86447 | G53: =(B$4/B$6)*K53 -> 490.69203 | H53: =F53-G53 -> 273.17244 | I53: =I52+G53 -> 26655.39 | J53: =J52+H53 -> 13065.563 | K53: =K52-H52 -> 147207.61 | L53: 400000 | M53: =L53-K53 -> 252792.39
E54: 52 | F54: =F53 -> 763.86447 | G54: =(B$4/B$6)*K54 -> 489.78146 | H54: =F54-G54 -> 274.08301 | I54: =I53+G54 -> 27145.172 | J54: =J53+H54 -> 13339.646 | K54: =K53-H53 -> 146934.44 | L54: 400000 | M54: =L54-K54 -> 253065.56
E55: 53 | F55: =F54 -> 763.86447 | G55: =(B$4/B$6)*K55 -> 488.86785 | H55: =F55-G55 -> 274.99662 | I55: =I54+G55 -> 27634.039 | J55: =J54+H55 -> 13614.642 | K55: =K54-H54 -> 146660.35 | L55: 400000 | M55: =L55-K55 -> 253339.65
... E362: 360 | F362: =F361 -> 763.86447 | G362: =(B$4/B$6)*K362 -> -8.2006106e-13 | H362: =F362-G362 -> 763.86447 | I362: =I361+G362 -> 114991.21 | J362: =J361+H362 -> 160763.86 | K362: =K361-H361 -> -2.4601832e-10 | L362: 400000 | M362: =L362-K362 -> 400000

Sheet Chapter 37
A1: Refi Scenario | G1: First example
B2: Purchase | C2: After Rehab | D2: After Refinance | H2: Time of Purchase | I2: 5 Years Later | J2: Refinance
A3: Property Value | B3: 300000 | C3: 400000 | D3: 400000 | G3: Property Value | H3: 400000 | I3: 450000 | J3: 450000
A4: Down Payment | B4: =B3*0.25 -> 75000 | C4: 75000 | D4: =D3*0.25 -> 100000 | G4: Down Payment | H4: =H3*0.2 -> 80000 | I4: 80000 | J4: =J3*0.2 -> 90000
A5: Interest Rate | B5: 0.04 | C5: 0.04 | D5: 0.04 | G5: Interest Rate | H5: 0.04 | I5: 0.04 | J5: 0.04
A6: Loan Balance | B6: =B3-B4 -> 225000 | C6: =B6 -> 225000 | D6: =D3-D4 -> 300000 | G6: Loan Balance | H6: =H3-H4 -> 320000 | I6: 290000 | J6: 340000
A7: Rehab Costs | B7: 50000 | C7: 50000 | D7: 0 | G7: Equity ($) | H7: =H4 -> 80000 | I7: =I3-I6 -> 160000 | J7: 90000
A8: Total Cash Invested | B8: =SUM(B4:B7) -> 350000.04 | C8: =SUM(C4:C7) -> 350000.04 | D8: =SUM(D4:D7) -> 400000.04 | G8: Equity (%) | H8: =H7/H3 -> 0.2 | I8: =I7/I3 -> 0.35555556 | J8: =J7/J3 -> 0.2
G9: Cash Flow | H9: 8000 | I9: 10000 | J9: 9000
A10: Equity ($) | B10: =B8 -> 350000.04 | C10: =C8+(C3-B3) -> 450000.04 | D10: =D3-D6 -> 100000 | G10: Return on Equity | H10: =H9/SUM(H4:H4) -> 0.1 | I10: =I9/I7 -> 0.0625 | J10: =J9/J7 -> 0.1
A11: Equity (%) | B11: =B10/B3 -> 1.1666668 | C11: =C10/C3 -> 1.1250001 | D11: =D10/D3 -> 0.25 | G11: Cash Out | J11: =I7-J7 -> 70000
A12: Cashflow | B12: 18000 | C12: 24000 | D12: 24000
A13: Return on Equity | B13: =B12/SUM(B4:B7) -> 0.051428566 | C13: =C12/SUM(C4:C7) -> 0.068571421 | D13: =D12/SUM(D4:D7) -> 0.059999994
A14: Cash Out | D14: =C10-D10 -> 350000.04
G16: Selling Scenario 1
H17: Time of Purchase | I17: 5 Years Later | J17: New Purchase
G18: Property Value | H18: 400000 | I18: 450000 | J18: 600000
G19: Down Payment | H19: =H18*0.2 -> 80000 | I19: 80000 | J19: =J18*0.2 -> 120000
G20: Interest Rate | H20: 0.04 | I20: 0.04 | J20: 0.04
G21: Loan Balance | H21: =H18-H19 -> 320000 | I21: 290000 | J21: =J18*0.2 -> 120000
G22: Equity ($) | H22: =H19 -> 80000 | I22: =I18-I21 -> 160000 | J22: =J19 -> 120000
G23: Equity (%) | H23: =H22/H18 -> 0.2 | I23: =I22/I18 -> 0.35555556 | J23: =J22/J18 -> 0.2
B24: =10000/88000 -> 0.11363636 | G24: Cash Flow | H24: 8000 | I24: 10000 | J24: 13500
G25: Return on Equity | H25: =H24/SUM(H19:H19) -> 0.1 | I25: =I24/I22 -> 0.0625 | J25: =J24/J22 -> 0.1125
G26: Cash Out | J26: =I22-J22 -> 40000
G31: Selling Scenario 2
H32: Time of Purchase | I32: 5 Years Later | J32: New Purchase 1 | K32: New Purchase 2
G33: Property Value | H33: 400000 | I33: 450000 | J33: 420000 | K33: 380000
G34: Down Payment | H34: =H33*0.2 -> 80000 | I34: 80000 | J34: =J33*0.2 -> 84000 | K34: =K33*0.2 -> 76000
G35: Interest Rate | H35: 0.04 | I35: 0.04 | J35: 0.04 | K35: 0.04
G36: Loan Balance | H36: =H33-H34 -> 320000 | I36: 290000 | J36: =J33*0.2 -> 84000 | K36: =K33*0.2 -> 76000
G37: Equity ($) | H37: =H34 -> 80000 | I37: =I33-I36 -> 160000 | J37: =J34 -> 84000 | K37: =K34 -> 76000
G38: Equity (%) | H38: =H37/H33 -> 0.2 | I38: =I37/I33 -> 0.35555556 | J38: =J37/J33 -> 0.2 | K38: =K37/K33 -> 0.2
G39: Cash Flow | H39: 8000 | I39: 10000 | J39: 8000 | K39: 7000
G40: Return on Equity | H40: =H39/SUM(H34:H34) -> 0.1 | I40: =I39/I37 -> 0.0625 | J40: =J39/J37 -> 0.095238095 | K40: =K39/K37 -> 0.092105263
G47: Investor Story
H48: Time of Purchase | I48: 8 Years Later | J48: New Purchase 1 | K48: New Purchase 2
G49: Property Value | H49: 467000 | I49: 650000 | J49: 550000 | K49: 740000
G50: Down Payment | H50: =H49*0.2 -> 93400 | I50: =H50 -> 93400 | J50: =J49*0.25 -> 137500 | K50: =K49*0.25 -> 185000
G51: Interest Rate | H51: 0.04 | I51: 0.04 | J51: 0.04 | K51: 0.04
G52: Loan Balance | H52: =H49-H50 -> 373600 | I52: 313500 | J52: =J49*0.2 -> 110000 | K52: =K49*0.2 -> 148000
G53: Rehab Costs | H53: 0 | I53: 0 | J53: 0 | K53: 0
G54: Total Cash Invested | H54: =SUM(H50:H50) -> 93400 | I54: =SUM(I50:I50) -> 93400 | J54: =SUM(J50:J50) -> 137500 | K54: =SUM(K50:K50) -> 185000
G56: Equity ($) | H56: =H54 -> 93400 | I56: =I49-I52 -> 336500 | J56: =J54 -> 137500 | K56: =K54 -> 185000
G57: Equity (%) | H57: =H56/H49 -> 0.2 | I57: =I56/I49 -> 0.51769231 | J57: =J56/J49 -> 0.25 | K57: =K56/K49 -> 0.25
G58: Cashflow | H58: 12000 | I58: 20000 | J58: 17500 | K58: 22000
G59: Return on Equity | H59: =H58/SUM(H50:H50) -> 0.12847966 | I59: =I58/I56 -> 0.059435364 | J59: =J58/J56 -> 0.12727273 | K59: =K58/K56 -> 0.11891892

Sheet Mortgage Calculator_IP
A1: Purchase Price | B1: ='Final Proforma'!F4 -> 400000 | E1: Payment Number | F1: Payment ($) | G1: Interest Paid | H1: Prinicipal Paid | I1: Total Interest Paid | J1: Total Principal Paid | K1: Principal Balance | L1: Sale Price | M1: Profit
A2: Down Payment (%) | B2: ='Final Proforma'!F5 -> 0.25 | E2: 0 | F2: =B8 -> 1432.2459 | G2: =(B$4/B$6)*K2 -> 1000 | H2: =F2-G2 -> 432.24589 | I2: =G2 -> 1000 | J2: =H2 -> 432.24589 | K2: =B3 -> 300000 | L2: 400000 | M2: =L2-K2 -> 100000
A3: Loan Amount (Principal) | B3: =(1-B2)*B1 -> 300000 | E3: 1 | F3: =F2 -> 1432.2459 | G3: =(B$4/B$6)*K3 -> 998.55918 | H3: =F3-G3 -> 433.68671 | I3: =I2+G3 -> 1998.5592 | J3: =J2+H3 -> 865.93259 | K3: =K2-H2 -> 299567.75 | L3: 400000 | M3: =L3-K3 -> 100432.25
A4: Annual Interest Rate | B4: ='Final Proforma'!F7 -> 0.04 | E4: 2 | F4: =F3 -> 1432.2459 | G4: =(B$4/B$6)*K4 -> 997.11356 | H4: =F4-G4 -> 435.13233 | I4: =I3+G4 -> 2995.6727 | J4: =J3+H4 -> 1301.0649 | K4: =K3-H3 -> 299134.07 | L4: 400000 | M4: =L4-K4 -> 100865.93 | O4: Annual | P4: 1 | Q4: 2 | R4: 3 | S4: 4 | T4: 5 | U4: 6 | V4: 7 | W4: 8 | X4: 9 | Y4: 10 | Z4: 11 | AA4: 12 | AB4: 13 | AC4: 14 | AD4: 15 | AE4: 16 | AF4: 17 | AG4: 18 | AH4: 19 | AI4: 20 | AJ4: 21 | AK4: 22 | AL4: 23 | AM4: 24 | AN4: 25 | AO4: 26 | AP4: 27 | AQ4: 28 | AR4: 29 | AS4: 30
A5: Term (Years) | B5: ='Final Proforma'!F8 -> 30 | E5: 3 | F5: =F4 -> 1432.2459 | G5: =(B$4/B$6)*K5 -> 995.66312 | H5: =F5-G5 -> 436.58277 | I5: =I4+G5 -> 3991.3359 | J5: =J4+H5 -> 1737.6477 | K5: =K4-H4 -> 298698.94 | L5: 400000 | M5: =L5-K5 -> 101301.06 | O5: Total Interest Paid | P5: =P14 -> 11903.841 | Q5: =P15 -> 23592.441 | R5: =P16 -> 35057.029 | S5: =P17 -> 46288.479 | T5: =P18 -> 57277.293 | U5: =P19 -> 68013.585 | V5: =P20 -> 78487.067 | W5: =P21 -> 88687.033 | X5: =P22 -> 98602.337 | Y5: =P23 -> 108221.38 | Z5: =P24 -> 117532.1 | AA5: =P25 -> 126521.93 | AB5: =P26 -> 135177.8 | AC5: =P27 -> 143486.09 | AD5: =P28 -> 151432.66 | AE5: =P29 -> 159002.76 | AF5: =P30 -> 166181.05 | AG5: =P31 -> 172951.57 | AH5: =P32 -> 179297.72 | AI5: =P33 -> 185202.19 | AJ5: =P34 -> 190647 | AK5: =P35 -> 195613.41 | AL5: =P36 -> 200081.94 | AM5: =P37 -> 204032.3 | AN5: =P38 -> 207443.38 | AO5: =P39 -> 210293.22 | AP5: =P40 -> 212558.93 | AQ5: =P41 -> 214216.74 | AR5: =P42 -> 215241.86 | AS5: =P43 -> 215608.52
A6: Payments/year | B6: ='Final Proforma'!F9 -> 12 | E6: 4 | F6: =F5 -> 1432.2459 | G6: =(B$4/B$6)*K6 -> 994.20784 | H6: =F6-G6 -> 438.03805 | I6: =I5+G6 -> 4985.5437 | J6: =J5+H6 -> 2175.6857 | K6: =K5-H5 -> 298262.35 | L6: 400000 | M6: =L6-K6 -> 101737.65 | O6: Total Principal Paid | P6: =Q14 -> 5283.1093 | Q6: =Q15 -> 10781.461 | R6: =Q16 -> 16503.823 | S6: =Q17 -> 22459.324 | T6: =Q18 -> 28657.461 | U6: =Q19 -> 35108.119 | V6: =Q20 -> 41821.587 | W6: =Q21 -> 48808.573 | X6: =Q22 -> 56080.218 | Y6: =Q23 -> 63648.122 | Z6: =Q24 -> 71524.354 | AA6: =Q25 -> 79721.476 | AB6: =Q26 -> 88252.561 | AC6: =Q27 -> 97131.216 | AD6: =Q28 -> 106371.6 | AE6: =Q29 -> 115988.45 | AF6: =Q30 -> 125997.11 | AG6: =Q31 -> 136413.54 | AH6: =Q32 -> 147254.34 | AI6: =Q33 -> 158536.82 | AJ6: =Q34 -> 170278.97 | AK6: =Q35 -> 182499.5 | AL6: =Q36 -> 195217.93 | AM6: =Q37 -> 208454.51 | AN6: =Q38 -> 222230.38 | AO6: =Q39 -> 236567.5 | AP6: =Q40 -> 251488.73 | AQ6: =Q41 -> 267017.88 | AR6: =Q42 -> 283179.71 | AS6: =Q43 -> 300000
A7: Total Payments | B7: =B6*B5 -> 360 | E7: 5 | F7: =F6 -> 1432.2459 | G7: =(B$4/B$6)*K7 -> 992.74771 | H7: =F7-G7 -> 439.49817 | I7: =I6+G7 -> 5978.2914 | J7: =J6+H7 -> 2615.1839 | K7: =K6-H6 -> 297824.31 | L7: 400000 | M7: =L7-K7 -> 102175.69 | O7: Principal/Year | P7: =S14 -> 5283.1093 | Q7: =Q6-P6 -> 5498.3513 | R7: =R6-Q6 -> 5722.3626 | S7: =S6-R6 -> 5955.5005 | T7: =T6-S6 -> 6198.1368 | U7: =U6-T6 -> 6450.6585 | V7: =V6-U6 -> 6713.4682 | W7: =W6-V6 -> 6986.9853 | X7: =X6-W6 -> 7271.6459 | ... AS7: =AS6-AR6 -> 16820.288
A8: Payment per Period | B8: =-PMT(B4/B6, B7, B3, 0) -> 1432.2459 | E8: 6 | F8: =F7 -> 1432.2459 | G8: =(B$4/B$6)*K8 -> 991.28272 | H8: =F8-G8 -> 440.96317 | I8: =I7+G8 -> 6969.5741 | J8: =J7+H8 -> 3056.1471 | K8: =K7-H7 -> 297384.82 | L8: 400000 | M8: =L8-K8 -> 102615.18 | O8: Principal Balance | P8: =R14 -> 295165.25 | Q8: =R15 -> 289685.17 | R8: =R16 -> 283981.82 | S8: =R17 -> 278046.1 | T8: =R18 -> 271868.56 | U8: =R19 -> 265439.33 | V8: =R20 -> 258748.16 | W8: =R21 -> 251784.39 | X8: =R22 -> 244536.9 | Y8: =R23 -> 236994.14 | Z8: =R24 -> 229144.08 | AA8: =R25 -> 220974.19 | AB8: =R26 -> 212471.45 | AC8: =R27 -> 203622.29 | AD8: =R28 -> 194412.6 | AE8: =R29 -> 184827.7 | AF8: =R30 -> 174852.29 | AG8: =R31 -> 164470.47 | AH8: =R32 -> 153665.68 | AI8: =R33 -> 142420.69 | AJ8: =R34 -> 130717.55 | AK8: =R35 -> 118537.62 | AL8: =R36 -> 105861.45 | AM8: =R37 -> 92668.836 | AN8: =R38 -> 78938.735 | AO8: =R39 -> 64649.249 | AP8: =R40 -> 49777.586 | AQ8: =R41 -> 34300.03 | AR8: =R42 -> 18191.894 | AS8: =R43 -> 1427.4876
A9: Sum of Payments | B9: =B8*B7 -> 515608.52 | E9: 7 | F9: =F8 -> 1432.2459 | G9: =(B$4/B$6)*K9 -> 989.81284 | H9: =F9-G9 -> 442.43304 | I9: =I8+G9 -> 7959.387 | J9: =J8+H9 -> 3498.5801 | K9: =K8-H8 -> 296943.85 | L9: 400000 | M9: =L9-K9 -> 103056.15
A10: Interest Cost | B10: =B9-B3 -> 215608.52 | E10: 8 | F10: =F9 -> 1432.2459 | G10: =(B$4/B$6)*K10 -> 988.33807 | H10: =F10-G10 -> 443.90782 | I10: =I9+G10 -> 8947.725 | J10: =J9+H10 -> 3942.4879 | K10: =K9-H9 -> 296501.42 | L10: 400000 | M10: =L10-K10 -> 103498.58
E11: 9 | F11: =F10 -> 1432.2459 | G11: =(B$4/B$6)*K11 -> 986.85837 | H11: =F11-G11 -> 445.38751 | I11: =I10+G11 -> 9934.5834 | J11: =J10+H11 -> 4387.8755 | K11: =K10-H10 -> 296057.51 | L11: 400000 | M11: =L11-K11 -> 103942.49
E12: 10 | F12: =F11 -> 1432.2459 | G12: =(B$4/B$6)*K12 -> 985.37375 | H12: =F12-G12 -> 446.87214 | I12: =I11+G12 -> 10919.957 | J12: =J11+H12 -> 4834.7476 | K12: =K11-H11 -> 295612.12 | L12: 400000 | M12: =L12-K12 -> 104387.88
E13: 11 | F13: =F12 -> 1432.2459 | G13: =(B$4/B$6)*K13 -> 983.88417 | H13: =F13-G13 -> 448.36171 | I13: =I12+G13 -> 11903.841 | J13: =J12+H13 -> 5283.1093 | K13: =K12-H12 -> 295165.25 | L13: 400000 | M13: =L13-K13 -> 104834.75 | O13: Year | P13: Total Interest Paid | Q13: Total Principal Paid | R13: Total Principal Paid | S13: Principal/Year
E14: 12 | F14: =F13 -> 1432.2459 | G14: =(B$4/B$6)*K14 -> 982.38964 | H14: =F14-G14 -> 449.85625 | I14: =I13+G14 -> 12886.231 | J14: =J13+H14 -> 5732.9656 | K14: =K13-H13 -> 294716.89 | L14: 400000 | M14: =L14-K14 -> 105283.11 | O14: 1 | P14: =I13 -> 11903.841 | Q14: =J13 -> 5283.1093 | R14: =K13 -> 295165.25 | S14: =Q14 -> 5283.1093
E15: 13 | F15: =F14 -> 1432.2459 | G15: =(B$4/B$6)*K15 -> 980.89011 | H15: =F15-G15 -> 451.35577 | I15: =I14+G15 -> 13867.121 | J15: =J14+H15 -> 6184.3213 | K15: =K14-H14 -> 294267.03 | L15: 400000 | M15: =L15-K15 -> 105732.97 | O15: 2 | P15: =I25 -> 23592.441 | Q15: =J25 -> 10781.461 | R15: =K25 -> 289685.17 | S15: =Q15-Q14 -> 5498.3513
E16: 14 | F16: =F15 -> 1432.2459 | G16: =(B$4/B$6)*K16 -> 979.3856 | H16: =F16-G16 -> 452.86029 | I16: =I15+G16 -> 14846.507 | J16: =J15+H16 -> 6637.1816 | K16: =K15-H15 -> 293815.68 | L16: 400000 | M16: =L16-K16 -> 106184.32 | O16: 3 | P16: =I37 -> 35057.029 | Q16: =J37 -> 16503.823 | R16: =K37 -> 283981.82 | S16: =Q16-Q15 -> 5722.3626
E17: 15 | F17: =F16 -> 1432.2459 | G17: =(B$4/B$6)*K17 -> 977.87606 | H17: =F17-G17 -> 454.36983 | I17: =I16+G17 -> 15824.383 | J17: =J16+H17 -> 7091.5514 | K17: =K16-H16 -> 293362.82 | L17: 400000 | M17: =L17-K17 -> 106637.18 | O17: 4 | P17: =I49 -> 46288.479 | Q17: =J49 -> 22459.324 | R17: =K49 -> 278046.1 | S17: =Q17-Q16 -> 5955.5005
A18: =B4/12 -> 0.0033333333 | E18: 16 | F18: =F17 -> 1432.2459 | G18: =(B$4/B$6)*K18 -> 976.3615 | H18: =F18-G18 -> 455.88439 | I18: =I17+G18 -> 16800.744 | J18: =J17+H18 -> 7547.4358 | K18: =K17-H17 -> 292908.45 | L18: 400000 | M18: =L18-K18 -> 107091.55 | O18: 5 | P18: =I61 -> 57277.293 | Q18: =J61 -> 28657.461 | R18: =K61 -> 271868.56 | S18: =Q18-Q17 -> 6198.1368
B19: =319615.33*A18 -> 1065.3844 | E19: 17 | F19: =F18 -> 1432.2459 | G19: =(B$4/B$6)*K19 -> 974.84188 | H19: =F19-G19 -> 457.40401 | I19: =I18+G19 -> 17775.586 | J19: =J18+H19 -> 8004.8398 | K19: =K18-H18 -> 292452.56 | L19: 400000 | M19: =L19-K19 -> 107547.44 | O19: 6 | P19: =I73 -> 68013.585 | Q19: =J73 -> 35108.119 | R19: =K73 -> 265439.33 | S19: =Q19-Q18 -> 6450.6585
B20: =A18*B3 -> 1000 | E20: 18 | F20: =F19 -> 1432.2459 | G20: =(B$4/B$6)*K20 -> 973.3172 | H20: =F20-G20 -> 458.92869 | I20: =I19+G20 -> 18748.903 | J20: =J19+H20 -> 8463.7685 | K20: =K19-H19 -> 291995.16 | L20: 400000 | M20: =L20-K20 -> 108004.84 | O20: 7 | P20: =I85 -> 78487.067 | Q20: =J85 -> 41821.587 | R20: =K85 -> 258748.16 | S20: =Q20-Q19 -> 6713.4682
E21: 19 | F21: =F20 -> 1432.2459 | G21: =(B$4/B$6)*K21 -> 971.78744 | H21: =F21-G21 -> 460.45845 | I21: =I20+G21 -> 19720.691 | J21: =J20+H21 -> 8924.227 | K21: =K20-H20 -> 291536.23 | L21: 400000 | M21: =L21-K21 -> 108463.77 | O21: 8 | P21: =I97 -> 88687.033 | Q21: =J97 -> 48808.573 | R21: =K97 -> 251784.39 | S21: =Q21-Q20 -> 6986.9853
E22: 20 | F22: =F21 -> 1432.2459 | G22: =(B$4/B$6)*K22 -> 970.25258 | H22: =F22-G22 -> 461.99331 | I22: =I21+G22 -> 20690.943 | J22: =J21+H22 -> 9386.2203 | K22: =K21-H21 -> 291075.77 | L22: 400000 | M22: =L22-K22 -> 108924.23 | O22: 9 | P22: =I109 -> 98602.337 | Q22: =J109 -> 56080.218 | R22: =K109 -> 244536.9 | S22: =Q22-Q21 -> 7271.6459
E23: 21 | F23: =F22 -> 1432.2459 | G23: =(B$4/B$6)*K23 -> 968.7126 | H23: =F23-G23 -> 463.53329 | I23: =I22+G23 -> 21659.656 | J23: =J22+H23 -> 9849.7536 | K23: =K22-H22 -> 290613.78 | L23: 400000 | M23: =L23-K23 -> 109386.22 | O23: 10 | P23: =I121 -> 108221.38 | Q23: =J121 -> 63648.122 | R23: =K121 -> 236994.14 | S23: =Q23-Q22 -> 7567.9039
E24: 22 | F24: =F23 -> 1432.2459 | G24: =(B$4/B$6)*K24 -> 967.16749 | H24: =F24-G24 -> 465.0784 | I24: =I23+G24 -> 22626.823 | J24: =J23+H24 -> 10314.832 | K24: =K23-H23 -> 290150.25 | L24: 400000 | M24: =L24-K24 -> 109849.75 | O24: 11 | P24: =I133 -> 117532.1 | Q24: =J133 -> 71524.354 | R24: =K133 -> 229144.08 | S24: =Q24-Q23 -> 7876.232
E25: 23 | F25: =F24 -> 1432.2459 | G25: =(B$4/B$6)*K25 -> 965.61723 | H25: =F25-G25 -> 466.62866 | I25: =I24+G25 -> 23592.441 | J25: =J24+H25 -> 10781.461 | K25: =K24-H24 -> 289685.17 | L25: 400000 | M25: =L25-K25 -> 110314.83 | O25: 12 | P25: =I145 -> 126521.93 | Q25: =J145 -> 79721.476 | R25: =K145 -> 220974.19 | S25: =Q25-Q24 -> 8197.1219
E26: 24 | F26: =F25 -> 1432.2459 | G26: =(B$4/B$6)*K26 -> 964.0618 | H26: =F26-G26 -> 468.18409 | I26: =I25+G26 -> 24556.502 | J26: =J25+H26 -> 11249.645 | K26: =K25-H25 -> 289218.54 | L26: 400000 | M26: =L26-K26 -> 110781.46 | O26: 13 | P26: =I157 -> 135177.8 | Q26: =J157 -> 88252.561 | R26: =K157 -> 212471.45 | S26: =Q26-Q25 -> 8531.0852
E27: 25 | F27: =F26 -> 1432.2459 | G27: =(B$4/B$6)*K27 -> 962.50118 | H27: =F27-G27 -> 469.7447 | I27: =I26+G27 -> 25519.004 | J27: =J26+H27 -> 11719.389 | K27: =K26-H26 -> 288750.36 | L27: 400000 | M27: =L27-K27 -> 111249.64 | O27: 14 | P27: =I169 -> 143486.09 | Q27: =J169 -> 97131.216 | R27: =K169 -> 203622.29 | S27: =Q27-Q26 -> 8878.6548
E28: 26 | F28: =F27 -> 1432.2459 | G28: =(B$4/B$6)*K28 -> 960.93537 | H28: =F28-G28 -> 471.31052 | I28: =I27+G28 -> 26479.939 | J28: =J27+H28 -> 12190.7 | K28: =K27-H27 -> 288280.61 | L28: 400000 | M28: =L28-K28 -> 111719.39 | O28: 15 | P28: =I181 -> 151432.66 | Q28: =J181 -> 106371.6 | R28: =K181 -> 194412.6 | S28: =Q28-Q27 -> 9240.3849
E29: 27 | F29: =F28 -> 1432.2459 | G29: =(B$4/B$6)*K29 -> 959.36433 | H29: =F29-G29 -> 472.88155 | I29: =I28+G29 -> 27439.303 | J29: =J28+H29 -> 12663.581 | K29: =K28-H28 -> 287809.3 | L29: 400000 | M29: =L29-K29 -> 112190.7 | O29: 16 | P29: =I193 -> 159002.76 | Q29: =J193 -> 115988.45 | R29: =K193 -> 184827.7 | S29: =Q29-Q28 -> 9616.8525
E30: 28 | F30: =F29 -> 1432.2459 | G30: =(B$4/B$6)*K30 -> 957.78806 | H30: =F30-G30 -> 474.45782 | I30: =I29+G30 -> 28397.091 | J30: =J29+H30 -> 13138.039 | K30: =K29-H29 -> 287336.42 | L30: 400000 | M30: =L30-K30 -> 112663.58 | O30: 17 | P30: =I205 -> 166181.05 | Q30: =J205 -> 125997.11 | R30: =K205 -> 174852.29 | S30: =Q30-Q29 -> 10008.658
E31: 29 | F31: =F30 -> 1432.2459 | G31: =(B$4/B$6)*K31 -> 956.20654 | H31: =F31-G31 -> 476.03935 | I31: =I30+G31 -> 29353.298 | J31: =J30+H31 -> 13614.079 | K31: =K30-H30 -> 286861.96 | L31: 400000 | M31: =L31-K31 -> 113138.04 | O31: 18 | P31: =I217 -> 172951.57 | Q31: =J217 -> 136413.54 | R31: =K217 -> 164470.47 | S31: =Q31-Q30 -> 10416.426
E32: 30 | F32: =F31 -> 1432.2459 | G32: =(B$4/B$6)*K32 -> 954.61974 | H32: =F32-G32 -> 477.62615 | I32: =I31+G32 -> 30307.918 | J32: =J31+H32 -> 14091.705 | K32: =K31-H31 -> 286385.92 | L32: 400000 | M32: =L32-K32 -> 113614.08 | O32: 19 | P32: =I229 -> 179297.72 | Q32: =J229 -> 147254.34 | R32: =K229 -> 153665.68 | S32: =Q32-Q31 -> 10840.807
E33: 31 | F33: =F32 -> 1432.2459 | G33: =(B$4/B$6)*K33 -> 953.02765 | H33: =F33-G33 -> 479.21824 | I33: =I32+G33 -> 31260.945 | J33: =J32+H33 -> 14570.923 | K33: =K32-H32 -> 285908.3 | L33: 400000 | M33: =L33-K33 -> 114091.7 | O33: 20 | P33: =I241 -> 185202.19 | Q33: =J241 -> 158536.82 | R33: =K241 -> 142420.69 | S33: =Q33-Q32 -> 11282.479
E34: 32 | F34: =F33 -> 1432.2459 | G34: =(B$4/B$6)*K34 -> 951.43026 | H34: =F34-G34 -> 480.81563 | I34: =I33+G34 -> 32212.376 | J34: =J33+H34 -> 15051.739 | K34: =K33-H33 -> 285429.08 | L34: 400000 | M34: =L34-K34 -> 114570.92 | O34: 21 | P34: =I253 -> 190647 | Q34: =J253 -> 170278.97 | R34: =K253 -> 130717.55 | S34: =Q34-Q33 -> 11742.144
E35: 33 | F35: =F34 -> 1432.2459 | G35: =(B$4/B$6)*K35 -> 949.82754 | H35: =F35-G35 -> 482.41835 | I35: =I34+G35 -> 33162.203 | J35: =J34+H35 -> 15534.157 | K35: =K34-H34 -> 284948.26 | L35: 400000 | M35: =L35-K35 -> 115051.74 | O35: 22 | P35: =I265 -> 195613.41 | Q35: =J265 -> 182499.5 | R35: =K265 -> 118537.62 | S35: =Q35-Q34 -> 12220.537
E36: 34 | F36: =F35 -> 1432.2459 | G36: =(B$4/B$6)*K36 -> 948.21948 | H36: =F36-G36 -> 484.02641 | I36: =I35+G36 -> 34110.423 | J36: =J35+H36 -> 16018.183 | K36: =K35-H35 -> 284465.84 | L36: 400000 | M36: =L36-K36 -> 115534.16 | O36: 23 | P36: =I277 -> 200081.94 | Q36: =J277 -> 195217.93 | R36: =K277 -> 105861.45 | S36: =Q36-Q35 -> 12718.421
E37: 35 | F37: =F36 -> 1432.2459 | G37: =(B$4/B$6)*K37 -> 946.60606 | H37: =F37-G37 -> 485.63983 | I37: =I36+G37 -> 35057.029 | J37: =J36+H37 -> 16503.823 | K37: =K36-H36 -> 283981.82 | L37: 400000 | M37: =L37-K37 -> 116018.18 | O37: 24 | P37: =I289 -> 204032.3 | Q37: =J289 -> 208454.51 | R37: =K289 -> 92668.836 | S37: =Q37-Q36 -> 13236.589
E38: 36 | F38: =F37 -> 1432.2459 | G38: =(B$4/B$6)*K38 -> 944.98726 | H38: =F38-G38 -> 487.25863 | I38: =I37+G38 -> 36002.016 | J38: =J37+H38 -> 16991.082 | K38: =K37-H37 -> 283496.18 | L38: 400000 | M38: =L38-K38 -> 116503.82 | O38: 25 | P38: =I301 -> 207443.38 | Q38: =J301 -> 222230.38 | R38: =K301 -> 78938.735 | S38: =Q38-Q37 -> 13775.868
E39: 37 | F39: =F38 -> 1432.2459 | G39: =(B$4/B$6)*K39 -> 943.36306 | H39: =F39-G39 -> 488.88283 | I39: =I38+G39 -> 36945.379 | J39: =J38+H39 -> 17479.965 | K39: =K38-H38 -> 283008.92 | L39: 400000 | M39: =L39-K39 -> 116991.08 | O39: 26 | P39: =I313 -> 210293.22 | Q39: =J313 -> 236567.5 | R39: =K313 -> 64649.249 | S39: =Q39-Q38 -> 14337.118
E40: 38 | F40: =F39 -> 1432.2459 | G40: =(B$4/B$6)*K40 -> 941.73345 | H40: =F40-G40 -> 490.51244 | I40: =I39+G40 -> 37887.112 | J40: =J39+H40 -> 17970.477 | K40: =K39-H39 -> 282520.04 | L40: 400000 | M40: =L40-K40 -> 117479.96 | O40: 27 | P40: =I325 -> 212558.93 | Q40: =J325 -> 251488.73 | R40: =K325 -> 49777.586 | S40: =Q40-Q39 -> 14921.234
E41: 39 | F41: =F40 -> 1432.2459 | G41: =(B$4/B$6)*K41 -> 940.09841 | H41: =F41-G41 -> 492.14748 | I41: =I40+G41 -> 38827.211 | J41: =J40+H41 -> 18462.625 | K41: =K40-H40 -> 282029.52 | L41: 400000 | M41: =L41-K41 -> 117970.48 | O41: 28 | P41: =I337 -> 214216.74 | Q41: =J337 -> 267017.88 | R41: =K337 -> 34300.03 | S41: =Q41-Q40 -> 15529.148
E42: 40 | F42: =F41 -> 1432.2459 | G42: =(B$4/B$6)*K42 -> 938.45792 | H42: =F42-G42 -> 493.78797 | I42: =I41+G42 -> 39765.669 | J42: =J41+H42 -> 18956.413 | K42: =K41-H41 -> 281537.38 | L42: 400000 | M42: =L42-K42 -> 118462.62 | O42: 29 | P42: =I349 -> 215241.86 | Q42: =J349 -> 283179.71 | R42: =K349 -> 18191.894 | S42: =Q42-Q41 -> 16161.83
E43: 41 | F43: =F42 -> 1432.2459 | G43: =(B$4/B$6)*K43 -> 936.81196 | H43: =F43-G43 -> 495.43393 | I43: =I42+G43 -> 40702.481 | J43: =J42+H43 -> 19451.847 | K43: =K42-H42 -> 281043.59 | L43: 400000 | M43: =L43-K43 -> 118956.41 | O43: 30 | P43: =I361 -> 215608.52 | Q43: =J361 -> 300000 | R43: =K361 -> 1427.4876 | S43: =Q43-Q42 -> 16820.288
E44: 42 | F44: =F43 -> 1432.2459 | G44: =(B$4/B$6)*K44 -> 935.16051 | H44: =F44-G44 -> 497.08537 | I44: =I43+G44 -> 41637.641 | J44: =J43+H44 -> 19948.932 | K44: =K43-H43 -> 280548.15 | L44: 400000 | M44: =L44-K44 -> 119451.85
E45: 43 | F45: =F44 -> 1432.2459 | G45: =(B$4/B$6)*K45 -> 933.50356 | H45: =F45-G45 -> 498.74233 | I45: =I44+G45 -> 42571.145 | J45: =J44+H45 -> 20447.674 | K45: =K44-H44 -> 280051.07 | L45: 400000 | M45: =L45-K45 -> 119948.93
E46: 44 | F46: =F45 -> 1432.2459 | G46: =(B$4/B$6)*K46 -> 931.84109 | H46: =F46-G46 -> 500.4048 | I46: =I45+G46 -> 43502.986 | J46: =J45+H46 -> 20948.079 | K46: =K45-H45 -> 279552.33 | L46: 400000 | M46: =L46-K46 -> 120447.67
E47: 45 | F47: =F46 -> 1432.2459 | G47: =(B$4/B$6)*K47 -> 930.17307 | H47: =F47-G47 -> 502.07282 | I47: =I46+G47 -> 44433.159 | J47: =J46+H47 -> 21450.152 | K47: =K46-H46 -> 279051.92 | L47: 400000 | M47: =L47-K47 -> 120948.08
E48: 46 | F48: =F47 -> 1432.2459 | G48: =(B$4/B$6)*K48 -> 928.49949 | H48: =F48-G48 -> 503.74639 | I48: =I47+G48 -> 45361.658 | J48: =J47+H48 -> 21953.898 | K48: =K47-H47 -> 278549.85 | L48: 400000 | M48: =L48-K48 -> 121450.15
E49: 47 | F49: =F48 -> 1432.2459 | G49: =(B$4/B$6)*K49 -> 926.82034 | H49: =F49-G49 -> 505.42555 | I49: =I48+G49 -> 46288.479 | J49: =J48+H49 -> 22459.324 | K49: =K48-H48 -> 278046.1 | L49: 400000 | M49: =L49-K49 -> 121953.9
E50: 48 | F50: =F49 -> 1432.2459 | G50: =(B$4/B$6)*K50 -> 925.13559 | H50: =F50-G50 -> 507.1103 | I50: =I49+G50 -> 47213.614 | J50: =J49+H50 -> 22966.434 | K50: =K49-H49 -> 277540.68 | L50: 400000 | M50: =L50-K50 -> 122459.32
E51: 49 | F51: =F50 -> 1432.2459 | G51: =(B$4/B$6)*K51 -> 923.44522 | H51: =F51-G51 -> 508.80067 | I51: =I50+G51 -> 48137.06 | J51: =J50+H51 -> 23475.235 | K51: =K50-H50 -> 277033.57 | L51: 400000 | M51: =L51-K51 -> 122966.43
E52: 50 | F52: =F51 -> 1432.2459 | G52: =(B$4/B$6)*K52 -> 921.74922 | H52: =F52-G52 -> 510.49667 | I52: =I51+G52 -> 49058.809 | J52: =J51+H52 -> 23985.731 | K52: =K51-H51 -> 276524.77 | L52: 400000 | M52: =L52-K52 -> 123475.23
E53: 51 | F53: =F52 -> 1432.2459 | G53: =(B$4/B$6)*K53 -> 920.04756 | H53: =F53-G53 -> 512.19832 | I53: =I52+G53 -> 49978.856 | J53: =J52+H53 -> 24497.93 | K53: =K52-H52 -> 276014.27 | L53: 400000 | M53: =L53-K53 -> 123985.73
E54: 52 | F54: =F53 -> 1432.2459 | G54: =(B$4/B$6)*K54 -> 918.34023 | H54: =F54-G54 -> 513.90565 | I54: =I53+G54 -> 50897.197 | J54: =J53+H54 -> 25011.835 | K54: =K53-H53 -> 275502.07 | L54: 400000 | M54: =L54-K54 -> 124497.93
E55: 53 | F55: =F54 -> 1432.2459 | G55: =(B$4/B$6)*K55 -> 916.62722 | H55: =F55-G55 -> 515.61867 | I55: =I54+G55 -> 51813.824 | J55: =J54+H55 -> 25527.454 | K55: =K54-H54 -> 274988.16 | L55: 400000 | M55: =L55-K55 -> 125011.84
... E362: 360 | F362: =F361 -> 1432.2459 | G362: =(B$4/B$6)*K362 -> 1.6446696e-12 | H362: =F362-G362 -> 1432.2459 | I362: =I361+G362 -> 215608.52 | J362: =J361+H362 -> 301432.25 | K362: =K361-H361 -> 4.9340088e-10 | L362: 400000 | M362: =L362-K362 -> 400000

Sheet RE Metrics
B2: GRM | G2: GRM
C4: Purchase Price | D4: Annual Rent | E4: GSM | H4: NOI | I4: TDS | J4: DSCR
B5: Property 1 | C5: 300000 | D5: 24000 | E5: =C5/D5 -> 12.5 | G5: Property 1 | H5: 25000 | I5: 21000 | J5: =H5/I5 -> 1.1904762
B6: Property 2 | C6: 350000 | D6: 36000 | E6: =C6/D6 -> 9.7222222 | G6: Property 2 | H6: 22000 | I6: 15000 | J6: =H6/I6 -> 1.4666667
B8: RTP
C9: Purchase Price | D9: Monthly Rent | E9: RTP
B10: Property 1 | C10: 300000 | D10: =D5/12 -> 2000 | E10: =D10/C10 -> 0.0066666667
B11: Property 2 | C11: 350000 | D11: =D6/12 -> 3000 | E11: =D11/C11 -> 0.0085714286
B17: Neighborhood | C17: Median Purchase Price | D17: Median Rent | E17: RTP
B18: North Lake | C18: 465000 | D18: 2400 | E18: =D18/C18 -> 0.0051612903
B19: South Lake | C19: 425000 | D19: 2600 | E19: =D19/C19 -> 0.0061176471
B20: East Lake | C20: 400000 | D20: 2825 | E20: =D20/C20 -> 0.0070625
B21: West Lake | C21: 365000 | D21: 2100 | E21: =D21/C21 -> 0.0057534247

Sheet AAGR
C5: Year-End Balance | D5: Annual ROI | G5: Year-End Balance | H5: Annual ROI
B6: Year 0 | C6: 100 | F6: Year 0 | G6: 100
B7: Year 1 | C7: 180 | D7: =(C7-C6)/C6 -> 0.8 | F7: Year 1 | G7: 180 | H7: =(G7-G6)/G6 -> 0.8
B8: Year 2 | C8: 135 | D8: =(C8-C7)/C7 -> -0.25 | F8: Year 2 | G8: 135 | H8: =(G8-G7)/G7 -> -0.25
B9: Year 3 | C9: 170 | D9: =(C9-C8)/C8 -> 0.25925926 | F9: Year 3 | G9: 170 | H9: =(G9-G8)/G8 -> 0.25925926
B10: Year 4 | C10: 220 | D10: =(C10-C9)/C9 -> 0.29411765 | F10: Year 4 | G10: 100 | H10: =(G10-G9)/G9 -> -0.41176471
B11: Simple ROI | C11: =C10/C6-1 -> 1.2 | F11: Simple ROI | G11: =G10/G6-1 -> 0
B12: AAGR | D12: =SUM(D7:D10)/COUNT(D7:D10) -> 0.27584423 | F12: AAGR | H12: =SUM(H7:H10)/COUNT(H7:H10) -> 0.099373638
C14: Year-End Balance | D14: Annual ROI
B15: Year 0 | C15: 200
B16: Year 1 | C16: 250 | D16: =(C16-C15)/C15 -> 0.25
B17: Year 2 | C17: 350 | D17: =(C17-C16)/C16 -> 0.4
B18: Simple ROI | C18: =C17/C15-1 -> 0.75
B19: AAGR | D19: =SUM(D15:D17)/COUNT(D15:D17) -> 0.325

Sheet Fin Statements
B2: PERSONAL FINANCIAL STATEMENT
B3: As of December 31, 2022
B5: Assets | E5: Liabilities | H5: Liabilities
C7: Estimated Value | F7: Estimated Value | I7: Estimated Value
B8: Cash or Cash Equivalent | E8: Loans | H8: Loans | M8: NO LOAN | N8: LOAN @ 4.5% | O8: LOAN @ 7%
B9: Cash On Hand | C9: 200 | E9: Mortgage - Personal Residence | F9: =145000-6800 -> 138200 | H9: Mortgage - Personal Residence | I9: =145000-6800 -> 138200 | L9: Purchase Price | M9: 100000 | N9: 100000 | O9: 100000
B10: Bank - Checking Account | C10: 20000 | E10: School Loan | F10: 26300 | H10: School Loan | I10: 26300 | L10: Loan Amount | M10: 0 | N10: 80000 | O10: 80000
B11: Money Owed From Bill Jones | C11: 5000 | E11: Money Owed to Bob Smith | F11: 3200 | H11: Money Owed to Bob Smith | I11: 3200 | L11: Down Payment (DP) | M11: 100000 | N11: 20000 | O11: 20000
L12: Interest Rate | M12: N/A | N12: 0.045 | O12: 0.07
B13: Retirement Accounts | E13: Revolving Debt | H13: Revolving Debt | L13: Cash Flow | M13: 7200 | N13: 2340 | O13: 816
B14: Self-Directed IRA | C14: 54500 | E14: Credit Cards | F14: 6800 | H14: Credit Cards | I14: 6800 | L14: ROI (Cash Flow / DP) | M14: 0.072 | N14: =N13/N11 -> 0.117 | O14: =O13/O11 -> 0.0408
B16: Investments | E16: Other | H16: Other
B17: Stocks | C17: 3200 | E17: Estimated Taxes Owed on April 15 | F17: 18000 | H17: Estimated Taxes Owed on April 15 | I17: 18000 | M17: NO LOAN | N17: LOAN @ 4.5% | O17: LOAN @ 7%
B18: Bonds | C18: 800 | L18: Cap Rate | M18: 0.072 | N18: N/A | O18: N/A
H19: Liabilities Total | I19: =SUM(I9:I18) -> 192500 | L19: Loan Constant | M19: N/A | N19: 0.061 | O19: =6384/80000 -> 0.0798
B20: Business Interests | L20: Leverage | M20: N/A | N20: =M18-N19 -> 0.011 | O20: =M18-O19 -> -0.0078
B21: Value of ABC Properties, LLC | C21: 65000
B23: Real/Personal Property Owned
B24: Personal Residence | C24: 185000 | M24: NO LOAN | N24: LOAN @ 4.5% | O24: LOAN @ 7%
B25: 2012 Honda Civic | C25: 7000 | L25: Purchase Price | M25: 100000 | N25: 100000 | O25: 100000
B26: Jewelry | C26: 2000 | L26: Loan Amount | M26: 0 | N26: 80000 | O26: 80000
B27: Furniture and Household Goods | C27: 5000 | H27: Ana | L27: Down Payment (DP) | M27: 100000 | N27: 20000 | O27: 20000
L28: Interest Rate | M28: N/A | N28: 0.045 | O28: 0.07
B29: Assets Total | C29: =SUM(C9:C28) -> 347700 | E29: Assets Total | F29: =SUM(F9:F28) -> 192500 | L29: Cash Flow | M29: 7200 | N29: 2340 | O29: 816
L30: Cap Rate | M30: 0.072 | N30: N/A | O30: N/A
E31: Estimated Net Worth: | F31: =C29-F29 -> 155200 | L31: Loan Constant | M31: N/A | N31: 0.061 | O31: 0.08
L32: Leverage | M32: N/A | N32: =M30-N31 -> 0.011 | O32: =M30-O31 -> -0.008
G35: PROFIT & LOSS STATEMENT - Catherine Corp
B36: BALANCE SHEET | G36: For the Fiscal Year 2022(Jan 1 - Dec 31, 2022)
B37: FOR YEAR ENDING DECEMBER 31, 2022 | G37: INCOME
G38: Gross Potential Rent | H38: 120000
B39: ASSETS | G39: Rent Loss | H39: -12000
B40: Investement in 123 Main Street | G40: Other Income | H40: 3000
B41: Land | C41: 75462 | G41: GROSS OPERATING INCOME: | H41: 111000
B42: Buildings / Improvements | C42: =281559-7021 -> 274538 | G42: EXPENSES
B43: Furniture & Fixtures | C43: 8254 | G43: Property Taxes | H43: 5250
B44: Accumulated Depreciation | C44: =-27115+7021 -> -20094 | G44: Insurance | H44: 2810
C45: =SUM(C41:C44) -> 338160 | G45: Property Management | H45: 8640
G46: Turnover | H46: 4800
B47: Other Assets | G47: Repairs & Maintenance | H47: 10000
B48: Cash in Operating Account | C48: 16581 | G48: Utilities | H48: 400
B49: Replacement Reserves | C49: 14000 | G49: Lawn Care | H49: 3600
B50: Rents Receivable | C50: 2220 | G50: Snow Removal | H50: 0
B51: Tenant Security Deposits | C51: 8450 | G51: Dumpster/Trash Removal | H51: 0
C52: =SUM(C48:C51) -> 41251 | G52: Grounds Cleanup | H52: 3000
B53: TOTAL ASSETS | C53: =C45+C52 -> 379411 | G53: Office Costs | H53: 0
G54: Legal | H54: 0
B55: LIABILITIES & OWNER EQUITY | G55: Accounting | H55: 1500
B56: Liabilities | G56: OPERATING EXPENSES: | H56: 40000
B57: Mortgage Principal Balance | C57: 276841 | G57: NET OPERATING INCOME: | H57: 71000
B58: Accounts Payable | C58: 16875 | G58: DEBT SERVICE: | H58: -40000
B59: Taxes Payable | C59: 12254 | G59: CAPITAL EXPENSES: | H59: -5000
B60: Tenant Security Deposits | C60: 8450 | G60: CASH FLOW | H60: 31000
B61: TOTAL LIABILITIES | C61: =SUM(C57:C60) -> 314420
B63: Owner Equity
B64: Initial Contributions | C64: 40000
B65: Retained Earnings | C65: =C53-C61-C64 -> 24991
B66: TOTAL OWNER EQUITY | C66: =SUM(C62:C65) -> 64991 | G66: EXPENSES
G67: Property Taxes | H67: -
B68: TOTAL LIABILITIES & OWNERS EQUITY | C68: =C61+C66 -> 379411 | G68: Insurance | H68: -
G69: Property Management | H69: -
G70: Turnover | H70: -
G71: Repairs & Maintenance | H71: -
B72: PROFIT & LOSS STATEMENT - GREAT FLIPS, LLC | G72: Utilities | H72: -
B73: For the Fiscal Year 2022(Jan 1 - Dec 31, 2022) | G73: Lawn Care | H73: -
G74: Snow Removal | H74: -
B75: INCOME | G75: Dumpster/Trash Removal | H75: -
B76: Revenue Source #1 | C76: 0 | G76: Grounds Cleanup | H76: -
B77: Revenue Source #2 | C77: 0 | G77: Office Costs | H77: -
B78: … | G78: Legal | H78: -
B79: TOTAL INCOME: | C79: 0 | G79: Accounting | H79: -
B81: Cost of Goods Sold (COGS) #1 | C81: 0
B82: Cost of Goods Sold (COGS) #2 | C82: 0 | G82: INCOME
B83: … | G83: Gross Potential Rent | H83: -
B84: TOTAL COGS: | C84: 0 | G84: Rent Loss | H84: -
G85: Other Income | H85: -
B86: GROSS PROFIT: | C86: 0 | G86: GROSS OPERATING INCOME: | H86: -
B88: EXPENSES
B89: Expense Source #1 | C89: 0
B90: Expense Source #2 | C90: 0
B91: …
B92: TOTAL OPERATING EXPENSES: | C92: 0
B94: OPERATING INCOME: | C94: 0
B97: PROFIT & LOSS STATEMENT
B98: For the Fiscal Year 2022(Jan 1 - Dec 31, 2022)
B100: INCOME
B101: … | C101: 0
B103: EXPENSES
B104: …
B106: PROFITABLITY: | C106: 0
B111: PROFIT & LOSS STATEMENT - GREAT FLIPS, LLC | G111: PROFIT & LOSS STATEMENT - RENTAL CORP, LLC
B112: For the Fiscal Year 2022(Jan 1 - Dec 31, 2022) | G112: For the Fiscal Year 2022(Jan 1 - Dec 31, 2022)
B114: INCOME | G114: INCOME
B115: Revenue from Sale of Properties | C115: 375000 | G115: Rental Income | H115: 30000
B116: Revenue from Commissions | C116: 25000 | G116: Other Income | H116: 200
B117: … | G117: …
B118: TOTAL INCOME | C118: =C115+C116 -> 400000 | G118: GROSS INCOME | H118: =H115+H116 -> 30200
B120: Property Purchase Costs | C120: 120000 | G120: OPERATING EXPENSES
B121: Rehab Labor | C121: 75000 | G121: Taxes | H121: 1250
B122: Rehab Materials | C122: 30000 | G122: Insurance | H122: 865
...

Sheet Example PFS
B2: PERSONAL FINANCIAL STATEMENT: John Robinson
B3: As of December 31, 2021
B5: Assets | E5: Liabilities | I5: LIQUID ASSETS: John Robinson | M5: Month 0 | N5: Month 1 | O5: Month 2 | P5: Month 3 | Q5: Month 4 | R5: Month 5 | S5: Month 6 | T5: Month 7 | U5: Month 8 | V5: Month 9 | W5: Month 10 | X5: Month 11 | Y5: Month 12
I6: As of December 31, 2021 | L6: Invement | M6: 0 | N6: 20000 | O6: 0
C7: Estimated Value | F7: Estimated Value | I7: Cash or Cash Equivalent | L7: Liquid Assets | M7: 24200 | N7: =M7-N6 -> 4200 | O7: =N7+N8 -> 3500 | P7: =O7+O8 -> 2800 | Q7: =P7+P8 -> 2100 | R7: =Q7+Q8 -> 1400 | S7: =R7+R8 -> 700 | T7: =S7+S8 -> 0 | U7: =T7+T8 -> -700 | V7: =U7+U8 -> -1400 | ... Y7: =X7+X8 -> -3500
B8: Cash or Cash Equivalent | E8: Loans | I8: Cash On Hand | J8: =C9 -> 200 | L8: Savings Rate | M8: -1000 | N8: -700 | O8: -700 | P8: -700 | Q8: -700 | R8: -700 | S8: -700 | T8: -700 | U8: -700 | V8: -700 | W8: -700 | X8: -700 | Y8: -700
B9: Cash On Hand | C9: 200 | E9: Mortgage - Personal Residence | F9: 138200 | I9: Bank - Checking Account | J9: =C10 -> 20000
B10: Bank - Checking Account | C10: 20000 | E10: School Loan | F10: 26300
B11: Money Owed From Bill Jones | C11: 5000 | E11: Car Loan | F11: 3200 | I11: Investments
I12: Stocks | J12: =C17 -> 3200
B13: Retirement Accounts | E13: Revolving Debt | I13: Bonds | J13: =C18 -> 800
B14: Self-Directed IRA | C14: 54500 | E14: Credit Cards | F14: 6800
I15: Total Liquid Assets | J15: =SUM(J8:J13) -> 24200
B16: Investments | E16: Other
B17: Stocks | C17: 3200 | E17: Estimated Taxes Owed on April 15 | F17: 18000
B18: Bonds | C18: 800
B20: Business Interests
B21: ABC Properties LLC | C21: 65000
B23: Real/Personal Property Owned
B24: Personal Residence | C24: 185000
B25: 2013 Honda CRV | C25: 7000
B26: Furniture and Household Goods | C26: 5000
B27: Jewelry | C27: 2000
B29: Assets Total | C29: =SUM(C9:C28) -> 347700 | E29: Liabilities Total | F29: =SUM(F9:F28) -> 192500
E31: Estimated Net Worth: | F31: =C29-F29 -> 155200
B37: SAVINGS RATE: John Robinson | I37: INVESTABLE ASSETS: John Robinson
B38: As of December 31, 2021 | I38: As of December 31, 2021
B40: Income | E40: Expenses | I40: Monthly Income | J40: =F53 -> 4000
I41: Desired reserve (months) | J41: 3
C42: Estimated Value | F42: Estimated Value | I42: Required reserve | J42: =J41*F53 -> 12000
B43: Cash or Cash Equivalent | E43: Expenses
B44: Monthly Salary | C44: 4500 | E44: Tax Witholdings | F44: =C44*0.3 -> 1350 | I44: Liquid Assets | J44: =J15 -> 24200
B45: Ridesharing Income | C45: 500 | E45: Mortgage Payments | F45: 1150 | I45: Required Reserves | J45: =-J42 -> -12000
E46: Student Loan Payments | F46: 200
E47: Food & Groceries | F47: 400 | I47: Investable Assets | J47: =J44-J42 -> 12200
E48: Entertainment | F48: 300
E49: Car loan payments | F49: 200
E50: Gas | F50: 100
E51: Misc. | F51: 300
B53: Total Income | C53: =SUM(C44:C50) -> 5000 | E53: Total Expenses | F53: =SUM(F44:F51) -> 4000
E55: Savings Rate | F55: =C53-F53 -> 1000
B59: Rideshare Income May | C59: 350 | E59: May Expenses | F59: 3100
B60: Rideshare Income June | C60: 475 | E60: June Expenses | F60: 3450
B61: Rideshare Income July | C61: 675 | E61: July Expenses | F61: 3050
B62: Average Income | C62: =AVERAGE(C59:C61) -> 500 | E62: Average Expenses | F62: =AVERAGE(F59:F61) -> 3200
B67: Starting Liquid Assets | C67: 24200
B68: Investment Amount | C68: 20000
B69: Ending Liquid Assets | C69: =C67-C68 -> 4200
B72: Monthly Expenses | C72: 3200
B73: Liquid Assets | C73: 24200

Sheet TVM Examples
A2: Initial Investment | B2: 50000 | C2: 75000
A3: Discount Rate | B3: 0.1 | C3: 0.1
A5: Year | B5: Expected Cashflow | C5: Expected Cashflow
A6: 1 | B6: 6000 | C6: 7500
A7: 2 | B7: =B6*1.05 -> 6300 | C7: =C6*1.03 -> 7725
A8: 3 | B8: =B7*1.05 -> 6615 | C8: =C7*1.03 -> 7956.75
A9: 4 | B9: =B8*1.05 -> 6945.75 | C9: =C8*1.03 -> 8195.4525
A10: 5 | B10: =B9*1.05 -> 7293.0375 | C10: =C9*1.03 -> 8441.3161
A11: 6 | B11: =B10*1.05 -> 7657.6894 | C11: =C10*1.03 -> 8694.5556
A12: 7 | B12: =B11*1.05 -> 8040.5738 | C12: =C11*1.03 -> 8955.3922
A13: 8 | B13: =B12*1.05 -> 8442.6025 | C13: =C12*1.03 -> 9224.054
A14: 9 | B14: =B13*1.05 -> 8864.7327 | C14: =C13*1.03 -> 9500.7756
A15: 10 | B15: =B14*1.05 -> 9307.9693 | C15: =C14*1.03 -> 9785.7989
A16: 11 | B16: =B15*1.05 -> 9773.3678 | C16: =C15*1.03 -> 10079.373
A17: 12 | B17: =B16*1.05 -> 10262.036 | C17: =C16*1.03 -> 10381.754
A18: 13 | B18: =B17*1.05 -> 10775.138 | C18: =C17*1.03 -> 10693.207
... A20: 15 | B20: =B19*1.05 -> 11879.59 | C20: =C19*1.03 -> 11344.423
A21: Total Cashflow | B21: =SUM(B6:B20) -> 129471.38 | C21: =SUM(C6:C20) -> 139491.85
A23: PV | B23: =B21/(1+B3)^15 -> 30994.419 | C23: =C21/(1+C3)^15 -> 33393.241
A24: NPV | B24: =NPV(B3, B6:B20)-B2 -> 10278.535 | C24: =NPV(C3, C6:C20)-C2 -> -7817.6799
A25: IRR

Sheet Js Images
B2: PERSONAL FINANCIAL STATEMENT
B3: As of December 31, 2019
B5: Assets | E5: Liabilities | H5: Liabilities
C7: Estimated Value | F7: Estimated Value | I7: Estimated Value
B8: Cash or Cash Equivalent | E8: Loans | H8: Loans | M8: NO LOAN | N8: LOAN @ 4.5% | O8: LOAN @ 7%
B9: Cash On Hand | C9: 200 | E9: Mortgage - Personal Residence | F9: =145000-6800 -> 138200 | H9: Mortgage - Personal Residence | I9: =145000-6800 -> 138200 | L9: Purchase Price | M9: 100000 | N9: 100000 | O9: 100000
B10: Bank - Checking Account | C10: 20000 | E10: School Loan | F10: 26300 | H10: School Loan | I10: 26300 | L10: Loan Amount | M10: 0 | N10: 80000 | O10: 80000
B11: Money Owed From Bill Jones | C11: 5000 | E11: Money Owed to Bob Smith | F11: 3200 | H11: Money Owed to Bob Smith | I11: 3200 | L11: Down Payment (DP) | M11: 100000 | N11: 20000 | O11: 20000
L12: Interest Rate | M12: N/A | N12: 0.045 | O12: 0.07
B13: Retirement Accounts | E13: Revolving Debt | H13: Revolving Debt | L13: Cash Flow | M13: 7200 | N13: 2340 | O13: 816
B14: Self-Directed IRA | C14: 54500 | E14: Credit Cards | F14: 6800 | H14: Credit Cards | I14: 6800 | L14: ROI (Cash Flow / DP) | M14: 0.072 | N14: =N13/N11 -> 0.117 | O14: =O13/O11 -> 0.0408
B16: Investments | E16: Other | H16: Other
B17: Stocks | C17: 3200 | E17: Estimated Taxes Owed on April 15 | F17: 18000 | H17: Estimated Taxes Owed on April 15 | I17: 18000 | M17: NO LOAN | N17: LOAN @ 4.5% | O17: LOAN @ 7%
B18: Bonds | C18: 800 | L18: Cap Rate | M18: 0.072 | N18: N/A | O18: N/A
H19: Liabilities Total | I19: =SUM(I9:I18) -> 192500 | L19: Loan Constant | M19: N/A | N19: 0.061 | O19: =6384/80000 -> 0.0798
B20: Business Interests | L20: Leverage | M20: N/A | N20: =M18-N19 -> 0.011 | O20: =M18-O19 -> -0.0078
B21: Value of ABC Properties, LLC | C21: 65000
B23: Real/Personal Property Owned
B24: Personal Residence | C24: 185000 | M24: NO LOAN | N24: LOAN @ 4.5% | O24: LOAN @ 7%
B25: 2012 Honda Civic | C25: 7000 | L25: Purchase Price | M25: 100000 | N25: 100000 | O25: 100000
B26: Jewelry | C26: 2000 | L26: Loan Amount | M26: 0 | N26: 80000 | O26: 80000
B27: Furniture and Household Goods | C27: 5000 | H27: Ana | L27: Down Payment (DP) | M27: 100000 | N27: 20000 | O27: 20000
L28: Interest Rate | M28: N/A | N28: 0.045 | O28: 0.07
B29: Assets Total | C29: =SUM(C9:C28) -> 347700 | E29: Assets Total | F29: =SUM(F9:F28) -> 192500 | L29: Cash Flow | M29: 7200 | N29: 2340 | O29: 816
L30: Cap Rate | M30: 0.072 | N30: N/A | O30: N/A
E31: Estimated Net Worth: | F31: =C29-F29 -> 155200 | L31: Loan Constant | M31: N/A | N31: 0.061 | O31: 0.08
L32: Leverage | M32: N/A | N32: =M30-N31 -> 0.011 | O32: =M30-O31 -> -0.008
B36: BALANCE SHEET
B37: FOR YEAR ENDING DECEMBER 31, 2018
B39: ASSETS
B40: Investement in 123 Main Street
B41: Land | C41: 75462
B42: Buildings / Improvements | C42: =281559-7021 -> 274538
B43: Furniture & Fixtures | C43: 8254
B44: Accumulated Depreciation | C44: =-27115+7021 -> -20094
C45: =SUM(C41:C44) -> 338160
B47: Other Assets
B48: Cash in Operating Account | C48: 16581
B49: Replacement Reserves | C49: 14000
B50: Rents Receivable | C50: 2220
B51: Tenant Security Deposits | C51: 8450
C52: =SUM(C48:C51) -> 41251
B53: TOTAL ASSETS | C53: =C45+C52 -> 379411
B55: LIABILITIES & OWNER EQUITY
B56: Liabilities
B57: Mortgage Principal Balance | C57: 276841
B58: Accounts Payable | C58: 16875
B59: Taxes Payable | C59: 12254
B60: Tenant Security Deposits | C60: 8450
B61: TOTAL LIABILITIES | C61: =SUM(C57:C60) -> 314420
B63: Owner Equity
B64: Initial Contributions | C64: 40000
B65: Retained Earnings | C65: =C53-C61-C64 -> 24991
B66: TOTAL OWNER EQUITY | C66: =SUM(C62:C65) -> 64991
B68: TOTAL LIABILITIES & OWNERS EQUITY | C68: =C61+C66 -> 379411
B72: PROFIT & LOSS STATEMENT - AWESOME FLIPS, LLC
B73: For the Fiscal Year 2018 (Jan 1 - Dec 31, 2018)
B75: INCOME
B76: Revenue Source #1 | C76: 0
B77: Revenue Source #2 | C77: 0
B78: …
B79: TOTAL INCOME: | C79: 0
B81: Cost of Goods Sold (COGS) #1 | C81: 0
B82: Cost of Goods Sold (COGS) #2 | C82: 0
B83: …
B84: TOTAL COGS: | C84: 0
B86: GROSS PROFIT: | C86: 0
B88: EXPENSES
B89: Expense Source #1 | C89: 0
B90: Expense Source #2 | C90: 0
B91: …
B92: TOTAL OPERATING EXPENSES: | C92: 0
B94: OPERATING INCOME: | C94: 0
B97: PROFIT & LOSS STATEMENT
B98: For the Fiscal Year 2018 (Jan 1 - Dec 31, 2018)
B100: INCOME
B101: … | C101: 0
B103: EXPENSES
B104: …
B106: PROFITABLITY: | C106: 0
B111: PROFIT & LOSS STATEMENT - AWESOME FLIPS, LLC
B112: For the Fiscal Year 2018 (Jan 1 - Dec 31, 2018)
B114: INCOME
B115: Revenue from Sale of Properties | C115: 375000
B116: Revenue from Commissions | C116: 25000
B117: …
B118: TOTAL INCOME | C118: =C115+C116 -> 400000
B120: Property Purchase Costs | C120: 120000
B121: Rehab Labor | C121: 75000
B122: Rehab Materials | C122: 30000
B123: Closing Costs | C123: 6000
B124: TOTAL COGS | C124: =SUM(C120:C123) -> 231000
B126: GROSS PROFIT | C126: =C118-C124 -> 169000
B128: EXPENSES
B129: Rent | C129: 7200
B130: Owner Salary | C130: 50000
B131: Insurance | C131: 2500
B132: Office Supplies | C132: 300
B133: Tools | C133: 2200
B134: Utilities | C134: 1800
...

Sheet IRR Final
B2: Purchase Price | C2: 480000 | G2: Purchas Price | H2: 480000
B3: Financing | C3: 0.8 | G3: Financing | H3: 0.8
B4: Down Payment | C4: =(1-C3)*C2 -> 96000 | G4: Down Payment | H4: =(1-H3)*H2 -> 96000
B5: Rehab Costs | C5: 120000 | G5: Rehab Costs | H5: 10000
B6: Total Initial Investment | C6: =SUM(C4:C5) -> 216000 | G6: Total Initial Investment | H6: =SUM(H4:H5) -> 106000
B8: Rehab Timeframe | C8: 6 Months | G8: Rehab Timeframe | H8: N/A
B9: Current Rent | C9: 2200 | G9: Current Rent | H9: =C9 -> 2200
B10: Post-Rehab Rent | C10: 3600 | G10: Post-Rehab Rent | H10: =H9 -> 2200
B11: Rent Inflation | C11: 0.03 | G11: Rent Inflation | H11: 0.01
B12: Property Apprecition | C12: 0.03 | G12: Property Appreciation | H12: 0.01
B13: Annual Expenses | C13: 7500 | G13: Annual Expenses | H13: 10000
B14: Sale Price | C14: =C2*(1+C12)^B27 -> 645079.86 | G14: Sale Price | H14: =H2*(1+H12)^G27 -> 530218.62
B16: Year | C16: Cashflows | G16: Year | H16: Cashflows
A17: 44562 | B17: 0 | C17: =-C6+(C10*6)-C13 -> -201900 | F17: 44562 | G17: 0 | H17: =-H6+(H10*6)-H13 -> -102800
A18: 44927 | B18: 1 | C18: =((C$10*12)*((1+$C$11)^B18))-C$13 -> 36996 | F18: 44927 | G18: 1 | H18: =((H$10*12)*((1+$C$11)^G18))-H$13 -> 17192
A19: 45292 | B19: 2 | C19: =((C$10*12)*((1+$C$11)^B19))-C$13 -> 38330.88 | F19: 45292 | G19: 2 | H19: =((H$10*12)*((1+$C$11)^G19))-H$13 -> 18007.76
A20: 45658 | B20: 3 | C20: =((C$10*12)*((1+$C$11)^B20))-C$13 -> 39705.806 | F20: 45658 | G20: 3 | H20: =((H$10*12)*((1+$C$11)^G20))-H$13 -> 18847.993
A21: 46023 | B21: 4 | C21: =((C$10*12)*((1+$C$11)^B21))-C$13 -> 41121.981 | F21: 46023 | G21: 4 | H21: =((H$10*12)*((1+$C$11)^G21))-H$13 -> 19713.433
A22: 46388 | B22: 5 | C22: =((C$10*12)*((1+$C$11)^B22))-C$13 -> 42580.64 | F22: 46388 | G22: 5 | H22: =((H$10*12)*((1+$C$11)^G22))-H$13 -> 20604.836
A23: 46753 | B23: 6 | C23: =((C$10*12)*((1+$C$11)^B23))-C$13 -> 44083.059 | F23: 46753 | G23: 6 | H23: =((H$10*12)*((1+$C$11)^G23))-H$13 -> 21522.981
A24: 47119 | B24: 7 | C24: =((C$10*12)*((1+$C$11)^B24))-C$13 -> 45630.551 | F24: 47119 | G24: 7 | H24: =((H$10*12)*((1+$C$11)^G24))-H$13 -> 22468.67
A25: 47484 | B25: 8 | C25: =((C$10*12)*((1+$C$11)^B25))-C$13 -> 47224.468 | F25: 47484 | G25: 8 | H25: =((H$10*12)*((1+$C$11)^G25))-H$13 -> 23442.73
A26: 47849 | B26: 9 | C26: =((C$10*12)*((1+$C$11)^B26))-C$13 -> 48866.202 | F26: 47849 | G26: 9 | H26: =((H$10*12)*((1+$C$11)^G26))-H$13 -> 24446.012
A27: 48214 | B27: 10 | C27: =C14 -> 645079.86 | F27: 48214 | G27: 10 | H27: =H14 -> 530218.62
B28: IRR | C28: =XIRR(C17:C27, A17:A27) -> 0.25847262 | G28: IRR | H28: =XIRR(H17:H27, F17:F27) -> 0.28689176

Sheet J example
B2: Month | C2: Cashflows
A3: 39661 | B3: 0 | C3: -63500
A4: 39692 | B4: 1 | C4: -17000
A5: 39722 | B5: 2 | C5: -17000
A6: 39753 | B6: 3 | C6: 0
A7: 39783 | B7: 4 | C7: 0
A8: 39814 | B8: 5 | C8: 0
A9: 39845 | B9: 6 | C9: 0
A10: 39873 | B10: 7 | C10: 0
A11: 39904 | B11: 8 | C11: 0
A12: 39934 | B12: 9 | C12: 1000
A13: 39965 | B13: 10 | C13: 1000
A14: 39995 | B14: 11 | C14: 1000
A15: 40026 | B15: 12 | C15: =1000-1400 -> -400
A16: 40057 | B16: 13 | C16: 1000
A17: 40087 | B17: 14 | C17: 1000
A18: 40118 | B18: 15 | C18: 1000
A19: 40148 | B19: 16 | C19: 1000
A20: 40179 | B20: 17 | C20: 1000
A21: 40210 | B21: 18 | C21: 1000
A22: 40238 | B22: 19 | C22: 1000
A23: 40269 | B23: 20 | C23: 1000
A24: 40299 | B24: 21 | C24: 1000
A25: 40330 | B25: 22 | C25: 1000
A26: 40360 | B26: 23 | C26: 1000
A27: 40391 | B27: 24 | C27: =66320+100-2300-1200 -> 62920
A28: 40422 | B28: 25 | C28: 1000
A29: 40452 | B29: 26 | C29: 1000
A30: 40483 | B30: 27 | C30: 1000
A31: 40513 | B31: 28 | C31: 1000
A32: 40544 | B32: 29 | C32: 1000
A33: 40575 | B33: 30 | C33: 1000
A34: 40603 | B34: 31 | C34: 1000
A35: 40634 | B35: 32 | C35: 1000
A36: 40664 | B36: 33 | C36: 1000
A37: 40695 | B37: 34 | C37: 1000
A38: 40725 | B38: 35 | C38: 50000
B39: IRR | C39: =XIRR(C3:C38, A3:A38) -> 0.1621164
