Workbook

Sheet START HERE Instructions
A2: *Please make a COPY of this Google Sheet in order to edit
B51: Questions? A team member from REI Nation is a phone call away!

Sheet Summary
B3: PORTFOLIO OF
B4: INVESTMENT SUMMARY
B8: REVENUE
C10: ='Input sheet'!B3 -> Example Property 1 | D10: ='Input sheet'!B4 -> 14920
C11: ='Input sheet'!D3 -> Example Property 2 | D11: ='Input sheet'!D4 -> 14945
C12: ='Input sheet'!F3 -> 0 | D12: ='Input sheet'!F4 -> 0
C13: ='Input sheet'!H3 -> 0 | D13: ='Input sheet'!H4 -> 0
C14: ='Input sheet'!J3 -> 0 | D14: ='Input sheet'!J4 -> 0
C15: ='Input sheet'!L3 -> 0 | D15: ='Input sheet'!L4 -> 0
C16: ='Input sheet'!N3 -> 0 | D16: ='Input sheet'!N4 -> 0
C17: ='Input sheet'!P3 -> 0 | D17: ='Input sheet'!P4 -> 0
C18: ='Input sheet'!R3 -> 0 | D18: ='Input sheet'!R4 -> 0
C19: ='Input sheet'!T3 -> 0 | D19: ='Input sheet'!T4 -> 0
C20: ='Input sheet'!V3 -> 0 | D20: ='Input sheet'!V4 -> 0
C21: ='Input sheet'!X3 -> 0 | D21: ='Input sheet'!X4 -> 0
C22: ='Input sheet'!Z3 -> 0 | D22: ='Input sheet'!Z4 -> 0
C23: ='Input sheet'!AB3 -> 0 | D23: ='Input sheet'!AB4 -> 0
C24: ='Input sheet'!AD3 -> 0 | D24: ='Input sheet'!AD4 -> 0
C25: ='Input sheet'!AF3 -> 0 | D25: ='Input sheet'!AF4 -> 0
B27: TOTAL REVENUE | E27: =SUM(D10:D25) -> 29865
B29: EXPENSES
C31: Management Fees & Maintenance Improvements | D31: ='Input sheet'!AH5 -> 9030.67
B33: TOTAL EXPENSES | E33: =D31 -> 9030.67
B35: NET OPERATING INCOME | E35: =E27-E33 -> 20834.33
B38: PORTFOLIO INVESTMENT DETAILS
C40: Initial Investment at Purchase | D40: ='Input sheet'!AH8 -> 211000
C41: Additional Capital Contributions | D41: ='Input sheet'!AH9 -> 1021.23
C42: Total Investment | D42: =D40+D41 -> 212021.23
C43: Property Appreciation | D43: ='Input sheet'!AH12-'Input sheet'!AH8 -> 19000
C44: Average Months Owned | D44: ='Input sheet'!AH13 -> 16
B47: TOTAL RETURN ON INVESTMENT | E47: =(E35+D43)/D42 -> 0.18787897
B49: ANNUALIZED RETURN ON INVESTMENT | E49: =E47/D44*12 -> 0.14090923
B51: This analysis is performed based on information available to us. Factors such as leverage, insurance deductibles, and other costs incurred by choice of the investor can affect these results.

Sheet Input sheet
A1: Portfolio Analysis of [YOUR NAME]
A2: As of [DATE]
B3: Example Property 1 | D3: Example Property 2 | AH3: Totals
A4: Gross Revenue | B4: 14920 | D4: 14945 | AH4: =SUM(A4:AF4) -> 29865
A5: Repairs/Mgmt Fees | B5: 1942 | D5: 7088.67 | AH5: =SUM(A5:AF5) -> 9030.67
A6: Net Income | B6: =B4-B5 -> 12978 | D6: =D4-D5 -> 7856.33 | F6: =F4-F5 -> 0 | H6: =H4-H5 -> 0 | J6: =J4-J5 -> 0 | L6: =L4-L5 -> 0 | N6: =N4-N5 -> 0 | P6: =P4-P5 -> 0 | R6: =R4-R5 -> 0 | T6: =T4-T5 -> 0 | V6: =V4-V5 -> 0 | X6: =X4-X5 -> 0 | Z6: =Z4-Z5 -> 0 | AB6: =AB4-AB5 -> 0 | AD6: =AD4-AD5 -> 0 | AF6: =AF4-AF5 -> 0 | AH6: =AH4-AH5 -> 20834.33
A8: Purchase Price | B8: 109000 | D8: 102000 | AH8: =SUM(A8:AF8) -> 211000
A9: Capital Contributions | B9: 0 | D9: =1021.23 -> 1021.23 | F9: 0 | H9: 0 | J9: 0 | L9: 0 | N9: 0 | P9: 0 | R9: 0 | T9: 0 | V9: 0 | X9: 0 | Z9: 0 | AB9: 0 | AD9: 0 | AF9: 0 | AH9: =SUM(A9:AF9) -> 1021.23
A10: TOTAL INVESTMENT | B10: =SUM(B8:B9) -> 109000 | D10: =SUM(D8:D9) -> 103021.23 | F10: =SUM(F8:F9) -> 0 | H10: =SUM(H8:H9) -> 0 | J10: =SUM(J8:J9) -> 0 | L10: =SUM(L8:L9) -> 0 | N10: =SUM(N8:N9) -> 0 | P10: =SUM(P8:P9) -> 0 | R10: =SUM(R8:R9) -> 0 | T10: =SUM(T8:T9) -> 0 | V10: =SUM(V8:V9) -> 0 | X10: =SUM(X8:X9) -> 0 | Z10: =SUM(Z8:Z9) -> 0 | AB10: =SUM(AB8:AB9) -> 0 | AD10: =SUM(AD8:AD9) -> 0 | AF10: =SUM(AF8:AF9) -> 0 | AH10: =SUM(AH8:AH9) -> 212021.23
A12: Current Property Value | B12: 120000 | D12: 110000 | AH12: =SUM(A12:AF12) -> 230000
A13: Months owned | B13: 16 | D13: 17 | AH13: =ROUNDDOWN(AVERAGE(B13:AF13),0) -> 16
A15: Annualized ROI (actual) | B15: =((B6+(B12-B8))/B10)/B13*12 -> 0.16498624 | D15: =((D6+(D12-D8))/D10)/D13*12 -> 0.10864463 | F15: =((F6+(F12-F8))/F10)/F13*12 -> #DIV/0! | H15: =((H6+(H12-H8))/H10)/H13*12 -> #DIV/0! | J15: =((J6+(J12-J8))/J10)/J13*12 -> #DIV/0! | L15: =((L6+(L12-L8))/L10)/L13*12 -> #DIV/0! | N15: =((N6+(N12-N8))/N10)/N13*12 -> #DIV/0! | P15: =((P6+(P12-P8))/P10)/P13*12 -> #DIV/0! | R15: =((R6+(R12-R8))/R10)/R13*12 -> #DIV/0! | T15: =((T6+(T12-T8))/T10)/T13*12 -> #DIV/0! | V15: =((V6+(V12-V8))/V10)/V13*12 -> #DIV/0! | X15: =((X6+(X12-X8))/X10)/X13*12 -> #DIV/0! | Z15: =((Z6+(Z12-Z8))/Z10)/Z13*12 -> #DIV/0! | AB15: =((AB6+(AB12-AB8))/AB10)/AB13*12 -> #DIV/0! | AD15: =((AD6+(AD12-AD8))/AD10)/AD13*12 -> #DIV/0! | AF15: =((AF6+(AF12-AF8))/AF10)/AF13*12 -> #DIV/0! | AH15: =((AH6+(AH12-AH8))/AH10)/AH13*12 -> 0.14090923
