Workbook
Name If: #REF!
Name If: #REF!

Sheet Calculators
A3: Year | C3: Annual ROI | G3: Year | I3: Annual ROI | S3: IRR | T3: =XIRR(T4:T10,R4:R10) -> 0.21632629
A4: 0 | B4: 100000 | G4: 0 | H4: 100000 | M4: Present Value=Future Value /( 1+i)^n | R4: 45292 | S4: Initial Investment | T4: -8500000
A5: =A4+1 -> 1 | B5: 110000 | C5: =(B5/B4)-1 -> 0.1 | G5: =G4+1 -> 1 | H5: 110000 | I5: =(H5/H4)-1 -> 0.1 | M5: interest | N5: 0.08 | R5: =R4+365 -> 45657 | S5: Year 1 Cashflow | T5: =-$T$4*$U$5 -> 1360000 | U5: 0.16 | V5: Cash On Cash
A6: =A5+1 -> 2 | B6: 105000 | C6: =(B6/B5)-1 -> -0.045454545 | G6: =G5+1 -> 2 | H6: 105000 | I6: =(H6/H5)-1 -> -0.045454545 | M6: time (yrs) | N6: 5 | O6: =N6*12 -> 60 | R6: =R5+365 -> 46022 | S6: Year 2 Cashflow | T6: =-$T$4*$U$5 -> 1360000
A7: =A6+1 -> 3 | B7: 120000 | C7: =(B7/B6)-1 -> 0.14285714 | G7: =G6+1 -> 3 | H7: 120000 | I7: =(H7/H6)-1 -> 0.14285714 | R7: =R6+365 -> 46387 | S7: Year 3 Cashflow | T7: =-$T$4*$U$5 -> 1360000
A8: =A7+1 -> 4 | B8: =B7+5000 -> 125000 | C8: =(B8/B7)-1 -> 0.041666667 | G8: =G7+1 -> 4 | H8: =H7+5000 -> 125000 | I8: =(H8/H7)-1 -> 0.041666667 | R8: =R7+365 -> 46752 | S8: Year 4 Cashflow | T8: =-$T$4*$U$5 -> 1360000
A9: =A8+1 -> 5 | B9: =B8+5000 -> 130000 | C9: =(B9/B8)-1 -> 0.04 | G9: =G8+1 -> 5 | H9: =H8+5000 -> 130000 | I9: =(H9/H8)-1 -> 0.04 | R9: =R8+365 -> 47117 | S9: Year 5 Cashflow | T9: =-$T$4*$U$5 -> 1360000
A10: =A9+1 -> 6 | B10: =B9+5000 -> 135000 | C10: =(B10/B9)-1 -> 0.038461538 | R10: =R9+365 -> 47482 | S10: 6 | T10: =-T4*(1+U10)^S10 -> 14813534 | U10: 0.097 | V10: Assumed Appreciation
A11: =A10+1 -> 7 | B11: =B10+5000 -> 140000 | C11: =(B11/B10)-1 -> 0.037037037 | I11: =(H9-H4)/H4 -> 0.3 | J11: ROI
A12: =A11+1 -> 8 | B12: =B11+5000 -> 145000 | C12: =(B12/B11)-1 -> 0.035714286 | I12: =SUM(I5:I9)/COUNT(I5:I9) -> 0.055813853 | J12: AAR
A13: =A12+1 -> 9 | B13: =B12+5000 -> 150000 | C13: =(B13/B12)-1 -> 0.034482759 | I13: =(H9/H4)^(1/COUNT(I4:I9))-1 -> 0.053873952 | J13: CAGR | M13: 0.105 | N13: projected Cash On Cash Return
A14: =A13+1 -> 10 | B14: =B13+5000 -> 155000 | C14: =(B14/B13)-1 -> 0.033333333 | I14: =H9/H4 -> 1.3 | J14: Equity Multiplier | M14: 8500000 | N14: initial investment
M15: =O15*12 -> 60 | N15: hold period | O15: 5
C16: =(B14-B4)/B4 -> 0.55 | D16: ROI
C17: =SUM(C5:C14)/COUNT(C5:C14) -> 0.045809822 | D17: AAR | M17: Future | N17: =M14*(1+M13/12)^(M15) -> 14336125 | O17: =N17/M14 -> 1.686603 | P17: Equity Multiple
C18: =(B14/B4)^(1/COUNT(C4:C14))-1 -> 0.044800014 | D18: CAGR | M18: CAGR | N18: =(N17/M14)^(1/(O15*4))-1 -> 0.026480357
C19: =B14/B4 -> 1.55 | D19: Equity Multiplier

Sheet STR Calculator
A1: https://www.zillow.com/homedetails/2615-Whippoorwill-Hill-Way-Sevierville-TN-37862/42506804_zpid/ | H1: Heloc Down Payment | I1: 0.0825
A2: 2615 Whippor Will Way - 1bd / 3bath - 1617 sqft | B2: 1617 | C2: sqft | D2: =A3/B2 -> 370.43908 | E2: per sqft | H2: Heloc Loan Terms | I2: 20 | J2: yrs
A3: =B5 -> 599000 | B3: asking price | H3: HELOC Amount | I3: =SUM(B7+B6-C5-C4) -> 64800
C4: 5000 | D4: earnest money | H4: HELOC P&I Payment | I4: =-PMT($I$1/12,$I$2*12,I3) -> 552.13854 | J4: =I4*12 -> 6625.6625 | L4: IRR | M4: =IRR(M5:M11) -> 0.036890162
A5: Purchase Price | B5: 599000 | C5: 50000 | D5: cash | H5: HELOC Principle Payment | I5: =-PPMT($I$1/12,1,$I$2*12,I3) -> 106.63854 | J5: =I5*12 -> 1279.6625 | L5: Initial Investment | M5: =-B5 -> -599000
A6: Closing Costs (4%) | B6: 0 | C6: $B$5*0.04 | H6: HELOC Interest Only Payment | I6: =-IPMT($I$1/12,1,$I$2*12,I3) -> 445.5 | J6: =I6*12 -> 5346 | L6: Year 1 Cashflow | M6: ='STR 10 Year'!B39 -> 10780.097
A7: Down Payment | B7: =B5*C7 -> 119800 | C7: 0.2 | D7: downpayment | L7: Year 2 Cashflow | M7: ='STR 10 Year'!C39 -> 11854.097
A8: Total Loan Amount | B8: =B5-B7 -> 479200 | H8: Conventional Loan Interest Rate | I8: =IF(C7=0.1,0.08062,0.0775) -> 0.0775 | J8: IF(C7=0.1,0.08062,0.0775) | L8: Year 3 Cashflow | M8: ='STR 10 Year'!D39 -> 12632.732
H9: Loan Term | I9: 30 | J9: yrs | L9: Year 4 Cashflow | M9: ='STR 10 Year'!E39 -> 13415.93
B10: Nightly | C10: Monthly | D10: Annually | H10: Monthly Payment on Purchase Price | I10: =-PMT($I$8/12,$I$9*12,$B$8) -> 3433.0475 | L10: Year 5 Cashflow | M10: ='STR 10 Year'!F39 -> 14203.613
A11: Average Rent | B11: 250 | C11: =B11*30.5 -> 7625 | D11: =C11*12 -> 91500 | H11: Monthly Interest Payment on Purchase Price | I11: =-IPMT($I$8/12,1,$I$9*12,$B$8) -> 3094.8333 | L11: 6 | M11: =$B$5*(1+0.02)^L11 -> 674571.29 | N11: assumes 2%/yr appreciation
A12: Occupancy Rate | B12: 1 | C12: =-C11*(1-B12) -> 0 | D12: =C12*12 -> 0 | H12: Monthly Principle Payment on Purchase Price | I12: =-PPMT($I$8/12,1,$I$9*12,$B$8) -> 338.21415 | J12: =I12*12 -> 4058.5698
A13: Additional Income (Laundry/Storage etc) | C13: 0 | D13: =C13*12 -> 0
H14: Financials
A15: Calculated Gross Revenue | C15: =SUM(C11:C13) -> 7625 | D15: =C15*12 -> 91500 | H15: Cash On Cash Return (CoC) | I15: =C44/SUM($B$6:$B$7) -> 0.087980775 | L15: Desired Return | M15: 0.08
H16: ROE (Return on Equity) | I16: =C44/B7 -> 0.087980775
A17: Estimated Expenses | B17: Monthly | C17: Annually | H17: AAR | I17: ='STR 10 Year'!L50 -> 0.20744104 | L17: IRR | O17: NPV
A18: Management Fees | B18: =C11*D18 -> 0 | C18: =B18*12 -> 0 | D18: 0 | E18: =IF(D18=0,1,0) -> 1 | H18: Mortgage Pay Down yr 1 | I18: =PPMT($I$8/12,1,$I$9*12,$B$8)*12 -> -4058.5698 | L18: 45536 | M18: 0 | N18: =-SUM('STR Calculator'!B6:B7) -> -119800 | O18: =N18 -> -119800
A19: Subscriptions (AirDnA/Pricelabs/Guesty) | B19: 50 | C19: =B19*12 -> 600 | H19: Tax Savings at 25% | I19: =C44*0.25 -> 2635.0242 | L19: 45901 | M19: 1 | N19: ='STR 10 Year'!B39 -> 10780.097 | O19: =N19/(1+$M$15)^M19 -> 9981.5712
A20: AirBnB / VRBO Fee (3% of nightly) | B20: 0 | C20: =B20*12 -> 0 | L20: 46266 | M20: 2 | N20: ='STR 10 Year'!C39 -> 11854.097 | O20: =N20/(1+$M$15)^M20 -> 10162.977
A21: Property Taxes / Year | B21: 200 | C21: =B21*12 -> 2400 | D21: =C21/B5 -> 0.0040066778 | H21: Rules of Thumb | L21: 46631 | M21: 3 | N21: ='STR 10 Year'!D39 -> 12632.732 | O21: =N21/(1+$M$15)^M21 -> 10028.27
A22: Insurance / Year | B22: 250 | C22: =B22*12 -> 3000 | D22: =C22/B5 -> 0.0050083472 | H22: 50% Rule | L22: 46997 | M22: 4 | N22: ='STR 10 Year'!E39 -> 13415.93 | O22: =N22/(1+$M$15)^M22 -> 9861.1088
A23: Cleaners (per stay, average 6/month) - Trash included. Soap/Toilet Paper/Detergent etc. | B23: =D23*6 -> 1500 | C23: =B23*12 -> 18000 | D23: 250 | H23: 2% Rule | I23: =$C$11/$B$5 -> 0.012729549 | L23: 47362 | M23: 5 | N23: ='STR 10 Year'!F39 -> 14203.613 | O23: =N23/(1+$M$15)^M23 -> 9666.7401
A24: Handyman | B24: 250 | C24: =B24*12 -> 3000 | H24: DSCR | I24: =B40/(B42+B41+B43) -> 1.2264614 | L24: 47727 | M24: 6 | N24: ='STR 10 Year'!G39 -> 14995.698 | O24: =N24/(1+$M$15)^M24 -> 9449.8331
A25: HOA / year | B25: 0 | C25: =B25*12 -> 0 | D25: =C25/B5 -> 0 | L25: 48092 | M25: 7 | N25: ='STR 10 Year'!H39 -> 15792.095 | O25: =N25/(1+$M$15)^M25 -> 9214.5359
A26: Electricity | B26: 250 | C26: =B26*12 -> 3000 | L26: 48458 | M26: 8 | N26: ='STR 10 Year'!I39 -> 16592.711 | O26: =N26/(1+$M$15)^M26 -> 8964.5253
A27: Nat Gas(~$2k for large tank, for ~1.5yrs) | B27: =2000/18 -> 111.11111 | C27: =B27*12 -> 1333.3333 | L27: 48823 | M27: 9 | N27: ='STR 10 Year'!J39 -> 17397.442 | O27: =N27/(1+$M$15)^M27 -> 8703.0524
A28: WIFI / Cable | B28: 150 | C28: =B28*12 -> 1800 | H28: Emergency Fund Needed (6 months) | I28: =B38*$J$28+SUM(B41:B42)*$J$28 -> 40479.952 | J28: 6 | K28: months | L28: 49188 | M28: 10 | N28: ='STR 10 Year'!K39+'STR 10 Year'!K44-('STR Calculator'!B8-SUM('STR 10 Year'!B46:K46)) -> 491848.63 | O28: =N28/(1+$M$15)^M28 -> 227821.08
A29: Pool Service (bi-weekly = 2xmonth) | B29: 0 | C29: =B29*12 -> 0 | I29: =I28/2 -> 20239.976 | J29: =J28/2 -> 3 | K29: months
A30: Water/Sewer ($0 for well/septic) | B30: 0 | C30: =B30*12 -> 0 | N30: =XIRR(N18:N28,L18:L28) -> 0.2162627 | O30: =SUM(O18:O28) -> 194053.7
A31: Building Maintenance | B31: =C31/12 -> 0 | C31: =B5*D31 -> 0 | D31: 0
A32: Capex (Future Repairs) | B32: =C32/12 -> 0 | C32: =D32*B5 -> 0 | D32: 0
A33: Grounds Cleanup/Services Maintenance/Snow Removal | B33: 0 | C33: =B33*12 -> 0
A34: City Permit Fees | B34: 25 | C34: =B34*12 -> 300
A35: Fire Marshal Permit | B35: 20 | C35: =B35*12 -> 240
A36: Incidentals (Coffee/Creamer etc) | B36: 25 | C36: =B36*12 -> 300
A37: Umbrella Insurance (Allstate Anchorage) | B37: 37 | C37: =B37*12 -> 444
A38: Totals | B38: =SUM(B18:B37) -> 2868.1111 | C38: =SUM(C18:C37) -> 34417.333 | H38: Ask cleaners what is included vs not - Linens/soaps/shampoos/coffee/creamer
A40: Net Operating Income | B40: =C15-B38 -> 4756.8889 | C40: =D15-C38 -> 57082.667 | D40: DSCR | E40: =B40/(B42+B41+B43) -> 1.2264614
A41: HELOC Payment (Interest Only) | B41: =IF(I6<0,0,I6) -> 445.5 | C41: =B41*12 -> 5346 | D41: =IF(B41=I6,1,0) -> 1
A42: Conventional Loan Payment | B42: =-PMT($I$8/12,$I$9*12,$B$8) -> 3433.0475 | C42: =B42*12 -> 41196.57 | D42: Cap Rate | E42: =C40/$B$5 -> 0.095296605
A43: PMI if down payment less than 20% | B43: =IF(C7<0.2,300,0) -> 0 | C43: =B43*12 -> 0 | D43: =ROUND(C43/B8,4)&"% of loan" -> 0% of loan
A44: Cash Flow | B44: =B40-B42-B41-B43 -> 878.34141 | C44: =B44*12 -> 10540.097
A47: Estimated CapEx | B47: Timeline of Repair (yrs) | C47: Cost per Unit | D47: Total Cost | E47: Monthly Cost
A48: Roof | B48: 5 | C48: 7000 | D48: =C48 -> 7000 | E48: =D48/B48/12 -> 116.66667
A49: Master Bath | B49: 10 | D49: =C49 -> 0 | E49: =D49/B49/12 -> 0
A50: Kitchen | B50: 10 | D50: =C50 -> 0 | E50: =D50/B50/12 -> 0
A51: Flooring | B51: 10 | C51: 8000 | D51: =C51 -> 8000 | E51: =D51/B51/12 -> 66.666667
A52: Guest baths | B52: 10 | D52: =C52 -> 0 | E52: =D52/B52/12 -> 0
A53: Exterior Paint | B53: 1 | D53: =C53 -> 0 | E53: =D53/B53/12 -> 0
A54: Interior Paint | B54: 6 | C54: 2000 | D54: =C54 -> 2000 | E54: =D54/B54/12 -> 27.777778
A55: Cabinets | B55: 10 | D55: =C55 -> 0 | E55: =D55/B55/12 -> 0
A56: Concrete walkways | B56: 4 | D56: =C56 -> 0 | E56: =D56/B56/12 -> 0
A57: Driveway Re-Pave (Asphalt) | B57: 1 | D57: =C57 -> 0 | E57: =D57/B57/12 -> 0
A58: Miscellaneous (light fixtures/door knobs etc) | B58: 10 | C58: 500 | D58: =C58 -> 500 | E58: =D58/B58/12 -> 4.1666667
A59: Total Estimated Repairs | E59: =SUM(E48:E58) -> 215.27778

Sheet Interest Rate Comparison
A1: Purchase Price | C1: 0.1 | D1: 0.15 | E1: 0.2 | F1: 0.25 | H1: 5% Increase in Down Payment | I1: Time to recoup
A2: ='STR Calculator'!B5 -> 599000 | B2: Down Payment | C2: =$A$2*C1 -> 59900 | D2: =$A$2*D1 -> 89850 | E2: =$A$2*E1 -> 119800 | F2: =$A$2*F1 -> 149750 | H2: =D2-C2 -> 29950
A3: 30 | B3: 0.0825 | C3: =PMT($B$3/12,$A$3*12,($A$2-C2)) -> -4050.0783 | D3: =PMT($B$3/12,$A$3*12,($A$2-D2)) -> -3825.0739 | E3: =PMT($B$3/12,$A$3*12,($A$2-E2)) -> -3600.0696 | F3: =PMT($B$3/12,$A$3*12,($A$2-F2)) -> -3375.0652 | G3: =B3 -> 0.0825 | H3: =D3-C3 -> 225.00435 | I3: =$H$2/H3/12 -> 11.092378
B4: 0.08 | C4: =PMT($B$4/12,$A$3*12,($A$2-C2)) -> -3955.7248 | D4: =PMT($B$4/12,$A$3*12,($A$2-D2)) -> -3735.9623 | E4: =PMT($B$4/12,$A$3*12,($A$2-E2)) -> -3516.1998 | F4: =PMT($B$4/12,$A$3*12,($A$2-F2)) -> -3296.4373 | G4: =B4 -> 0.08 | H4: =D4-C4 -> 219.76249 | I4: =$H$2/H4/12 -> 11.356958
B5: 0.0775 | C5: =PMT($B$5/12,$A$3*12,($A$2-C2)) -> -3862.1784 | D5: =PMT($B$5/12,$A$3*12,($A$2-D2)) -> -3647.6129 | E5: =PMT($B$5/12,$A$3*12,($A$2-E2)) -> -3433.0475 | F5: =PMT($B$5/12,$A$3*12,($A$2-F2)) -> -3218.482 | G5: =B5 -> 0.0775 | H5: =D5-C5 -> 214.56547 | I5: =$H$2/H5/12 -> 11.632036
B6: 0.075 | C6: =PMT($B$6/12,$A$3*12,($A$2-C2)) -> -3769.4654 | D6: =PMT($B$6/12,$A$3*12,($A$2-D2)) -> -3560.0507 | E6: =PMT($B$6/12,$A$3*12,($A$2-E2)) -> -3350.6359 | F6: =PMT($B$6/12,$A$3*12,($A$2-F2)) -> -3141.2212 | G6: =B6 -> 0.075 | H6: =D6-C6 -> 209.41475 | I6: =$H$2/H6/12 -> 11.918136
B7: 0.0725 | C7: =PMT($B$7/12,$A$3*12,($A$2-C2)) -> -3677.6123 | D7: =PMT($B$7/12,$A$3*12,($A$2-D2)) -> -3473.3005 | E7: =PMT($B$7/12,$A$3*12,($A$2-E2)) -> -3268.9887 | F7: =PMT($B$7/12,$A$3*12,($A$2-F2)) -> -3064.6769 | G7: =B7 -> 0.0725 | H7: =D7-C7 -> 204.3118 | I7: =$H$2/H7/12 -> 12.215806
B8: 0.07 | C8: =PMT($B$8/12,$A$3*12,($A$2-C2)) -> -3586.6458 | D8: =PMT($B$8/12,$A$3*12,($A$2-D2)) -> -3387.3877 | E8: =PMT($B$8/12,$A$3*12,($A$2-E2)) -> -3188.1296 | F8: =PMT($B$8/12,$A$3*12,($A$2-F2)) -> -2988.8715 | G8: =B8 -> 0.07 | H8: =D8-C8 -> 199.2581 | I8: =$H$2/H8/12 -> 12.525631
G9: Higher delta between P&I payment at higher interest rate compared to lower = shorter payout, when factoring in increased down payment for lower rate
A12: Down Payment % | B12: Down Payment | C12: Interest Rate | D12: ="Interest Paid on Down Payment by Year "&ROUND(I4,0) -> Interest Paid on Down Payment by Year 11 | E12: Down Payment Difference | F12: ="Interest Paid Difference @ year "&ROUND(I4,0) -> Interest Paid Difference @ year 11 | G12: Down Payment vs Interest Paid | H12: =ROUND(I4,0)&"yr FV of down payment saved @ 8%" -> 11yr FV of down payment saved @ 8% | I12: NPV of Interest Saved/Lost | J12: ="Cum Interest Paid Year "&ROUND(I4,0) -> Cum Interest Paid Year 11 | K12: Interest Saved Compared to 10% Loan | L12: Total Interest Paid - Life of Loan
A13: =C1 -> 0.1 | B13: =$A$2*A13 -> 59900 | C13: =B4 -> 0.08 | D13: =B13*(1+C13)^$I$4 -> 143555.23 | E13: 0 | F13: 0 | G13: =F13-E13 -> 0 | H13: 0 | I13: 0 | J13: =VLOOKUP($I$4*12,'Amoritization Scenario 10% DP'!$W$8:$AH$367,10) -> 458293.33 | K13: 0 | L13: 1270301
A14: =D1 -> 0.15 | B14: =$A$2*A14 -> 89850 | C14: =B4 -> 0.08 | D14: =B14*(1+C14)^$I$4 -> 215332.84 | E14: =B14-B13 -> 29950 | F14: =D14-D13 -> 71777.613 | G14: =F14-E14 -> 41827.613 | H14: =E14*(1+0.08)^I4 -> 71777.613 | I14: =G14/(1+C14)^I4 -> 17453.032 | J14: =VLOOKUP($I$4*12,'Amoritization Scenario 15% DP'!$W$8:$AH$367,10) -> 432832.59 | K14: =J13-J14 -> 25460.74 | L14: 1199728 | M14: =L14+H14 -> 1271505.6
A15: =E1 -> 0.2 | B15: =$A$2*A15 -> 119800 | C15: =B5 -> 0.0775 | D15: =B15*(1+C15)^$I$4 -> 279652.36 | E15: =B15-B13 -> 59900 | F15: =D15-D13 -> 136097.13 | G15: =F15-E15 -> 76197.134 | H15: =E15*(1+0.08)^I4 -> 143555.23 | I15: =G15/(1+C15)^I4 -> 32642.016 | J15: =VLOOKUP($I$4*12,'Amoritization Scenario 20% DP'!$AJ$8:$AU$367,10) -> 393573.27 | K15: =J13-J15 -> 64720.056 | L15: 1034105 | M15: =L15+H15 -> 1177660.2
K17: Present Value=Future Value /( 1+i)^n

Sheet STR 10 Year
A1: Year | B1: 1 | C1: 2 | D1: 3 | E1: 4 | F1: 5 | G1: 6 | H1: 7 | I1: 8 | J1: 9 | K1: 10
A2: Property Income | L2: Desired Return | M2: 0.08 | N2: match stock market
A3: Yearly Revenue | B3: ='STR Calculator'!D11 -> 91500 | C3: =B3*(1+C5) -> 92415 | D3: =C3*(1+D5) -> 93339.15 | E3: =D3*(1+E5) -> 94272.541 | F3: =E3*(1+F5) -> 95215.267 | G3: =F3*(1+G5) -> 96167.42 | H3: =G3*(1+H5) -> 97129.094 | I3: =H3*(1+I5) -> 98100.385 | J3: =I3*(1+J5) -> 99081.389 | K3: =J3*(1+K5) -> 100072.2
A4: Monthly Revenue | B4: =B3/12 -> 7625 | C4: =C3/12 -> 7701.25 | D4: =D3/12 -> 7778.2625 | E4: =E3/12 -> 7856.0451 | F4: =F3/12 -> 7934.6056 | G4: =G3/12 -> 8013.9516 | H4: =H3/12 -> 8094.0911 | I4: =I3/12 -> 8175.0321 | ... K4: =K3/12 -> 8339.3502 | M4: IRR | P4: NPV
A5: Rent Appreciation | B5: 0.01 | C5: =$B$5 -> 0.01 | D5: =$B$5 -> 0.01 | E5: =$B$5 -> 0.01 | F5: =$B$5 -> 0.01 | G5: =$B$5 -> 0.01 | H5: =$B$5 -> 0.01 | I5: =$B$5 -> 0.01 | J5: =$B$5 -> 0.01 | K5: =$B$5 -> 0.01 | M5: 45536 | N5: 0 | O5: =-SUM('STR Calculator'!B6:B7) -> -119800 | P5: =O5 -> -119800
A6: ="Vacancy Loss (Occupancy rate "&'STR Calculator'!$B$12&"%)" -> Vacancy Loss (Occupancy rate 1%) | B6: =B3*(1-'STR Calculator'!$B$12) -> 0 | C6: =C3*(1-'STR Calculator'!$B$12) -> 0 | D6: =D3*(1-'STR Calculator'!$B$12) -> 0 | E6: =E3*(1-'STR Calculator'!$B$12) -> 0 | F6: =F3*(1-'STR Calculator'!$B$12) -> 0 | G6: =G3*(1-'STR Calculator'!$B$12) -> 0 | H6: =H3*(1-'STR Calculator'!$B$12) -> 0 | I6: =I3*(1-'STR Calculator'!$B$12) -> 0 | ... K6: =K3*(1-'STR Calculator'!$B$12) -> 0 | M6: 45901 | N6: 1 | O6: =B39 -> 10780.097 | P6: =O6/(1+$M$2)^N6 -> 9981.5712
M7: 46266 | N7: 2 | O7: =C39 -> 11854.097 | P7: =O7/(1+$M$2)^N7 -> 10162.977
A8: Operating Income | B8: =B3-B6 -> 91500 | C8: =C3-C6 -> 92415 | D8: =D3-D6 -> 93339.15 | E8: =E3-E6 -> 94272.541 | F8: =F3-F6 -> 95215.267 | G8: =G3-G6 -> 96167.42 | H8: =H3-H6 -> 97129.094 | I8: =I3-I6 -> 98100.385 | ... K8: =K3-K6 -> 100072.2 | M8: 46631 | N8: 3 | O8: =D39 -> 12632.732 | P8: =O8/(1+$M$2)^N8 -> 10028.27
M9: 46997 | N9: 4 | O9: =E39 -> 13415.93 | P9: =O9/(1+$M$2)^N9 -> 9861.1088
A10: Property Expenses | M10: 47362 | N10: 5 | O10: =F39 -> 14203.613 | P10: =O10/(1+$M$2)^N10 -> 9666.7401
A11: Management Fee | B11: ='STR Calculator'!$C$18 -> 0 | C11: =$B$11 -> 0 | D11: =$B$11 -> 0 | E11: =$B$11 -> 0 | F11: =$B$11 -> 0 | G11: =$B$11 -> 0 | H11: =$B$11 -> 0 | I11: =$B$11 -> 0 | J11: =$B$11 -> 0 | K11: =$B$11 -> 0 | M11: 47727 | N11: 6 | O11: =G39 -> 14995.698 | P11: =O11/(1+$M$2)^N11 -> 9449.8331
A12: Subscriptions | B12: ='STR Calculator'!$C$19 -> 600 | C12: ='STR Calculator'!$C$19 -> 600 | D12: ='STR Calculator'!$C$19 -> 600 | E12: ='STR Calculator'!$C$19 -> 600 | F12: ='STR Calculator'!$C$19 -> 600 | G12: ='STR Calculator'!$C$19 -> 600 | H12: ='STR Calculator'!$C$19 -> 600 | I12: ='STR Calculator'!$C$19 -> 600 | ... K12: ='STR Calculator'!$C$19 -> 600 | M12: 48092 | N12: 7 | O12: =H39 -> 15792.095 | P12: =O12/(1+$M$2)^N12 -> 9214.5359
A13: AirBnB/VRBO Fee (3% of nightly- Passed to guest) | B13: ='STR Calculator'!$C$20 -> 0 | C13: ='STR Calculator'!$C$20 -> 0 | D13: ='STR Calculator'!$C$20 -> 0 | E13: ='STR Calculator'!$C$20 -> 0 | F13: ='STR Calculator'!$C$20 -> 0 | G13: ='STR Calculator'!$C$20 -> 0 | H13: ='STR Calculator'!$C$20 -> 0 | I13: ='STR Calculator'!$C$20 -> 0 | ... K13: ='STR Calculator'!$C$20 -> 0 | M13: 48458 | N13: 8 | O13: =I39 -> 16592.711 | P13: =O13/(1+$M$2)^N13 -> 8964.5253
A14: Property Taxes (1.5%) | B14: ='STR Calculator'!$C$21 -> 2400 | C14: =B44*($B$14/'STR Calculator'!$B$5) -> 2496 | D14: =C44*($B$14/'STR Calculator'!$B$5) -> 2595.84 | E14: =D44*($B$14/'STR Calculator'!$B$5) -> 2699.6736 | F14: =E44*($B$14/'STR Calculator'!$B$5) -> 2807.6605 | G14: =F44*($B$14/'STR Calculator'!$B$5) -> 2919.967 | H14: =G44*($B$14/'STR Calculator'!$B$5) -> 3036.7656 | I14: =H44*($B$14/'STR Calculator'!$B$5) -> 3158.2363 | J14: =I44*($B$14/'STR Calculator'!$B$5) -> 3284.5657 | K14: =J44*($B$14/'STR Calculator'!$B$5) -> 3415.9483 | M14: 48823 | N14: 9 | O14: =J39 -> 17397.442 | P14: =O14/(1+$M$2)^N14 -> 8703.0524
A15: Insurance (1.5%) | B15: ='STR Calculator'!$C$22 -> 3000 | C15: =B15+(B15*0.015) -> 3045 | D15: =C15+(C15*0.015) -> 3090.675 | E15: =D15+(D15*0.015) -> 3137.0351 | F15: =E15+(E15*0.015) -> 3184.0907 | G15: =F15+(F15*0.015) -> 3231.852 | H15: =G15+(G15*0.015) -> 3280.3298 | I15: =H15+(H15*0.015) -> 3329.5347 | J15: =I15+(I15*0.015) -> 3379.4778 | K15: =J15+(J15*0.015) -> 3430.1699 | M15: 49188 | N15: 10 | O15: =K39+K44-('STR Calculator'!B8-SUM('STR 10 Year'!B46:K46)) -> 491848.63 | P15: =O15/(1+$M$2)^N15 -> 227821.08
A16: Cleaners/Handyman | B16: =SUM('STR Calculator'!$C$23:$C$24) -> 21000 | C16: =SUM('STR Calculator'!$C$23:$C$24) -> 21000 | D16: =SUM('STR Calculator'!$C$23:$C$24) -> 21000 | E16: =SUM('STR Calculator'!$C$23:$C$24) -> 21000 | F16: =SUM('STR Calculator'!$C$23:$C$24) -> 21000 | G16: =SUM('STR Calculator'!$C$23:$C$24) -> 21000 | H16: =SUM('STR Calculator'!$C$23:$C$24) -> 21000 | I16: =SUM('STR Calculator'!$C$23:$C$24) -> 21000 | ... K16: =SUM('STR Calculator'!$C$23:$C$24) -> 21000
A17: HOA Fees | B17: ='STR Calculator'!$C$25 -> 0 | C17: ='STR Calculator'!$C$25 -> 0 | D17: ='STR Calculator'!$C$25 -> 0 | E17: ='STR Calculator'!$C$25 -> 0 | F17: ='STR Calculator'!$C$25 -> 0 | G17: ='STR Calculator'!$C$25 -> 0 | H17: ='STR Calculator'!$C$25 -> 0 | I17: ='STR Calculator'!$C$25 -> 0 | ... K17: ='STR Calculator'!$C$25 -> 0 | O17: =XIRR(O5:O15,M5:M15) -> 0.2162627 | P17: =SUM(P5:P15) -> 194053.7
A18: Electricity | B18: ='STR Calculator'!$C$26 -> 3000 | C18: ='STR Calculator'!$C$26 -> 3000 | D18: ='STR Calculator'!$C$26 -> 3000 | E18: ='STR Calculator'!$C$26 -> 3000 | F18: ='STR Calculator'!$C$26 -> 3000 | G18: ='STR Calculator'!$C$26 -> 3000 | H18: ='STR Calculator'!$C$26 -> 3000 | I18: ='STR Calculator'!$C$26 -> 3000 | ... K18: ='STR Calculator'!$C$26 -> 3000
A19: Natural Gas | B19: ='STR Calculator'!$C$27 -> 1333.3333 | C19: ='STR Calculator'!$C$27 -> 1333.3333 | D19: ='STR Calculator'!$C$27 -> 1333.3333 | E19: ='STR Calculator'!$C$27 -> 1333.3333 | F19: ='STR Calculator'!$C$27 -> 1333.3333 | G19: ='STR Calculator'!$C$27 -> 1333.3333 | H19: ='STR Calculator'!$C$27 -> 1333.3333 | I19: ='STR Calculator'!$C$27 -> 1333.3333 | ... K19: ='STR Calculator'!$C$27 -> 1333.3333
A20: WIFI/Cable | B20: ='STR Calculator'!$C$28 -> 1800 | C20: ='STR Calculator'!$C$28 -> 1800 | D20: ='STR Calculator'!$C$28 -> 1800 | E20: ='STR Calculator'!$C$28 -> 1800 | F20: ='STR Calculator'!$C$28 -> 1800 | G20: ='STR Calculator'!$C$28 -> 1800 | H20: ='STR Calculator'!$C$28 -> 1800 | I20: ='STR Calculator'!$C$28 -> 1800 | ... K20: ='STR Calculator'!$C$28 -> 1800
A21: Water/Sewer ($0 if septic/well) | B21: ='STR Calculator'!$C$30 -> 0 | C21: ='STR Calculator'!$C$30 -> 0 | D21: ='STR Calculator'!$C$30 -> 0 | E21: ='STR Calculator'!$C$30 -> 0 | F21: ='STR Calculator'!$C$30 -> 0 | G21: ='STR Calculator'!$C$30 -> 0 | H21: ='STR Calculator'!$C$30 -> 0 | I21: ='STR Calculator'!$C$30 -> 0 | ... K21: ='STR Calculator'!$C$30 -> 0
A22: Pool Service ($75/each x biweekly) | B22: ='STR Calculator'!$C$29 -> 0 | C22: ='STR Calculator'!$C$29 -> 0 | D22: ='STR Calculator'!$C$29 -> 0 | E22: ='STR Calculator'!$C$29 -> 0 | F22: ='STR Calculator'!$C$29 -> 0 | G22: ='STR Calculator'!$C$29 -> 0 | H22: ='STR Calculator'!$C$29 -> 0 | I22: ='STR Calculator'!$C$29 -> 0 | ... K22: ='STR Calculator'!$C$29 -> 0
A23: Building Maintenance (1%) | B23: ='STR Calculator'!$C$31 -> 0 | C23: ='STR Calculator'!$B$5*'STR Calculator'!$D$31 -> 0 | D23: ='STR Calculator'!$B$5*'STR Calculator'!$D$31 -> 0 | E23: ='STR Calculator'!$B$5*'STR Calculator'!$D$31 -> 0 | F23: ='STR Calculator'!$B$5*'STR Calculator'!$D$31 -> 0 | G23: ='STR Calculator'!$B$5*'STR Calculator'!$D$31 -> 0 | H23: ='STR Calculator'!$B$5*'STR Calculator'!$D$31 -> 0 | I23: ='STR Calculator'!$B$5*'STR Calculator'!$D$31 -> 0 | J23: ='STR Calculator'!$B$5*'STR Calculator'!$D$31 -> 0 | K23: ='STR Calculator'!$B$5*'STR Calculator'!$D$31 -> 0
A24: Capex (1%) | B24: ='STR Calculator'!$C$32 -> 0 | C24: ='STR Calculator'!$C$32 -> 0 | D24: ='STR Calculator'!$C$32 -> 0 | E24: ='STR Calculator'!$C$32 -> 0 | F24: ='STR Calculator'!$C$32 -> 0 | G24: ='STR Calculator'!$C$32 -> 0 | H24: ='STR Calculator'!$C$32 -> 0 | I24: ='STR Calculator'!$C$32 -> 0 | ... K24: ='STR Calculator'!$C$32 -> 0
A25: Grounds Cleanup/Services/Snow Removal | B25: ='STR Calculator'!$C$33 -> 0 | C25: ='STR Calculator'!$C$33 -> 0 | D25: ='STR Calculator'!$C$33 -> 0 | E25: ='STR Calculator'!$C$33 -> 0 | F25: ='STR Calculator'!$C$33 -> 0 | G25: ='STR Calculator'!$C$33 -> 0 | H25: ='STR Calculator'!$C$33 -> 0 | I25: ='STR Calculator'!$C$33 -> 0 | ... K25: ='STR Calculator'!$C$33 -> 0
A26: City Permit Fee | B26: 300 | C26: 0 | D26: 0 | E26: 0 | F26: 0 | G26: 0 | H26: 0 | I26: 0 | J26: 0 | K26: 0
A27: Incidentals (Coffee/Creamer etc) | B27: ='STR Calculator'!$C$36 -> 300 | C27: ='STR Calculator'!$C$36 -> 300 | D27: ='STR Calculator'!$C$36 -> 300 | E27: ='STR Calculator'!$C$36 -> 300 | F27: ='STR Calculator'!$C$36 -> 300 | G27: ='STR Calculator'!$C$36 -> 300 | H27: ='STR Calculator'!$C$36 -> 300 | I27: ='STR Calculator'!$C$36 -> 300 | ... K27: ='STR Calculator'!$C$36 -> 300
A28: Umbrella Insurance | B28: ='STR Calculator'!$C$37 -> 444 | C28: ='STR Calculator'!$C$37 -> 444 | D28: ='STR Calculator'!$C$37 -> 444 | E28: ='STR Calculator'!$C$37 -> 444 | F28: ='STR Calculator'!$C$37 -> 444 | G28: ='STR Calculator'!$C$37 -> 444 | H28: ='STR Calculator'!$C$37 -> 444 | I28: ='STR Calculator'!$C$37 -> 444 | ... K28: ='STR Calculator'!$C$37 -> 444
A30: Operating Expenses | B30: =SUM(B12:B28) -> 34177.333 | C30: =SUM(C12:C28) -> 34018.333 | D30: =SUM(D12:D28) -> 34163.848 | E30: =SUM(E12:E28) -> 34314.042 | F30: =SUM(F12:F28) -> 34469.085 | G30: =SUM(G12:G28) -> 34629.152 | H30: =SUM(H12:H28) -> 34794.429 | I30: =SUM(I12:I28) -> 34965.104 | ... K30: =SUM(K12:K28) -> 35323.452
A32: Net Operating Income (NOI) | B32: =B8-B30 -> 57322.667 | C32: =C8-C30 -> 58396.667 | D32: =D8-D30 -> 59175.302 | E32: =E8-E30 -> 59958.499 | F32: =F8-F30 -> 60746.182 | G32: =G8-G30 -> 61538.267 | H32: =H8-H30 -> 62334.665 | I32: =I8-I30 -> 63135.28 | ... K32: =K8-K30 -> 64748.751
A33: Capitalization Rate (CAP Rate) | B33: =B32/'STR Calculator'!$B$5 -> 0.095697273 | C33: =C32/'STR Calculator'!$B$5 -> 0.097490262 | D33: =D32/'STR Calculator'!$B$5 -> 0.098790153 | E33: =E32/'STR Calculator'!$B$5 -> 0.10009766 | F33: =F32/'STR Calculator'!$B$5 -> 0.10141266 | G33: =G32/'STR Calculator'!$B$5 -> 0.102735 | H33: =H32/'STR Calculator'!$B$5 -> 0.10406455 | I33: =I32/'STR Calculator'!$B$5 -> 0.10540114 | ... K33: =K32/'STR Calculator'!$B$5 -> 0.10809474
A35: Key Investment Indicators
A36: Mortgage Payment | B36: =PMT('STR Calculator'!$I$8/12, 'STR Calculator'!$I$9*12,'STR Calculator'!$B$8)*12 -> -41196.57 | C36: =PMT('STR Calculator'!$I$8/12, 'STR Calculator'!$I$9*12,'STR Calculator'!$B$8)*12 -> -41196.57 | D36: =PMT('STR Calculator'!$I$8/12, 'STR Calculator'!$I$9*12,'STR Calculator'!$B$8)*12 -> -41196.57 | E36: =PMT('STR Calculator'!$I$8/12, 'STR Calculator'!$I$9*12,'STR Calculator'!$B$8)*12 -> -41196.57 | F36: =PMT('STR Calculator'!$I$8/12, 'STR Calculator'!$I$9*12,'STR Calculator'!$B$8)*12 -> -41196.57 | G36: =PMT('STR Calculator'!$I$8/12, 'STR Calculator'!$I$9*12,'STR Calculator'!$B$8)*12 -> -41196.57 | H36: =PMT('STR Calculator'!$I$8/12, 'STR Calculator'!$I$9*12,'STR Calculator'!$B$8)*12 -> -41196.57 | I36: =PMT('STR Calculator'!$I$8/12, 'STR Calculator'!$I$9*12,'STR Calculator'!$B$8)*12 -> -41196.57 | ... K36: =PMT('STR Calculator'!$I$8/12, 'STR Calculator'!$I$9*12,'STR Calculator'!$B$8)*12 -> -41196.57
A37: ="HELOC Payment ($"& 'STR Calculator'!I3&")" -> HELOC Payment ($64800) | B37: =-'STR Calculator'!$C$41 -> -5346 | C37: =-'STR Calculator'!$C$41 -> -5346 | D37: =-'STR Calculator'!$C$41 -> -5346 | E37: =-'STR Calculator'!$C$41 -> -5346 | F37: =-'STR Calculator'!$C$41 -> -5346 | G37: =-'STR Calculator'!$C$41 -> -5346 | H37: =-'STR Calculator'!$C$41 -> -5346 | I37: =-'STR Calculator'!$C$41 -> -5346 | ... K37: =-'STR Calculator'!$C$41 -> -5346
A38: PMI if Down Payment less than 20% | B38: =-'STR Calculator'!$C$43 -> 0 | C38: =-'STR Calculator'!$C$43 -> 0 | D38: =-'STR Calculator'!$C$43 -> 0 | E38: =-'STR Calculator'!$C$43 -> 0 | F38: =-'STR Calculator'!$C$43 -> 0 | G38: =-'STR Calculator'!$C$43 -> 0 | H38: =-'STR Calculator'!$C$43 -> 0 | I38: =-'STR Calculator'!$C$43 -> 0 | ... K38: =-'STR Calculator'!$C$43 -> 0
A39: Net Cash Flow | B39: =B32+B36+B37+B38 -> 10780.097 | C39: =C32+C36+C37+C38 -> 11854.097 | D39: =D32+D36+D37+D38 -> 12632.732 | E39: =E32+E36+E37+E38 -> 13415.93 | F39: =F32+F36+F37+F38 -> 14203.613 | G39: =G32+G36+G37+G38 -> 14995.698 | H39: =H32+H36+H37+H38 -> 15792.095 | I39: =I32+I36+I37+I38 -> 16592.711 | ... K39: =K32+K36+K37+K38 -> 18206.181 | L39: =SUM(B39:K39) -> 145870.59 | M39: FV of all cash flows
A40: Monthly Cash Flow | B40: =B39/12 -> 898.34141 | C40: =C39/12 -> 987.84141 | D40: =D39/12 -> 1052.7277 | E40: =E39/12 -> 1117.9941 | F40: =F39/12 -> 1183.6344 | G40: =G39/12 -> 1249.6415 | H40: =H39/12 -> 1316.0079 | I40: =I39/12 -> 1382.7259 | ... K40: =K39/12 -> 1517.1818
A41: ="Discounted Cash Flow (DCF) @ "&M2&"% return" -> Discounted Cash Flow (DCF) @ 0.08% return | B41: =B39/(1+$M$2)^B1 -> 9981.5712 | C41: =C39/(1+$M$2)^C1 -> 10162.977 | D41: =D39/(1+$M$2)^D1 -> 10028.27 | E41: =E39/(1+$M$2)^E1 -> 9861.1088 | F41: =F39/(1+$M$2)^F1 -> 9666.7401 | G41: =G39/(1+$M$2)^G1 -> 9449.8331 | H41: =H39/(1+$M$2)^H1 -> 9214.5359 | I41: =I39/(1+$M$2)^I1 -> 8964.5253 | ... K41: =K39/(1+$M$2)^K1 -> 8432.9845 | L41: =SUM(B41:K41) -> 94465.599 | M41: PV of all cash flows
A42: Cash on Cash ROI | B42: =B39/(SUM('STR Calculator'!$B$7,'STR Calculator'!$B$6)) -> 0.089984114 | C42: =C39/(SUM('STR Calculator'!$B$7,'STR Calculator'!$B$6)) -> 0.098949056 | D42: =D39/(SUM('STR Calculator'!$B$7,'STR Calculator'!$B$6)) -> 0.10544851 | E42: =E39/(SUM('STR Calculator'!$B$7,'STR Calculator'!$B$6)) -> 0.11198606 | F42: =F39/(SUM('STR Calculator'!$B$7,'STR Calculator'!$B$6)) -> 0.11856104 | G42: =G39/(SUM('STR Calculator'!$B$7,'STR Calculator'!$B$6)) -> 0.12517277 | H42: =H39/(SUM('STR Calculator'!$B$7,'STR Calculator'!$B$6)) -> 0.13182049 | I42: =I39/(SUM('STR Calculator'!$B$7,'STR Calculator'!$B$6)) -> 0.13850343 | ... K42: =K39/(SUM('STR Calculator'!$B$7,'STR Calculator'!$B$6)) -> 0.15197146
A43: Property Appreciation | B43: 0.04 | C43: =$B$43 -> 0.04 | D43: =$B$43 -> 0.04 | E43: =$B$43 -> 0.04 | F43: =$B$43 -> 0.04 | G43: =$B$43 -> 0.04 | H43: =$B$43 -> 0.04 | I43: =$B$43 -> 0.04 | J43: =$B$43 -> 0.04 | K43: =$B$43 -> 0.04
A44: Property Value | B44: ='STR Calculator'!$B$5*(1+'STR 10 Year'!B43) -> 622960 | C44: =B44*(1+'STR 10 Year'!C43) -> 647878.4 | D44: =C44*(1+'STR 10 Year'!D43) -> 673793.54 | E44: =D44*(1+'STR 10 Year'!E43) -> 700745.28 | F44: =E44*(1+'STR 10 Year'!F43) -> 728775.09 | G44: =F44*(1+'STR 10 Year'!G43) -> 757926.09 | H44: =G44*(1+'STR 10 Year'!H43) -> 788243.14 | I44: =H44*(1+'STR 10 Year'!I43) -> 819772.86 | J44: =I44*(1+'STR 10 Year'!J43) -> 852563.78 | K44: =J44*(1+'STR 10 Year'!K43) -> 886666.33
A45: Property Appreciation | B45: ='STR Calculator'!$B$5*B43 -> 23960 | C45: =B44*C43 -> 24918.4 | D45: =C44*D43 -> 25915.136 | E45: =D44*E43 -> 26951.741 | F45: =E44*F43 -> 28029.811 | G45: =F44*G43 -> 29151.004 | H45: =G44*H43 -> 30317.044 | I45: =H44*I43 -> 31529.725 | J45: =I44*J43 -> 32790.914 | K45: =J44*K43 -> 34102.551
A46: Mortgage Principle Reduction | B46: =VLOOKUP('STR 10 Year'!B1*12,'Amoritization Scenario 10% DP'!$W$8:$AH$367,9) -> 4503.4472 | C46: =VLOOKUP('STR 10 Year'!C1*12,'Amoritization Scenario 10% DP'!$W$8:$AH$367,9)-B46 -> 4877.2311 | D46: =VLOOKUP('STR 10 Year'!D1*12,'Amoritization Scenario 10% DP'!$W$8:$AH$367,9)-SUM(B46:C46) -> 5282.0389 | E46: =VLOOKUP('STR 10 Year'!E1*12,'Amoritization Scenario 10% DP'!$W$8:$AH$367,9)-SUM(B46:D46) -> 5720.4455 | F46: =VLOOKUP('STR 10 Year'!F1*12,'Amoritization Scenario 10% DP'!$W$8:$AH$367,9)-SUM(B46:E46) -> 6195.2397 | G46: =VLOOKUP('STR 10 Year'!G1*12,'Amoritization Scenario 10% DP'!$W$8:$AH$367,9)-SUM(B46:F46) -> 6709.4415 | H46: =VLOOKUP('STR 10 Year'!H1*12,'Amoritization Scenario 10% DP'!$W$8:$AH$367,9)-SUM(B46:G46) -> 7266.3219 | I46: =VLOOKUP('STR 10 Year'!I1*12,'Amoritization Scenario 10% DP'!$W$8:$AH$367,9)-SUM(B46:H46) -> 7869.423 | J46: =VLOOKUP('STR 10 Year'!J1*12,'Amoritization Scenario 10% DP'!$W$8:$AH$367,9)-SUM(B46:I46) -> 8522.5812 | K46: =VLOOKUP('STR 10 Year'!K1*12,'Amoritization Scenario 10% DP'!$W$8:$AH$367,9)-SUM(B46:J46) -> 9229.9512 | L46: =SUM(B46:K46) -> 66176.121 | M46: loan paid down
A47: Net Tax Savings (25% Bracket) | B47: =B39*0.25 -> 2695.0242 | C47: =C39*0.25 -> 2963.5242 | D47: =D39*0.25 -> 3158.183 | E47: =E39*0.25 -> 3353.9824 | F47: =F39*0.25 -> 3550.9032 | G47: =G39*0.25 -> 3748.9244 | H47: =H39*0.25 -> 3948.0238 | I47: =I39*0.25 -> 4148.1777 | ... K47: =K39*0.25 -> 4551.5453
A48: Tax ROI | B48: =B47/SUM('STR Calculator'!$B$6:$B$7) -> 0.022496029 | C48: =C47/SUM('STR Calculator'!$B$6:$B$7) -> 0.024737264 | D48: =D47/SUM('STR Calculator'!$B$6:$B$7) -> 0.026362128 | E48: =E47/SUM('STR Calculator'!$B$6:$B$7) -> 0.027996514 | F48: =F47/SUM('STR Calculator'!$B$6:$B$7) -> 0.02964026 | G48: =G47/SUM('STR Calculator'!$B$6:$B$7) -> 0.031293192 | H48: =H47/SUM('STR Calculator'!$B$6:$B$7) -> 0.032955124 | I48: =I47/SUM('STR Calculator'!$B$6:$B$7) -> 0.034625857 | ... K48: =K47/SUM('STR Calculator'!$B$6:$B$7) -> 0.037992865
A49: Total Return (Not counting appreciation) | B49: =SUM(B39,B46,B47) -> 17978.568 | C49: =SUM(C39,C46,C47) -> 19694.852 | D49: =SUM(D39,D46,D47) -> 21072.954 | E49: =SUM(E39,E46,E47) -> 22490.358 | F49: =SUM(F39,F46,F47) -> 23949.755 | G49: =SUM(G39,G46,G47) -> 25454.063 | H49: =SUM(H39,H46,H47) -> 27006.441 | I49: =SUM(I39,I46,I47) -> 28610.311 | ... K49: =SUM(K39,K46,K47) -> 31987.678
A50: Total ROI | B50: =B49/SUM('STR Calculator'!$B$6:$B$7) -> 0.15007152 | C50: =C49/SUM('STR Calculator'!$B$6:$B$7) -> 0.16439776 | D50: =D49/SUM('STR Calculator'!$B$6:$B$7) -> 0.17590112 | E50: =E49/SUM('STR Calculator'!$B$6:$B$7) -> 0.18773253 | F50: =F49/SUM('STR Calculator'!$B$6:$B$7) -> 0.19991449 | G50: =G49/SUM('STR Calculator'!$B$6:$B$7) -> 0.21247131 | H50: =H49/SUM('STR Calculator'!$B$6:$B$7) -> 0.22542939 | I50: =I49/SUM('STR Calculator'!$B$6:$B$7) -> 0.23881729 | ... K50: =K49/SUM('STR Calculator'!$B$6:$B$7) -> 0.26700899 | L50: =SUM(B50:K50)/K1 -> 0.20744104 | M50: AAR
L51: =('STR 10 Year'!K44/'STR Calculator'!B5)^(1/'STR 10 Year'!K1)-1 -> 0.04 | M51: CAGR
A53: Total Property Equity (not counting appreciation) | B53: =SUM('STR Calculator'!$B$7,'STR 10 Year'!B46) -> 124303.45 | C53: =B53+C46 -> 129180.68 | D53: =C53+D46 -> 134462.72 | E53: =D53+E46 -> 140183.16 | F53: =E53+F46 -> 146378.4 | G53: =F53+G46 -> 153087.84 | H53: =G53+H46 -> 160354.17 | I53: =H53+I46 -> 168223.59 | J53: =I53+J46 -> 176746.17 | K53: =J53+K46 -> 185976.12
K54: =(K53-B53)/B53 -> 0.49614613 | L54: =(K53/B53)^(1/K1)-1 -> 0.041111878 | M54: CAGR
A55: Total Property Equity (counting appreciation) | B55: =SUM('STR Calculator'!$B$7,'STR 10 Year'!B46,B45) -> 148263.45 | C55: =B55+C46+C45 -> 178059.08 | D55: =C55+D46+D45 -> 209256.25 | E55: =D55+E46+E45 -> 241928.44 | F55: =E55+F46+F45 -> 276153.49 | G55: =F55+G46+G45 -> 312013.94 | H55: =G55+H46+H45 -> 349597.3 | I55: =H55+I46+I45 -> 388996.45 | J55: =I55+J46+J45 -> 430309.95 | K55: =J55+K46+K45 -> 473642.45
K56: =(K55-B55)/B55 -> 2.1946003 | L56: =(K55/B55)^(1/K1)-1 -> 0.12316006 | M56: CAGR w/ Appreciation

Sheet STR 7yr IRR Financing
A1: ='STR Calculator'!A2 &" - FINANCING CALCULATIONS" -> 2615 Whippor Will Way - 1bd / 3bath - 1617 sqft - FINANCING CALCULATIONS
B4: Year 1 | C4: Year 2 | D4: Year 3 | E4: Year 4 | F4: Year 5 | G4: Year 6 | H4: Year 7
A5: Maintenance | B5: 0.01 | C5: 0.01 | D5: 0.01 | E5: 0.01 | F5: 0.01 | G5: 0.01 | H5: 0.01
A6: Property Appreciation | B6: 0.02 | C6: 0.02 | D6: 0.02 | E6: 0.02 | F6: 0.02 | G6: 0.02 | H6: 0.02
A7: Rental Appreciation | B7: 0.01 | C7: 0.01 | D7: 0.01 | E7: 0.01 | F7: 0.01 | G7: 0.01 | H7: 0.01
A8: Tax/Insurance/HOA Appreciation | B8: 0.015 | C8: 0.015 | D8: 0.015 | E8: 0.015 | F8: 0.015 | G8: 0.015 | H8: 0.015
A9: Vacancy | B9: =1-'STR Calculator'!$B$12 -> 0 | C9: =1-'STR Calculator'!$B$12 -> 0 | D9: =1-'STR Calculator'!$B$12 -> 0 | E9: =1-'STR Calculator'!$B$12 -> 0 | F9: =1-'STR Calculator'!$B$12 -> 0 | G9: =1-'STR Calculator'!$B$12 -> 0 | H9: =1-'STR Calculator'!$B$12 -> 0
B11: Year 1 | C11: Year 2 | D11: Year 3 | E11: Year 4 | F11: Year 5 | G11: Year 6 | H11: Year 7
A12: Revenues
A13: Rental Income | B13: ='STR Calculator'!D11 -> 91500 | C13: =SUM(B$13+(C$7*B$13)) -> 92415 | D13: =SUM(C$13+(D$7*C$13)) -> 93339.15 | E13: =SUM(D$13+(E$7*D$13)) -> 94272.541 | F13: =SUM(E$13+(F$7*E$13)) -> 95215.267 | G13: =SUM(F$13+(G$7*F$13)) -> 96167.42 | H13: =SUM(G$13+(H$7*G$13)) -> 97129.094
A14: Monthly Revenue | B14: =B13/12 -> 7625 | C14: =C13/12 -> 7701.25 | D14: =D13/12 -> 7778.2625 | E14: =E13/12 -> 7856.0451 | F14: =F13/12 -> 7934.6056 | G14: =G13/12 -> 8013.9516 | H14: =H13/12 -> 8094.0911
A15: Vacancy Rate | B15: ='STR Calculator'!D12 -> 0 | C15: =-(C13*C9) -> 0 | D15: =-(D13*D9) -> 0 | E15: =-(E13*E9) -> 0 | F15: =-(F13*F9) -> 0 | G15: =-(G13*G9) -> 0 | H15: =-(H13*H9) -> 0
A16: Net Revenue | B16: =SUM(B13,B15) -> 91500 | C16: =SUM(C13,C15) -> 92415 | D16: =SUM(D13,D15) -> 93339.15 | E16: =SUM(E13,E15) -> 94272.541 | F16: =SUM(F13,F15) -> 95215.267 | G16: =SUM(G13,G15) -> 96167.42 | H16: =SUM(H13,H15) -> 97129.094
A18: Expenses
A19: Management Fees | B19: 0 | C19: 0 | D19: 0 | E19: 0 | F19: 0 | G19: 0 | H19: 0
A20: Subscriptions | B20: ='STR Calculator'!$C$19 -> 600 | C20: ='STR Calculator'!$C$19 -> 600 | D20: ='STR Calculator'!$C$19 -> 600 | E20: ='STR Calculator'!$C$19 -> 600 | F20: ='STR Calculator'!$C$19 -> 600 | G20: ='STR Calculator'!$C$19 -> 600 | H20: ='STR Calculator'!$C$19 -> 600
A21: Property Taxes | B21: ='STR Calculator'!$C$21 -> 2400 | C21: =B$21+(B$21*C$8) -> 2436 | D21: =C$21+(C$21*D$8) -> 2472.54 | E21: =D$21+(D$21*E$8) -> 2509.6281 | F21: =E$21+(E$21*F$8) -> 2547.2725 | G21: =F$21+(F$21*G$8) -> 2585.4816 | H21: =G$21+(G$21*H$8) -> 2624.2638
A22: Insurance | B22: =('STR Calculator'!$C$22) -> 3000 | C22: =('STR Calculator'!$B$5+B48)*($B$22/'STR Calculator'!$B$5) -> 3060 | D22: =('STR Calculator'!$B$5+C48)*($B$22/'STR Calculator'!$B$5) -> 3061.2 | E22: =('STR Calculator'!$B$5+D48)*($B$22/'STR Calculator'!$B$5) -> 3061.224 | F22: =('STR Calculator'!$B$5+E48)*($B$22/'STR Calculator'!$B$5) -> 3061.2245 | G22: =('STR Calculator'!$B$5+F48)*($B$22/'STR Calculator'!$B$5) -> 3061.2245 | H22: =('STR Calculator'!$B$5+G48)*($B$22/'STR Calculator'!$B$5) -> 3061.2245
A23: Cleaners/Handyman | B23: =SUM('STR Calculator'!$C$23:$C$24) -> 21000 | C23: =SUM('STR Calculator'!$C$23:$C$24) -> 21000 | D23: =SUM('STR Calculator'!$C$23:$C$24) -> 21000 | E23: =SUM('STR Calculator'!$C$23:$C$24) -> 21000 | F23: =SUM('STR Calculator'!$C$23:$C$24) -> 21000 | G23: =SUM('STR Calculator'!$C$23:$C$24) -> 21000 | H23: =SUM('STR Calculator'!$C$23:$C$24) -> 21000
A24: Electricity | B24: ='STR Calculator'!$C$26 -> 3000 | C24: ='STR Calculator'!$C$26 -> 3000 | D24: ='STR Calculator'!$C$26 -> 3000 | E24: ='STR Calculator'!$C$26 -> 3000 | F24: ='STR Calculator'!$C$26 -> 3000 | G24: ='STR Calculator'!$C$26 -> 3000 | H24: ='STR Calculator'!$C$26 -> 3000
A25: Natural Gas | B25: ='STR Calculator'!$C$27 -> 1333.3333 | C25: ='STR Calculator'!$C$27 -> 1333.3333 | D25: ='STR Calculator'!$C$27 -> 1333.3333 | E25: ='STR Calculator'!$C$27 -> 1333.3333 | F25: ='STR Calculator'!$C$27 -> 1333.3333 | G25: ='STR Calculator'!$C$27 -> 1333.3333 | H25: ='STR Calculator'!$C$27 -> 1333.3333
A26: WIFI/Cable | B26: ='STR Calculator'!$C$28 -> 1800 | C26: ='STR Calculator'!$C$28 -> 1800 | D26: ='STR Calculator'!$C$28 -> 1800 | E26: ='STR Calculator'!$C$28 -> 1800 | F26: ='STR Calculator'!$C$28 -> 1800 | G26: ='STR Calculator'!$C$28 -> 1800 | H26: ='STR Calculator'!$C$28 -> 1800
A27: Water/Sewer | B27: ='STR Calculator'!$C$30 -> 0 | C27: ='STR Calculator'!$C$30 -> 0 | D27: ='STR Calculator'!$C$30 -> 0 | E27: ='STR Calculator'!$C$30 -> 0 | F27: ='STR Calculator'!$C$30 -> 0 | G27: ='STR Calculator'!$C$30 -> 0 | H27: ='STR Calculator'!$C$30 -> 0
A28: Pool Service | B28: ='STR Calculator'!$C$29 -> 0 | C28: ='STR Calculator'!$C$29 -> 0 | D28: ='STR Calculator'!$C$29 -> 0 | E28: ='STR Calculator'!$C$29 -> 0 | F28: ='STR Calculator'!$C$29 -> 0 | G28: ='STR Calculator'!$C$29 -> 0 | H28: ='STR Calculator'!$C$29 -> 0
A29: HOA | B29: ='STR Calculator'!$C$25 -> 0 | C29: =B29+(B29*C8) -> 0 | D29: =C29+(C29*D8) -> 0 | E29: =D29+(D29*E8) -> 0 | F29: =E29+(E29*F8) -> 0 | G29: =F29+(F29*G8) -> 0 | H29: =G29+(G29*H8) -> 0
A30: Maintenance & Repairs | B30: ='STR Calculator'!$C$31 -> 0 | C30: ='STR Calculator'!$B$5*C5 -> 5990 | D30: ='STR Calculator'!$B$5*D5 -> 5990 | E30: ='STR Calculator'!$B$5*E5 -> 5990 | F30: ='STR Calculator'!$B$5*F5 -> 5990 | G30: ='STR Calculator'!$B$5*G5 -> 5990 | H30: ='STR Calculator'!$B$5*H5 -> 5990
A31: Capex | B31: ='STR Calculator'!$C$32 -> 0 | C31: ='STR Calculator'!$C$32 -> 0 | D31: ='STR Calculator'!$C$32 -> 0 | E31: ='STR Calculator'!$C$32 -> 0 | F31: ='STR Calculator'!$C$32 -> 0 | G31: ='STR Calculator'!$C$32 -> 0 | H31: ='STR Calculator'!$C$32 -> 0
A32: City Permit | B32: ='STR Calculator'!C34 -> 300 | C32: 0 | D32: 0 | E32: 0 | F32: 0 | G32: 0 | H32: 0
A33: Incidentals (Coffee, etc) | B33: ='STR Calculator'!$C$36 -> 300 | C33: ='STR Calculator'!$C$36 -> 300 | D33: ='STR Calculator'!$C$36 -> 300 | E33: ='STR Calculator'!$C$36 -> 300 | F33: ='STR Calculator'!$C$36 -> 300 | G33: ='STR Calculator'!$C$36 -> 300 | H33: ='STR Calculator'!$C$36 -> 300
A34: Umbrella Insurance | B34: ='STR Calculator'!$C$37 -> 444 | C34: ='STR Calculator'!$C$37 -> 444 | D34: ='STR Calculator'!$C$37 -> 444 | E34: ='STR Calculator'!$C$37 -> 444 | F34: ='STR Calculator'!$C$37 -> 444 | G34: ='STR Calculator'!$C$37 -> 444 | H34: ='STR Calculator'!$C$37 -> 444
A35: Total Expenses | B35: =SUM(B20:B34) -> 34177.333 | C35: =SUM(C20:C34) -> 39963.333 | D35: =SUM(D20:D34) -> 40001.073 | E35: =SUM(E20:E34) -> 40038.185 | F35: =SUM(F20:F34) -> 40075.83 | G35: =SUM(G20:G34) -> 40114.039 | H35: =SUM(H20:H34) -> 40152.822
A37: Net Operating Income (NOI) | B37: =SUM(B16-B35) -> 57322.667 | C37: =SUM(C16-C35) -> 52451.667 | D37: =SUM(D16-D35) -> 53338.077 | E37: =SUM(E16-E35) -> 54234.356 | F37: =SUM(F16-F35) -> 55139.437 | G37: =SUM(G16-G35) -> 56053.38 | H37: =SUM(H16-H35) -> 56976.272
A39: Cash Flow
A40: NOI (Cash Available) | B40: =B37 -> 57322.667 | C40: =C37 -> 52451.667 | D40: =D37 -> 53338.077 | E40: =E37 -> 54234.356 | F40: =F37 -> 55139.437 | G40: =G37 -> 56053.38 | H40: =H37 -> 56976.272
A41: Conventional Mortgage | B41: ='STR Calculator'!$C$42 -> 41196.57 | C41: ='STR Calculator'!$C$42 -> 41196.57 | D41: ='STR Calculator'!$C$42 -> 41196.57 | E41: ='STR Calculator'!$C$42 -> 41196.57 | F41: ='STR Calculator'!$C$42 -> 41196.57 | G41: ='STR Calculator'!$C$42 -> 41196.57 | H41: ='STR Calculator'!$C$42 -> 41196.57
A42: HELOC Mortgage | B42: ='STR Calculator'!$C$41 -> 5346 | C42: ='STR Calculator'!$C$41 -> 5346 | D42: ='STR Calculator'!$C$41 -> 5346 | E42: ='STR Calculator'!$C$41 -> 5346 | F42: ='STR Calculator'!$C$41 -> 5346 | G42: ='STR Calculator'!$C$41 -> 5346 | H42: ='STR Calculator'!$C$41 -> 5346
A43: PMI if Down Payment less than 20% | B43: ='STR Calculator'!$C$43 -> 0 | C43: ='STR Calculator'!$C$43 -> 0 | D43: ='STR Calculator'!$C$43 -> 0 | E43: ='STR Calculator'!$C$43 -> 0 | F43: ='STR Calculator'!$C$43 -> 0 | G43: ='STR Calculator'!$C$43 -> 0 | H43: ='STR Calculator'!$C$43 -> 0
A44: Total Cash Flow | B44: =SUM(B40-B41-B42-B43) -> 10780.097 | C44: =SUM(C40-C41-C42-C43) -> 5909.0969 | D44: =SUM(D40-D41-D42-D43) -> 6795.5069 | E44: =SUM(E40-E41-E42-E43) -> 7691.7863 | F44: =SUM(F40-F41-F42-F43) -> 8596.8668 | G44: =SUM(G40-G41-G42-G43) -> 9510.8104 | H44: =SUM(H40-H41-H42-H43) -> 10433.702
A45: Monthly Cash Flow | B45: =B44/12 -> 898.34141 | C45: =C44/12 -> 492.42474 | D45: =D44/12 -> 566.29224 | E45: =E44/12 -> 640.98219 | F45: =F44/12 -> 716.40557 | G45: =G44/12 -> 792.56753 | H45: =H44/12 -> 869.4752
A46: DSCR | B46: =B40/SUM(B41:B43) -> 1.231618 | C46: =C40/SUM(C41:C43) -> 1.1269611 | D46: =D40/SUM(D41:D43) -> 1.1460063 | E46: =E40/SUM(E41:E43) -> 1.1652635 | F46: =F40/SUM(F41:F43) -> 1.1847098 | G46: =G40/SUM(G41:G43) -> 1.2043465 | H46: =H40/SUM(H41:H43) -> 1.2241755
A47: Equity Accrued | B47: =-CUMPRINC('STR Calculator'!$I$8/12,'STR Calculator'!$I$9*12,'STR Calculator'!$B$8,1,12,0) -> 4205.8826 | C47: =-CUMPRINC('STR Calculator'!$I$8/12,'STR Calculator'!$I$9*12,'STR Calculator'!$B$8,13,24,0) -> 4543.6697 | D47: =-CUMPRINC('STR Calculator'!$I$8/12,'STR Calculator'!$I$9*12,'STR Calculator'!$B$8,25,36,0) -> 4908.5854 | E47: =-CUMPRINC('STR Calculator'!$I$8/12,'STR Calculator'!$I$9*12,'STR Calculator'!$B$8,37,48,0) -> 5302.8086 | F47: =-CUMPRINC('STR Calculator'!$I$8/12,'STR Calculator'!$I$9*12,'STR Calculator'!$B$8,49,60,0) -> 5728.6931 | G47: =-CUMPRINC('STR Calculator'!$I$8/12,'STR Calculator'!$I$9*12,'STR Calculator'!$B$8,61,72,0) -> 6188.7816 | H47: =-CUMPRINC('STR Calculator'!$I$8/12,'STR Calculator'!$I$9*12,'STR Calculator'!$B$8,73,84,0) -> 6685.8212
A48: Appreciation | B48: =SUM(B6*'STR Calculator'!$B$5) -> 11980 | C48: =(SUM(B48)+'STR Calculator'!$B$5)*C$6 -> 12219.6 | D48: =(SUM(C48)+'STR Calculator'!$B$5)*D$6 -> 12224.392 | E48: =(SUM(D48)+'STR Calculator'!$B$5)*E$6 -> 12224.488 | F48: =(SUM(E48)+'STR Calculator'!$B$5)*F$6 -> 12224.49 | G48: =(SUM(F48)+'STR Calculator'!$B$5)*G$6 -> 12224.49 | H48: =(SUM(G48)+'STR Calculator'!$B$5)*H$6 -> 12224.49
A49: Total Return w/o Appreciation | B49: =SUM(B47+B44) -> 14985.98 | C49: =SUM(C47+C44) -> 10452.767 | D49: =SUM(D47+D44) -> 11704.092 | E49: =SUM(E47+E44) -> 12994.595 | F49: =SUM(F47+F44) -> 14325.56 | G49: =SUM(G47+G44) -> 15699.592 | H49: =SUM(H47+H44) -> 17119.524
A50: ROI w/o appreciation | B50: =B49/SUM('STR Calculator'!$B$6:$B$7) -> 0.12509165 | C50: =C49/SUM('STR Calculator'!$B$6:$B$7) -> 0.087251808 | D50: =D49/SUM('STR Calculator'!$B$6:$B$7) -> 0.097696931 | E50: =E49/SUM('STR Calculator'!$B$6:$B$7) -> 0.10846907 | F50: =F49/SUM('STR Calculator'!$B$6:$B$7) -> 0.11957896 | G50: =G49/SUM('STR Calculator'!$B$6:$B$7) -> 0.13104835 | H50: =H49/SUM('STR Calculator'!$B$6:$B$7) -> 0.14290086
A51: Total Return w/ Appreciation | B51: =SUM(B44+B47+B48) -> 26965.98 | C51: =SUM(C44+C47+C48) -> 22672.367 | D51: =SUM(D44+D47+D48) -> 23928.484 | E51: =SUM(E44+E47+E48) -> 25219.083 | F51: =SUM(F44+F47+F48) -> 26550.05 | G51: =SUM(G44+G47+G48) -> 27924.082 | H51: =SUM(H44+H47+H48) -> 29344.013
A52: Total ROI | B52: =B51/SUM('STR Calculator'!$B$6:$B$7) -> 0.22509165 | C52: =C51/SUM('STR Calculator'!$B$6:$B$7) -> 0.18925181 | D52: =D51/SUM('STR Calculator'!$B$6:$B$7) -> 0.19973693 | E52: =E51/SUM('STR Calculator'!$B$6:$B$7) -> 0.21050987 | F52: =F51/SUM('STR Calculator'!$B$6:$B$7) -> 0.22161978 | G52: =G51/SUM('STR Calculator'!$B$6:$B$7) -> 0.23308916 | H52: =H51/SUM('STR Calculator'!$B$6:$B$7) -> 0.24494168
A53: Average ROI | G53: =AVERAGE(B50:H50) -> 0.11600538
A54: Estimated Value at Year 7 | G54: ='STR Calculator'!B5+(SUM('STR 7yr IRR Financing'!B48:H48)) -> 684321.95
A55: Loan Paid Down over 7 Years | G55: =SUM(B47:H47) -> 37564.242
A56: Total returns are based on calculations of external data and is subject to change. Estimated returns are estimated, and may not factor in all scenarios or costs. REI Nation, LLC and Premier Property Management Group, LLC have offered this estimator of returns in good faith. We realize that there are alternate methods to calculate return, and that some assumptions may not be applicable for your calculations. Data provided for the calculation is the user’s responsibility. We do not make any representations or warranties of any kind on the information provided. We also disclaim any liability or responsibility for the accuracy, correctness, or completeness of any information provided. *All calculations include estimated maintenance, estimated vacancy, estimated property management fees, estimated equity accrual, estimated property taxes, estimated insurance and estimated appreciation.

Sheet Amoritization Scenario 10% DP
A1: If deciding between different Down Payment % and Interest Rates, compare Cumulative Interest Payment over duration to recoup additional Down Payment Lump Sum, to see which is better. NPV / PV/FV money calculation
C3: sqft | J3: Interest | K3: ='Interest Rate Comparison'!B3 -> 0.0825 | N3: =K3/12 -> 0.006875 | O3: r | W3: Interest | X3: ='Interest Rate Comparison'!B4 -> 0.08 | AA3: =X3/12 -> 0.0066666667 | AB3: r | AJ3: Interest | AK3: ='Interest Rate Comparison'!B5 -> 0.0775 | AN3: =AK3/12 -> 0.0064583333 | AO3: r | AW3: Interest | AX3: ='Interest Rate Comparison'!B6 -> 0.075 | BA3: =AX3/12 -> 0.00625 | BB3: r | BJ3: Interest | BK3: ='Interest Rate Comparison'!B7 -> 0.0725 | BN3: =BK3/12 -> 0.0060416667 | BO3: r | BW3: Interest | BX3: ='Interest Rate Comparison'!B8 -> 0.07 | CA3: =BX3/12 -> 0.0058333333 | CB3: r
C4: $/sqft Market Estimate | J4: Term | K4: =$L$4*12 -> 360 | L4: ='STR Calculator'!I9 -> 30 | M4: years | N4: =(1+N3)^K4 -> 11.781506 | O4: (1+r)^n | W4: Term | X4: =$L$4*12 -> 360 | Y4: 30 | Z4: years | AA4: =(1+AA3)^X4 -> 10.93573 | AB4: (1+r)^n | AJ4: Term | AK4: =$L$4*12 -> 360 | AL4: 30 | AM4: years | AN4: =(1+AN3)^AK4 -> 10.150514 | AO4: (1+r)^n | AW4: Term | AX4: =$L$4*12 -> 360 | AY4: 30 | AZ4: years | BA4: =(1+BA3)^AX4 -> 9.4215339 | BB4: (1+r)^n | BJ4: Term | BK4: =$L$4*12 -> 360 | BL4: 30 | BM4: years | BN4: =(1+BN3)^BK4 -> 8.744772 | BO4: (1+r)^n | BW4: Term | BX4: =$L$4*12 -> 360 | BY4: 30 | BZ4: years | CA4: =(1+CA3)^BX4 -> 8.1164975 | CB4: (1+r)^n
A5: Original Purchase Price | B5: ='STR Calculator'!B5 -> 599000 | C5: =B5/B3 -> #DIV/0! | D5: sqft | J5: Monthly Payment | W5: Monthly Payment | AJ5: Monthly Payment | AW5: Monthly Payment | BJ5: Monthly Payment | BW5: Monthly Payment
A6: Down Payment | B6: 0.1
A7: Current Loan Balance | B7: =B5-(B5*B6) -> 539100 | C7: as of 11/13/22 | J7: paymentNumber | K7: paymentDate | L7: startingBalance | M7: Monthly Payment | N7: principalPayment | O7: Principle Pay Down | P7: interestPayment | Q7: Interest Percent | R7: cumulativePrincipal | S7: cumulativeInterest | T7: endingBalance | U7: Total Paid End of Loan | W7: paymentNumber | X7: paymentDate | Y7: startingBalance | Z7: Monthly Payment | AA7: principalPayment | AB7: Principle Pay Down | AC7: interestPayment | AD7: Interest Percent | AE7: cumulativePrincipal | AF7: cumulativeInterest | AG7: endingBalance | AH7: Total Paid End of Loan | AJ7: paymentNumber | AK7: paymentDate | AL7: startingBalance | AM7: Monthly Payment | AN7: principalPayment | AO7: Principle Pay Down | AP7: interestPayment | AQ7: Interest Percent | AR7: cumulativePrincipal | AS7: cumulativeInterest | AT7: endingBalance | AU7: Total Paid End of Loan | AW7: paymentNumber | AX7: paymentDate | AY7: startingBalance | AZ7: Monthly Payment | BA7: principalPayment | BB7: Principle Pay Down | BC7: interestPayment | BD7: Interest Percent | BE7: cumulativePrincipal | BF7: cumulativeInterest | BG7: endingBalance | BH7: Total Paid End of Loan | BJ7: paymentNumber | BK7: paymentDate | BL7: startingBalance | BM7: Monthly Payment | BN7: principalPayment | BO7: Principle Pay Down | BP7: interestPayment | BQ7: Interest Percent | BR7: cumulativePrincipal | BS7: cumulativeInterest | BT7: endingBalance | BU7: Total Paid End of Loan | BW7: paymentNumber | BX7: paymentDate | BY7: startingBalance | BZ7: Monthly Payment | CA7: principalPayment | CB7: Principle Pay Down | CC7: interestPayment | CD7: Interest Percent | CE7: cumulativePrincipal | CF7: cumulativeInterest | CG7: endingBalance | CH7: Total Paid End of Loan
A8: Current Equity | B8: =B5-B7 -> 59900 | J8: 1 | K8: 44866 | L8: ='Amoritization Scenario 10% DP'!$B$7 -> 539100 | M8: =$L$8/((($N$4)-1)/($N$3*$N$4)) -> 4050.0783 | N8: =M8-P8 -> 343.76576 | O8: =(N8/L8)*12 -> 0.0076519925 | P8: =L8*($K$3/12) -> 3706.3125 | Q8: =(P8/L8)*12 -> 0.0825 | R8: =N8 -> 343.76576 | S8: =P8 -> 3706.3125 | T8: =L8-N8 -> 538756.23 | U8: =R8+S8 -> 4050.0783 | W8: 1 | X8: 44866 | Y8: ='Amoritization Scenario 10% DP'!$B$7 -> 539100 | Z8: =$Y$8/((($AA$4)-1)/($AA$3*$AA$4)) -> 3955.7248 | AA8: =Z8-AC8 -> 361.72482 | AB8: =(AA8/Y8)*12 -> 0.0080517489 | AC8: =Y8*($X$3/12) -> 3594 | AD8: =(AC8/Y8)*12 -> 0.08 | AE8: =AA8 -> 361.72482 | AF8: =AC8 -> 3594 | AG8: =Y8-AA8 -> 538738.28 | AH8: =AE8+AF8 -> 3955.7248 | AJ8: 1 | AK8: 44866 | AL8: ='Amoritization Scenario 10% DP'!$B$7 -> 539100 | AM8: =$AL$8/((($AN$4)-1)/($AN$3*$AN$4)) -> 3862.1784 | AN8: =AM8-AP8 -> 380.49092 | AO8: =(AN8/AL8)*12 -> 0.0084694695 | AP8: =AL8*($AK$3/12) -> 3481.6875 | AQ8: =(AP8/AL8)*12 -> 0.0775 | AR8: =AN8 -> 380.49092 | AS8: =AP8 -> 3481.6875 | AT8: =AL8-AN8 -> 538719.51 | AU8: =AR8+AS8 -> 3862.1784 | AW8: 1 | AX8: 44866 | AY8: ='Amoritization Scenario 10% DP'!$B$7 -> 539100 | AZ8: =$AY$8/((($BA$4)-1)/($BA$3*$BA$4)) -> 3769.4654 | BA8: =AZ8-BC8 -> 400.09042 | BB8: =(BA8/AY8)*12 -> 0.008905741 | BC8: =AY8*($AX$3/12) -> 3369.375 | BD8: =(BC8/AY8)*12 -> 0.075 | BE8: =BA8 -> 400.09042 | BF8: =BC8 -> 3369.375 | BG8: =AY8-BA8 -> 538699.91 | BH8: =BE8+BF8 -> 3769.4654 | BJ8: 1 | BK8: 44866 | BL8: ='Amoritization Scenario 10% DP'!$B$7 -> 539100 | BM8: =$BL$8/((($BN$4)-1)/($BN$3*$BN$4)) -> 3677.6123 | BN8: =BM8-BP8 -> 420.54983 | BO8: =(BN8/BL8)*12 -> 0.0093611536 | BP8: =BL8*($BK$3/12) -> 3257.0625 | BQ8: =(BP8/BL8)*12 -> 0.0725 | BR8: =BN8 -> 420.54983 | BS8: =BP8 -> 3257.0625 | BT8: =BL8-BN8 -> 538679.45 | BU8: =BR8+BS8 -> 3677.6123 | BW8: 1 | BX8: 44866 | BY8: ='Amoritization Scenario 10% DP'!$B$7 -> 539100 | BZ8: =$BY$8/((($CA$4)-1)/($CA$3*$CA$4)) -> 3586.6458 | CA8: =BZ8-CC8 -> 441.89575 | CB8: =(CA8/BY8)*12 -> 0.0098362994 | CC8: =BY8*($BX$3/12) -> 3144.75 | CD8: =(CC8/BY8)*12 -> 0.07 | CE8: =CA8 -> 441.89575 | CF8: =CC8 -> 3144.75 | CG8: =BY8-CA8 -> 538658.1 | CH8: =CE8+CF8 -> 3586.6458
J9: 2 | K9: 44896 | L9: =T8 -> 538756.23 | M9: =$L$8/((($N$4)-1)/($N$3*$N$4)) -> 4050.0783 | N9: =M9-P9 -> 346.12915 | O9: =(N9/L9)*12 -> 0.007709516 | P9: =L9*($K$3/12) -> 3703.9491 | Q9: =(P9/L9)*12 -> 0.0825 | R9: =R8+N9 -> 689.89491 | S9: =S8+P9 -> 7410.2616 | T9: =L9-N9 -> 538410.11 | U9: =R9+S9 -> 8100.1565 | W9: 2 | X9: 44896 | Y9: =AG8 -> 538738.28 | Z9: =Z8 -> 3955.7248 | AA9: =Z9-AC9 -> 364.13632 | AB9: =(AA9/Y9)*12 -> 0.0081108694 | AC9: =Y9*($X$3/12) -> 3591.5885 | AD9: =(AC9/Y9)*12 -> 0.08 | AE9: =AE8+AA9 -> 725.86113 | AF9: =AF8+AC9 -> 7185.5885 | AG9: =Y9-AA9 -> 538374.14 | AH9: =AE9+AF9 -> 7911.4496 | AJ9: 2 | AK9: 44896 | AL9: =AT8 -> 538719.51 | AM9: =AM8 -> 3862.1784 | AN9: =AM9-AP9 -> 382.94825 | AO9: =(AN9/AL9)*12 -> 0.0085301886 | AP9: =AL9*($AK$3/12) -> 3479.2302 | AQ9: =(AP9/AL9)*12 -> 0.0775 | AR9: =AR8+AN9 -> 763.43917 | AS9: =AS8+AP9 -> 6960.9177 | AT9: =AL9-AN9 -> 538336.56 | AU9: =AR9+AS9 -> 7724.3568 | AW9: 2 | AX9: 44896 | AY9: =BG8 -> 538699.91 | AZ9: =AZ8 -> 3769.4654 | BA9: =AZ9-BC9 -> 402.59098 | BB9: =(BA9/AY9)*12 -> 0.0089680575 | BC9: =AY9*($AX$3/12) -> 3366.8744 | BD9: =(BC9/AY9)*12 -> 0.075 | BE9: =BE8+BA9 -> 802.6814 | BF9: =BF8+BC9 -> 6736.2494 | BG9: =AY9-BA9 -> 538297.32 | BH9: =BE9+BF9 -> 7538.9308 | BJ9: 2 | BK9: 44896 | BL9: =BT8 -> 538679.45 | BM9: =BM8 -> 3677.6123 | BN9: =BM9-BP9 -> 423.09065 | BO9: =(BN9/BL9)*12 -> 0.009425063 | BP9: =BL9*($BK$3/12) -> 3254.5217 | BQ9: =(BP9/BL9)*12 -> 0.0725 | BR9: =BR8+BN9 -> 843.64047 | BS9: =BS8+BP9 -> 6511.5842 | BT9: =BL9-BN9 -> 538256.36 | BU9: =BR9+BS9 -> 7355.2247 | BW9: 2 | BX9: 44896 | BY9: =CG8 -> 538658.1 | BZ9: =BZ8 -> 3586.6458 | CA9: =BZ9-CC9 -> 444.47348 | CB9: =(CA9/BY9)*12 -> 0.0099017943 | CC9: =BY9*($BX$3/12) -> 3142.1723 | CD9: =(CC9/BY9)*12 -> 0.07 | CE9: =CE8+CA9 -> 886.36923 | CF9: =CF8+CC9 -> 6286.9223 | CG9: =BY9-CA9 -> 538213.63 | CH9: =CE9+CF9 -> 7173.2915
A10: Year | B10: ="Cum Interest @ "&K3&"%" -> Cum Interest @ 0.0825% | C10: ="Cum Interest @ "&X3&"%" -> Cum Interest @ 0.08% | D10: ="Cum Interest @ "&AK3&"%" -> Cum Interest @ 0.0775% | E10: ="Cum Interest @ "&AX3&"%" -> Cum Interest @ 0.075% | F10: ="Cum Interest @ "&BK3&"%" -> Cum Interest @ 0.0725% | G10: ="Cum Interest @ "&BX3&"%" -> Cum Interest @ 0.07% | J10: 3 | K10: 44927 | L10: =T9 -> 538410.11 | M10: =$L$8/((($N$4)-1)/($N$3*$N$4)) -> 4050.0783 | N10: =M10-P10 -> 348.50879 | O10: =(N10/L10)*12 -> 0.0077675093 | P10: =L10*($K$3/12) -> 3701.5695 | Q10: =(P10/L10)*12 -> 0.0825 | R10: =R9+N10 -> 1038.4037 | S10: =S9+P10 -> 11111.831 | T10: =L10-N10 -> 538061.6 | U10: =R10+S10 -> 12150.235 | W10: 3 | X10: 44927 | Y10: =AG9 -> 538374.14 | Z10: =Z9 -> 3955.7248 | AA10: =Z10-AC10 -> 366.56389 | AB10: =(AA10/Y10)*12 -> 0.0081704643 | AC10: =Y10*($X$3/12) -> 3589.1609 | AD10: =(AC10/Y10)*12 -> 0.08 | AE10: =AE9+AA10 -> 1092.425 | AF10: =AF9+AC10 -> 10774.749 | AG10: =Y10-AA10 -> 538007.57 | AH10: =AE10+AF10 -> 11867.174 | AJ10: 3 | AK10: 44927 | AL10: =AT9 -> 538336.56 | AM10: =AM9 -> 3862.1784 | AN10: =AM10-AP10 -> 385.42146 | AO10: =(AN10/AL10)*12 -> 0.0085913866 | AP10: =AL10*($AK$3/12) -> 3476.757 | AQ10: =(AP10/AL10)*12 -> 0.0775 | AR10: =AR9+AN10 -> 1148.8606 | AS10: =AS9+AP10 -> 10437.675 | AT10: =AL10-AN10 -> 537951.14 | AU10: =AR10+AS10 -> 11586.535 | AW10: 3 | AX10: 44927 | AY10: =BG9 -> 538297.32 | AZ10: =AZ9 -> 3769.4654 | BA10: =AZ10-BC10 -> 405.10717 | BB10: =(BA10/AY10)*12 -> 0.009030857 | BC10: =AY10*($AX$3/12) -> 3364.3582 | BD10: =(BC10/AY10)*12 -> 0.075 | BE10: =BE9+BA10 -> 1207.7886 | BF10: =BF9+BC10 -> 10100.608 | BG10: =AY10-BA10 -> 537892.21 | BH10: =BE10+BF10 -> 11308.396 | BJ10: 3 | BK10: 44927 | BL10: =BT9 -> 538256.36 | BM10: =BM9 -> 3677.6123 | BN10: =BM10-BP10 -> 425.64682 | BO10: =(BN10/BL10)*12 -> 0.0094894594 | BP10: =BL10*($BK$3/12) -> 3251.9655 | BQ10: =(BP10/BL10)*12 -> 0.0725 | BR10: =BR9+BN10 -> 1269.2873 | BS10: =BS9+BP10 -> 9763.5497 | BT10: =BL10-BN10 -> 537830.71 | BU10: =BR10+BS10 -> 11032.837 | BW10: 3 | BX10: 44927 | BY10: =CG9 -> 538213.63 | BZ10: =BZ9 -> 3586.6458 | CA10: =BZ10-CC10 -> 447.06624 | CB10: =(CA10/BY10)*12 -> 0.0099677796 | CC10: =BY10*($BX$3/12) -> 3139.5795 | CD10: =(CC10/BY10)*12 -> 0.07 | CE10: =CE9+CA10 -> 1333.4355 | CF10: =CF9+CC10 -> 9426.5018 | CG10: =BY10-CA10 -> 537766.56 | CH10: =CE10+CF10 -> 10759.937
A11: 1 | B11: =VLOOKUP($A$11*12,$J$7:$U$367,10) -> 44316.136 | C11: =VLOOKUP(A11*12,$W$7:$AH$367,10) -> 42965.251 | D11: =VLOOKUP(A11*12,$AJ$7:$AU$367,10) -> 41614.523 | E11: =VLOOKUP(A11*12,$AW$7:$BH$367,10) -> 40263.976 | F11: =VLOOKUP(A11*12,$BJ$7:$BU$367,10) -> 38913.632 | G11: =VLOOKUP(A11*12,$BW$7:$CH$367,10) -> 37563.518 | J11: 4 | K11: 44958 | L11: =T10 -> 538061.6 | M11: =$L$8/((($N$4)-1)/($N$3*$N$4)) -> 4050.0783 | N11: =M11-P11 -> 350.90479 | O11: =(N11/L11)*12 -> 0.0078259766 | P11: =L11*($K$3/12) -> 3699.1735 | Q11: =(P11/L11)*12 -> 0.0825 | R11: =R10+N11 -> 1389.3085 | S11: =S10+P11 -> 14811.005 | T11: =L11-N11 -> 537710.69 | U11: =R11+S11 -> 16200.313 | W11: 4 | X11: 44958 | Y11: =AG10 -> 538007.57 | Z11: =Z10 -> 3955.7248 | AA11: =Z11-AC11 -> 369.00765 | AB11: =(AA11/Y11)*12 -> 0.008230538 | AC11: =Y11*($X$3/12) -> 3586.7172 | AD11: =(AC11/Y11)*12 -> 0.08 | AE11: =AE10+AA11 -> 1461.4327 | AF11: =AF10+AC11 -> 14361.467 | AG11: =Y11-AA11 -> 537638.57 | AH11: =AE11+AF11 -> 15822.899 | AJ11: 4 | AK11: 44958 | AL11: =AT10 -> 537951.14 | AM11: =AM10 -> 3862.1784 | AN11: =AM11-AP11 -> 387.91064 | AO11: =(AN11/AL11)*12 -> 0.0086530678 | AP11: =AL11*($AK$3/12) -> 3474.2678 | AQ11: =(AP11/AL11)*12 -> 0.0775 | AR11: =AR10+AN11 -> 1536.7713 | AS11: =AS10+AP11 -> 13911.942 | AT11: =AL11-AN11 -> 537563.23 | AU11: =AR11+AS11 -> 15448.714 | AW11: 4 | AX11: 44958 | AY11: =BG10 -> 537892.21 | AZ11: =AZ10 -> 3769.4654 | BA11: =AZ11-BC11 -> 407.63909 | BB11: =(BA11/AY11)*12 -> 0.0090941438 | BC11: =AY11*($AX$3/12) -> 3361.8263 | BD11: =(BC11/AY11)*12 -> 0.075 | BE11: =BE10+BA11 -> 1615.4277 | BF11: =BF10+BC11 -> 13462.434 | BG11: =AY11-BA11 -> 537484.57 | BH11: =BE11+BF11 -> 15077.862 | BJ11: 4 | BK11: 44958 | BL11: =BT10 -> 537830.71 | BM11: =BM10 -> 3677.6123 | BN11: =BM11-BP11 -> 428.21844 | BO11: =(BN11/BL11)*12 -> 0.009554347 | BP11: =BL11*($BK$3/12) -> 3249.3939 | BQ11: =(BP11/BL11)*12 -> 0.0725 | BR11: =BR10+BN11 -> 1697.5057 | BS11: =BS10+BP11 -> 13012.944 | BT11: =BL11-BN11 -> 537402.49 | BU11: =BR11+BS11 -> 14710.449 | BW11: 4 | BX11: 44958 | BY11: =CG10 -> 537766.56 | BZ11: =BZ10 -> 3586.6458 | CA11: =BZ11-CC11 -> 449.67413 | CB11: =(CA11/BY11)*12 -> 0.01003426 | CC11: =BY11*($BX$3/12) -> 3136.9716 | CD11: =(CC11/BY11)*12 -> 0.07 | CE11: =CE10+CA11 -> 1783.1096 | CF11: =CF10+CC11 -> 12563.473 | CG11: =BY11-CA11 -> 537316.89 | CH11: =CE11+CF11 -> 14346.583
A12: =A11+1 -> 2 | B12: =VLOOKUP(A12*12,$J$7:$U$367,10) -> 88265.098 | C12: =VLOOKUP(A12*12,$W$7:$AH$367,10) -> 85556.717 | D12: =VLOOKUP(A12*12,$AJ$7:$AU$367,10) -> 82849.036 | E12: =VLOOKUP(A12*12,$AW$7:$BH$367,10) -> 80142.147 | F12: =VLOOKUP(A12*12,$BJ$7:$BU$367,10) -> 77436.153 | G12: =VLOOKUP(A12*12,$BW$7:$CH$367,10) -> 74731.159 | J12: 5 | K12: 44986 | L12: =T11 -> 537710.69 | M12: =$L$8/((($N$4)-1)/($N$3*$N$4)) -> 4050.0783 | N12: =M12-P12 -> 353.31726 | O12: =(N12/L12)*12 -> 0.0078849224 | P12: =L12*($K$3/12) -> 3696.761 | Q12: =(P12/L12)*12 -> 0.0825 | R12: =R11+N12 -> 1742.6258 | S12: =S11+P12 -> 18507.766 | T12: =L12-N12 -> 537357.37 | U12: =R12+S12 -> 20250.391 | W12: 5 | X12: 44986 | Y12: =AG11 -> 537638.57 | Z12: =Z11 -> 3955.7248 | AA12: =Z12-AC12 -> 371.4677 | AB12: =(AA12/Y12)*12 -> 0.008291095 | AC12: =Y12*($X$3/12) -> 3584.2571 | AD12: =(AC12/Y12)*12 -> 0.08 | AE12: =AE11+AA12 -> 1832.9004 | AF12: =AF11+AC12 -> 17945.724 | AG12: =Y12-AA12 -> 537267.1 | AH12: =AE12+AF12 -> 19778.624 | AJ12: 5 | AK12: 44986 | AL12: =AT11 -> 537563.23 | AM12: =AM11 -> 3862.1784 | AN12: =AM12-AP12 -> 390.4159 | AO12: =(AN12/AL12)*12 -> 0.0087152367 | AP12: =AL12*($AK$3/12) -> 3471.7625 | AQ12: =(AP12/AL12)*12 -> 0.0775 | AR12: =AR11+AN12 -> 1927.1872 | AS12: =AS11+AP12 -> 17383.705 | AT12: =AL12-AN12 -> 537172.81 | AU12: =AR12+AS12 -> 19310.892 | AW12: 5 | AX12: 44986 | AY12: =BG11 -> 537484.57 | AZ12: =AZ11 -> 3769.4654 | BA12: =AZ12-BC12 -> 410.18684 | BB12: =(BA12/AY12)*12 -> 0.0091579225 | BC12: =AY12*($AX$3/12) -> 3359.2786 | BD12: =(BC12/AY12)*12 -> 0.075 | BE12: =BE11+BA12 -> 2025.6145 | BF12: =BF11+BC12 -> 16821.713 | BG12: =AY12-BA12 -> 537074.39 | BH12: =BE12+BF12 -> 18847.327 | BJ12: 5 | BK12: 44986 | BL12: =BT11 -> 537402.49 | BM12: =BM11 -> 3677.6123 | BN12: =BM12-BP12 -> 430.80559 | BO12: =(BN12/BL12)*12 -> 0.0096197303 | BP12: =BL12*($BK$3/12) -> 3246.8067 | BQ12: =(BP12/BL12)*12 -> 0.0725 | BR12: =BR11+BN12 -> 2128.3113 | BS12: =BS11+BP12 -> 16259.75 | BT12: =BL12-BN12 -> 536971.69 | BU12: =BR12+BS12 -> 18388.062 | BW12: 5 | BX12: 44986 | BY12: =CG11 -> 537316.89 | BZ12: =BZ11 -> 3586.6458 | CA12: =BZ12-CC12 -> 452.29722 | CB12: =(CA12/BY12)*12 -> 0.01010124 | CC12: =BY12*($BX$3/12) -> 3134.3485 | CD12: =(CC12/BY12)*12 -> 0.07 | CE12: =CE11+CA12 -> 2235.4068 | CF12: =CF11+CC12 -> 15697.822 | CG12: =BY12-CA12 -> 536864.59 | CH12: =CE12+CF12 -> 17933.229
A13: =A12+1 -> 3 | B13: =VLOOKUP(A13*12,$J$7:$U$367,10) -> 131815.42 | C13: =VLOOKUP(A13*12,$W$7:$AH$367,10) -> 127743.38 | D13: =VLOOKUP(A13*12,$AJ$7:$AU$367,10) -> 123673.02 | E13: =VLOOKUP(A13*12,$AW$7:$BH$367,10) -> 119604.56 | F13: =VLOOKUP(A13*12,$BJ$7:$BU$367,10) -> 115538.25 | G13: =VLOOKUP(A13*12,$BW$7:$CH$367,10) -> 111474.31 | J13: 6 | K13: 45017 | L13: =T12 -> 537357.37 | M13: =$L$8/((($N$4)-1)/($N$3*$N$4)) -> 4050.0783 | N13: =M13-P13 -> 355.74631 | O13: =(N13/L13)*12 -> 0.0079443513 | P13: =L13*($K$3/12) -> 3694.3319 | Q13: =(P13/L13)*12 -> 0.0825 | R13: =R12+N13 -> 2098.3721 | S13: =S12+P13 -> 22202.098 | T13: =L13-N13 -> 537001.63 | U13: =R13+S13 -> 24300.47 | W13: 6 | X13: 45017 | Y13: =AG12 -> 537267.1 | Z13: =Z12 -> 3955.7248 | AA13: =Z13-AC13 -> 373.94415 | AB13: =(AA13/Y13)*12 -> 0.0083521396 | AC13: =Y13*($X$3/12) -> 3581.7807 | AD13: =(AC13/Y13)*12 -> 0.08 | AE13: =AE12+AA13 -> 2206.8445 | AF13: =AF12+AC13 -> 21527.504 | AG13: =Y13-AA13 -> 536893.16 | AH13: =AE13+AF13 -> 23734.349 | AJ13: 6 | AK13: 45017 | AL13: =AT12 -> 537172.81 | AM13: =AM12 -> 3862.1784 | AN13: =AM13-AP13 -> 392.93733 | AO13: =(AN13/AL13)*12 -> 0.0087778977 | AP13: =AL13*($AK$3/12) -> 3469.2411 | AQ13: =(AP13/AL13)*12 -> 0.0775 | AR13: =AR12+AN13 -> 2320.1245 | AS13: =AS12+AP13 -> 20852.946 | AT13: =AL13-AN13 -> 536779.88 | AU13: =AR13+AS13 -> 23173.07 | AW13: 6 | AX13: 45017 | AY13: =BG12 -> 537074.39 | AZ13: =AZ12 -> 3769.4654 | BA13: =AZ13-BC13 -> 412.75051 | BB13: =(BA13/AY13)*12 -> 0.0092221975 | BC13: =AY13*($AX$3/12) -> 3356.7149 | BD13: =(BC13/AY13)*12 -> 0.075 | BE13: =BE12+BA13 -> 2438.365 | BF13: =BF12+BC13 -> 20178.427 | BG13: =AY13-BA13 -> 536661.63 | BH13: =BE13+BF13 -> 22616.792 | BJ13: 6 | BK13: 45017 | BL13: =BT12 -> 536971.69 | BM13: =BM12 -> 3677.6123 | BN13: =BM13-BP13 -> 433.40837 | BO13: =(BN13/BL13)*12 -> 0.009685614 | BP13: =BL13*($BK$3/12) -> 3244.204 | BQ13: =(BP13/BL13)*12 -> 0.0725 | BR13: =BR12+BN13 -> 2561.7197 | BS13: =BS12+BP13 -> 19503.954 | BT13: =BL13-BN13 -> 536538.28 | BU13: =BR13+BS13 -> 22065.674 | BW13: 6 | BX13: 45017 | BY13: =CG12 -> 536864.59 | BZ13: =BZ12 -> 3586.6458 | CA13: =BZ13-CC13 -> 454.93562 | CB13: =(CA13/BY13)*12 -> 0.010168723 | CC13: =BY13*($BX$3/12) -> 3131.7101 | CD13: =(CC13/BY13)*12 -> 0.07 | CE13: =CE12+CA13 -> 2690.3424 | CF13: =CF12+CC13 -> 18829.532 | CG13: =BY13-CA13 -> 536409.66 | CH13: =CE13+CF13 -> 21519.875
A14: =A13+1 -> 4 | B14: =VLOOKUP(A14*12,$J$7:$U$367,10) -> 174932.95 | C14: =VLOOKUP(A14*12,$W$7:$AH$367,10) -> 169491.63 | D14: =VLOOKUP(A14*12,$AJ$7:$AU$367,10) -> 164053.5 | E14: =VLOOKUP(A14*12,$AW$7:$BH$367,10) -> 158618.95 | F14: =VLOOKUP(A14*12,$BJ$7:$BU$367,10) -> 153188.4 | G14: =VLOOKUP(A14*12,$BW$7:$CH$367,10) -> 147762.27 | J14: 7 | K14: 45047 | L14: =T13 -> 537001.63 | M14: =$L$8/((($N$4)-1)/($N$3*$N$4)) -> 4050.0783 | N14: =M14-P14 -> 358.19207 | O14: =(N14/L14)*12 -> 0.0080042678 | P14: =L14*($K$3/12) -> 3691.8862 | Q14: =(P14/L14)*12 -> 0.0825 | R14: =R13+N14 -> 2456.5641 | S14: =S13+P14 -> 25893.984 | T14: =L14-N14 -> 536643.44 | U14: =R14+S14 -> 28350.548 | W14: 7 | X14: 45047 | Y14: =AG13 -> 536893.16 | Z14: =Z13 -> 3955.7248 | AA14: =Z14-AC14 -> 376.43711 | AB14: =(AA14/Y14)*12 -> 0.0084136766 | AC14: =Y14*($X$3/12) -> 3579.2877 | AD14: =(AC14/Y14)*12 -> 0.08 | AE14: =AE13+AA14 -> 2583.2816 | AF14: =AF13+AC14 -> 25106.792 | AG14: =Y14-AA14 -> 536516.72 | AH14: =AE14+AF14 -> 27690.074 | AJ14: 7 | AK14: 45047 | AL14: =AT13 -> 536779.88 | AM14: =AM13 -> 3862.1784 | AN14: =AM14-AP14 -> 395.47505 | AO14: =(AN14/AL14)*12 -> 0.0088410554 | AP14: =AL14*($AK$3/12) -> 3466.7034 | AQ14: =(AP14/AL14)*12 -> 0.0775 | AR14: =AR13+AN14 -> 2715.5996 | AS14: =AS13+AP14 -> 24319.649 | AT14: =AL14-AN14 -> 536384.4 | AU14: =AR14+AS14 -> 27035.249 | AW14: 7 | AX14: 45047 | AY14: =BG13 -> 536661.63 | AZ14: =AZ13 -> 3769.4654 | BA14: =AZ14-BC14 -> 415.3302 | BB14: =(BA14/AY14)*12 -> 0.0092869735 | BC14: =AY14*($AX$3/12) -> 3354.1352 | BD14: =(BC14/AY14)*12 -> 0.075 | BE14: =BE13+BA14 -> 2853.6952 | BF14: =BF13+BC14 -> 23532.563 | BG14: =AY14-BA14 -> 536246.3 | BH14: =BE14+BF14 -> 26386.258 | BJ14: 7 | BK14: 45047 | BL14: =BT13 -> 536538.28 | BM14: =BM13 -> 3677.6123 | BN14: =BM14-BP14 -> 436.02688 | BO14: =(BN14/BL14)*12 -> 0.0097520024 | BP14: =BL14*($BK$3/12) -> 3241.5854 | BQ14: =(BP14/BL14)*12 -> 0.0725 | BR14: =BR13+BN14 -> 2997.7466 | BS14: =BS13+BP14 -> 22745.54 | BT14: =BL14-BN14 -> 536102.25 | BU14: =BR14+BS14 -> 25743.286 | BW14: 7 | BX14: 45047 | BY14: =CG13 -> 536409.66 | BZ14: =BZ13 -> 3586.6458 | CA14: =BZ14-CC14 -> 457.58942 | CB14: =(CA14/BY14)*12 -> 0.010236715 | CC14: =BY14*($BX$3/12) -> 3129.0563 | CD14: =(CC14/BY14)*12 -> 0.07 | CE14: =CE13+CA14 -> 3147.9319 | CF14: =CF13+CC14 -> 21958.588 | CG14: =BY14-CA14 -> 535952.07 | CH14: =CE14+CF14 -> 25106.52
A15: =A14+1 -> 5 | B15: =VLOOKUP(A15*12,$J$7:$U$367,10) -> 217580.59 | C15: =VLOOKUP(A15*12,$W$7:$AH$367,10) -> 210765.09 | D15: =VLOOKUP(A15*12,$AJ$7:$AU$367,10) -> 203954.86 | E15: =VLOOKUP(A15*12,$AW$7:$BH$367,10) -> 197150.53 | F15: =VLOOKUP(A15*12,$BJ$7:$BU$367,10) -> 190352.73 | G15: =VLOOKUP(A15*12,$BW$7:$CH$367,10) -> 183562.15 | J15: 8 | K15: 45078 | L15: =T14 -> 536643.44 | M15: =$L$8/((($N$4)-1)/($N$3*$N$4)) -> 4050.0783 | N15: =M15-P15 -> 360.65464 | O15: =(N15/L15)*12 -> 0.0080646765 | P15: =L15*($K$3/12) -> 3689.4236 | Q15: =(P15/L15)*12 -> 0.0825 | R15: =R14+N15 -> 2817.2188 | S15: =S14+P15 -> 29583.407 | T15: =L15-N15 -> 536282.78 | U15: =R15+S15 -> 32400.626 | W15: 8 | X15: 45078 | Y15: =AG14 -> 536516.72 | Z15: =Z14 -> 3955.7248 | AA15: =Z15-AC15 -> 378.9467 | AB15: =(AA15/Y15)*12 -> 0.0084757104 | AC15: =Y15*($X$3/12) -> 3576.7781 | AD15: =(AC15/Y15)*12 -> 0.08 | AE15: =AE14+AA15 -> 2962.2283 | AF15: =AF14+AC15 -> 28683.57 | AG15: =Y15-AA15 -> 536137.77 | AH15: =AE15+AF15 -> 31645.799 | AJ15: 8 | AK15: 45078 | AL15: =AT14 -> 536384.4 | AM15: =AM14 -> 3862.1784 | AN15: =AM15-AP15 -> 398.02916 | AO15: =(AN15/AL15)*12 -> 0.0089047145 | AP15: =AL15*($AK$3/12) -> 3464.1493 | AQ15: =(AP15/AL15)*12 -> 0.0775 | AR15: =AR14+AN15 -> 3113.6287 | AS15: =AS14+AP15 -> 27783.799 | AT15: =AL15-AN15 -> 535986.37 | AU15: =AR15+AS15 -> 30897.427 | AW15: 8 | AX15: 45078 | AY15: =BG14 -> 536246.3 | AZ15: =AZ14 -> 3769.4654 | BA15: =AZ15-BC15 -> 417.92601 | BB15: =(BA15/AY15)*12 -> 0.0093522549 | BC15: =AY15*($AX$3/12) -> 3351.5394 | BD15: =(BC15/AY15)*12 -> 0.075 | BE15: =BE14+BA15 -> 3271.6212 | BF15: =BF14+BC15 -> 26884.102 | BG15: =AY15-BA15 -> 535828.38 | BH15: =BE15+BF15 -> 30155.723 | BJ15: 8 | BK15: 45078 | BL15: =BT14 -> 536102.25 | BM15: =BM14 -> 3677.6123 | BN15: =BM15-BP15 -> 438.66121 | BO15: =(BN15/BL15)*12 -> 0.0098189002 | BP15: =BL15*($BK$3/12) -> 3238.9511 | BQ15: =(BP15/BL15)*12 -> 0.0725 | BR15: =BR14+BN15 -> 3436.4078 | BS15: =BS14+BP15 -> 25984.491 | BT15: =BL15-BN15 -> 535663.59 | BU15: =BR15+BS15 -> 29420.899 | BW15: 8 | BX15: 45078 | BY15: =CG14 -> 535952.07 | BZ15: =BZ14 -> 3586.6458 | CA15: =BZ15-CC15 -> 460.25869 | CB15: =(CA15/BY15)*12 -> 0.010305221 | CC15: =BY15*($BX$3/12) -> 3126.3871 | CD15: =(CC15/BY15)*12 -> 0.07 | CE15: =CE14+CA15 -> 3608.1905 | CF15: =CF14+CC15 -> 25084.975 | CG15: =BY15-CA15 -> 535491.81 | CH15: =CE15+CF15 -> 28693.166
A16: =A15+1 -> 6 | B16: =VLOOKUP(A16*12,$J$7:$U$367,10) -> 259718.08 | C16: =VLOOKUP(A16*12,$W$7:$AH$367,10) -> 251524.34 | D16: =VLOOKUP(A16*12,$AJ$7:$AU$367,10) -> 243338.62 | E16: =VLOOKUP(A16*12,$AW$7:$BH$367,10) -> 235161.8 | F16: =VLOOKUP(A16*12,$BJ$7:$BU$367,10) -> 226994.82 | G16: =VLOOKUP(A16*12,$BW$7:$CH$367,10) -> 218838.65 | J16: 9 | K16: 45108 | L16: =T15 -> 536282.78 | M16: =$L$8/((($N$4)-1)/($N$3*$N$4)) -> 4050.0783 | N16: =M16-P16 -> 363.13414 | O16: =(N16/L16)*12 -> 0.008125582 | P16: =L16*($K$3/12) -> 3686.9441 | Q16: =(P16/L16)*12 -> 0.0825 | R16: =R15+N16 -> 3180.3529 | S16: =S15+P16 -> 33270.351 | T16: =L16-N16 -> 535919.65 | U16: =R16+S16 -> 36450.704 | W16: 9 | X16: 45108 | Y16: =AG15 -> 536137.77 | Z16: =Z15 -> 3955.7248 | AA16: =Z16-AC16 -> 381.47301 | AB16: =(AA16/Y16)*12 -> 0.0085382458 | AC16: =Y16*($X$3/12) -> 3574.2518 | AD16: =(AC16/Y16)*12 -> 0.08 | AE16: =AE15+AA16 -> 3343.7014 | AF16: =AF15+AC16 -> 32257.822 | AG16: =Y16-AA16 -> 535756.3 | AH16: =AE16+AF16 -> 35601.523 | AJ16: 9 | AK16: 45108 | AL16: =AT15 -> 535986.37 | AM16: =AM15 -> 3862.1784 | AN16: =AM16-AP16 -> 400.59977 | AO16: =(AN16/AL16)*12 -> 0.0089688796 | AP16: =AL16*($AK$3/12) -> 3461.5786 | AQ16: =(AP16/AL16)*12 -> 0.0775 | AR16: =AR15+AN16 -> 3514.2285 | AS16: =AS15+AP16 -> 31245.377 | AT16: =AL16-AN16 -> 535585.77 | AU16: =AR16+AS16 -> 34759.606 | AW16: 9 | AX16: 45108 | AY16: =BG15 -> 535828.38 | AZ16: =AZ15 -> 3769.4654 | BA16: =AZ16-BC16 -> 420.53805 | BB16: =(BA16/AY16)*12 -> 0.0094180465 | BC16: =AY16*($AX$3/12) -> 3348.9274 | BD16: =(BC16/AY16)*12 -> 0.075 | BE16: =BE15+BA16 -> 3692.1593 | BF16: =BF15+BC16 -> 30233.029 | BG16: =AY16-BA16 -> 535407.84 | BH16: =BE16+BF16 -> 33925.189 | BJ16: 9 | BK16: 45108 | BL16: =BT15 -> 535663.59 | BM16: =BM15 -> 3677.6123 | BN16: =BM16-BP16 -> 441.31146 | BO16: =(BN16/BL16)*12 -> 0.0098863121 | BP16: =BL16*($BK$3/12) -> 3236.3009 | BQ16: =(BP16/BL16)*12 -> 0.0725 | BR16: =BR15+BN16 -> 3877.7192 | BS16: =BS15+BP16 -> 29220.792 | BT16: =BL16-BN16 -> 535222.28 | BU16: =BR16+BS16 -> 33098.511 | BW16: 9 | BX16: 45108 | BY16: =CG15 -> 535491.81 | BZ16: =BZ15 -> 3586.6458 | CA16: =BZ16-CC16 -> 462.94353 | CB16: =(CA16/BY16)*12 -> 0.010374243 | CC16: =BY16*($BX$3/12) -> 3123.7022 | CD16: =(CC16/BY16)*12 -> 0.07 | CE16: =CE15+CA16 -> 4071.1341 | CF16: =CF15+CC16 -> 28208.678 | CG16: =BY16-CA16 -> 535028.87 | CH16: =CE16+CF16 -> 32279.812
A17: =A16+1 -> 7 | B17: =VLOOKUP(A17*12,$J$7:$U$367,10) -> 301301.7 | C17: =VLOOKUP(A17*12,$W$7:$AH$367,10) -> 291726.72 | D17: =VLOOKUP(A17*12,$AJ$7:$AU$367,10) -> 282163.21 | E17: =VLOOKUP(A17*12,$AW$7:$BH$367,10) -> 272612.4 | F17: =VLOOKUP(A17*12,$BJ$7:$BU$367,10) -> 263075.54 | G17: =VLOOKUP(A17*12,$BW$7:$CH$367,10) -> 253553.95 | J17: 10 | K17: 45139 | L17: =T16 -> 535919.65 | M17: =$L$8/((($N$4)-1)/($N$3*$N$4)) -> 4050.0783 | N17: =M17-P17 -> 365.63069 | O17: =(N17/L17)*12 -> 0.008186989 | P17: =L17*($K$3/12) -> 3684.4476 | Q17: =(P17/L17)*12 -> 0.0825 | R17: =R16+N17 -> 3545.9836 | S17: =S16+P17 -> 36954.799 | T17: =L17-N17 -> 535554.02 | U17: =R17+S17 -> 40500.783 | W17: 10 | X17: 45139 | Y17: =AG16 -> 535756.3 | Z17: =Z16 -> 3955.7248 | AA17: =Z17-AC17 -> 384.01616 | AB17: =(AA17/Y17)*12 -> 0.0086012874 | AC17: =Y17*($X$3/12) -> 3571.7087 | AD17: =(AC17/Y17)*12 -> 0.08 | AE17: =AE16+AA17 -> 3727.7175 | AF17: =AF16+AC17 -> 35829.531 | AG17: =Y17-AA17 -> 535372.28 | AH17: =AE17+AF17 -> 39557.248 | AJ17: 10 | AK17: 45139 | AL17: =AT16 -> 535585.77 | AM17: =AM16 -> 3862.1784 | AN17: =AM17-AP17 -> 403.18697 | AO17: =(AN17/AL17)*12 -> 0.0090335553 | AP17: =AL17*($AK$3/12) -> 3458.9914 | AQ17: =(AP17/AL17)*12 -> 0.0775 | AR17: =AR16+AN17 -> 3917.4155 | AS17: =AS16+AP17 -> 34704.369 | AT17: =AL17-AN17 -> 535182.58 | AU17: =AR17+AS17 -> 38621.784 | AW17: 10 | AX17: 45139 | AY17: =BG16 -> 535407.84 | AZ17: =AZ16 -> 3769.4654 | BA17: =AZ17-BC17 -> 423.16641 | BB17: =(BA17/AY17)*12 -> 0.0094843529 | BC17: =AY17*($AX$3/12) -> 3346.299 | BD17: =(BC17/AY17)*12 -> 0.075 | BE17: =BE16+BA17 -> 4115.3257 | BF17: =BF16+BC17 -> 33579.328 | BG17: =AY17-BA17 -> 534984.67 | BH17: =BE17+BF17 -> 37694.654 | BJ17: 10 | BK17: 45139 | BL17: =BT16 -> 535222.28 | BM17: =BM16 -> 3677.6123 | BN17: =BM17-BP17 -> 443.97771 | BO17: =(BN17/BL17)*12 -> 0.0099542428 | BP17: =BL17*($BK$3/12) -> 3233.6346 | BQ17: =(BP17/BL17)*12 -> 0.0725 | BR17: =BR16+BN17 -> 4321.697 | BS17: =BS16+BP17 -> 32454.426 | BT17: =BL17-BN17 -> 534778.3 | BU17: =BR17+BS17 -> 36776.123 | BW17: 10 | BX17: 45139 | BY17: =CG16 -> 535028.87 | BZ17: =BZ16 -> 3586.6458 | CA17: =BZ17-CC17 -> 465.64403 | CB17: =(CA17/BY17)*12 -> 0.010443789 | CC17: =BY17*($BX$3/12) -> 3121.0017 | CD17: =(CC17/BY17)*12 -> 0.07 | CE17: =CE16+CA17 -> 4536.7781 | CF17: =CF16+CC17 -> 31329.679 | CG17: =BY17-CA17 -> 534563.22 | CH17: =CE17+CF17 -> 35866.458
A18: =A17+1 -> 8 | B18: =VLOOKUP(A18*12,$J$7:$U$367,10) -> 342283.99 | C18: =VLOOKUP(A18*12,$W$7:$AH$367,10) -> 331325.99 | D18: =VLOOKUP(A18*12,$AJ$7:$AU$367,10) -> 320383.73 | E18: =VLOOKUP(A18*12,$AW$7:$BH$367,10) -> 309458.78 | F18: =VLOOKUP(A18*12,$BJ$7:$BU$367,10) -> 298552.79 | G18: =VLOOKUP(A18*12,$BW$7:$CH$367,10) -> 287667.48 | J18: 11 | K18: 45170 | L18: =T17 -> 535554.02 | M18: =$L$8/((($N$4)-1)/($N$3*$N$4)) -> 4050.0783 | N18: =M18-P18 -> 368.1444 | O18: =(N18/L18)*12 -> 0.0082489024 | P18: =L18*($K$3/12) -> 3681.9339 | Q18: =(P18/L18)*12 -> 0.0825 | R18: =R17+N18 -> 3914.128 | S18: =S17+P18 -> 40636.733 | T18: =L18-N18 -> 535185.87 | U18: =R18+S18 -> 44550.861 | W18: 11 | X18: 45170 | Y18: =AG17 -> 535372.28 | Z18: =Z17 -> 3955.7248 | AA18: =Z18-AC18 -> 386.57627 | AB18: =(AA18/Y18)*12 -> 0.0086648401 | AC18: =Y18*($X$3/12) -> 3569.1485 | AD18: =(AC18/Y18)*12 -> 0.08 | AE18: =AE17+AA18 -> 4114.2938 | AF18: =AF17+AC18 -> 39398.679 | AG18: =Y18-AA18 -> 534985.71 | AH18: =AE18+AF18 -> 43512.973 | AJ18: 11 | AK18: 45170 | AL18: =AT17 -> 535182.58 | AM18: =AM17 -> 3862.1784 | AN18: =AM18-AP18 -> 405.79089 | AO18: =(AN18/AL18)*12 -> 0.0090987465 | AP18: =AL18*($AK$3/12) -> 3456.3875 | AQ18: =(AP18/AL18)*12 -> 0.0775 | AR18: =AR17+AN18 -> 4323.2063 | AS18: =AS17+AP18 -> 38160.756 | AT18: =AL18-AN18 -> 534776.79 | AU18: =AR18+AS18 -> 42483.963 | AW18: 11 | AX18: 45170 | AY18: =BG17 -> 534984.67 | AZ18: =AZ17 -> 3769.4654 | BA18: =AZ18-BC18 -> 425.8112 | BB18: =(BA18/AY18)*12 -> 0.009551179 | BC18: =AY18*($AX$3/12) -> 3343.6542 | BD18: =(BC18/AY18)*12 -> 0.075 | BE18: =BE17+BA18 -> 4541.1369 | BF18: =BF17+BC18 -> 36922.983 | BG18: =AY18-BA18 -> 534558.86 | BH18: =BE18+BF18 -> 41464.12 | BJ18: 11 | BK18: 45170 | BL18: =BT17 -> 534778.3 | BM18: =BM17 -> 3677.6123 | BN18: =BM18-BP18 -> 446.66008 | BO18: =(BN18/BL18)*12 -> 0.010022697 | BP18: =BL18*($BK$3/12) -> 3230.9522 | BQ18: =(BP18/BL18)*12 -> 0.0725 | BR18: =BR17+BN18 -> 4768.357 | BS18: =BS17+BP18 -> 35685.379 | BT18: =BL18-BN18 -> 534331.64 | BU18: =BR18+BS18 -> 40453.736 | BW18: 11 | BX18: 45170 | BY18: =CG17 -> 534563.22 | BZ18: =BZ17 -> 3586.6458 | CA18: =BZ18-CC18 -> 468.36029 | CB18: =(CA18/BY18)*12 -> 0.010513861 | CC18: =BY18*($BX$3/12) -> 3118.2855 | CD18: =(CC18/BY18)*12 -> 0.07 | CE18: =CE17+CA18 -> 5005.1384 | CF18: =CF17+CC18 -> 34447.965 | CG18: =BY18-CA18 -> 534094.86 | CH18: =CE18+CF18 -> 39453.103
A19: =A18+1 -> 9 | B19: =VLOOKUP(A19*12,$J$7:$U$367,10) -> 382613.43 | C19: =VLOOKUP(A19*12,$W$7:$AH$367,10) -> 370272.11 | D19: =VLOOKUP(A19*12,$AJ$7:$AU$367,10) -> 357951.65 | E19: =VLOOKUP(A19*12,$AW$7:$BH$367,10) -> 345654.04 | F19: =VLOOKUP(A19*12,$BJ$7:$BU$367,10) -> 333381.34 | G19: =VLOOKUP(A19*12,$BW$7:$CH$367,10) -> 321135.73 | J19: 12 | K19: 45200 | L19: =T18 -> 535185.87 | M19: =$L$8/((($N$4)-1)/($N$3*$N$4)) -> 4050.0783 | N19: =M19-P19 -> 370.67539 | O19: =(N19/L19)*12 -> 0.0083113269 | P19: =L19*($K$3/12) -> 3679.4029 | Q19: =(P19/L19)*12 -> 0.0825 | R19: =R18+N19 -> 4284.8034 | S19: =S18+P19 -> 44316.136 | T19: =L19-N19 -> 534815.2 | U19: =R19+S19 -> 48600.939 | W19: 12 | X19: 45200 | Y19: =AG18 -> 534985.71 | Z19: =Z18 -> 3955.7248 | AA19: =Z19-AC19 -> 389.15344 | AB19: =(AA19/Y19)*12 -> 0.0087289086 | AC19: =Y19*($X$3/12) -> 3566.5714 | AD19: =(AC19/Y19)*12 -> 0.08 | AE19: =AE18+AA19 -> 4503.4472 | AF19: =AF18+AC19 -> 42965.251 | AG19: =Y19-AA19 -> 534596.55 | AH19: =AE19+AF19 -> 47468.698 | AJ19: 12 | AK19: 45200 | AL19: =AT18 -> 534776.79 | AM19: =AM18 -> 3862.1784 | AN19: =AM19-AP19 -> 408.41162 | AO19: =(AN19/AL19)*12 -> 0.009164458 | AP19: =AL19*($AK$3/12) -> 3453.7668 | AQ19: =(AP19/AL19)*12 -> 0.0775 | AR19: =AR18+AN19 -> 4731.618 | AS19: =AS18+AP19 -> 41614.523 | AT19: =AL19-AN19 -> 534368.38 | AU19: =AR19+AS19 -> 46346.141 | AW19: 12 | AX19: 45200 | AY19: =BG18 -> 534558.86 | AZ19: =AZ18 -> 3769.4654 | BA19: =AZ19-BC19 -> 428.47252 | BB19: =(BA19/AY19)*12 -> 0.0096185296 | BC19: =AY19*($AX$3/12) -> 3340.9929 | BD19: =(BC19/AY19)*12 -> 0.075 | BE19: =BE18+BA19 -> 4969.6094 | BF19: =BF18+BC19 -> 40263.976 | BG19: =AY19-BA19 -> 534130.39 | BH19: =BE19+BF19 -> 45233.585 | BJ19: 12 | BK19: 45200 | BL19: =BT18 -> 534331.64 | BM19: =BM18 -> 3677.6123 | BN19: =BM19-BP19 -> 449.35865 | BO19: =(BN19/BL19)*12 -> 0.01009168 | BP19: =BL19*($BK$3/12) -> 3228.2537 | BQ19: =(BP19/BL19)*12 -> 0.0725 | BR19: =BR18+BN19 -> 5217.7157 | BS19: =BS18+BP19 -> 38913.632 | BT19: =BL19-BN19 -> 533882.28 | BU19: =BR19+BS19 -> 44131.348 | BW19: 12 | BX19: 45200 | BY19: =CG18 -> 534094.86 | BZ19: =BZ18 -> 3586.6458 | CA19: =BZ19-CC19 -> 471.09239 | CB19: =(CA19/BY19)*12 -> 0.010584466 | CC19: =BY19*($BX$3/12) -> 3115.5534 | CD19: =(CC19/BY19)*12 -> 0.07 | CE19: =CE18+CA19 -> 5476.2308 | CF19: =CF18+CC19 -> 37563.518 | CG19: =BY19-CA19 -> 533623.77 | CH19: =CE19+CF19 -> 43039.749
A20: =A19+1 -> 10 | B20: =VLOOKUP(A20*12,$J$7:$U$367,10) -> 422234.06 | C20: =VLOOKUP(A20*12,$W$7:$AH$367,10) -> 408510.86 | D20: =VLOOKUP(A20*12,$AJ$7:$AU$367,10) -> 394814.56 | E20: =VLOOKUP(A20*12,$AW$7:$BH$367,10) -> 381147.63 | F20: =VLOOKUP(A20*12,$BJ$7:$BU$367,10) -> 367512.58 | G20: =VLOOKUP(A20*12,$BW$7:$CH$367,10) -> 353912.05 | J20: 13 | K20: 45231 | L20: =T19 -> 534815.2 | M20: =$L$8/((($N$4)-1)/($N$3*$N$4)) -> 4050.0783 | N20: =M20-P20 -> 373.22379 | O20: =(N20/L20)*12 -> 0.0083742673 | P20: =L20*($K$3/12) -> 3676.8545 | Q20: =(P20/L20)*12 -> 0.0825 | R20: =R19+N20 -> 4658.0272 | S20: =S19+P20 -> 47992.99 | T20: =L20-N20 -> 534441.97 | U20: =R20+S20 -> 52651.017 | W20: 13 | X20: 45231 | Y20: =AG19 -> 534596.55 | Z20: =Z19 -> 3955.7248 | AA20: =Z20-AC20 -> 391.7478 | AB20: =(AA20/Y20)*12 -> 0.0087934978 | AC20: =Y20*($X$3/12) -> 3563.977 | AD20: =(AC20/Y20)*12 -> 0.08 | AE20: =AE19+AA20 -> 4895.195 | AF20: =AF19+AC20 -> 46529.228 | AG20: =Y20-AA20 -> 534204.8 | AH20: =AE20+AF20 -> 51424.423 | AJ20: 13 | AK20: 45231 | AL20: =AT19 -> 534368.38 | AM20: =AM19 -> 3862.1784 | AN20: =AM20-AP20 -> 411.04928 | AO20: =(AN20/AL20)*12 -> 0.0092306947 | AP20: =AL20*($AK$3/12) -> 3451.1291 | AQ20: =(AP20/AL20)*12 -> 0.0775 | AR20: =AR19+AN20 -> 5142.6673 | AS20: =AS19+AP20 -> 45065.652 | AT20: =AL20-AN20 -> 533957.33 | AU20: =AR20+AS20 -> 50208.319 | AW20: 13 | AX20: 45231 | AY20: =BG19 -> 534130.39 | AZ20: =AZ19 -> 3769.4654 | BA20: =AZ20-BC20 -> 431.15047 | BB20: =(BA20/AY20)*12 -> 0.0096864095 | BC20: =AY20*($AX$3/12) -> 3338.3149 | BD20: =(BC20/AY20)*12 -> 0.075 | BE20: =BE19+BA20 -> 5400.7599 | BF20: =BF19+BC20 -> 43602.291 | BG20: =AY20-BA20 -> 533699.24 | BH20: =BE20+BF20 -> 49003.05 | BJ20: 13 | BK20: 45231 | BL20: =BT19 -> 533882.28 | BM20: =BM19 -> 3677.6123 | BN20: =BM20-BP20 -> 452.07352 | BO20: =(BN20/BL20)*12 -> 0.010161196 | BP20: =BL20*($BK$3/12) -> 3225.5388 | BQ20: =(BP20/BL20)*12 -> 0.0725 | BR20: =BR19+BN20 -> 5669.7892 | BS20: =BS19+BP20 -> 42139.171 | BT20: =BL20-BN20 -> 533430.21 | BU20: =BR20+BS20 -> 47808.96 | BW20: 13 | BX20: 45231 | BY20: =CG19 -> 533623.77 | BZ20: =BZ19 -> 3586.6458 | CA20: =BZ20-CC20 -> 473.84043 | CB20: =(CA20/BY20)*12 -> 0.010655607 | CC20: =BY20*($BX$3/12) -> 3112.8053 | CD20: =(CC20/BY20)*12 -> 0.07 | CE20: =CE19+CA20 -> 5950.0712 | CF20: =CF19+CC20 -> 40676.324 | CG20: =BY20-CA20 -> 533149.93 | CH20: =CE20+CF20 -> 46626.395
A21: =A20+1 -> 11 | B21: =VLOOKUP(A21*12,$J$7:$U$367,10) -> 461085.15 | C21: =VLOOKUP(A21*12,$W$7:$AH$367,10) -> 445983.52 | D21: =VLOOKUP(A21*12,$AJ$7:$AU$367,10) -> 430915.85 | E21: =VLOOKUP(A21*12,$AW$7:$BH$367,10) -> 415885.07 | F21: =VLOOKUP(A21*12,$BJ$7:$BU$367,10) -> 400894.22 | G21: =VLOOKUP(A21*12,$BW$7:$CH$367,10) -> 385946.43 | J21: 14 | K21: 45261 | L21: =T20 -> 534441.97 | M21: =$L$8/((($N$4)-1)/($N$3*$N$4)) -> 4050.0783 | N21: =M21-P21 -> 375.7897 | O21: =(N21/L21)*12 -> 0.0084377287 | P21: =L21*($K$3/12) -> 3674.2886 | Q21: =(P21/L21)*12 -> 0.0825 | R21: =R20+N21 -> 5033.8169 | S21: =S20+P21 -> 51667.279 | T21: =L21-N21 -> 534066.18 | U21: =R21+S21 -> 56701.096 | W21: 14 | X21: 45261 | Y21: =AG20 -> 534204.8 | Z21: =Z20 -> 3955.7248 | AA21: =Z21-AC21 -> 394.35945 | AB21: =(AA21/Y21)*12 -> 0.0088586126 | AC21: =Y21*($X$3/12) -> 3561.3654 | AD21: =(AC21/Y21)*12 -> 0.08 | AE21: =AE20+AA21 -> 5289.5545 | AF21: =AF20+AC21 -> 50090.593 | AG21: =Y21-AA21 -> 533810.45 | AH21: =AE21+AF21 -> 55380.147 | AJ21: 14 | AK21: 45261 | AL21: =AT20 -> 533957.33 | AM21: =AM20 -> 3862.1784 | AN21: =AM21-AP21 -> 413.70398 | AO21: =(AN21/AL21)*12 -> 0.0092974614 | AP21: =AL21*($AK$3/12) -> 3448.4744 | AQ21: =(AP21/AL21)*12 -> 0.0775 | AR21: =AR20+AN21 -> 5556.3712 | AS21: =AS20+AP21 -> 48514.127 | AT21: =AL21-AN21 -> 533543.63 | AU21: =AR21+AS21 -> 54070.498 | AW21: 14 | AX21: 45261 | AY21: =BG20 -> 533699.24 | AZ21: =AZ20 -> 3769.4654 | BA21: =AZ21-BC21 -> 433.84516 | BB21: =(BA21/AY21)*12 -> 0.0097548237 | BC21: =AY21*($AX$3/12) -> 3335.6203 | BD21: =(BC21/AY21)*12 -> 0.075 | BE21: =BE20+BA21 -> 5834.605 | BF21: =BF20+BC21 -> 46937.911 | BG21: =AY21-BA21 -> 533265.39 | BH21: =BE21+BF21 -> 52772.516 | BJ21: 14 | BK21: 45261 | BL21: =BT20 -> 533430.21 | BM21: =BM20 -> 3677.6123 | BN21: =BM21-BP21 -> 454.8048 | BO21: =(BN21/BL21)*12 -> 0.01023125 | BP21: =BL21*($BK$3/12) -> 3222.8075 | BQ21: =(BP21/BL21)*12 -> 0.0725 | BR21: =BR20+BN21 -> 6124.594 | BS21: =BS20+BP21 -> 45361.979 | BT21: =BL21-BN21 -> 532975.41 | BU21: =BR21+BS21 -> 51486.573 | BW21: 14 | BX21: 45261 | BY21: =CG20 -> 533149.93 | BZ21: =BZ20 -> 3586.6458 | CA21: =BZ21-CC21 -> 476.6045 | CB21: =(CA21/BY21)*12 -> 0.01072729 | CC21: =BY21*($BX$3/12) -> 3110.0413 | CD21: =(CC21/BY21)*12 -> 0.07 | CE21: =CE20+CA21 -> 6426.6757 | CF21: =CF20+CC21 -> 43786.365 | CG21: =BY21-CA21 -> 532673.32 | CH21: =CE21+CF21 -> 50213.041
A22: =A21+1 -> 12 | B22: =VLOOKUP(A22*12,$J$7:$U$367,10) -> 499100.76 | C22: =VLOOKUP(A22*12,$W$7:$AH$367,10) -> 482626.52 | D22: =VLOOKUP(A22*12,$AJ$7:$AU$367,10) -> 466194.35 | E22: =VLOOKUP(A22*12,$AW$7:$BH$367,10) -> 449807.68 | F22: =VLOOKUP(A22*12,$BJ$7:$BU$367,10) -> 433470.08 | G22: =VLOOKUP(A22*12,$BW$7:$CH$367,10) -> 417185.23 | J22: 15 | K22: 45292 | L22: =T21 -> 534066.18 | M22: =$L$8/((($N$4)-1)/($N$3*$N$4)) -> 4050.0783 | N22: =M22-P22 -> 378.37325 | O22: =(N22/L22)*12 -> 0.0085017161 | P22: =L22*($K$3/12) -> 3671.705 | Q22: =(P22/L22)*12 -> 0.0825 | R22: =R21+N22 -> 5412.1901 | S22: =S21+P22 -> 55338.984 | T22: =L22-N22 -> 533687.81 | U22: =R22+S22 -> 60751.174 | W22: 15 | X22: 45292 | Y22: =AG21 -> 533810.45 | Z22: =Z21 -> 3955.7248 | AA22: =Z22-AC22 -> 396.98851 | AB22: =(AA22/Y22)*12 -> 0.0089242581 | AC22: =Y22*($X$3/12) -> 3558.7363 | AD22: =(AC22/Y22)*12 -> 0.08 | AE22: =AE21+AA22 -> 5686.543 | AF22: =AF21+AC22 -> 53649.329 | AG22: =Y22-AA22 -> 533413.46 | AH22: =AE22+AF22 -> 59335.872 | AJ22: 15 | AK22: 45292 | AL22: =AT21 -> 533543.63 | AM22: =AM21 -> 3862.1784 | AN22: =AM22-AP22 -> 416.37581 | AO22: =(AN22/AL22)*12 -> 0.0093647632 | AP22: =AL22*($AK$3/12) -> 3445.8026 | AQ22: =(AP22/AL22)*12 -> 0.0775 | AR22: =AR21+AN22 -> 5972.747 | AS22: =AS21+AP22 -> 51959.929 | AT22: =AL22-AN22 -> 533127.25 | AU22: =AR22+AS22 -> 57932.676 | AW22: 15 | AX22: 45292 | AY22: =BG21 -> 533265.39 | AZ22: =AZ21 -> 3769.4654 | BA22: =AZ22-BC22 -> 436.5567 | BB22: =(BA22/AY22)*12 -> 0.0098237771 | BC22: =AY22*($AX$3/12) -> 3332.9087 | BD22: =(BC22/AY22)*12 -> 0.075 | BE22: =BE21+BA22 -> 6271.1617 | BF22: =BF21+BC22 -> 50270.819 | BG22: =AY22-BA22 -> 532828.84 | BH22: =BE22+BF22 -> 56541.981 | BJ22: 15 | BK22: 45292 | BL22: =BT21 -> 532975.41 | BM22: =BM21 -> 3677.6123 | BN22: =BM22-BP22 -> 457.55258 | BO22: =(BN22/BL22)*12 -> 0.010301847 | BP22: =BL22*($BK$3/12) -> 3220.0597 | BQ22: =(BP22/BL22)*12 -> 0.0725 | BR22: =BR21+BN22 -> 6582.1466 | BS22: =BS21+BP22 -> 48582.038 | BT22: =BL22-BN22 -> 532517.85 | BU22: =BR22+BS22 -> 55164.185 | BW22: 15 | BX22: 45292 | BY22: =CG21 -> 532673.32 | BZ22: =BZ21 -> 3586.6458 | CA22: =BZ22-CC22 -> 479.38469 | CB22: =(CA22/BY22)*12 -> 0.01079952 | CC22: =BY22*($BX$3/12) -> 3107.2611 | CD22: =(CC22/BY22)*12 -> 0.07 | CE22: =CE21+CA22 -> 6906.0604 | CF22: =CF21+CC22 -> 46893.626 | CG22: =BY22-CA22 -> 532193.94 | CH22: =CE22+CF22 -> 53799.686
A23: =A22+1 -> 13 | B23: =VLOOKUP(A23*12,$J$7:$U$367,10) -> 536209.29 | C23: =VLOOKUP(A23*12,$W$7:$AH$367,10) -> 518370.99 | D23: =VLOOKUP(A23*12,$AJ$7:$AU$367,10) -> 500583.97 | E23: =VLOOKUP(A23*12,$AW$7:$BH$367,10) -> 482852.19 | F23: =VLOOKUP(A23*12,$BJ$7:$BU$367,10) -> 465179.76 | G23: =VLOOKUP(A23*12,$BW$7:$CH$367,10) -> 447570.94 | J23: 16 | K23: 45323 | L23: =T22 -> 533687.81 | M23: =$L$8/((($N$4)-1)/($N$3*$N$4)) -> 4050.0783 | N23: =M23-P23 -> 380.97457 | O23: =(N23/L23)*12 -> 0.0085662343 | P23: =L23*($K$3/12) -> 3669.1037 | Q23: =(P23/L23)*12 -> 0.0825 | R23: =R22+N23 -> 5793.1647 | S23: =S22+P23 -> 59008.087 | T23: =L23-N23 -> 533306.84 | U23: =R23+S23 -> 64801.252 | W23: 16 | X23: 45323 | Y23: =AG22 -> 533413.46 | Z23: =Z22 -> 3955.7248 | AA23: =Z23-AC23 -> 399.6351 | AB23: =(AA23/Y23)*12 -> 0.0089904392 | AC23: =Y23*($X$3/12) -> 3556.0897 | AD23: =(AC23/Y23)*12 -> 0.08 | AE23: =AE22+AA23 -> 6086.1781 | AF23: =AF22+AC23 -> 57205.419 | AG23: =Y23-AA23 -> 533013.82 | AH23: =AE23+AF23 -> 63291.597 | AJ23: 16 | AK23: 45323 | AL23: =AT22 -> 533127.25 | AM23: =AM22 -> 3862.1784 | AN23: =AM23-AP23 -> 419.06491 | AO23: =(AN23/AL23)*12 -> 0.0094326052 | AP23: =AL23*($AK$3/12) -> 3443.1135 | AQ23: =(AP23/AL23)*12 -> 0.0775 | AR23: =AR22+AN23 -> 6391.812 | AS23: =AS22+AP23 -> 55403.043 | AT23: =AL23-AN23 -> 532708.19 | AU23: =AR23+AS23 -> 61794.855 | AW23: 16 | AX23: 45323 | AY23: =BG22 -> 532828.84 | AZ23: =AZ22 -> 3769.4654 | BA23: =AZ23-BC23 -> 439.28518 | BB23: =(BA23/AY23)*12 -> 0.0098932748 | BC23: =AY23*($AX$3/12) -> 3330.1802 | BD23: =(BC23/AY23)*12 -> 0.075 | BE23: =BE22+BA23 -> 6710.4469 | BF23: =BF22+BC23 -> 53601 | BG23: =AY23-BA23 -> 532389.55 | BH23: =BE23+BF23 -> 60311.447 | BJ23: 16 | BK23: 45323 | BL23: =BT22 -> 532517.85 | BM23: =BM22 -> 3677.6123 | BN23: =BM23-BP23 -> 460.31696 | BO23: =(BN23/BL23)*12 -> 0.010372992 | BP23: =BL23*($BK$3/12) -> 3217.2954 | BQ23: =(BP23/BL23)*12 -> 0.0725 | BR23: =BR22+BN23 -> 7042.4636 | BS23: =BS22+BP23 -> 51799.334 | BT23: =BL23-BN23 -> 532057.54 | BU23: =BR23+BS23 -> 58841.797 | BW23: 16 | BX23: 45323 | BY23: =CG22 -> 532193.94 | BZ23: =BZ22 -> 3586.6458 | CA23: =BZ23-CC23 -> 482.1811 | CB23: =(CA23/BY23)*12 -> 0.010872302 | CC23: =BY23*($BX$3/12) -> 3104.4646 | CD23: =(CC23/BY23)*12 -> 0.07 | CE23: =CE22+CA23 -> 7388.2415 | CF23: =CF22+CC23 -> 49998.091 | CG23: =BY23-CA23 -> 531711.76 | CH23: =CE23+CF23 -> 57386.332
... A40: =A39+1 -> 30 | B40: =VLOOKUP(A40*12,$J$7:$U$367,10) -> 918928.17 | C40: =VLOOKUP(A40*12,$W$7:$AH$367,10) -> 884960.93 | D40: =VLOOKUP(A40*12,$AJ$7:$AU$367,10) -> 851284.23 | E40: =VLOOKUP(A40*12,$AW$7:$BH$367,10) -> 817907.55 | F40: =VLOOKUP(A40*12,$BJ$7:$BU$367,10) -> 784840.44 | G40: =VLOOKUP(A40*12,$BW$7:$CH$367,10) -> 752092.47 | J40: 33 | K40: 45839 | L40: =T39 -> 526842.49 | M40: =$L$8/((($N$4)-1)/($N$3*$N$4)) -> 4050.0783 | N40: =M40-P40 -> 428.03617 | O40: =(N40/L40)*12 -> 0.0097494681 | P40: =L40*($K$3/12) -> 3622.0421 | Q40: =(P40/L40)*12 -> 0.0825 | R40: =R39+N40 -> 12685.55 | S40: =S39+P40 -> 120967.03 | T40: =L40-N40 -> 526414.45 | U40: =R40+S40 -> 133652.58 | W40: 33 | X40: 45839 | Y40: =AG39 -> 526244.96 | Z40: =Z39 -> 3955.7248 | AA40: =Z40-AC40 -> 447.42509 | AB40: =(AA40/Y40)*12 -> 0.010202665 | AC40: =Y40*($X$3/12) -> 3508.2997 | AD40: =(AC40/Y40)*12 -> 0.08 | AE40: =AE39+AA40 -> 13302.465 | AF40: =AF39+AC40 -> 117236.45 | AG40: =Y40-AA40 -> 525797.53 | AH40: =AE40+AF40 -> 130538.92 | AJ40: 33 | AK40: 45839 | AL40: =AT39 -> 525622.91 | AM40: =AM39 -> 3862.1784 | AN40: =AM40-AP40 -> 467.53044 | AO40: =(AN40/AL40)*12 -> 0.010673746 | AP40: =AL40*($AK$3/12) -> 3394.648 | AQ40: =(AP40/AL40)*12 -> 0.0775 | AR40: =AR39+AN40 -> 13944.619 | AS40: =AS39+AP40 -> 113507.27 | AT40: =AL40-AN40 -> 525155.38 | AU40: =AR40+AS40 -> 127451.89 | AW40: 33 | AX40: 45839 | AY40: =BG39 -> 524975.67 | AZ40: =AZ39 -> 3769.4654 | BA40: =AZ40-BC40 -> 488.36748 | BB40: =(BA40/AY40)*12 -> 0.011163203 | BC40: =AY40*($AX$3/12) -> 3281.0979 | BD40: =(BC40/AY40)*12 -> 0.075 | BE40: =BE39+BA40 -> 14612.698 | BF40: =BF39+BC40 -> 109779.66 | BG40: =AY40-BA40 -> 524487.3 | BH40: =BE40+BF40 -> 124392.36 | BJ40: 33 | BK40: 45839 | BL40: =BT39 -> 524302.57 | BM40: =BM39 -> 3677.6123 | BN40: =BM40-BP40 -> 509.95098 | BO40: =(BN40/BL40)*12 -> 0.011671527 | BP40: =BL40*($BK$3/12) -> 3167.6613 | BQ40: =(BP40/BL40)*12 -> 0.0725 | BR40: =BR39+BN40 -> 15307.384 | BS40: =BS39+BP40 -> 106053.82 | BT40: =BL40-BN40 -> 523792.62 | BU40: =BR40+BS40 -> 121361.21 | BW40: 33 | BX40: 45839 | BY40: =CG39 -> 523602.94 | BZ40: =BZ39 -> 3586.6458 | CA40: =BZ40-CC40 -> 532.29526 | CB40: =(CA40/BY40)*12 -> 0.012199212 | CC40: =BY40*($BX$3/12) -> 3054.3505 | CD40: =(CC40/BY40)*12 -> 0.07 | CE40: =CE39+CA40 -> 16029.353 | CF40: =CF39+CC40 -> 102329.96 | CG40: =BY40-CA40 -> 523070.65 | CH40: =CE40+CF40 -> 118359.31
J41: 34 | K41: 45870 | L41: =T40 -> 526414.45 | M41: =$L$8/((($N$4)-1)/($N$3*$N$4)) -> 4050.0783 | N41: =M41-P41 -> 430.97892 | O41: =(N41/L41)*12 -> 0.0098244777 | P41: =L41*($K$3/12) -> 3619.0993 | Q41: =(P41/L41)*12 -> 0.0825 | R41: =R40+N41 -> 13116.529 | S41: =S40+P41 -> 124586.13 | T41: =L41-N41 -> 525983.47 | U41: =R41+S41 -> 137702.66 | W41: 34 | X41: 45870 | Y41: =AG40 -> 525797.53 | Z41: =Z40 -> 3955.7248 | AA41: =Z41-AC41 -> 450.40792 | AB41: =(AA41/Y41)*12 -> 0.010279423 | AC41: =Y41*($X$3/12) -> 3505.3169 | AD41: =(AC41/Y41)*12 -> 0.08 | AE41: =AE40+AA41 -> 13752.873 | AF41: =AF40+AC41 -> 120741.77 | AG41: =Y41-AA41 -> 525347.13 | AH41: =AE41+AF41 -> 134494.64 | AJ41: 34 | AK41: 45870 | AL41: =AT40 -> 525155.38 | AM41: =AM40 -> 3862.1784 | AN41: =AM41-AP41 -> 470.54991 | AO41: =(AN41/AL41)*12 -> 0.010752244 | AP41: =AL41*($AK$3/12) -> 3391.6285 | AQ41: =(AP41/AL41)*12 -> 0.0775 | AR41: =AR40+AN41 -> 14415.169 | AS41: =AS40+AP41 -> 116898.9 | AT41: =AL41-AN41 -> 524684.83 | AU41: =AR41+AS41 -> 131314.07 | AW41: 34 | AX41: 45870 | AY41: =BG40 -> 524487.3 | AZ41: =AZ40 -> 3769.4654 | BA41: =AZ41-BC41 -> 491.41978 | BB41: =(BA41/AY41)*12 -> 0.011243432 | BC41: =AY41*($AX$3/12) -> 3278.0456 | BD41: =(BC41/AY41)*12 -> 0.075 | BE41: =BE40+BA41 -> 15104.117 | BF41: =BF40+BC41 -> 113057.71 | BG41: =AY41-BA41 -> 523995.88 | BH41: =BE41+BF41 -> 128161.82 | BJ41: 34 | BK41: 45870 | BL41: =BT40 -> 523792.62 | BM41: =BM40 -> 3677.6123 | BN41: =BM41-BP41 -> 513.03194 | BO41: =(BN41/BL41)*12 -> 0.011753475 | BP41: =BL41*($BK$3/12) -> 3164.5804 | BQ41: =(BP41/BL41)*12 -> 0.0725 | BR41: =BR40+BN41 -> 15820.416 | BS41: =BS40+BP41 -> 109218.4 | BT41: =BL41-BN41 -> 523279.58 | BU41: =BR41+BS41 -> 125038.82 | BW41: 34 | BX41: 45870 | BY41: =CG40 -> 523070.65 | BZ41: =BZ40 -> 3586.6458 | CA41: =BZ41-CC41 -> 535.40031 | CB41: =(CA41/BY41)*12 -> 0.01228286 | CC41: =BY41*($BX$3/12) -> 3051.2454 | CD41: =(CC41/BY41)*12 -> 0.07 | CE41: =CE40+CA41 -> 16564.754 | CF41: =CF40+CC41 -> 105381.2 | CG41: =BY41-CA41 -> 522535.25 | CH41: =CE41+CF41 -> 121945.96
J42: 35 | K42: 45901 | L42: =T41 -> 525983.47 | M42: =$L$8/((($N$4)-1)/($N$3*$N$4)) -> 4050.0783 | N42: =M42-P42 -> 433.9419 | O42: =(N42/L42)*12 -> 0.0099001263 | P42: =L42*($K$3/12) -> 3616.1364 | Q42: =(P42/L42)*12 -> 0.0825 | R42: =R41+N42 -> 13550.471 | S42: =S41+P42 -> 128202.27 | T42: =L42-N42 -> 525549.53 | U42: =R42+S42 -> 141752.74 | W42: 35 | X42: 45901 | Y42: =AG41 -> 525347.13 | Z42: =Z41 -> 3955.7248 | AA42: =Z42-AC42 -> 453.41064 | AB42: =(AA42/Y42)*12 -> 0.010356824 | AC42: =Y42*($X$3/12) -> 3502.3142 | AD42: =(AC42/Y42)*12 -> 0.08 | AE42: =AE41+AA42 -> 14206.284 | AF42: =AF41+AC42 -> 124244.08 | AG42: =Y42-AA42 -> 524893.72 | AH42: =AE42+AF42 -> 138450.37 | AJ42: 35 | AK42: 45901 | AL42: =AT41 -> 524684.83 | AM42: =AM41 -> 3862.1784 | AN42: =AM42-AP42 -> 473.58888 | AO42: =(AN42/AL42)*12 -> 0.010831391 | AP42: =AL42*($AK$3/12) -> 3388.5895 | AQ42: =(AP42/AL42)*12 -> 0.0775 | AR42: =AR41+AN42 -> 14888.757 | AS42: =AS41+AP42 -> 120287.49 | AT42: =AL42-AN42 -> 524211.24 | AU42: =AR42+AS42 -> 135176.24 | AW42: 35 | AX42: 45901 | AY42: =BG41 -> 523995.88 | AZ42: =AZ41 -> 3769.4654 | BA42: =AZ42-BC42 -> 494.49115 | BB42: =(BA42/AY42)*12 -> 0.011324314 | BC42: =AY42*($AX$3/12) -> 3274.9743 | BD42: =(BC42/AY42)*12 -> 0.075 | BE42: =BE41+BA42 -> 15598.608 | BF42: =BF41+BC42 -> 116332.68 | BG42: =AY42-BA42 -> 523501.39 | BH42: =BE42+BF42 -> 131931.29 | BJ42: 35 | BK42: 45901 | BL42: =BT41 -> 523279.58 | BM42: =BM41 -> 3677.6123 | BN42: =BM42-BP42 -> 516.13151 | BO42: =(BN42/BL42)*12 -> 0.011836078 | BP42: =BL42*($BK$3/12) -> 3161.4808 | BQ42: =(BP42/BL42)*12 -> 0.0725 | BR42: =BR41+BN42 -> 16336.548 | BS42: =BS41+BP42 -> 112379.88 | BT42: =BL42-BN42 -> 522763.45 | BU42: =BR42+BS42 -> 128716.43 | BW42: 35 | BX42: 45901 | BY42: =CG41 -> 522535.25 | BZ42: =BZ41 -> 3586.6458 | CA42: =BZ42-CC42 -> 538.52348 | CB42: =(CA42/BY42)*12 -> 0.012367169 | CC42: =BY42*($BX$3/12) -> 3048.1223 | CD42: =(CC42/BY42)*12 -> 0.07 | CE42: =CE41+CA42 -> 17103.277 | CF42: =CF41+CC42 -> 108429.32 | CG42: =BY42-CA42 -> 521996.72 | CH42: =CE42+CF42 -> 125532.6
J43: 36 | K43: 45931 | L43: =T42 -> 525549.53 | M43: =$L$8/((($N$4)-1)/($N$3*$N$4)) -> 4050.0783 | N43: =M43-P43 -> 436.92525 | O43: =(N43/L43)*12 -> 0.0099764203 | P43: =L43*($K$3/12) -> 3613.153 | Q43: =(P43/L43)*12 -> 0.0825 | R43: =R42+N43 -> 13987.396 | S43: =S42+P43 -> 131815.42 | T43: =L43-N43 -> 525112.6 | U43: =R43+S43 -> 145802.82 | W43: 36 | X43: 45931 | Y43: =AG42 -> 524893.72 | Z43: =Z42 -> 3955.7248 | AA43: =Z43-AC43 -> 456.43338 | AB43: =(AA43/Y43)*12 -> 0.010434875 | AC43: =Y43*($X$3/12) -> 3499.2914 | AD43: =(AC43/Y43)*12 -> 0.08 | AE43: =AE42+AA43 -> 14662.717 | AF43: =AF42+AC43 -> 127743.38 | AG43: =Y43-AA43 -> 524437.28 | AH43: =AE43+AF43 -> 142406.09 | AJ43: 36 | AK43: 45931 | AL43: =AT42 -> 524211.24 | AM43: =AM42 -> 3862.1784 | AN43: =AM43-AP43 -> 476.64747 | AO43: =(AN43/AL43)*12 -> 0.010911192 | AP43: =AL43*($AK$3/12) -> 3385.5309 | AQ43: =(AP43/AL43)*12 -> 0.0775 | AR43: =AR42+AN43 -> 15365.405 | AS43: =AS42+AP43 -> 123673.02 | AT43: =AL43-AN43 -> 523734.6 | AU43: =AR43+AS43 -> 139038.42 | AW43: 36 | AX43: 45931 | AY43: =BG42 -> 523501.39 | AZ43: =AZ42 -> 3769.4654 | BA43: =AZ43-BC43 -> 497.58172 | BB43: =(BA43/AY43)*12 -> 0.011405854 | BC43: =AY43*($AX$3/12) -> 3271.8837 | BD43: =(BC43/AY43)*12 -> 0.075 | BE43: =BE42+BA43 -> 16096.19 | BF43: =BF42+BC43 -> 119604.56 | BG43: =AY43-BA43 -> 523003.81 | BH43: =BE43+BF43 -> 135700.75 | BJ43: 36 | BK43: 45931 | BL43: =BT42 -> 522763.45 | BM43: =BM42 -> 3677.6123 | BN43: =BM43-BP43 -> 519.2498 | BO43: =(BN43/BL43)*12 -> 0.011919344 | BP43: =BL43*($BK$3/12) -> 3158.3625 | BQ43: =(BP43/BL43)*12 -> 0.0725 | BR43: =BR42+BN43 -> 16855.797 | BS43: =BS42+BP43 -> 115538.25 | BT43: =BL43-BN43 -> 522244.2 | BU43: =BR43+BS43 -> 132394.04 | BW43: 36 | BX43: 45931 | BY43: =CG42 -> 521996.72 | BZ43: =BZ42 -> 3586.6458 | CA43: =BZ43-CC43 -> 541.66487 | CB43: =(CA43/BY43)*12 -> 0.012452144 | CC43: =BY43*($BX$3/12) -> 3044.9809 | CD43: =(CC43/BY43)*12 -> 0.07 | CE43: =CE42+CA43 -> 17644.942 | CF43: =CF42+CC43 -> 111474.31 | CG43: =BY43-CA43 -> 521455.06 | CH43: =CE43+CF43 -> 129119.25
J44: 37 | K44: 45962 | L44: =T43 -> 525112.6 | M44: =$L$8/((($N$4)-1)/($N$3*$N$4)) -> 4050.0783 | N44: =M44-P44 -> 439.92911 | O44: =(N44/L44)*12 -> 0.010053366 | P44: =L44*($K$3/12) -> 3610.1492 | Q44: =(P44/L44)*12 -> 0.0825 | R44: =R43+N44 -> 14427.325 | S44: =S43+P44 -> 135425.57 | T44: =L44-N44 -> 524672.67 | U44: =R44+S44 -> 149852.9 | W44: 37 | X44: 45962 | Y44: =AG43 -> 524437.28 | Z44: =Z43 -> 3955.7248 | AA44: =Z44-AC44 -> 459.47627 | AB44: =(AA44/Y44)*12 -> 0.010513584 | AC44: =Y44*($X$3/12) -> 3496.2486 | AD44: =(AC44/Y44)*12 -> 0.08 | AE44: =AE43+AA44 -> 15122.194 | AF44: =AF43+AC44 -> 131239.62 | AG44: =Y44-AA44 -> 523977.81 | AH44: =AE44+AF44 -> 146361.82 | AJ44: 37 | AK44: 45962 | AL44: =AT43 -> 523734.6 | AM44: =AM43 -> 3862.1784 | AN44: =AM44-AP44 -> 479.72582 | AO44: =(AN44/AL44)*12 -> 0.010991655 | AP44: =AL44*($AK$3/12) -> 3382.4526 | AQ44: =(AP44/AL44)*12 -> 0.0775 | AR44: =AR43+AN44 -> 15845.131 | AS44: =AS43+AP44 -> 127055.47 | AT44: =AL44-AN44 -> 523254.87 | AU44: =AR44+AS44 -> 142900.6 | AW44: 37 | AX44: 45962 | AY44: =BG43 -> 523003.81 | AZ44: =AZ43 -> 3769.4654 | BA44: =AZ44-BC44 -> 500.6916 | BB44: =(BA44/AY44)*12 -> 0.01148806 | BC44: =AY44*($AX$3/12) -> 3268.7738 | BD44: =(BC44/AY44)*12 -> 0.075 | BE44: =BE43+BA44 -> 16596.882 | BF44: =BF43+BC44 -> 122873.34 | BG44: =AY44-BA44 -> 522503.12 | BH44: =BE44+BF44 -> 139470.22 | BJ44: 37 | BK44: 45962 | BL44: =BT43 -> 522244.2 | BM44: =BM43 -> 3677.6123 | BN44: =BM44-BP44 -> 522.38693 | BO44: =(BN44/BL44)*12 -> 0.01200328 | BP44: =BL44*($BK$3/12) -> 3155.2254 | BQ44: =(BP44/BL44)*12 -> 0.0725 | BR44: =BR43+BN44 -> 17378.184 | BS44: =BS43+BP44 -> 118693.47 | BT44: =BL44-BN44 -> 521721.82 | BU44: =BR44+BS44 -> 136071.66 | BW44: 37 | BX44: 45962 | BY44: =CG43 -> 521455.06 | BZ44: =BZ43 -> 3586.6458 | CA44: =BZ44-CC44 -> 544.82458 | CB44: =(CA44/BY44)*12 -> 0.012537792 | CC44: =BY44*($BX$3/12) -> 3041.8212 | CD44: =(CC44/BY44)*12 -> 0.07 | CE44: =CE43+CA44 -> 18189.766 | CF44: =CF43+CC44 -> 114516.13 | CG44: =BY44-CA44 -> 520910.23 | CH44: =CE44+CF44 -> 132705.89
J45: 38 | K45: 45992 | L45: =T44 -> 524672.67 | M45: =$L$8/((($N$4)-1)/($N$3*$N$4)) -> 4050.0783 | N45: =M45-P45 -> 442.95362 | O45: =(N45/L45)*12 -> 0.010130971 | P45: =L45*($K$3/12) -> 3607.1246 | Q45: =(P45/L45)*12 -> 0.0825 | R45: =R44+N45 -> 14870.279 | S45: =S44+P45 -> 139032.7 | T45: =L45-N45 -> 524229.72 | U45: =R45+S45 -> 153902.97 | W45: 38 | X45: 45992 | Y45: =AG44 -> 523977.81 | Z45: =Z44 -> 3955.7248 | AA45: =Z45-AC45 -> 462.53944 | AB45: =(AA45/Y45)*12 -> 0.010592955 | AC45: =Y45*($X$3/12) -> 3493.1854 | AD45: =(AC45/Y45)*12 -> 0.08 | AE45: =AE44+AA45 -> 15584.733 | AF45: =AF44+AC45 -> 134732.81 | AG45: =Y45-AA45 -> 523515.27 | AH45: =AE45+AF45 -> 150317.54 | AJ45: 38 | AK45: 45992 | AL45: =AT44 -> 523254.87 | AM45: =AM44 -> 3862.1784 | AN45: =AM45-AP45 -> 482.82405 | AO45: =(AN45/AL45)*12 -> 0.011072785 | AP45: =AL45*($AK$3/12) -> 3379.3544 | AQ45: =(AP45/AL45)*12 -> 0.0775 | AR45: =AR44+AN45 -> 16327.955 | AS45: =AS44+AP45 -> 130434.82 | AT45: =AL45-AN45 -> 522772.05 | AU45: =AR45+AS45 -> 146762.78 | AW45: 38 | AX45: 45992 | AY45: =BG44 -> 522503.12 | AZ45: =AZ44 -> 3769.4654 | BA45: =AZ45-BC45 -> 503.82093 | BB45: =(BA45/AY45)*12 -> 0.011570938 | BC45: =AY45*($AX$3/12) -> 3265.6445 | BD45: =(BC45/AY45)*12 -> 0.075 | BE45: =BE44+BA45 -> 17100.703 | BF45: =BF44+BC45 -> 126138.98 | BG45: =AY45-BA45 -> 521999.3 | BH45: =BE45+BF45 -> 143239.69 | BJ45: 38 | BK45: 45992 | BL45: =BT44 -> 521721.82 | BM45: =BM44 -> 3677.6123 | BN45: =BM45-BP45 -> 525.54302 | BO45: =(BN45/BL45)*12 -> 0.012087891 | BP45: =BL45*($BK$3/12) -> 3152.0693 | BQ45: =(BP45/BL45)*12 -> 0.0725 | BR45: =BR44+BN45 -> 17903.727 | BS45: =BS44+BP45 -> 121845.54 | BT45: =BL45-BN45 -> 521196.27 | BU45: =BR45+BS45 -> 139749.27 | BW45: 38 | BX45: 45992 | BY45: =CG44 -> 520910.23 | BZ45: =BZ44 -> 3586.6458 | CA45: =BZ45-CC45 -> 548.00272 | CB45: =(CA45/BY45)*12 -> 0.012624119 | CC45: =BY45*($BX$3/12) -> 3038.643 | CD45: =(CC45/BY45)*12 -> 0.07 | CE45: =CE44+CA45 -> 18737.769 | CF45: =CF44+CC45 -> 117554.77 | CG45: =BY45-CA45 -> 520362.23 | CH45: =CE45+CF45 -> 136292.54
J46: 39 | K46: 46023 | L46: =T45 -> 524229.72 | M46: =$L$8/((($N$4)-1)/($N$3*$N$4)) -> 4050.0783 | N46: =M46-P46 -> 445.99893 | O46: =(N46/L46)*12 -> 0.01020924 | P46: =L46*($K$3/12) -> 3604.0793 | Q46: =(P46/L46)*12 -> 0.0825 | R46: =R45+N46 -> 15316.278 | S46: =S45+P46 -> 142636.77 | T46: =L46-N46 -> 523783.72 | U46: =R46+S46 -> 157953.05 | W46: 39 | X46: 46023 | Y46: =AG45 -> 523515.27 | Z46: =Z45 -> 3955.7248 | AA46: =Z46-AC46 -> 465.62304 | AB46: =(AA46/Y46)*12 -> 0.010672996 | AC46: =Y46*($X$3/12) -> 3490.1018 | AD46: =(AC46/Y46)*12 -> 0.08 | AE46: =AE45+AA46 -> 16050.356 | AF46: =AF45+AC46 -> 138222.91 | AG46: =Y46-AA46 -> 523049.64 | AH46: =AE46+AF46 -> 154273.27 | AJ46: 39 | AK46: 46023 | AL46: =AT45 -> 522772.05 | AM46: =AM45 -> 3862.1784 | AN46: =AM46-AP46 -> 485.94229 | AO46: =(AN46/AL46)*12 -> 0.011154589 | AP46: =AL46*($AK$3/12) -> 3376.2361 | AQ46: =(AP46/AL46)*12 -> 0.0775 | AR46: =AR45+AN46 -> 16813.897 | AS46: =AS45+AP46 -> 133811.06 | AT46: =AL46-AN46 -> 522286.1 | AU46: =AR46+AS46 -> 150624.96 | AW46: 39 | AX46: 46023 | AY46: =BG45 -> 521999.3 | AZ46: =AZ45 -> 3769.4654 | BA46: =AZ46-BC46 -> 506.96981 | BB46: =(BA46/AY46)*12 -> 0.011654494 | BC46: =AY46*($AX$3/12) -> 3262.4956 | BD46: =(BC46/AY46)*12 -> 0.075 | BE46: =BE45+BA46 -> 17607.673 | BF46: =BF45+BC46 -> 129401.48 | BG46: =AY46-BA46 -> 521492.33 | BH46: =BE46+BF46 -> 147009.15 | BJ46: 39 | BK46: 46023 | BL46: =BT45 -> 521196.27 | BM46: =BM45 -> 3677.6123 | BN46: =BM46-BP46 -> 528.71818 | BO46: =(BN46/BL46)*12 -> 0.012173184 | BP46: =BL46*($BK$3/12) -> 3148.8941 | BQ46: =(BP46/BL46)*12 -> 0.0725 | BR46: =BR45+BN46 -> 18432.445 | BS46: =BS45+BP46 -> 124994.44 | BT46: =BL46-BN46 -> 520667.55 | BU46: =BR46+BS46 -> 143426.88 | BW46: 39 | BX46: 46023 | BY46: =CG45 -> 520362.23 | BZ46: =BZ45 -> 3586.6458 | CA46: =BZ46-CC46 -> 551.1994 | CB46: =(CA46/BY46)*12 -> 0.012711132 | CC46: =BY46*($BX$3/12) -> 3035.4463 | CD46: =(CC46/BY46)*12 -> 0.07 | CE46: =CE45+CA46 -> 19288.969 | CF46: =CF45+CC46 -> 120590.22 | CG46: =BY46-CA46 -> 519811.03 | CH46: =CE46+CF46 -> 139879.18
J47: 40 | K47: 46054 | L47: =T46 -> 523783.72 | M47: =$L$8/((($N$4)-1)/($N$3*$N$4)) -> 4050.0783 | N47: =M47-P47 -> 449.06517 | O47: =(N47/L47)*12 -> 0.010288182 | P47: =L47*($K$3/12) -> 3601.0131 | Q47: =(P47/L47)*12 -> 0.0825 | R47: =R46+N47 -> 15765.343 | S47: =S46+P47 -> 146237.79 | T47: =L47-N47 -> 523334.66 | U47: =R47+S47 -> 162003.13 | W47: 40 | X47: 46054 | Y47: =AG46 -> 523049.64 | Z47: =Z46 -> 3955.7248 | AA47: =Z47-AC47 -> 468.72719 | AB47: =(AA47/Y47)*12 -> 0.010753714 | AC47: =Y47*($X$3/12) -> 3486.9976 | AD47: =(AC47/Y47)*12 -> 0.08 | AE47: =AE46+AA47 -> 16519.083 | AF47: =AF46+AC47 -> 141709.91 | AG47: =Y47-AA47 -> 522580.92 | AH47: =AE47+AF47 -> 158228.99 | AJ47: 40 | AK47: 46054 | AL47: =AT46 -> 522286.1 | AM47: =AM46 -> 3862.1784 | AN47: =AM47-AP47 -> 489.08067 | AO47: =(AN47/AL47)*12 -> 0.011237075 | AP47: =AL47*($AK$3/12) -> 3373.0977 | AQ47: =(AP47/AL47)*12 -> 0.0775 | AR47: =AR46+AN47 -> 17302.978 | AS47: =AS46+AP47 -> 137184.16 | AT47: =AL47-AN47 -> 521797.02 | AU47: =AR47+AS47 -> 154487.14 | AW47: 40 | AX47: 46054 | AY47: =BG46 -> 521492.33 | AZ47: =AZ46 -> 3769.4654 | BA47: =AZ47-BC47 -> 510.13837 | BB47: =(BA47/AY47)*12 -> 0.011738735 | BC47: =AY47*($AX$3/12) -> 3259.327 | BD47: =(BC47/AY47)*12 -> 0.075 | BE47: =BE46+BA47 -> 18117.811 | BF47: =BF46+BC47 -> 132660.81 | BG47: =AY47-BA47 -> 520982.19 | BH47: =BE47+BF47 -> 150778.62 | BJ47: 40 | BK47: 46054 | BL47: =BT46 -> 520667.55 | BM47: =BM46 -> 3677.6123 | BN47: =BM47-BP47 -> 531.91252 | BO47: =(BN47/BL47)*12 -> 0.012259166 | BP47: =BL47*($BK$3/12) -> 3145.6998 | BQ47: =(BP47/BL47)*12 -> 0.0725 | BR47: =BR46+BN47 -> 18964.358 | BS47: =BS46+BP47 -> 128140.14 | BT47: =BL47-BN47 -> 520135.64 | BU47: =BR47+BS47 -> 147104.49 | BW47: 40 | BX47: 46054 | BY47: =CG46 -> 519811.03 | BZ47: =BZ46 -> 3586.6458 | CA47: =BZ47-CC47 -> 554.41473 | CB47: =(CA47/BY47)*12 -> 0.012798837 | CC47: =BY47*($BX$3/12) -> 3032.231 | CD47: =(CC47/BY47)*12 -> 0.07 | CE47: =CE46+CA47 -> 19843.383 | CF47: =CF46+CC47 -> 123622.45 | CG47: =BY47-CA47 -> 519256.62 | CH47: =CE47+CF47 -> 143465.83
J48: 41 | K48: 46082 | L48: =T47 -> 523334.66 | M48: =$L$8/((($N$4)-1)/($N$3*$N$4)) -> 4050.0783 | N48: =M48-P48 -> 452.15249 | O48: =(N48/L48)*12 -> 0.010367802 | P48: =L48*($K$3/12) -> 3597.9258 | Q48: =(P48/L48)*12 -> 0.0825 | R48: =R47+N48 -> 16217.495 | S48: =S47+P48 -> 149835.71 | T48: =L48-N48 -> 522882.5 | U48: =R48+S48 -> 166053.21 | W48: 41 | X48: 46082 | Y48: =AG47 -> 522580.92 | Z48: =Z47 -> 3955.7248 | AA48: =Z48-AC48 -> 471.85204 | AB48: =(AA48/Y48)*12 -> 0.010835115 | AC48: =Y48*($X$3/12) -> 3483.8728 | AD48: =(AC48/Y48)*12 -> 0.08 | AE48: =AE47+AA48 -> 16990.935 | AF48: =AF47+AC48 -> 145193.78 | AG48: =Y48-AA48 -> 522109.06 | AH48: =AE48+AF48 -> 162184.72 | AJ48: 41 | AK48: 46082 | AL48: =AT47 -> 521797.02 | AM48: =AM47 -> 3862.1784 | AN48: =AM48-AP48 -> 492.23931 | AO48: =(AN48/AL48)*12 -> 0.011320248 | AP48: =AL48*($AK$3/12) -> 3369.9391 | AQ48: =(AP48/AL48)*12 -> 0.0775 | AR48: =AR47+AN48 -> 17795.217 | AS48: =AS47+AP48 -> 140554.1 | AT48: =AL48-AN48 -> 521304.78 | AU48: =AR48+AS48 -> 158349.32 | AW48: 41 | AX48: 46082 | AY48: =BG47 -> 520982.19 | AZ48: =AZ47 -> 3769.4654 | BA48: =AZ48-BC48 -> 513.32673 | BB48: =(BA48/AY48)*12 -> 0.011823669 | BC48: =AY48*($AX$3/12) -> 3256.1387 | BD48: =(BC48/AY48)*12 -> 0.075 | BE48: =BE47+BA48 -> 18631.138 | BF48: =BF47+BC48 -> 135916.94 | BG48: =AY48-BA48 -> 520468.86 | BH48: =BE48+BF48 -> 154548.08 | BJ48: 41 | BK48: 46082 | BL48: =BT47 -> 520135.64 | BM48: =BM47 -> 3677.6123 | BN48: =BM48-BP48 -> 535.12616 | BO48: =(BN48/BL48)*12 -> 0.012345845 | BP48: =BL48*($BK$3/12) -> 3142.4862 | BQ48: =(BP48/BL48)*12 -> 0.0725 | BR48: =BR47+BN48 -> 19499.484 | BS48: =BS47+BP48 -> 131282.62 | BT48: =BL48-BN48 -> 519600.52 | BU48: =BR48+BS48 -> 150782.11 | BW48: 41 | BX48: 46082 | BY48: =CG47 -> 519256.62 | BZ48: =BZ47 -> 3586.6458 | CA48: =BZ48-CC48 -> 557.64882 | CB48: =(CA48/BY48)*12 -> 0.012887242 | CC48: =BY48*($BX$3/12) -> 3028.9969 | CD48: =(CC48/BY48)*12 -> 0.07 | CE48: =CE47+CA48 -> 20401.032 | CF48: =CF47+CC48 -> 126651.44 | CG48: =BY48-CA48 -> 518698.97 | CH48: =CE48+CF48 -> 147052.48
J49: 42 | K49: 46113 | L49: =T48 -> 522882.5 | M49: =$L$8/((($N$4)-1)/($N$3*$N$4)) -> 4050.0783 | N49: =M49-P49 -> 455.26104 | O49: =(N49/L49)*12 -> 0.010448107 | P49: =L49*($K$3/12) -> 3594.8172 | Q49: =(P49/L49)*12 -> 0.0825 | R49: =R48+N49 -> 16672.756 | S49: =S48+P49 -> 153430.53 | T49: =L49-N49 -> 522427.24 | U49: =R49+S49 -> 170103.29 | W49: 42 | X49: 46113 | Y49: =AG48 -> 522109.06 | Z49: =Z48 -> 3955.7248 | AA49: =Z49-AC49 -> 474.99772 | AB49: =(AA49/Y49)*12 -> 0.010917207 | AC49: =Y49*($X$3/12) -> 3480.7271 | AD49: =(AC49/Y49)*12 -> 0.08 | AE49: =AE48+AA49 -> 17465.933 | AF49: =AF48+AC49 -> 148674.51 | AG49: =Y49-AA49 -> 521634.07 | AH49: =AE49+AF49 -> 166140.44 | AJ49: 42 | AK49: 46113 | AL49: =AT48 -> 521304.78 | AM49: =AM48 -> 3862.1784 | AN49: =AM49-AP49 -> 495.41836 | AO49: =(AN49/AL49)*12 -> 0.011404116 | AP49: =AL49*($AK$3/12) -> 3366.7601 | AQ49: =(AP49/AL49)*12 -> 0.0775 | AR49: =AR48+AN49 -> 18290.635 | AS49: =AS48+AP49 -> 143920.86 | AT49: =AL49-AN49 -> 520809.36 | AU49: =AR49+AS49 -> 162211.49 | AW49: 42 | AX49: 46113 | AY49: =BG48 -> 520468.86 | AZ49: =AZ48 -> 3769.4654 | BA49: =AZ49-BC49 -> 516.53503 | BB49: =(BA49/AY49)*12 -> 0.011909301 | BC49: =AY49*($AX$3/12) -> 3252.9304 | BD49: =(BC49/AY49)*12 -> 0.075 | BE49: =BE48+BA49 -> 19147.673 | BF49: =BF48+BC49 -> 139169.87 | BG49: =AY49-BA49 -> 519952.33 | BH49: =BE49+BF49 -> 158317.55 | BJ49: 42 | BK49: 46113 | BL49: =BT48 -> 519600.52 | BM49: =BM48 -> 3677.6123 | BN49: =BM49-BP49 -> 538.35921 | BO49: =(BN49/BL49)*12 -> 0.012433226 | BP49: =BL49*($BK$3/12) -> 3139.2531 | BQ49: =(BP49/BL49)*12 -> 0.0725 | BR49: =BR48+BN49 -> 20037.843 | BS49: =BS48+BP49 -> 134421.87 | BT49: =BL49-BN49 -> 519062.16 | BU49: =BR49+BS49 -> 154459.72 | BW49: 42 | BX49: 46113 | BY49: =CG48 -> 518698.97 | BZ49: =BZ48 -> 3586.6458 | CA49: =BZ49-CC49 -> 560.90177 | CB49: =(CA49/BY49)*12 -> 0.012976354 | CC49: =BY49*($BX$3/12) -> 3025.744 | CD49: =(CC49/BY49)*12 -> 0.07 | CE49: =CE48+CA49 -> 20961.934 | CF49: =CF48+CC49 -> 129677.19 | CG49: =BY49-CA49 -> 518138.07 | CH49: =CE49+CF49 -> 150639.12
J50: 43 | K50: 46143 | L50: =T49 -> 522427.24 | M50: =$L$8/((($N$4)-1)/($N$3*$N$4)) -> 4050.0783 | N50: =M50-P50 -> 458.39096 | O50: =(N50/L50)*12 -> 0.010529105 | P50: =L50*($K$3/12) -> 3591.6873 | Q50: =(P50/L50)*12 -> 0.0825 | R50: =R49+N50 -> 17131.147 | S50: =S49+P50 -> 157022.22 | T50: =L50-N50 -> 521968.85 | U50: =R50+S50 -> 174153.37 | W50: 43 | X50: 46143 | Y50: =AG49 -> 521634.07 | Z50: =Z49 -> 3955.7248 | AA50: =Z50-AC50 -> 478.16437 | AB50: =(AA50/Y50)*12 -> 0.010999996 | AC50: =Y50*($X$3/12) -> 3477.5604 | AD50: =(AC50/Y50)*12 -> 0.08 | AE50: =AE49+AA50 -> 17944.097 | AF50: =AF49+AC50 -> 152152.07 | AG50: =Y50-AA50 -> 521155.9 | AH50: =AE50+AF50 -> 170096.17 | AJ50: 43 | AK50: 46143 | AL50: =AT49 -> 520809.36 | AM50: =AM49 -> 3862.1784 | AN50: =AM50-AP50 -> 498.61794 | AO50: =(AN50/AL50)*12 -> 0.011488686 | AP50: =AL50*($AK$3/12) -> 3363.5605 | AQ50: =(AP50/AL50)*12 -> 0.0775 | AR50: =AR49+AN50 -> 18789.253 | AS50: =AS49+AP50 -> 147284.42 | AT50: =AL50-AN50 -> 520310.75 | AU50: =AR50+AS50 -> 166073.67 | AW50: 43 | AX50: 46143 | AY50: =BG49 -> 519952.33 | AZ50: =AZ49 -> 3769.4654 | BA50: =AZ50-BC50 -> 519.76337 | BB50: =(BA50/AY50)*12 -> 0.011995639 | BC50: =AY50*($AX$3/12) -> 3249.702 | BD50: =(BC50/AY50)*12 -> 0.075 | BE50: =BE49+BA50 -> 19667.436 | BF50: =BF49+BC50 -> 142419.58 | BG50: =AY50-BA50 -> 519432.56 | BH50: =BE50+BF50 -> 162087.01 | BJ50: 43 | BK50: 46143 | BL50: =BT49 -> 519062.16 | BM50: =BM49 -> 3677.6123 | BN50: =BM50-BP50 -> 541.6118 | BO50: =(BN50/BL50)*12 -> 0.012521317 | BP50: =BL50*($BK$3/12) -> 3136.0005 | BQ50: =(BP50/BL50)*12 -> 0.0725 | BR50: =BR49+BN50 -> 20579.455 | BS50: =BS49+BP50 -> 137557.87 | BT50: =BL50-BN50 -> 518520.54 | BU50: =BR50+BS50 -> 158137.33 | BW50: 43 | BX50: 46143 | BY50: =CG49 -> 518138.07 | BZ50: =BZ49 -> 3586.6458 | CA50: =BZ50-CC50 -> 564.1737 | CB50: =(CA50/BY50)*12 -> 0.013066178 | CC50: =BY50*($BX$3/12) -> 3022.4721 | CD50: =(CC50/BY50)*12 -> 0.07 | CE50: =CE49+CA50 -> 21526.108 | CF50: =CF49+CC50 -> 132699.66 | CG50: =BY50-CA50 -> 517573.89 | CH50: =CE50+CF50 -> 154225.77
J51: 44 | K51: 46174 | L51: =T50 -> 521968.85 | M51: =$L$8/((($N$4)-1)/($N$3*$N$4)) -> 4050.0783 | N51: =M51-P51 -> 461.5424 | O51: =(N51/L51)*12 -> 0.010610803 | P51: =L51*($K$3/12) -> 3588.5359 | Q51: =(P51/L51)*12 -> 0.0825 | R51: =R50+N51 -> 17592.69 | S51: =S50+P51 -> 160610.75 | T51: =L51-N51 -> 521507.31 | U51: =R51+S51 -> 178203.44 | W51: 44 | X51: 46174 | Y51: =AG50 -> 521155.9 | Z51: =Z50 -> 3955.7248 | AA51: =Z51-AC51 -> 481.35213 | AB51: =(AA51/Y51)*12 -> 0.011083489 | AC51: =Y51*($X$3/12) -> 3474.3727 | AD51: =(AC51/Y51)*12 -> 0.08 | AE51: =AE50+AA51 -> 18425.449 | AF51: =AF50+AC51 -> 155626.44 | AG51: =Y51-AA51 -> 520674.55 | AH51: =AE51+AF51 -> 174051.89 | AJ51: 44 | AK51: 46174 | AL51: =AT50 -> 520310.75 | AM51: =AM50 -> 3862.1784 | AN51: =AM51-AP51 -> 501.83818 | AO51: =(AN51/AL51)*12 -> 0.011573965 | AP51: =AL51*($AK$3/12) -> 3360.3402 | AQ51: =(AP51/AL51)*12 -> 0.0775 | AR51: =AR50+AN51 -> 19291.092 | AS51: =AS50+AP51 -> 150644.76 | AT51: =AL51-AN51 -> 519808.91 | AU51: =AR51+AS51 -> 169935.85 | AW51: 44 | AX51: 46174 | AY51: =BG50 -> 519432.56 | AZ51: =AZ50 -> 3769.4654 | BA51: =AZ51-BC51 -> 523.01189 | BB51: =(BA51/AY51)*12 -> 0.01208269 | BC51: =AY51*($AX$3/12) -> 3246.4535 | BD51: =(BC51/AY51)*12 -> 0.075 | BE51: =BE50+BA51 -> 20190.448 | BF51: =BF50+BC51 -> 145666.03 | BG51: =AY51-BA51 -> 518909.55 | BH51: =BE51+BF51 -> 165856.48 | BJ51: 44 | BK51: 46174 | BL51: =BT50 -> 518520.54 | BM51: =BM50 -> 3677.6123 | BN51: =BM51-BP51 -> 544.88403 | BO51: =(BN51/BL51)*12 -> 0.012610124 | BP51: =BL51*($BK$3/12) -> 3132.7283 | BQ51: =(BP51/BL51)*12 -> 0.0725 | BR51: =BR50+BN51 -> 21124.339 | BS51: =BS50+BP51 -> 140690.6 | BT51: =BL51-BN51 -> 517975.66 | BU51: =BR51+BS51 -> 161814.94 | BW51: 44 | BX51: 46174 | BY51: =CG50 -> 517573.89 | BZ51: =BZ50 -> 3586.6458 | CA51: =BZ51-CC51 -> 567.46471 | CB51: =(CA51/BY51)*12 -> 0.013156723 | CC51: =BY51*($BX$3/12) -> 3019.181 | CD51: =(CC51/BY51)*12 -> 0.07 | CE51: =CE50+CA51 -> 22093.572 | CF51: =CF50+CC51 -> 135718.84 | CG51: =BY51-CA51 -> 517006.43 | CH51: =CE51+CF51 -> 157812.41
J52: 45 | K52: 46204 | L52: =T51 -> 521507.31 | M52: =$L$8/((($N$4)-1)/($N$3*$N$4)) -> 4050.0783 | N52: =M52-P52 -> 464.7155 | O52: =(N52/L52)*12 -> 0.010693208 | P52: =L52*($K$3/12) -> 3585.3628 | Q52: =(P52/L52)*12 -> 0.0825 | R52: =R51+N52 -> 18057.405 | S52: =S51+P52 -> 164196.12 | T52: =L52-N52 -> 521042.59 | U52: =R52+S52 -> 182253.52 | W52: 45 | X52: 46204 | Y52: =AG51 -> 520674.55 | Z52: =Z51 -> 3955.7248 | AA52: =Z52-AC52 -> 484.56115 | AB52: =(AA52/Y52)*12 -> 0.011167693 | AC52: =Y52*($X$3/12) -> 3471.1637 | AD52: =(AC52/Y52)*12 -> 0.08 | AE52: =AE51+AA52 -> 18910.011 | AF52: =AF51+AC52 -> 159097.61 | AG52: =Y52-AA52 -> 520189.99 | AH52: =AE52+AF52 -> 178007.62 | AJ52: 45 | AK52: 46204 | AL52: =AT51 -> 519808.91 | AM52: =AM51 -> 3862.1784 | AN52: =AM52-AP52 -> 505.07922 | AO52: =(AN52/AL52)*12 -> 0.011659959 | AP52: =AL52*($AK$3/12) -> 3357.0992 | AQ52: =(AP52/AL52)*12 -> 0.0775 | AR52: =AR51+AN52 -> 19796.171 | AS52: =AS51+AP52 -> 154001.86 | AT52: =AL52-AN52 -> 519303.83 | AU52: =AR52+AS52 -> 173798.03 | AW52: 45 | AX52: 46204 | AY52: =BG51 -> 518909.55 | AZ52: =AZ51 -> 3769.4654 | BA52: =AZ52-BC52 -> 526.28072 | BB52: =(BA52/AY52)*12 -> 0.012170461 | BC52: =AY52*($AX$3/12) -> 3243.1847 | BD52: =(BC52/AY52)*12 -> 0.075 | BE52: =BE51+BA52 -> 20716.729 | BF52: =BF51+BC52 -> 148909.22 | BG52: =AY52-BA52 -> 518383.27 | BH52: =BE52+BF52 -> 169625.94 | BJ52: 45 | BK52: 46204 | BL52: =BT51 -> 517975.66 | BM52: =BM51 -> 3677.6123 | BN52: =BM52-BP52 -> 548.17604 | BO52: =(BN52/BL52)*12 -> 0.012699656 | BP52: =BL52*($BK$3/12) -> 3129.4363 | BQ52: =(BP52/BL52)*12 -> 0.0725 | BR52: =BR51+BN52 -> 21672.515 | BS52: =BS51+BP52 -> 143820.04 | BT52: =BL52-BN52 -> 517427.48 | BU52: =BR52+BS52 -> 165492.55 | BW52: 45 | BX52: 46204 | BY52: =CG51 -> 517006.43 | BZ52: =BZ51 -> 3586.6458 | CA52: =BZ52-CC52 -> 570.77492 | CB52: =(CA52/BY52)*12 -> 0.013247996 | CC52: =BY52*($BX$3/12) -> 3015.8708 | CD52: =(CC52/BY52)*12 -> 0.07 | CE52: =CE51+CA52 -> 22664.347 | CF52: =CF51+CC52 -> 138734.71 | CG52: =BY52-CA52 -> 516435.65 | CH52: =CE52+CF52 -> 161399.06
... J342: 335 | K342: 55032 | L342: =T341 -> 96125.8 | M342: =$L$8/((($N$4)-1)/($N$3*$N$4)) -> 4050.0783 | N342: =M342-P342 -> 3389.2134 | O342: =(N342/L342)*12 -> 0.42309724 | P342: =L342*($K$3/12) -> 660.86487 | Q342: =(P342/L342)*12 -> 0.0825 | R342: =R341+N342 -> 446363.41 | S342: =S341+P342 -> 910412.8 | T342: =L342-N342 -> 92736.586 | U342: =R342+S342 -> 1356776.2 | W342: 335 | X342: 55032 | Y342: =AG341 -> 94141.641 | Z342: =Z341 -> 3955.7248 | AA342: =Z342-AC342 -> 3328.1139 | AB342: =(AA342/Y342)*12 -> 0.42422637 | AC342: =Y342*($X$3/12) -> 627.61094 | AD342: =(AC342/Y342)*12 -> 0.08 | AE342: =AE341+AA342 -> 448286.47 | AF342: =AF341+AC342 -> 876881.34 | AG342: =Y342-AA342 -> 90813.527 | AH342: =AE342+AF342 -> 1325167.8 | AJ342: 335 | AK342: 55032 | AL342: =AT341 -> 92165.516 | AM342: =AM341 -> 3862.1784 | AN342: =AM342-AP342 -> 3266.9428 | AO342: =(AN342/AL342)*12 -> 0.42535772 | AP342: =AL342*($AK$3/12) -> 595.23562 | AQ342: =(AP342/AL342)*12 -> 0.0775 | AR342: =AR341+AN342 -> 450201.43 | AS342: =AS341+AP342 -> 843628.34 | AT342: =AL342-AN342 -> 88898.573 | AU342: =AR342+AS342 -> 1293829.8 | AW342: 335 | AX342: 55032 | AY342: =BG341 -> 90198.146 | AZ342: =AZ341 -> 3769.4654 | BA342: =AZ342-BC342 -> 3205.727 | BB342: =(BA342/AY342)*12 -> 0.42649129 | BC342: =AY342*($AX$3/12) -> 563.73841 | BD342: =(BC342/AY342)*12 -> 0.075 | BE342: =BE341+BA342 -> 452107.58 | BF342: =BF341+BC342 -> 810663.33 | BG342: =AY342-BA342 -> 86992.419 | BH342: =BE342+BF342 -> 1262770.9 | BJ342: 335 | BK342: 55032 | BL342: =BT341 -> 88240.266 | BM342: =BM341 -> 3677.6123 | BN342: =BM342-BP342 -> 3144.4941 | BO342: =(BN342/BL342)*12 -> 0.4276271 | BP342: =BL342*($BK$3/12) -> 533.11827 | BQ342: =(BP342/BL342)*12 -> 0.0725 | BR342: =BR341+BN342 -> 454004.23 | BS342: =BS341+BP342 -> 777995.9 | BT342: =BL342-BN342 -> 85095.772 | BU342: =BR342+BS342 -> 1232000.1 | BW342: 335 | BX342: 55032 | BY342: =CG341 -> 86292.619 | BZ342: =BZ341 -> 3586.6458 | CA342: =BZ342-CC342 -> 3083.2721 | CB342: =(CA342/BY342)*12 -> 0.42876513 | CC342: =BY342*($BX$3/12) -> 503.37361 | CD342: =(CC342/BY342)*12 -> 0.07 | CE342: =CE341+CA342 -> 455890.65 | CF342: =CF341+CC342 -> 745635.67 | CG342: =BY342-CA342 -> 83209.347 | CH342: =CE342+CF342 -> 1201526.3
J343: =J342+1 -> 336 | L343: =T342 -> 92736.586 | M343: =$L$8/((($N$4)-1)/($N$3*$N$4)) -> 4050.0783 | N343: =M343-P343 -> 3412.5142 | O343: =(N343/L343)*12 -> 0.44157514 | P343: =L343*($K$3/12) -> 637.56403 | Q343: =(P343/L343)*12 -> 0.0825 | R343: =R342+N343 -> 449775.93 | S343: =S342+P343 -> 911050.37 | T343: =L343-N343 -> 89324.072 | U343: =R343+S343 -> 1360826.3 | W343: =W342+1 -> 336 | Y343: =AG342 -> 90813.527 | Z343: =Z342 -> 3955.7248 | AA343: =Z343-AC343 -> 3350.3013 | AB343: =(AA343/Y343)*12 -> 0.44270514 | AC343: =Y343*($X$3/12) -> 605.42352 | AD343: =(AC343/Y343)*12 -> 0.08 | AE343: =AE342+AA343 -> 451636.77 | AF343: =AF342+AC343 -> 877486.76 | AG343: =Y343-AA343 -> 87463.226 | AH343: =AE343+AF343 -> 1329123.5 | AJ343: =AJ342+1 -> 336 | AL343: =AT342 -> 88898.573 | AM343: =AM342 -> 3862.1784 | AN343: =AM343-AP343 -> 3288.0418 | AO343: =(AN343/AL343)*12 -> 0.44383729 | AP343: =AL343*($AK$3/12) -> 574.13662 | AQ343: =(AP343/AL343)*12 -> 0.0775 | AR343: =AR342+AN343 -> 453489.47 | AS343: =AS342+AP343 -> 844202.48 | AT343: =AL343-AN343 -> 85610.531 | AU343: =AR343+AS343 -> 1297691.9 | AW343: =AW342+1 -> 336 | AY343: =BG342 -> 86992.419 | AZ343: =AZ342 -> 3769.4654 | BA343: =AZ343-BC343 -> 3225.7628 | BB343: =(BA343/AY343)*12 -> 0.44497157 | BC343: =AY343*($AX$3/12) -> 543.70262 | BD343: =(BC343/AY343)*12 -> 0.075 | BE343: =BE342+BA343 -> 455333.34 | BF343: =BF342+BC343 -> 811207.04 | BG343: =AY343-BA343 -> 83766.656 | BH343: =BE343+BF343 -> 1266540.4 | BJ343: =BJ342+1 -> 336 | BL343: =BT342 -> 85095.772 | BM343: =BM342 -> 3677.6123 | BN343: =BM343-BP343 -> 3163.492 | BO343: =(BN343/BL343)*12 -> 0.446108 | BP343: =BL343*($BK$3/12) -> 514.12029 | BQ343: =(BP343/BL343)*12 -> 0.0725 | BR343: =BR342+BN343 -> 457167.72 | BS343: =BS342+BP343 -> 778510.02 | BT343: =BL343-BN343 -> 81932.28 | BU343: =BR343+BS343 -> 1235677.7 | BW343: =BW342+1 -> 336 | BY343: =CG342 -> 83209.347 | BZ343: =BZ342 -> 3586.6458 | CA343: =BZ343-CC343 -> 3101.2579 | CB343: =(CA343/BY343)*12 -> 0.44724657 | CC343: =BY343*($BX$3/12) -> 485.38786 | CD343: =(CC343/BY343)*12 -> 0.07 | CE343: =CE342+CA343 -> 458991.91 | CF343: =CF342+CC343 -> 746121.06 | CG343: =BY343-CA343 -> 80108.089 | CH343: =CE343+CF343 -> 1205113
J344: =J343+1 -> 337 | L344: =T343 -> 89324.072 | M344: =$L$8/((($N$4)-1)/($N$3*$N$4)) -> 4050.0783 | N344: =M344-P344 -> 3435.9753 | O344: =(N344/L344)*12 -> 0.46159677 | P344: =L344*($K$3/12) -> 614.10299 | Q344: =(P344/L344)*12 -> 0.0825 | R344: =R343+N344 -> 453211.9 | S344: =S343+P344 -> 911664.47 | T344: =L344-N344 -> 85888.097 | U344: =R344+S344 -> 1364876.4 | W344: =W343+1 -> 337 | Y344: =AG343 -> 87463.226 | Z344: =Z343 -> 3955.7248 | AA344: =Z344-AC344 -> 3372.6366 | AB344: =(AA344/Y344)*12 -> 0.4627275 | AC344: =Y344*($X$3/12) -> 583.08817 | AD344: =(AC344/Y344)*12 -> 0.08 | AE344: =AE343+AA344 -> 455009.41 | AF344: =AF343+AC344 -> 878069.85 | AG344: =Y344-AA344 -> 84090.589 | AH344: =AE344+AF344 -> 1333079.3 | AJ344: =AJ343+1 -> 337 | AL344: =AT343 -> 85610.531 | AM344: =AM343 -> 3862.1784 | AN344: =AM344-AP344 -> 3309.2771 | AO344: =(AN344/AL344)*12 -> 0.46386028 | AP344: =AL344*($AK$3/12) -> 552.90135 | AQ344: =(AP344/AL344)*12 -> 0.0775 | AR344: =AR343+AN344 -> 456798.75 | AS344: =AS343+AP344 -> 844755.38 | AT344: =AL344-AN344 -> 82301.254 | AU344: =AR344+AS344 -> 1301554.1 | AW344: =AW343+1 -> 337 | AY344: =BG343 -> 83766.656 | AZ344: =AZ343 -> 3769.4654 | BA344: =AZ344-BC344 -> 3245.9238 | BB344: =(BA344/AY344)*12 -> 0.46499511 | BC344: =AY344*($AX$3/12) -> 523.5416 | BD344: =(BC344/AY344)*12 -> 0.075 | BE344: =BE343+BA344 -> 458579.27 | BF344: =BF343+BC344 -> 811730.58 | BG344: =AY344-BA344 -> 80520.733 | BH344: =BE344+BF344 -> 1270309.8 | BJ344: =BJ343+1 -> 337 | BL344: =BT343 -> 81932.28 | BM344: =BM343 -> 3677.6123 | BN344: =BM344-BP344 -> 3182.6048 | BO344: =(BN344/BL344)*12 -> 0.466132 | BP344: =BL344*($BK$3/12) -> 495.00752 | BQ344: =(BP344/BL344)*12 -> 0.0725 | BR344: =BR343+BN344 -> 460350.33 | BS344: =BS343+BP344 -> 779005.03 | BT344: =BL344-BN344 -> 78749.675 | BU344: =BR344+BS344 -> 1239355.4 | BW344: =BW343+1 -> 337 | BY344: =CG343 -> 80108.089 | BZ344: =BZ343 -> 3586.6458 | CA344: =BZ344-CC344 -> 3119.3486 | CB344: =(CA344/BY344)*12 -> 0.46727095 | CC344: =BY344*($BX$3/12) -> 467.29719 | CD344: =(CC344/BY344)*12 -> 0.07 | CE344: =CE343+CA344 -> 462111.26 | CF344: =CF343+CC344 -> 746588.36 | CG344: =BY344-CA344 -> 76988.74 | CH344: =CE344+CF344 -> 1208699.6
J345: =J344+1 -> 338 | L345: =T344 -> 85888.097 | M345: =$L$8/((($N$4)-1)/($N$3*$N$4)) -> 4050.0783 | N345: =M345-P345 -> 3459.5976 | O345: =(N345/L345)*12 -> 0.4833635 | P345: =L345*($K$3/12) -> 590.48066 | Q345: =(P345/L345)*12 -> 0.0825 | R345: =R344+N345 -> 456671.5 | S345: =S344+P345 -> 912254.95 | T345: =L345-N345 -> 82428.499 | U345: =R345+S345 -> 1368926.5 | W345: =W344+1 -> 338 | Y345: =AG344 -> 84090.589 | Z345: =Z344 -> 3955.7248 | AA345: =Z345-AC345 -> 3395.1209 | AB345: =(AA345/Y345)*12 -> 0.48449477 | AC345: =Y345*($X$3/12) -> 560.60393 | AD345: =(AC345/Y345)*12 -> 0.08 | AE345: =AE344+AA345 -> 458404.53 | AF345: =AF344+AC345 -> 878630.46 | AG345: =Y345-AA345 -> 80695.469 | AH345: =AE345+AF345 -> 1337035 | AJ345: =AJ344+1 -> 338 | AL345: =AT344 -> 82301.254 | AM345: =AM344 -> 3862.1784 | AN345: =AM345-AP345 -> 3330.6495 | AO345: =(AN345/AL345)*12 -> 0.485628 | AP345: =AL345*($AK$3/12) -> 531.52893 | AQ345: =(AP345/AL345)*12 -> 0.0775 | AR345: =AR344+AN345 -> 460129.4 | AS345: =AS344+AP345 -> 845286.91 | AT345: =AL345-AN345 -> 78970.605 | AU345: =AR345+AS345 -> 1305416.3 | AW345: =AW344+1 -> 338 | AY345: =BG344 -> 80520.733 | AZ345: =AZ344 -> 3769.4654 | BA345: =AZ345-BC345 -> 3266.2108 | BB345: =(BA345/AY345)*12 -> 0.48676321 | BC345: =AY345*($AX$3/12) -> 503.25458 | BD345: =(BC345/AY345)*12 -> 0.075 | BE345: =BE344+BA345 -> 461845.48 | BF345: =BF344+BC345 -> 812233.83 | BG345: =AY345-BA345 -> 77254.522 | BH345: =BE345+BF345 -> 1274079.3 | BJ345: =BJ344+1 -> 338 | BL345: =BT344 -> 78749.675 | BM345: =BM344 -> 3677.6123 | BN345: =BM345-BP345 -> 3201.833 | BO345: =(BN345/BL345)*12 -> 0.48790038 | BP345: =BL345*($BK$3/12) -> 475.77929 | BQ345: =(BP345/BL345)*12 -> 0.0725 | BR345: =BR344+BN345 -> 463552.16 | BS345: =BS344+BP345 -> 779480.81 | BT345: =BL345-BN345 -> 75547.842 | BU345: =BR345+BS345 -> 1243033 | BW345: =BW344+1 -> 338 | BY345: =CG344 -> 76988.74 | BZ345: =BZ344 -> 3586.6458 | CA345: =BZ345-CC345 -> 3137.5448 | CB345: =(CA345/BY345)*12 -> 0.48903953 | CC345: =BY345*($BX$3/12) -> 449.10099 | CD345: =(CC345/BY345)*12 -> 0.07 | CE345: =CE344+CA345 -> 465248.8 | CF345: =CF344+CC345 -> 747037.46 | CG345: =BY345-CA345 -> 73851.196 | CH345: =CE345+CF345 -> 1212286.3
J346: =J345+1 -> 339 | L346: =T345 -> 82428.499 | M346: =$L$8/((($N$4)-1)/($N$3*$N$4)) -> 4050.0783 | N346: =M346-P346 -> 3483.3823 | O346: =(N346/L346)*12 -> 0.5071133 | P346: =L346*($K$3/12) -> 566.69593 | Q346: =(P346/L346)*12 -> 0.0825 | R346: =R345+N346 -> 460154.88 | S346: =S345+P346 -> 912821.65 | T346: =L346-N346 -> 78945.117 | U346: =R346+S346 -> 1372976.5 | W346: =W345+1 -> 339 | Y346: =AG345 -> 80695.469 | Z346: =Z345 -> 3955.7248 | AA346: =Z346-AC346 -> 3417.755 | AB346: =(AA346/Y346)*12 -> 0.5082449 | AC346: =Y346*($X$3/12) -> 537.96979 | AD346: =(AC346/Y346)*12 -> 0.08 | AE346: =AE345+AA346 -> 461822.29 | AF346: =AF345+AC346 -> 879168.43 | AG346: =Y346-AA346 -> 77277.714 | AH346: =AE346+AF346 -> 1340990.7 | AJ346: =AJ345+1 -> 339 | AL346: =AT345 -> 78970.605 | AM346: =AM345 -> 3862.1784 | AN346: =AM346-AP346 -> 3352.1599 | AO346: =(AN346/AL346)*12 -> 0.50937838 | AP346: =AL346*($AK$3/12) -> 510.01849 | AQ346: =(AP346/AL346)*12 -> 0.0775 | AR346: =AR345+AN346 -> 463481.56 | AS346: =AS345+AP346 -> 845796.93 | AT346: =AL346-AN346 -> 75618.445 | AU346: =AR346+AS346 -> 1309278.5 | AW346: =AW345+1 -> 339 | AY346: =BG345 -> 77254.522 | AZ346: =AZ345 -> 3769.4654 | BA346: =AZ346-BC346 -> 3286.6247 | BB346: =(BA346/AY346)*12 -> 0.51051375 | BC346: =AY346*($AX$3/12) -> 482.84076 | BD346: =(BC346/AY346)*12 -> 0.075 | BE346: =BE345+BA346 -> 465132.1 | BF346: =BF345+BC346 -> 812716.67 | BG346: =AY346-BA346 -> 73967.897 | BH346: =BE346+BF346 -> 1277848.8 | BJ346: =BJ345+1 -> 339 | BL346: =BT345 -> 75547.842 | BM346: =BM345 -> 3677.6123 | BN346: =BM346-BP346 -> 3221.1774 | BO346: =(BN346/BL346)*12 -> 0.51165101 | BP346: =BL346*($BK$3/12) -> 456.43488 | BQ346: =(BP346/BL346)*12 -> 0.0725 | BR346: =BR345+BN346 -> 466773.34 | BS346: =BS345+BP346 -> 779937.24 | BT346: =BL346-BN346 -> 72326.665 | BU346: =BR346+BS346 -> 1246710.6 | BW346: =BW345+1 -> 339 | BY346: =CG345 -> 73851.196 | BZ346: =BZ345 -> 3586.6458 | CA346: =BZ346-CC346 -> 3155.8471 | CB346: =(CA346/BY346)*12 -> 0.51279014 | CC346: =BY346*($BX$3/12) -> 430.79864 | CD346: =(CC346/BY346)*12 -> 0.07 | CE346: =CE345+CA346 -> 468404.65 | CF346: =CF345+CC346 -> 747468.26 | CG346: =BY346-CA346 -> 70695.349 | CH346: =CE346+CF346 -> 1215872.9
J347: =J346+1 -> 340 | L347: =T346 -> 78945.117 | M347: =$L$8/((($N$4)-1)/($N$3*$N$4)) -> 4050.0783 | N347: =M347-P347 -> 3507.3306 | O347: =(N347/L347)*12 -> 0.53312945 | P347: =L347*($K$3/12) -> 542.74768 | Q347: =(P347/L347)*12 -> 0.0825 | R347: =R346+N347 -> 463662.21 | S347: =S346+P347 -> 913364.4 | T347: =L347-N347 -> 75437.786 | U347: =R347+S347 -> 1377026.6 | W347: =W346+1 -> 340 | Y347: =AG346 -> 77277.714 | Z347: =Z346 -> 3955.7248 | AA347: =Z347-AC347 -> 3440.5401 | AB347: =(AA347/Y347)*12 -> 0.53426116 | AC347: =Y347*($X$3/12) -> 515.18476 | AD347: =(AC347/Y347)*12 -> 0.08 | AE347: =AE346+AA347 -> 465262.83 | AF347: =AF346+AC347 -> 879683.61 | AG347: =Y347-AA347 -> 73837.173 | AH347: =AE347+AF347 -> 1344946.4 | AJ347: =AJ346+1 -> 340 | AL347: =AT346 -> 75618.445 | AM347: =AM346 -> 3862.1784 | AN347: =AM347-AP347 -> 3373.8093 | AO347: =(AN347/AL347)*12 -> 0.53539466 | AP347: =AL347*($AK$3/12) -> 488.36912 | AQ347: =(AP347/AL347)*12 -> 0.0775 | AR347: =AR346+AN347 -> 466855.36 | AS347: =AS346+AP347 -> 846285.3 | AT347: =AL347-AN347 -> 72244.636 | AU347: =AR347+AS347 -> 1313140.7 | AW347: =AW346+1 -> 340 | AY347: =BG346 -> 73967.897 | AZ347: =AZ346 -> 3769.4654 | BA347: =AZ347-BC347 -> 3307.1661 | BB347: =(BA347/AY347)*12 -> 0.53652996 | BC347: =AY347*($AX$3/12) -> 462.29936 | BD347: =(BC347/AY347)*12 -> 0.075 | BE347: =BE346+BA347 -> 468439.27 | BF347: =BF346+BC347 -> 813178.97 | BG347: =AY347-BA347 -> 70660.731 | BH347: =BE347+BF347 -> 1281618.2 | BJ347: =BJ346+1 -> 340 | BL347: =BT346 -> 72326.665 | BM347: =BM346 -> 3677.6123 | BN347: =BM347-BP347 -> 3240.6387 | BO347: =(BN347/BL347)*12 -> 0.53766706 | BP347: =BL347*($BK$3/12) -> 436.9736 | BQ347: =(BP347/BL347)*12 -> 0.0725 | BR347: =BR346+BN347 -> 470013.97 | BS347: =BS346+BP347 -> 780374.22 | BT347: =BL347-BN347 -> 69086.026 | BU347: =BR347+BS347 -> 1250388.2 | BW347: =BW346+1 -> 340 | BY347: =CG346 -> 70695.349 | BZ347: =BZ346 -> 3586.6458 | CA347: =BZ347-CC347 -> 3174.2562 | CB347: =(CA347/BY347)*12 -> 0.53880595 | CC347: =BY347*($BX$3/12) -> 412.38953 | CD347: =(CC347/BY347)*12 -> 0.07 | CE347: =CE346+CA347 -> 471578.91 | CF347: =CF346+CC347 -> 747880.65 | CG347: =BY347-CA347 -> 67521.092 | CH347: =CE347+CF347 -> 1219459.6
J348: =J347+1 -> 341 | L348: =T347 -> 75437.786 | M348: =$L$8/((($N$4)-1)/($N$3*$N$4)) -> 4050.0783 | N348: =M348-P348 -> 3531.4435 | O348: =(N348/L348)*12 -> 0.56175193 | P348: =L348*($K$3/12) -> 518.63478 | Q348: =(P348/L348)*12 -> 0.0825 | R348: =R347+N348 -> 467193.66 | S348: =S347+P348 -> 913883.03 | T348: =L348-N348 -> 71906.343 | U348: =R348+S348 -> 1381076.7 | W348: =W347+1 -> 341 | Y348: =AG347 -> 73837.173 | Z348: =Z347 -> 3955.7248 | AA348: =Z348-AC348 -> 3463.477 | AB348: =(AA348/Y348)*12 -> 0.56288346 | AC348: =Y348*($X$3/12) -> 492.24782 | AD348: =(AC348/Y348)*12 -> 0.08 | AE348: =AE347+AA348 -> 468726.3 | AF348: =AF347+AC348 -> 880175.86 | AG348: =Y348-AA348 -> 70373.696 | AH348: =AE348+AF348 -> 1348902.2 | AJ348: =AJ347+1 -> 341 | AL348: =AT347 -> 72244.636 | AM348: =AM347 -> 3862.1784 | AN348: =AM348-AP348 -> 3395.5985 | AO348: =(AN348/AL348)*12 -> 0.56401671 | AP348: =AL348*($AK$3/12) -> 466.57994 | AQ348: =(AP348/AL348)*12 -> 0.0775 | AR348: =AR347+AN348 -> 470250.96 | AS348: =AS347+AP348 -> 846751.88 | AT348: =AL348-AN348 -> 68849.037 | AU348: =AR348+AS348 -> 1317002.8 | AW348: =AW347+1 -> 341 | AY348: =BG347 -> 70660.731 | AZ348: =AZ347 -> 3769.4654 | BA348: =AZ348-BC348 -> 3327.8358 | BB348: =(BA348/AY348)*12 -> 0.56515167 | BC348: =AY348*($AX$3/12) -> 441.62957 | BD348: =(BC348/AY348)*12 -> 0.075 | BE348: =BE347+BA348 -> 471767.1 | BF348: =BF347+BC348 -> 813620.6 | BG348: =AY348-BA348 -> 67332.895 | BH348: =BE348+BF348 -> 1285387.7 | BJ348: =BJ347+1 -> 341 | BL348: =BT347 -> 69086.026 | BM348: =BM347 -> 3677.6123 | BN348: =BM348-BP348 -> 3260.2176 | BO348: =(BN348/BL348)*12 -> 0.56628834 | BP348: =BL348*($BK$3/12) -> 417.39474 | BQ348: =(BP348/BL348)*12 -> 0.0725 | BR348: =BR347+BN348 -> 473274.19 | BS348: =BS347+BP348 -> 780791.61 | BT348: =BL348-BN348 -> 65825.808 | BU348: =BR348+BS348 -> 1254065.8 | BW348: =BW347+1 -> 341 | BY348: =CG347 -> 67521.092 | BZ348: =BZ347 -> 3586.6458 | CA348: =BZ348-CC348 -> 3192.7727 | CB348: =(CA348/BY348)*12 -> 0.56742673 | CC348: =BY348*($BX$3/12) -> 393.87304 | CD348: =(CC348/BY348)*12 -> 0.07 | CE348: =CE347+CA348 -> 474771.68 | CF348: =CF347+CC348 -> 748274.52 | CG348: =BY348-CA348 -> 64328.32 | CH348: =CE348+CF348 -> 1223046.2
J349: =J348+1 -> 342 | L349: =T348 -> 71906.343 | M349: =$L$8/((($N$4)-1)/($N$3*$N$4)) -> 4050.0783 | N349: =M349-P349 -> 3555.7222 | O349: =(N349/L349)*12 -> 0.59339224 | P349: =L349*($K$3/12) -> 494.35611 | Q349: =(P349/L349)*12 -> 0.0825 | R349: =R348+N349 -> 470749.38 | S349: =S348+P349 -> 914377.39 | T349: =L349-N349 -> 68350.62 | U349: =R349+S349 -> 1385126.8 | W349: =W348+1 -> 342 | Y349: =AG348 -> 70373.696 | Z349: =Z348 -> 3955.7248 | AA349: =Z349-AC349 -> 3486.5668 | AB349: =(AA349/Y349)*12 -> 0.5945233 | AC349: =Y349*($X$3/12) -> 469.15798 | AD349: =(AC349/Y349)*12 -> 0.08 | AE349: =AE348+AA349 -> 472212.87 | AF349: =AF348+AC349 -> 880645.02 | AG349: =Y349-AA349 -> 66887.13 | AH349: =AE349+AF349 -> 1352857.9 | AJ349: =AJ348+1 -> 342 | AL349: =AT348 -> 68849.037 | AM349: =AM348 -> 3862.1784 | AN349: =AM349-AP349 -> 3417.5284 | AO349: =(AN349/AL349)*12 -> 0.59565598 | AP349: =AL349*($AK$3/12) -> 444.65003 | AQ349: =(AP349/AL349)*12 -> 0.0775 | AR349: =AR348+AN349 -> 473668.49 | AS349: =AS348+AP349 -> 847196.53 | AT349: =AL349-AN349 -> 65431.509 | AU349: =AR349+AS349 -> 1320865 | AW349: =AW348+1 -> 342 | AY349: =BG348 -> 67332.895 | AZ349: =AZ348 -> 3769.4654 | BA349: =AZ349-BC349 -> 3348.6348 | BB349: =(BA349/AY349)*12 -> 0.59679029 | BC349: =AY349*($AX$3/12) -> 420.83059 | BD349: =(BC349/AY349)*12 -> 0.075 | BE349: =BE348+BA349 -> 475115.74 | BF349: =BF348+BC349 -> 814041.43 | BG349: =AY349-BA349 -> 63984.26 | BH349: =BE349+BF349 -> 1289157.2 | BJ349: =BJ348+1 -> 342 | BL349: =BT348 -> 65825.808 | BM349: =BM348 -> 3677.6123 | BN349: =BM349-BP349 -> 3279.9147 | BO349: =(BN349/BL349)*12 -> 0.59792622 | BP349: =BL349*($BK$3/12) -> 397.69759 | BQ349: =(BP349/BL349)*12 -> 0.0725 | BR349: =BR348+BN349 -> 476554.11 | BS349: =BS348+BP349 -> 781189.31 | BT349: =BL349-BN349 -> 62545.893 | BU349: =BR349+BS349 -> 1257743.4 | BW349: =BW348+1 -> 342 | BY349: =CG348 -> 64328.32 | BZ349: =BZ348 -> 3586.6458 | CA349: =BZ349-CC349 -> 3211.3972 | CB349: =(CA349/BY349)*12 -> 0.59906379 | CC349: =BY349*($BX$3/12) -> 375.24853 | CD349: =(CC349/BY349)*12 -> 0.07 | CE349: =CE348+CA349 -> 477983.08 | CF349: =CF348+CC349 -> 748649.77 | CG349: =BY349-CA349 -> 61116.922 | CH349: =CE349+CF349 -> 1226632.8
J350: =J349+1 -> 343 | L350: =T349 -> 68350.62 | M350: =$L$8/((($N$4)-1)/($N$3*$N$4)) -> 4050.0783 | N350: =M350-P350 -> 3580.1677 | O350: =(N350/L350)*12 -> 0.62855337 | P350: =L350*($K$3/12) -> 469.91052 | Q350: =(P350/L350)*12 -> 0.0825 | R350: =R349+N350 -> 474329.55 | S350: =S349+P350 -> 914847.3 | T350: =L350-N350 -> 64770.453 | U350: =R350+S350 -> 1389176.8 | W350: =W349+1 -> 343 | Y350: =AG349 -> 66887.13 | Z350: =Z349 -> 3955.7248 | AA350: =Z350-AC350 -> 3509.8106 | AB350: =(AA350/Y350)*12 -> 0.62968358 | AC350: =Y350*($X$3/12) -> 445.9142 | AD350: =(AC350/Y350)*12 -> 0.08 | AE350: =AE349+AA350 -> 475722.68 | AF350: =AF349+AC350 -> 881090.93 | AG350: =Y350-AA350 -> 63377.319 | AH350: =AE350+AF350 -> 1356813.6 | AJ350: =AJ349+1 -> 343 | AL350: =AT349 -> 65431.509 | AM350: =AM349 -> 3862.1784 | AN350: =AM350-AP350 -> 3439.5999 | AO350: =(AN350/AL350)*12 -> 0.63081533 | AP350: =AL350*($AK$3/12) -> 422.57849 | AQ350: =(AP350/AL350)*12 -> 0.0775 | AR350: =AR349+AN350 -> 477108.09 | AS350: =AS349+AP350 -> 847619.11 | AT350: =AL350-AN350 -> 61991.909 | AU350: =AR350+AS350 -> 1324727.2 | AW350: =AW349+1 -> 343 | AY350: =BG349 -> 63984.26 | AZ350: =AZ349 -> 3769.4654 | BA350: =AZ350-BC350 -> 3369.5638 | BB350: =(BA350/AY350)*12 -> 0.63194863 | BC350: =AY350*($AX$3/12) -> 399.90163 | BD350: =(BC350/AY350)*12 -> 0.075 | BE350: =BE349+BA350 -> 478485.3 | BF350: =BF349+BC350 -> 814441.33 | BG350: =AY350-BA350 -> 60614.697 | BH350: =BE350+BF350 -> 1292926.6 | BJ350: =BJ349+1 -> 343 | BL350: =BT349 -> 62545.893 | BM350: =BM349 -> 3677.6123 | BN350: =BM350-BP350 -> 3299.7309 | BO350: =(BN350/BL350)*12 -> 0.63308346 | BP350: =BL350*($BK$3/12) -> 377.88144 | BQ350: =(BP350/BL350)*12 -> 0.0725 | BR350: =BR349+BN350 -> 479853.84 | BS350: =BS349+BP350 -> 781567.19 | BT350: =BL350-BN350 -> 59246.163 | BU350: =BR350+BS350 -> 1261421 | BW350: =BW349+1 -> 343 | BY350: =CG349 -> 61116.922 | BZ350: =BZ349 -> 3586.6458 | CA350: =BZ350-CC350 -> 3230.1304 | CB350: =(CA350/BY350)*12 -> 0.63421984 | CC350: =BY350*($BX$3/12) -> 356.51538 | CD350: =(CC350/BY350)*12 -> 0.07 | CE350: =CE349+CA350 -> 481213.21 | CF350: =CF349+CC350 -> 749006.28 | CG350: =BY350-CA350 -> 57886.792 | CH350: =CE350+CF350 -> 1230219.5
J351: =J350+1 -> 344 | L351: =T350 -> 64770.453 | M351: =$L$8/((($N$4)-1)/($N$3*$N$4)) -> 4050.0783 | N351: =M351-P351 -> 3604.7814 | O351: =(N351/L351)*12 -> 0.66785664 | P351: =L351*($K$3/12) -> 445.29686 | Q351: =(P351/L351)*12 -> 0.0825 | R351: =R350+N351 -> 477934.33 | S351: =S350+P351 -> 915292.59 | T351: =L351-N351 -> 61165.671 | U351: =R351+S351 -> 1393226.9 | W351: =W350+1 -> 344 | Y351: =AG350 -> 63377.319 | Z351: =Z350 -> 3955.7248 | AA351: =Z351-AC351 -> 3533.2094 | AB351: =(AA351/Y351)*12 -> 0.66898558 | AC351: =Y351*($X$3/12) -> 422.51546 | AD351: =(AC351/Y351)*12 -> 0.08 | AE351: =AE350+AA351 -> 479255.89 | AF351: =AF350+AC351 -> 881513.45 | AG351: =Y351-AA351 -> 59844.11 | AH351: =AE351+AF351 -> 1360769.3 | AJ351: =AJ350+1 -> 344 | AL351: =AT350 -> 61991.909 | AM351: =AM350 -> 3862.1784 | AN351: =AM351-AP351 -> 3461.814 | AO351: =(AN351/AL351)*12 -> 0.67011597 | AP351: =AL351*($AK$3/12) -> 400.36441 | AQ351: =(AP351/AL351)*12 -> 0.0775 | AR351: =AR350+AN351 -> 480569.91 | AS351: =AS350+AP351 -> 848019.47 | AT351: =AL351-AN351 -> 58530.095 | AU351: =AR351+AS351 -> 1328589.4 | AW351: =AW350+1 -> 344 | AY351: =BG350 -> 60614.697 | AZ351: =AZ350 -> 3769.4654 | BA351: =AZ351-BC351 -> 3390.6236 | BB351: =(BA351/AY351)*12 -> 0.67124782 | BC351: =AY351*($AX$3/12) -> 378.84185 | BD351: =(BC351/AY351)*12 -> 0.075 | BE351: =BE350+BA351 -> 481875.93 | BF351: =BF350+BC351 -> 814820.18 | BG351: =AY351-BA351 -> 57224.073 | BH351: =BE351+BF351 -> 1296696.1 | BJ351: =BJ350+1 -> 344 | BL351: =BT350 -> 59246.163 | BM351: =BM350 -> 3677.6123 | BN351: =BM351-BP351 -> 3319.6668 | BO351: =(BN351/BL351)*12 -> 0.67238112 | BP351: =BL351*($BK$3/12) -> 357.94557 | BQ351: =(BP351/BL351)*12 -> 0.0725 | BR351: =BR350+BN351 -> 483173.5 | BS351: =BS350+BP351 -> 781925.14 | BT351: =BL351-BN351 -> 55926.496 | BU351: =BR351+BS351 -> 1265098.6 | BW351: =BW350+1 -> 344 | BY351: =CG350 -> 57886.792 | BZ351: =BZ350 -> 3586.6458 | CA351: =BZ351-CC351 -> 3248.9728 | CB351: =(CA351/BY351)*12 -> 0.67351588 | CC351: =BY351*($BX$3/12) -> 337.67295 | CD351: =(CC351/BY351)*12 -> 0.07 | CE351: =CE350+CA351 -> 484462.18 | CF351: =CF350+CC351 -> 749343.96 | CG351: =BY351-CA351 -> 54637.819 | CH351: =CE351+CF351 -> 1233806.1
J352: =J351+1 -> 345 | L352: =T351 -> 61165.671 | M352: =$L$8/((($N$4)-1)/($N$3*$N$4)) -> 4050.0783 | N352: =M352-P352 -> 3629.5643 | O352: =(N352/L352)*12 -> 0.71207869 | P352: =L352*($K$3/12) -> 420.51399 | Q352: =(P352/L352)*12 -> 0.0825 | R352: =R351+N352 -> 481563.89 | S352: =S351+P352 -> 915713.11 | T352: =L352-N352 -> 57536.107 | U352: =R352+S352 -> 1397277 | W352: =W351+1 -> 345 | Y352: =AG351 -> 59844.11 | Z352: =Z351 -> 3955.7248 | AA352: =Z352-AC352 -> 3556.7641 | AB352: =(AA352/Y352)*12 -> 0.71320585 | AC352: =Y352*($X$3/12) -> 398.96073 | AD352: =(AC352/Y352)*12 -> 0.08 | AE352: =AE351+AA352 -> 482812.65 | AF352: =AF351+AC352 -> 881912.41 | AG352: =Y352-AA352 -> 56287.346 | AH352: =AE352+AF352 -> 1364725.1 | AJ352: =AJ351+1 -> 345 | AL352: =AT351 -> 58530.095 | AM352: =AM351 -> 3862.1784 | AN352: =AM352-AP352 -> 3484.1716 | AO352: =(AN352/AL352)*12 -> 0.71433437 | AP352: =AL352*($AK$3/12) -> 378.00686 | AQ352: =(AP352/AL352)*12 -> 0.0775 | AR352: =AR351+AN352 -> 484054.08 | AS352: =AS351+AP352 -> 848397.48 | AT352: =AL352-AN352 -> 55045.923 | AU352: =AR352+AS352 -> 1332451.6 | AW352: =AW351+1 -> 345 | AY352: =BG351 -> 57224.073 | AZ352: =AZ351 -> 3769.4654 | BA352: =AZ352-BC352 -> 3411.815 | BB352: =(BA352/AY352)*12 -> 0.71546427 | BC352: =AY352*($AX$3/12) -> 357.65046 | BD352: =(BC352/AY352)*12 -> 0.075 | BE352: =BE351+BA352 -> 485287.74 | BF352: =BF351+BC352 -> 815177.83 | BG352: =AY352-BA352 -> 53812.258 | BH352: =BE352+BF352 -> 1300465.6 | BJ352: =BJ351+1 -> 345 | BL352: =BT351 -> 55926.496 | BM352: =BM351 -> 3677.6123 | BN352: =BM352-BP352 -> 3339.7231 | BO352: =(BN352/BL352)*12 -> 0.71659553 | BP352: =BL352*($BK$3/12) -> 337.88925 | BQ352: =(BP352/BL352)*12 -> 0.0725 | BR352: =BR351+BN352 -> 486513.23 | BS352: =BS351+BP352 -> 782263.03 | BT352: =BL352-BN352 -> 52586.773 | BU352: =BR352+BS352 -> 1268776.3 | BW352: =BW351+1 -> 345 | BY352: =CG351 -> 54637.819 | BZ352: =BZ351 -> 3586.6458 | CA352: =BZ352-CC352 -> 3267.9251 | CB352: =(CA352/BY352)*12 -> 0.71772816 | CC352: =BY352*($BX$3/12) -> 318.72061 | CD352: =(CC352/BY352)*12 -> 0.07 | CE352: =CE351+CA352 -> 487730.11 | CF352: =CF351+CC352 -> 749662.68 | CG352: =BY352-CA352 -> 51369.894 | CH352: =CE352+CF352 -> 1237392.8
J353: =J352+1 -> 346 | L353: =T352 -> 57536.107 | M353: =$L$8/((($N$4)-1)/($N$3*$N$4)) -> 4050.0783 | N353: =M353-P353 -> 3654.5175 | O353: =(N353/L353)*12 -> 0.76220329 | P353: =L353*($K$3/12) -> 395.56074 | Q353: =(P353/L353)*12 -> 0.0825 | R353: =R352+N353 -> 485218.41 | S353: =S352+P353 -> 916108.67 | T353: =L353-N353 -> 53881.59 | U353: =R353+S353 -> 1401327.1 | W353: =W352+1 -> 346 | Y353: =AG352 -> 56287.346 | Z353: =Z352 -> 3955.7248 | AA353: =Z353-AC353 -> 3580.4758 | AB353: =(AA353/Y353)*12 -> 0.76332806 | AC353: =Y353*($X$3/12) -> 375.24897 | AD353: =(AC353/Y353)*12 -> 0.08 | AE353: =AE352+AA353 -> 486393.13 | AF353: =AF352+AC353 -> 882287.66 | AG353: =Y353-AA353 -> 52706.87 | AH353: =AE353+AF353 -> 1368680.8 | AJ353: =AJ352+1 -> 346 | AL353: =AT352 -> 55045.923 | AM353: =AM352 -> 3862.1784 | AN353: =AM353-AP353 -> 3506.6735 | AO353: =(AN353/AL353)*12 -> 0.7644541 | AP353: =AL353*($AK$3/12) -> 355.50492 | AQ353: =(AP353/AL353)*12 -> 0.0775 | AR353: =AR352+AN353 -> 487560.75 | AS353: =AS352+AP353 -> 848752.98 | AT353: =AL353-AN353 -> 51539.25 | AU353: =AR353+AS353 -> 1336313.7 | AW353: =AW352+1 -> 346 | AY353: =BG352 -> 53812.258 | AZ353: =AZ352 -> 3769.4654 | BA353: =AZ353-BC353 -> 3433.1388 | BB353: =(BA353/AY353)*12 -> 0.76558143 | BC353: =AY353*($AX$3/12) -> 336.32661 | BD353: =(BC353/AY353)*12 -> 0.075 | BE353: =BE352+BA353 -> 488720.88 | BF353: =BF352+BC353 -> 815514.15 | BG353: =AY353-BA353 -> 50379.119 | BH353: =BE353+BF353 -> 1304235 | BJ353: =BJ352+1 -> 346 | BL353: =BT352 -> 52586.773 | BM353: =BM352 -> 3677.6123 | BN353: =BM353-BP353 -> 3359.9006 | BO353: =(BN353/BL353)*12 -> 0.76671004 | BP353: =BL353*($BK$3/12) -> 317.71175 | BQ353: =(BP353/BL353)*12 -> 0.0725 | BR353: =BR352+BN353 -> 489873.13 | BS353: =BS352+BP353 -> 782580.74 | BT353: =BL353-BN353 -> 49226.872 | BU353: =BR353+BS353 -> 1272453.9 | BW353: =BW352+1 -> 346 | BY353: =CG352 -> 51369.894 | BZ353: =BZ352 -> 3586.6458 | CA353: =BZ353-CC353 -> 3286.988 | CB353: =(CA353/BY353)*12 -> 0.76783994 | CC353: =BY353*($BX$3/12) -> 299.65772 | CD353: =(CC353/BY353)*12 -> 0.07 | CE353: =CE352+CA353 -> 491017.09 | CF353: =CF352+CC353 -> 749962.34 | CG353: =BY353-CA353 -> 48082.906 | CH353: =CE353+CF353 -> 1240979.4
J354: =J353+1 -> 347 | L354: =T353 -> 53881.59 | M354: =$L$8/((($N$4)-1)/($N$3*$N$4)) -> 4050.0783 | N354: =M354-P354 -> 3679.6423 | O354: =(N354/L354)*12 -> 0.81949527 | P354: =L354*($K$3/12) -> 370.43593 | Q354: =(P354/L354)*12 -> 0.0825 | R354: =R353+N354 -> 488898.05 | S354: =S353+P354 -> 916479.1 | T354: =L354-N354 -> 50201.947 | U354: =R354+S354 -> 1405377.2 | W354: =W353+1 -> 347 | Y354: =AG353 -> 52706.87 | Z354: =Z353 -> 3955.7248 | AA354: =Z354-AC354 -> 3604.3457 | AB354: =(AA354/Y354)*12 -> 0.8206169 | AC354: =Y354*($X$3/12) -> 351.37913 | AD354: =(AC354/Y354)*12 -> 0.08 | AE354: =AE353+AA354 -> 489997.48 | AF354: =AF353+AC354 -> 882639.04 | AG354: =Y354-AA354 -> 49102.524 | AH354: =AE354+AF354 -> 1372636.5 | AJ354: =AJ353+1 -> 347 | AL354: =AT353 -> 51539.25 | AM354: =AM353 -> 3862.1784 | AN354: =AM354-AP354 -> 3529.3208 | AO354: =(AN354/AL354)*12 -> 0.82173973 | AP354: =AL354*($AK$3/12) -> 332.85765 | AQ354: =(AP354/AL354)*12 -> 0.0775 | AR354: =AR353+AN354 -> 491090.07 | AS354: =AS353+AP354 -> 849085.84 | AT354: =AL354-AN354 -> 48009.929 | AU354: =AR354+AS354 -> 1340175.9 | AW354: =AW353+1 -> 347 | AY354: =BG353 -> 50379.119 | AZ354: =AZ353 -> 3769.4654 | BA354: =AZ354-BC354 -> 3454.5959 | BB354: =(BA354/AY354)*12 -> 0.82286375 | BC354: =AY354*($AX$3/12) -> 314.8695 | BD354: =(BC354/AY354)*12 -> 0.075 | BE354: =BE353+BA354 -> 492175.48 | BF354: =BF353+BC354 -> 815829.02 | BG354: =AY354-BA354 -> 46924.523 | BH354: =BE354+BF354 -> 1308004.5 | BJ354: =BJ353+1 -> 347 | BL354: =BT353 -> 49226.872 | BM354: =BM353 -> 3677.6123 | BN354: =BM354-BP354 -> 3380.2 | BO354: =(BN354/BL354)*12 -> 0.82398897 | BP354: =BL354*($BK$3/12) -> 297.41235 | BQ354: =(BP354/BL354)*12 -> 0.0725 | BR354: =BR353+BN354 -> 493253.33 | BS354: =BS353+BP354 -> 782878.15 | BT354: =BL354-BN354 -> 45846.672 | BU354: =BR354+BS354 -> 1276131.5 | BW354: =BW353+1 -> 347 | BY354: =CG353 -> 48082.906 | BZ354: =BZ353 -> 3586.6458 | CA354: =BZ354-CC354 -> 3306.1621 | CB354: =(CA354/BY354)*12 -> 0.82511539 | CC354: =BY354*($BX$3/12) -> 280.48362 | CD354: =(CC354/BY354)*12 -> 0.07 | CE354: =CE353+CA354 -> 494323.26 | CF354: =CF353+CC354 -> 750242.82 | CG354: =BY354-CA354 -> 44776.744 | CH354: =CE354+CF354 -> 1244566.1
... J367: =J366+1 -> 360 | L367: =T366 -> 4022.4241 | M367: =$L$8/((($N$4)-1)/($N$3*$N$4)) -> 4050.0783 | N367: =M367-P367 -> 4022.4241 | O367: =(N367/L367)*12 -> 12 | P367: =L367*($K$3/12) -> 27.654166 | Q367: =(P367/L367)*12 -> 0.0825 | R367: =R366+N367 -> 539100 | S367: =S366+P367 -> 918928.17 | T367: =L367-N367 -> -1.5070327e-08 | U367: =R367+S367 -> 1458028.2 | W367: =W366+1 -> 360 | Y367: =AG366 -> 3929.528 | Z367: =Z366 -> 3955.7248 | AA367: =Z367-AC367 -> 3929.528 | AB367: =(AA367/Y367)*12 -> 12 | AC367: =Y367*($X$3/12) -> 26.196853 | AD367: =(AC367/Y367)*12 -> 0.08 | AE367: =AE366+AA367 -> 539100 | AF367: =AF366+AC367 -> 884960.93 | AG367: =Y367-AA367 -> -8.877123e-09 | AH367: =AE367+AF367 -> 1424060.9 | AJ367: =AJ366+1 -> 360 | AL367: =AT366 -> 3837.3952 | AM367: =AM366 -> 3862.1784 | AN367: =AM367-AP367 -> 3837.3952 | AO367: =(AN367/AL367)*12 -> 12 | AP367: =AL367*($AK$3/12) -> 24.783178 | AQ367: =(AP367/AL367)*12 -> 0.0775 | AR367: =AR366+AN367 -> 539100 | AS367: =AS366+AP367 -> 851284.23 | AT367: =AL367-AN367 -> -1.0146778e-08 | AU367: =AR367+AS367 -> 1390384.2 | AW367: =AW366+1 -> 360 | AY367: =BG366 -> 3746.0526 | AZ367: =AZ366 -> 3769.4654 | BA367: =AZ367-BC367 -> 3746.0526 | BB367: =(BA367/AY367)*12 -> 12 | BC367: =AY367*($AX$3/12) -> 23.412829 | BD367: =(BC367/AY367)*12 -> 0.075 | BE367: =BE366+BA367 -> 539100 | BF367: =BF366+BC367 -> 817907.55 | BG367: =AY367-BA367 -> 1.2311375e-08 | BH367: =BE367+BF367 -> 1357007.5 | BJ367: =BJ366+1 -> 360 | BL367: =BT366 -> 3655.5269 | BM367: =BM366 -> 3677.6123 | BN367: =BM367-BP367 -> 3655.5269 | BO367: =(BN367/BL367)*12 -> 12 | BP367: =BL367*($BK$3/12) -> 22.085475 | BQ367: =(BP367/BL367)*12 -> 0.0725 | BR367: =BR366+BN367 -> 539100 | BS367: =BS366+BP367 -> 784840.44 | BT367: =BL367-BN367 -> 1.3387762e-09 | BU367: =BR367+BS367 -> 1323940.4 | BW367: =BW366+1 -> 360 | BY367: =CG366 -> 3565.845 | BZ367: =BZ366 -> 3586.6458 | CA367: =BZ367-CC367 -> 3565.845 | CB367: =(CA367/BY367)*12 -> 12 | CC367: =BY367*($BX$3/12) -> 20.800762 | CD367: =(CC367/BY367)*12 -> 0.07 | CE367: =CE366+CA367 -> 539100 | CF367: =CF366+CC367 -> 752092.47 | CG367: =BY367-CA367 -> 4.6352397e-09 | CH367: =CE367+CF367 -> 1291192.5

Sheet Amoritization Scenario 15% DP
J1: Interest | K1: ='Interest Rate Comparison'!B3 -> 0.0825 | N1: =K1/12 -> 0.006875 | O1: r | W1: Interest | X1: ='Interest Rate Comparison'!B4 -> 0.08 | AA1: =X1/12 -> 0.0066666667 | AB1: r | AJ1: Interest | AK1: ='Interest Rate Comparison'!B5 -> 0.0775 | AN1: =AK1/12 -> 0.0064583333 | AO1: r | AW1: Interest | AX1: ='Interest Rate Comparison'!B6 -> 0.075 | BA1: =AX1/12 -> 0.00625 | BB1: r | BJ1: Interest | BK1: ='Interest Rate Comparison'!B7 -> 0.0725 | BN1: =BK1/12 -> 0.0060416667 | BO1: r | BW1: Interest | BX1: ='Interest Rate Comparison'!B8 -> 0.07 | CA1: =BX1/12 -> 0.0058333333 | CB1: r
J2: Term | K2: =$L$2*12 -> 360 | L2: ='STR Calculator'!I9 -> 30 | M2: years | N2: =(1+N1)^K2 -> 11.781506 | O2: (1+r)^n | W2: Term | X2: =$L$2*12 -> 360 | Y2: 30 | Z2: years | AA2: =(1+AA1)^X2 -> 10.93573 | AB2: (1+r)^n | AJ2: Term | AK2: =$L$2*12 -> 360 | AL2: 30 | AM2: years | AN2: =(1+AN1)^AK2 -> 10.150514 | AO2: (1+r)^n | AW2: Term | AX2: =$L$2*12 -> 360 | AY2: 30 | AZ2: years | BA2: =(1+BA1)^AX2 -> 9.4215339 | BB2: (1+r)^n | BJ2: Term | BK2: =$L$2*12 -> 360 | BL2: 30 | BM2: years | BN2: =(1+BN1)^BK2 -> 8.744772 | BO2: (1+r)^n | BW2: Term | BX2: =$L$2*12 -> 360 | BY2: 30 | BZ2: years | CA2: =(1+CA1)^BX2 -> 8.1164975 | CB2: (1+r)^n
A3: Original Purchase Price | B3: ='STR Calculator'!B5 -> 599000 | C3: =B3/B1 -> #DIV/0! | D3: sqft | J3: Monthly Payment | W3: Monthly Payment | AJ3: Monthly Payment | AW3: Monthly Payment | BJ3: Monthly Payment | BW3: Monthly Payment
A4: Down Payment | B4: 0.15
A5: Current Loan Balance | B5: =B3-(B3*B4) -> 509150 | C5: as of 11/13/22 | J5: paymentNumber | K5: paymentDate | L5: startingBalance | M5: Monthly Payment | N5: principalPayment | O5: Principle Pay Down | P5: interestPayment | Q5: Interest Percent | R5: cumulativePrincipal | S5: cumulativeInterest | T5: endingBalance | U5: Total Paid End of Loan | W5: paymentNumber | X5: paymentDate | Y5: startingBalance | Z5: Monthly Payment | AA5: principalPayment | AB5: Principle Pay Down | AC5: interestPayment | AD5: Interest Percent | AE5: cumulativePrincipal | AF5: cumulativeInterest | AG5: endingBalance | AH5: Total Paid End of Loan | AJ5: paymentNumber | AK5: paymentDate | AL5: startingBalance | AM5: Monthly Payment | AN5: principalPayment | AO5: Principle Pay Down | AP5: interestPayment | AQ5: Interest Percent | AR5: cumulativePrincipal | AS5: cumulativeInterest | AT5: endingBalance | AU5: Total Paid End of Loan | AW5: paymentNumber | AX5: paymentDate | AY5: startingBalance | AZ5: Monthly Payment | BA5: principalPayment | BB5: Principle Pay Down | BC5: interestPayment | BD5: Interest Percent | BE5: cumulativePrincipal | BF5: cumulativeInterest | BG5: endingBalance | BH5: Total Paid End of Loan | BJ5: paymentNumber | BK5: paymentDate | BL5: startingBalance | BM5: Monthly Payment | BN5: principalPayment | BO5: Principle Pay Down | BP5: interestPayment | BQ5: Interest Percent | BR5: cumulativePrincipal | BS5: cumulativeInterest | BT5: endingBalance | BU5: Total Paid End of Loan | BW5: paymentNumber | BX5: paymentDate | BY5: startingBalance | BZ5: Monthly Payment | CA5: principalPayment | CB5: Principle Pay Down | CC5: interestPayment | CD5: Interest Percent | CE5: cumulativePrincipal | CF5: cumulativeInterest | CG5: endingBalance | CH5: Total Paid End of Loan
A6: Current Equity | B6: =B3-B5 -> 89850 | J6: 1 | K6: 44866 | L6: ='Amoritization Scenario 15% DP'!$B$5 -> 509150 | M6: =$L$6/((($N$2)-1)/($N$1*$N$2)) -> 3825.0739 | N6: =M6-P6 -> 324.66766 | O6: =(N6/L6)*12 -> 0.0076519925 | P6: =L6*($K$1/12) -> 3500.4062 | Q6: =(P6/L6)*12 -> 0.0825 | R6: =N6 -> 324.66766 | S6: =P6 -> 3500.4062 | T6: =L6-N6 -> 508825.33 | U6: =R6+S6 -> 3825.0739 | W6: 1 | X6: 44866 | Y6: ='Amoritization Scenario 15% DP'!$B$5 -> 509150 | Z6: =$Y$6/((($AA$2)-1)/($AA$1*$AA$2)) -> 3735.9623 | AA6: =Z6-AC6 -> 341.62899 | AB6: =(AA6/Y6)*12 -> 0.0080517489 | AC6: =Y6*($X$1/12) -> 3394.3333 | AD6: =(AC6/Y6)*12 -> 0.08 | AE6: =AA6 -> 341.62899 | AF6: =AC6 -> 3394.3333 | AG6: =Y6-AA6 -> 508808.37 | AH6: =AE6+AF6 -> 3735.9623 | AJ6: 1 | AK6: 44866 | AL6: ='Amoritization Scenario 15% DP'!$B$5 -> 509150 | AM6: =$AL$6/((($AN$2)-1)/($AN$1*$AN$2)) -> 3647.6129 | AN6: =AM6-AP6 -> 359.35253 | AO6: =(AN6/AL6)*12 -> 0.0084694695 | AP6: =AL6*($AK$1/12) -> 3288.2604 | AQ6: =(AP6/AL6)*12 -> 0.0775 | AR6: =AN6 -> 359.35253 | AS6: =AP6 -> 3288.2604 | AT6: =AL6-AN6 -> 508790.65 | AU6: =AR6+AS6 -> 3647.6129 | AW6: 1 | AX6: 44866 | AY6: ='Amoritization Scenario 15% DP'!$B$5 -> 509150 | AZ6: =$AY$6/((($BA$2)-1)/($BA$1*$BA$2)) -> 3560.0507 | BA6: =AZ6-BC6 -> 377.86317 | BB6: =(BA6/AY6)*12 -> 0.008905741 | BC6: =AY6*($AX$1/12) -> 3182.1875 | BD6: =(BC6/AY6)*12 -> 0.075 | BE6: =BA6 -> 377.86317 | BF6: =BC6 -> 3182.1875 | BG6: =AY6-BA6 -> 508772.14 | BH6: =BE6+BF6 -> 3560.0507 | BJ6: 1 | BK6: 44866 | BL6: ='Amoritization Scenario 15% DP'!$B$5 -> 509150 | BM6: =$BL$6/((($BN$2)-1)/($BN$1*$BN$2)) -> 3473.3005 | BN6: =BM6-BP6 -> 397.18595 | BO6: =(BN6/BL6)*12 -> 0.0093611536 | BP6: =BL6*($BK$1/12) -> 3076.1146 | BQ6: =(BP6/BL6)*12 -> 0.0725 | BR6: =BN6 -> 397.18595 | BS6: =BP6 -> 3076.1146 | BT6: =BL6-BN6 -> 508752.81 | BU6: =BR6+BS6 -> 3473.3005 | BW6: 1 | BX6: 44866 | BY6: ='Amoritization Scenario 15% DP'!$B$5 -> 509150 | BZ6: =$BY$6/((($CA$2)-1)/($CA$1*$CA$2)) -> 3387.3877 | CA6: =BZ6-CC6 -> 417.34599 | CB6: =(CA6/BY6)*12 -> 0.0098362994 | CC6: =BY6*($BX$1/12) -> 2970.0417 | CD6: =(CC6/BY6)*12 -> 0.07 | CE6: =CA6 -> 417.34599 | CF6: =CC6 -> 2970.0417 | CG6: =BY6-CA6 -> 508732.65 | CH6: =CE6+CF6 -> 3387.3877
J7: 2 | K7: 44896 | L7: =T6 -> 508825.33 | M7: =$L$6/((($N$2)-1)/($N$1*$N$2)) -> 3825.0739 | N7: =M7-P7 -> 326.89975 | O7: =(N7/L7)*12 -> 0.007709516 | P7: =L7*($K$1/12) -> 3498.1742 | Q7: =(P7/L7)*12 -> 0.0825 | R7: =R6+N7 -> 651.56742 | S7: =S6+P7 -> 6998.5804 | T7: =L7-N7 -> 508498.43 | U7: =R7+S7 -> 7650.1478 | W7: 2 | X7: 44896 | Y7: =AG6 -> 508808.37 | Z7: =Z6 -> 3735.9623 | AA7: =Z7-AC7 -> 343.90652 | AB7: =(AA7/Y7)*12 -> 0.0081108694 | AC7: =Y7*($X$1/12) -> 3392.0558 | AD7: =(AC7/Y7)*12 -> 0.08 | AE7: =AE6+AA7 -> 685.53552 | AF7: =AF6+AC7 -> 6786.3891 | AG7: =Y7-AA7 -> 508464.46 | AH7: =AE7+AF7 -> 7471.9247 | AJ7: 2 | AK7: 44896 | AL7: =AT6 -> 508790.65 | AM7: =AM6 -> 3647.6129 | AN7: =AM7-AP7 -> 361.67335 | AO7: =(AN7/AL7)*12 -> 0.0085301886 | AP7: =AL7*($AK$1/12) -> 3285.9396 | AQ7: =(AP7/AL7)*12 -> 0.0775 | AR7: =AR6+AN7 -> 721.02588 | AS7: =AS6+AP7 -> 6574.2 | AT7: =AL7-AN7 -> 508428.97 | AU7: =AR7+AS7 -> 7295.2259 | AW7: 2 | AX7: 44896 | AY7: =BG6 -> 508772.14 | AZ7: =AZ6 -> 3560.0507 | BA7: =AZ7-BC7 -> 380.22482 | BB7: =(BA7/AY7)*12 -> 0.0089680575 | BC7: =AY7*($AX$1/12) -> 3179.8259 | BD7: =(BC7/AY7)*12 -> 0.075 | BE7: =BE6+BA7 -> 758.08799 | BF7: =BF6+BC7 -> 6362.0134 | BG7: =AY7-BA7 -> 508391.91 | BH7: =BE7+BF7 -> 7120.1013 | BJ7: 2 | BK7: 44896 | BL7: =BT6 -> 508752.81 | BM7: =BM6 -> 3473.3005 | BN7: =BM7-BP7 -> 399.58561 | BO7: =(BN7/BL7)*12 -> 0.009425063 | BP7: =BL7*($BK$1/12) -> 3073.7149 | BQ7: =(BP7/BL7)*12 -> 0.0725 | BR7: =BR6+BN7 -> 796.77156 | BS7: =BS6+BP7 -> 6149.8295 | BT7: =BL7-BN7 -> 508353.23 | BU7: =BR7+BS7 -> 6946.6011 | BW7: 2 | BX7: 44896 | BY7: =CG6 -> 508732.65 | BZ7: =BZ6 -> 3387.3877 | CA7: =BZ7-CC7 -> 419.78051 | CB7: =(CA7/BY7)*12 -> 0.0099017943 | CC7: =BY7*($BX$1/12) -> 2967.6071 | CD7: =(CC7/BY7)*12 -> 0.07 | CE7: =CE6+CA7 -> 837.12649 | CF7: =CF6+CC7 -> 5937.6488 | CG7: =BY7-CA7 -> 508312.87 | CH7: =CE7+CF7 -> 6774.7753
A8: Year | B8: ="Cum Interest @ "&K1&"%" -> Cum Interest @ 0.0825% | C8: ="Cum Interest @ "&X1&"%" -> Cum Interest @ 0.08% | D8: ="Cum Interest @ "&AK1&"%" -> Cum Interest @ 0.0775% | E8: ="Cum Interest @ "&AX1&"%" -> Cum Interest @ 0.075% | F8: ="Cum Interest @ "&BK1&"%" -> Cum Interest @ 0.0725% | G8: ="Cum Interest @ "&BX1&"%" -> Cum Interest @ 0.07% | J8: 3 | K8: 44927 | L8: =T7 -> 508498.43 | M8: =$L$6/((($N$2)-1)/($N$1*$N$2)) -> 3825.0739 | N8: =M8-P8 -> 329.14719 | O8: =(N8/L8)*12 -> 0.0077675093 | P8: =L8*($K$1/12) -> 3495.9267 | Q8: =(P8/L8)*12 -> 0.0825 | R8: =R7+N8 -> 980.71461 | S8: =S7+P8 -> 10494.507 | T8: =L8-N8 -> 508169.29 | U8: =R8+S8 -> 11475.222 | W8: 3 | X8: 44927 | Y8: =AG7 -> 508464.46 | Z8: =Z7 -> 3735.9623 | AA8: =Z8-AC8 -> 346.19923 | AB8: =(AA8/Y8)*12 -> 0.0081704643 | AC8: =Y8*($X$1/12) -> 3389.7631 | AD8: =(AC8/Y8)*12 -> 0.08 | AE8: =AE7+AA8 -> 1031.7347 | AF8: =AF7+AC8 -> 10176.152 | AG8: =Y8-AA8 -> 508118.27 | AH8: =AE8+AF8 -> 11207.887 | AJ8: 3 | AK8: 44927 | AL8: =AT7 -> 508428.97 | AM8: =AM7 -> 3647.6129 | AN8: =AM8-AP8 -> 364.00916 | AO8: =(AN8/AL8)*12 -> 0.0085913866 | AP8: =AL8*($AK$1/12) -> 3283.6038 | AQ8: =(AP8/AL8)*12 -> 0.0775 | AR8: =AR7+AN8 -> 1085.035 | AS8: =AS7+AP8 -> 9857.8038 | AT8: =AL8-AN8 -> 508064.96 | AU8: =AR8+AS8 -> 10942.839 | AW8: 3 | AX8: 44927 | AY8: =BG7 -> 508391.91 | AZ8: =AZ7 -> 3560.0507 | BA8: =AZ8-BC8 -> 382.60122 | BB8: =(BA8/AY8)*12 -> 0.009030857 | BC8: =AY8*($AX$1/12) -> 3177.4495 | BD8: =(BC8/AY8)*12 -> 0.075 | BE8: =BE7+BA8 -> 1140.6892 | BF8: =BF7+BC8 -> 9539.4628 | BG8: =AY8-BA8 -> 508009.31 | BH8: =BE8+BF8 -> 10680.152 | BJ8: 3 | BK8: 44927 | BL8: =BT7 -> 508353.23 | BM8: =BM7 -> 3473.3005 | BN8: =BM8-BP8 -> 401.99977 | BO8: =(BN8/BL8)*12 -> 0.0094894594 | BP8: =BL8*($BK$1/12) -> 3071.3008 | BQ8: =(BP8/BL8)*12 -> 0.0725 | BR8: =BR7+BN8 -> 1198.7713 | BS8: =BS7+BP8 -> 9221.1303 | BT8: =BL8-BN8 -> 507951.23 | BU8: =BR8+BS8 -> 10419.902 | BW8: 3 | BX8: 44927 | BY8: =CG7 -> 508312.87 | BZ8: =BZ7 -> 3387.3877 | CA8: =BZ8-CC8 -> 422.22923 | CB8: =(CA8/BY8)*12 -> 0.0099677796 | CC8: =BY8*($BX$1/12) -> 2965.1584 | CD8: =(CC8/BY8)*12 -> 0.07 | CE8: =CE7+CA8 -> 1259.3557 | CF8: =CF7+CC8 -> 8902.8072 | CG8: =BY8-CA8 -> 507890.64 | CH8: =CE8+CF8 -> 10162.163
A9: 1 | B9: =VLOOKUP($A$9*12,$J$5:$U$365,10) -> 41854.128 | C9: =VLOOKUP(A9*12,$W$5:$AH$365,10) -> 40578.292 | D9: =VLOOKUP(A9*12,$AJ$5:$AU$365,10) -> 39302.605 | E9: =VLOOKUP(A9*12,$AW$5:$BH$365,10) -> 38027.088 | F9: =VLOOKUP(A9*12,$BJ$5:$BU$365,10) -> 36751.764 | G9: =VLOOKUP(A9*12,$BW$5:$CH$365,10) -> 35476.656 | J9: 4 | K9: 44958 | L9: =T8 -> 508169.29 | M9: =$L$6/((($N$2)-1)/($N$1*$N$2)) -> 3825.0739 | N9: =M9-P9 -> 331.41008 | O9: =(N9/L9)*12 -> 0.0078259766 | P9: =L9*($K$1/12) -> 3493.6638 | Q9: =(P9/L9)*12 -> 0.0825 | R9: =R8+N9 -> 1312.1247 | S9: =S8+P9 -> 13988.171 | T9: =L9-N9 -> 507837.88 | U9: =R9+S9 -> 15300.296 | W9: 4 | X9: 44958 | Y9: =AG8 -> 508118.27 | Z9: =Z8 -> 3735.9623 | AA9: =Z9-AC9 -> 348.50723 | AB9: =(AA9/Y9)*12 -> 0.008230538 | AC9: =Y9*($X$1/12) -> 3387.4551 | AD9: =(AC9/Y9)*12 -> 0.08 | AE9: =AE8+AA9 -> 1380.242 | AF9: =AF8+AC9 -> 13563.607 | AG9: =Y9-AA9 -> 507769.76 | AH9: =AE9+AF9 -> 14943.849 | AJ9: 4 | AK9: 44958 | AL9: =AT8 -> 508064.96 | AM9: =AM8 -> 3647.6129 | AN9: =AM9-AP9 -> 366.36005 | AO9: =(AN9/AL9)*12 -> 0.0086530678 | AP9: =AL9*($AK$1/12) -> 3281.2529 | AQ9: =(AP9/AL9)*12 -> 0.0775 | AR9: =AR8+AN9 -> 1451.3951 | AS9: =AS8+AP9 -> 13139.057 | AT9: =AL9-AN9 -> 507698.6 | AU9: =AR9+AS9 -> 14590.452 | AW9: 4 | AX9: 44958 | AY9: =BG8 -> 508009.31 | AZ9: =AZ8 -> 3560.0507 | BA9: =AZ9-BC9 -> 384.99248 | BB9: =(BA9/AY9)*12 -> 0.0090941438 | BC9: =AY9*($AX$1/12) -> 3175.0582 | BD9: =(BC9/AY9)*12 -> 0.075 | BE9: =BE8+BA9 -> 1525.6817 | BF9: =BF8+BC9 -> 12714.521 | BG9: =AY9-BA9 -> 507624.32 | BH9: =BE9+BF9 -> 14240.203 | BJ9: 4 | BK9: 44958 | BL9: =BT8 -> 507951.23 | BM9: =BM8 -> 3473.3005 | BN9: =BM9-BP9 -> 404.42852 | BO9: =(BN9/BL9)*12 -> 0.009554347 | BP9: =BL9*($BK$1/12) -> 3068.872 | BQ9: =(BP9/BL9)*12 -> 0.0725 | BR9: =BR8+BN9 -> 1603.1999 | BS9: =BS8+BP9 -> 12290.002 | BT9: =BL9-BN9 -> 507546.8 | BU9: =BR9+BS9 -> 13893.202 | BW9: 4 | BX9: 44958 | BY9: =CG8 -> 507890.64 | BZ9: =BZ8 -> 3387.3877 | CA9: =BZ9-CC9 -> 424.69223 | CB9: =(CA9/BY9)*12 -> 0.01003426 | CC9: =BY9*($BX$1/12) -> 2962.6954 | CD9: =(CC9/BY9)*12 -> 0.07 | CE9: =CE8+CA9 -> 1684.0479 | CF9: =CF8+CC9 -> 11865.503 | CG9: =BY9-CA9 -> 507465.95 | CH9: =CE9+CF9 -> 13549.551
A10: =A9+1 -> 2 | B10: =VLOOKUP(A10*12,$J$5:$U$365,10) -> 83361.481 | C10: =VLOOKUP(A10*12,$W$5:$AH$365,10) -> 80803.566 | D10: =VLOOKUP(A10*12,$AJ$5:$AU$365,10) -> 78246.311 | E10: =VLOOKUP(A10*12,$AW$5:$BH$365,10) -> 75689.806 | F10: =VLOOKUP(A10*12,$BJ$5:$BU$365,10) -> 73134.145 | G10: =VLOOKUP(A10*12,$BW$5:$CH$365,10) -> 70579.428 | J10: 5 | K10: 44986 | L10: =T9 -> 507837.88 | M10: =$L$6/((($N$2)-1)/($N$1*$N$2)) -> 3825.0739 | N10: =M10-P10 -> 333.68852 | O10: =(N10/L10)*12 -> 0.0078849224 | P10: =L10*($K$1/12) -> 3491.3854 | Q10: =(P10/L10)*12 -> 0.0825 | R10: =R9+N10 -> 1645.8132 | S10: =S9+P10 -> 17479.556 | T10: =L10-N10 -> 507504.19 | U10: =R10+S10 -> 19125.37 | W10: 5 | X10: 44986 | Y10: =AG9 -> 507769.76 | Z10: =Z9 -> 3735.9623 | AA10: =Z10-AC10 -> 350.83061 | AB10: =(AA10/Y10)*12 -> 0.008291095 | AC10: =Y10*($X$1/12) -> 3385.1317 | AD10: =(AC10/Y10)*12 -> 0.08 | AE10: =AE9+AA10 -> 1731.0726 | AF10: =AF9+AC10 -> 16948.739 | AG10: =Y10-AA10 -> 507418.93 | AH10: =AE10+AF10 -> 18679.812 | AJ10: 5 | AK10: 44986 | AL10: =AT9 -> 507698.6 | AM10: =AM9 -> 3647.6129 | AN10: =AM10-AP10 -> 368.72612 | AO10: =(AN10/AL10)*12 -> 0.0087152367 | AP10: =AL10*($AK$1/12) -> 3278.8868 | AQ10: =(AP10/AL10)*12 -> 0.0775 | AR10: =AR9+AN10 -> 1820.1212 | AS10: =AS9+AP10 -> 16417.944 | AT10: =AL10-AN10 -> 507329.88 | AU10: =AR10+AS10 -> 18238.065 | AW10: 5 | AX10: 44986 | AY10: =BG9 -> 507624.32 | AZ10: =AZ9 -> 3560.0507 | BA10: =AZ10-BC10 -> 387.39868 | BB10: =(BA10/AY10)*12 -> 0.0091579225 | BC10: =AY10*($AX$1/12) -> 3172.652 | BD10: =(BC10/AY10)*12 -> 0.075 | BE10: =BE9+BA10 -> 1913.0804 | BF10: =BF9+BC10 -> 15887.173 | BG10: =AY10-BA10 -> 507236.92 | BH10: =BE10+BF10 -> 17800.253 | BJ10: 5 | BK10: 44986 | BL10: =BT9 -> 507546.8 | BM10: =BM9 -> 3473.3005 | BN10: =BM10-BP10 -> 406.87195 | BO10: =(BN10/BL10)*12 -> 0.0096197303 | BP10: =BL10*($BK$1/12) -> 3066.4286 | BQ10: =(BP10/BL10)*12 -> 0.0725 | BR10: =BR9+BN10 -> 2010.0718 | BS10: =BS9+BP10 -> 15356.431 | BT10: =BL10-BN10 -> 507139.93 | BU10: =BR10+BS10 -> 17366.503 | BW10: 5 | BX10: 44986 | BY10: =CG9 -> 507465.95 | BZ10: =BZ9 -> 3387.3877 | CA10: =BZ10-CC10 -> 427.1696 | CB10: =(CA10/BY10)*12 -> 0.01010124 | CC10: =BY10*($BX$1/12) -> 2960.2181 | CD10: =(CC10/BY10)*12 -> 0.07 | CE10: =CE9+CA10 -> 2111.2175 | CF10: =CF9+CC10 -> 14825.721 | CG10: =BY10-CA10 -> 507038.78 | CH10: =CE10+CF10 -> 16936.938
A11: =A10+1 -> 3 | B11: =VLOOKUP(A11*12,$J$5:$U$365,10) -> 124492.34 | C11: =VLOOKUP(A11*12,$W$5:$AH$365,10) -> 120646.52 | D11: =VLOOKUP(A11*12,$AJ$5:$AU$365,10) -> 116802.29 | E11: =VLOOKUP(A11*12,$AW$5:$BH$365,10) -> 112959.87 | F11: =VLOOKUP(A11*12,$BJ$5:$BU$365,10) -> 109119.45 | G11: =VLOOKUP(A11*12,$BW$5:$CH$365,10) -> 105281.29 | J11: 6 | K11: 45017 | L11: =T10 -> 507504.19 | M11: =$L$6/((($N$2)-1)/($N$1*$N$2)) -> 3825.0739 | N11: =M11-P11 -> 335.98263 | O11: =(N11/L11)*12 -> 0.0079443513 | P11: =L11*($K$1/12) -> 3489.0913 | Q11: =(P11/L11)*12 -> 0.0825 | R11: =R10+N11 -> 1981.7958 | S11: =S10+P11 -> 20968.648 | T11: =L11-N11 -> 507168.2 | U11: =R11+S11 -> 22950.443 | W11: 6 | X11: 45017 | Y11: =AG10 -> 507418.93 | Z11: =Z10 -> 3735.9623 | AA11: =Z11-AC11 -> 353.16948 | AB11: =(AA11/Y11)*12 -> 0.0083521396 | AC11: =Y11*($X$1/12) -> 3382.7928 | AD11: =(AC11/Y11)*12 -> 0.08 | AE11: =AE10+AA11 -> 2084.2421 | AF11: =AF10+AC11 -> 20331.532 | AG11: =Y11-AA11 -> 507065.76 | AH11: =AE11+AF11 -> 22415.774 | AJ11: 6 | AK11: 45017 | AL11: =AT10 -> 507329.88 | AM11: =AM10 -> 3647.6129 | AN11: =AM11-AP11 -> 371.10748 | AO11: =(AN11/AL11)*12 -> 0.0087778977 | AP11: =AL11*($AK$1/12) -> 3276.5055 | AQ11: =(AP11/AL11)*12 -> 0.0775 | AR11: =AR10+AN11 -> 2191.2287 | AS11: =AS10+AP11 -> 19694.449 | AT11: =AL11-AN11 -> 506958.77 | AU11: =AR11+AS11 -> 21885.678 | AW11: 6 | AX11: 45017 | AY11: =BG10 -> 507236.92 | AZ11: =AZ10 -> 3560.0507 | BA11: =AZ11-BC11 -> 389.81992 | BB11: =(BA11/AY11)*12 -> 0.0092221975 | BC11: =AY11*($AX$1/12) -> 3170.2307 | BD11: =(BC11/AY11)*12 -> 0.075 | BE11: =BE10+BA11 -> 2302.9003 | BF11: =BF10+BC11 -> 19057.404 | BG11: =AY11-BA11 -> 506847.1 | BH11: =BE11+BF11 -> 21360.304 | BJ11: 6 | BK11: 45017 | BL11: =BT10 -> 507139.93 | BM11: =BM10 -> 3473.3005 | BN11: =BM11-BP11 -> 409.33013 | BO11: =(BN11/BL11)*12 -> 0.009685614 | BP11: =BL11*($BK$1/12) -> 3063.9704 | BQ11: =(BP11/BL11)*12 -> 0.0725 | BR11: =BR10+BN11 -> 2419.4019 | BS11: =BS10+BP11 -> 18420.401 | BT11: =BL11-BN11 -> 506730.6 | BU11: =BR11+BS11 -> 20839.803 | BW11: 6 | BX11: 45017 | BY11: =CG10 -> 507038.78 | BZ11: =BZ10 -> 3387.3877 | CA11: =BZ11-CC11 -> 429.66142 | CB11: =(CA11/BY11)*12 -> 0.010168723 | CC11: =BY11*($BX$1/12) -> 2957.7262 | CD11: =(CC11/BY11)*12 -> 0.07 | CE11: =CE10+CA11 -> 2540.879 | CF11: =CF10+CC11 -> 17783.447 | CG11: =BY11-CA11 -> 506609.12 | CH11: =CE11+CF11 -> 20324.326
A12: =A11+1 -> 4 | B12: =VLOOKUP(A12*12,$J$5:$U$365,10) -> 165214.45 | C12: =VLOOKUP(A12*12,$W$5:$AH$365,10) -> 160075.43 | D12: =VLOOKUP(A12*12,$AJ$5:$AU$365,10) -> 154939.42 | E12: =VLOOKUP(A12*12,$AW$5:$BH$365,10) -> 149806.79 | F12: =VLOOKUP(A12*12,$BJ$5:$BU$365,10) -> 144677.93 | G12: =VLOOKUP(A12*12,$BW$5:$CH$365,10) -> 139553.25 | J12: 7 | K12: 45047 | L12: =T11 -> 507168.2 | M12: =$L$6/((($N$2)-1)/($N$1*$N$2)) -> 3825.0739 | N12: =M12-P12 -> 338.29251 | O12: =(N12/L12)*12 -> 0.0080042678 | P12: =L12*($K$1/12) -> 3486.7814 | Q12: =(P12/L12)*12 -> 0.0825 | R12: =R11+N12 -> 2320.0884 | S12: =S11+P12 -> 24455.429 | T12: =L12-N12 -> 506829.91 | U12: =R12+S12 -> 26775.517 | W12: 7 | X12: 45047 | Y12: =AG11 -> 507065.76 | Z12: =Z11 -> 3735.9623 | AA12: =Z12-AC12 -> 355.52394 | AB12: =(AA12/Y12)*12 -> 0.0084136766 | AC12: =Y12*($X$1/12) -> 3380.4384 | AD12: =(AC12/Y12)*12 -> 0.08 | AE12: =AE11+AA12 -> 2439.766 | AF12: =AF11+AC12 -> 23711.97 | AG12: =Y12-AA12 -> 506710.23 | AH12: =AE12+AF12 -> 26151.736 | AJ12: 7 | AK12: 45047 | AL12: =AT11 -> 506958.77 | AM12: =AM11 -> 3647.6129 | AN12: =AM12-AP12 -> 373.50422 | AO12: =(AN12/AL12)*12 -> 0.0088410554 | AP12: =AL12*($AK$1/12) -> 3274.1087 | AQ12: =(AP12/AL12)*12 -> 0.0775 | AR12: =AR11+AN12 -> 2564.7329 | AS12: =AS11+AP12 -> 22968.558 | AT12: =AL12-AN12 -> 506585.27 | AU12: =AR12+AS12 -> 25533.291 | AW12: 7 | AX12: 45047 | AY12: =BG11 -> 506847.1 | AZ12: =AZ11 -> 3560.0507 | BA12: =AZ12-BC12 -> 392.2563 | BB12: =(BA12/AY12)*12 -> 0.0092869735 | BC12: =AY12*($AX$1/12) -> 3167.7944 | BD12: =(BC12/AY12)*12 -> 0.075 | BE12: =BE11+BA12 -> 2695.1566 | BF12: =BF11+BC12 -> 22225.198 | BG12: =AY12-BA12 -> 506454.84 | BH12: =BE12+BF12 -> 24920.355 | BJ12: 7 | BK12: 45047 | BL12: =BT11 -> 506730.6 | BM12: =BM11 -> 3473.3005 | BN12: =BM12-BP12 -> 411.80317 | BO12: =(BN12/BL12)*12 -> 0.0097520024 | BP12: =BL12*($BK$1/12) -> 3061.4974 | BQ12: =(BP12/BL12)*12 -> 0.0725 | BR12: =BR11+BN12 -> 2831.2051 | BS12: =BS11+BP12 -> 21481.899 | BT12: =BL12-BN12 -> 506318.79 | BU12: =BR12+BS12 -> 24313.104 | BW12: 7 | BX12: 45047 | BY12: =CG11 -> 506609.12 | BZ12: =BZ11 -> 3387.3877 | CA12: =BZ12-CC12 -> 432.16778 | CB12: =(CA12/BY12)*12 -> 0.010236715 | CC12: =BY12*($BX$1/12) -> 2955.2199 | CD12: =(CC12/BY12)*12 -> 0.07 | CE12: =CE11+CA12 -> 2973.0468 | CF12: =CF11+CC12 -> 20738.667 | CG12: =BY12-CA12 -> 506176.95 | CH12: =CE12+CF12 -> 23711.714
A13: =A12+1 -> 5 | B13: =VLOOKUP(A13*12,$J$5:$U$365,10) -> 205492.78 | C13: =VLOOKUP(A13*12,$W$5:$AH$365,10) -> 199055.92 | D13: =VLOOKUP(A13*12,$AJ$5:$AU$365,10) -> 192624.03 | E13: =VLOOKUP(A13*12,$AW$5:$BH$365,10) -> 186197.72 | F13: =VLOOKUP(A13*12,$BJ$5:$BU$365,10) -> 179777.58 | G13: =VLOOKUP(A13*12,$BW$5:$CH$365,10) -> 173364.25 | J13: 8 | K13: 45078 | L13: =T12 -> 506829.91 | M13: =$L$6/((($N$2)-1)/($N$1*$N$2)) -> 3825.0739 | N13: =M13-P13 -> 340.61827 | O13: =(N13/L13)*12 -> 0.0080646765 | P13: =L13*($K$1/12) -> 3484.4556 | Q13: =(P13/L13)*12 -> 0.0825 | R13: =R12+N13 -> 2660.7066 | S13: =S12+P13 -> 27939.885 | T13: =L13-N13 -> 506489.29 | U13: =R13+S13 -> 30600.591 | W13: 8 | X13: 45078 | Y13: =AG12 -> 506710.23 | Z13: =Z12 -> 3735.9623 | AA13: =Z13-AC13 -> 357.8941 | AB13: =(AA13/Y13)*12 -> 0.0084757104 | AC13: =Y13*($X$1/12) -> 3378.0682 | AD13: =(AC13/Y13)*12 -> 0.08 | AE13: =AE12+AA13 -> 2797.6601 | AF13: =AF12+AC13 -> 27090.039 | AG13: =Y13-AA13 -> 506352.34 | AH13: =AE13+AF13 -> 29887.699 | AJ13: 8 | AK13: 45078 | AL13: =AT12 -> 506585.27 | AM13: =AM12 -> 3647.6129 | AN13: =AM13-AP13 -> 375.91643 | AO13: =(AN13/AL13)*12 -> 0.0089047145 | AP13: =AL13*($AK$1/12) -> 3271.6965 | AQ13: =(AP13/AL13)*12 -> 0.0775 | AR13: =AR12+AN13 -> 2940.6493 | AS13: =AS12+AP13 -> 26240.254 | AT13: =AL13-AN13 -> 506209.35 | AU13: =AR13+AS13 -> 29180.904 | AW13: 8 | AX13: 45078 | AY13: =BG12 -> 506454.84 | AZ13: =AZ12 -> 3560.0507 | BA13: =AZ13-BC13 -> 394.7079 | BB13: =(BA13/AY13)*12 -> 0.0093522549 | BC13: =AY13*($AX$1/12) -> 3165.3428 | BD13: =(BC13/AY13)*12 -> 0.075 | BE13: =BE12+BA13 -> 3089.8645 | BF13: =BF12+BC13 -> 25390.541 | BG13: =AY13-BA13 -> 506060.14 | BH13: =BE13+BF13 -> 28480.405 | BJ13: 8 | BK13: 45078 | BL13: =BT12 -> 506318.79 | BM13: =BM12 -> 3473.3005 | BN13: =BM13-BP13 -> 414.29114 | BO13: =(BN13/BL13)*12 -> 0.0098189002 | BP13: =BL13*($BK$1/12) -> 3059.0094 | BQ13: =(BP13/BL13)*12 -> 0.0725 | BR13: =BR12+BN13 -> 3245.4962 | BS13: =BS12+BP13 -> 24540.908 | BT13: =BL13-BN13 -> 505904.5 | BU13: =BR13+BS13 -> 27786.404 | BW13: 8 | BX13: 45078 | BY13: =CG12 -> 506176.95 | BZ13: =BZ12 -> 3387.3877 | CA13: =BZ13-CC13 -> 434.68876 | CB13: =(CA13/BY13)*12 -> 0.010305221 | CC13: =BY13*($BX$1/12) -> 2952.6989 | CD13: =(CC13/BY13)*12 -> 0.07 | CE13: =CE12+CA13 -> 3407.7355 | CF13: =CF12+CC13 -> 23691.366 | CG13: =BY13-CA13 -> 505742.26 | CH13: =CE13+CF13 -> 27099.101
A14: =A13+1 -> 6 | B14: =VLOOKUP(A14*12,$J$5:$U$365,10) -> 245289.3 | C14: =VLOOKUP(A14*12,$W$5:$AH$365,10) -> 237550.77 | D14: =VLOOKUP(A14*12,$AJ$5:$AU$365,10) -> 229819.81 | E14: =VLOOKUP(A14*12,$AW$5:$BH$365,10) -> 222097.26 | F14: =VLOOKUP(A14*12,$BJ$5:$BU$365,10) -> 214384 | G14: =VLOOKUP(A14*12,$BW$5:$CH$365,10) -> 206680.95 | J14: 9 | K14: 45108 | L14: =T13 -> 506489.29 | M14: =$L$6/((($N$2)-1)/($N$1*$N$2)) -> 3825.0739 | N14: =M14-P14 -> 342.96002 | O14: =(N14/L14)*12 -> 0.008125582 | P14: =L14*($K$1/12) -> 3482.1139 | Q14: =(P14/L14)*12 -> 0.0825 | R14: =R13+N14 -> 3003.6666 | S14: =S13+P14 -> 31421.999 | T14: =L14-N14 -> 506146.33 | U14: =R14+S14 -> 34425.665 | W14: 9 | X14: 45108 | Y14: =AG13 -> 506352.34 | Z14: =Z13 -> 3735.9623 | AA14: =Z14-AC14 -> 360.28006 | AB14: =(AA14/Y14)*12 -> 0.0085382458 | AC14: =Y14*($X$1/12) -> 3375.6823 | AD14: =(AC14/Y14)*12 -> 0.08 | AE14: =AE13+AA14 -> 3157.9402 | AF14: =AF13+AC14 -> 30465.721 | AG14: =Y14-AA14 -> 505992.06 | AH14: =AE14+AF14 -> 33623.661 | AJ14: 9 | AK14: 45108 | AL14: =AT13 -> 506209.35 | AM14: =AM13 -> 3647.6129 | AN14: =AM14-AP14 -> 378.34423 | AO14: =(AN14/AL14)*12 -> 0.0089688796 | AP14: =AL14*($AK$1/12) -> 3269.2687 | AQ14: =(AP14/AL14)*12 -> 0.0775 | AR14: =AR13+AN14 -> 3318.9936 | AS14: =AS13+AP14 -> 29509.523 | AT14: =AL14-AN14 -> 505831.01 | AU14: =AR14+AS14 -> 32828.517 | AW14: 9 | AX14: 45108 | AY14: =BG13 -> 506060.14 | AZ14: =AZ13 -> 3560.0507 | BA14: =AZ14-BC14 -> 397.17482 | BB14: =(BA14/AY14)*12 -> 0.0094180465 | BC14: =AY14*($AX$1/12) -> 3162.8758 | BD14: =(BC14/AY14)*12 -> 0.075 | BE14: =BE13+BA14 -> 3487.0393 | BF14: =BF13+BC14 -> 28553.417 | BG14: =AY14-BA14 -> 505662.96 | BH14: =BE14+BF14 -> 32040.456 | BJ14: 9 | BK14: 45108 | BL14: =BT13 -> 505904.5 | BM14: =BM13 -> 3473.3005 | BN14: =BM14-BP14 -> 416.79415 | BO14: =(BN14/BL14)*12 -> 0.0098863121 | BP14: =BL14*($BK$1/12) -> 3056.5064 | BQ14: =(BP14/BL14)*12 -> 0.0725 | BR14: =BR13+BN14 -> 3662.2904 | BS14: =BS13+BP14 -> 27597.414 | BT14: =BL14-BN14 -> 505487.71 | BU14: =BR14+BS14 -> 31259.705 | BW14: 9 | BX14: 45108 | BY14: =CG13 -> 505742.26 | BZ14: =BZ13 -> 3387.3877 | CA14: =BZ14-CC14 -> 437.22444 | CB14: =(CA14/BY14)*12 -> 0.010374243 | CC14: =BY14*($BX$1/12) -> 2950.1632 | CD14: =(CC14/BY14)*12 -> 0.07 | CE14: =CE13+CA14 -> 3844.96 | CF14: =CF13+CC14 -> 26641.529 | CG14: =BY14-CA14 -> 505305.04 | CH14: =CE14+CF14 -> 30486.489
A15: =A14+1 -> 7 | B15: =VLOOKUP(A15*12,$J$5:$U$365,10) -> 284562.72 | C15: =VLOOKUP(A15*12,$W$5:$AH$365,10) -> 275519.68 | D15: =VLOOKUP(A15*12,$AJ$5:$AU$365,10) -> 266487.48 | E15: =VLOOKUP(A15*12,$AW$5:$BH$365,10) -> 257467.26 | F15: =VLOOKUP(A15*12,$BJ$5:$BU$365,10) -> 248460.23 | G15: =VLOOKUP(A15*12,$BW$5:$CH$365,10) -> 239467.62 | J15: 10 | K15: 45139 | L15: =T14 -> 506146.33 | M15: =$L$6/((($N$2)-1)/($N$1*$N$2)) -> 3825.0739 | N15: =M15-P15 -> 345.31787 | O15: =(N15/L15)*12 -> 0.008186989 | P15: =L15*($K$1/12) -> 3479.756 | Q15: =(P15/L15)*12 -> 0.0825 | R15: =R14+N15 -> 3348.9845 | S15: =S14+P15 -> 34901.755 | T15: =L15-N15 -> 505801.02 | U15: =R15+S15 -> 38250.739 | W15: 10 | X15: 45139 | Y15: =AG14 -> 505992.06 | Z15: =Z14 -> 3735.9623 | AA15: =Z15-AC15 -> 362.68193 | AB15: =(AA15/Y15)*12 -> 0.0086012874 | AC15: =Y15*($X$1/12) -> 3373.2804 | AD15: =(AC15/Y15)*12 -> 0.08 | AE15: =AE14+AA15 -> 3520.6221 | AF15: =AF14+AC15 -> 33839.001 | AG15: =Y15-AA15 -> 505629.38 | AH15: =AE15+AF15 -> 37359.623 | AJ15: 10 | AK15: 45139 | AL15: =AT14 -> 505831.01 | AM15: =AM14 -> 3647.6129 | AN15: =AM15-AP15 -> 380.7877 | AO15: =(AN15/AL15)*12 -> 0.0090335553 | AP15: =AL15*($AK$1/12) -> 3266.8252 | AQ15: =(AP15/AL15)*12 -> 0.0775 | AR15: =AR14+AN15 -> 3699.7813 | AS15: =AS14+AP15 -> 32776.348 | AT15: =AL15-AN15 -> 505450.22 | AU15: =AR15+AS15 -> 36476.129 | AW15: 10 | AX15: 45139 | AY15: =BG14 -> 505662.96 | AZ15: =AZ14 -> 3560.0507 | BA15: =AZ15-BC15 -> 399.65717 | BB15: =(BA15/AY15)*12 -> 0.0094843529 | BC15: =AY15*($AX$1/12) -> 3160.3935 | BD15: =(BC15/AY15)*12 -> 0.075 | BE15: =BE14+BA15 -> 3886.6965 | BF15: =BF14+BC15 -> 31713.81 | BG15: =AY15-BA15 -> 505263.3 | BH15: =BE15+BF15 -> 35600.507 | BJ15: 10 | BK15: 45139 | BL15: =BT14 -> 505487.71 | BM15: =BM14 -> 3473.3005 | BN15: =BM15-BP15 -> 419.31228 | BO15: =(BN15/BL15)*12 -> 0.0099542428 | BP15: =BL15*($BK$1/12) -> 3053.9882 | BQ15: =(BP15/BL15)*12 -> 0.0725 | BR15: =BR14+BN15 -> 4081.6027 | BS15: =BS14+BP15 -> 30651.403 | BT15: =BL15-BN15 -> 505068.4 | BU15: =BR15+BS15 -> 34733.005 | BW15: 10 | BX15: 45139 | BY15: =CG14 -> 505305.04 | BZ15: =BZ14 -> 3387.3877 | CA15: =BZ15-CC15 -> 439.77492 | CB15: =(CA15/BY15)*12 -> 0.010443789 | CC15: =BY15*($BX$1/12) -> 2947.6127 | CD15: =(CC15/BY15)*12 -> 0.07 | CE15: =CE14+CA15 -> 4284.7349 | CF15: =CF14+CC15 -> 29589.142 | CG15: =BY15-CA15 -> 504865.27 | CH15: =CE15+CF15 -> 33873.877
A16: =A15+1 -> 8 | B16: =VLOOKUP(A16*12,$J$5:$U$365,10) -> 323268.22 | C16: =VLOOKUP(A16*12,$W$5:$AH$365,10) -> 312918.99 | D16: =VLOOKUP(A16*12,$AJ$5:$AU$365,10) -> 302584.63 | E16: =VLOOKUP(A16*12,$AW$5:$BH$365,10) -> 292266.62 | F16: =VLOOKUP(A16*12,$BJ$5:$BU$365,10) -> 281966.52 | G16: =VLOOKUP(A16*12,$BW$5:$CH$365,10) -> 271685.95 | J16: 11 | K16: 45170 | L16: =T15 -> 505801.02 | M16: =$L$6/((($N$2)-1)/($N$1*$N$2)) -> 3825.0739 | N16: =M16-P16 -> 347.69193 | O16: =(N16/L16)*12 -> 0.0082489024 | P16: =L16*($K$1/12) -> 3477.382 | Q16: =(P16/L16)*12 -> 0.0825 | R16: =R15+N16 -> 3696.6765 | S16: =S15+P16 -> 38379.137 | T16: =L16-N16 -> 505453.32 | U16: =R16+S16 -> 42075.813 | W16: 11 | X16: 45170 | Y16: =AG15 -> 505629.38 | Z16: =Z15 -> 3735.9623 | AA16: =Z16-AC16 -> 365.09981 | AB16: =(AA16/Y16)*12 -> 0.0086648401 | AC16: =Y16*($X$1/12) -> 3370.8625 | AD16: =(AC16/Y16)*12 -> 0.08 | AE16: =AE15+AA16 -> 3885.7219 | AF16: =AF15+AC16 -> 37209.864 | AG16: =Y16-AA16 -> 505264.28 | AH16: =AE16+AF16 -> 41095.586 | AJ16: 11 | AK16: 45170 | AL16: =AT15 -> 505450.22 | AM16: =AM15 -> 3647.6129 | AN16: =AM16-AP16 -> 383.24695 | AO16: =(AN16/AL16)*12 -> 0.0090987465 | AP16: =AL16*($AK$1/12) -> 3264.366 | AQ16: =(AP16/AL16)*12 -> 0.0775 | AR16: =AR15+AN16 -> 4083.0282 | AS16: =AS15+AP16 -> 36040.714 | AT16: =AL16-AN16 -> 505066.97 | AU16: =AR16+AS16 -> 40123.742 | AW16: 11 | AX16: 45170 | AY16: =BG15 -> 505263.3 | AZ16: =AZ15 -> 3560.0507 | BA16: =AZ16-BC16 -> 402.15502 | BB16: =(BA16/AY16)*12 -> 0.009551179 | BC16: =AY16*($AX$1/12) -> 3157.8956 | BD16: =(BC16/AY16)*12 -> 0.075 | BE16: =BE15+BA16 -> 4288.8515 | BF16: =BF15+BC16 -> 34871.706 | BG16: =AY16-BA16 -> 504861.15 | BH16: =BE16+BF16 -> 39160.557 | BJ16: 11 | BK16: 45170 | BL16: =BT15 -> 505068.4 | BM16: =BM15 -> 3473.3005 | BN16: =BM16-BP16 -> 421.84563 | BO16: =(BN16/BL16)*12 -> 0.010022697 | BP16: =BL16*($BK$1/12) -> 3051.4549 | BQ16: =(BP16/BL16)*12 -> 0.0725 | BR16: =BR15+BN16 -> 4503.4483 | BS16: =BS15+BP16 -> 33702.858 | BT16: =BL16-BN16 -> 504646.55 | BU16: =BR16+BS16 -> 38206.306 | BW16: 11 | BX16: 45170 | BY16: =CG15 -> 504865.27 | BZ16: =BZ15 -> 3387.3877 | CA16: =BZ16-CC16 -> 442.34027 | CB16: =(CA16/BY16)*12 -> 0.010513861 | CC16: =BY16*($BX$1/12) -> 2945.0474 | CD16: =(CC16/BY16)*12 -> 0.07 | CE16: =CE15+CA16 -> 4727.0752 | CF16: =CF15+CC16 -> 32534.189 | CG16: =BY16-CA16 -> 504422.92 | CH16: =CE16+CF16 -> 37261.264
A17: =A16+1 -> 9 | B17: =VLOOKUP(A17*12,$J$5:$U$365,10) -> 361357.13 | C17: =VLOOKUP(A17*12,$W$5:$AH$365,10) -> 349701.44 | D17: =VLOOKUP(A17*12,$AJ$5:$AU$365,10) -> 338065.45 | E17: =VLOOKUP(A17*12,$AW$5:$BH$365,10) -> 326451.03 | F17: =VLOOKUP(A17*12,$BJ$5:$BU$365,10) -> 314860.16 | G17: =VLOOKUP(A17*12,$BW$5:$CH$365,10) -> 303294.85 | J17: 12 | K17: 45200 | L17: =T16 -> 505453.32 | M17: =$L$6/((($N$2)-1)/($N$1*$N$2)) -> 3825.0739 | N17: =M17-P17 -> 350.08232 | O17: =(N17/L17)*12 -> 0.0083113269 | P17: =L17*($K$1/12) -> 3474.9916 | Q17: =(P17/L17)*12 -> 0.0825 | R17: =R16+N17 -> 4046.7588 | S17: =S16+P17 -> 41854.128 | T17: =L17-N17 -> 505103.24 | U17: =R17+S17 -> 45900.887 | W17: 12 | X17: 45200 | Y17: =AG16 -> 505264.28 | Z17: =Z16 -> 3735.9623 | AA17: =Z17-AC17 -> 367.53381 | AB17: =(AA17/Y17)*12 -> 0.0087289086 | AC17: =Y17*($X$1/12) -> 3368.4285 | AD17: =(AC17/Y17)*12 -> 0.08 | AE17: =AE16+AA17 -> 4253.2557 | AF17: =AF16+AC17 -> 40578.292 | AG17: =Y17-AA17 -> 504896.74 | AH17: =AE17+AF17 -> 44831.548 | AJ17: 12 | AK17: 45200 | AL17: =AT16 -> 505066.97 | AM17: =AM16 -> 3647.6129 | AN17: =AM17-AP17 -> 385.72209 | AO17: =(AN17/AL17)*12 -> 0.009164458 | AP17: =AL17*($AK$1/12) -> 3261.8909 | AQ17: =(AP17/AL17)*12 -> 0.0775 | AR17: =AR16+AN17 -> 4468.7503 | AS17: =AS16+AP17 -> 39302.605 | AT17: =AL17-AN17 -> 504681.25 | AU17: =AR17+AS17 -> 43771.355 | AW17: 12 | AX17: 45200 | AY17: =BG16 -> 504861.15 | AZ17: =AZ16 -> 3560.0507 | BA17: =AZ17-BC17 -> 404.66849 | BB17: =(BA17/AY17)*12 -> 0.0096185296 | BC17: =AY17*($AX$1/12) -> 3155.3822 | BD17: =(BC17/AY17)*12 -> 0.075 | BE17: =BE16+BA17 -> 4693.52 | BF17: =BF16+BC17 -> 38027.088 | BG17: =AY17-BA17 -> 504456.48 | BH17: =BE17+BF17 -> 42720.608 | BJ17: 12 | BK17: 45200 | BL17: =BT16 -> 504646.55 | BM17: =BM16 -> 3473.3005 | BN17: =BM17-BP17 -> 424.39428 | BO17: =(BN17/BL17)*12 -> 0.01009168 | BP17: =BL17*($BK$1/12) -> 3048.9062 | BQ17: =(BP17/BL17)*12 -> 0.0725 | BR17: =BR16+BN17 -> 4927.8426 | BS17: =BS16+BP17 -> 36751.764 | BT17: =BL17-BN17 -> 504222.16 | BU17: =BR17+BS17 -> 41679.606 | BW17: 12 | BX17: 45200 | BY17: =CG16 -> 504422.92 | BZ17: =BZ16 -> 3387.3877 | CA17: =BZ17-CC17 -> 444.92059 | CB17: =(CA17/BY17)*12 -> 0.010584466 | CC17: =BY17*($BX$1/12) -> 2942.4671 | CD17: =(CC17/BY17)*12 -> 0.07 | CE17: =CE16+CA17 -> 5171.9957 | CF17: =CF16+CC17 -> 35476.656 | CG17: =BY17-CA17 -> 503978 | CH17: =CE17+CF17 -> 40648.652
A18: =A17+1 -> 10 | B18: =VLOOKUP(A18*12,$J$5:$U$365,10) -> 398776.62 | C18: =VLOOKUP(A18*12,$W$5:$AH$365,10) -> 385815.81 | D18: =VLOOKUP(A18*12,$AJ$5:$AU$365,10) -> 372880.42 | E18: =VLOOKUP(A18*12,$AW$5:$BH$365,10) -> 359972.76 | F18: =VLOOKUP(A18*12,$BJ$5:$BU$365,10) -> 347095.21 | G18: =VLOOKUP(A18*12,$BW$5:$CH$365,10) -> 334250.27 | J18: 13 | K18: 45231 | L18: =T17 -> 505103.24 | M18: =$L$6/((($N$2)-1)/($N$1*$N$2)) -> 3825.0739 | N18: =M18-P18 -> 352.48913 | O18: =(N18/L18)*12 -> 0.0083742673 | P18: =L18*($K$1/12) -> 3472.5848 | Q18: =(P18/L18)*12 -> 0.0825 | R18: =R17+N18 -> 4399.2479 | S18: =S17+P18 -> 45326.713 | T18: =L18-N18 -> 504750.75 | U18: =R18+S18 -> 49725.961 | W18: 13 | X18: 45231 | Y18: =AG17 -> 504896.74 | Z18: =Z17 -> 3735.9623 | AA18: =Z18-AC18 -> 369.98403 | AB18: =(AA18/Y18)*12 -> 0.0087934978 | AC18: =Y18*($X$1/12) -> 3365.9783 | AD18: =(AC18/Y18)*12 -> 0.08 | AE18: =AE17+AA18 -> 4623.2397 | AF18: =AF17+AC18 -> 43944.271 | AG18: =Y18-AA18 -> 504526.76 | AH18: =AE18+AF18 -> 48567.51 | AJ18: 13 | AK18: 45231 | AL18: =AT17 -> 504681.25 | AM18: =AM17 -> 3647.6129 | AN18: =AM18-AP18 -> 388.21321 | AO18: =(AN18/AL18)*12 -> 0.0092306947 | AP18: =AL18*($AK$1/12) -> 3259.3997 | AQ18: =(AP18/AL18)*12 -> 0.0775 | AR18: =AR17+AN18 -> 4856.9635 | AS18: =AS17+AP18 -> 42562.005 | AT18: =AL18-AN18 -> 504293.04 | AU18: =AR18+AS18 -> 47418.968 | AW18: 13 | AX18: 45231 | AY18: =BG17 -> 504456.48 | AZ18: =AZ17 -> 3560.0507 | BA18: =AZ18-BC18 -> 407.19767 | BB18: =(BA18/AY18)*12 -> 0.0096864095 | BC18: =AY18*($AX$1/12) -> 3152.853 | BD18: =(BC18/AY18)*12 -> 0.075 | BE18: =BE17+BA18 -> 5100.7177 | BF18: =BF17+BC18 -> 41179.941 | BG18: =AY18-BA18 -> 504049.28 | BH18: =BE18+BF18 -> 46280.659 | BJ18: 13 | BK18: 45231 | BL18: =BT17 -> 504222.16 | BM18: =BM17 -> 3473.3005 | BN18: =BM18-BP18 -> 426.95833 | BO18: =(BN18/BL18)*12 -> 0.010161196 | BP18: =BL18*($BK$1/12) -> 3046.3422 | BQ18: =(BP18/BL18)*12 -> 0.0725 | BR18: =BR17+BN18 -> 5354.8009 | BS18: =BS17+BP18 -> 39798.106 | BT18: =BL18-BN18 -> 503795.2 | BU18: =BR18+BS18 -> 45152.907 | BW18: 13 | BX18: 45231 | BY18: =CG17 -> 503978 | BZ18: =BZ17 -> 3387.3877 | CA18: =BZ18-CC18 -> 447.51596 | CB18: =(CA18/BY18)*12 -> 0.010655607 | CC18: =BY18*($BX$1/12) -> 2939.8717 | CD18: =(CC18/BY18)*12 -> 0.07 | CE18: =CE17+CA18 -> 5619.5117 | CF18: =CF17+CC18 -> 38416.528 | CG18: =BY18-CA18 -> 503530.49 | CH18: =CE18+CF18 -> 44036.04
A19: =A18+1 -> 11 | B19: =VLOOKUP(A19*12,$J$5:$U$365,10) -> 435469.31 | C19: =VLOOKUP(A19*12,$W$5:$AH$365,10) -> 421206.66 | D19: =VLOOKUP(A19*12,$AJ$5:$AU$365,10) -> 406976.08 | E19: =VLOOKUP(A19*12,$AW$5:$BH$365,10) -> 392780.35 | F19: =VLOOKUP(A19*12,$BJ$5:$BU$365,10) -> 378622.32 | G19: =VLOOKUP(A19*12,$BW$5:$CH$365,10) -> 364504.96 | J19: 14 | K19: 45261 | L19: =T18 -> 504750.75 | M19: =$L$6/((($N$2)-1)/($N$1*$N$2)) -> 3825.0739 | N19: =M19-P19 -> 354.91249 | O19: =(N19/L19)*12 -> 0.0084377287 | P19: =L19*($K$1/12) -> 3470.1614 | Q19: =(P19/L19)*12 -> 0.0825 | R19: =R18+N19 -> 4754.1604 | S19: =S18+P19 -> 48796.874 | T19: =L19-N19 -> 504395.84 | U19: =R19+S19 -> 53551.035 | W19: 14 | X19: 45261 | Y19: =AG18 -> 504526.76 | Z19: =Z18 -> 3735.9623 | AA19: =Z19-AC19 -> 372.45059 | AB19: =(AA19/Y19)*12 -> 0.0088586126 | AC19: =Y19*($X$1/12) -> 3363.5117 | AD19: =(AC19/Y19)*12 -> 0.08 | AE19: =AE18+AA19 -> 4995.6903 | AF19: =AF18+AC19 -> 47307.782 | AG19: =Y19-AA19 -> 504154.31 | AH19: =AE19+AF19 -> 52303.473 | AJ19: 14 | AK19: 45261 | AL19: =AT18 -> 504293.04 | AM19: =AM18 -> 3647.6129 | AN19: =AM19-AP19 -> 390.72042 | AO19: =(AN19/AL19)*12 -> 0.0092974614 | AP19: =AL19*($AK$1/12) -> 3256.8925 | AQ19: =(AP19/AL19)*12 -> 0.0775 | AR19: =AR18+AN19 -> 5247.6839 | AS19: =AS18+AP19 -> 45818.897 | AT19: =AL19-AN19 -> 503902.32 | AU19: =AR19+AS19 -> 51066.581 | AW19: 14 | AX19: 45261 | AY19: =BG18 -> 504049.28 | AZ19: =AZ18 -> 3560.0507 | BA19: =AZ19-BC19 -> 409.74266 | BB19: =(BA19/AY19)*12 -> 0.0097548237 | BC19: =AY19*($AX$1/12) -> 3150.308 | BD19: =(BC19/AY19)*12 -> 0.075 | BE19: =BE18+BA19 -> 5510.4603 | BF19: =BF18+BC19 -> 44330.249 | BG19: =AY19-BA19 -> 503639.54 | BH19: =BE19+BF19 -> 49840.709 | BJ19: 14 | BK19: 45261 | BL19: =BT18 -> 503795.2 | BM19: =BM18 -> 3473.3005 | BN19: =BM19-BP19 -> 429.53787 | BO19: =(BN19/BL19)*12 -> 0.01023125 | BP19: =BL19*($BK$1/12) -> 3043.7627 | BQ19: =(BP19/BL19)*12 -> 0.0725 | BR19: =BR18+BN19 -> 5784.3388 | BS19: =BS18+BP19 -> 42841.869 | BT19: =BL19-BN19 -> 503365.66 | BU19: =BR19+BS19 -> 48626.207 | BW19: 14 | BX19: 45261 | BY19: =CG18 -> 503530.49 | BZ19: =BZ18 -> 3387.3877 | CA19: =BZ19-CC19 -> 450.12647 | CB19: =(CA19/BY19)*12 -> 0.01072729 | CC19: =BY19*($BX$1/12) -> 2937.2612 | CD19: =(CC19/BY19)*12 -> 0.07 | CE19: =CE18+CA19 -> 6069.6382 | CF19: =CF18+CC19 -> 41353.789 | CG19: =BY19-CA19 -> 503080.36 | CH19: =CE19+CF19 -> 47423.427
A20: =A19+1 -> 12 | B20: =VLOOKUP(A20*12,$J$5:$U$365,10) -> 471372.94 | C20: =VLOOKUP(A20*12,$W$5:$AH$365,10) -> 455813.94 | D20: =VLOOKUP(A20*12,$AJ$5:$AU$365,10) -> 440294.66 | E20: =VLOOKUP(A20*12,$AW$5:$BH$365,10) -> 424818.36 | F20: =VLOOKUP(A20*12,$BJ$5:$BU$365,10) -> 409388.41 | G20: =VLOOKUP(A20*12,$BW$5:$CH$365,10) -> 394008.27 | J20: 15 | K20: 45292 | L20: =T19 -> 504395.84 | M20: =$L$6/((($N$2)-1)/($N$1*$N$2)) -> 3825.0739 | N20: =M20-P20 -> 357.35252 | O20: =(N20/L20)*12 -> 0.0085017161 | P20: =L20*($K$1/12) -> 3467.7214 | Q20: =(P20/L20)*12 -> 0.0825 | R20: =R19+N20 -> 5111.5129 | S20: =S19+P20 -> 52264.596 | T20: =L20-N20 -> 504038.49 | U20: =R20+S20 -> 57376.109 | W20: 15 | X20: 45292 | Y20: =AG19 -> 504154.31 | Z20: =Z19 -> 3735.9623 | AA20: =Z20-AC20 -> 374.9336 | AB20: =(AA20/Y20)*12 -> 0.0089242581 | AC20: =Y20*($X$1/12) -> 3361.0287 | AD20: =(AC20/Y20)*12 -> 0.08 | AE20: =AE19+AA20 -> 5370.6239 | AF20: =AF19+AC20 -> 50668.811 | AG20: =Y20-AA20 -> 503779.38 | AH20: =AE20+AF20 -> 56039.435 | AJ20: 15 | AK20: 45292 | AL20: =AT19 -> 503902.32 | AM20: =AM19 -> 3647.6129 | AN20: =AM20-AP20 -> 393.24382 | AO20: =(AN20/AL20)*12 -> 0.0093647632 | AP20: =AL20*($AK$1/12) -> 3254.3691 | AQ20: =(AP20/AL20)*12 -> 0.0775 | AR20: =AR19+AN20 -> 5640.9278 | AS20: =AS19+AP20 -> 49073.266 | AT20: =AL20-AN20 -> 503509.07 | AU20: =AR20+AS20 -> 54714.194 | AW20: 15 | AX20: 45292 | AY20: =BG19 -> 503639.54 | AZ20: =AZ19 -> 3560.0507 | BA20: =AZ20-BC20 -> 412.30355 | BB20: =(BA20/AY20)*12 -> 0.0098237771 | BC20: =AY20*($AX$1/12) -> 3147.7471 | BD20: =(BC20/AY20)*12 -> 0.075 | BE20: =BE19+BA20 -> 5922.7639 | BF20: =BF19+BC20 -> 47477.996 | BG20: =AY20-BA20 -> 503227.24 | BH20: =BE20+BF20 -> 53400.76 | BJ20: 15 | BK20: 45292 | BL20: =BT19 -> 503365.66 | BM20: =BM19 -> 3473.3005 | BN20: =BM20-BP20 -> 432.13299 | BO20: =(BN20/BL20)*12 -> 0.010301847 | BP20: =BL20*($BK$1/12) -> 3041.1675 | BQ20: =(BP20/BL20)*12 -> 0.0725 | BR20: =BR19+BN20 -> 6216.4718 | BS20: =BS19+BP20 -> 45883.036 | BT20: =BL20-BN20 -> 502933.53 | BU20: =BR20+BS20 -> 52099.508 | BW20: 15 | BX20: 45292 | BY20: =CG19 -> 503080.36 | BZ20: =BZ19 -> 3387.3877 | CA20: =BZ20-CC20 -> 452.75221 | CB20: =(CA20/BY20)*12 -> 0.01079952 | CC20: =BY20*($BX$1/12) -> 2934.6354 | CD20: =(CC20/BY20)*12 -> 0.07 | CE20: =CE19+CA20 -> 6522.3904 | CF20: =CF19+CC20 -> 44288.424 | CG20: =BY20-CA20 -> 502627.61 | CH20: =CE20+CF20 -> 50810.815
A21: =A20+1 -> 13 | B21: =VLOOKUP(A21*12,$J$5:$U$365,10) -> 506419.88 | C21: =VLOOKUP(A21*12,$W$5:$AH$365,10) -> 489572.6 | D21: =VLOOKUP(A21*12,$AJ$5:$AU$365,10) -> 472773.75 | E21: =VLOOKUP(A21*12,$AW$5:$BH$365,10) -> 456027.06 | F21: =VLOOKUP(A21*12,$BJ$5:$BU$365,10) -> 439336.44 | G21: =VLOOKUP(A21*12,$BW$5:$CH$365,10) -> 422705.89 | J21: 16 | K21: 45323 | L21: =T20 -> 504038.49 | M21: =$L$6/((($N$2)-1)/($N$1*$N$2)) -> 3825.0739 | N21: =M21-P21 -> 359.80932 | O21: =(N21/L21)*12 -> 0.0085662343 | P21: =L21*($K$1/12) -> 3465.2646 | Q21: =(P21/L21)*12 -> 0.0825 | R21: =R20+N21 -> 5471.3222 | S21: =S20+P21 -> 55729.86 | T21: =L21-N21 -> 503678.68 | U21: =R21+S21 -> 61201.183 | W21: 16 | X21: 45323 | Y21: =AG20 -> 503779.38 | Z21: =Z20 -> 3735.9623 | AA21: =Z21-AC21 -> 377.43315 | AB21: =(AA21/Y21)*12 -> 0.0089904392 | AC21: =Y21*($X$1/12) -> 3358.5292 | AD21: =(AC21/Y21)*12 -> 0.08 | AE21: =AE20+AA21 -> 5748.0571 | AF21: =AF20+AC21 -> 54027.34 | AG21: =Y21-AA21 -> 503401.94 | AH21: =AE21+AF21 -> 59775.397 | AJ21: 16 | AK21: 45323 | AL21: =AT20 -> 503509.07 | AM21: =AM20 -> 3647.6129 | AN21: =AM21-AP21 -> 395.78352 | AO21: =(AN21/AL21)*12 -> 0.0094326052 | AP21: =AL21*($AK$1/12) -> 3251.8294 | AQ21: =(AP21/AL21)*12 -> 0.0775 | AR21: =AR20+AN21 -> 6036.7113 | AS21: =AS20+AP21 -> 52325.096 | AT21: =AL21-AN21 -> 503113.29 | AU21: =AR21+AS21 -> 58361.807 | AW21: 16 | AX21: 45323 | AY21: =BG20 -> 503227.24 | AZ21: =AZ20 -> 3560.0507 | BA21: =AZ21-BC21 -> 414.88044 | BB21: =(BA21/AY21)*12 -> 0.0098932748 | BC21: =AY21*($AX$1/12) -> 3145.1702 | BD21: =(BC21/AY21)*12 -> 0.075 | BE21: =BE20+BA21 -> 6337.6443 | BF21: =BF20+BC21 -> 50623.166 | BG21: =AY21-BA21 -> 502812.36 | BH21: =BE21+BF21 -> 56960.811 | BJ21: 16 | BK21: 45323 | BL21: =BT20 -> 502933.53 | BM21: =BM20 -> 3473.3005 | BN21: =BM21-BP21 -> 434.7438 | BO21: =(BN21/BL21)*12 -> 0.010372992 | BP21: =BL21*($BK$1/12) -> 3038.5567 | BQ21: =(BP21/BL21)*12 -> 0.0725 | BR21: =BR20+BN21 -> 6651.2156 | BS21: =BS20+BP21 -> 48921.593 | BT21: =BL21-BN21 -> 502498.78 | BU21: =BR21+BS21 -> 55572.808 | BW21: 16 | BX21: 45323 | BY21: =CG20 -> 502627.61 | BZ21: =BZ20 -> 3387.3877 | CA21: =BZ21-CC21 -> 455.39326 | CB21: =(CA21/BY21)*12 -> 0.010872302 | CC21: =BY21*($BX$1/12) -> 2931.9944 | CD21: =(CC21/BY21)*12 -> 0.07 | CE21: =CE20+CA21 -> 6977.7837 | CF21: =CF20+CC21 -> 47220.419 | CG21: =BY21-CA21 -> 502172.22 | CH21: =CE21+CF21 -> 54198.202
... A38: =A37+1 -> 30 | B38: =VLOOKUP(A38*12,$J$5:$U$365,10) -> 867876.61 | C38: =VLOOKUP(A38*12,$W$5:$AH$365,10) -> 835796.44 | D38: =VLOOKUP(A38*12,$AJ$5:$AU$365,10) -> 803990.66 | E38: =VLOOKUP(A38*12,$AW$5:$BH$365,10) -> 772468.24 | F38: =VLOOKUP(A38*12,$BJ$5:$BU$365,10) -> 741238.19 | G38: =VLOOKUP(A38*12,$BW$5:$CH$365,10) -> 710309.56 | J38: 33 | K38: 45839 | L38: =T37 -> 497573.46 | M38: =$L$6/((($N$2)-1)/($N$1*$N$2)) -> 3825.0739 | N38: =M38-P38 -> 404.25638 | O38: =(N38/L38)*12 -> 0.0097494681 | P38: =L38*($K$1/12) -> 3420.8175 | Q38: =(P38/L38)*12 -> 0.0825 | R38: =R37+N38 -> 11980.797 | S38: =S37+P38 -> 114246.64 | T38: =L38-N38 -> 497169.2 | U38: =R38+S38 -> 126227.44 | W38: 33 | X38: 45839 | Y38: =AG37 -> 497009.13 | Z38: =Z37 -> 3735.9623 | AA38: =Z38-AC38 -> 422.56814 | AB38: =(AA38/Y38)*12 -> 0.010202665 | AC38: =Y38*($X$1/12) -> 3313.3942 | AD38: =(AC38/Y38)*12 -> 0.08 | AE38: =AE37+AA38 -> 12563.439 | AF38: =AF37+AC38 -> 110723.32 | AG38: =Y38-AA38 -> 496586.56 | AH38: =AE38+AF38 -> 123286.76 | AJ38: 33 | AK38: 45839 | AL38: =AT37 -> 496421.64 | AM38: =AM37 -> 3647.6129 | AN38: =AM38-AP38 -> 441.55653 | AO38: =(AN38/AL38)*12 -> 0.010673746 | AP38: =AL38*($AK$1/12) -> 3206.0564 | AQ38: =(AP38/AL38)*12 -> 0.0775 | AR38: =AR37+AN38 -> 13169.918 | AS38: =AS37+AP38 -> 107201.31 | AT38: =AL38-AN38 -> 495980.08 | AU38: =AR38+AS38 -> 120371.23 | AW38: 33 | AX38: 45839 | AY38: =BG37 -> 495810.35 | AZ38: =AZ37 -> 3560.0507 | BA38: =AZ38-BC38 -> 461.23595 | BB38: =(BA38/AY38)*12 -> 0.011163203 | BC38: =AY38*($AX$1/12) -> 3098.8147 | BD38: =(BC38/AY38)*12 -> 0.075 | BE38: =BE37+BA38 -> 13800.881 | BF38: =BF37+BC38 -> 103680.79 | BG38: =AY38-BA38 -> 495349.12 | BH38: =BE38+BF38 -> 117481.67 | BJ38: 33 | BK38: 45839 | BL38: =BT37 -> 495174.65 | BM38: =BM37 -> 3473.3005 | BN38: =BM38-BP38 -> 481.62037 | BO38: =(BN38/BL38)*12 -> 0.011671527 | BP38: =BL38*($BK$1/12) -> 2991.6802 | BQ38: =(BP38/BL38)*12 -> 0.0725 | BR38: =BR37+BN38 -> 14456.974 | BS38: =BS37+BP38 -> 100161.94 | BT38: =BL38-BN38 -> 494693.03 | BU38: =BR38+BS38 -> 114618.92 | BW38: 33 | BX38: 45839 | BY38: =CG37 -> 494513.89 | BZ38: =BZ37 -> 3387.3877 | CA38: =BZ38-CC38 -> 502.7233 | CB38: =(CA38/BY38)*12 -> 0.012199212 | CC38: =BY38*($BX$1/12) -> 2884.6644 | CD38: =(CC38/BY38)*12 -> 0.07 | CE38: =CE37+CA38 -> 15138.834 | CF38: =CF37+CC38 -> 96644.959 | CG38: =BY38-CA38 -> 494011.17 | CH38: =CE38+CF38 -> 111783.79
J39: 34 | K39: 45870 | L39: =T38 -> 497169.2 | M39: =$L$6/((($N$2)-1)/($N$1*$N$2)) -> 3825.0739 | N39: =M39-P39 -> 407.03565 | O39: =(N39/L39)*12 -> 0.0098244777 | P39: =L39*($K$1/12) -> 3418.0383 | Q39: =(P39/L39)*12 -> 0.0825 | R39: =R38+N39 -> 12387.833 | S39: =S38+P39 -> 117664.68 | T39: =L39-N39 -> 496762.17 | U39: =R39+S39 -> 130052.51 | W39: 34 | X39: 45870 | Y39: =AG38 -> 496586.56 | Z39: =Z38 -> 3735.9623 | AA39: =Z39-AC39 -> 425.38526 | AB39: =(AA39/Y39)*12 -> 0.010279423 | AC39: =Y39*($X$1/12) -> 3310.5771 | AD39: =(AC39/Y39)*12 -> 0.08 | AE39: =AE38+AA39 -> 12988.825 | AF39: =AF38+AC39 -> 114033.89 | AG39: =Y39-AA39 -> 496161.18 | AH39: =AE39+AF39 -> 127022.72 | AJ39: 34 | AK39: 45870 | AL39: =AT38 -> 495980.08 | AM39: =AM38 -> 3647.6129 | AN39: =AM39-AP39 -> 444.40825 | AO39: =(AN39/AL39)*12 -> 0.010752244 | AP39: =AL39*($AK$1/12) -> 3203.2047 | AQ39: =(AP39/AL39)*12 -> 0.0775 | AR39: =AR38+AN39 -> 13614.326 | AS39: =AS38+AP39 -> 110404.51 | AT39: =AL39-AN39 -> 495535.67 | AU39: =AR39+AS39 -> 124018.84 | AW39: 34 | AX39: 45870 | AY39: =BG38 -> 495349.12 | AZ39: =AZ38 -> 3560.0507 | BA39: =AZ39-BC39 -> 464.11868 | BB39: =(BA39/AY39)*12 -> 0.011243432 | BC39: =AY39*($AX$1/12) -> 3095.932 | BD39: =(BC39/AY39)*12 -> 0.075 | BE39: =BE38+BA39 -> 14265 | BF39: =BF38+BC39 -> 106776.72 | BG39: =AY39-BA39 -> 494885 | BH39: =BE39+BF39 -> 121041.72 | BJ39: 34 | BK39: 45870 | BL39: =BT38 -> 494693.03 | BM39: =BM38 -> 3473.3005 | BN39: =BM39-BP39 -> 484.53016 | BO39: =(BN39/BL39)*12 -> 0.011753475 | BP39: =BL39*($BK$1/12) -> 2988.7704 | BQ39: =(BP39/BL39)*12 -> 0.0725 | BR39: =BR38+BN39 -> 14941.504 | BS39: =BS38+BP39 -> 103150.71 | BT39: =BL39-BN39 -> 494208.5 | BU39: =BR39+BS39 -> 118092.22 | BW39: 34 | BX39: 45870 | BY39: =CG38 -> 494011.17 | BZ39: =BZ38 -> 3387.3877 | CA39: =BZ39-CC39 -> 505.65585 | CB39: =(CA39/BY39)*12 -> 0.01228286 | CC39: =BY39*($BX$1/12) -> 2881.7318 | CD39: =(CC39/BY39)*12 -> 0.07 | CE39: =CE38+CA39 -> 15644.489 | CF39: =CF38+CC39 -> 99526.691 | CG39: =BY39-CA39 -> 493505.51 | CH39: =CE39+CF39 -> 115171.18
J40: 35 | K40: 45901 | L40: =T39 -> 496762.17 | M40: =$L$6/((($N$2)-1)/($N$1*$N$2)) -> 3825.0739 | N40: =M40-P40 -> 409.83402 | O40: =(N40/L40)*12 -> 0.0099001263 | P40: =L40*($K$1/12) -> 3415.2399 | Q40: =(P40/L40)*12 -> 0.0825 | R40: =R39+N40 -> 12797.667 | S40: =S39+P40 -> 121079.92 | T40: =L40-N40 -> 496352.33 | U40: =R40+S40 -> 133877.59 | W40: 35 | X40: 45901 | Y40: =AG39 -> 496161.18 | Z40: =Z39 -> 3735.9623 | AA40: =Z40-AC40 -> 428.22116 | AB40: =(AA40/Y40)*12 -> 0.010356824 | AC40: =Y40*($X$1/12) -> 3307.7412 | AD40: =(AC40/Y40)*12 -> 0.08 | AE40: =AE39+AA40 -> 13417.046 | AF40: =AF39+AC40 -> 117341.64 | AG40: =Y40-AA40 -> 495732.95 | AH40: =AE40+AF40 -> 130758.68 | AJ40: 35 | AK40: 45901 | AL40: =AT39 -> 495535.67 | AM40: =AM39 -> 3647.6129 | AN40: =AM40-AP40 -> 447.27839 | AO40: =(AN40/AL40)*12 -> 0.010831391 | AP40: =AL40*($AK$1/12) -> 3200.3346 | AQ40: =(AP40/AL40)*12 -> 0.0775 | AR40: =AR39+AN40 -> 14061.604 | AS40: =AS39+AP40 -> 113604.85 | AT40: =AL40-AN40 -> 495088.4 | AU40: =AR40+AS40 -> 127666.45 | AW40: 35 | AX40: 45901 | AY40: =BG39 -> 494885 | AZ40: =AZ39 -> 3560.0507 | BA40: =AZ40-BC40 -> 467.01942 | BB40: =(BA40/AY40)*12 -> 0.011324314 | BC40: =AY40*($AX$1/12) -> 3093.0313 | BD40: =(BC40/AY40)*12 -> 0.075 | BE40: =BE39+BA40 -> 14732.019 | BF40: =BF39+BC40 -> 109869.75 | BG40: =AY40-BA40 -> 494417.98 | BH40: =BE40+BF40 -> 124601.77 | BJ40: 35 | BK40: 45901 | BL40: =BT39 -> 494208.5 | BM40: =BM39 -> 3473.3005 | BN40: =BM40-BP40 -> 487.45753 | BO40: =(BN40/BL40)*12 -> 0.011836078 | BP40: =BL40*($BK$1/12) -> 2985.843 | BQ40: =(BP40/BL40)*12 -> 0.0725 | BR40: =BR39+BN40 -> 15428.962 | BS40: =BS39+BP40 -> 106136.56 | BT40: =BL40-BN40 -> 493721.04 | BU40: =BR40+BS40 -> 121565.52 | BW40: 35 | BX40: 45901 | BY40: =CG39 -> 493505.51 | BZ40: =BZ39 -> 3387.3877 | CA40: =BZ40-CC40 -> 508.60551 | CB40: =(CA40/BY40)*12 -> 0.012367169 | CC40: =BY40*($BX$1/12) -> 2878.7821 | CD40: =(CC40/BY40)*12 -> 0.07 | CE40: =CE39+CA40 -> 16153.095 | CF40: =CF39+CC40 -> 102405.47 | CG40: =BY40-CA40 -> 492996.91 | CH40: =CE40+CF40 -> 118558.57
J41: 36 | K41: 45931 | L41: =T40 -> 496352.33 | M41: =$L$6/((($N$2)-1)/($N$1*$N$2)) -> 3825.0739 | N41: =M41-P41 -> 412.65162 | O41: =(N41/L41)*12 -> 0.0099764203 | P41: =L41*($K$1/12) -> 3412.4223 | Q41: =(P41/L41)*12 -> 0.0825 | R41: =R40+N41 -> 13210.318 | S41: =S40+P41 -> 124492.34 | T41: =L41-N41 -> 495939.68 | U41: =R41+S41 -> 137702.66 | W41: 36 | X41: 45931 | Y41: =AG40 -> 495732.95 | Z41: =Z40 -> 3735.9623 | AA41: =Z41-AC41 -> 431.07597 | AB41: =(AA41/Y41)*12 -> 0.010434875 | AC41: =Y41*($X$1/12) -> 3304.8864 | AD41: =(AC41/Y41)*12 -> 0.08 | AE41: =AE40+AA41 -> 13848.122 | AF41: =AF40+AC41 -> 120646.52 | AG41: =Y41-AA41 -> 495301.88 | AH41: =AE41+AF41 -> 134494.64 | AJ41: 36 | AK41: 45931 | AL41: =AT40 -> 495088.4 | AM41: =AM40 -> 3647.6129 | AN41: =AM41-AP41 -> 450.16706 | AO41: =(AN41/AL41)*12 -> 0.010911192 | AP41: =AL41*($AK$1/12) -> 3197.4459 | AQ41: =(AP41/AL41)*12 -> 0.0775 | AR41: =AR40+AN41 -> 14511.771 | AS41: =AS40+AP41 -> 116802.29 | AT41: =AL41-AN41 -> 494638.23 | AU41: =AR41+AS41 -> 131314.07 | AW41: 36 | AX41: 45931 | AY41: =BG40 -> 494417.98 | AZ41: =AZ40 -> 3560.0507 | BA41: =AZ41-BC41 -> 469.93829 | BB41: =(BA41/AY41)*12 -> 0.011405854 | BC41: =AY41*($AX$1/12) -> 3090.1124 | BD41: =(BC41/AY41)*12 -> 0.075 | BE41: =BE40+BA41 -> 15201.957 | BF41: =BF40+BC41 -> 112959.87 | BG41: =AY41-BA41 -> 493948.04 | BH41: =BE41+BF41 -> 128161.82 | BJ41: 36 | BK41: 45931 | BL41: =BT40 -> 493721.04 | BM41: =BM40 -> 3473.3005 | BN41: =BM41-BP41 -> 490.40259 | BO41: =(BN41/BL41)*12 -> 0.011919344 | BP41: =BL41*($BK$1/12) -> 2982.8979 | BQ41: =(BP41/BL41)*12 -> 0.0725 | BR41: =BR40+BN41 -> 15919.364 | BS41: =BS40+BP41 -> 109119.45 | BT41: =BL41-BN41 -> 493230.64 | BU41: =BR41+BS41 -> 125038.82 | BW41: 36 | BX41: 45931 | BY41: =CG40 -> 492996.91 | BZ41: =BZ40 -> 3387.3877 | CA41: =BZ41-CC41 -> 511.57237 | CB41: =(CA41/BY41)*12 -> 0.012452144 | CC41: =BY41*($BX$1/12) -> 2875.8153 | CD41: =(CC41/BY41)*12 -> 0.07 | CE41: =CE40+CA41 -> 16664.667 | CF41: =CF40+CC41 -> 105281.29 | CG41: =BY41-CA41 -> 492485.33 | CH41: =CE41+CF41 -> 121945.96
J42: 37 | K42: 45962 | L42: =T41 -> 495939.68 | M42: =$L$6/((($N$2)-1)/($N$1*$N$2)) -> 3825.0739 | N42: =M42-P42 -> 415.4886 | O42: =(N42/L42)*12 -> 0.010053366 | P42: =L42*($K$1/12) -> 3409.5853 | Q42: =(P42/L42)*12 -> 0.0825 | R42: =R41+N42 -> 13625.807 | S42: =S41+P42 -> 127901.93 | T42: =L42-N42 -> 495524.19 | U42: =R42+S42 -> 141527.73 | W42: 37 | X42: 45962 | Y42: =AG41 -> 495301.88 | Z42: =Z41 -> 3735.9623 | AA42: =Z42-AC42 -> 433.94981 | AB42: =(AA42/Y42)*12 -> 0.010513584 | AC42: =Y42*($X$1/12) -> 3302.0125 | AD42: =(AC42/Y42)*12 -> 0.08 | AE42: =AE41+AA42 -> 14282.072 | AF42: =AF41+AC42 -> 123948.53 | AG42: =Y42-AA42 -> 494867.93 | AH42: =AE42+AF42 -> 138230.61 | AJ42: 37 | AK42: 45962 | AL42: =AT41 -> 494638.23 | AM42: =AM41 -> 3647.6129 | AN42: =AM42-AP42 -> 453.07439 | AO42: =(AN42/AL42)*12 -> 0.010991655 | AP42: =AL42*($AK$1/12) -> 3194.5386 | AQ42: =(AP42/AL42)*12 -> 0.0775 | AR42: =AR41+AN42 -> 14964.846 | AS42: =AS41+AP42 -> 119996.83 | AT42: =AL42-AN42 -> 494185.15 | AU42: =AR42+AS42 -> 134961.68 | AW42: 37 | AX42: 45962 | AY42: =BG41 -> 493948.04 | AZ42: =AZ41 -> 3560.0507 | BA42: =AZ42-BC42 -> 472.8754 | BB42: =(BA42/AY42)*12 -> 0.01148806 | BC42: =AY42*($AX$1/12) -> 3087.1753 | BD42: =(BC42/AY42)*12 -> 0.075 | BE42: =BE41+BA42 -> 15674.833 | BF42: =BF41+BC42 -> 116047.04 | BG42: =AY42-BA42 -> 493475.17 | BH42: =BE42+BF42 -> 131721.87 | BJ42: 37 | BK42: 45962 | BL42: =BT41 -> 493230.64 | BM42: =BM41 -> 3473.3005 | BN42: =BM42-BP42 -> 493.36544 | BO42: =(BN42/BL42)*12 -> 0.01200328 | BP42: =BL42*($BK$1/12) -> 2979.9351 | BQ42: =(BP42/BL42)*12 -> 0.0725 | BR42: =BR41+BN42 -> 16412.73 | BS42: =BS41+BP42 -> 112099.39 | BT42: =BL42-BN42 -> 492737.27 | BU42: =BR42+BS42 -> 128512.12 | BW42: 37 | BX42: 45962 | BY42: =CG41 -> 492485.33 | BZ42: =BZ41 -> 3387.3877 | CA42: =BZ42-CC42 -> 514.55655 | CB42: =(CA42/BY42)*12 -> 0.012537792 | CC42: =BY42*($BX$1/12) -> 2872.8311 | CD42: =(CC42/BY42)*12 -> 0.07 | CE42: =CE41+CA42 -> 17179.224 | CF42: =CF41+CC42 -> 108154.12 | CG42: =BY42-CA42 -> 491970.78 | CH42: =CE42+CF42 -> 125333.34
