Workbook
Name If: #REF!
Name If: #REF!

Sheet Calculators
A3: Year | C3: Annual ROI | G3: Year | I3: Annual ROI | S3: IRR | T3: =XIRR(T4:T10,R4:R10) -> 0.21632629
A4: 0 | B4: 100000 | G4: 0 | H4: 100000 | M4: Present Value=Future Value /( 1+i)^n | R4: 45292 | S4: Initial Investment | T4: -8500000
A5: =A4+1 -> 1 | B5: 110000 | C5: =(B5/B4)-1 -> 0.1 | G5: =G4+1 -> 1 | H5: 110000 | I5: =(H5/H4)-1 -> 0.1 | M5: interest | N5: 0.08 | R5: =R4+365 -> 45657 | S5: Year 1 Cashflow | T5: =-$T$4*$U$5 -> 1360000 | U5: 0.16 | V5: Cash On Cash
A6: =A5+1 -> 2 | B6: 105000 | C6: =(B6/B5)-1 -> -0.045454545 | G6: =G5+1 -> 2 | H6: 105000 | I6: =(H6/H5)-1 -> -0.045454545 | M6: time (yrs) | N6: 5 | O6: =N6*12 -> 60 | R6: =R5+365 -> 46022 | S6: Year 2 Cashflow | T6: =-$T$4*$U$5 -> 1360000
A7: =A6+1 -> 3 | B7: 120000 | C7: =(B7/B6)-1 -> 0.14285714 | G7: =G6+1 -> 3 | H7: 120000 | I7: =(H7/H6)-1 -> 0.14285714 | R7: =R6+365 -> 46387 | S7: Year 3 Cashflow | T7: =-$T$4*$U$5 -> 1360000
A8: =A7+1 -> 4 | B8: =B7+5000 -> 125000 | C8: =(B8/B7)-1 -> 0.041666667 | G8: =G7+1 -> 4 | H8: =H7+5000 -> 125000 | I8: =(H8/H7)-1 -> 0.041666667 | R8: =R7+365 -> 46752 | S8: Year 4 Cashflow | T8: =-$T$4*$U$5 -> 1360000
A9: =A8+1 -> 5 | B9: =B8+5000 -> 130000 | C9: =(B9/B8)-1 -> 0.04 | G9: =G8+1 -> 5 | H9: =H8+5000 -> 130000 | I9: =(H9/H8)-1 -> 0.04 | R9: =R8+365 -> 47117 | S9: Year 5 Cashflow | T9: =-$T$4*$U$5 -> 1360000
A10: =A9+1 -> 6 | B10: =B9+5000 -> 135000 | C10: =(B10/B9)-1 -> 0.038461538 | R10: =R9+365 -> 47482 | S10: 6 | T10: =-T4*(1+U10)^S10 -> 14813534 | U10: 0.097 | V10: Assumed Appreciation
A11: =A10+1 -> 7 | B11: =B10+5000 -> 140000 | C11: =(B11/B10)-1 -> 0.037037037 | I11: =(H9-H4)/H4 -> 0.3 | J11: ROI
A12: =A11+1 -> 8 | B12: =B11+5000 -> 145000 | C12: =(B12/B11)-1 -> 0.035714286 | I12: =SUM(I5:I9)/COUNT(I5:I9) -> 0.055813853 | J12: AAR
A13: =A12+1 -> 9 | B13: =B12+5000 -> 150000 | C13: =(B13/B12)-1 -> 0.034482759 | I13: =(H9/H4)^(1/COUNT(I4:I9))-1 -> 0.053873952 | J13: CAGR | M13: 0.105 | N13: projected Cash On Cash Return
A14: =A13+1 -> 10 | B14: =B13+5000 -> 155000 | C14: =(B14/B13)-1 -> 0.033333333 | I14: =H9/H4 -> 1.3 | J14: Equity Multiplier | M14: 8500000 | N14: initial investment
M15: =O15*12 -> 60 | N15: hold period | O15: 5
C16: =(B14-B4)/B4 -> 0.55 | D16: ROI
C17: =SUM(C5:C14)/COUNT(C5:C14) -> 0.045809822 | D17: AAR | M17: Future | N17: =M14*(1+M13/12)^(M15) -> 14336125 | O17: =N17/M14 -> 1.686603 | P17: Equity Multiple
C18: =(B14/B4)^(1/COUNT(C4:C14))-1 -> 0.044800014 | D18: CAGR | M18: CAGR | N18: =(N17/M14)^(1/(O15*4))-1 -> 0.026480357
C19: =B14/B4 -> 1.55 | D19: Equity Multiplier

Sheet STR Calculator
H1: Heloc Down Payment | I1: 0.0825
A2: 915 Sanctuary Shores Way - 3bd / 4bath - 3240 sqft | B2: 3240 | C2: sqft | D2: =A3/B2 -> 231.48148 | E2: per sqft | H2: Heloc Loan Terms | I2: 20 | J2: yrs
A3: =B5 -> 750000 | B3: asking price | H3: HELOC Amount | I3: =SUM(B7+B6-C5-C4) -> 20000
C4: 5000 | D4: earnest money | H4: HELOC P&I Payment | I4: =-PMT($I$1/12,$I$2*12,I3) -> 170.41313 | J4: =I4*12 -> 2044.9576 | L4: IRR | M4: =IRR(M5:M11) -> 0.033020744
A5: Purchase Price | B5: 750000 | C5: 50000 | D5: cash | H5: HELOC Principle Payment | I5: =-PPMT($I$1/12,1,$I$2*12,I3) -> 32.91313 | J5: =I5*12 -> 394.95757 | L5: Initial Investment | M5: =-B5 -> -750000
A6: Closing Costs (4%) | B6: 0 | C6: $B$5*0.04 | H6: HELOC Interest Only Payment | I6: =-IPMT($I$1/12,1,$I$2*12,I3) -> 137.5 | J6: =I6*12 -> 1650 | L6: Year 1 Cashflow | M6: ='STR 10 Year'!B39 -> 9987.2708
A7: Down Payment | B7: =B5*C7 -> 75000 | C7: 0.1 | D7: downpayment | L7: Year 2 Cashflow | M7: ='STR 10 Year'!C39 -> 11253.271
A8: Total Loan Amount | B8: =B5-B7 -> 675000 | H8: Conventional Loan Interest Rate | I8: =IF(C7=0.1,0.08062,0.0775) -> 0.08062 | J8: IF(C7=0.1,0.08062,0.0775) | L8: Year 3 Cashflow | M8: ='STR 10 Year'!D39 -> 12225.871
H9: Loan Term | I9: 30 | J9: yrs | L9: Year 4 Cashflow | M9: ='STR 10 Year'!E39 -> 13205.019
H10: Monthly Payment on Purchase Price | I10: =-PMT($I$8/12,$I$9*12,$B$8) -> 4982.1163 | L10: Year 5 Cashflow | M10: ='STR 10 Year'!F39 -> 14190.658
A11: All In Price (Purchase+Repairs) | B11: =SUM(B5) -> 750000 | H11: Monthly Interest Payment on Purchase Price | I11: =-IPMT($I$8/12,1,$I$9*12,$B$8) -> 4534.875 | L11: 6 | M11: =$B$5*(1+0.02)^L11 -> 844621.81 | N11: assumes 2%/yr appreciation
A12: Estimated ARV (After Repair Value) | B12: =B5 -> 750000 | H12: Monthly Principle Payment on Purchase Price | I12: =-PPMT($I$8/12,1,$I$9*12,$B$8) -> 447.24132 | J12: =I12*12 -> 5366.8959
B14: Nightly | C14: Monthly | D14: Annually | H14: Financials
A15: Average Rent | B15: 300 | C15: =B15*30.5 -> 9150 | D15: =C15*12 -> 109800 | H15: Cash On Cash Return (CoC) | I15: =C48/SUM($B$6:$B$7) -> 0.13316361
A16: Occupancy Rate | B16: 1 | C16: =-C15*(1-B16) -> 0 | D16: =C16*12 -> 0 | H16: ROE (Return on Equity) | I16: =C48/B7 -> 0.13316361
A17: Additional Income (Laundry/Storage etc) | C17: 0 | D17: =C17*12 -> 0 | H17: AAR
H18: Mortgage Pay Down yr 1 | I18: =PPMT($I$8/12,1,$I$9*12,$B$8)*12 -> -5366.8959
A19: Calculated Gross Revenue | C19: =SUM(C15:C17) -> 9150 | D19: =C19*12 -> 109800 | H19: Tax Savings at 25% | I19: =C48*0.25 -> 2496.8177
H21: Rules of Thumb
A22: Estimated Expenses | B22: Monthly | C22: Annually | H22: 50% Rule
A23: Management Fees | B23: =C15*D23 -> 0 | C23: =B23*12 -> 0 | D23: 0 | E23: =IF(D23=0,1,0) -> 1 | H23: 2% Rule | I23: =$C$15/$B$5 -> 0.0122
A24: Subscriptions (AirDnA/Pricelabs/Guesty) | B24: 50 | C24: =B24*12 -> 600 | H24: DSCR | I24: =B44/(B46+B45+B47) -> 1.1535667
A25: AirBnB / VRBO Fee (3% of nightly) | B25: 0 | C25: =B25*12 -> 0
A26: Property Taxes / Year | B26: 200 | C26: =B26*12 -> 2400 | D26: =C26/B5 -> 0.0032
A27: Insurance / Year | B27: 200 | C27: =B27*12 -> 2400 | D27: =C27/B5 -> 0.0032
A28: Cleaners (per stay, average 6/month) - Trash included. Soap/Toilet Paper/Detergent etc. | B28: =D28*6 -> 1500 | C28: =B28*12 -> 18000 | D28: 250 | H28: Emergency Fund Needed (6 months) | I28: =B42*$J$28+SUM(B45:B46)*$J$28 -> 48106.365 | J28: 6 | K28: months
A29: Handyman | B29: 250 | C29: =B29*12 -> 3000 | I29: =I28/2 -> 24053.182 | J29: =J28/2 -> 3 | K29: months
A30: HOA / year | B30: 100 | C30: =B30*12 -> 1200 | D30: =C30/B5 -> 0.0016
A31: Electricity | B31: 250 | C31: =B31*12 -> 3000
A32: Nat Gas(~$2k for large tank, for ~1.5yrs) | B32: =2000/18 -> 111.11111 | C32: =B32*12 -> 1333.3333
A33: WIFI / Cable | B33: 150 | C33: =B33*12 -> 1800
A34: Pool Service (bi-weekly = 2xmonth) | B34: 0 | C34: =B34*12 -> 0
A35: Water/Sewer ($0 for well/septic) | B35: 0 | C35: =B35*12 -> 0
A36: Building Maintenance | B36: =C36/12 -> 0 | C36: =B5*D36 -> 0 | D36: 0
A37: Capex (Future Repairs) | B37: =C37/12 -> 0 | C37: =D37*B5 -> 0 | D37: 0
A38: Grounds Cleanup/Services Maintenance/Snow Removal | B38: 0 | C38: =B38*12 -> 0 | H38: Ask cleaners what is included vs not - Linens/soaps/shampoos/coffee/creamer
A39: City Permit Fees | B39: 25 | C39: =B39*12 -> 300
A40: Incidentals (Coffee/Creamer etc) | B40: 25 | C40: =B40*12 -> 300
A41: Umbrella Insurance (Allstate Anchorage) | B41: 37 | C41: =B41*12 -> 444
A42: Totals | B42: =SUM(B23:B41) -> 2898.1111 | C42: =SUM(C23:C41) -> 34777.333
A44: Net Operating Income | B44: =C19-B42 -> 6251.8889 | C44: =D19-C42 -> 75022.667 | D44: DSCR | E44: =B44/(B46+B45+B47) -> 1.1535667
A45: HELOC Payment (Interest Only) | B45: =IF(I6<0,0,I6) -> 137.5 | C45: =B45*12 -> 1650 | D45: =IF(B45=I6,1,0) -> 1
A46: Conventional Loan Payment | B46: =-PMT($I$8/12,$I$9*12,$B$8) -> 4982.1163 | C46: =B46*12 -> 59785.396 | D46: Cap Rate | E46: =C44/$B$5 -> 0.10003022
A47: PMI if down payment less than 20% | B47: =IF(C7<0.2,300,0) -> 300 | C47: =B47*12 -> 3600 | D47: =ROUND(C47/B8,4)&"% of loan" -> 0.0053% of loan
A48: Cash Flow | B48: =B44-B46-B45-B47 -> 832.27257 | C48: =B48*12 -> 9987.2708
A51: Estimated CapEx | B51: Timeline of Repair (yrs) | C51: Cost per Unit | D51: Total Cost | E51: Monthly Cost
A52: Roof | B52: 5 | C52: 7000 | D52: =C52 -> 7000 | E52: =D52/B52/12 -> 116.66667
A53: Master Bath | B53: 10 | D53: =C53 -> 0 | E53: =D53/B53/12 -> 0
A54: Kitchen | B54: 10 | D54: =C54 -> 0 | E54: =D54/B54/12 -> 0
A55: Flooring | B55: 10 | C55: 8000 | D55: =C55 -> 8000 | E55: =D55/B55/12 -> 66.666667
A56: Guest baths | B56: 10 | D56: =C56 -> 0 | E56: =D56/B56/12 -> 0
A57: Exterior Paint | B57: 1 | D57: =C57 -> 0 | E57: =D57/B57/12 -> 0
A58: Interior Paint | B58: 6 | C58: 2000 | D58: =C58 -> 2000 | E58: =D58/B58/12 -> 27.777778
A59: Cabinets | B59: 10 | D59: =C59 -> 0 | E59: =D59/B59/12 -> 0
A60: Concrete walkways | B60: 4 | D60: =C60 -> 0 | E60: =D60/B60/12 -> 0
A61: Driveway Re-Pave (Asphalt) | B61: 1 | D61: =C61 -> 0 | E61: =D61/B61/12 -> 0
A62: Miscellaneous (light fixtures/door knobs etc) | B62: 10 | C62: 500 | D62: =C62 -> 500 | E62: =D62/B62/12 -> 4.1666667
A63: Total Estimated Repairs | E63: =SUM(E52:E62) -> 215.27778

Sheet Interest Rate Comparison
A1: Purchase Price | C1: 0.1 | D1: 0.15 | E1: 0.2 | F1: 0.25 | H1: 5% Increase in Down Payment | I1: Time to recoup
A2: ='STR Calculator'!B5 -> 750000 | B2: Down Payment | C2: =$A$2*C1 -> 75000 | D2: =$A$2*D1 -> 112500 | E2: =$A$2*E1 -> 150000 | F2: =$A$2*F1 -> 187500 | H2: =D2-C2 -> 37500
A3: 30 | B3: 0.0825 | C3: =PMT($B$3/12,$A$3*12,($A$2-C2)) -> -5071.0496 | D3: =PMT($B$3/12,$A$3*12,($A$2-D2)) -> -4789.3246 | E3: =PMT($B$3/12,$A$3*12,($A$2-E2)) -> -4507.5996 | F3: =PMT($B$3/12,$A$3*12,($A$2-F2)) -> -4225.8746 | G3: =B3 -> 0.0825 | H3: =D3-C3 -> 281.72498 | I3: =$H$2/H3/12 -> 11.092378
B4: 0.08 | C4: =PMT($B$4/12,$A$3*12,($A$2-C2)) -> -4952.9109 | D4: =PMT($B$4/12,$A$3*12,($A$2-D2)) -> -4677.7492 | E4: =PMT($B$4/12,$A$3*12,($A$2-E2)) -> -4402.5874 | F4: =PMT($B$4/12,$A$3*12,($A$2-F2)) -> -4127.4257 | G4: =B4 -> 0.08 | H4: =D4-C4 -> 275.16172 | I4: =$H$2/H4/12 -> 11.356958
B5: 0.0775 | C5: =PMT($B$5/12,$A$3*12,($A$2-C2)) -> -4835.7827 | D5: =PMT($B$5/12,$A$3*12,($A$2-D2)) -> -4567.1281 | E5: =PMT($B$5/12,$A$3*12,($A$2-E2)) -> -4298.4735 | F5: =PMT($B$5/12,$A$3*12,($A$2-F2)) -> -4029.8189 | G5: =B5 -> 0.0775 | H5: =D5-C5 -> 268.65459 | I5: =$H$2/H5/12 -> 11.632036
B6: 0.075 | C6: =PMT($B$6/12,$A$3*12,($A$2-C2)) -> -4719.6979 | D6: =PMT($B$6/12,$A$3*12,($A$2-D2)) -> -4457.4925 | E6: =PMT($B$6/12,$A$3*12,($A$2-E2)) -> -4195.2871 | F6: =PMT($B$6/12,$A$3*12,($A$2-F2)) -> -3933.0816 | G6: =B6 -> 0.075 | H6: =D6-C6 -> 262.20544 | I6: =$H$2/H6/12 -> 11.918136
B7: 0.0725 | C7: =PMT($B$7/12,$A$3*12,($A$2-C2)) -> -4604.6899 | D7: =PMT($B$7/12,$A$3*12,($A$2-D2)) -> -4348.8738 | E7: =PMT($B$7/12,$A$3*12,($A$2-E2)) -> -4093.0577 | F7: =PMT($B$7/12,$A$3*12,($A$2-F2)) -> -3837.2416 | G7: =B7 -> 0.0725 | H7: =D7-C7 -> 255.81611 | I7: =$H$2/H7/12 -> 12.215806
B8: 0.07 | C8: =PMT($B$8/12,$A$3*12,($A$2-C2)) -> -4490.7918 | D8: =PMT($B$8/12,$A$3*12,($A$2-D2)) -> -4241.3034 | E8: =PMT($B$8/12,$A$3*12,($A$2-E2)) -> -3991.815 | F8: =PMT($B$8/12,$A$3*12,($A$2-F2)) -> -3742.3265 | G8: =B8 -> 0.07 | H8: =D8-C8 -> 249.48844 | I8: =$H$2/H8/12 -> 12.525631
G9: Higher delta between P&I payment at higher interest rate compared to lower = shorter payout, when factoring in increased down payment for lower rate
A12: Down Payment % | B12: Down Payment | C12: Interest Rate | D12: ="Interest Paid on Down Payment by Year "&ROUND(I4,0) -> Interest Paid on Down Payment by Year 11 | E12: Down Payment Difference | F12: ="Interest Paid Difference @ year "&ROUND(I4,0) -> Interest Paid Difference @ year 11 | G12: Down Payment vs Interest Paid | H12: =ROUND(I4,0)&"yr FV of down payment saved @ 8%" -> 11yr FV of down payment saved @ 8% | I12: NPV of Interest Saved/Lost | J12: ="Cum Interest Paid Year "&ROUND(I4,0) -> Cum Interest Paid Year 11 | K12: Interest Saved Compared to 10% Loan | L12: Total Interest Paid - Life of Loan
A13: =C1 -> 0.1 | B13: =$A$2*A13 -> 75000 | C13: =B4 -> 0.08 | D13: =B13*(1+C13)^$I$4 -> 179743.6 | E13: 0 | F13: 0 | G13: =F13-E13 -> 0 | H13: 0 | I13: 0 | J13: =VLOOKUP($I$4*12,'Amoritization Scenario 10% DP'!$W$8:$AH$367,10) -> 573823.03 | K13: 0 | L13: 1270301
A14: =D1 -> 0.15 | B14: =$A$2*A14 -> 112500 | C14: =B4 -> 0.08 | D14: =B14*(1+C14)^$I$4 -> 269615.41 | E14: =B14-B13 -> 37500 | F14: =D14-D13 -> 89871.802 | G14: =F14-E14 -> 52371.802 | H14: =E14*(1+0.08)^I4 -> 89871.802 | I14: =G14/(1+C14)^I4 -> 21852.712 | J14: =VLOOKUP($I$4*12,'Amoritization Scenario 15% DP'!$W$8:$AH$367,10) -> 541943.97 | K14: =J13-J14 -> 31879.057 | L14: 1199728 | M14: =L14+H14 -> 1289599.8
A15: =E1 -> 0.2 | B15: =$A$2*A15 -> 150000 | C15: =B5 -> 0.0775 | D15: =B15*(1+C15)^$I$4 -> 350149.03 | E15: =B15-B13 -> 75000 | F15: =D15-D13 -> 170405.43 | G15: =F15-E15 -> 95405.426 | H15: =E15*(1+0.08)^I4 -> 179743.6 | I15: =G15/(1+C15)^I4 -> 40870.637 | J15: =VLOOKUP($I$4*12,'Amoritization Scenario 20% DP'!$AJ$8:$AU$367,10) -> 492787.9 | K15: =J13-J15 -> 81035.128 | L15: 1034105 | M15: =L15+H15 -> 1213848.6
K17: Present Value=Future Value /( 1+i)^n

Sheet STR 10 Year
A1: Year | B1: 1 | C1: 2 | D1: 3 | E1: 4 | F1: 5 | G1: 6 | H1: 7 | I1: 8 | J1: 9 | K1: 10
A2: Property Income | L2: Desired Return | M2: 0.08 | N2: match stock market
A3: Yearly Revenue | B3: ='STR Calculator'!D15 -> 109800 | C3: =B3*(1+C5) -> 110898 | D3: =C3*(1+D5) -> 112006.98 | E3: =D3*(1+E5) -> 113127.05 | F3: =E3*(1+F5) -> 114258.32 | G3: =F3*(1+G5) -> 115400.9 | H3: =G3*(1+H5) -> 116554.91 | I3: =H3*(1+I5) -> 117720.46 | J3: =I3*(1+J5) -> 118897.67 | K3: =J3*(1+K5) -> 120086.64
A4: Monthly Revenue | B4: =B3/12 -> 9150 | C4: =C3/12 -> 9241.5 | D4: =D3/12 -> 9333.915 | E4: =E3/12 -> 9427.2541 | F4: =F3/12 -> 9521.5267 | G4: =G3/12 -> 9616.742 | H4: =H3/12 -> 9712.9094 | I4: =I3/12 -> 9810.0385 | ... K4: =K3/12 -> 10007.22 | M4: IRR | P4: NPV
A5: Rent Appreciation | B5: 0.01 | C5: =$B$5 -> 0.01 | D5: =$B$5 -> 0.01 | E5: =$B$5 -> 0.01 | F5: =$B$5 -> 0.01 | G5: =$B$5 -> 0.01 | H5: =$B$5 -> 0.01 | I5: =$B$5 -> 0.01 | J5: =$B$5 -> 0.01 | K5: =$B$5 -> 0.01 | M5: 45536 | N5: 0 | O5: =-SUM('STR Calculator'!B6:B7) -> -75000 | P5: =O5 -> -75000
A6: ="Vacancy Loss (Occupancy rate "&'STR Calculator'!$B$16&"%)" -> Vacancy Loss (Occupancy rate 1%) | B6: =B3*(1-'STR Calculator'!$B$16) -> 0 | C6: =C3*(1-'STR Calculator'!$B$16) -> 0 | D6: =D3*(1-'STR Calculator'!$B$16) -> 0 | E6: =E3*(1-'STR Calculator'!$B$16) -> 0 | F6: =F3*(1-'STR Calculator'!$B$16) -> 0 | G6: =G3*(1-'STR Calculator'!$B$16) -> 0 | H6: =H3*(1-'STR Calculator'!$B$16) -> 0 | I6: =I3*(1-'STR Calculator'!$B$16) -> 0 | ... K6: =K3*(1-'STR Calculator'!$B$16) -> 0 | M6: 45901 | N6: 1 | O6: =B39 -> 9987.2708 | P6: =O6/(1+$M$2)^N6 -> 9247.473
M7: 46266 | N7: 2 | O7: =C39 -> 11253.271 | P7: =O7/(1+$M$2)^N7 -> 9647.8659
A8: Operating Income | B8: =B3-B6 -> 109800 | C8: =C3-C6 -> 110898 | D8: =D3-D6 -> 112006.98 | E8: =E3-E6 -> 113127.05 | F8: =F3-F6 -> 114258.32 | G8: =G3-G6 -> 115400.9 | H8: =H3-H6 -> 116554.91 | I8: =I3-I6 -> 117720.46 | ... K8: =K3-K6 -> 120086.64 | M8: 46631 | N8: 3 | O8: =D39 -> 12225.871 | P8: =O8/(1+$M$2)^N8 -> 9705.2904
M9: 46997 | N9: 4 | O9: =E39 -> 13205.019 | P9: =O9/(1+$M$2)^N9 -> 9706.0831
A10: Property Expenses | M10: 47362 | N10: 5 | O10: =F39 -> 14190.658 | P10: =O10/(1+$M$2)^N10 -> 9657.9234
A11: Management Fee | B11: ='STR Calculator'!$C$23 -> 0 | C11: =$B$11 -> 0 | D11: =$B$11 -> 0 | E11: =$B$11 -> 0 | F11: =$B$11 -> 0 | G11: =$B$11 -> 0 | H11: =$B$11 -> 0 | I11: =$B$11 -> 0 | J11: =$B$11 -> 0 | K11: =$B$11 -> 0 | M11: 47727 | N11: 6 | O11: =G39 -> 15182.726 | P11: =O11/(1+$M$2)^N11 -> 9567.6926
A12: Subscriptions | B12: ='STR Calculator'!$C$24 -> 600 | C12: ='STR Calculator'!$C$24 -> 600 | D12: ='STR Calculator'!$C$24 -> 600 | E12: ='STR Calculator'!$C$24 -> 600 | F12: ='STR Calculator'!$C$24 -> 600 | G12: ='STR Calculator'!$C$24 -> 600 | H12: ='STR Calculator'!$C$24 -> 600 | I12: ='STR Calculator'!$C$24 -> 600 | ... K12: ='STR Calculator'!$C$24 -> 600 | M12: 48092 | N12: 7 | O12: =H39 -> 16181.154 | P12: =O12/(1+$M$2)^N12 -> 9441.5479
A13: AirBnB/VRBO Fee (3% of nightly- Passed to guest) | B13: ='STR Calculator'!$C$25 -> 0 | C13: ='STR Calculator'!$C$25 -> 0 | D13: ='STR Calculator'!$C$25 -> 0 | E13: ='STR Calculator'!$C$25 -> 0 | F13: ='STR Calculator'!$C$25 -> 0 | G13: ='STR Calculator'!$C$25 -> 0 | H13: ='STR Calculator'!$C$25 -> 0 | I13: ='STR Calculator'!$C$25 -> 0 | ... K13: ='STR Calculator'!$C$25 -> 0 | M13: 48458 | N13: 8 | O13: =I39 -> 17185.868 | P13: =O13/(1+$M$2)^N13 -> 9284.99
A14: Property Taxes (1.5%) | B14: ='STR Calculator'!$C$26 -> 2400 | C14: =B44*($B$14/'STR Calculator'!$B$5) -> 2496 | D14: =C44*($B$14/'STR Calculator'!$B$5) -> 2595.84 | E14: =D44*($B$14/'STR Calculator'!$B$5) -> 2699.6736 | F14: =E44*($B$14/'STR Calculator'!$B$5) -> 2807.6605 | G14: =F44*($B$14/'STR Calculator'!$B$5) -> 2919.967 | H14: =G44*($B$14/'STR Calculator'!$B$5) -> 3036.7656 | I14: =H44*($B$14/'STR Calculator'!$B$5) -> 3158.2363 | J14: =I44*($B$14/'STR Calculator'!$B$5) -> 3284.5657 | K14: =J44*($B$14/'STR Calculator'!$B$5) -> 3415.9483 | M14: 48823 | N14: 9 | O14: =J39 -> 18196.789 | P14: =O14/(1+$M$2)^N14 -> 9102.925
A15: Insurance (1.5%) | B15: ='STR Calculator'!$C$27 -> 2400 | C15: =B15+(B15*0.015) -> 2436 | D15: =C15+(C15*0.015) -> 2472.54 | E15: =D15+(D15*0.015) -> 2509.6281 | F15: =E15+(E15*0.015) -> 2547.2725 | G15: =F15+(F15*0.015) -> 2585.4816 | H15: =G15+(G15*0.015) -> 2624.2638 | I15: =H15+(H15*0.015) -> 2663.6278 | J15: =I15+(I15*0.015) -> 2703.5822 | K15: =J15+(J15*0.015) -> 2744.1359 | M15: 49188 | N15: 10 | O15: =K39+K44-('STR Calculator'!B8-SUM('STR 10 Year'!B46:K46)) -> 537255.29 | P15: =O15/(1+$M$2)^N15 -> 248853.15
A16: Cleaners/Handyman | B16: =SUM('STR Calculator'!$C$28:$C$29) -> 21000 | C16: =SUM('STR Calculator'!$C$28:$C$29) -> 21000 | D16: =SUM('STR Calculator'!$C$28:$C$29) -> 21000 | E16: =SUM('STR Calculator'!$C$28:$C$29) -> 21000 | F16: =SUM('STR Calculator'!$C$28:$C$29) -> 21000 | G16: =SUM('STR Calculator'!$C$28:$C$29) -> 21000 | H16: =SUM('STR Calculator'!$C$28:$C$29) -> 21000 | I16: =SUM('STR Calculator'!$C$28:$C$29) -> 21000 | ... K16: =SUM('STR Calculator'!$C$28:$C$29) -> 21000
A17: HOA Fees | B17: ='STR Calculator'!$C$30 -> 1200 | C17: ='STR Calculator'!$C$30 -> 1200 | D17: ='STR Calculator'!$C$30 -> 1200 | E17: ='STR Calculator'!$C$30 -> 1200 | F17: ='STR Calculator'!$C$30 -> 1200 | G17: ='STR Calculator'!$C$30 -> 1200 | H17: ='STR Calculator'!$C$30 -> 1200 | I17: ='STR Calculator'!$C$30 -> 1200 | ... K17: ='STR Calculator'!$C$30 -> 1200 | O17: =XIRR(O5:O15,M5:M15) -> 0.30445239 | P17: =SUM(P5:P15) -> 259214.94
A18: Electricity | B18: ='STR Calculator'!$C$31 -> 3000 | C18: ='STR Calculator'!$C$31 -> 3000 | D18: ='STR Calculator'!$C$31 -> 3000 | E18: ='STR Calculator'!$C$31 -> 3000 | F18: ='STR Calculator'!$C$31 -> 3000 | G18: ='STR Calculator'!$C$31 -> 3000 | H18: ='STR Calculator'!$C$31 -> 3000 | I18: ='STR Calculator'!$C$31 -> 3000 | ... K18: ='STR Calculator'!$C$31 -> 3000
A19: Natural Gas | B19: ='STR Calculator'!$C$32 -> 1333.3333 | C19: ='STR Calculator'!$C$32 -> 1333.3333 | D19: ='STR Calculator'!$C$32 -> 1333.3333 | E19: ='STR Calculator'!$C$32 -> 1333.3333 | F19: ='STR Calculator'!$C$32 -> 1333.3333 | G19: ='STR Calculator'!$C$32 -> 1333.3333 | H19: ='STR Calculator'!$C$32 -> 1333.3333 | I19: ='STR Calculator'!$C$32 -> 1333.3333 | ... K19: ='STR Calculator'!$C$32 -> 1333.3333
A20: WIFI/Cable | B20: ='STR Calculator'!$C$33 -> 1800 | C20: ='STR Calculator'!$C$33 -> 1800 | D20: ='STR Calculator'!$C$33 -> 1800 | E20: ='STR Calculator'!$C$33 -> 1800 | F20: ='STR Calculator'!$C$33 -> 1800 | G20: ='STR Calculator'!$C$33 -> 1800 | H20: ='STR Calculator'!$C$33 -> 1800 | I20: ='STR Calculator'!$C$33 -> 1800 | ... K20: ='STR Calculator'!$C$33 -> 1800
A21: Water/Sewer ($0 if septic/well) | B21: ='STR Calculator'!$C$35 -> 0 | C21: ='STR Calculator'!$C$35 -> 0 | D21: ='STR Calculator'!$C$35 -> 0 | E21: ='STR Calculator'!$C$35 -> 0 | F21: ='STR Calculator'!$C$35 -> 0 | G21: ='STR Calculator'!$C$35 -> 0 | H21: ='STR Calculator'!$C$35 -> 0 | I21: ='STR Calculator'!$C$35 -> 0 | ... K21: ='STR Calculator'!$C$35 -> 0
A22: Pool Service ($75/each x biweekly) | B22: ='STR Calculator'!$C$34 -> 0 | C22: ='STR Calculator'!$C$34 -> 0 | D22: ='STR Calculator'!$C$34 -> 0 | E22: ='STR Calculator'!$C$34 -> 0 | F22: ='STR Calculator'!$C$34 -> 0 | G22: ='STR Calculator'!$C$34 -> 0 | H22: ='STR Calculator'!$C$34 -> 0 | I22: ='STR Calculator'!$C$34 -> 0 | ... K22: ='STR Calculator'!$C$34 -> 0
A23: Building Maintenance (1%) | B23: ='STR Calculator'!$C$36 -> 0 | C23: ='STR Calculator'!$B$5*'STR Calculator'!$D$37 -> 0 | D23: ='STR Calculator'!$B$5*'STR Calculator'!$D$37 -> 0 | E23: ='STR Calculator'!$B$5*'STR Calculator'!$D$37 -> 0 | F23: ='STR Calculator'!$B$5*'STR Calculator'!$D$37 -> 0 | G23: ='STR Calculator'!$B$5*'STR Calculator'!$D$37 -> 0 | H23: ='STR Calculator'!$B$5*'STR Calculator'!$D$37 -> 0 | I23: ='STR Calculator'!$B$5*'STR Calculator'!$D$37 -> 0 | J23: ='STR Calculator'!$B$5*'STR Calculator'!$D$37 -> 0 | K23: ='STR Calculator'!$B$5*'STR Calculator'!$D$37 -> 0
A24: Capex (1%) | B24: ='STR Calculator'!$C$37 -> 0 | C24: ='STR Calculator'!$C$37 -> 0 | D24: ='STR Calculator'!$C$37 -> 0 | E24: ='STR Calculator'!$C$37 -> 0 | F24: ='STR Calculator'!$C$37 -> 0 | G24: ='STR Calculator'!$C$37 -> 0 | H24: ='STR Calculator'!$C$37 -> 0 | I24: ='STR Calculator'!$C$37 -> 0 | ... K24: ='STR Calculator'!$C$37 -> 0
A25: Grounds Cleanup/Services/Snow Removal | B25: ='STR Calculator'!$C$38 -> 0 | C25: ='STR Calculator'!$C$38 -> 0 | D25: ='STR Calculator'!$C$38 -> 0 | E25: ='STR Calculator'!$C$38 -> 0 | F25: ='STR Calculator'!$C$38 -> 0 | G25: ='STR Calculator'!$C$38 -> 0 | H25: ='STR Calculator'!$C$38 -> 0 | I25: ='STR Calculator'!$C$38 -> 0 | ... K25: ='STR Calculator'!$C$38 -> 0
A26: City Permit Fee | B26: 300 | C26: 0 | D26: 0 | E26: 0 | F26: 0 | G26: 0 | H26: 0 | I26: 0 | J26: 0 | K26: 0
A27: Incidentals (Coffee/Creamer etc) | B27: ='STR Calculator'!$C$40 -> 300 | C27: ='STR Calculator'!$C$40 -> 300 | D27: ='STR Calculator'!$C$40 -> 300 | E27: ='STR Calculator'!$C$40 -> 300 | F27: ='STR Calculator'!$C$40 -> 300 | G27: ='STR Calculator'!$C$40 -> 300 | H27: ='STR Calculator'!$C$40 -> 300 | I27: ='STR Calculator'!$C$40 -> 300 | ... K27: ='STR Calculator'!$C$40 -> 300
A28: Umbrella Insurance | B28: ='STR Calculator'!$C$41 -> 444 | C28: ='STR Calculator'!$C$41 -> 444 | D28: ='STR Calculator'!$C$41 -> 444 | E28: ='STR Calculator'!$C$41 -> 444 | F28: ='STR Calculator'!$C$41 -> 444 | G28: ='STR Calculator'!$C$41 -> 444 | H28: ='STR Calculator'!$C$41 -> 444 | I28: ='STR Calculator'!$C$41 -> 444 | ... K28: ='STR Calculator'!$C$41 -> 444
A30: Operating Expenses | B30: =SUM(B12:B28) -> 34777.333 | C30: =SUM(C12:C28) -> 34609.333 | D30: =SUM(D12:D28) -> 34745.713 | E30: =SUM(E12:E28) -> 34886.635 | F30: =SUM(F12:F28) -> 35032.266 | G30: =SUM(G12:G28) -> 35182.782 | H30: =SUM(H12:H28) -> 35338.363 | I30: =SUM(I12:I28) -> 35499.197 | ... K30: =SUM(K12:K28) -> 35837.418
A32: Net Operating Income (NOI) | B32: =B8-B30 -> 75022.667 | C32: =C8-C30 -> 76288.667 | D32: =D8-D30 -> 77261.267 | E32: =E8-E30 -> 78240.415 | F32: =F8-F30 -> 79226.054 | G32: =G8-G30 -> 80218.122 | H32: =H8-H30 -> 81216.55 | I32: =I8-I30 -> 82221.264 | ... K32: =K8-K30 -> 84249.225
A33: Capitalization Rate (CAP Rate) | B33: =B32/'STR Calculator'!$B$5 -> 0.10003022 | C33: =C32/'STR Calculator'!$B$5 -> 0.10171822 | D33: =D32/'STR Calculator'!$B$5 -> 0.10301502 | E33: =E32/'STR Calculator'!$B$5 -> 0.10432055 | F33: =F32/'STR Calculator'!$B$5 -> 0.10563474 | G33: =G32/'STR Calculator'!$B$5 -> 0.1069575 | H33: =H32/'STR Calculator'!$B$5 -> 0.10828873 | I33: =I32/'STR Calculator'!$B$5 -> 0.10962835 | ... K33: =K32/'STR Calculator'!$B$5 -> 0.1123323
A35: Key Investment Indicators
A36: Mortgage Payment | B36: =PMT('STR Calculator'!$I$8/12, 'STR Calculator'!$I$9*12,'STR Calculator'!$B$8)*12 -> -59785.396 | C36: =PMT('STR Calculator'!$I$8/12, 'STR Calculator'!$I$9*12,'STR Calculator'!$B$8)*12 -> -59785.396 | D36: =PMT('STR Calculator'!$I$8/12, 'STR Calculator'!$I$9*12,'STR Calculator'!$B$8)*12 -> -59785.396 | E36: =PMT('STR Calculator'!$I$8/12, 'STR Calculator'!$I$9*12,'STR Calculator'!$B$8)*12 -> -59785.396 | F36: =PMT('STR Calculator'!$I$8/12, 'STR Calculator'!$I$9*12,'STR Calculator'!$B$8)*12 -> -59785.396 | G36: =PMT('STR Calculator'!$I$8/12, 'STR Calculator'!$I$9*12,'STR Calculator'!$B$8)*12 -> -59785.396 | H36: =PMT('STR Calculator'!$I$8/12, 'STR Calculator'!$I$9*12,'STR Calculator'!$B$8)*12 -> -59785.396 | I36: =PMT('STR Calculator'!$I$8/12, 'STR Calculator'!$I$9*12,'STR Calculator'!$B$8)*12 -> -59785.396 | ... K36: =PMT('STR Calculator'!$I$8/12, 'STR Calculator'!$I$9*12,'STR Calculator'!$B$8)*12 -> -59785.396
A37: ="HELOC Payment ($"& 'STR Calculator'!I3&")" -> HELOC Payment ($20000) | B37: =-'STR Calculator'!$C$45 -> -1650 | C37: =-'STR Calculator'!$C$45 -> -1650 | D37: =-'STR Calculator'!$C$45 -> -1650 | E37: =-'STR Calculator'!$C$45 -> -1650 | F37: =-'STR Calculator'!$C$45 -> -1650 | G37: =-'STR Calculator'!$C$45 -> -1650 | H37: =-'STR Calculator'!$C$45 -> -1650 | I37: =-'STR Calculator'!$C$45 -> -1650 | ... K37: =-'STR Calculator'!$C$45 -> -1650
A38: PMI if Down Payment less than 20% | B38: =-'STR Calculator'!$C$47 -> -3600 | C38: =-'STR Calculator'!$C$47 -> -3600 | D38: =-'STR Calculator'!$C$47 -> -3600 | E38: =-'STR Calculator'!$C$47 -> -3600 | F38: =-'STR Calculator'!$C$47 -> -3600 | G38: =-'STR Calculator'!$C$47 -> -3600 | H38: =-'STR Calculator'!$C$47 -> -3600 | I38: =-'STR Calculator'!$C$47 -> -3600 | ... K38: =-'STR Calculator'!$C$47 -> -3600
A39: Net Cash Flow | B39: =B32+B36+B37+B38 -> 9987.2708 | C39: =C32+C36+C37+C38 -> 11253.271 | D39: =D32+D36+D37+D38 -> 12225.871 | E39: =E32+E36+E37+E38 -> 13205.019 | F39: =F32+F36+F37+F38 -> 14190.658 | G39: =G32+G36+G37+G38 -> 15182.726 | H39: =H32+H36+H37+H38 -> 16181.154 | I39: =I32+I36+I37+I38 -> 17185.868 | ... K39: =K32+K36+K37+K38 -> 19213.829 | L39: =SUM(B39:K39) -> 146822.46 | M39: FV of all cash flows
A40: Monthly Cash Flow | B40: =B39/12 -> 832.27257 | C40: =C39/12 -> 937.77257 | D40: =D39/12 -> 1018.8226 | E40: =E39/12 -> 1100.4182 | F40: =F39/12 -> 1182.5548 | G40: =G39/12 -> 1265.2271 | H40: =H39/12 -> 1348.4295 | I40: =I39/12 -> 1432.1557 | ... K40: =K39/12 -> 1601.1525
A41: ="Discounted Cash Flow (DCF) @ "&M2&"% return" -> Discounted Cash Flow (DCF) @ 0.08% return | B41: =B39/(1+$M$2)^B1 -> 9247.473 | C41: =C39/(1+$M$2)^C1 -> 9647.8659 | D41: =D39/(1+$M$2)^D1 -> 9705.2904 | E41: =E39/(1+$M$2)^E1 -> 9706.0831 | F41: =F39/(1+$M$2)^F1 -> 9657.9234 | G41: =G39/(1+$M$2)^G1 -> 9567.6926 | H41: =H39/(1+$M$2)^H1 -> 9441.5479 | I41: =I39/(1+$M$2)^I1 -> 9284.99 | ... K41: =K39/(1+$M$2)^K1 -> 8899.7207 | L41: =SUM(B41:K41) -> 94261.512 | M41: PV of all cash flows
A42: Cash on Cash ROI | B42: =B39/(SUM('STR Calculator'!$B$7,'STR Calculator'!$B$6)) -> 0.13316361 | C42: =C39/(SUM('STR Calculator'!$B$7,'STR Calculator'!$B$6)) -> 0.15004361 | D42: =D39/(SUM('STR Calculator'!$B$7,'STR Calculator'!$B$6)) -> 0.16301161 | E42: =E39/(SUM('STR Calculator'!$B$7,'STR Calculator'!$B$6)) -> 0.17606692 | F42: =F39/(SUM('STR Calculator'!$B$7,'STR Calculator'!$B$6)) -> 0.18920877 | G42: =G39/(SUM('STR Calculator'!$B$7,'STR Calculator'!$B$6)) -> 0.20243634 | H42: =H39/(SUM('STR Calculator'!$B$7,'STR Calculator'!$B$6)) -> 0.21574872 | I42: =I39/(SUM('STR Calculator'!$B$7,'STR Calculator'!$B$6)) -> 0.22914491 | ... K42: =K39/(SUM('STR Calculator'!$B$7,'STR Calculator'!$B$6)) -> 0.25618439
A43: Property Appreciation | B43: 0.04 | C43: =$B$43 -> 0.04 | D43: =$B$43 -> 0.04 | E43: =$B$43 -> 0.04 | F43: =$B$43 -> 0.04 | G43: =$B$43 -> 0.04 | H43: =$B$43 -> 0.04 | I43: =$B$43 -> 0.04 | J43: =$B$43 -> 0.04 | K43: =$B$43 -> 0.04
A44: Property Value | B44: ='STR Calculator'!$B$5*(1+'STR 10 Year'!B43) -> 780000 | C44: =B44*(1+'STR 10 Year'!C43) -> 811200 | D44: =C44*(1+'STR 10 Year'!D43) -> 843648 | E44: =D44*(1+'STR 10 Year'!E43) -> 877393.92 | F44: =E44*(1+'STR 10 Year'!F43) -> 912489.68 | G44: =F44*(1+'STR 10 Year'!G43) -> 948989.26 | H44: =G44*(1+'STR 10 Year'!H43) -> 986948.83 | I44: =H44*(1+'STR 10 Year'!I43) -> 1026426.8 | J44: =I44*(1+'STR 10 Year'!J43) -> 1067483.9 | K44: =J44*(1+'STR 10 Year'!K43) -> 1110183.2
A45: Property Appreciation | B45: ='STR Calculator'!$B$5*B43 -> 30000 | C45: =B44*C43 -> 31200 | D45: =C44*D43 -> 32448 | E45: =D44*E43 -> 33745.92 | F45: =E44*F43 -> 35095.757 | G45: =F44*G43 -> 36499.587 | H45: =G44*H43 -> 37959.571 | I45: =H44*I43 -> 39477.953 | J45: =I44*J43 -> 41057.072 | K45: =J44*K43 -> 42699.354
A46: Mortgage Principle Reduction | B46: =VLOOKUP('STR 10 Year'!B1*12,'Amoritization Scenario 10% DP'!$W$8:$AH$367,9) -> 5638.7069 | C46: =VLOOKUP('STR 10 Year'!C1*12,'Amoritization Scenario 10% DP'!$W$8:$AH$367,9)-B46 -> 6106.7168 | D46: =VLOOKUP('STR 10 Year'!D1*12,'Amoritization Scenario 10% DP'!$W$8:$AH$367,9)-SUM(B46:C46) -> 6613.5712 | E46: =VLOOKUP('STR 10 Year'!E1*12,'Amoritization Scenario 10% DP'!$W$8:$AH$367,9)-SUM(B46:D46) -> 7162.4944 | F46: =VLOOKUP('STR 10 Year'!F1*12,'Amoritization Scenario 10% DP'!$W$8:$AH$367,9)-SUM(B46:E46) -> 7756.9779 | G46: =VLOOKUP('STR 10 Year'!G1*12,'Amoritization Scenario 10% DP'!$W$8:$AH$367,9)-SUM(B46:F46) -> 8400.8032 | H46: =VLOOKUP('STR 10 Year'!H1*12,'Amoritization Scenario 10% DP'!$W$8:$AH$367,9)-SUM(B46:G46) -> 9098.0658 | I46: =VLOOKUP('STR 10 Year'!I1*12,'Amoritization Scenario 10% DP'!$W$8:$AH$367,9)-SUM(B46:H46) -> 9853.2007 | J46: =VLOOKUP('STR 10 Year'!J1*12,'Amoritization Scenario 10% DP'!$W$8:$AH$367,9)-SUM(B46:I46) -> 10671.012 | K46: =VLOOKUP('STR 10 Year'!K1*12,'Amoritization Scenario 10% DP'!$W$8:$AH$367,9)-SUM(B46:J46) -> 11556.7 | L46: =SUM(B46:K46) -> 82858.249 | M46: loan paid down
A47: Net Tax Savings (25% Bracket) | B47: =B39*0.25 -> 2496.8177 | C47: =C39*0.25 -> 2813.3177 | D47: =D39*0.25 -> 3056.4677 | E47: =E39*0.25 -> 3301.2547 | F47: =F39*0.25 -> 3547.6645 | G47: =G39*0.25 -> 3795.6814 | H47: =H39*0.25 -> 4045.2885 | I47: =I39*0.25 -> 4296.4671 | ... K47: =K39*0.25 -> 4803.4574
A48: Tax ROI | B48: =B47/SUM('STR Calculator'!$B$6:$B$7) -> 0.033290903 | C48: =C47/SUM('STR Calculator'!$B$6:$B$7) -> 0.037510903 | D48: =D47/SUM('STR Calculator'!$B$6:$B$7) -> 0.040752903 | E48: =E47/SUM('STR Calculator'!$B$6:$B$7) -> 0.04401673 | F48: =F47/SUM('STR Calculator'!$B$6:$B$7) -> 0.047302193 | G48: =G47/SUM('STR Calculator'!$B$6:$B$7) -> 0.050609086 | H48: =H47/SUM('STR Calculator'!$B$6:$B$7) -> 0.05393718 | I48: =I47/SUM('STR Calculator'!$B$6:$B$7) -> 0.057286228 | ... K48: =K47/SUM('STR Calculator'!$B$6:$B$7) -> 0.064046098
A49: Total Return (Not counting appreciation) | B49: =SUM(B39,B46,B47) -> 18122.795 | C49: =SUM(C39,C46,C47) -> 20173.305 | D49: =SUM(D39,D46,D47) -> 21895.91 | E49: =SUM(E39,E46,E47) -> 23668.768 | F49: =SUM(F39,F46,F47) -> 25495.3 | G49: =SUM(G39,G46,G47) -> 27379.21 | H49: =SUM(H39,H46,H47) -> 29324.508 | I49: =SUM(I39,I46,I47) -> 31335.536 | ... K49: =SUM(K39,K46,K47) -> 35573.987
A50: Total ROI | B50: =B49/SUM('STR Calculator'!$B$6:$B$7) -> 0.24163727 | C50: =C49/SUM('STR Calculator'!$B$6:$B$7) -> 0.2689774 | D50: =D49/SUM('STR Calculator'!$B$6:$B$7) -> 0.29194546 | E50: =E49/SUM('STR Calculator'!$B$6:$B$7) -> 0.31558357 | F50: =F49/SUM('STR Calculator'!$B$6:$B$7) -> 0.33993734 | G50: =G49/SUM('STR Calculator'!$B$6:$B$7) -> 0.36505614 | H50: =H49/SUM('STR Calculator'!$B$6:$B$7) -> 0.39099344 | I50: =I49/SUM('STR Calculator'!$B$6:$B$7) -> 0.41780715 | ... K50: =K49/SUM('STR Calculator'!$B$6:$B$7) -> 0.47431983 | L50: =SUM(B50:K50)/K1 -> 0.35518176 | M50: AAR
L51: =('STR 10 Year'!K44/'STR Calculator'!B5)^(1/'STR 10 Year'!K1)-1 -> 0.04 | M51: CAGR
A53: Total Property Equity (not counting appreciation) | B53: =SUM('STR Calculator'!$B$7,'STR 10 Year'!B46) -> 80638.707 | C53: =B53+C46 -> 86745.424 | D53: =C53+D46 -> 93358.995 | E53: =D53+E46 -> 100521.49 | F53: =E53+F46 -> 108278.47 | G53: =F53+G46 -> 116679.27 | H53: =G53+H46 -> 125777.34 | I53: =H53+I46 -> 135630.54 | J53: =I53+J46 -> 146301.55 | K53: =J53+K46 -> 157858.25
K54: =(K53-B53)/B53 -> 0.95759896 | L54: =(K53/B53)^(1/K1)-1 -> 0.069479274 | M54: CAGR
A55: Total Property Equity (counting appreciation) | B55: =SUM('STR Calculator'!$B$7,'STR 10 Year'!B46,B45) -> 110638.71 | C55: =B55+C46+C45 -> 147945.42 | D55: =C55+D46+D45 -> 187006.99 | E55: =D55+E46+E45 -> 227915.41 | F55: =E55+F46+F45 -> 270768.14 | G55: =F55+G46+G45 -> 315668.53 | H55: =G55+H46+H45 -> 362726.17 | I55: =H55+I46+I45 -> 412057.32 | J55: =I55+J46+J45 -> 463785.41 | K55: =J55+K46+K45 -> 518041.46
K56: =(K55-B55)/B55 -> 3.6822805 | L56: =(K55/B55)^(1/K1)-1 -> 0.16693252 | M56: CAGR w/ Appreciation

Sheet STR 7yr IRR Financing
A1: ='STR Calculator'!A2 &" - FINANCING CALCULATIONS" -> 915 Sanctuary Shores Way - 3bd / 4bath - 3240 sqft - FINANCING CALCULATIONS
B4: Year 1 | C4: Year 2 | D4: Year 3 | E4: Year 4 | F4: Year 5 | G4: Year 6 | H4: Year 7
A5: Maintenance | B5: 0.01 | C5: 0.01 | D5: 0.01 | E5: 0.01 | F5: 0.01 | G5: 0.01 | H5: 0.01
A6: Property Appreciation | B6: 0.02 | C6: 0.02 | D6: 0.02 | E6: 0.02 | F6: 0.02 | G6: 0.02 | H6: 0.02
A7: Rental Appreciation | B7: 0.01 | C7: 0.01 | D7: 0.01 | E7: 0.01 | F7: 0.01 | G7: 0.01 | H7: 0.01
A8: Tax/Insurance/HOA Appreciation | B8: 0.015 | C8: 0.015 | D8: 0.015 | E8: 0.015 | F8: 0.015 | G8: 0.015 | H8: 0.015
A9: Vacancy | B9: =1-'STR Calculator'!$B$16 -> 0 | C9: =1-'STR Calculator'!$B$16 -> 0 | D9: =1-'STR Calculator'!$B$16 -> 0 | E9: =1-'STR Calculator'!$B$16 -> 0 | F9: =1-'STR Calculator'!$B$16 -> 0 | G9: =1-'STR Calculator'!$B$16 -> 0 | H9: =1-'STR Calculator'!$B$16 -> 0
B11: Year 1 | C11: Year 2 | D11: Year 3 | E11: Year 4 | F11: Year 5 | G11: Year 6 | H11: Year 7
A12: Revenues
A13: Rental Income | B13: ='STR Calculator'!D15 -> 109800 | C13: =SUM(B$13+(C$7*B$13)) -> 110898 | D13: =SUM(C$13+(D$7*C$13)) -> 112006.98 | E13: =SUM(D$13+(E$7*D$13)) -> 113127.05 | F13: =SUM(E$13+(F$7*E$13)) -> 114258.32 | G13: =SUM(F$13+(G$7*F$13)) -> 115400.9 | H13: =SUM(G$13+(H$7*G$13)) -> 116554.91
A14: Monthly Revenue | B14: =B13/12 -> 9150 | C14: =C13/12 -> 9241.5 | D14: =D13/12 -> 9333.915 | E14: =E13/12 -> 9427.2541 | F14: =F13/12 -> 9521.5267 | G14: =G13/12 -> 9616.742 | H14: =H13/12 -> 9712.9094
A15: Vacancy Rate | B15: ='STR Calculator'!D16 -> 0 | C15: =-(C13*C9) -> 0 | D15: =-(D13*D9) -> 0 | E15: =-(E13*E9) -> 0 | F15: =-(F13*F9) -> 0 | G15: =-(G13*G9) -> 0 | H15: =-(H13*H9) -> 0
A16: Net Revenue | B16: =SUM(B13,B15) -> 109800 | C16: =SUM(C13,C15) -> 110898 | D16: =SUM(D13,D15) -> 112006.98 | E16: =SUM(E13,E15) -> 113127.05 | F16: =SUM(F13,F15) -> 114258.32 | G16: =SUM(G13,G15) -> 115400.9 | H16: =SUM(H13,H15) -> 116554.91
A18: Expenses
A19: Management Fees | B19: 0 | C19: 0 | D19: 0 | E19: 0 | F19: 0 | G19: 0 | H19: 0
A20: Subscriptions | B20: ='STR Calculator'!$C$24 -> 600 | C20: ='STR Calculator'!$C$24 -> 600 | D20: ='STR Calculator'!$C$24 -> 600 | E20: ='STR Calculator'!$C$24 -> 600 | F20: ='STR Calculator'!$C$24 -> 600 | G20: ='STR Calculator'!$C$24 -> 600 | H20: ='STR Calculator'!$C$24 -> 600
A21: Property Taxes | B21: ='STR Calculator'!$C$26 -> 2400 | C21: =B$21+(B$21*C$8) -> 2436 | D21: =C$21+(C$21*D$8) -> 2472.54 | E21: =D$21+(D$21*E$8) -> 2509.6281 | F21: =E$21+(E$21*F$8) -> 2547.2725 | G21: =F$21+(F$21*G$8) -> 2585.4816 | H21: =G$21+(G$21*H$8) -> 2624.2638
A22: Insurance | B22: =('STR Calculator'!$C$27) -> 2400 | C22: =('STR Calculator'!$B$5+B48)*($B$22/'STR Calculator'!$B$5) -> 2448 | D22: =('STR Calculator'!$B$5+C48)*($B$22/'STR Calculator'!$B$5) -> 2448.96 | E22: =('STR Calculator'!$B$5+D48)*($B$22/'STR Calculator'!$B$5) -> 2448.9792 | F22: =('STR Calculator'!$B$5+E48)*($B$22/'STR Calculator'!$B$5) -> 2448.9796 | G22: =('STR Calculator'!$B$5+F48)*($B$22/'STR Calculator'!$B$5) -> 2448.9796 | H22: =('STR Calculator'!$B$5+G48)*($B$22/'STR Calculator'!$B$5) -> 2448.9796
A23: Cleaners/Handyman | B23: =SUM('STR Calculator'!$C$28:$C$29) -> 21000 | C23: =SUM('STR Calculator'!$C$28:$C$29) -> 21000 | D23: =SUM('STR Calculator'!$C$28:$C$29) -> 21000 | E23: =SUM('STR Calculator'!$C$28:$C$29) -> 21000 | F23: =SUM('STR Calculator'!$C$28:$C$29) -> 21000 | G23: =SUM('STR Calculator'!$C$28:$C$29) -> 21000 | H23: =SUM('STR Calculator'!$C$28:$C$29) -> 21000
A24: Electricity | B24: ='STR Calculator'!$C$31 -> 3000 | C24: ='STR Calculator'!$C$31 -> 3000 | D24: ='STR Calculator'!$C$31 -> 3000 | E24: ='STR Calculator'!$C$31 -> 3000 | F24: ='STR Calculator'!$C$31 -> 3000 | G24: ='STR Calculator'!$C$31 -> 3000 | H24: ='STR Calculator'!$C$31 -> 3000
A25: Natural Gas | B25: ='STR Calculator'!$C$32 -> 1333.3333 | C25: ='STR Calculator'!$C$32 -> 1333.3333 | D25: ='STR Calculator'!$C$32 -> 1333.3333 | E25: ='STR Calculator'!$C$32 -> 1333.3333 | F25: ='STR Calculator'!$C$32 -> 1333.3333 | G25: ='STR Calculator'!$C$32 -> 1333.3333 | H25: ='STR Calculator'!$C$32 -> 1333.3333
A26: WIFI/Cable | B26: ='STR Calculator'!$C$33 -> 1800 | C26: ='STR Calculator'!$C$33 -> 1800 | D26: ='STR Calculator'!$C$33 -> 1800 | E26: ='STR Calculator'!$C$33 -> 1800 | F26: ='STR Calculator'!$C$33 -> 1800 | G26: ='STR Calculator'!$C$33 -> 1800 | H26: ='STR Calculator'!$C$33 -> 1800
A27: Water/Sewer | B27: ='STR Calculator'!$C$35 -> 0 | C27: ='STR Calculator'!$C$35 -> 0 | D27: ='STR Calculator'!$C$35 -> 0 | E27: ='STR Calculator'!$C$35 -> 0 | F27: ='STR Calculator'!$C$35 -> 0 | G27: ='STR Calculator'!$C$35 -> 0 | H27: ='STR Calculator'!$C$35 -> 0
A28: Pool Service | B28: ='STR Calculator'!$C$34 -> 0 | C28: ='STR Calculator'!$C$34 -> 0 | D28: ='STR Calculator'!$C$34 -> 0 | E28: ='STR Calculator'!$C$34 -> 0 | F28: ='STR Calculator'!$C$34 -> 0 | G28: ='STR Calculator'!$C$34 -> 0 | H28: ='STR Calculator'!$C$34 -> 0
A29: HOA | B29: ='STR Calculator'!$C$30 -> 1200 | C29: =B29+(B29*C8) -> 1218 | D29: =C29+(C29*D8) -> 1236.27 | E29: =D29+(D29*E8) -> 1254.814 | F29: =E29+(E29*F8) -> 1273.6363 | G29: =F29+(F29*G8) -> 1292.7408 | H29: =G29+(G29*H8) -> 1312.1319
A30: Maintenance & Repairs | B30: ='STR Calculator'!$C$36 -> 0 | C30: ='STR Calculator'!$B$5*C5 -> 7500 | D30: ='STR Calculator'!$B$5*D5 -> 7500 | E30: ='STR Calculator'!$B$5*E5 -> 7500 | F30: ='STR Calculator'!$B$5*F5 -> 7500 | G30: ='STR Calculator'!$B$5*G5 -> 7500 | H30: ='STR Calculator'!$B$5*H5 -> 7500
A31: Capex | B31: ='STR Calculator'!$C$37 -> 0 | C31: ='STR Calculator'!$C$37 -> 0 | D31: ='STR Calculator'!$C$37 -> 0 | E31: ='STR Calculator'!$C$37 -> 0 | F31: ='STR Calculator'!$C$37 -> 0 | G31: ='STR Calculator'!$C$37 -> 0 | H31: ='STR Calculator'!$C$37 -> 0
A32: City Permit | B32: ='STR Calculator'!C39 -> 300 | C32: 0 | D32: 0 | E32: 0 | F32: 0 | G32: 0 | H32: 0
A33: Incidentals (Coffee, etc) | B33: ='STR Calculator'!$C$40 -> 300 | C33: ='STR Calculator'!$C$40 -> 300 | D33: ='STR Calculator'!$C$40 -> 300 | E33: ='STR Calculator'!$C$40 -> 300 | F33: ='STR Calculator'!$C$40 -> 300 | G33: ='STR Calculator'!$C$40 -> 300 | H33: ='STR Calculator'!$C$40 -> 300
A34: Umbrella Insurance | B34: ='STR Calculator'!$C$41 -> 444 | C34: ='STR Calculator'!$C$41 -> 444 | D34: ='STR Calculator'!$C$41 -> 444 | E34: ='STR Calculator'!$C$41 -> 444 | F34: ='STR Calculator'!$C$41 -> 444 | G34: ='STR Calculator'!$C$41 -> 444 | H34: ='STR Calculator'!$C$41 -> 444
A35: Total Expenses | B35: =SUM(B20:B34) -> 34777.333 | C35: =SUM(C20:C34) -> 42079.333 | D35: =SUM(D20:D34) -> 42135.103 | E35: =SUM(E20:E34) -> 42190.755 | F35: =SUM(F20:F34) -> 42247.222 | G35: =SUM(G20:G34) -> 42304.535 | H35: =SUM(H20:H34) -> 42362.709
A37: Net Operating Income (NOI) | B37: =SUM(B16-B35) -> 75022.667 | C37: =SUM(C16-C35) -> 68818.667 | D37: =SUM(D16-D35) -> 69871.877 | E37: =SUM(E16-E35) -> 70936.295 | F37: =SUM(F16-F35) -> 72011.099 | G37: =SUM(G16-G35) -> 73096.368 | H37: =SUM(H16-H35) -> 74192.204
A39: Cash Flow
A40: NOI (Cash Available) | B40: =B37 -> 75022.667 | C40: =C37 -> 68818.667 | D40: =D37 -> 69871.877 | E40: =E37 -> 70936.295 | F40: =F37 -> 72011.099 | G40: =G37 -> 73096.368 | H40: =H37 -> 74192.204
A41: Conventional Mortgage | B41: ='STR Calculator'!$C$46 -> 59785.396 | C41: ='STR Calculator'!$C$46 -> 59785.396 | D41: ='STR Calculator'!$C$46 -> 59785.396 | E41: ='STR Calculator'!$C$46 -> 59785.396 | F41: ='STR Calculator'!$C$46 -> 59785.396 | G41: ='STR Calculator'!$C$46 -> 59785.396 | H41: ='STR Calculator'!$C$46 -> 59785.396
A42: HELOC Mortgage | B42: ='STR Calculator'!$C$45 -> 1650 | C42: ='STR Calculator'!$C$45 -> 1650 | D42: ='STR Calculator'!$C$45 -> 1650 | E42: ='STR Calculator'!$C$45 -> 1650 | F42: ='STR Calculator'!$C$45 -> 1650 | G42: ='STR Calculator'!$C$45 -> 1650 | H42: ='STR Calculator'!$C$45 -> 1650
A43: PMI if Down Payment less than 20% | B43: ='STR Calculator'!$C$47 -> 3600 | C43: ='STR Calculator'!$C$47 -> 3600 | D43: ='STR Calculator'!$C$47 -> 3600 | E43: ='STR Calculator'!$C$47 -> 3600 | F43: ='STR Calculator'!$C$47 -> 3600 | G43: ='STR Calculator'!$C$47 -> 3600 | H43: ='STR Calculator'!$C$47 -> 3600
A44: Total Cash Flow | B44: =SUM(B40-B41-B42-B43) -> 9987.2708 | C44: =SUM(C40-C41-C42-C43) -> 3783.2708 | D44: =SUM(D40-D41-D42-D43) -> 4836.4808 | E44: =SUM(E40-E41-E42-E43) -> 5900.8993 | F44: =SUM(F40-F41-F42-F43) -> 6975.7027 | G44: =SUM(G40-G41-G42-G43) -> 8060.9723 | H44: =SUM(H40-H41-H42-H43) -> 9156.808
A45: Monthly Cash Flow | B45: =B44/12 -> 832.27257 | C45: =C44/12 -> 315.27257 | D45: =D44/12 -> 403.04007 | E45: =E44/12 -> 491.7416 | F45: =F44/12 -> 581.30856 | G45: =G44/12 -> 671.74769 | H45: =H44/12 -> 763.06733
A46: DSCR | B46: =B40/SUM(B41:B43) -> 1.1535667 | C46: =C40/SUM(C41:C43) -> 1.0581725 | D46: =D40/SUM(D41:D43) -> 1.0743669 | E46: =E40/SUM(E41:E43) -> 1.0907337 | F46: =F40/SUM(F41:F43) -> 1.1072601 | G46: =G40/SUM(G41:G43) -> 1.1239475 | H46: =H40/SUM(H41:H43) -> 1.1407973
A47: Equity Accrued | B47: =-CUMPRINC('STR Calculator'!$I$8/12,'STR Calculator'!$I$9*12,'STR Calculator'!$B$8,1,12,0) -> 5569.7161 | C47: =-CUMPRINC('STR Calculator'!$I$8/12,'STR Calculator'!$I$9*12,'STR Calculator'!$B$8,13,24,0) -> 6035.7159 | D47: =-CUMPRINC('STR Calculator'!$I$8/12,'STR Calculator'!$I$9*12,'STR Calculator'!$B$8,25,36,0) -> 6540.7043 | E47: =-CUMPRINC('STR Calculator'!$I$8/12,'STR Calculator'!$I$9*12,'STR Calculator'!$B$8,37,48,0) -> 7087.9436 | F47: =-CUMPRINC('STR Calculator'!$I$8/12,'STR Calculator'!$I$9*12,'STR Calculator'!$B$8,49,60,0) -> 7680.9685 | G47: =-CUMPRINC('STR Calculator'!$I$8/12,'STR Calculator'!$I$9*12,'STR Calculator'!$B$8,61,72,0) -> 8323.6098 | H47: =-CUMPRINC('STR Calculator'!$I$8/12,'STR Calculator'!$I$9*12,'STR Calculator'!$B$8,73,84,0) -> 9020.0188
A48: Appreciation | B48: =SUM(B6*'STR Calculator'!$B$5) -> 15000 | C48: =(SUM(B48)+'STR Calculator'!$B$5)*C$6 -> 15300 | D48: =(SUM(C48)+'STR Calculator'!$B$5)*D$6 -> 15306 | E48: =(SUM(D48)+'STR Calculator'!$B$5)*E$6 -> 15306.12 | F48: =(SUM(E48)+'STR Calculator'!$B$5)*F$6 -> 15306.122 | G48: =(SUM(F48)+'STR Calculator'!$B$5)*G$6 -> 15306.122 | H48: =(SUM(G48)+'STR Calculator'!$B$5)*H$6 -> 15306.122
A49: Total Return w/o Appreciation | B49: =SUM(B47+B44) -> 15556.987 | C49: =SUM(C47+C44) -> 9818.9867 | D49: =SUM(D47+D44) -> 11377.185 | E49: =SUM(E47+E44) -> 12988.843 | F49: =SUM(F47+F44) -> 14656.671 | G49: =SUM(G47+G44) -> 16384.582 | H49: =SUM(H47+H44) -> 18176.827
A50: ROI w/o appreciation | B50: =B49/SUM('STR Calculator'!$B$6:$B$7) -> 0.20742649 | C50: =C49/SUM('STR Calculator'!$B$6:$B$7) -> 0.13091982 | D50: =D49/SUM('STR Calculator'!$B$6:$B$7) -> 0.1516958 | E50: =E49/SUM('STR Calculator'!$B$6:$B$7) -> 0.17318457 | F50: =F49/SUM('STR Calculator'!$B$6:$B$7) -> 0.19542228 | G50: =G49/SUM('STR Calculator'!$B$6:$B$7) -> 0.21846109 | H50: =H49/SUM('STR Calculator'!$B$6:$B$7) -> 0.24235769
A51: Total Return w/ Appreciation | B51: =SUM(B44+B47+B48) -> 30556.987 | C51: =SUM(C44+C47+C48) -> 25118.987 | D51: =SUM(D44+D47+D48) -> 26683.185 | E51: =SUM(E44+E47+E48) -> 28294.963 | F51: =SUM(F44+F47+F48) -> 29962.794 | G51: =SUM(G44+G47+G48) -> 31690.705 | H51: =SUM(H44+H47+H48) -> 33482.949
A52: Total ROI | B52: =B51/SUM('STR Calculator'!$B$6:$B$7) -> 0.40742649 | C52: =C51/SUM('STR Calculator'!$B$6:$B$7) -> 0.33491982 | D52: =D51/SUM('STR Calculator'!$B$6:$B$7) -> 0.3557758 | E52: =E51/SUM('STR Calculator'!$B$6:$B$7) -> 0.37726617 | F52: =F51/SUM('STR Calculator'!$B$6:$B$7) -> 0.39950391 | G52: =G51/SUM('STR Calculator'!$B$6:$B$7) -> 0.42254273 | H52: =H51/SUM('STR Calculator'!$B$6:$B$7) -> 0.44643932
A53: Average ROI | G53: =AVERAGE(B50:H50) -> 0.18849539
A54: Estimated Value at Year 7 | G54: ='STR Calculator'!B5+(SUM('STR 7yr IRR Financing'!B48:H48)) -> 856830.49
A55: Loan Paid Down over 7 Years | G55: =SUM(B47:H47) -> 50258.677
A56: Total returns are based on calculations of external data and is subject to change. Estimated returns are estimated, and may not factor in all scenarios or costs. REI Nation, LLC and Premier Property Management Group, LLC have offered this estimator of returns in good faith. We realize that there are alternate methods to calculate return, and that some assumptions may not be applicable for your calculations. Data provided for the calculation is the user’s responsibility. We do not make any representations or warranties of any kind on the information provided. We also disclaim any liability or responsibility for the accuracy, correctness, or completeness of any information provided. *All calculations include estimated maintenance, estimated vacancy, estimated property management fees, estimated equity accrual, estimated property taxes, estimated insurance and estimated appreciation.

Sheet Amoritization Scenario 10% DP
A1: If deciding between different Down Payment % and Interest Rates, compare Cumulative Interest Payment over duration to recoup additional Down Payment Lump Sum, to see which is better. NPV / PV/FV money calculation
C3: sqft | J3: Interest | K3: ='Interest Rate Comparison'!B3 -> 0.0825 | N3: =K3/12 -> 0.006875 | O3: r | W3: Interest | X3: ='Interest Rate Comparison'!B4 -> 0.08 | AA3: =X3/12 -> 0.0066666667 | AB3: r | AJ3: Interest | AK3: ='Interest Rate Comparison'!B5 -> 0.0775 | AN3: =AK3/12 -> 0.0064583333 | AO3: r | AW3: Interest | AX3: ='Interest Rate Comparison'!B6 -> 0.075 | BA3: =AX3/12 -> 0.00625 | BB3: r | BJ3: Interest | BK3: ='Interest Rate Comparison'!B7 -> 0.0725 | BN3: =BK3/12 -> 0.0060416667 | BO3: r | BW3: Interest | BX3: ='Interest Rate Comparison'!B8 -> 0.07 | CA3: =BX3/12 -> 0.0058333333 | CB3: r
C4: $/sqft Market Estimate | J4: Term | K4: =$L$4*12 -> 360 | L4: ='STR Calculator'!I9 -> 30 | M4: years | N4: =(1+N3)^K4 -> 11.781506 | O4: (1+r)^n | W4: Term | X4: =$L$4*12 -> 360 | Y4: 30 | Z4: years | AA4: =(1+AA3)^X4 -> 10.93573 | AB4: (1+r)^n | AJ4: Term | AK4: =$L$4*12 -> 360 | AL4: 30 | AM4: years | AN4: =(1+AN3)^AK4 -> 10.150514 | AO4: (1+r)^n | AW4: Term | AX4: =$L$4*12 -> 360 | AY4: 30 | AZ4: years | BA4: =(1+BA3)^AX4 -> 9.4215339 | BB4: (1+r)^n | BJ4: Term | BK4: =$L$4*12 -> 360 | BL4: 30 | BM4: years | BN4: =(1+BN3)^BK4 -> 8.744772 | BO4: (1+r)^n | BW4: Term | BX4: =$L$4*12 -> 360 | BY4: 30 | BZ4: years | CA4: =(1+CA3)^BX4 -> 8.1164975 | CB4: (1+r)^n
A5: Original Purchase Price | B5: ='STR Calculator'!B5 -> 750000 | C5: =B5/B3 -> #DIV/0! | D5: sqft | J5: Monthly Payment | W5: Monthly Payment | AJ5: Monthly Payment | AW5: Monthly Payment | BJ5: Monthly Payment | BW5: Monthly Payment
A6: Down Payment | B6: 0.1
A7: Current Loan Balance | B7: =B5-(B5*B6) -> 675000 | C7: as of 11/13/22 | J7: paymentNumber | K7: paymentDate | L7: startingBalance | M7: Monthly Payment | N7: principalPayment | O7: Principle Pay Down | P7: interestPayment | Q7: Interest Percent | R7: cumulativePrincipal | S7: cumulativeInterest | T7: endingBalance | U7: Total Paid End of Loan | W7: paymentNumber | X7: paymentDate | Y7: startingBalance | Z7: Monthly Payment | AA7: principalPayment | AB7: Principle Pay Down | AC7: interestPayment | AD7: Interest Percent | AE7: cumulativePrincipal | AF7: cumulativeInterest | AG7: endingBalance | AH7: Total Paid End of Loan | AJ7: paymentNumber | AK7: paymentDate | AL7: startingBalance | AM7: Monthly Payment | AN7: principalPayment | AO7: Principle Pay Down | AP7: interestPayment | AQ7: Interest Percent | AR7: cumulativePrincipal | AS7: cumulativeInterest | AT7: endingBalance | AU7: Total Paid End of Loan | AW7: paymentNumber | AX7: paymentDate | AY7: startingBalance | AZ7: Monthly Payment | BA7: principalPayment | BB7: Principle Pay Down | BC7: interestPayment | BD7: Interest Percent | BE7: cumulativePrincipal | BF7: cumulativeInterest | BG7: endingBalance | BH7: Total Paid End of Loan | BJ7: paymentNumber | BK7: paymentDate | BL7: startingBalance | BM7: Monthly Payment | BN7: principalPayment | BO7: Principle Pay Down | BP7: interestPayment | BQ7: Interest Percent | BR7: cumulativePrincipal | BS7: cumulativeInterest | BT7: endingBalance | BU7: Total Paid End of Loan | BW7: paymentNumber | BX7: paymentDate | BY7: startingBalance | BZ7: Monthly Payment | CA7: principalPayment | CB7: Principle Pay Down | CC7: interestPayment | CD7: Interest Percent | CE7: cumulativePrincipal | CF7: cumulativeInterest | CG7: endingBalance | CH7: Total Paid End of Loan
A8: Current Equity | B8: =B5-B7 -> 75000 | J8: 1 | K8: 44866 | L8: ='Amoritization Scenario 10% DP'!$B$7 -> 675000 | M8: =$L$8/((($N$4)-1)/($N$3*$N$4)) -> 5071.0496 | N8: =M8-P8 -> 430.42458 | O8: =(N8/L8)*12 -> 0.0076519925 | P8: =L8*($K$3/12) -> 4640.625 | Q8: =(P8/L8)*12 -> 0.0825 | R8: =N8 -> 430.42458 | S8: =P8 -> 4640.625 | T8: =L8-N8 -> 674569.58 | U8: =R8+S8 -> 5071.0496 | W8: 1 | X8: 44866 | Y8: ='Amoritization Scenario 10% DP'!$B$7 -> 675000 | Z8: =$Y$8/((($AA$4)-1)/($AA$3*$AA$4)) -> 4952.9109 | AA8: =Z8-AC8 -> 452.91087 | AB8: =(AA8/Y8)*12 -> 0.0080517489 | AC8: =Y8*($X$3/12) -> 4500 | AD8: =(AC8/Y8)*12 -> 0.08 | AE8: =AA8 -> 452.91087 | AF8: =AC8 -> 4500 | AG8: =Y8-AA8 -> 674547.09 | AH8: =AE8+AF8 -> 4952.9109 | AJ8: 1 | AK8: 44866 | AL8: ='Amoritization Scenario 10% DP'!$B$7 -> 675000 | AM8: =$AL$8/((($AN$4)-1)/($AN$3*$AN$4)) -> 4835.7827 | AN8: =AM8-AP8 -> 476.40766 | AO8: =(AN8/AL8)*12 -> 0.0084694695 | AP8: =AL8*($AK$3/12) -> 4359.375 | AQ8: =(AP8/AL8)*12 -> 0.0775 | AR8: =AN8 -> 476.40766 | AS8: =AP8 -> 4359.375 | AT8: =AL8-AN8 -> 674523.59 | AU8: =AR8+AS8 -> 4835.7827 | AW8: 1 | AX8: 44866 | AY8: ='Amoritization Scenario 10% DP'!$B$7 -> 675000 | AZ8: =$AY$8/((($BA$4)-1)/($BA$3*$BA$4)) -> 4719.6979 | BA8: =AZ8-BC8 -> 500.94793 | BB8: =(BA8/AY8)*12 -> 0.008905741 | BC8: =AY8*($AX$3/12) -> 4218.75 | BD8: =(BC8/AY8)*12 -> 0.075 | BE8: =BA8 -> 500.94793 | BF8: =BC8 -> 4218.75 | BG8: =AY8-BA8 -> 674499.05 | BH8: =BE8+BF8 -> 4719.6979 | BJ8: 1 | BK8: 44866 | BL8: ='Amoritization Scenario 10% DP'!$B$7 -> 675000 | BM8: =$BL$8/((($BN$4)-1)/($BN$3*$BN$4)) -> 4604.6899 | BN8: =BM8-BP8 -> 526.56489 | BO8: =(BN8/BL8)*12 -> 0.0093611536 | BP8: =BL8*($BK$3/12) -> 4078.125 | BQ8: =(BP8/BL8)*12 -> 0.0725 | BR8: =BN8 -> 526.56489 | BS8: =BP8 -> 4078.125 | BT8: =BL8-BN8 -> 674473.44 | BU8: =BR8+BS8 -> 4604.6899 | BW8: 1 | BX8: 44866 | BY8: ='Amoritization Scenario 10% DP'!$B$7 -> 675000 | BZ8: =$BY$8/((($CA$4)-1)/($CA$3*$CA$4)) -> 4490.7918 | CA8: =BZ8-CC8 -> 553.29184 | CB8: =(CA8/BY8)*12 -> 0.0098362994 | CC8: =BY8*($BX$3/12) -> 3937.5 | CD8: =(CC8/BY8)*12 -> 0.07 | CE8: =CA8 -> 553.29184 | CF8: =CC8 -> 3937.5 | CG8: =BY8-CA8 -> 674446.71 | CH8: =CE8+CF8 -> 4490.7918
J9: 2 | K9: 44896 | L9: =T8 -> 674569.58 | M9: =$L$8/((($N$4)-1)/($N$3*$N$4)) -> 5071.0496 | N9: =M9-P9 -> 433.38375 | O9: =(N9/L9)*12 -> 0.007709516 | P9: =L9*($K$3/12) -> 4637.6658 | Q9: =(P9/L9)*12 -> 0.0825 | R9: =R8+N9 -> 863.80832 | S9: =S8+P9 -> 9278.2908 | T9: =L9-N9 -> 674136.19 | U9: =R9+S9 -> 10142.099 | W9: 2 | X9: 44896 | Y9: =AG8 -> 674547.09 | Z9: =Z8 -> 4952.9109 | AA9: =Z9-AC9 -> 455.93028 | AB9: =(AA9/Y9)*12 -> 0.0081108694 | AC9: =Y9*($X$3/12) -> 4496.9806 | AD9: =(AC9/Y9)*12 -> 0.08 | AE9: =AE8+AA9 -> 908.84115 | AF9: =AF8+AC9 -> 8996.9806 | AG9: =Y9-AA9 -> 674091.16 | AH9: =AE9+AF9 -> 9905.8217 | AJ9: 2 | AK9: 44896 | AL9: =AT8 -> 674523.59 | AM9: =AM8 -> 4835.7827 | AN9: =AM9-AP9 -> 479.48446 | AO9: =(AN9/AL9)*12 -> 0.0085301886 | AP9: =AL9*($AK$3/12) -> 4356.2982 | AQ9: =(AP9/AL9)*12 -> 0.0775 | AR9: =AR8+AN9 -> 955.89211 | AS9: =AS8+AP9 -> 8715.6732 | AT9: =AL9-AN9 -> 674044.11 | AU9: =AR9+AS9 -> 9671.5653 | AW9: 2 | AX9: 44896 | AY9: =BG8 -> 674499.05 | AZ9: =AZ8 -> 4719.6979 | BA9: =AZ9-BC9 -> 504.07886 | BB9: =(BA9/AY9)*12 -> 0.0089680575 | BC9: =AY9*($AX$3/12) -> 4215.6191 | BD9: =(BC9/AY9)*12 -> 0.075 | BE9: =BE8+BA9 -> 1005.0268 | BF9: =BF8+BC9 -> 8434.3691 | BG9: =AY9-BA9 -> 673994.97 | BH9: =BE9+BF9 -> 9439.3959 | BJ9: 2 | BK9: 44896 | BL9: =BT8 -> 674473.44 | BM9: =BM8 -> 4604.6899 | BN9: =BM9-BP9 -> 529.74622 | BO9: =(BN9/BL9)*12 -> 0.009425063 | BP9: =BL9*($BK$3/12) -> 4074.9437 | BQ9: =(BP9/BL9)*12 -> 0.0725 | BR9: =BR8+BN9 -> 1056.3111 | BS9: =BS8+BP9 -> 8153.0687 | BT9: =BL9-BN9 -> 673943.69 | BU9: =BR9+BS9 -> 9209.3798 | BW9: 2 | BX9: 44896 | BY9: =CG8 -> 674446.71 | BZ9: =BZ8 -> 4490.7918 | CA9: =BZ9-CC9 -> 556.51938 | CB9: =(CA9/BY9)*12 -> 0.0099017943 | CC9: =BY9*($BX$3/12) -> 3934.2725 | CD9: =(CC9/BY9)*12 -> 0.07 | CE9: =CE8+CA9 -> 1109.8112 | CF9: =CF8+CC9 -> 7871.7725 | CG9: =BY9-CA9 -> 673890.19 | CH9: =CE9+CF9 -> 8981.5837
A10: Year | B10: ="Cum Interest @ "&K3&"%" -> Cum Interest @ 0.0825% | C10: ="Cum Interest @ "&X3&"%" -> Cum Interest @ 0.08% | D10: ="Cum Interest @ "&AK3&"%" -> Cum Interest @ 0.0775% | E10: ="Cum Interest @ "&AX3&"%" -> Cum Interest @ 0.075% | F10: ="Cum Interest @ "&BK3&"%" -> Cum Interest @ 0.0725% | G10: ="Cum Interest @ "&BX3&"%" -> Cum Interest @ 0.07% | J10: 3 | K10: 44927 | L10: =T9 -> 674136.19 | M10: =$L$8/((($N$4)-1)/($N$3*$N$4)) -> 5071.0496 | N10: =M10-P10 -> 436.36326 | O10: =(N10/L10)*12 -> 0.0077675093 | P10: =L10*($K$3/12) -> 4634.6863 | Q10: =(P10/L10)*12 -> 0.0825 | R10: =R9+N10 -> 1300.1716 | S10: =S9+P10 -> 13912.977 | T10: =L10-N10 -> 673699.83 | U10: =R10+S10 -> 15213.149 | W10: 3 | X10: 44927 | Y10: =AG9 -> 674091.16 | Z10: =Z9 -> 4952.9109 | AA10: =Z10-AC10 -> 458.96981 | AB10: =(AA10/Y10)*12 -> 0.0081704643 | AC10: =Y10*($X$3/12) -> 4493.9411 | AD10: =(AC10/Y10)*12 -> 0.08 | AE10: =AE9+AA10 -> 1367.811 | AF10: =AF9+AC10 -> 13490.922 | AG10: =Y10-AA10 -> 673632.19 | AH10: =AE10+AF10 -> 14858.733 | AJ10: 3 | AK10: 44927 | AL10: =AT9 -> 674044.11 | AM10: =AM9 -> 4835.7827 | AN10: =AM10-AP10 -> 482.58113 | AO10: =(AN10/AL10)*12 -> 0.0085913866 | AP10: =AL10*($AK$3/12) -> 4353.2015 | AQ10: =(AP10/AL10)*12 -> 0.0775 | AR10: =AR9+AN10 -> 1438.4732 | AS10: =AS9+AP10 -> 13068.875 | AT10: =AL10-AN10 -> 673561.53 | AU10: =AR10+AS10 -> 14507.348 | AW10: 3 | AX10: 44927 | AY10: =BG9 -> 673994.97 | AZ10: =AZ9 -> 4719.6979 | BA10: =AZ10-BC10 -> 507.22935 | BB10: =(BA10/AY10)*12 -> 0.009030857 | BC10: =AY10*($AX$3/12) -> 4212.4686 | BD10: =(BC10/AY10)*12 -> 0.075 | BE10: =BE9+BA10 -> 1512.2561 | BF10: =BF9+BC10 -> 12646.838 | BG10: =AY10-BA10 -> 673487.74 | BH10: =BE10+BF10 -> 14159.094 | BJ10: 3 | BK10: 44927 | BL10: =BT9 -> 673943.69 | BM10: =BM9 -> 4604.6899 | BN10: =BM10-BP10 -> 532.94677 | BO10: =(BN10/BL10)*12 -> 0.0094894594 | BP10: =BL10*($BK$3/12) -> 4071.7431 | BQ10: =(BP10/BL10)*12 -> 0.0725 | BR10: =BR9+BN10 -> 1589.2579 | BS10: =BS9+BP10 -> 12224.812 | BT10: =BL10-BN10 -> 673410.74 | BU10: =BR10+BS10 -> 13814.07 | BW10: 3 | BX10: 44927 | BY10: =CG9 -> 673890.19 | BZ10: =BZ9 -> 4490.7918 | CA10: =BZ10-CC10 -> 559.76574 | CB10: =(CA10/BY10)*12 -> 0.0099677796 | CC10: =BY10*($BX$3/12) -> 3931.0261 | CD10: =(CC10/BY10)*12 -> 0.07 | CE10: =CE9+CA10 -> 1669.577 | CF10: =CF9+CC10 -> 11802.799 | CG10: =BY10-CA10 -> 673330.42 | CH10: =CE10+CF10 -> 13472.376
A11: 1 | B11: =VLOOKUP($A$11*12,$J$7:$U$367,10) -> 55487.649 | C11: =VLOOKUP(A11*12,$W$7:$AH$367,10) -> 53796.224 | D11: =VLOOKUP(A11*12,$AJ$7:$AU$367,10) -> 52104.995 | E11: =VLOOKUP(A11*12,$AW$7:$BH$367,10) -> 50413.993 | F11: =VLOOKUP(A11*12,$BJ$7:$BU$367,10) -> 48723.246 | G11: =VLOOKUP(A11*12,$BW$7:$CH$367,10) -> 47032.786 | J11: 4 | K11: 44958 | L11: =T10 -> 673699.83 | M11: =$L$8/((($N$4)-1)/($N$3*$N$4)) -> 5071.0496 | N11: =M11-P11 -> 439.36326 | O11: =(N11/L11)*12 -> 0.0078259766 | P11: =L11*($K$3/12) -> 4631.6863 | Q11: =(P11/L11)*12 -> 0.0825 | R11: =R10+N11 -> 1739.5348 | S11: =S10+P11 -> 18544.663 | T11: =L11-N11 -> 673260.47 | U11: =R11+S11 -> 20284.198 | W11: 4 | X11: 44958 | Y11: =AG10 -> 673632.19 | Z11: =Z10 -> 4952.9109 | AA11: =Z11-AC11 -> 462.02961 | AB11: =(AA11/Y11)*12 -> 0.008230538 | AC11: =Y11*($X$3/12) -> 4490.8813 | AD11: =(AC11/Y11)*12 -> 0.08 | AE11: =AE10+AA11 -> 1829.8406 | AF11: =AF10+AC11 -> 17981.803 | AG11: =Y11-AA11 -> 673170.16 | AH11: =AE11+AF11 -> 19811.643 | AJ11: 4 | AK11: 44958 | AL11: =AT10 -> 673561.53 | AM11: =AM10 -> 4835.7827 | AN11: =AM11-AP11 -> 485.6978 | AO11: =(AN11/AL11)*12 -> 0.0086530678 | AP11: =AL11*($AK$3/12) -> 4350.0849 | AQ11: =(AP11/AL11)*12 -> 0.0775 | AR11: =AR10+AN11 -> 1924.171 | AS11: =AS10+AP11 -> 17418.96 | AT11: =AL11-AN11 -> 673075.83 | AU11: =AR11+AS11 -> 19343.131 | AW11: 4 | AX11: 44958 | AY11: =BG10 -> 673487.74 | AZ11: =AZ10 -> 4719.6979 | BA11: =AZ11-BC11 -> 510.39953 | BB11: =(BA11/AY11)*12 -> 0.0090941438 | BC11: =AY11*($AX$3/12) -> 4209.2984 | BD11: =(BC11/AY11)*12 -> 0.075 | BE11: =BE10+BA11 -> 2022.6557 | BF11: =BF10+BC11 -> 16856.136 | BG11: =AY11-BA11 -> 672977.34 | BH11: =BE11+BF11 -> 18878.792 | BJ11: 4 | BK11: 44958 | BL11: =BT10 -> 673410.74 | BM11: =BM10 -> 4604.6899 | BN11: =BM11-BP11 -> 536.16666 | BO11: =(BN11/BL11)*12 -> 0.009554347 | BP11: =BL11*($BK$3/12) -> 4068.5232 | BQ11: =(BP11/BL11)*12 -> 0.0725 | BR11: =BR10+BN11 -> 2125.4245 | BS11: =BS10+BP11 -> 16293.335 | BT11: =BL11-BN11 -> 672874.58 | BU11: =BR11+BS11 -> 18418.76 | BW11: 4 | BX11: 44958 | BY11: =CG10 -> 673330.42 | BZ11: =BZ10 -> 4490.7918 | CA11: =BZ11-CC11 -> 563.03104 | CB11: =(CA11/BY11)*12 -> 0.01003426 | CC11: =BY11*($BX$3/12) -> 3927.7608 | CD11: =(CC11/BY11)*12 -> 0.07 | CE11: =CE10+CA11 -> 2232.608 | CF11: =CF10+CC11 -> 15730.559 | CG11: =BY11-CA11 -> 672767.39 | CH11: =CE11+CF11 -> 17963.167
A12: =A11+1 -> 2 | B12: =VLOOKUP(A12*12,$J$7:$U$367,10) -> 110515.56 | C12: =VLOOKUP(A12*12,$W$7:$AH$367,10) -> 107124.44 | D12: =VLOOKUP(A12*12,$AJ$7:$AU$367,10) -> 103734.18 | E12: =VLOOKUP(A12*12,$AW$7:$BH$367,10) -> 100344.93 | F12: =VLOOKUP(A12*12,$BJ$7:$BU$367,10) -> 96956.786 | G12: =VLOOKUP(A12*12,$BW$7:$CH$367,10) -> 93569.899 | J12: 5 | K12: 44986 | L12: =T11 -> 673260.47 | M12: =$L$8/((($N$4)-1)/($N$3*$N$4)) -> 5071.0496 | N12: =M12-P12 -> 442.38388 | O12: =(N12/L12)*12 -> 0.0078849224 | P12: =L12*($K$3/12) -> 4628.6657 | Q12: =(P12/L12)*12 -> 0.0825 | R12: =R11+N12 -> 2181.9187 | S12: =S11+P12 -> 23173.329 | T12: =L12-N12 -> 672818.08 | U12: =R12+S12 -> 25355.248 | W12: 5 | X12: 44986 | Y12: =AG11 -> 673170.16 | Z12: =Z11 -> 4952.9109 | AA12: =Z12-AC12 -> 465.10981 | AB12: =(AA12/Y12)*12 -> 0.008291095 | AC12: =Y12*($X$3/12) -> 4487.8011 | AD12: =(AC12/Y12)*12 -> 0.08 | AE12: =AE11+AA12 -> 2294.9504 | AF12: =AF11+AC12 -> 22469.604 | AG12: =Y12-AA12 -> 672705.05 | AH12: =AE12+AF12 -> 24764.554 | AJ12: 5 | AK12: 44986 | AL12: =AT11 -> 673075.83 | AM12: =AM11 -> 4835.7827 | AN12: =AM12-AP12 -> 488.8346 | AO12: =(AN12/AL12)*12 -> 0.0087152367 | AP12: =AL12*($AK$3/12) -> 4346.9481 | AQ12: =(AP12/AL12)*12 -> 0.0775 | AR12: =AR11+AN12 -> 2413.0056 | AS12: =AS11+AP12 -> 21765.908 | AT12: =AL12-AN12 -> 672586.99 | AU12: =AR12+AS12 -> 24178.913 | AW12: 5 | AX12: 44986 | AY12: =BG11 -> 672977.34 | AZ12: =AZ11 -> 4719.6979 | BA12: =AZ12-BC12 -> 513.58953 | BB12: =(BA12/AY12)*12 -> 0.0091579225 | BC12: =AY12*($AX$3/12) -> 4206.1084 | BD12: =(BC12/AY12)*12 -> 0.075 | BE12: =BE11+BA12 -> 2536.2452 | BF12: =BF11+BC12 -> 21062.244 | BG12: =AY12-BA12 -> 672463.75 | BH12: =BE12+BF12 -> 23598.49 | BJ12: 5 | BK12: 44986 | BL12: =BT11 -> 672874.58 | BM12: =BM11 -> 4604.6899 | BN12: =BM12-BP12 -> 539.406 | BO12: =(BN12/BL12)*12 -> 0.0096197303 | BP12: =BL12*($BK$3/12) -> 4065.2839 | BQ12: =(BP12/BL12)*12 -> 0.0725 | BR12: =BR11+BN12 -> 2664.8305 | BS12: =BS11+BP12 -> 20358.619 | BT12: =BL12-BN12 -> 672335.17 | BU12: =BR12+BS12 -> 23023.449 | BW12: 5 | BX12: 44986 | BY12: =CG11 -> 672767.39 | BZ12: =BZ11 -> 4490.7918 | CA12: =BZ12-CC12 -> 566.31539 | CB12: =(CA12/BY12)*12 -> 0.01010124 | CC12: =BY12*($BX$3/12) -> 3924.4765 | CD12: =(CC12/BY12)*12 -> 0.07 | CE12: =CE11+CA12 -> 2798.9234 | CF12: =CF11+CC12 -> 19655.036 | CG12: =BY12-CA12 -> 672201.08 | CH12: =CE12+CF12 -> 22453.959
A13: =A12+1 -> 3 | B13: =VLOOKUP(A13*12,$J$7:$U$367,10) -> 165044.35 | C13: =VLOOKUP(A13*12,$W$7:$AH$367,10) -> 159945.8 | D13: =VLOOKUP(A13*12,$AJ$7:$AU$367,10) -> 154849.35 | E13: =VLOOKUP(A13*12,$AW$7:$BH$367,10) -> 149755.3 | F13: =VLOOKUP(A13*12,$BJ$7:$BU$367,10) -> 144663.91 | G13: =VLOOKUP(A13*12,$BW$7:$CH$367,10) -> 139575.51 | J13: 6 | K13: 45017 | L13: =T12 -> 672818.08 | M13: =$L$8/((($N$4)-1)/($N$3*$N$4)) -> 5071.0496 | N13: =M13-P13 -> 445.42527 | O13: =(N13/L13)*12 -> 0.0079443513 | P13: =L13*($K$3/12) -> 4625.6243 | Q13: =(P13/L13)*12 -> 0.0825 | R13: =R12+N13 -> 2627.344 | S13: =S12+P13 -> 27798.953 | T13: =L13-N13 -> 672372.66 | U13: =R13+S13 -> 30426.297 | W13: 6 | X13: 45017 | Y13: =AG12 -> 672705.05 | Z13: =Z12 -> 4952.9109 | AA13: =Z13-AC13 -> 468.21054 | AB13: =(AA13/Y13)*12 -> 0.0083521396 | AC13: =Y13*($X$3/12) -> 4484.7003 | AD13: =(AC13/Y13)*12 -> 0.08 | AE13: =AE12+AA13 -> 2763.1609 | AF13: =AF12+AC13 -> 26954.304 | AG13: =Y13-AA13 -> 672236.84 | AH13: =AE13+AF13 -> 29717.465 | AJ13: 6 | AK13: 45017 | AL13: =AT12 -> 672586.99 | AM13: =AM12 -> 4835.7827 | AN13: =AM13-AP13 -> 491.99165 | AO13: =(AN13/AL13)*12 -> 0.0087778977 | AP13: =AL13*($AK$3/12) -> 4343.791 | AQ13: =(AP13/AL13)*12 -> 0.0775 | AR13: =AR12+AN13 -> 2904.9973 | AS13: =AS12+AP13 -> 26109.699 | AT13: =AL13-AN13 -> 672095 | AU13: =AR13+AS13 -> 29014.696 | AW13: 6 | AX13: 45017 | AY13: =BG12 -> 672463.75 | AZ13: =AZ12 -> 4719.6979 | BA13: =AZ13-BC13 -> 516.79947 | BB13: =(BA13/AY13)*12 -> 0.0092221975 | BC13: =AY13*($AX$3/12) -> 4202.8985 | BD13: =(BC13/AY13)*12 -> 0.075 | BE13: =BE12+BA13 -> 3053.0447 | BF13: =BF12+BC13 -> 25265.143 | BG13: =AY13-BA13 -> 671946.96 | BH13: =BE13+BF13 -> 28318.188 | BJ13: 6 | BK13: 45017 | BL13: =BT12 -> 672335.17 | BM13: =BM12 -> 4604.6899 | BN13: =BM13-BP13 -> 542.66491 | BO13: =(BN13/BL13)*12 -> 0.009685614 | BP13: =BL13*($BK$3/12) -> 4062.025 | BQ13: =(BP13/BL13)*12 -> 0.0725 | BR13: =BR12+BN13 -> 3207.4954 | BS13: =BS12+BP13 -> 24420.644 | BT13: =BL13-BN13 -> 671792.5 | BU13: =BR13+BS13 -> 27628.139 | BW13: 6 | BX13: 45017 | BY13: =CG12 -> 672201.08 | BZ13: =BZ12 -> 4490.7918 | CA13: =BZ13-CC13 -> 569.6189 | CB13: =(CA13/BY13)*12 -> 0.010168723 | CC13: =BY13*($BX$3/12) -> 3921.1729 | CD13: =(CC13/BY13)*12 -> 0.07 | CE13: =CE12+CA13 -> 3368.5423 | CF13: =CF12+CC13 -> 23576.209 | CG13: =BY13-CA13 -> 671631.46 | CH13: =CE13+CF13 -> 26944.751
A14: =A13+1 -> 4 | B14: =VLOOKUP(A14*12,$J$7:$U$367,10) -> 219031.24 | C14: =VLOOKUP(A14*12,$W$7:$AH$367,10) -> 212218.23 | D14: =VLOOKUP(A14*12,$AJ$7:$AU$367,10) -> 205409.22 | E14: =VLOOKUP(A14*12,$AW$7:$BH$367,10) -> 198604.7 | F14: =VLOOKUP(A14*12,$BJ$7:$BU$367,10) -> 191805.17 | G14: =VLOOKUP(A14*12,$BW$7:$CH$367,10) -> 185011.19 | J14: 7 | K14: 45047 | L14: =T13 -> 672372.66 | M14: =$L$8/((($N$4)-1)/($N$3*$N$4)) -> 5071.0496 | N14: =M14-P14 -> 448.48757 | O14: =(N14/L14)*12 -> 0.0080042678 | P14: =L14*($K$3/12) -> 4622.562 | Q14: =(P14/L14)*12 -> 0.0825 | R14: =R13+N14 -> 3075.8316 | S14: =S13+P14 -> 32421.515 | T14: =L14-N14 -> 671924.17 | U14: =R14+S14 -> 35497.347 | W14: 7 | X14: 45047 | Y14: =AG13 -> 672236.84 | Z14: =Z13 -> 4952.9109 | AA14: =Z14-AC14 -> 471.33195 | AB14: =(AA14/Y14)*12 -> 0.0084136766 | AC14: =Y14*($X$3/12) -> 4481.5789 | AD14: =(AC14/Y14)*12 -> 0.08 | AE14: =AE13+AA14 -> 3234.4929 | AF14: =AF13+AC14 -> 31435.883 | AG14: =Y14-AA14 -> 671765.51 | AH14: =AE14+AF14 -> 34670.376 | AJ14: 7 | AK14: 45047 | AL14: =AT13 -> 672095 | AM14: =AM13 -> 4835.7827 | AN14: =AM14-AP14 -> 495.1691 | AO14: =(AN14/AL14)*12 -> 0.0088410554 | AP14: =AL14*($AK$3/12) -> 4340.6136 | AQ14: =(AP14/AL14)*12 -> 0.0775 | AR14: =AR13+AN14 -> 3400.1664 | AS14: =AS13+AP14 -> 30450.312 | AT14: =AL14-AN14 -> 671599.83 | AU14: =AR14+AS14 -> 33850.479 | AW14: 7 | AX14: 45047 | AY14: =BG13 -> 671946.96 | AZ14: =AZ13 -> 4719.6979 | BA14: =AZ14-BC14 -> 520.02946 | BB14: =(BA14/AY14)*12 -> 0.0092869735 | BC14: =AY14*($AX$3/12) -> 4199.6685 | BD14: =(BC14/AY14)*12 -> 0.075 | BE14: =BE13+BA14 -> 3573.0741 | BF14: =BF13+BC14 -> 29464.811 | BG14: =AY14-BA14 -> 671426.93 | BH14: =BE14+BF14 -> 33037.886 | BJ14: 7 | BK14: 45047 | BL14: =BT13 -> 671792.5 | BM14: =BM13 -> 4604.6899 | BN14: =BM14-BP14 -> 545.94351 | BO14: =(BN14/BL14)*12 -> 0.0097520024 | BP14: =BL14*($BK$3/12) -> 4058.7464 | BQ14: =(BP14/BL14)*12 -> 0.0725 | BR14: =BR13+BN14 -> 3753.439 | BS14: =BS13+BP14 -> 28479.39 | BT14: =BL14-BN14 -> 671246.56 | BU14: =BR14+BS14 -> 32232.829 | BW14: 7 | BX14: 45047 | BY14: =CG13 -> 671631.46 | BZ14: =BZ13 -> 4490.7918 | CA14: =BZ14-CC14 -> 572.94167 | CB14: =(CA14/BY14)*12 -> 0.010236715 | CC14: =BY14*($BX$3/12) -> 3917.8502 | CD14: =(CC14/BY14)*12 -> 0.07 | CE14: =CE13+CA14 -> 3941.484 | CF14: =CF13+CC14 -> 27494.059 | CG14: =BY14-CA14 -> 671058.52 | CH14: =CE14+CF14 -> 31435.543
A15: =A14+1 -> 5 | B15: =VLOOKUP(A15*12,$J$7:$U$367,10) -> 272429.78 | C15: =VLOOKUP(A15*12,$W$7:$AH$367,10) -> 263896.19 | D15: =VLOOKUP(A15*12,$AJ$7:$AU$367,10) -> 255369.19 | E15: =VLOOKUP(A15*12,$AW$7:$BH$367,10) -> 246849.57 | F15: =VLOOKUP(A15*12,$BJ$7:$BU$367,10) -> 238338.14 | G15: =VLOOKUP(A15*12,$BW$7:$CH$367,10) -> 229835.74 | J15: 8 | K15: 45078 | L15: =T14 -> 671924.17 | M15: =$L$8/((($N$4)-1)/($N$3*$N$4)) -> 5071.0496 | N15: =M15-P15 -> 451.57092 | O15: =(N15/L15)*12 -> 0.0080646765 | P15: =L15*($K$3/12) -> 4619.4787 | Q15: =(P15/L15)*12 -> 0.0825 | R15: =R14+N15 -> 3527.4025 | S15: =S14+P15 -> 37040.994 | T15: =L15-N15 -> 671472.6 | U15: =R15+S15 -> 40568.397 | W15: 8 | X15: 45078 | Y15: =AG14 -> 671765.51 | Z15: =Z14 -> 4952.9109 | AA15: =Z15-AC15 -> 474.47416 | AB15: =(AA15/Y15)*12 -> 0.0084757104 | AC15: =Y15*($X$3/12) -> 4478.4367 | AD15: =(AC15/Y15)*12 -> 0.08 | AE15: =AE14+AA15 -> 3708.967 | AF15: =AF14+AC15 -> 35914.32 | AG15: =Y15-AA15 -> 671291.03 | AH15: =AE15+AF15 -> 39623.287 | AJ15: 8 | AK15: 45078 | AL15: =AT14 -> 671599.83 | AM15: =AM14 -> 4835.7827 | AN15: =AM15-AP15 -> 498.36707 | AO15: =(AN15/AL15)*12 -> 0.0089047145 | AP15: =AL15*($AK$3/12) -> 4337.4156 | AQ15: =(AP15/AL15)*12 -> 0.0775 | AR15: =AR14+AN15 -> 3898.5335 | AS15: =AS14+AP15 -> 34787.728 | AT15: =AL15-AN15 -> 671101.47 | AU15: =AR15+AS15 -> 38686.261 | AW15: 8 | AX15: 45078 | AY15: =BG14 -> 671426.93 | AZ15: =AZ14 -> 4719.6979 | BA15: =AZ15-BC15 -> 523.27965 | BB15: =(BA15/AY15)*12 -> 0.0093522549 | BC15: =AY15*($AX$3/12) -> 4196.4183 | BD15: =(BC15/AY15)*12 -> 0.075 | BE15: =BE14+BA15 -> 4096.3538 | BF15: =BF14+BC15 -> 33661.23 | BG15: =AY15-BA15 -> 670903.65 | BH15: =BE15+BF15 -> 37757.583 | BJ15: 8 | BK15: 45078 | BL15: =BT14 -> 671246.56 | BM15: =BM14 -> 4604.6899 | BN15: =BM15-BP15 -> 549.24192 | BO15: =(BN15/BL15)*12 -> 0.0098189002 | BP15: =BL15*($BK$3/12) -> 4055.448 | BQ15: =(BP15/BL15)*12 -> 0.0725 | BR15: =BR14+BN15 -> 4302.6809 | BS15: =BS14+BP15 -> 32534.838 | BT15: =BL15-BN15 -> 670697.32 | BU15: =BR15+BS15 -> 36837.519 | BW15: 8 | BX15: 45078 | BY15: =CG14 -> 671058.52 | BZ15: =BZ14 -> 4490.7918 | CA15: =BZ15-CC15 -> 576.28383 | CB15: =(CA15/BY15)*12 -> 0.010305221 | CC15: =BY15*($BX$3/12) -> 3914.508 | CD15: =(CC15/BY15)*12 -> 0.07 | CE15: =CE14+CA15 -> 4517.7678 | CF15: =CF14+CC15 -> 31408.567 | CG15: =BY15-CA15 -> 670482.23 | CH15: =CE15+CF15 -> 35926.335
A16: =A15+1 -> 6 | B16: =VLOOKUP(A16*12,$J$7:$U$367,10) -> 325189.58 | C16: =VLOOKUP(A16*12,$W$7:$AH$367,10) -> 314930.31 | D16: =VLOOKUP(A16*12,$AJ$7:$AU$367,10) -> 304681.08 | E16: =VLOOKUP(A16*12,$AW$7:$BH$367,10) -> 294442.99 | F16: =VLOOKUP(A16*12,$BJ$7:$BU$367,10) -> 284217.22 | G16: =VLOOKUP(A16*12,$BW$7:$CH$367,10) -> 274004.99 | J16: 9 | K16: 45108 | L16: =T15 -> 671472.6 | M16: =$L$8/((($N$4)-1)/($N$3*$N$4)) -> 5071.0496 | N16: =M16-P16 -> 454.67547 | O16: =(N16/L16)*12 -> 0.008125582 | P16: =L16*($K$3/12) -> 4616.3741 | Q16: =(P16/L16)*12 -> 0.0825 | R16: =R15+N16 -> 3982.0779 | S16: =S15+P16 -> 41657.368 | T16: =L16-N16 -> 671017.92 | U16: =R16+S16 -> 45639.446 | W16: 9 | X16: 45108 | Y16: =AG15 -> 671291.03 | Z16: =Z15 -> 4952.9109 | AA16: =Z16-AC16 -> 477.63732 | AB16: =(AA16/Y16)*12 -> 0.0085382458 | AC16: =Y16*($X$3/12) -> 4475.2736 | AD16: =(AC16/Y16)*12 -> 0.08 | AE16: =AE15+AA16 -> 4186.6044 | AF16: =AF15+AC16 -> 40389.594 | AG16: =Y16-AA16 -> 670813.4 | AH16: =AE16+AF16 -> 44576.198 | AJ16: 9 | AK16: 45108 | AL16: =AT15 -> 671101.47 | AM16: =AM15 -> 4835.7827 | AN16: =AM16-AP16 -> 501.58569 | AO16: =(AN16/AL16)*12 -> 0.0089688796 | AP16: =AL16*($AK$3/12) -> 4334.197 | AQ16: =(AP16/AL16)*12 -> 0.0775 | AR16: =AR15+AN16 -> 4400.1191 | AS16: =AS15+AP16 -> 39121.925 | AT16: =AL16-AN16 -> 670599.88 | AU16: =AR16+AS16 -> 43522.044 | AW16: 9 | AX16: 45108 | AY16: =BG15 -> 670903.65 | AZ16: =AZ15 -> 4719.6979 | BA16: =AZ16-BC16 -> 526.55014 | BB16: =(BA16/AY16)*12 -> 0.0094180465 | BC16: =AY16*($AX$3/12) -> 4193.1478 | BD16: =(BC16/AY16)*12 -> 0.075 | BE16: =BE15+BA16 -> 4622.9039 | BF16: =BF15+BC16 -> 37854.377 | BG16: =AY16-BA16 -> 670377.1 | BH16: =BE16+BF16 -> 42477.281 | BJ16: 9 | BK16: 45108 | BL16: =BT15 -> 670697.32 | BM16: =BM15 -> 4604.6899 | BN16: =BM16-BP16 -> 552.56025 | BO16: =(BN16/BL16)*12 -> 0.0098863121 | BP16: =BL16*($BK$3/12) -> 4052.1296 | BQ16: =(BP16/BL16)*12 -> 0.0725 | BR16: =BR15+BN16 -> 4855.2411 | BS16: =BS15+BP16 -> 36586.968 | BT16: =BL16-BN16 -> 670144.76 | BU16: =BR16+BS16 -> 41442.209 | BW16: 9 | BX16: 45108 | BY16: =CG15 -> 670482.23 | BZ16: =BZ15 -> 4490.7918 | CA16: =BZ16-CC16 -> 579.64549 | CB16: =(CA16/BY16)*12 -> 0.010374243 | CC16: =BY16*($BX$3/12) -> 3911.1464 | CD16: =(CC16/BY16)*12 -> 0.07 | CE16: =CE15+CA16 -> 5097.4133 | CF16: =CF15+CC16 -> 35319.713 | CG16: =BY16-CA16 -> 669902.59 | CH16: =CE16+CF16 -> 40417.127
A17: =A16+1 -> 7 | B17: =VLOOKUP(A17*12,$J$7:$U$367,10) -> 377255.88 | C17: =VLOOKUP(A17*12,$W$7:$AH$367,10) -> 365267.18 | D17: =VLOOKUP(A17*12,$AJ$7:$AU$367,10) -> 353292.84 | E17: =VLOOKUP(A17*12,$AW$7:$BH$367,10) -> 341334.39 | F17: =VLOOKUP(A17*12,$BJ$7:$BU$367,10) -> 329393.41 | G17: =VLOOKUP(A17*12,$BW$7:$CH$367,10) -> 317471.56 | J17: 10 | K17: 45139 | L17: =T16 -> 671017.92 | M17: =$L$8/((($N$4)-1)/($N$3*$N$4)) -> 5071.0496 | N17: =M17-P17 -> 457.80136 | O17: =(N17/L17)*12 -> 0.008186989 | P17: =L17*($K$3/12) -> 4613.2482 | Q17: =(P17/L17)*12 -> 0.0825 | R17: =R16+N17 -> 4439.8793 | S17: =S16+P17 -> 46270.616 | T17: =L17-N17 -> 670560.12 | U17: =R17+S17 -> 50710.496 | W17: 10 | X17: 45139 | Y17: =AG16 -> 670813.4 | Z17: =Z16 -> 4952.9109 | AA17: =Z17-AC17 -> 480.82157 | AB17: =(AA17/Y17)*12 -> 0.0086012874 | AC17: =Y17*($X$3/12) -> 4472.0893 | AD17: =(AC17/Y17)*12 -> 0.08 | AE17: =AE16+AA17 -> 4667.4259 | AF17: =AF16+AC17 -> 44861.683 | AG17: =Y17-AA17 -> 670332.57 | AH17: =AE17+AF17 -> 49529.109 | AJ17: 10 | AK17: 45139 | AL17: =AT16 -> 670599.88 | AM17: =AM16 -> 4835.7827 | AN17: =AM17-AP17 -> 504.82509 | AO17: =(AN17/AL17)*12 -> 0.0090335553 | AP17: =AL17*($AK$3/12) -> 4330.9576 | AQ17: =(AP17/AL17)*12 -> 0.0775 | AR17: =AR16+AN17 -> 4904.9442 | AS17: =AS16+AP17 -> 43452.882 | AT17: =AL17-AN17 -> 670095.06 | AU17: =AR17+AS17 -> 48357.827 | AW17: 10 | AX17: 45139 | AY17: =BG16 -> 670377.1 | AZ17: =AZ16 -> 4719.6979 | BA17: =AZ17-BC17 -> 529.84108 | BB17: =(BA17/AY17)*12 -> 0.0094843529 | BC17: =AY17*($AX$3/12) -> 4189.8569 | BD17: =(BC17/AY17)*12 -> 0.075 | BE17: =BE16+BA17 -> 5152.745 | BF17: =BF16+BC17 -> 42044.234 | BG17: =AY17-BA17 -> 669847.25 | BH17: =BE17+BF17 -> 47196.979 | BJ17: 10 | BK17: 45139 | BL17: =BT16 -> 670144.76 | BM17: =BM16 -> 4604.6899 | BN17: =BM17-BP17 -> 555.89864 | BO17: =(BN17/BL17)*12 -> 0.0099542428 | BP17: =BL17*($BK$3/12) -> 4048.7913 | BQ17: =(BP17/BL17)*12 -> 0.0725 | BR17: =BR16+BN17 -> 5411.1398 | BS17: =BS16+BP17 -> 40635.759 | BT17: =BL17-BN17 -> 669588.86 | BU17: =BR17+BS17 -> 46046.899 | BW17: 10 | BX17: 45139 | BY17: =CG16 -> 669902.59 | BZ17: =BZ16 -> 4490.7918 | CA17: =BZ17-CC17 -> 583.02675 | CB17: =(CA17/BY17)*12 -> 0.010443789 | CC17: =BY17*($BX$3/12) -> 3907.7651 | CD17: =(CC17/BY17)*12 -> 0.07 | CE17: =CE16+CA17 -> 5680.44 | CF17: =CF16+CC17 -> 39227.478 | CG17: =BY17-CA17 -> 669319.56 | CH17: =CE17+CF17 -> 44907.918
A18: =A17+1 -> 8 | B18: =VLOOKUP(A18*12,$J$7:$U$367,10) -> 428569.27 | C18: =VLOOKUP(A18*12,$W$7:$AH$367,10) -> 414848.91 | D18: =VLOOKUP(A18*12,$AJ$7:$AU$367,10) -> 401148.24 | E18: =VLOOKUP(A18*12,$AW$7:$BH$367,10) -> 387469.25 | F18: =VLOOKUP(A18*12,$BJ$7:$BU$367,10) -> 373814.01 | G18: =VLOOKUP(A18*12,$BW$7:$CH$367,10) -> 360184.65 | J18: 11 | K18: 45170 | L18: =T17 -> 670560.12 | M18: =$L$8/((($N$4)-1)/($N$3*$N$4)) -> 5071.0496 | N18: =M18-P18 -> 460.94875 | O18: =(N18/L18)*12 -> 0.0082489024 | P18: =L18*($K$3/12) -> 4610.1008 | Q18: =(P18/L18)*12 -> 0.0825 | R18: =R17+N18 -> 4900.8281 | S18: =S17+P18 -> 50880.717 | T18: =L18-N18 -> 670099.17 | U18: =R18+S18 -> 55781.545 | W18: 11 | X18: 45170 | Y18: =AG17 -> 670332.57 | Z18: =Z17 -> 4952.9109 | AA18: =Z18-AC18 -> 484.02705 | AB18: =(AA18/Y18)*12 -> 0.0086648401 | AC18: =Y18*($X$3/12) -> 4468.8838 | AD18: =(AC18/Y18)*12 -> 0.08 | AE18: =AE17+AA18 -> 5151.453 | AF18: =AF17+AC18 -> 49330.567 | AG18: =Y18-AA18 -> 669848.55 | AH18: =AE18+AF18 -> 54482.02 | AJ18: 11 | AK18: 45170 | AL18: =AT17 -> 670095.06 | AM18: =AM17 -> 4835.7827 | AN18: =AM18-AP18 -> 508.08542 | AO18: =(AN18/AL18)*12 -> 0.0090987465 | AP18: =AL18*($AK$3/12) -> 4327.6972 | AQ18: =(AP18/AL18)*12 -> 0.0775 | AR18: =AR17+AN18 -> 5413.0297 | AS18: =AS17+AP18 -> 47780.58 | AT18: =AL18-AN18 -> 669586.97 | AU18: =AR18+AS18 -> 53193.609 | AW18: 11 | AX18: 45170 | AY18: =BG17 -> 669847.25 | AZ18: =AZ17 -> 4719.6979 | BA18: =AZ18-BC18 -> 533.15259 | BB18: =(BA18/AY18)*12 -> 0.009551179 | BC18: =AY18*($AX$3/12) -> 4186.5453 | BD18: =(BC18/AY18)*12 -> 0.075 | BE18: =BE17+BA18 -> 5685.8976 | BF18: =BF17+BC18 -> 46230.78 | BG18: =AY18-BA18 -> 669314.1 | BH18: =BE18+BF18 -> 51916.677 | BJ18: 11 | BK18: 45170 | BL18: =BT17 -> 669588.86 | BM18: =BM17 -> 4604.6899 | BN18: =BM18-BP18 -> 559.25719 | BO18: =(BN18/BL18)*12 -> 0.010022697 | BP18: =BL18*($BK$3/12) -> 4045.4327 | BQ18: =(BP18/BL18)*12 -> 0.0725 | BR18: =BR17+BN18 -> 5970.397 | BS18: =BS17+BP18 -> 44681.192 | BT18: =BL18-BN18 -> 669029.6 | BU18: =BR18+BS18 -> 50651.589 | BW18: 11 | BX18: 45170 | BY18: =CG17 -> 669319.56 | BZ18: =BZ17 -> 4490.7918 | CA18: =BZ18-CC18 -> 586.42774 | CB18: =(CA18/BY18)*12 -> 0.010513861 | CC18: =BY18*($BX$3/12) -> 3904.3641 | CD18: =(CC18/BY18)*12 -> 0.07 | CE18: =CE17+CA18 -> 6266.8678 | CF18: =CF17+CC18 -> 43131.842 | CG18: =BY18-CA18 -> 668733.13 | CH18: =CE18+CF18 -> 49398.71
A19: =A18+1 -> 9 | B19: =VLOOKUP(A19*12,$J$7:$U$367,10) -> 479065.23 | C19: =VLOOKUP(A19*12,$W$7:$AH$367,10) -> 463612.83 | D19: =VLOOKUP(A19*12,$AJ$7:$AU$367,10) -> 448186.54 | E19: =VLOOKUP(A19*12,$AW$7:$BH$367,10) -> 432788.86 | F19: =VLOOKUP(A19*12,$BJ$7:$BU$367,10) -> 417422.38 | G19: =VLOOKUP(A19*12,$BW$7:$CH$367,10) -> 402089.81 | J19: 12 | K19: 45200 | L19: =T18 -> 670099.17 | M19: =$L$8/((($N$4)-1)/($N$3*$N$4)) -> 5071.0496 | N19: =M19-P19 -> 464.11777 | O19: =(N19/L19)*12 -> 0.0083113269 | P19: =L19*($K$3/12) -> 4606.9318 | Q19: =(P19/L19)*12 -> 0.0825 | R19: =R18+N19 -> 5364.9458 | S19: =S18+P19 -> 55487.649 | T19: =L19-N19 -> 669635.05 | U19: =R19+S19 -> 60852.595 | W19: 12 | X19: 45200 | Y19: =AG18 -> 669848.55 | Z19: =Z18 -> 4952.9109 | AA19: =Z19-AC19 -> 487.25389 | AB19: =(AA19/Y19)*12 -> 0.0087289086 | AC19: =Y19*($X$3/12) -> 4465.657 | AD19: =(AC19/Y19)*12 -> 0.08 | AE19: =AE18+AA19 -> 5638.7069 | AF19: =AF18+AC19 -> 53796.224 | AG19: =Y19-AA19 -> 669361.29 | AH19: =AE19+AF19 -> 59434.93 | AJ19: 12 | AK19: 45200 | AL19: =AT18 -> 669586.97 | AM19: =AM18 -> 4835.7827 | AN19: =AM19-AP19 -> 511.36681 | AO19: =(AN19/AL19)*12 -> 0.009164458 | AP19: =AL19*($AK$3/12) -> 4324.4159 | AQ19: =(AP19/AL19)*12 -> 0.0775 | AR19: =AR18+AN19 -> 5924.3965 | AS19: =AS18+AP19 -> 52104.995 | AT19: =AL19-AN19 -> 669075.6 | AU19: =AR19+AS19 -> 58029.392 | AW19: 12 | AX19: 45200 | AY19: =BG18 -> 669314.1 | AZ19: =AZ18 -> 4719.6979 | BA19: =AZ19-BC19 -> 536.48479 | BB19: =(BA19/AY19)*12 -> 0.0096185296 | BC19: =AY19*($AX$3/12) -> 4183.2131 | BD19: =(BC19/AY19)*12 -> 0.075 | BE19: =BE18+BA19 -> 6222.3824 | BF19: =BF18+BC19 -> 50413.993 | BG19: =AY19-BA19 -> 668777.62 | BH19: =BE19+BF19 -> 56636.375 | BJ19: 12 | BK19: 45200 | BL19: =BT18 -> 669029.6 | BM19: =BM18 -> 4604.6899 | BN19: =BM19-BP19 -> 562.63604 | BO19: =(BN19/BL19)*12 -> 0.01009168 | BP19: =BL19*($BK$3/12) -> 4042.0539 | BQ19: =(BP19/BL19)*12 -> 0.0725 | BR19: =BR18+BN19 -> 6533.033 | BS19: =BS18+BP19 -> 48723.246 | BT19: =BL19-BN19 -> 668466.97 | BU19: =BR19+BS19 -> 55256.279 | BW19: 12 | BX19: 45200 | BY19: =CG18 -> 668733.13 | BZ19: =BZ18 -> 4490.7918 | CA19: =BZ19-CC19 -> 589.84857 | CB19: =(CA19/BY19)*12 -> 0.010584466 | CC19: =BY19*($BX$3/12) -> 3900.9433 | CD19: =(CC19/BY19)*12 -> 0.07 | CE19: =CE18+CA19 -> 6856.7163 | CF19: =CF18+CC19 -> 47032.786 | CG19: =BY19-CA19 -> 668143.28 | CH19: =CE19+CF19 -> 53889.502
A20: =A19+1 -> 10 | B20: =VLOOKUP(A20*12,$J$7:$U$367,10) -> 528673.7 | C20: =VLOOKUP(A20*12,$W$7:$AH$367,10) -> 511491.06 | D20: =VLOOKUP(A20*12,$AJ$7:$AU$367,10) -> 494342.11 | E20: =VLOOKUP(A20*12,$AW$7:$BH$367,10) -> 477229.91 | F20: =VLOOKUP(A20*12,$BJ$7:$BU$367,10) -> 460157.65 | G20: =VLOOKUP(A20*12,$BW$7:$CH$367,10) -> 443128.61 | J20: 13 | K20: 45231 | L20: =T19 -> 669635.05 | M20: =$L$8/((($N$4)-1)/($N$3*$N$4)) -> 5071.0496 | N20: =M20-P20 -> 467.30858 | O20: =(N20/L20)*12 -> 0.0083742673 | P20: =L20*($K$3/12) -> 4603.741 | Q20: =(P20/L20)*12 -> 0.0825 | R20: =R19+N20 -> 5832.2544 | S20: =S19+P20 -> 60091.39 | T20: =L20-N20 -> 669167.75 | U20: =R20+S20 -> 65923.645 | W20: 13 | X20: 45231 | Y20: =AG19 -> 669361.29 | Z20: =Z19 -> 4952.9109 | AA20: =Z20-AC20 -> 490.50225 | AB20: =(AA20/Y20)*12 -> 0.0087934978 | AC20: =Y20*($X$3/12) -> 4462.4086 | AD20: =(AC20/Y20)*12 -> 0.08 | AE20: =AE19+AA20 -> 6129.2091 | AF20: =AF19+AC20 -> 58258.632 | AG20: =Y20-AA20 -> 668870.79 | AH20: =AE20+AF20 -> 64387.841 | AJ20: 13 | AK20: 45231 | AL20: =AT19 -> 669075.6 | AM20: =AM19 -> 4835.7827 | AN20: =AM20-AP20 -> 514.66938 | AO20: =(AN20/AL20)*12 -> 0.0092306947 | AP20: =AL20*($AK$3/12) -> 4321.1133 | AQ20: =(AP20/AL20)*12 -> 0.0775 | AR20: =AR19+AN20 -> 6439.0658 | AS20: =AS19+AP20 -> 56426.109 | AT20: =AL20-AN20 -> 668560.93 | AU20: =AR20+AS20 -> 62865.175 | AW20: 13 | AX20: 45231 | AY20: =BG19 -> 668777.62 | AZ20: =AZ19 -> 4719.6979 | BA20: =AZ20-BC20 -> 539.83782 | BB20: =(BA20/AY20)*12 -> 0.0096864095 | BC20: =AY20*($AX$3/12) -> 4179.8601 | BD20: =(BC20/AY20)*12 -> 0.075 | BE20: =BE19+BA20 -> 6762.2202 | BF20: =BF19+BC20 -> 54593.853 | BG20: =AY20-BA20 -> 668237.78 | BH20: =BE20+BF20 -> 61356.073 | BJ20: 13 | BK20: 45231 | BL20: =BT19 -> 668466.97 | BM20: =BM19 -> 4604.6899 | BN20: =BM20-BP20 -> 566.0353 | BO20: =(BN20/BL20)*12 -> 0.010161196 | BP20: =BL20*($BK$3/12) -> 4038.6546 | BQ20: =(BP20/BL20)*12 -> 0.0725 | BR20: =BR19+BN20 -> 7099.0683 | BS20: =BS19+BP20 -> 52761.9 | BT20: =BL20-BN20 -> 667900.93 | BU20: =BR20+BS20 -> 59860.969 | BW20: 13 | BX20: 45231 | BY20: =CG19 -> 668143.28 | BZ20: =BZ19 -> 4490.7918 | CA20: =BZ20-CC20 -> 593.28935 | CB20: =(CA20/BY20)*12 -> 0.010655607 | CC20: =BY20*($BX$3/12) -> 3897.5025 | CD20: =(CC20/BY20)*12 -> 0.07 | CE20: =CE19+CA20 -> 7450.0057 | CF20: =CF19+CC20 -> 50930.288 | CG20: =BY20-CA20 -> 667549.99 | CH20: =CE20+CF20 -> 58380.294
A21: =A20+1 -> 11 | B21: =VLOOKUP(A21*12,$J$7:$U$367,10) -> 577318.64 | C21: =VLOOKUP(A21*12,$W$7:$AH$367,10) -> 558410.09 | D21: =VLOOKUP(A21*12,$AJ$7:$AU$367,10) -> 539544.06 | E21: =VLOOKUP(A21*12,$AW$7:$BH$367,10) -> 520724.22 | F21: =VLOOKUP(A21*12,$BJ$7:$BU$367,10) -> 501954.36 | G21: =VLOOKUP(A21*12,$BW$7:$CH$367,10) -> 483238.43 | J21: 14 | K21: 45261 | L21: =T20 -> 669167.75 | M21: =$L$8/((($N$4)-1)/($N$3*$N$4)) -> 5071.0496 | N21: =M21-P21 -> 470.52133 | O21: =(N21/L21)*12 -> 0.0084377287 | P21: =L21*($K$3/12) -> 4600.5283 | Q21: =(P21/L21)*12 -> 0.0825 | R21: =R20+N21 -> 6302.7757 | S21: =S20+P21 -> 64691.918 | T21: =L21-N21 -> 668697.22 | U21: =R21+S21 -> 70994.694 | W21: 14 | X21: 45261 | Y21: =AG20 -> 668870.79 | Z21: =Z20 -> 4952.9109 | AA21: =Z21-AC21 -> 493.77227 | AB21: =(AA21/Y21)*12 -> 0.0088586126 | AC21: =Y21*($X$3/12) -> 4459.1386 | AD21: =(AC21/Y21)*12 -> 0.08 | AE21: =AE20+AA21 -> 6622.9814 | AF21: =AF20+AC21 -> 62717.771 | AG21: =Y21-AA21 -> 668377.02 | AH21: =AE21+AF21 -> 69340.752 | AJ21: 14 | AK21: 45261 | AL21: =AT20 -> 668560.93 | AM21: =AM20 -> 4835.7827 | AN21: =AM21-AP21 -> 517.99329 | AO21: =(AN21/AL21)*12 -> 0.0092974614 | AP21: =AL21*($AK$3/12) -> 4317.7894 | AQ21: =(AP21/AL21)*12 -> 0.0775 | AR21: =AR20+AN21 -> 6957.0591 | AS21: =AS20+AP21 -> 60743.898 | AT21: =AL21-AN21 -> 668042.94 | AU21: =AR21+AS21 -> 67700.957 | AW21: 14 | AX21: 45261 | AY21: =BG20 -> 668237.78 | AZ21: =AZ20 -> 4719.6979 | BA21: =AZ21-BC21 -> 543.21181 | BB21: =(BA21/AY21)*12 -> 0.0097548237 | BC21: =AY21*($AX$3/12) -> 4176.4861 | BD21: =(BC21/AY21)*12 -> 0.075 | BE21: =BE20+BA21 -> 7305.432 | BF21: =BF20+BC21 -> 58770.339 | BG21: =AY21-BA21 -> 667694.57 | BH21: =BE21+BF21 -> 66075.771 | BJ21: 14 | BK21: 45261 | BL21: =BT20 -> 667900.93 | BM21: =BM20 -> 4604.6899 | BN21: =BM21-BP21 -> 569.45509 | BO21: =(BN21/BL21)*12 -> 0.01023125 | BP21: =BL21*($BK$3/12) -> 4035.2348 | BQ21: =(BP21/BL21)*12 -> 0.0725 | BR21: =BR20+BN21 -> 7668.5234 | BS21: =BS20+BP21 -> 56797.135 | BT21: =BL21-BN21 -> 667331.48 | BU21: =BR21+BS21 -> 64465.658 | BW21: 14 | BX21: 45261 | BY21: =CG20 -> 667549.99 | BZ21: =BZ20 -> 4490.7918 | CA21: =BZ21-CC21 -> 596.75021 | CB21: =(CA21/BY21)*12 -> 0.01072729 | CC21: =BY21*($BX$3/12) -> 3894.0416 | CD21: =(CC21/BY21)*12 -> 0.07 | CE21: =CE20+CA21 -> 8046.7559 | CF21: =CF20+CC21 -> 54824.33 | CG21: =BY21-CA21 -> 666953.24 | CH21: =CE21+CF21 -> 62871.086
A22: =A21+1 -> 12 | B22: =VLOOKUP(A22*12,$J$7:$U$367,10) -> 624917.48 | C22: =VLOOKUP(A22*12,$W$7:$AH$367,10) -> 604290.3 | D22: =VLOOKUP(A22*12,$AJ$7:$AU$367,10) -> 583715.79 | E22: =VLOOKUP(A22*12,$AW$7:$BH$367,10) -> 563198.26 | F22: =VLOOKUP(A22*12,$BJ$7:$BU$367,10) -> 542742.17 | G22: =VLOOKUP(A22*12,$BW$7:$CH$367,10) -> 522352.12 | J22: 15 | K22: 45292 | L22: =T21 -> 668697.22 | M22: =$L$8/((($N$4)-1)/($N$3*$N$4)) -> 5071.0496 | N22: =M22-P22 -> 473.75616 | O22: =(N22/L22)*12 -> 0.0085017161 | P22: =L22*($K$3/12) -> 4597.2934 | Q22: =(P22/L22)*12 -> 0.0825 | R22: =R21+N22 -> 6776.5319 | S22: =S21+P22 -> 69289.212 | T22: =L22-N22 -> 668223.47 | U22: =R22+S22 -> 76065.744 | W22: 15 | X22: 45292 | Y22: =AG21 -> 668377.02 | Z22: =Z21 -> 4952.9109 | AA22: =Z22-AC22 -> 497.06408 | AB22: =(AA22/Y22)*12 -> 0.0089242581 | AC22: =Y22*($X$3/12) -> 4455.8468 | AD22: =(AC22/Y22)*12 -> 0.08 | AE22: =AE21+AA22 -> 7120.0455 | AF22: =AF21+AC22 -> 67173.618 | AG22: =Y22-AA22 -> 667879.95 | AH22: =AE22+AF22 -> 74293.663 | AJ22: 15 | AK22: 45292 | AL22: =AT21 -> 668042.94 | AM22: =AM21 -> 4835.7827 | AN22: =AM22-AP22 -> 521.33866 | AO22: =(AN22/AL22)*12 -> 0.0093647632 | AP22: =AL22*($AK$3/12) -> 4314.444 | AQ22: =(AP22/AL22)*12 -> 0.0775 | AR22: =AR21+AN22 -> 7478.3978 | AS22: =AS21+AP22 -> 65058.342 | AT22: =AL22-AN22 -> 667521.6 | AU22: =AR22+AS22 -> 72536.74 | AW22: 15 | AX22: 45292 | AY22: =BG21 -> 667694.57 | AZ22: =AZ21 -> 4719.6979 | BA22: =AZ22-BC22 -> 546.60688 | BB22: =(BA22/AY22)*12 -> 0.0098237771 | BC22: =AY22*($AX$3/12) -> 4173.091 | BD22: =(BC22/AY22)*12 -> 0.075 | BE22: =BE21+BA22 -> 7852.0389 | BF22: =BF21+BC22 -> 62943.43 | BG22: =AY22-BA22 -> 667147.96 | BH22: =BE22+BF22 -> 70795.469 | BJ22: 15 | BK22: 45292 | BL22: =BT21 -> 667331.48 | BM22: =BM21 -> 4604.6899 | BN22: =BM22-BP22 -> 572.89555 | BO22: =(BN22/BL22)*12 -> 0.010301847 | BP22: =BL22*($BK$3/12) -> 4031.7943 | BQ22: =(BP22/BL22)*12 -> 0.0725 | BR22: =BR21+BN22 -> 8241.4189 | BS22: =BS21+BP22 -> 60828.929 | BT22: =BL22-BN22 -> 666758.58 | BU22: =BR22+BS22 -> 69070.348 | BW22: 15 | BX22: 45292 | BY22: =CG21 -> 666953.24 | BZ22: =BZ21 -> 4490.7918 | CA22: =BZ22-CC22 -> 600.23125 | CB22: =(CA22/BY22)*12 -> 0.01079952 | CC22: =BY22*($BX$3/12) -> 3890.5606 | CD22: =(CC22/BY22)*12 -> 0.07 | CE22: =CE21+CA22 -> 8646.9872 | CF22: =CF21+CC22 -> 58714.89 | CG22: =BY22-CA22 -> 666353.01 | CH22: =CE22+CF22 -> 67361.878
A23: =A22+1 -> 13 | B23: =VLOOKUP(A23*12,$J$7:$U$367,10) -> 671380.58 | C23: =VLOOKUP(A23*12,$W$7:$AH$367,10) -> 649045.48 | D23: =VLOOKUP(A23*12,$AJ$7:$AU$367,10) -> 626774.58 | E23: =VLOOKUP(A23*12,$AW$7:$BH$367,10) -> 604572.85 | F23: =VLOOKUP(A23*12,$BJ$7:$BU$367,10) -> 582445.45 | G23: =VLOOKUP(A23*12,$BW$7:$CH$367,10) -> 560397.67 | J23: 16 | K23: 45323 | L23: =T22 -> 668223.47 | M23: =$L$8/((($N$4)-1)/($N$3*$N$4)) -> 5071.0496 | N23: =M23-P23 -> 477.01323 | O23: =(N23/L23)*12 -> 0.0085662343 | P23: =L23*($K$3/12) -> 4594.0363 | Q23: =(P23/L23)*12 -> 0.0825 | R23: =R22+N23 -> 7253.5451 | S23: =S22+P23 -> 73883.248 | T23: =L23-N23 -> 667746.45 | U23: =R23+S23 -> 81136.793 | W23: 16 | X23: 45323 | Y23: =AG22 -> 667879.95 | Z23: =Z22 -> 4952.9109 | AA23: =Z23-AC23 -> 500.37784 | AB23: =(AA23/Y23)*12 -> 0.0089904392 | AC23: =Y23*($X$3/12) -> 4452.533 | AD23: =(AC23/Y23)*12 -> 0.08 | AE23: =AE22+AA23 -> 7620.4233 | AF23: =AF22+AC23 -> 71626.151 | AG23: =Y23-AA23 -> 667379.58 | AH23: =AE23+AF23 -> 79246.574 | AJ23: 16 | AK23: 45323 | AL23: =AT22 -> 667521.6 | AM23: =AM22 -> 4835.7827 | AN23: =AM23-AP23 -> 524.70564 | AO23: =(AN23/AL23)*12 -> 0.0094326052 | AP23: =AL23*($AK$3/12) -> 4311.077 | AQ23: =(AP23/AL23)*12 -> 0.0775 | AR23: =AR22+AN23 -> 8003.1034 | AS23: =AS22+AP23 -> 69369.419 | AT23: =AL23-AN23 -> 666996.9 | AU23: =AR23+AS23 -> 77372.523 | AW23: 16 | AX23: 45323 | AY23: =BG22 -> 667147.96 | AZ23: =AZ22 -> 4719.6979 | BA23: =AZ23-BC23 -> 550.02318 | BB23: =(BA23/AY23)*12 -> 0.0098932748 | BC23: =AY23*($AX$3/12) -> 4169.6748 | BD23: =(BC23/AY23)*12 -> 0.075 | BE23: =BE22+BA23 -> 8402.0621 | BF23: =BF22+BC23 -> 67113.105 | BG23: =AY23-BA23 -> 666597.94 | BH23: =BE23+BF23 -> 75515.167 | BJ23: 16 | BK23: 45323 | BL23: =BT22 -> 666758.58 | BM23: =BM22 -> 4604.6899 | BN23: =BM23-BP23 -> 576.3568 | BO23: =(BN23/BL23)*12 -> 0.010372992 | BP23: =BL23*($BK$3/12) -> 4028.3331 | BQ23: =(BP23/BL23)*12 -> 0.0725 | BR23: =BR22+BN23 -> 8817.7757 | BS23: =BS22+BP23 -> 64857.263 | BT23: =BL23-BN23 -> 666182.22 | BU23: =BR23+BS23 -> 73675.038 | BW23: 16 | BX23: 45323 | BY23: =CG22 -> 666353.01 | BZ23: =BZ22 -> 4490.7918 | CA23: =BZ23-CC23 -> 603.7326 | CB23: =(CA23/BY23)*12 -> 0.010872302 | CC23: =BY23*($BX$3/12) -> 3887.0592 | CD23: =(CC23/BY23)*12 -> 0.07 | CE23: =CE22+CA23 -> 9250.7198 | CF23: =CF22+CC23 -> 62601.95 | CG23: =BY23-CA23 -> 665749.28 | CH23: =CE23+CF23 -> 71852.669
... A40: =A39+1 -> 30 | B40: =VLOOKUP(A40*12,$J$7:$U$367,10) -> 1150577.8 | C40: =VLOOKUP(A40*12,$W$7:$AH$367,10) -> 1108047.9 | D40: =VLOOKUP(A40*12,$AJ$7:$AU$367,10) -> 1065881.8 | E40: =VLOOKUP(A40*12,$AW$7:$BH$367,10) -> 1024091.3 | F40: =VLOOKUP(A40*12,$BJ$7:$BU$367,10) -> 982688.36 | G40: =VLOOKUP(A40*12,$BW$7:$CH$367,10) -> 941685.06 | J40: 33 | K40: 45839 | L40: =T39 -> 659652.53 | M40: =$L$8/((($N$4)-1)/($N$3*$N$4)) -> 5071.0496 | N40: =M40-P40 -> 535.93844 | O40: =(N40/L40)*12 -> 0.0097494681 | P40: =L40*($K$3/12) -> 4535.1111 | Q40: =(P40/L40)*12 -> 0.0825 | R40: =R39+N40 -> 15883.41 | S40: =S39+P40 -> 151461.23 | T40: =L40-N40 -> 659116.59 | U40: =R40+S40 -> 167344.64 | W40: 33 | X40: 45839 | Y40: =AG39 -> 658904.37 | Z40: =Z39 -> 4952.9109 | AA40: =Z40-AC40 -> 560.21505 | AB40: =(AA40/Y40)*12 -> 0.010202665 | AC40: =Y40*($X$3/12) -> 4392.6958 | AD40: =(AC40/Y40)*12 -> 0.08 | AE40: =AE39+AA40 -> 16655.841 | AF40: =AF39+AC40 -> 146790.22 | AG40: =Y40-AA40 -> 658344.16 | AH40: =AE40+AF40 -> 163446.06 | AJ40: 33 | AK40: 45839 | AL40: =AT39 -> 658125.52 | AM40: =AM39 -> 4835.7827 | AN40: =AM40-AP40 -> 585.3887 | AO40: =(AN40/AL40)*12 -> 0.010673746 | AP40: =AL40*($AK$3/12) -> 4250.394 | AQ40: =(AP40/AL40)*12 -> 0.0775 | AR40: =AR39+AN40 -> 17459.873 | AS40: =AS39+AP40 -> 142120.95 | AT40: =AL40-AN40 -> 657540.13 | AU40: =AR40+AS40 -> 159580.83 | AW40: 33 | AX40: 45839 | AY40: =BG39 -> 657315.11 | AZ40: =AZ39 -> 4719.6979 | BA40: =AZ40-BC40 -> 611.47848 | BB40: =(BA40/AY40)*12 -> 0.011163203 | BC40: =AY40*($AX$3/12) -> 4108.2195 | BD40: =(BC40/AY40)*12 -> 0.075 | BE40: =BE39+BA40 -> 18296.366 | BF40: =BF39+BC40 -> 137453.67 | BG40: =AY40-BA40 -> 656703.63 | BH40: =BE40+BF40 -> 155750.03 | BJ40: 33 | BK40: 45839 | BL40: =BT39 -> 656472.33 | BM40: =BM39 -> 4604.6899 | BN40: =BM40-BP40 -> 638.5029 | BO40: =(BN40/BL40)*12 -> 0.011671527 | BP40: =BL40*($BK$3/12) -> 3966.187 | BQ40: =(BP40/BL40)*12 -> 0.0725 | BR40: =BR39+BN40 -> 19166.174 | BS40: =BS39+BP40 -> 132788.59 | BT40: =BL40-BN40 -> 655833.83 | BU40: =BR40+BS40 -> 151954.77 | BW40: 33 | BX40: 45839 | BY40: =CG39 -> 655596.34 | BZ40: =BZ39 -> 4490.7918 | CA40: =BZ40-CC40 -> 666.47987 | CB40: =(CA40/BY40)*12 -> 0.012199212 | CC40: =BY40*($BX$3/12) -> 3824.312 | CD40: =(CC40/BY40)*12 -> 0.07 | CE40: =CE39+CA40 -> 20070.142 | CF40: =CF39+CC40 -> 128125.99 | CG40: =BY40-CA40 -> 654929.86 | CH40: =CE40+CF40 -> 148196.13
J41: 34 | K41: 45870 | L41: =T40 -> 659116.59 | M41: =$L$8/((($N$4)-1)/($N$3*$N$4)) -> 5071.0496 | N41: =M41-P41 -> 539.62302 | O41: =(N41/L41)*12 -> 0.0098244777 | P41: =L41*($K$3/12) -> 4531.4266 | Q41: =(P41/L41)*12 -> 0.0825 | R41: =R40+N41 -> 16423.033 | S41: =S40+P41 -> 155992.65 | T41: =L41-N41 -> 658576.97 | U41: =R41+S41 -> 172415.69 | W41: 34 | X41: 45870 | Y41: =AG40 -> 658344.16 | Z41: =Z40 -> 4952.9109 | AA41: =Z41-AC41 -> 563.94982 | AB41: =(AA41/Y41)*12 -> 0.010279423 | AC41: =Y41*($X$3/12) -> 4388.9611 | AD41: =(AC41/Y41)*12 -> 0.08 | AE41: =AE40+AA41 -> 17219.791 | AF41: =AF40+AC41 -> 151179.18 | AG41: =Y41-AA41 -> 657780.21 | AH41: =AE41+AF41 -> 168398.97 | AJ41: 34 | AK41: 45870 | AL41: =AT40 -> 657540.13 | AM41: =AM40 -> 4835.7827 | AN41: =AM41-AP41 -> 589.16934 | AO41: =(AN41/AL41)*12 -> 0.010752244 | AP41: =AL41*($AK$3/12) -> 4246.6133 | AQ41: =(AP41/AL41)*12 -> 0.0775 | AR41: =AR40+AN41 -> 18049.043 | AS41: =AS40+AP41 -> 146367.57 | AT41: =AL41-AN41 -> 656950.96 | AU41: =AR41+AS41 -> 164416.61 | AW41: 34 | AX41: 45870 | AY41: =BG40 -> 656703.63 | AZ41: =AZ40 -> 4719.6979 | BA41: =AZ41-BC41 -> 615.30022 | BB41: =(BA41/AY41)*12 -> 0.011243432 | BC41: =AY41*($AX$3/12) -> 4104.3977 | BD41: =(BC41/AY41)*12 -> 0.075 | BE41: =BE40+BA41 -> 18911.666 | BF41: =BF40+BC41 -> 141558.06 | BG41: =AY41-BA41 -> 656088.33 | BH41: =BE41+BF41 -> 160469.73 | BJ41: 34 | BK41: 45870 | BL41: =BT40 -> 655833.83 | BM41: =BM40 -> 4604.6899 | BN41: =BM41-BP41 -> 642.36052 | BO41: =(BN41/BL41)*12 -> 0.011753475 | BP41: =BL41*($BK$3/12) -> 3962.3294 | BQ41: =(BP41/BL41)*12 -> 0.0725 | BR41: =BR40+BN41 -> 19808.534 | BS41: =BS40+BP41 -> 136750.92 | BT41: =BL41-BN41 -> 655191.47 | BU41: =BR41+BS41 -> 156559.46 | BW41: 34 | BX41: 45870 | BY41: =CG40 -> 654929.86 | BZ41: =BZ40 -> 4490.7918 | CA41: =BZ41-CC41 -> 670.36767 | CB41: =(CA41/BY41)*12 -> 0.01228286 | CC41: =BY41*($BX$3/12) -> 3820.4242 | CD41: =(CC41/BY41)*12 -> 0.07 | CE41: =CE40+CA41 -> 20740.509 | CF41: =CF40+CC41 -> 131946.41 | CG41: =BY41-CA41 -> 654259.49 | CH41: =CE41+CF41 -> 152686.92
J42: 35 | K42: 45901 | L42: =T41 -> 658576.97 | M42: =$L$8/((($N$4)-1)/($N$3*$N$4)) -> 5071.0496 | N42: =M42-P42 -> 543.33293 | O42: =(N42/L42)*12 -> 0.0099001263 | P42: =L42*($K$3/12) -> 4527.7166 | Q42: =(P42/L42)*12 -> 0.0825 | R42: =R41+N42 -> 16966.366 | S42: =S41+P42 -> 160520.37 | T42: =L42-N42 -> 658033.63 | U42: =R42+S42 -> 177486.74 | W42: 35 | X42: 45901 | Y42: =AG41 -> 657780.21 | Z42: =Z41 -> 4952.9109 | AA42: =Z42-AC42 -> 567.70948 | AB42: =(AA42/Y42)*12 -> 0.010356824 | AC42: =Y42*($X$3/12) -> 4385.2014 | AD42: =(AC42/Y42)*12 -> 0.08 | AE42: =AE41+AA42 -> 17787.501 | AF42: =AF41+AC42 -> 155564.38 | AG42: =Y42-AA42 -> 657212.5 | AH42: =AE42+AF42 -> 173351.88 | AJ42: 35 | AK42: 45901 | AL42: =AT41 -> 656950.96 | AM42: =AM41 -> 4835.7827 | AN42: =AM42-AP42 -> 592.97439 | AO42: =(AN42/AL42)*12 -> 0.010831391 | AP42: =AL42*($AK$3/12) -> 4242.8083 | AQ42: =(AP42/AL42)*12 -> 0.0775 | AR42: =AR41+AN42 -> 18642.017 | AS42: =AS41+AP42 -> 150610.38 | AT42: =AL42-AN42 -> 656357.98 | AU42: =AR42+AS42 -> 169252.39 | AW42: 35 | AX42: 45901 | AY42: =BG41 -> 656088.33 | AZ42: =AZ41 -> 4719.6979 | BA42: =AZ42-BC42 -> 619.14585 | BB42: =(BA42/AY42)*12 -> 0.011324314 | BC42: =AY42*($AX$3/12) -> 4100.5521 | BD42: =(BC42/AY42)*12 -> 0.075 | BE42: =BE41+BA42 -> 19530.812 | BF42: =BF41+BC42 -> 145658.62 | BG42: =AY42-BA42 -> 655469.19 | BH42: =BE42+BF42 -> 165189.43 | BJ42: 35 | BK42: 45901 | BL42: =BT41 -> 655191.47 | BM42: =BM41 -> 4604.6899 | BN42: =BM42-BP42 -> 646.24145 | BO42: =(BN42/BL42)*12 -> 0.011836078 | BP42: =BL42*($BK$3/12) -> 3958.4484 | BQ42: =(BP42/BL42)*12 -> 0.0725 | BR42: =BR41+BN42 -> 20454.776 | BS42: =BS41+BP42 -> 140709.37 | BT42: =BL42-BN42 -> 654545.22 | BU42: =BR42+BS42 -> 161164.15 | BW42: 35 | BX42: 45901 | BY42: =CG41 -> 654259.49 | BZ42: =BZ41 -> 4490.7918 | CA42: =BZ42-CC42 -> 674.27815 | CB42: =(CA42/BY42)*12 -> 0.012367169 | CC42: =BY42*($BX$3/12) -> 3816.5137 | CD42: =(CC42/BY42)*12 -> 0.07 | CE42: =CE41+CA42 -> 21414.788 | CF42: =CF41+CC42 -> 135762.93 | CG42: =BY42-CA42 -> 653585.21 | CH42: =CE42+CF42 -> 157177.71
J43: 36 | K43: 45931 | L43: =T42 -> 658033.63 | M43: =$L$8/((($N$4)-1)/($N$3*$N$4)) -> 5071.0496 | N43: =M43-P43 -> 547.06834 | O43: =(N43/L43)*12 -> 0.0099764203 | P43: =L43*($K$3/12) -> 4523.9812 | Q43: =(P43/L43)*12 -> 0.0825 | R43: =R42+N43 -> 17513.434 | S43: =S42+P43 -> 165044.35 | T43: =L43-N43 -> 657486.57 | U43: =R43+S43 -> 182557.78 | W43: 36 | X43: 45931 | Y43: =AG42 -> 657212.5 | Z43: =Z42 -> 4952.9109 | AA43: =Z43-AC43 -> 571.49421 | AB43: =(AA43/Y43)*12 -> 0.010434875 | AC43: =Y43*($X$3/12) -> 4381.4167 | AD43: =(AC43/Y43)*12 -> 0.08 | AE43: =AE42+AA43 -> 18358.995 | AF43: =AF42+AC43 -> 159945.8 | AG43: =Y43-AA43 -> 656641.01 | AH43: =AE43+AF43 -> 178304.79 | AJ43: 36 | AK43: 45931 | AL43: =AT42 -> 656357.98 | AM43: =AM42 -> 4835.7827 | AN43: =AM43-AP43 -> 596.80402 | AO43: =(AN43/AL43)*12 -> 0.010911192 | AP43: =AL43*($AK$3/12) -> 4238.9786 | AQ43: =(AP43/AL43)*12 -> 0.0775 | AR43: =AR42+AN43 -> 19238.821 | AS43: =AS42+AP43 -> 154849.35 | AT43: =AL43-AN43 -> 655761.18 | AU43: =AR43+AS43 -> 174088.18 | AW43: 36 | AX43: 45931 | AY43: =BG42 -> 655469.19 | AZ43: =AZ42 -> 4719.6979 | BA43: =AZ43-BC43 -> 623.01551 | BB43: =(BA43/AY43)*12 -> 0.011405854 | BC43: =AY43*($AX$3/12) -> 4096.6824 | BD43: =(BC43/AY43)*12 -> 0.075 | BE43: =BE42+BA43 -> 20153.827 | BF43: =BF42+BC43 -> 149755.3 | BG43: =AY43-BA43 -> 654846.17 | BH43: =BE43+BF43 -> 169909.13 | BJ43: 36 | BK43: 45931 | BL43: =BT42 -> 654545.22 | BM43: =BM42 -> 4604.6899 | BN43: =BM43-BP43 -> 650.14583 | BO43: =(BN43/BL43)*12 -> 0.011919344 | BP43: =BL43*($BK$3/12) -> 3954.5441 | BQ43: =(BP43/BL43)*12 -> 0.0725 | BR43: =BR42+BN43 -> 21104.922 | BS43: =BS42+BP43 -> 144663.91 | BT43: =BL43-BN43 -> 653895.08 | BU43: =BR43+BS43 -> 165768.84 | BW43: 36 | BX43: 45931 | BY43: =CG42 -> 653585.21 | BZ43: =BZ42 -> 4490.7918 | CA43: =BZ43-CC43 -> 678.21144 | CB43: =(CA43/BY43)*12 -> 0.012452144 | CC43: =BY43*($BX$3/12) -> 3812.5804 | CD43: =(CC43/BY43)*12 -> 0.07 | CE43: =CE42+CA43 -> 22092.999 | CF43: =CF42+CC43 -> 139575.51 | CG43: =BY43-CA43 -> 652907 | CH43: =CE43+CF43 -> 161668.51
J44: 37 | K44: 45962 | L44: =T43 -> 657486.57 | M44: =$L$8/((($N$4)-1)/($N$3*$N$4)) -> 5071.0496 | N44: =M44-P44 -> 550.82944 | O44: =(N44/L44)*12 -> 0.010053366 | P44: =L44*($K$3/12) -> 4520.2201 | Q44: =(P44/L44)*12 -> 0.0825 | R44: =R43+N44 -> 18064.264 | S44: =S43+P44 -> 169564.57 | T44: =L44-N44 -> 656935.74 | U44: =R44+S44 -> 187628.83 | W44: 37 | X44: 45962 | Y44: =AG43 -> 656641.01 | Z44: =Z43 -> 4952.9109 | AA44: =Z44-AC44 -> 575.30417 | AB44: =(AA44/Y44)*12 -> 0.010513584 | AC44: =Y44*($X$3/12) -> 4377.6067 | AD44: =(AC44/Y44)*12 -> 0.08 | AE44: =AE43+AA44 -> 18934.299 | AF44: =AF43+AC44 -> 164323.4 | AG44: =Y44-AA44 -> 656065.7 | AH44: =AE44+AF44 -> 183257.7 | AJ44: 37 | AK44: 45962 | AL44: =AT43 -> 655761.18 | AM44: =AM43 -> 4835.7827 | AN44: =AM44-AP44 -> 600.65838 | AO44: =(AN44/AL44)*12 -> 0.010991655 | AP44: =AL44*($AK$3/12) -> 4235.1243 | AQ44: =(AP44/AL44)*12 -> 0.0775 | AR44: =AR43+AN44 -> 19839.479 | AS44: =AS43+AP44 -> 159084.48 | AT44: =AL44-AN44 -> 655160.52 | AU44: =AR44+AS44 -> 178923.96 | AW44: 37 | AX44: 45962 | AY44: =BG43 -> 654846.17 | AZ44: =AZ43 -> 4719.6979 | BA44: =AZ44-BC44 -> 626.90935 | BB44: =(BA44/AY44)*12 -> 0.01148806 | BC44: =AY44*($AX$3/12) -> 4092.7886 | BD44: =(BC44/AY44)*12 -> 0.075 | BE44: =BE43+BA44 -> 20780.737 | BF44: =BF43+BC44 -> 153848.09 | BG44: =AY44-BA44 -> 654219.26 | BH44: =BE44+BF44 -> 174628.82 | BJ44: 37 | BK44: 45962 | BL44: =BT43 -> 653895.08 | BM44: =BM43 -> 4604.6899 | BN44: =BM44-BP44 -> 654.07379 | BO44: =(BN44/BL44)*12 -> 0.01200328 | BP44: =BL44*($BK$3/12) -> 3950.6161 | BQ44: =(BP44/BL44)*12 -> 0.0725 | BR44: =BR43+BN44 -> 21758.995 | BS44: =BS43+BP44 -> 148614.53 | BT44: =BL44-BN44 -> 653241 | BU44: =BR44+BS44 -> 170373.53 | BW44: 37 | BX44: 45962 | BY44: =CG43 -> 652907 | BZ44: =BZ43 -> 4490.7918 | CA44: =BZ44-CC44 -> 682.16767 | CB44: =(CA44/BY44)*12 -> 0.012537792 | CC44: =BY44*($BX$3/12) -> 3808.6242 | CD44: =(CC44/BY44)*12 -> 0.07 | CE44: =CE43+CA44 -> 22775.167 | CF44: =CF43+CC44 -> 143384.13 | CG44: =BY44-CA44 -> 652224.83 | CH44: =CE44+CF44 -> 166159.3
J45: 38 | K45: 45992 | L45: =T44 -> 656935.74 | M45: =$L$8/((($N$4)-1)/($N$3*$N$4)) -> 5071.0496 | N45: =M45-P45 -> 554.61639 | O45: =(N45/L45)*12 -> 0.010130971 | P45: =L45*($K$3/12) -> 4516.4332 | Q45: =(P45/L45)*12 -> 0.0825 | R45: =R44+N45 -> 18618.88 | S45: =S44+P45 -> 174081 | T45: =L45-N45 -> 656381.12 | U45: =R45+S45 -> 192699.88 | W45: 38 | X45: 45992 | Y45: =AG44 -> 656065.7 | Z45: =Z44 -> 4952.9109 | AA45: =Z45-AC45 -> 579.13953 | AB45: =(AA45/Y45)*12 -> 0.010592955 | AC45: =Y45*($X$3/12) -> 4373.7713 | AD45: =(AC45/Y45)*12 -> 0.08 | AE45: =AE44+AA45 -> 19513.439 | AF45: =AF44+AC45 -> 168697.17 | AG45: =Y45-AA45 -> 655486.56 | AH45: =AE45+AF45 -> 188210.61 | AJ45: 38 | AK45: 45992 | AL45: =AT44 -> 655160.52 | AM45: =AM44 -> 4835.7827 | AN45: =AM45-AP45 -> 604.53763 | AO45: =(AN45/AL45)*12 -> 0.011072785 | AP45: =AL45*($AK$3/12) -> 4231.245 | AQ45: =(AP45/AL45)*12 -> 0.0775 | AR45: =AR44+AN45 -> 20444.017 | AS45: =AS44+AP45 -> 163315.72 | AT45: =AL45-AN45 -> 654555.98 | AU45: =AR45+AS45 -> 183759.74 | AW45: 38 | AX45: 45992 | AY45: =BG44 -> 654219.26 | AZ45: =AZ44 -> 4719.6979 | BA45: =AZ45-BC45 -> 630.82754 | BB45: =(BA45/AY45)*12 -> 0.011570938 | BC45: =AY45*($AX$3/12) -> 4088.8704 | BD45: =(BC45/AY45)*12 -> 0.075 | BE45: =BE44+BA45 -> 21411.564 | BF45: =BF44+BC45 -> 157936.96 | BG45: =AY45-BA45 -> 653588.44 | BH45: =BE45+BF45 -> 179348.52 | BJ45: 38 | BK45: 45992 | BL45: =BT44 -> 653241 | BM45: =BM44 -> 4604.6899 | BN45: =BM45-BP45 -> 658.02549 | BO45: =(BN45/BL45)*12 -> 0.012087891 | BP45: =BL45*($BK$3/12) -> 3946.6644 | BQ45: =(BP45/BL45)*12 -> 0.0725 | BR45: =BR44+BN45 -> 22417.021 | BS45: =BS44+BP45 -> 152561.2 | BT45: =BL45-BN45 -> 652582.98 | BU45: =BR45+BS45 -> 174978.22 | BW45: 38 | BX45: 45992 | BY45: =CG44 -> 652224.83 | BZ45: =BZ44 -> 4490.7918 | CA45: =BZ45-CC45 -> 686.14698 | CB45: =(CA45/BY45)*12 -> 0.012624119 | CC45: =BY45*($BX$3/12) -> 3804.6449 | CD45: =(CC45/BY45)*12 -> 0.07 | CE45: =CE44+CA45 -> 23461.314 | CF45: =CF44+CC45 -> 147188.78 | CG45: =BY45-CA45 -> 651538.69 | CH45: =CE45+CF45 -> 170650.09
J46: 39 | K46: 46023 | L46: =T45 -> 656381.12 | M46: =$L$8/((($N$4)-1)/($N$3*$N$4)) -> 5071.0496 | N46: =M46-P46 -> 558.42938 | O46: =(N46/L46)*12 -> 0.01020924 | P46: =L46*($K$3/12) -> 4512.6202 | Q46: =(P46/L46)*12 -> 0.0825 | R46: =R45+N46 -> 19177.309 | S46: =S45+P46 -> 178593.62 | T46: =L46-N46 -> 655822.69 | U46: =R46+S46 -> 197770.93 | W46: 39 | X46: 46023 | Y46: =AG45 -> 655486.56 | Z46: =Z45 -> 4952.9109 | AA46: =Z46-AC46 -> 583.00046 | AB46: =(AA46/Y46)*12 -> 0.010672996 | AC46: =Y46*($X$3/12) -> 4369.9104 | AD46: =(AC46/Y46)*12 -> 0.08 | AE46: =AE45+AA46 -> 20096.439 | AF46: =AF45+AC46 -> 173067.09 | AG46: =Y46-AA46 -> 654903.56 | AH46: =AE46+AF46 -> 193163.52 | AJ46: 39 | AK46: 46023 | AL46: =AT45 -> 654555.98 | AM46: =AM45 -> 4835.7827 | AN46: =AM46-AP46 -> 608.44193 | AO46: =(AN46/AL46)*12 -> 0.011154589 | AP46: =AL46*($AK$3/12) -> 4227.3407 | AQ46: =(AP46/AL46)*12 -> 0.0775 | AR46: =AR45+AN46 -> 21052.459 | AS46: =AS45+AP46 -> 167543.06 | AT46: =AL46-AN46 -> 653947.54 | AU46: =AR46+AS46 -> 188595.52 | AW46: 39 | AX46: 46023 | AY46: =BG45 -> 653588.44 | AZ46: =AZ45 -> 4719.6979 | BA46: =AZ46-BC46 -> 634.77021 | BB46: =(BA46/AY46)*12 -> 0.011654494 | BC46: =AY46*($AX$3/12) -> 4084.9277 | BD46: =(BC46/AY46)*12 -> 0.075 | BE46: =BE45+BA46 -> 22046.335 | BF46: =BF45+BC46 -> 162021.88 | BG46: =AY46-BA46 -> 652953.67 | BH46: =BE46+BF46 -> 184068.22 | BJ46: 39 | BK46: 46023 | BL46: =BT45 -> 652582.98 | BM46: =BM45 -> 4604.6899 | BN46: =BM46-BP46 -> 662.00106 | BO46: =(BN46/BL46)*12 -> 0.012173184 | BP46: =BL46*($BK$3/12) -> 3942.6888 | BQ46: =(BP46/BL46)*12 -> 0.0725 | BR46: =BR45+BN46 -> 23079.022 | BS46: =BS45+BP46 -> 156503.88 | BT46: =BL46-BN46 -> 651920.98 | BU46: =BR46+BS46 -> 179582.91 | BW46: 39 | BX46: 46023 | BY46: =CG45 -> 651538.69 | BZ46: =BZ45 -> 4490.7918 | CA46: =BZ46-CC46 -> 690.14951 | CB46: =(CA46/BY46)*12 -> 0.012711132 | CC46: =BY46*($BX$3/12) -> 3800.6423 | CD46: =(CC46/BY46)*12 -> 0.07 | CE46: =CE45+CA46 -> 24151.463 | CF46: =CF45+CC46 -> 150989.42 | CG46: =BY46-CA46 -> 650848.54 | CH46: =CE46+CF46 -> 175140.88
J47: 40 | K47: 46054 | L47: =T46 -> 655822.69 | M47: =$L$8/((($N$4)-1)/($N$3*$N$4)) -> 5071.0496 | N47: =M47-P47 -> 562.26858 | O47: =(N47/L47)*12 -> 0.010288182 | P47: =L47*($K$3/12) -> 4508.781 | Q47: =(P47/L47)*12 -> 0.0825 | R47: =R46+N47 -> 19739.578 | S47: =S46+P47 -> 183102.41 | T47: =L47-N47 -> 655260.42 | U47: =R47+S47 -> 202841.98 | W47: 40 | X47: 46054 | Y47: =AG46 -> 654903.56 | Z47: =Z46 -> 4952.9109 | AA47: =Z47-AC47 -> 586.88713 | AB47: =(AA47/Y47)*12 -> 0.010753714 | AC47: =Y47*($X$3/12) -> 4366.0237 | AD47: =(AC47/Y47)*12 -> 0.08 | AE47: =AE46+AA47 -> 20683.326 | AF47: =AF46+AC47 -> 177433.11 | AG47: =Y47-AA47 -> 654316.67 | AH47: =AE47+AF47 -> 198116.43 | AJ47: 40 | AK47: 46054 | AL47: =AT46 -> 653947.54 | AM47: =AM46 -> 4835.7827 | AN47: =AM47-AP47 -> 612.37145 | AO47: =(AN47/AL47)*12 -> 0.011237075 | AP47: =AL47*($AK$3/12) -> 4223.4112 | AQ47: =(AP47/AL47)*12 -> 0.0775 | AR47: =AR46+AN47 -> 21664.83 | AS47: =AS46+AP47 -> 171766.48 | AT47: =AL47-AN47 -> 653335.17 | AU47: =AR47+AS47 -> 193431.31 | AW47: 40 | AX47: 46054 | AY47: =BG46 -> 652953.67 | AZ47: =AZ46 -> 4719.6979 | BA47: =AZ47-BC47 -> 638.73752 | BB47: =(BA47/AY47)*12 -> 0.011738735 | BC47: =AY47*($AX$3/12) -> 4080.9604 | BD47: =(BC47/AY47)*12 -> 0.075 | BE47: =BE46+BA47 -> 22685.072 | BF47: =BF46+BC47 -> 166102.85 | BG47: =AY47-BA47 -> 652314.93 | BH47: =BE47+BF47 -> 188787.92 | BJ47: 40 | BK47: 46054 | BL47: =BT46 -> 651920.98 | BM47: =BM46 -> 4604.6899 | BN47: =BM47-BP47 -> 666.00065 | BO47: =(BN47/BL47)*12 -> 0.012259166 | BP47: =BL47*($BK$3/12) -> 3938.6892 | BQ47: =(BP47/BL47)*12 -> 0.0725 | BR47: =BR46+BN47 -> 23745.023 | BS47: =BS46+BP47 -> 160442.57 | BT47: =BL47-BN47 -> 651254.98 | BU47: =BR47+BS47 -> 184187.6 | BW47: 40 | BX47: 46054 | BY47: =CG46 -> 650848.54 | BZ47: =BZ46 -> 4490.7918 | CA47: =BZ47-CC47 -> 694.17538 | CB47: =(CA47/BY47)*12 -> 0.012798837 | CC47: =BY47*($BX$3/12) -> 3796.6165 | CD47: =(CC47/BY47)*12 -> 0.07 | CE47: =CE46+CA47 -> 24845.639 | CF47: =CF46+CC47 -> 154786.04 | CG47: =BY47-CA47 -> 650154.36 | CH47: =CE47+CF47 -> 179631.67
J48: 41 | K48: 46082 | L48: =T47 -> 655260.42 | M48: =$L$8/((($N$4)-1)/($N$3*$N$4)) -> 5071.0496 | N48: =M48-P48 -> 566.13418 | O48: =(N48/L48)*12 -> 0.010367802 | P48: =L48*($K$3/12) -> 4504.9154 | Q48: =(P48/L48)*12 -> 0.0825 | R48: =R47+N48 -> 20305.712 | S48: =S47+P48 -> 187607.32 | T48: =L48-N48 -> 654694.29 | U48: =R48+S48 -> 207913.03 | W48: 41 | X48: 46082 | Y48: =AG47 -> 654316.67 | Z48: =Z47 -> 4952.9109 | AA48: =Z48-AC48 -> 590.79971 | AB48: =(AA48/Y48)*12 -> 0.010835115 | AC48: =Y48*($X$3/12) -> 4362.1112 | AD48: =(AC48/Y48)*12 -> 0.08 | AE48: =AE47+AA48 -> 21274.126 | AF48: =AF47+AC48 -> 181795.22 | AG48: =Y48-AA48 -> 653725.87 | AH48: =AE48+AF48 -> 203069.35 | AJ48: 41 | AK48: 46082 | AL48: =AT47 -> 653335.17 | AM48: =AM47 -> 4835.7827 | AN48: =AM48-AP48 -> 616.32635 | AO48: =(AN48/AL48)*12 -> 0.011320248 | AP48: =AL48*($AK$3/12) -> 4219.4563 | AQ48: =(AP48/AL48)*12 -> 0.0775 | AR48: =AR47+AN48 -> 22281.157 | AS48: =AS47+AP48 -> 175985.93 | AT48: =AL48-AN48 -> 652718.84 | AU48: =AR48+AS48 -> 198267.09 | AW48: 41 | AX48: 46082 | AY48: =BG47 -> 652314.93 | AZ48: =AZ47 -> 4719.6979 | BA48: =AZ48-BC48 -> 642.72963 | BB48: =(BA48/AY48)*12 -> 0.011823669 | BC48: =AY48*($AX$3/12) -> 4076.9683 | BD48: =(BC48/AY48)*12 -> 0.075 | BE48: =BE47+BA48 -> 23327.802 | BF48: =BF47+BC48 -> 170179.81 | BG48: =AY48-BA48 -> 651672.2 | BH48: =BE48+BF48 -> 193507.62 | BJ48: 41 | BK48: 46082 | BL48: =BT47 -> 651254.98 | BM48: =BM47 -> 4604.6899 | BN48: =BM48-BP48 -> 670.0244 | BO48: =(BN48/BL48)*12 -> 0.012345845 | BP48: =BL48*($BK$3/12) -> 3934.6655 | BQ48: =(BP48/BL48)*12 -> 0.0725 | BR48: =BR47+BN48 -> 24415.047 | BS48: =BS47+BP48 -> 164377.24 | BT48: =BL48-BN48 -> 650584.95 | BU48: =BR48+BS48 -> 188792.29 | BW48: 41 | BX48: 46082 | BY48: =CG47 -> 650154.36 | BZ48: =BZ47 -> 4490.7918 | CA48: =BZ48-CC48 -> 698.22473 | CB48: =(CA48/BY48)*12 -> 0.012887242 | CC48: =BY48*($BX$3/12) -> 3792.5671 | CD48: =(CC48/BY48)*12 -> 0.07 | CE48: =CE47+CA48 -> 25543.863 | CF48: =CF47+CC48 -> 158578.6 | CG48: =BY48-CA48 -> 649456.14 | CH48: =CE48+CF48 -> 184122.47
J49: 42 | K49: 46113 | L49: =T48 -> 654694.29 | M49: =$L$8/((($N$4)-1)/($N$3*$N$4)) -> 5071.0496 | N49: =M49-P49 -> 570.02635 | O49: =(N49/L49)*12 -> 0.010448107 | P49: =L49*($K$3/12) -> 4501.0232 | Q49: =(P49/L49)*12 -> 0.0825 | R49: =R48+N49 -> 20875.738 | S49: =S48+P49 -> 192108.34 | T49: =L49-N49 -> 654124.26 | U49: =R49+S49 -> 212984.08 | W49: 42 | X49: 46113 | Y49: =AG48 -> 653725.87 | Z49: =Z48 -> 4952.9109 | AA49: =Z49-AC49 -> 594.73838 | AB49: =(AA49/Y49)*12 -> 0.010917207 | AC49: =Y49*($X$3/12) -> 4358.1725 | AD49: =(AC49/Y49)*12 -> 0.08 | AE49: =AE48+AA49 -> 21868.864 | AF49: =AF48+AC49 -> 186153.39 | AG49: =Y49-AA49 -> 653131.14 | AH49: =AE49+AF49 -> 208022.26 | AJ49: 42 | AK49: 46113 | AL49: =AT48 -> 652718.84 | AM49: =AM48 -> 4835.7827 | AN49: =AM49-AP49 -> 620.30679 | AO49: =(AN49/AL49)*12 -> 0.011404116 | AP49: =AL49*($AK$3/12) -> 4215.4759 | AQ49: =(AP49/AL49)*12 -> 0.0775 | AR49: =AR48+AN49 -> 22901.463 | AS49: =AS48+AP49 -> 180201.41 | AT49: =AL49-AN49 -> 652098.54 | AU49: =AR49+AS49 -> 203102.87 | AW49: 42 | AX49: 46113 | AY49: =BG48 -> 651672.2 | AZ49: =AZ48 -> 4719.6979 | BA49: =AZ49-BC49 -> 646.74669 | BB49: =(BA49/AY49)*12 -> 0.011909301 | BC49: =AY49*($AX$3/12) -> 4072.9512 | BD49: =(BC49/AY49)*12 -> 0.075 | BE49: =BE48+BA49 -> 23974.548 | BF49: =BF48+BC49 -> 174252.76 | BG49: =AY49-BA49 -> 651025.45 | BH49: =BE49+BF49 -> 198227.31 | BJ49: 42 | BK49: 46113 | BL49: =BT48 -> 650584.95 | BM49: =BM48 -> 4604.6899 | BN49: =BM49-BP49 -> 674.07247 | BO49: =(BN49/BL49)*12 -> 0.012433226 | BP49: =BL49*($BK$3/12) -> 3930.6174 | BQ49: =(BP49/BL49)*12 -> 0.0725 | BR49: =BR48+BN49 -> 25089.119 | BS49: =BS48+BP49 -> 168307.86 | BT49: =BL49-BN49 -> 649910.88 | BU49: =BR49+BS49 -> 193396.98 | BW49: 42 | BX49: 46113 | BY49: =CG48 -> 649456.14 | BZ49: =BZ48 -> 4490.7918 | CA49: =BZ49-CC49 -> 702.29771 | CB49: =(CA49/BY49)*12 -> 0.012976354 | CC49: =BY49*($BX$3/12) -> 3788.4941 | CD49: =(CC49/BY49)*12 -> 0.07 | CE49: =CE48+CA49 -> 26246.161 | CF49: =CF48+CC49 -> 162367.1 | CG49: =BY49-CA49 -> 648753.84 | CH49: =CE49+CF49 -> 188613.26
J50: 43 | K50: 46143 | L50: =T49 -> 654124.26 | M50: =$L$8/((($N$4)-1)/($N$3*$N$4)) -> 5071.0496 | N50: =M50-P50 -> 573.94528 | O50: =(N50/L50)*12 -> 0.010529105 | P50: =L50*($K$3/12) -> 4497.1043 | Q50: =(P50/L50)*12 -> 0.0825 | R50: =R49+N50 -> 21449.684 | S50: =S49+P50 -> 196605.45 | T50: =L50-N50 -> 653550.32 | U50: =R50+S50 -> 218055.13 | W50: 43 | X50: 46143 | Y50: =AG49 -> 653131.14 | Z50: =Z49 -> 4952.9109 | AA50: =Z50-AC50 -> 598.7033 | AB50: =(AA50/Y50)*12 -> 0.010999996 | AC50: =Y50*($X$3/12) -> 4354.2076 | AD50: =(AC50/Y50)*12 -> 0.08 | AE50: =AE49+AA50 -> 22467.568 | AF50: =AF49+AC50 -> 190507.6 | AG50: =Y50-AA50 -> 652532.43 | AH50: =AE50+AF50 -> 212975.17 | AJ50: 43 | AK50: 46143 | AL50: =AT49 -> 652098.54 | AM50: =AM49 -> 4835.7827 | AN50: =AM50-AP50 -> 624.31294 | AO50: =(AN50/AL50)*12 -> 0.011488686 | AP50: =AL50*($AK$3/12) -> 4211.4697 | AQ50: =(AP50/AL50)*12 -> 0.0775 | AR50: =AR49+AN50 -> 23525.776 | AS50: =AS49+AP50 -> 184412.88 | AT50: =AL50-AN50 -> 651474.22 | AU50: =AR50+AS50 -> 207938.65 | AW50: 43 | AX50: 46143 | AY50: =BG49 -> 651025.45 | AZ50: =AZ49 -> 4719.6979 | BA50: =AZ50-BC50 -> 650.78886 | BB50: =(BA50/AY50)*12 -> 0.011995639 | BC50: =AY50*($AX$3/12) -> 4068.9091 | BD50: =(BC50/AY50)*12 -> 0.075 | BE50: =BE49+BA50 -> 24625.337 | BF50: =BF49+BC50 -> 178321.67 | BG50: =AY50-BA50 -> 650374.66 | BH50: =BE50+BF50 -> 202947.01 | BJ50: 43 | BK50: 46143 | BL50: =BT49 -> 649910.88 | BM50: =BM49 -> 4604.6899 | BN50: =BM50-BP50 -> 678.14499 | BO50: =(BN50/BL50)*12 -> 0.012521317 | BP50: =BL50*($BK$3/12) -> 3926.5449 | BQ50: =(BP50/BL50)*12 -> 0.0725 | BR50: =BR49+BN50 -> 25767.264 | BS50: =BS49+BP50 -> 172234.4 | BT50: =BL50-BN50 -> 649232.74 | BU50: =BR50+BS50 -> 198001.67 | BW50: 43 | BX50: 46143 | BY50: =CG49 -> 648753.84 | BZ50: =BZ49 -> 4490.7918 | CA50: =BZ50-CC50 -> 706.39445 | CB50: =(CA50/BY50)*12 -> 0.013066178 | CC50: =BY50*($BX$3/12) -> 3784.3974 | CD50: =(CC50/BY50)*12 -> 0.07 | CE50: =CE49+CA50 -> 26952.555 | CF50: =CF49+CC50 -> 166151.49 | CG50: =BY50-CA50 -> 648047.44 | CH50: =CE50+CF50 -> 193104.05
J51: 44 | K51: 46174 | L51: =T50 -> 653550.32 | M51: =$L$8/((($N$4)-1)/($N$3*$N$4)) -> 5071.0496 | N51: =M51-P51 -> 577.89115 | O51: =(N51/L51)*12 -> 0.010610803 | P51: =L51*($K$3/12) -> 4493.1584 | Q51: =(P51/L51)*12 -> 0.0825 | R51: =R50+N51 -> 22027.575 | S51: =S50+P51 -> 201098.61 | T51: =L51-N51 -> 652972.43 | U51: =R51+S51 -> 223126.18 | W51: 44 | X51: 46174 | Y51: =AG50 -> 652532.43 | Z51: =Z50 -> 4952.9109 | AA51: =Z51-AC51 -> 602.69466 | AB51: =(AA51/Y51)*12 -> 0.011083489 | AC51: =Y51*($X$3/12) -> 4350.2162 | AD51: =(AC51/Y51)*12 -> 0.08 | AE51: =AE50+AA51 -> 23070.262 | AF51: =AF50+AC51 -> 194857.82 | AG51: =Y51-AA51 -> 651929.74 | AH51: =AE51+AF51 -> 217928.08 | AJ51: 44 | AK51: 46174 | AL51: =AT50 -> 651474.22 | AM51: =AM50 -> 4835.7827 | AN51: =AM51-AP51 -> 628.34496 | AO51: =(AN51/AL51)*12 -> 0.011573965 | AP51: =AL51*($AK$3/12) -> 4207.4377 | AQ51: =(AP51/AL51)*12 -> 0.0775 | AR51: =AR50+AN51 -> 24154.121 | AS51: =AS50+AP51 -> 188620.32 | AT51: =AL51-AN51 -> 650845.88 | AU51: =AR51+AS51 -> 212774.44 | AW51: 44 | AX51: 46174 | AY51: =BG50 -> 650374.66 | AZ51: =AZ50 -> 4719.6979 | BA51: =AZ51-BC51 -> 654.85629 | BB51: =(BA51/AY51)*12 -> 0.01208269 | BC51: =AY51*($AX$3/12) -> 4064.8416 | BD51: =(BC51/AY51)*12 -> 0.075 | BE51: =BE50+BA51 -> 25280.194 | BF51: =BF50+BC51 -> 182386.52 | BG51: =AY51-BA51 -> 649719.81 | BH51: =BE51+BF51 -> 207666.71 | BJ51: 44 | BK51: 46174 | BL51: =BT50 -> 649232.74 | BM51: =BM50 -> 4604.6899 | BN51: =BM51-BP51 -> 682.24211 | BO51: =(BN51/BL51)*12 -> 0.012610124 | BP51: =BL51*($BK$3/12) -> 3922.4478 | BQ51: =(BP51/BL51)*12 -> 0.0725 | BR51: =BR50+BN51 -> 26449.506 | BS51: =BS50+BP51 -> 176156.85 | BT51: =BL51-BN51 -> 648550.49 | BU51: =BR51+BS51 -> 202606.36 | BW51: 44 | BX51: 46174 | BY51: =CG50 -> 648047.44 | BZ51: =BZ50 -> 4490.7918 | CA51: =BZ51-CC51 -> 710.51508 | CB51: =(CA51/BY51)*12 -> 0.013156723 | CC51: =BY51*($BX$3/12) -> 3780.2768 | CD51: =(CC51/BY51)*12 -> 0.07 | CE51: =CE50+CA51 -> 27663.071 | CF51: =CF50+CC51 -> 169931.77 | CG51: =BY51-CA51 -> 647336.93 | CH51: =CE51+CF51 -> 197594.84
J52: 45 | K52: 46204 | L52: =T51 -> 652972.43 | M52: =$L$8/((($N$4)-1)/($N$3*$N$4)) -> 5071.0496 | N52: =M52-P52 -> 581.86415 | O52: =(N52/L52)*12 -> 0.010693208 | P52: =L52*($K$3/12) -> 4489.1854 | Q52: =(P52/L52)*12 -> 0.0825 | R52: =R51+N52 -> 22609.439 | S52: =S51+P52 -> 205587.79 | T52: =L52-N52 -> 652390.56 | U52: =R52+S52 -> 228197.23 | W52: 45 | X52: 46204 | Y52: =AG51 -> 651929.74 | Z52: =Z51 -> 4952.9109 | AA52: =Z52-AC52 -> 606.71262 | AB52: =(AA52/Y52)*12 -> 0.011167693 | AC52: =Y52*($X$3/12) -> 4346.1983 | AD52: =(AC52/Y52)*12 -> 0.08 | AE52: =AE51+AA52 -> 23676.975 | AF52: =AF51+AC52 -> 199204.01 | AG52: =Y52-AA52 -> 651323.03 | AH52: =AE52+AF52 -> 222880.99 | AJ52: 45 | AK52: 46204 | AL52: =AT51 -> 650845.88 | AM52: =AM51 -> 4835.7827 | AN52: =AM52-AP52 -> 632.40302 | AO52: =(AN52/AL52)*12 -> 0.011659959 | AP52: =AL52*($AK$3/12) -> 4203.3796 | AQ52: =(AP52/AL52)*12 -> 0.0775 | AR52: =AR51+AN52 -> 24786.524 | AS52: =AS51+AP52 -> 192823.7 | AT52: =AL52-AN52 -> 650213.48 | AU52: =AR52+AS52 -> 217610.22 | AW52: 45 | AX52: 46204 | AY52: =BG51 -> 649719.81 | AZ52: =AZ51 -> 4719.6979 | BA52: =AZ52-BC52 -> 658.94914 | BB52: =(BA52/AY52)*12 -> 0.012170461 | BC52: =AY52*($AX$3/12) -> 4060.7488 | BD52: =(BC52/AY52)*12 -> 0.075 | BE52: =BE51+BA52 -> 25939.143 | BF52: =BF51+BC52 -> 186447.26 | BG52: =AY52-BA52 -> 649060.86 | BH52: =BE52+BF52 -> 212386.41 | BJ52: 45 | BK52: 46204 | BL52: =BT51 -> 648550.49 | BM52: =BM51 -> 4604.6899 | BN52: =BM52-BP52 -> 686.36399 | BO52: =(BN52/BL52)*12 -> 0.012699656 | BP52: =BL52*($BK$3/12) -> 3918.3259 | BQ52: =(BP52/BL52)*12 -> 0.0725 | BR52: =BR51+BN52 -> 27135.87 | BS52: =BS51+BP52 -> 180075.17 | BT52: =BL52-BN52 -> 647864.13 | BU52: =BR52+BS52 -> 207211.05 | BW52: 45 | BX52: 46204 | BY52: =CG51 -> 647336.93 | BZ52: =BZ51 -> 4490.7918 | CA52: =BZ52-CC52 -> 714.65975 | CB52: =(CA52/BY52)*12 -> 0.013247996 | CC52: =BY52*($BX$3/12) -> 3776.1321 | CD52: =(CC52/BY52)*12 -> 0.07 | CE52: =CE51+CA52 -> 28377.73 | CF52: =CF51+CC52 -> 173707.9 | CG52: =BY52-CA52 -> 646622.27 | CH52: =CE52+CF52 -> 202085.63
... J342: 335 | K342: 55032 | L342: =T341 -> 120357.85 | M342: =$L$8/((($N$4)-1)/($N$3*$N$4)) -> 5071.0496 | N342: =M342-P342 -> 4243.5894 | O342: =(N342/L342)*12 -> 0.42309724 | P342: =L342*($K$3/12) -> 827.46019 | Q342: =(P342/L342)*12 -> 0.0825 | R342: =R341+N342 -> 558885.74 | S342: =S341+P342 -> 1139915.9 | T342: =L342-N342 -> 116114.26 | U342: =R342+S342 -> 1698801.6 | W342: 335 | X342: 55032 | Y342: =AG341 -> 117873.51 | Z342: =Z341 -> 4952.9109 | AA342: =Z342-AC342 -> 4167.0875 | AB342: =(AA342/Y342)*12 -> 0.42422637 | AC342: =Y342*($X$3/12) -> 785.82338 | AD342: =(AC342/Y342)*12 -> 0.08 | AE342: =AE341+AA342 -> 561293.58 | AF342: =AF341+AC342 -> 1097931.6 | AG342: =Y342-AA342 -> 113706.42 | AH342: =AE342+AF342 -> 1659225.1 | AJ342: 335 | AK342: 55032 | AL342: =AT341 -> 115399.23 | AM342: =AM341 -> 4835.7827 | AN342: =AM342-AP342 -> 4090.496 | AO342: =(AN342/AL342)*12 -> 0.42535772 | AP342: =AL342*($AK$3/12) -> 745.28667 | AQ342: =(AP342/AL342)*12 -> 0.0775 | AR342: =AR341+AN342 -> 563691.27 | AS342: =AS341+AP342 -> 1056295.9 | AT342: =AL342-AN342 -> 111308.73 | AU342: =AR342+AS342 -> 1619987.2 | AW342: 335 | AX342: 55032 | AY342: =BG341 -> 112935.91 | AZ342: =AZ341 -> 4719.6979 | BA342: =AZ342-BC342 -> 4013.8485 | BB342: =(BA342/AY342)*12 -> 0.42649129 | BC342: =AY342*($AX$3/12) -> 705.84943 | BD342: =(BC342/AY342)*12 -> 0.075 | BE342: =BE341+BA342 -> 566077.94 | BF342: =BF341+BC342 -> 1015020.9 | BG342: =AY342-BA342 -> 108922.06 | BH342: =BE342+BF342 -> 1581098.8 | BJ342: 335 | BK342: 55032 | BL342: =BT341 -> 110484.47 | BM342: =BM341 -> 4604.6899 | BN342: =BM342-BP342 -> 3937.1795 | BO342: =(BN342/BL342)*12 -> 0.4276271 | BP342: =BL342*($BK$3/12) -> 667.51036 | BQ342: =(BP342/BL342)*12 -> 0.0725 | BR342: =BR341+BN342 -> 568452.71 | BS342: =BS341+BP342 -> 974118.41 | BT342: =BL342-BN342 -> 106547.29 | BU342: =BR342+BS342 -> 1542571.1 | BW342: 335 | BX342: 55032 | BY342: =CG341 -> 108045.85 | BZ342: =BZ341 -> 4490.7918 | CA342: =BZ342-CC342 -> 3860.5244 | CB342: =(CA342/BY342)*12 -> 0.42876513 | CC342: =BY342*($BX$3/12) -> 630.26746 | CD342: =(CC342/BY342)*12 -> 0.07 | CE342: =CE341+CA342 -> 570814.67 | CF342: =CF341+CC342 -> 933600.59 | CG342: =BY342-CA342 -> 104185.33 | CH342: =CE342+CF342 -> 1504415.3
J343: =J342+1 -> 336 | L343: =T342 -> 116114.26 | M343: =$L$8/((($N$4)-1)/($N$3*$N$4)) -> 5071.0496 | N343: =M343-P343 -> 4272.7641 | O343: =(N343/L343)*12 -> 0.44157514 | P343: =L343*($K$3/12) -> 798.28551 | Q343: =(P343/L343)*12 -> 0.0825 | R343: =R342+N343 -> 563158.51 | S343: =S342+P343 -> 1140714.2 | T343: =L343-N343 -> 111841.49 | U343: =R343+S343 -> 1703872.7 | W343: =W342+1 -> 336 | Y343: =AG342 -> 113706.42 | Z343: =Z342 -> 4952.9109 | AA343: =Z343-AC343 -> 4194.8681 | AB343: =(AA343/Y343)*12 -> 0.44270514 | AC343: =Y343*($X$3/12) -> 758.0428 | AD343: =(AC343/Y343)*12 -> 0.08 | AE343: =AE342+AA343 -> 565488.45 | AF343: =AF342+AC343 -> 1098689.6 | AG343: =Y343-AA343 -> 109511.55 | AH343: =AE343+AF343 -> 1664178.1 | AJ343: =AJ342+1 -> 336 | AL343: =AT342 -> 111308.73 | AM343: =AM342 -> 4835.7827 | AN343: =AM343-AP343 -> 4116.9138 | AO343: =(AN343/AL343)*12 -> 0.44383729 | AP343: =AL343*($AK$3/12) -> 718.86889 | AQ343: =(AP343/AL343)*12 -> 0.0775 | AR343: =AR342+AN343 -> 567808.18 | AS343: =AS342+AP343 -> 1057014.8 | AT343: =AL343-AN343 -> 107191.82 | AU343: =AR343+AS343 -> 1624823 | AW343: =AW342+1 -> 336 | AY343: =BG342 -> 108922.06 | AZ343: =AZ342 -> 4719.6979 | BA343: =AZ343-BC343 -> 4038.9351 | BB343: =(BA343/AY343)*12 -> 0.44497157 | BC343: =AY343*($AX$3/12) -> 680.76288 | BD343: =(BC343/AY343)*12 -> 0.075 | BE343: =BE342+BA343 -> 570116.87 | BF343: =BF342+BC343 -> 1015701.6 | BG343: =AY343-BA343 -> 104883.13 | BH343: =BE343+BF343 -> 1585818.5 | BJ343: =BJ342+1 -> 336 | BL343: =BT342 -> 106547.29 | BM343: =BM342 -> 4604.6899 | BN343: =BM343-BP343 -> 3960.9667 | BO343: =(BN343/BL343)*12 -> 0.446108 | BP343: =BL343*($BK$3/12) -> 643.72323 | BQ343: =(BP343/BL343)*12 -> 0.0725 | BR343: =BR342+BN343 -> 572413.67 | BS343: =BS342+BP343 -> 974762.13 | BT343: =BL343-BN343 -> 102586.33 | BU343: =BR343+BS343 -> 1547175.8 | BW343: =BW342+1 -> 336 | BY343: =CG342 -> 104185.33 | BZ343: =BZ342 -> 4490.7918 | CA343: =BZ343-CC343 -> 3883.0441 | CB343: =(CA343/BY343)*12 -> 0.44724657 | CC343: =BY343*($BX$3/12) -> 607.74773 | CD343: =(CC343/BY343)*12 -> 0.07 | CE343: =CE342+CA343 -> 574697.72 | CF343: =CF342+CC343 -> 934208.34 | CG343: =BY343-CA343 -> 100302.28 | CH343: =CE343+CF343 -> 1508906.1
J344: =J343+1 -> 337 | L344: =T343 -> 111841.49 | M344: =$L$8/((($N$4)-1)/($N$3*$N$4)) -> 5071.0496 | N344: =M344-P344 -> 4302.1393 | O344: =(N344/L344)*12 -> 0.46159677 | P344: =L344*($K$3/12) -> 768.91026 | Q344: =(P344/L344)*12 -> 0.0825 | R344: =R343+N344 -> 567460.65 | S344: =S343+P344 -> 1141483.1 | T344: =L344-N344 -> 107539.35 | U344: =R344+S344 -> 1708943.7 | W344: =W343+1 -> 337 | Y344: =AG343 -> 109511.55 | Z344: =Z343 -> 4952.9109 | AA344: =Z344-AC344 -> 4222.8339 | AB344: =(AA344/Y344)*12 -> 0.4627275 | AC344: =Y344*($X$3/12) -> 730.07701 | AD344: =(AC344/Y344)*12 -> 0.08 | AE344: =AE343+AA344 -> 569711.28 | AF344: =AF343+AC344 -> 1099419.7 | AG344: =Y344-AA344 -> 105288.72 | AH344: =AE344+AF344 -> 1669131 | AJ344: =AJ343+1 -> 337 | AL344: =AT343 -> 107191.82 | AM344: =AM343 -> 4835.7827 | AN344: =AM344-AP344 -> 4143.5022 | AO344: =(AN344/AL344)*12 -> 0.46386028 | AP344: =AL344*($AK$3/12) -> 692.28049 | AQ344: =(AP344/AL344)*12 -> 0.0775 | AR344: =AR343+AN344 -> 571951.68 | AS344: =AS343+AP344 -> 1057707.1 | AT344: =AL344-AN344 -> 103048.32 | AU344: =AR344+AS344 -> 1629658.8 | AW344: =AW343+1 -> 337 | AY344: =BG343 -> 104883.13 | AZ344: =AZ343 -> 4719.6979 | BA344: =AZ344-BC344 -> 4064.1784 | BB344: =(BA344/AY344)*12 -> 0.46499511 | BC344: =AY344*($AX$3/12) -> 655.51954 | BD344: =(BC344/AY344)*12 -> 0.075 | BE344: =BE343+BA344 -> 574181.05 | BF344: =BF343+BC344 -> 1016357.2 | BG344: =AY344-BA344 -> 100818.95 | BH344: =BE344+BF344 -> 1590538.2 | BJ344: =BJ343+1 -> 337 | BL344: =BT343 -> 102586.33 | BM344: =BM343 -> 4604.6899 | BN344: =BM344-BP344 -> 3984.8975 | BO344: =(BN344/BL344)*12 -> 0.466132 | BP344: =BL344*($BK$3/12) -> 619.79239 | BQ344: =(BP344/BL344)*12 -> 0.0725 | BR344: =BR343+BN344 -> 576398.57 | BS344: =BS343+BP344 -> 975381.92 | BT344: =BL344-BN344 -> 98601.429 | BU344: =BR344+BS344 -> 1551780.5 | BW344: =BW343+1 -> 337 | BY344: =CG343 -> 100302.28 | BZ344: =BZ343 -> 4490.7918 | CA344: =BZ344-CC344 -> 3905.6952 | CB344: =(CA344/BY344)*12 -> 0.46727095 | CC344: =BY344*($BX$3/12) -> 585.09664 | CD344: =(CC344/BY344)*12 -> 0.07 | CE344: =CE343+CA344 -> 578603.41 | CF344: =CF343+CC344 -> 934793.44 | CG344: =BY344-CA344 -> 96396.587 | CH344: =CE344+CF344 -> 1513396.9
J345: =J344+1 -> 338 | L345: =T344 -> 107539.35 | M345: =$L$8/((($N$4)-1)/($N$3*$N$4)) -> 5071.0496 | N345: =M345-P345 -> 4331.7165 | O345: =(N345/L345)*12 -> 0.4833635 | P345: =L345*($K$3/12) -> 739.33305 | Q345: =(P345/L345)*12 -> 0.0825 | R345: =R344+N345 -> 571792.36 | S345: =S344+P345 -> 1142222.4 | T345: =L345-N345 -> 103207.64 | U345: =R345+S345 -> 1714014.8 | W345: =W344+1 -> 338 | Y345: =AG344 -> 105288.72 | Z345: =Z344 -> 4952.9109 | AA345: =Z345-AC345 -> 4250.9861 | AB345: =(AA345/Y345)*12 -> 0.48449477 | AC345: =Y345*($X$3/12) -> 701.92479 | AD345: =(AC345/Y345)*12 -> 0.08 | AE345: =AE344+AA345 -> 573962.27 | AF345: =AF344+AC345 -> 1100121.6 | AG345: =Y345-AA345 -> 101037.73 | AH345: =AE345+AF345 -> 1674083.9 | AJ345: =AJ344+1 -> 338 | AL345: =AT344 -> 103048.32 | AM345: =AM344 -> 4835.7827 | AN345: =AM345-AP345 -> 4170.2623 | AO345: =(AN345/AL345)*12 -> 0.485628 | AP345: =AL345*($AK$3/12) -> 665.52037 | AQ345: =(AP345/AL345)*12 -> 0.0775 | AR345: =AR344+AN345 -> 576121.95 | AS345: =AS344+AP345 -> 1058372.6 | AT345: =AL345-AN345 -> 98878.053 | AU345: =AR345+AS345 -> 1634494.5 | AW345: =AW344+1 -> 338 | AY345: =BG344 -> 100818.95 | AZ345: =AZ344 -> 4719.6979 | BA345: =AZ345-BC345 -> 4089.5795 | BB345: =(BA345/AY345)*12 -> 0.48676321 | BC345: =AY345*($AX$3/12) -> 630.11842 | BD345: =(BC345/AY345)*12 -> 0.075 | BE345: =BE344+BA345 -> 578270.63 | BF345: =BF344+BC345 -> 1016987.3 | BG345: =AY345-BA345 -> 96729.368 | BH345: =BE345+BF345 -> 1595257.9 | BJ345: =BJ344+1 -> 338 | BL345: =BT344 -> 98601.429 | BM345: =BM344 -> 4604.6899 | BN345: =BM345-BP345 -> 4008.9729 | BO345: =(BN345/BL345)*12 -> 0.48790038 | BP345: =BL345*($BK$3/12) -> 595.71697 | BQ345: =(BP345/BL345)*12 -> 0.0725 | BR345: =BR344+BN345 -> 580407.54 | BS345: =BS344+BP345 -> 975977.64 | BT345: =BL345-BN345 -> 94592.457 | BU345: =BR345+BS345 -> 1556385.2 | BW345: =BW344+1 -> 338 | BY345: =CG344 -> 96396.587 | BZ345: =BZ344 -> 4490.7918 | CA345: =BZ345-CC345 -> 3928.4784 | CB345: =(CA345/BY345)*12 -> 0.48903953 | CC345: =BY345*($BX$3/12) -> 562.31342 | CD345: =(CC345/BY345)*12 -> 0.07 | CE345: =CE344+CA345 -> 582531.89 | CF345: =CF344+CC345 -> 935355.75 | CG345: =BY345-CA345 -> 92468.108 | CH345: =CE345+CF345 -> 1517887.6
J346: =J345+1 -> 339 | L346: =T345 -> 103207.64 | M346: =$L$8/((($N$4)-1)/($N$3*$N$4)) -> 5071.0496 | N346: =M346-P346 -> 4361.4971 | O346: =(N346/L346)*12 -> 0.5071133 | P346: =L346*($K$3/12) -> 709.5525 | Q346: =(P346/L346)*12 -> 0.0825 | R346: =R345+N346 -> 576153.86 | S346: =S345+P346 -> 1142931.9 | T346: =L346-N346 -> 98846.139 | U346: =R346+S346 -> 1719085.8 | W346: =W345+1 -> 339 | Y346: =AG345 -> 101037.73 | Z346: =Z345 -> 4952.9109 | AA346: =Z346-AC346 -> 4279.326 | AB346: =(AA346/Y346)*12 -> 0.5082449 | AC346: =Y346*($X$3/12) -> 673.58488 | AD346: =(AC346/Y346)*12 -> 0.08 | AE346: =AE345+AA346 -> 578241.59 | AF346: =AF345+AC346 -> 1100795.2 | AG346: =Y346-AA346 -> 96758.406 | AH346: =AE346+AF346 -> 1679036.8 | AJ346: =AJ345+1 -> 339 | AL346: =AT345 -> 98878.053 | AM346: =AM345 -> 4835.7827 | AN346: =AM346-AP346 -> 4197.1952 | AO346: =(AN346/AL346)*12 -> 0.50937838 | AP346: =AL346*($AK$3/12) -> 638.58742 | AQ346: =(AP346/AL346)*12 -> 0.0775 | AR346: =AR345+AN346 -> 580319.14 | AS346: =AS345+AP346 -> 1059011.2 | AT346: =AL346-AN346 -> 94680.858 | AU346: =AR346+AS346 -> 1639330.3 | AW346: =AW345+1 -> 339 | AY346: =BG345 -> 96729.368 | AZ346: =AZ345 -> 4719.6979 | BA346: =AZ346-BC346 -> 4115.1394 | BB346: =(BA346/AY346)*12 -> 0.51051375 | BC346: =AY346*($AX$3/12) -> 604.55855 | BD346: =(BC346/AY346)*12 -> 0.075 | BE346: =BE345+BA346 -> 582385.77 | BF346: =BF345+BC346 -> 1017591.8 | BG346: =AY346-BA346 -> 92614.228 | BH346: =BE346+BF346 -> 1599977.6 | BJ346: =BJ345+1 -> 339 | BL346: =BT345 -> 94592.457 | BM346: =BM345 -> 4604.6899 | BN346: =BM346-BP346 -> 4033.1938 | BO346: =(BN346/BL346)*12 -> 0.51165101 | BP346: =BL346*($BK$3/12) -> 571.49609 | BQ346: =(BP346/BL346)*12 -> 0.0725 | BR346: =BR345+BN346 -> 584440.74 | BS346: =BS345+BP346 -> 976549.14 | BT346: =BL346-BN346 -> 90559.263 | BU346: =BR346+BS346 -> 1560989.9 | BW346: =BW345+1 -> 339 | BY346: =CG345 -> 92468.108 | BZ346: =BZ345 -> 4490.7918 | CA346: =BZ346-CC346 -> 3951.3945 | CB346: =(CA346/BY346)*12 -> 0.51279014 | CC346: =BY346*($BX$3/12) -> 539.3973 | CD346: =(CC346/BY346)*12 -> 0.07 | CE346: =CE345+CA346 -> 586483.29 | CF346: =CF345+CC346 -> 935895.15 | CG346: =BY346-CA346 -> 88516.714 | CH346: =CE346+CF346 -> 1522378.4
J347: =J346+1 -> 340 | L347: =T346 -> 98846.139 | M347: =$L$8/((($N$4)-1)/($N$3*$N$4)) -> 5071.0496 | N347: =M347-P347 -> 4391.4824 | O347: =(N347/L347)*12 -> 0.53312945 | P347: =L347*($K$3/12) -> 679.56721 | Q347: =(P347/L347)*12 -> 0.0825 | R347: =R346+N347 -> 580545.34 | S347: =S346+P347 -> 1143611.5 | T347: =L347-N347 -> 94454.657 | U347: =R347+S347 -> 1724156.9 | W347: =W346+1 -> 340 | Y347: =AG346 -> 96758.406 | Z347: =Z346 -> 4952.9109 | AA347: =Z347-AC347 -> 4307.8548 | AB347: =(AA347/Y347)*12 -> 0.53426116 | AC347: =Y347*($X$3/12) -> 645.05604 | AD347: =(AC347/Y347)*12 -> 0.08 | AE347: =AE346+AA347 -> 582549.45 | AF347: =AF346+AC347 -> 1101440.2 | AG347: =Y347-AA347 -> 92450.551 | AH347: =AE347+AF347 -> 1683989.7 | AJ347: =AJ346+1 -> 340 | AL347: =AT346 -> 94680.858 | AM347: =AM346 -> 4835.7827 | AN347: =AM347-AP347 -> 4224.3021 | AO347: =(AN347/AL347)*12 -> 0.53539466 | AP347: =AL347*($AK$3/12) -> 611.48054 | AQ347: =(AP347/AL347)*12 -> 0.0775 | AR347: =AR346+AN347 -> 584543.44 | AS347: =AS346+AP347 -> 1059622.7 | AT347: =AL347-AN347 -> 90456.555 | AU347: =AR347+AS347 -> 1644166.1 | AW347: =AW346+1 -> 340 | AY347: =BG346 -> 92614.228 | AZ347: =AZ346 -> 4719.6979 | BA347: =AZ347-BC347 -> 4140.859 | BB347: =(BA347/AY347)*12 -> 0.53652996 | BC347: =AY347*($AX$3/12) -> 578.83893 | BD347: =(BC347/AY347)*12 -> 0.075 | BE347: =BE346+BA347 -> 586526.63 | BF347: =BF346+BC347 -> 1018170.7 | BG347: =AY347-BA347 -> 88473.369 | BH347: =BE347+BF347 -> 1604697.3 | BJ347: =BJ346+1 -> 340 | BL347: =BT346 -> 90559.263 | BM347: =BM346 -> 4604.6899 | BN347: =BM347-BP347 -> 4057.561 | BO347: =(BN347/BL347)*12 -> 0.53766706 | BP347: =BL347*($BK$3/12) -> 547.12888 | BQ347: =(BP347/BL347)*12 -> 0.0725 | BR347: =BR346+BN347 -> 588498.3 | BS347: =BS346+BP347 -> 977096.26 | BT347: =BL347-BN347 -> 86501.702 | BU347: =BR347+BS347 -> 1565594.6 | BW347: =BW346+1 -> 340 | BY347: =CG346 -> 88516.714 | BZ347: =BZ346 -> 4490.7918 | CA347: =BZ347-CC347 -> 3974.4443 | CB347: =(CA347/BY347)*12 -> 0.53880595 | CC347: =BY347*($BX$3/12) -> 516.3475 | CD347: =(CC347/BY347)*12 -> 0.07 | CE347: =CE346+CA347 -> 590457.73 | CF347: =CF346+CC347 -> 936411.5 | CG347: =BY347-CA347 -> 84542.269 | CH347: =CE347+CF347 -> 1526869.2
J348: =J347+1 -> 341 | L348: =T347 -> 94454.657 | M348: =$L$8/((($N$4)-1)/($N$3*$N$4)) -> 5071.0496 | N348: =M348-P348 -> 4421.6738 | O348: =(N348/L348)*12 -> 0.56175193 | P348: =L348*($K$3/12) -> 649.37577 | Q348: =(P348/L348)*12 -> 0.0825 | R348: =R347+N348 -> 584967.02 | S348: =S347+P348 -> 1144260.9 | T348: =L348-N348 -> 90032.983 | U348: =R348+S348 -> 1729227.9 | W348: =W347+1 -> 341 | Y348: =AG347 -> 92450.551 | Z348: =Z347 -> 4952.9109 | AA348: =Z348-AC348 -> 4336.5739 | AB348: =(AA348/Y348)*12 -> 0.56288346 | AC348: =Y348*($X$3/12) -> 616.33701 | AD348: =(AC348/Y348)*12 -> 0.08 | AE348: =AE347+AA348 -> 586886.02 | AF348: =AF347+AC348 -> 1102056.6 | AG348: =Y348-AA348 -> 88113.977 | AH348: =AE348+AF348 -> 1688942.6 | AJ348: =AJ347+1 -> 341 | AL348: =AT347 -> 90456.555 | AM348: =AM347 -> 4835.7827 | AN348: =AM348-AP348 -> 4251.5841 | AO348: =(AN348/AL348)*12 -> 0.56401671 | AP348: =AL348*($AK$3/12) -> 584.19859 | AQ348: =(AP348/AL348)*12 -> 0.0775 | AR348: =AR347+AN348 -> 588795.03 | AS348: =AS347+AP348 -> 1060206.9 | AT348: =AL348-AN348 -> 86204.971 | AU348: =AR348+AS348 -> 1649001.9 | AW348: =AW347+1 -> 341 | AY348: =BG347 -> 88473.369 | AZ348: =AZ347 -> 4719.6979 | BA348: =AZ348-BC348 -> 4166.7394 | BB348: =(BA348/AY348)*12 -> 0.56515167 | BC348: =AY348*($AX$3/12) -> 552.95856 | BD348: =(BC348/AY348)*12 -> 0.075 | BE348: =BE347+BA348 -> 590693.37 | BF348: =BF347+BC348 -> 1018723.6 | BG348: =AY348-BA348 -> 84306.63 | BH348: =BE348+BF348 -> 1609417 | BJ348: =BJ347+1 -> 341 | BL348: =BT347 -> 86501.702 | BM348: =BM347 -> 4604.6899 | BN348: =BM348-BP348 -> 4082.0754 | BO348: =(BN348/BL348)*12 -> 0.56628834 | BP348: =BL348*($BK$3/12) -> 522.61445 | BQ348: =(BP348/BL348)*12 -> 0.0725 | BR348: =BR347+BN348 -> 592580.37 | BS348: =BS347+BP348 -> 977618.88 | BT348: =BL348-BN348 -> 82419.626 | BU348: =BR348+BS348 -> 1570199.3 | BW348: =BW347+1 -> 341 | BY348: =CG347 -> 84542.269 | BZ348: =BZ347 -> 4490.7918 | CA348: =BZ348-CC348 -> 3997.6286 | CB348: =(CA348/BY348)*12 -> 0.56742673 | CC348: =BY348*($BX$3/12) -> 493.16324 | CD348: =(CC348/BY348)*12 -> 0.07 | CE348: =CE347+CA348 -> 594455.36 | CF348: =CF347+CC348 -> 936904.66 | CG348: =BY348-CA348 -> 80544.641 | CH348: =CE348+CF348 -> 1531360
J349: =J348+1 -> 342 | L349: =T348 -> 90032.983 | M349: =$L$8/((($N$4)-1)/($N$3*$N$4)) -> 5071.0496 | N349: =M349-P349 -> 4452.0728 | O349: =(N349/L349)*12 -> 0.59339224 | P349: =L349*($K$3/12) -> 618.97676 | Q349: =(P349/L349)*12 -> 0.0825 | R349: =R348+N349 -> 589419.09 | S349: =S348+P349 -> 1144879.9 | T349: =L349-N349 -> 85580.91 | U349: =R349+S349 -> 1734299 | W349: =W348+1 -> 342 | Y349: =AG348 -> 88113.977 | Z349: =Z348 -> 4952.9109 | AA349: =Z349-AC349 -> 4365.4844 | AB349: =(AA349/Y349)*12 -> 0.5945233 | AC349: =Y349*($X$3/12) -> 587.42651 | AD349: =(AC349/Y349)*12 -> 0.08 | AE349: =AE348+AA349 -> 591251.51 | AF349: =AF348+AC349 -> 1102644 | AG349: =Y349-AA349 -> 83748.493 | AH349: =AE349+AF349 -> 1693895.5 | AJ349: =AJ348+1 -> 342 | AL349: =AT348 -> 86204.971 | AM349: =AM348 -> 4835.7827 | AN349: =AM349-AP349 -> 4279.0422 | AO349: =(AN349/AL349)*12 -> 0.59565598 | AP349: =AL349*($AK$3/12) -> 556.74044 | AQ349: =(AP349/AL349)*12 -> 0.0775 | AR349: =AR348+AN349 -> 593074.07 | AS349: =AS348+AP349 -> 1060763.6 | AT349: =AL349-AN349 -> 81925.929 | AU349: =AR349+AS349 -> 1653837.7 | AW349: =AW348+1 -> 342 | AY349: =BG348 -> 84306.63 | AZ349: =AZ348 -> 4719.6979 | BA349: =AZ349-BC349 -> 4192.7815 | BB349: =(BA349/AY349)*12 -> 0.59679029 | BC349: =AY349*($AX$3/12) -> 526.91644 | BD349: =(BC349/AY349)*12 -> 0.075 | BE349: =BE348+BA349 -> 594886.15 | BF349: =BF348+BC349 -> 1019250.5 | BG349: =AY349-BA349 -> 80113.849 | BH349: =BE349+BF349 -> 1614136.7 | BJ349: =BJ348+1 -> 342 | BL349: =BT348 -> 82419.626 | BM349: =BM348 -> 4604.6899 | BN349: =BM349-BP349 -> 4106.738 | BO349: =(BN349/BL349)*12 -> 0.59792622 | BP349: =BL349*($BK$3/12) -> 497.95191 | BQ349: =(BP349/BL349)*12 -> 0.0725 | BR349: =BR348+BN349 -> 596687.11 | BS349: =BS348+BP349 -> 978116.83 | BT349: =BL349-BN349 -> 78312.888 | BU349: =BR349+BS349 -> 1574803.9 | BW349: =BW348+1 -> 342 | BY349: =CG348 -> 80544.641 | BZ349: =BZ348 -> 4490.7918 | CA349: =BZ349-CC349 -> 4020.9481 | CB349: =(CA349/BY349)*12 -> 0.59906379 | CC349: =BY349*($BX$3/12) -> 469.84374 | CD349: =(CC349/BY349)*12 -> 0.07 | CE349: =CE348+CA349 -> 598476.31 | CF349: =CF348+CC349 -> 937374.5 | CG349: =BY349-CA349 -> 76523.692 | CH349: =CE349+CF349 -> 1535850.8
J350: =J349+1 -> 343 | L350: =T349 -> 85580.91 | M350: =$L$8/((($N$4)-1)/($N$3*$N$4)) -> 5071.0496 | N350: =M350-P350 -> 4482.6808 | O350: =(N350/L350)*12 -> 0.62855337 | P350: =L350*($K$3/12) -> 588.36876 | Q350: =(P350/L350)*12 -> 0.0825 | R350: =R349+N350 -> 593901.77 | S350: =S349+P350 -> 1145468.2 | T350: =L350-N350 -> 81098.23 | U350: =R350+S350 -> 1739370 | W350: =W349+1 -> 343 | Y350: =AG349 -> 83748.493 | Z350: =Z349 -> 4952.9109 | AA350: =Z350-AC350 -> 4394.5876 | AB350: =(AA350/Y350)*12 -> 0.62968358 | AC350: =Y350*($X$3/12) -> 558.32329 | AD350: =(AC350/Y350)*12 -> 0.08 | AE350: =AE349+AA350 -> 595646.09 | AF350: =AF349+AC350 -> 1103202.3 | AG350: =Y350-AA350 -> 79353.905 | AH350: =AE350+AF350 -> 1698848.4 | AJ350: =AJ349+1 -> 343 | AL350: =AT349 -> 81925.929 | AM350: =AM349 -> 4835.7827 | AN350: =AM350-AP350 -> 4306.6777 | AO350: =(AN350/AL350)*12 -> 0.63081533 | AP350: =AL350*($AK$3/12) -> 529.10496 | AQ350: =(AP350/AL350)*12 -> 0.0775 | AR350: =AR349+AN350 -> 597380.75 | AS350: =AS349+AP350 -> 1061292.7 | AT350: =AL350-AN350 -> 77619.251 | AU350: =AR350+AS350 -> 1658673.5 | AW350: =AW349+1 -> 343 | AY350: =BG349 -> 80113.849 | AZ350: =AZ349 -> 4719.6979 | BA350: =AZ350-BC350 -> 4218.9864 | BB350: =(BA350/AY350)*12 -> 0.63194863 | BC350: =AY350*($AX$3/12) -> 500.71155 | BD350: =(BC350/AY350)*12 -> 0.075 | BE350: =BE349+BA350 -> 599105.14 | BF350: =BF349+BC350 -> 1019751.3 | BG350: =AY350-BA350 -> 75894.862 | BH350: =BE350+BF350 -> 1618856.4 | BJ350: =BJ349+1 -> 343 | BL350: =BT349 -> 78312.888 | BM350: =BM349 -> 4604.6899 | BN350: =BM350-BP350 -> 4131.5495 | BO350: =(BN350/BL350)*12 -> 0.63308346 | BP350: =BL350*($BK$3/12) -> 473.14037 | BQ350: =(BP350/BL350)*12 -> 0.0725 | BR350: =BR349+BN350 -> 600818.66 | BS350: =BS349+BP350 -> 978589.97 | BT350: =BL350-BN350 -> 74181.339 | BU350: =BR350+BS350 -> 1579408.6 | BW350: =BW349+1 -> 343 | BY350: =CG349 -> 76523.692 | BZ350: =BZ349 -> 4490.7918 | CA350: =BZ350-CC350 -> 4044.4036 | CB350: =(CA350/BY350)*12 -> 0.63421984 | CC350: =BY350*($BX$3/12) -> 446.38821 | CD350: =(CC350/BY350)*12 -> 0.07 | CE350: =CE349+CA350 -> 602520.71 | CF350: =CF349+CC350 -> 937820.89 | CG350: =BY350-CA350 -> 72479.289 | CH350: =CE350+CF350 -> 1540341.6
J351: =J350+1 -> 344 | L351: =T350 -> 81098.23 | M351: =$L$8/((($N$4)-1)/($N$3*$N$4)) -> 5071.0496 | N351: =M351-P351 -> 4513.4992 | O351: =(N351/L351)*12 -> 0.66785664 | P351: =L351*($K$3/12) -> 557.55033 | Q351: =(P351/L351)*12 -> 0.0825 | R351: =R350+N351 -> 598415.27 | S351: =S350+P351 -> 1146025.8 | T351: =L351-N351 -> 76584.73 | U351: =R351+S351 -> 1744441.1 | W351: =W350+1 -> 344 | Y351: =AG350 -> 79353.905 | Z351: =Z350 -> 4952.9109 | AA351: =Z351-AC351 -> 4423.8848 | AB351: =(AA351/Y351)*12 -> 0.66898558 | AC351: =Y351*($X$3/12) -> 529.02604 | AD351: =(AC351/Y351)*12 -> 0.08 | AE351: =AE350+AA351 -> 600069.98 | AF351: =AF350+AC351 -> 1103731.4 | AG351: =Y351-AA351 -> 74930.02 | AH351: =AE351+AF351 -> 1703801.3 | AJ351: =AJ350+1 -> 344 | AL351: =AT350 -> 77619.251 | AM351: =AM350 -> 4835.7827 | AN351: =AM351-AP351 -> 4334.4917 | AO351: =(AN351/AL351)*12 -> 0.67011597 | AP351: =AL351*($AK$3/12) -> 501.291 | AQ351: =(AP351/AL351)*12 -> 0.0775 | AR351: =AR350+AN351 -> 601715.24 | AS351: =AS350+AP351 -> 1061794 | AT351: =AL351-AN351 -> 73284.76 | AU351: =AR351+AS351 -> 1663509.2 | AW351: =AW350+1 -> 344 | AY351: =BG350 -> 75894.862 | AZ351: =AZ350 -> 4719.6979 | BA351: =AZ351-BC351 -> 4245.355 | BB351: =(BA351/AY351)*12 -> 0.67124782 | BC351: =AY351*($AX$3/12) -> 474.34289 | BD351: =(BC351/AY351)*12 -> 0.075 | BE351: =BE350+BA351 -> 603350.49 | BF351: =BF350+BC351 -> 1020225.6 | BG351: =AY351-BA351 -> 71649.507 | BH351: =BE351+BF351 -> 1623576.1 | BJ351: =BJ350+1 -> 344 | BL351: =BT350 -> 74181.339 | BM351: =BM350 -> 4604.6899 | BN351: =BM351-BP351 -> 4156.511 | BO351: =(BN351/BL351)*12 -> 0.67238112 | BP351: =BL351*($BK$3/12) -> 448.17892 | BQ351: =(BP351/BL351)*12 -> 0.0725 | BR351: =BR350+BN351 -> 604975.17 | BS351: =BS350+BP351 -> 979038.15 | BT351: =BL351-BN351 -> 70024.828 | BU351: =BR351+BS351 -> 1584013.3 | BW351: =BW350+1 -> 344 | BY351: =CG350 -> 72479.289 | BZ351: =BZ350 -> 4490.7918 | CA351: =BZ351-CC351 -> 4067.996 | CB351: =(CA351/BY351)*12 -> 0.67351588 | CC351: =BY351*($BX$3/12) -> 422.79585 | CD351: =(CC351/BY351)*12 -> 0.07 | CE351: =CE350+CA351 -> 606588.71 | CF351: =CF350+CC351 -> 938243.69 | CG351: =BY351-CA351 -> 68411.293 | CH351: =CE351+CF351 -> 1544832.4
J352: =J351+1 -> 345 | L352: =T351 -> 76584.73 | M352: =$L$8/((($N$4)-1)/($N$3*$N$4)) -> 5071.0496 | N352: =M352-P352 -> 4544.5296 | O352: =(N352/L352)*12 -> 0.71207869 | P352: =L352*($K$3/12) -> 526.52002 | Q352: =(P352/L352)*12 -> 0.0825 | R352: =R351+N352 -> 602959.8 | S352: =S351+P352 -> 1146552.3 | T352: =L352-N352 -> 72040.201 | U352: =R352+S352 -> 1749512.1 | W352: =W351+1 -> 345 | Y352: =AG351 -> 74930.02 | Z352: =Z351 -> 4952.9109 | AA352: =Z352-AC352 -> 4453.3774 | AB352: =(AA352/Y352)*12 -> 0.71320585 | AC352: =Y352*($X$3/12) -> 499.53347 | AD352: =(AC352/Y352)*12 -> 0.08 | AE352: =AE351+AA352 -> 604523.36 | AF352: =AF351+AC352 -> 1104230.9 | AG352: =Y352-AA352 -> 70476.643 | AH352: =AE352+AF352 -> 1708754.3 | AJ352: =AJ351+1 -> 345 | AL352: =AT351 -> 73284.76 | AM352: =AM351 -> 4835.7827 | AN352: =AM352-AP352 -> 4362.4853 | AO352: =(AN352/AL352)*12 -> 0.71433437 | AP352: =AL352*($AK$3/12) -> 473.29741 | AQ352: =(AP352/AL352)*12 -> 0.0775 | AR352: =AR351+AN352 -> 606077.73 | AS352: =AS351+AP352 -> 1062267.3 | AT352: =AL352-AN352 -> 68922.275 | AU352: =AR352+AS352 -> 1668345 | AW352: =AW351+1 -> 345 | AY352: =BG351 -> 71649.507 | AZ352: =AZ351 -> 4719.6979 | BA352: =AZ352-BC352 -> 4271.8885 | BB352: =(BA352/AY352)*12 -> 0.71546427 | BC352: =AY352*($AX$3/12) -> 447.80942 | BD352: =(BC352/AY352)*12 -> 0.075 | BE352: =BE351+BA352 -> 607622.38 | BF352: =BF351+BC352 -> 1020673.4 | BG352: =AY352-BA352 -> 67377.619 | BH352: =BE352+BF352 -> 1628295.8 | BJ352: =BJ351+1 -> 345 | BL352: =BT351 -> 70024.828 | BM352: =BM351 -> 4604.6899 | BN352: =BM352-BP352 -> 4181.6232 | BO352: =(BN352/BL352)*12 -> 0.71659553 | BP352: =BL352*($BK$3/12) -> 423.06667 | BQ352: =(BP352/BL352)*12 -> 0.0725 | BR352: =BR351+BN352 -> 609156.8 | BS352: =BS351+BP352 -> 979461.22 | BT352: =BL352-BN352 -> 65843.205 | BU352: =BR352+BS352 -> 1588618 | BW352: =BW351+1 -> 345 | BY352: =CG351 -> 68411.293 | BZ352: =BZ351 -> 4490.7918 | CA352: =BZ352-CC352 -> 4091.726 | CB352: =(CA352/BY352)*12 -> 0.71772816 | CC352: =BY352*($BX$3/12) -> 399.06588 | CD352: =(CC352/BY352)*12 -> 0.07 | CE352: =CE351+CA352 -> 610680.43 | CF352: =CF351+CC352 -> 938642.75 | CG352: =BY352-CA352 -> 64319.567 | CH352: =CE352+CF352 -> 1549323.2
J353: =J352+1 -> 346 | L353: =T352 -> 72040.201 | M353: =$L$8/((($N$4)-1)/($N$3*$N$4)) -> 5071.0496 | N353: =M353-P353 -> 4575.7732 | O353: =(N353/L353)*12 -> 0.76220329 | P353: =L353*($K$3/12) -> 495.27638 | Q353: =(P353/L353)*12 -> 0.0825 | R353: =R352+N353 -> 607535.57 | S353: =S352+P353 -> 1147047.6 | T353: =L353-N353 -> 67464.428 | U353: =R353+S353 -> 1754583.2 | W353: =W352+1 -> 346 | Y353: =AG352 -> 70476.643 | Z353: =Z352 -> 4952.9109 | AA353: =Z353-AC353 -> 4483.0666 | AB353: =(AA353/Y353)*12 -> 0.76332806 | AC353: =Y353*($X$3/12) -> 469.84429 | AD353: =(AC353/Y353)*12 -> 0.08 | AE353: =AE352+AA353 -> 609006.42 | AF353: =AF352+AC353 -> 1104700.7 | AG353: =Y353-AA353 -> 65993.576 | AH353: =AE353+AF353 -> 1713707.2 | AJ353: =AJ352+1 -> 346 | AL353: =AT352 -> 68922.275 | AM353: =AM352 -> 4835.7827 | AN353: =AM353-AP353 -> 4390.6596 | AO353: =(AN353/AL353)*12 -> 0.7644541 | AP353: =AL353*($AK$3/12) -> 445.12302 | AQ353: =(AP353/AL353)*12 -> 0.0775 | AR353: =AR352+AN353 -> 610468.39 | AS353: =AS352+AP353 -> 1062712.4 | AT353: =AL353-AN353 -> 64531.615 | AU353: =AR353+AS353 -> 1673180.8 | AW353: =AW352+1 -> 346 | AY353: =BG352 -> 67377.619 | AZ353: =AZ352 -> 4719.6979 | BA353: =AZ353-BC353 -> 4298.5878 | BB353: =(BA353/AY353)*12 -> 0.76558143 | BC353: =AY353*($AX$3/12) -> 421.11012 | BD353: =(BC353/AY353)*12 -> 0.075 | BE353: =BE352+BA353 -> 611920.97 | BF353: =BF352+BC353 -> 1021094.5 | BG353: =AY353-BA353 -> 63079.031 | BH353: =BE353+BF353 -> 1633015.5 | BJ353: =BJ352+1 -> 346 | BL353: =BT352 -> 65843.205 | BM353: =BM352 -> 4604.6899 | BN353: =BM353-BP353 -> 4206.8872 | BO353: =(BN353/BL353)*12 -> 0.76671004 | BP353: =BL353*($BK$3/12) -> 397.80269 | BQ353: =(BP353/BL353)*12 -> 0.0725 | BR353: =BR352+BN353 -> 613363.68 | BS353: =BS352+BP353 -> 979859.02 | BT353: =BL353-BN353 -> 61636.317 | BU353: =BR353+BS353 -> 1593222.7 | BW353: =BW352+1 -> 346 | BY353: =CG352 -> 64319.567 | BZ353: =BZ352 -> 4490.7918 | CA353: =BZ353-CC353 -> 4115.5944 | CB353: =(CA353/BY353)*12 -> 0.76783994 | CC353: =BY353*($BX$3/12) -> 375.19747 | CD353: =(CC353/BY353)*12 -> 0.07 | CE353: =CE352+CA353 -> 614796.03 | CF353: =CF352+CC353 -> 939017.95 | CG353: =BY353-CA353 -> 60203.973 | CH353: =CE353+CF353 -> 1553814
J354: =J353+1 -> 347 | L354: =T353 -> 67464.428 | M354: =$L$8/((($N$4)-1)/($N$3*$N$4)) -> 5071.0496 | N354: =M354-P354 -> 4607.2316 | O354: =(N354/L354)*12 -> 0.81949527 | P354: =L354*($K$3/12) -> 463.81794 | Q354: =(P354/L354)*12 -> 0.0825 | R354: =R353+N354 -> 612142.8 | S354: =S353+P354 -> 1147511.4 | T354: =L354-N354 -> 62857.196 | U354: =R354+S354 -> 1759654.2 | W354: =W353+1 -> 347 | Y354: =AG353 -> 65993.576 | Z354: =Z353 -> 4952.9109 | AA354: =Z354-AC354 -> 4512.9537 | AB354: =(AA354/Y354)*12 -> 0.8206169 | AC354: =Y354*($X$3/12) -> 439.95718 | AD354: =(AC354/Y354)*12 -> 0.08 | AE354: =AE353+AA354 -> 613519.38 | AF354: =AF353+AC354 -> 1105140.7 | AG354: =Y354-AA354 -> 61480.623 | AH354: =AE354+AF354 -> 1718660.1 | AJ354: =AJ353+1 -> 347 | AL354: =AT353 -> 64531.615 | AM354: =AM353 -> 4835.7827 | AN354: =AM354-AP354 -> 4419.016 | AO354: =(AN354/AL354)*12 -> 0.82173973 | AP354: =AL354*($AK$3/12) -> 416.76668 | AQ354: =(AP354/AL354)*12 -> 0.0775 | AR354: =AR353+AN354 -> 614887.4 | AS354: =AS353+AP354 -> 1063129.2 | AT354: =AL354-AN354 -> 60112.599 | AU354: =AR354+AS354 -> 1678016.6 | AW354: =AW353+1 -> 347 | AY354: =BG353 -> 63079.031 | AZ354: =AZ353 -> 4719.6979 | BA354: =AZ354-BC354 -> 4325.454 | BB354: =(BA354/AY354)*12 -> 0.82286375 | BC354: =AY354*($AX$3/12) -> 394.24394 | BD354: =(BC354/AY354)*12 -> 0.075 | BE354: =BE353+BA354 -> 616246.42 | BF354: =BF353+BC354 -> 1021488.8 | BG354: =AY354-BA354 -> 58753.577 | BH354: =BE354+BF354 -> 1637735.2 | BJ354: =BJ353+1 -> 347 | BL354: =BT353 -> 61636.317 | BM354: =BM353 -> 4604.6899 | BN354: =BM354-BP354 -> 4232.3038 | BO354: =(BN354/BL354)*12 -> 0.82398897 | BP354: =BL354*($BK$3/12) -> 372.38608 | BQ354: =(BP354/BL354)*12 -> 0.0725 | BR354: =BR353+BN354 -> 617595.99 | BS354: =BS353+BP354 -> 980231.41 | BT354: =BL354-BN354 -> 57404.014 | BU354: =BR354+BS354 -> 1597827.4 | BW354: =BW353+1 -> 347 | BY354: =CG353 -> 60203.973 | BZ354: =BZ353 -> 4490.7918 | CA354: =BZ354-CC354 -> 4139.602 | CB354: =(CA354/BY354)*12 -> 0.82511539 | CC354: =BY354*($BX$3/12) -> 351.18984 | CD354: =(CC354/BY354)*12 -> 0.07 | CE354: =CE353+CA354 -> 618935.63 | CF354: =CF353+CC354 -> 939369.14 | CG354: =BY354-CA354 -> 56064.371 | CH354: =CE354+CF354 -> 1558304.8
... J367: =J366+1 -> 360 | L367: =T366 -> 5036.4242 | M367: =$L$8/((($N$4)-1)/($N$3*$N$4)) -> 5071.0496 | N367: =M367-P367 -> 5036.4242 | O367: =(N367/L367)*12 -> 12 | P367: =L367*($K$3/12) -> 34.625416 | Q367: =(P367/L367)*12 -> 0.0825 | R367: =R366+N367 -> 675000 | S367: =S366+P367 -> 1150577.8 | T367: =L367-N367 -> -1.5978912e-08 | U367: =R367+S367 -> 1825577.8 | W367: =W366+1 -> 360 | Y367: =AG366 -> 4920.1101 | Z367: =Z366 -> 4952.9109 | AA367: =Z367-AC367 -> 4920.1101 | AB367: =(AA367/Y367)*12 -> 12 | AC367: =Y367*($X$3/12) -> 32.800734 | AD367: =(AC367/Y367)*12 -> 0.08 | AE367: =AE366+AA367 -> 675000 | AF367: =AF366+AC367 -> 1108047.9 | AG367: =Y367-AA367 -> -1.4491889e-08 | AH367: =AE367+AF367 -> 1783047.9 | AJ367: =AJ366+1 -> 360 | AL367: =AT366 -> 4804.752 | AM367: =AM366 -> 4835.7827 | AN367: =AM367-AP367 -> 4804.752 | AO367: =(AN367/AL367)*12 -> 12 | AP367: =AL367*($AK$3/12) -> 31.03069 | AQ367: =(AP367/AL367)*12 -> 0.0775 | AR367: =AR366+AN367 -> 675000 | AS367: =AS366+AP367 -> 1065881.8 | AT367: =AL367-AN367 -> -1.601984e-08 | AU367: =AR367+AS367 -> 1740881.8 | AW367: =AW366+1 -> 360 | AY367: =BG366 -> 4690.383 | AZ367: =AZ366 -> 4719.6979 | BA367: =AZ367-BC367 -> 4690.383 | BB367: =(BA367/AY367)*12 -> 12 | BC367: =AY367*($AX$3/12) -> 29.314894 | BD367: =(BC367/AY367)*12 -> 0.075 | BE367: =BE366+BA367 -> 675000 | BF367: =BF366+BC367 -> 1024091.3 | BG367: =AY367-BA367 -> 1.544322e-08 | BH367: =BE367+BF367 -> 1699091.3 | BJ367: =BJ366+1 -> 360 | BL367: =BT366 -> 4577.037 | BM367: =BM366 -> 4604.6899 | BN367: =BM367-BP367 -> 4577.037 | BO367: =(BN367/BL367)*12 -> 12 | BP367: =BL367*($BK$3/12) -> 27.652932 | BQ367: =(BP367/BL367)*12 -> 0.0725 | BR367: =BR366+BN367 -> 675000 | BS367: =BS366+BP367 -> 982688.36 | BT367: =BL367-BN367 -> 1.9299478e-09 | BU367: =BR367+BS367 -> 1657688.4 | BW367: =BW366+1 -> 360 | BY367: =CG366 -> 4464.7475 | BZ367: =BZ366 -> 4490.7918 | CA367: =BZ367-CC367 -> 4464.7475 | CB367: =(CA367/BY367)*12 -> 12 | CC367: =BY367*($BX$3/12) -> 26.04436 | CD367: =(CC367/BY367)*12 -> 0.07 | CE367: =CE366+CA367 -> 675000 | CF367: =CF366+CC367 -> 941685.06 | CG367: =BY367-CA367 -> 1.9826984e-09 | CH367: =CE367+CF367 -> 1616685.1

Sheet Amoritization Scenario 15% DP
J1: Interest | K1: ='Interest Rate Comparison'!B3 -> 0.0825 | N1: =K1/12 -> 0.006875 | O1: r | W1: Interest | X1: ='Interest Rate Comparison'!B4 -> 0.08 | AA1: =X1/12 -> 0.0066666667 | AB1: r | AJ1: Interest | AK1: ='Interest Rate Comparison'!B5 -> 0.0775 | AN1: =AK1/12 -> 0.0064583333 | AO1: r | AW1: Interest | AX1: ='Interest Rate Comparison'!B6 -> 0.075 | BA1: =AX1/12 -> 0.00625 | BB1: r | BJ1: Interest | BK1: ='Interest Rate Comparison'!B7 -> 0.0725 | BN1: =BK1/12 -> 0.0060416667 | BO1: r | BW1: Interest | BX1: ='Interest Rate Comparison'!B8 -> 0.07 | CA1: =BX1/12 -> 0.0058333333 | CB1: r
J2: Term | K2: =$L$2*12 -> 360 | L2: ='STR Calculator'!I9 -> 30 | M2: years | N2: =(1+N1)^K2 -> 11.781506 | O2: (1+r)^n | W2: Term | X2: =$L$2*12 -> 360 | Y2: 30 | Z2: years | AA2: =(1+AA1)^X2 -> 10.93573 | AB2: (1+r)^n | AJ2: Term | AK2: =$L$2*12 -> 360 | AL2: 30 | AM2: years | AN2: =(1+AN1)^AK2 -> 10.150514 | AO2: (1+r)^n | AW2: Term | AX2: =$L$2*12 -> 360 | AY2: 30 | AZ2: years | BA2: =(1+BA1)^AX2 -> 9.4215339 | BB2: (1+r)^n | BJ2: Term | BK2: =$L$2*12 -> 360 | BL2: 30 | BM2: years | BN2: =(1+BN1)^BK2 -> 8.744772 | BO2: (1+r)^n | BW2: Term | BX2: =$L$2*12 -> 360 | BY2: 30 | BZ2: years | CA2: =(1+CA1)^BX2 -> 8.1164975 | CB2: (1+r)^n
A3: Original Purchase Price | B3: ='STR Calculator'!B5 -> 750000 | C3: =B3/B1 -> #DIV/0! | D3: sqft | J3: Monthly Payment | W3: Monthly Payment | AJ3: Monthly Payment | AW3: Monthly Payment | BJ3: Monthly Payment | BW3: Monthly Payment
A4: Down Payment | B4: 0.15
A5: Current Loan Balance | B5: =B3-(B3*B4) -> 637500 | C5: as of 11/13/22 | J5: paymentNumber | K5: paymentDate | L5: startingBalance | M5: Monthly Payment | N5: principalPayment | O5: Principle Pay Down | P5: interestPayment | Q5: Interest Percent | R5: cumulativePrincipal | S5: cumulativeInterest | T5: endingBalance | U5: Total Paid End of Loan | W5: paymentNumber | X5: paymentDate | Y5: startingBalance | Z5: Monthly Payment | AA5: principalPayment | AB5: Principle Pay Down | AC5: interestPayment | AD5: Interest Percent | AE5: cumulativePrincipal | AF5: cumulativeInterest | AG5: endingBalance | AH5: Total Paid End of Loan | AJ5: paymentNumber | AK5: paymentDate | AL5: startingBalance | AM5: Monthly Payment | AN5: principalPayment | AO5: Principle Pay Down | AP5: interestPayment | AQ5: Interest Percent | AR5: cumulativePrincipal | AS5: cumulativeInterest | AT5: endingBalance | AU5: Total Paid End of Loan | AW5: paymentNumber | AX5: paymentDate | AY5: startingBalance | AZ5: Monthly Payment | BA5: principalPayment | BB5: Principle Pay Down | BC5: interestPayment | BD5: Interest Percent | BE5: cumulativePrincipal | BF5: cumulativeInterest | BG5: endingBalance | BH5: Total Paid End of Loan | BJ5: paymentNumber | BK5: paymentDate | BL5: startingBalance | BM5: Monthly Payment | BN5: principalPayment | BO5: Principle Pay Down | BP5: interestPayment | BQ5: Interest Percent | BR5: cumulativePrincipal | BS5: cumulativeInterest | BT5: endingBalance | BU5: Total Paid End of Loan | BW5: paymentNumber | BX5: paymentDate | BY5: startingBalance | BZ5: Monthly Payment | CA5: principalPayment | CB5: Principle Pay Down | CC5: interestPayment | CD5: Interest Percent | CE5: cumulativePrincipal | CF5: cumulativeInterest | CG5: endingBalance | CH5: Total Paid End of Loan
A6: Current Equity | B6: =B3-B5 -> 112500 | J6: 1 | K6: 44866 | L6: ='Amoritization Scenario 15% DP'!$B$5 -> 637500 | M6: =$L$6/((($N$2)-1)/($N$1*$N$2)) -> 4789.3246 | N6: =M6-P6 -> 406.5121 | O6: =(N6/L6)*12 -> 0.0076519925 | P6: =L6*($K$1/12) -> 4382.8125 | Q6: =(P6/L6)*12 -> 0.0825 | R6: =N6 -> 406.5121 | S6: =P6 -> 4382.8125 | T6: =L6-N6 -> 637093.49 | U6: =R6+S6 -> 4789.3246 | W6: 1 | X6: 44866 | Y6: ='Amoritization Scenario 15% DP'!$B$5 -> 637500 | Z6: =$Y$6/((($AA$2)-1)/($AA$1*$AA$2)) -> 4677.7492 | AA6: =Z6-AC6 -> 427.74916 | AB6: =(AA6/Y6)*12 -> 0.0080517489 | AC6: =Y6*($X$1/12) -> 4250 | AD6: =(AC6/Y6)*12 -> 0.08 | AE6: =AA6 -> 427.74916 | AF6: =AC6 -> 4250 | AG6: =Y6-AA6 -> 637072.25 | AH6: =AE6+AF6 -> 4677.7492 | AJ6: 1 | AK6: 44866 | AL6: ='Amoritization Scenario 15% DP'!$B$5 -> 637500 | AM6: =$AL$6/((($AN$2)-1)/($AN$1*$AN$2)) -> 4567.1281 | AN6: =AM6-AP6 -> 449.94057 | AO6: =(AN6/AL6)*12 -> 0.0084694695 | AP6: =AL6*($AK$1/12) -> 4117.1875 | AQ6: =(AP6/AL6)*12 -> 0.0775 | AR6: =AN6 -> 449.94057 | AS6: =AP6 -> 4117.1875 | AT6: =AL6-AN6 -> 637050.06 | AU6: =AR6+AS6 -> 4567.1281 | AW6: 1 | AX6: 44866 | AY6: ='Amoritization Scenario 15% DP'!$B$5 -> 637500 | AZ6: =$AY$6/((($BA$2)-1)/($BA$1*$BA$2)) -> 4457.4925 | BA6: =AZ6-BC6 -> 473.11749 | BB6: =(BA6/AY6)*12 -> 0.008905741 | BC6: =AY6*($AX$1/12) -> 3984.375 | BD6: =(BC6/AY6)*12 -> 0.075 | BE6: =BA6 -> 473.11749 | BF6: =BC6 -> 3984.375 | BG6: =AY6-BA6 -> 637026.88 | BH6: =BE6+BF6 -> 4457.4925 | BJ6: 1 | BK6: 44866 | BL6: ='Amoritization Scenario 15% DP'!$B$5 -> 637500 | BM6: =$BL$6/((($BN$2)-1)/($BN$1*$BN$2)) -> 4348.8738 | BN6: =BM6-BP6 -> 497.31129 | BO6: =(BN6/BL6)*12 -> 0.0093611536 | BP6: =BL6*($BK$1/12) -> 3851.5625 | BQ6: =(BP6/BL6)*12 -> 0.0725 | BR6: =BN6 -> 497.31129 | BS6: =BP6 -> 3851.5625 | BT6: =BL6-BN6 -> 637002.69 | BU6: =BR6+BS6 -> 4348.8738 | BW6: 1 | BX6: 44866 | BY6: ='Amoritization Scenario 15% DP'!$B$5 -> 637500 | BZ6: =$BY$6/((($CA$2)-1)/($CA$1*$CA$2)) -> 4241.3034 | CA6: =BZ6-CC6 -> 522.55341 | CB6: =(CA6/BY6)*12 -> 0.0098362994 | CC6: =BY6*($BX$1/12) -> 3718.75 | CD6: =(CC6/BY6)*12 -> 0.07 | CE6: =CA6 -> 522.55341 | CF6: =CC6 -> 3718.75 | CG6: =BY6-CA6 -> 636977.45 | CH6: =CE6+CF6 -> 4241.3034
J7: 2 | K7: 44896 | L7: =T6 -> 637093.49 | M7: =$L$6/((($N$2)-1)/($N$1*$N$2)) -> 4789.3246 | N7: =M7-P7 -> 409.30687 | O7: =(N7/L7)*12 -> 0.007709516 | P7: =L7*($K$1/12) -> 4380.0177 | Q7: =(P7/L7)*12 -> 0.0825 | R7: =R6+N7 -> 815.81897 | S7: =S6+P7 -> 8762.8302 | T7: =L7-N7 -> 636684.18 | U7: =R7+S7 -> 9578.6492 | W7: 2 | X7: 44896 | Y7: =AG6 -> 637072.25 | Z7: =Z6 -> 4677.7492 | AA7: =Z7-AC7 -> 430.60082 | AB7: =(AA7/Y7)*12 -> 0.0081108694 | AC7: =Y7*($X$1/12) -> 4247.1483 | AD7: =(AC7/Y7)*12 -> 0.08 | AE7: =AE6+AA7 -> 858.34998 | AF7: =AF6+AC7 -> 8497.1483 | AG7: =Y7-AA7 -> 636641.65 | AH7: =AE7+AF7 -> 9355.4983 | AJ7: 2 | AK7: 44896 | AL7: =AT6 -> 637050.06 | AM7: =AM6 -> 4567.1281 | AN7: =AM7-AP7 -> 452.84643 | AO7: =(AN7/AL7)*12 -> 0.0085301886 | AP7: =AL7*($AK$1/12) -> 4114.2816 | AQ7: =(AP7/AL7)*12 -> 0.0775 | AR7: =AR6+AN7 -> 902.787 | AS7: =AS6+AP7 -> 8231.4691 | AT7: =AL7-AN7 -> 636597.21 | AU7: =AR7+AS7 -> 9134.2561 | AW7: 2 | AX7: 44896 | AY7: =BG6 -> 637026.88 | AZ7: =AZ6 -> 4457.4925 | BA7: =AZ7-BC7 -> 476.07448 | BB7: =(BA7/AY7)*12 -> 0.0089680575 | BC7: =AY7*($AX$1/12) -> 3981.418 | BD7: =(BC7/AY7)*12 -> 0.075 | BE7: =BE6+BA7 -> 949.19197 | BF7: =BF6+BC7 -> 7965.793 | BG7: =AY7-BA7 -> 636550.81 | BH7: =BE7+BF7 -> 8914.985 | BJ7: 2 | BK7: 44896 | BL7: =BT6 -> 637002.69 | BM7: =BM6 -> 4348.8738 | BN7: =BM7-BP7 -> 500.31587 | BO7: =(BN7/BL7)*12 -> 0.009425063 | BP7: =BL7*($BK$1/12) -> 3848.5579 | BQ7: =(BP7/BL7)*12 -> 0.0725 | BR7: =BR6+BN7 -> 997.62716 | BS7: =BS6+BP7 -> 7700.1204 | BT7: =BL7-BN7 -> 636502.37 | BU7: =BR7+BS7 -> 8697.7476 | BW7: 2 | BX7: 44896 | BY7: =CG6 -> 636977.45 | BZ7: =BZ6 -> 4241.3034 | CA7: =BZ7-CC7 -> 525.60163 | CB7: =(CA7/BY7)*12 -> 0.0099017943 | CC7: =BY7*($BX$1/12) -> 3715.7018 | CD7: =(CC7/BY7)*12 -> 0.07 | CE7: =CE6+CA7 -> 1048.155 | CF7: =CF6+CC7 -> 7434.4518 | CG7: =BY7-CA7 -> 636451.84 | CH7: =CE7+CF7 -> 8482.6068
A8: Year | B8: ="Cum Interest @ "&K1&"%" -> Cum Interest @ 0.0825% | C8: ="Cum Interest @ "&X1&"%" -> Cum Interest @ 0.08% | D8: ="Cum Interest @ "&AK1&"%" -> Cum Interest @ 0.0775% | E8: ="Cum Interest @ "&AX1&"%" -> Cum Interest @ 0.075% | F8: ="Cum Interest @ "&BK1&"%" -> Cum Interest @ 0.0725% | G8: ="Cum Interest @ "&BX1&"%" -> Cum Interest @ 0.07% | J8: 3 | K8: 44927 | L8: =T7 -> 636684.18 | M8: =$L$6/((($N$2)-1)/($N$1*$N$2)) -> 4789.3246 | N8: =M8-P8 -> 412.12086 | O8: =(N8/L8)*12 -> 0.0077675093 | P8: =L8*($K$1/12) -> 4377.2037 | Q8: =(P8/L8)*12 -> 0.0825 | R8: =R7+N8 -> 1227.9398 | S8: =S7+P8 -> 13140.034 | T8: =L8-N8 -> 636272.06 | U8: =R8+S8 -> 14367.974 | W8: 3 | X8: 44927 | Y8: =AG7 -> 636641.65 | Z8: =Z7 -> 4677.7492 | AA8: =Z8-AC8 -> 433.47149 | AB8: =(AA8/Y8)*12 -> 0.0081704643 | AC8: =Y8*($X$1/12) -> 4244.2777 | AD8: =(AC8/Y8)*12 -> 0.08 | AE8: =AE7+AA8 -> 1291.8215 | AF8: =AF7+AC8 -> 12741.426 | AG8: =Y8-AA8 -> 636208.18 | AH8: =AE8+AF8 -> 14033.247 | AJ8: 3 | AK8: 44927 | AL8: =AT7 -> 636597.21 | AM8: =AM7 -> 4567.1281 | AN8: =AM8-AP8 -> 455.77106 | AO8: =(AN8/AL8)*12 -> 0.0085913866 | AP8: =AL8*($AK$1/12) -> 4111.357 | AQ8: =(AP8/AL8)*12 -> 0.0775 | AR8: =AR7+AN8 -> 1358.5581 | AS8: =AS7+AP8 -> 12342.826 | AT8: =AL8-AN8 -> 636141.44 | AU8: =AR8+AS8 -> 13701.384 | AW8: 3 | AX8: 44927 | AY8: =BG7 -> 636550.81 | AZ8: =AZ7 -> 4457.4925 | BA8: =AZ8-BC8 -> 479.04994 | BB8: =(BA8/AY8)*12 -> 0.009030857 | BC8: =AY8*($AX$1/12) -> 3978.4426 | BD8: =(BC8/AY8)*12 -> 0.075 | BE8: =BE7+BA8 -> 1428.2419 | BF8: =BF7+BC8 -> 11944.236 | BG8: =AY8-BA8 -> 636071.76 | BH8: =BE8+BF8 -> 13372.477 | BJ8: 3 | BK8: 44927 | BL8: =BT7 -> 636502.37 | BM8: =BM7 -> 4348.8738 | BN8: =BM8-BP8 -> 503.33862 | BO8: =(BN8/BL8)*12 -> 0.0094894594 | BP8: =BL8*($BK$1/12) -> 3845.5352 | BQ8: =(BP8/BL8)*12 -> 0.0725 | BR8: =BR7+BN8 -> 1500.9658 | BS8: =BS7+BP8 -> 11545.656 | BT8: =BL8-BN8 -> 635999.03 | BU8: =BR8+BS8 -> 13046.621 | BW8: 3 | BX8: 44927 | BY8: =CG7 -> 636451.84 | BZ8: =BZ7 -> 4241.3034 | CA8: =BZ8-CC8 -> 528.66764 | CB8: =(CA8/BY8)*12 -> 0.0099677796 | CC8: =BY8*($BX$1/12) -> 3712.6358 | CD8: =(CC8/BY8)*12 -> 0.07 | CE8: =CE7+CA8 -> 1576.8227 | CF8: =CF7+CC8 -> 11147.088 | CG8: =BY8-CA8 -> 635923.18 | CH8: =CE8+CF8 -> 12723.91
A9: 1 | B9: =VLOOKUP($A$9*12,$J$5:$U$365,10) -> 52405.002 | C9: =VLOOKUP(A9*12,$W$5:$AH$365,10) -> 50807.545 | D9: =VLOOKUP(A9*12,$AJ$5:$AU$365,10) -> 49210.273 | E9: =VLOOKUP(A9*12,$AW$5:$BH$365,10) -> 47613.215 | F9: =VLOOKUP(A9*12,$BJ$5:$BU$365,10) -> 46016.399 | G9: =VLOOKUP(A9*12,$BW$5:$CH$365,10) -> 44419.853 | J9: 4 | K9: 44958 | L9: =T8 -> 636272.06 | M9: =$L$6/((($N$2)-1)/($N$1*$N$2)) -> 4789.3246 | N9: =M9-P9 -> 414.95419 | O9: =(N9/L9)*12 -> 0.0078259766 | P9: =L9*($K$1/12) -> 4374.3704 | Q9: =(P9/L9)*12 -> 0.0825 | R9: =R8+N9 -> 1642.894 | S9: =S8+P9 -> 17514.404 | T9: =L9-N9 -> 635857.11 | U9: =R9+S9 -> 19157.298 | W9: 4 | X9: 44958 | Y9: =AG8 -> 636208.18 | Z9: =Z8 -> 4677.7492 | AA9: =Z9-AC9 -> 436.3613 | AB9: =(AA9/Y9)*12 -> 0.008230538 | AC9: =Y9*($X$1/12) -> 4241.3879 | AD9: =(AC9/Y9)*12 -> 0.08 | AE9: =AE8+AA9 -> 1728.1828 | AF9: =AF8+AC9 -> 16982.814 | AG9: =Y9-AA9 -> 635771.82 | AH9: =AE9+AF9 -> 18710.997 | AJ9: 4 | AK9: 44958 | AL9: =AT8 -> 636141.44 | AM9: =AM8 -> 4567.1281 | AN9: =AM9-AP9 -> 458.71459 | AO9: =(AN9/AL9)*12 -> 0.0086530678 | AP9: =AL9*($AK$1/12) -> 4108.4135 | AQ9: =(AP9/AL9)*12 -> 0.0775 | AR9: =AR8+AN9 -> 1817.2726 | AS9: =AS8+AP9 -> 16451.24 | AT9: =AL9-AN9 -> 635682.73 | AU9: =AR9+AS9 -> 18268.512 | AW9: 4 | AX9: 44958 | AY9: =BG8 -> 636071.76 | AZ9: =AZ8 -> 4457.4925 | BA9: =AZ9-BC9 -> 482.044 | BB9: =(BA9/AY9)*12 -> 0.0090941438 | BC9: =AY9*($AX$1/12) -> 3975.4485 | BD9: =(BC9/AY9)*12 -> 0.075 | BE9: =BE8+BA9 -> 1910.2859 | BF9: =BF8+BC9 -> 15919.684 | BG9: =AY9-BA9 -> 635589.71 | BH9: =BE9+BF9 -> 17829.97 | BJ9: 4 | BK9: 44958 | BL9: =BT8 -> 635999.03 | BM9: =BM8 -> 4348.8738 | BN9: =BM9-BP9 -> 506.37962 | BO9: =(BN9/BL9)*12 -> 0.009554347 | BP9: =BL9*($BK$1/12) -> 3842.4942 | BQ9: =(BP9/BL9)*12 -> 0.0725 | BR9: =BR8+BN9 -> 2007.3454 | BS9: =BS8+BP9 -> 15388.15 | BT9: =BL9-BN9 -> 635492.65 | BU9: =BR9+BS9 -> 17395.495 | BW9: 4 | BX9: 44958 | BY9: =CG8 -> 635923.18 | BZ9: =BZ8 -> 4241.3034 | CA9: =BZ9-CC9 -> 531.75154 | CB9: =(CA9/BY9)*12 -> 0.01003426 | CC9: =BY9*($BX$1/12) -> 3709.5519 | CD9: =(CC9/BY9)*12 -> 0.07 | CE9: =CE8+CA9 -> 2108.5742 | CF9: =CF8+CC9 -> 14856.639 | CG9: =BY9-CA9 -> 635391.43 | CH9: =CE9+CF9 -> 16965.214
A10: =A9+1 -> 2 | B10: =VLOOKUP(A10*12,$J$5:$U$365,10) -> 104375.81 | C10: =VLOOKUP(A10*12,$W$5:$AH$365,10) -> 101173.08 | D10: =VLOOKUP(A10*12,$AJ$5:$AU$365,10) -> 97971.175 | E10: =VLOOKUP(A10*12,$AW$5:$BH$365,10) -> 94770.208 | F10: =VLOOKUP(A10*12,$BJ$5:$BU$365,10) -> 91570.298 | G10: =VLOOKUP(A10*12,$BW$5:$CH$365,10) -> 88371.571 | J10: 5 | K10: 44986 | L10: =T9 -> 635857.11 | M10: =$L$6/((($N$2)-1)/($N$1*$N$2)) -> 4789.3246 | N10: =M10-P10 -> 417.807 | O10: =(N10/L10)*12 -> 0.0078849224 | P10: =L10*($K$1/12) -> 4371.5176 | Q10: =(P10/L10)*12 -> 0.0825 | R10: =R9+N10 -> 2060.701 | S10: =S9+P10 -> 21885.922 | T10: =L10-N10 -> 635439.3 | U10: =R10+S10 -> 23946.623 | W10: 5 | X10: 44986 | Y10: =AG9 -> 635771.82 | Z10: =Z9 -> 4677.7492 | AA10: =Z10-AC10 -> 439.27038 | AB10: =(AA10/Y10)*12 -> 0.008291095 | AC10: =Y10*($X$1/12) -> 4238.4788 | AD10: =(AC10/Y10)*12 -> 0.08 | AE10: =AE9+AA10 -> 2167.4531 | AF10: =AF9+AC10 -> 21221.293 | AG10: =Y10-AA10 -> 635332.55 | AH10: =AE10+AF10 -> 23388.746 | AJ10: 5 | AK10: 44986 | AL10: =AT9 -> 635682.73 | AM10: =AM9 -> 4567.1281 | AN10: =AM10-AP10 -> 461.67712 | AO10: =(AN10/AL10)*12 -> 0.0087152367 | AP10: =AL10*($AK$1/12) -> 4105.4509 | AQ10: =(AP10/AL10)*12 -> 0.0775 | AR10: =AR9+AN10 -> 2278.9498 | AS10: =AS9+AP10 -> 20556.691 | AT10: =AL10-AN10 -> 635221.05 | AU10: =AR10+AS10 -> 22835.64 | AW10: 5 | AX10: 44986 | AY10: =BG9 -> 635589.71 | AZ10: =AZ9 -> 4457.4925 | BA10: =AZ10-BC10 -> 485.05678 | BB10: =(BA10/AY10)*12 -> 0.0091579225 | BC10: =AY10*($AX$1/12) -> 3972.4357 | BD10: =(BC10/AY10)*12 -> 0.075 | BE10: =BE9+BA10 -> 2395.3427 | BF10: =BF9+BC10 -> 19892.12 | BG10: =AY10-BA10 -> 635104.66 | BH10: =BE10+BF10 -> 22287.462 | BJ10: 5 | BK10: 44986 | BL10: =BT9 -> 635492.65 | BM10: =BM9 -> 4348.8738 | BN10: =BM10-BP10 -> 509.439 | BO10: =(BN10/BL10)*12 -> 0.0096197303 | BP10: =BL10*($BK$1/12) -> 3839.4348 | BQ10: =(BP10/BL10)*12 -> 0.0725 | BR10: =BR9+BN10 -> 2516.7844 | BS10: =BS9+BP10 -> 19227.585 | BT10: =BL10-BN10 -> 634983.22 | BU10: =BR10+BS10 -> 21744.369 | BW10: 5 | BX10: 44986 | BY10: =CG9 -> 635391.43 | BZ10: =BZ9 -> 4241.3034 | CA10: =BZ10-CC10 -> 534.85342 | CB10: =(CA10/BY10)*12 -> 0.01010124 | CC10: =BY10*($BX$1/12) -> 3706.45 | CD10: =(CC10/BY10)*12 -> 0.07 | CE10: =CE9+CA10 -> 2643.4276 | CF10: =CF9+CC10 -> 18563.089 | CG10: =BY10-CA10 -> 634856.57 | CH10: =CE10+CF10 -> 21206.517
A11: =A10+1 -> 3 | B11: =VLOOKUP(A11*12,$J$5:$U$365,10) -> 155875.22 | C11: =VLOOKUP(A11*12,$W$5:$AH$365,10) -> 151059.92 | D11: =VLOOKUP(A11*12,$AJ$5:$AU$365,10) -> 146246.61 | E11: =VLOOKUP(A11*12,$AW$5:$BH$365,10) -> 141435.56 | F11: =VLOOKUP(A11*12,$BJ$5:$BU$365,10) -> 136627.03 | G11: =VLOOKUP(A11*12,$BW$5:$CH$365,10) -> 131821.31 | J11: 6 | K11: 45017 | L11: =T10 -> 635439.3 | M11: =$L$6/((($N$2)-1)/($N$1*$N$2)) -> 4789.3246 | N11: =M11-P11 -> 420.67942 | O11: =(N11/L11)*12 -> 0.0079443513 | P11: =L11*($K$1/12) -> 4368.6452 | Q11: =(P11/L11)*12 -> 0.0825 | R11: =R10+N11 -> 2481.3804 | S11: =S10+P11 -> 26254.567 | T11: =L11-N11 -> 635018.62 | U11: =R11+S11 -> 28735.948 | W11: 6 | X11: 45017 | Y11: =AG10 -> 635332.55 | Z11: =Z10 -> 4677.7492 | AA11: =Z11-AC11 -> 442.19885 | AB11: =(AA11/Y11)*12 -> 0.0083521396 | AC11: =Y11*($X$1/12) -> 4235.5503 | AD11: =(AC11/Y11)*12 -> 0.08 | AE11: =AE10+AA11 -> 2609.652 | AF11: =AF10+AC11 -> 25456.843 | AG11: =Y11-AA11 -> 634890.35 | AH11: =AE11+AF11 -> 28066.495 | AJ11: 6 | AK11: 45017 | AL11: =AT10 -> 635221.05 | AM11: =AM10 -> 4567.1281 | AN11: =AM11-AP11 -> 464.65878 | AO11: =(AN11/AL11)*12 -> 0.0087778977 | AP11: =AL11*($AK$1/12) -> 4102.4693 | AQ11: =(AP11/AL11)*12 -> 0.0775 | AR11: =AR10+AN11 -> 2743.6085 | AS11: =AS10+AP11 -> 24659.16 | AT11: =AL11-AN11 -> 634756.39 | AU11: =AR11+AS11 -> 27402.768 | AW11: 6 | AX11: 45017 | AY11: =BG10 -> 635104.66 | AZ11: =AZ10 -> 4457.4925 | BA11: =AZ11-BC11 -> 488.08838 | BB11: =(BA11/AY11)*12 -> 0.0092221975 | BC11: =AY11*($AX$1/12) -> 3969.4041 | BD11: =(BC11/AY11)*12 -> 0.075 | BE11: =BE10+BA11 -> 2883.4311 | BF11: =BF10+BC11 -> 23861.524 | BG11: =AY11-BA11 -> 634616.57 | BH11: =BE11+BF11 -> 26744.955 | BJ11: 6 | BK11: 45017 | BL11: =BT10 -> 634983.22 | BM11: =BM10 -> 4348.8738 | BN11: =BM11-BP11 -> 512.51686 | BO11: =(BN11/BL11)*12 -> 0.009685614 | BP11: =BL11*($BK$1/12) -> 3836.3569 | BQ11: =(BP11/BL11)*12 -> 0.0725 | BR11: =BR10+BN11 -> 3029.3013 | BS11: =BS10+BP11 -> 23063.941 | BT11: =BL11-BN11 -> 634470.7 | BU11: =BR11+BS11 -> 26093.243 | BW11: 6 | BX11: 45017 | BY11: =CG10 -> 634856.57 | BZ11: =BZ10 -> 4241.3034 | CA11: =BZ11-CC11 -> 537.9734 | CB11: =(CA11/BY11)*12 -> 0.010168723 | CC11: =BY11*($BX$1/12) -> 3703.33 | CD11: =(CC11/BY11)*12 -> 0.07 | CE11: =CE10+CA11 -> 3181.401 | CF11: =CF10+CC11 -> 22266.419 | CG11: =BY11-CA11 -> 634318.6 | CH11: =CE11+CF11 -> 25447.82
A12: =A11+1 -> 4 | B12: =VLOOKUP(A12*12,$J$5:$U$365,10) -> 206862.83 | C12: =VLOOKUP(A12*12,$W$5:$AH$365,10) -> 200428.33 | D12: =VLOOKUP(A12*12,$AJ$5:$AU$365,10) -> 193997.6 | E12: =VLOOKUP(A12*12,$AW$5:$BH$365,10) -> 187571.1 | F12: =VLOOKUP(A12*12,$BJ$5:$BU$365,10) -> 181149.33 | G12: =VLOOKUP(A12*12,$BW$5:$CH$365,10) -> 174732.79 | J12: 7 | K12: 45047 | L12: =T11 -> 635018.62 | M12: =$L$6/((($N$2)-1)/($N$1*$N$2)) -> 4789.3246 | N12: =M12-P12 -> 423.57159 | O12: =(N12/L12)*12 -> 0.0080042678 | P12: =L12*($K$1/12) -> 4365.753 | Q12: =(P12/L12)*12 -> 0.0825 | R12: =R11+N12 -> 2904.952 | S12: =S11+P12 -> 30620.32 | T12: =L12-N12 -> 634595.05 | U12: =R12+S12 -> 33525.272 | W12: 7 | X12: 45047 | Y12: =AG11 -> 634890.35 | Z12: =Z11 -> 4677.7492 | AA12: =Z12-AC12 -> 445.14684 | AB12: =(AA12/Y12)*12 -> 0.0084136766 | AC12: =Y12*($X$1/12) -> 4232.6023 | AD12: =(AC12/Y12)*12 -> 0.08 | AE12: =AE11+AA12 -> 3054.7988 | AF12: =AF11+AC12 -> 29689.445 | AG12: =Y12-AA12 -> 634445.2 | AH12: =AE12+AF12 -> 32744.244 | AJ12: 7 | AK12: 45047 | AL12: =AT11 -> 634756.39 | AM12: =AM11 -> 4567.1281 | AN12: =AM12-AP12 -> 467.6597 | AO12: =(AN12/AL12)*12 -> 0.0088410554 | AP12: =AL12*($AK$1/12) -> 4099.4684 | AQ12: =(AP12/AL12)*12 -> 0.0775 | AR12: =AR11+AN12 -> 3211.2683 | AS12: =AS11+AP12 -> 28758.628 | AT12: =AL12-AN12 -> 634288.73 | AU12: =AR12+AS12 -> 31969.896 | AW12: 7 | AX12: 45047 | AY12: =BG11 -> 634616.57 | AZ12: =AZ11 -> 4457.4925 | BA12: =AZ12-BC12 -> 491.13894 | BB12: =(BA12/AY12)*12 -> 0.0092869735 | BC12: =AY12*($AX$1/12) -> 3966.3536 | BD12: =(BC12/AY12)*12 -> 0.075 | BE12: =BE11+BA12 -> 3374.57 | BF12: =BF11+BC12 -> 27827.877 | BG12: =AY12-BA12 -> 634125.43 | BH12: =BE12+BF12 -> 31202.447 | BJ12: 7 | BK12: 45047 | BL12: =BT11 -> 634470.7 | BM12: =BM11 -> 4348.8738 | BN12: =BM12-BP12 -> 515.61331 | BO12: =(BN12/BL12)*12 -> 0.0097520024 | BP12: =BL12*($BK$1/12) -> 3833.2605 | BQ12: =(BP12/BL12)*12 -> 0.0725 | BR12: =BR11+BN12 -> 3544.9146 | BS12: =BS11+BP12 -> 26897.202 | BT12: =BL12-BN12 -> 633955.09 | BU12: =BR12+BS12 -> 30442.116 | BW12: 7 | BX12: 45047 | BY12: =CG11 -> 634318.6 | BZ12: =BZ11 -> 4241.3034 | CA12: =BZ12-CC12 -> 541.11158 | CB12: =(CA12/BY12)*12 -> 0.010236715 | CC12: =BY12*($BX$1/12) -> 3700.1918 | CD12: =(CC12/BY12)*12 -> 0.07 | CE12: =CE11+CA12 -> 3722.5126 | CF12: =CF11+CC12 -> 25966.611 | CG12: =BY12-CA12 -> 633777.49 | CH12: =CE12+CF12 -> 29689.124
A13: =A12+1 -> 5 | B13: =VLOOKUP(A13*12,$J$5:$U$365,10) -> 257294.8 | C13: =VLOOKUP(A13*12,$W$5:$AH$365,10) -> 249235.29 | D13: =VLOOKUP(A13*12,$AJ$5:$AU$365,10) -> 241182.01 | E13: =VLOOKUP(A13*12,$AW$5:$BH$365,10) -> 233135.71 | F13: =VLOOKUP(A13*12,$BJ$5:$BU$365,10) -> 225097.13 | G13: =VLOOKUP(A13*12,$BW$5:$CH$365,10) -> 217067.09 | J13: 8 | K13: 45078 | L13: =T12 -> 634595.05 | M13: =$L$6/((($N$2)-1)/($N$1*$N$2)) -> 4789.3246 | N13: =M13-P13 -> 426.48365 | O13: =(N13/L13)*12 -> 0.0080646765 | P13: =L13*($K$1/12) -> 4362.841 | Q13: =(P13/L13)*12 -> 0.0825 | R13: =R12+N13 -> 3331.4357 | S13: =S12+P13 -> 34983.161 | T13: =L13-N13 -> 634168.56 | U13: =R13+S13 -> 38314.597 | W13: 8 | X13: 45078 | Y13: =AG12 -> 634445.2 | Z13: =Z12 -> 4677.7492 | AA13: =Z13-AC13 -> 448.11448 | AB13: =(AA13/Y13)*12 -> 0.0084757104 | AC13: =Y13*($X$1/12) -> 4229.6347 | AD13: =(AC13/Y13)*12 -> 0.08 | AE13: =AE12+AA13 -> 3502.9133 | AF13: =AF12+AC13 -> 33919.08 | AG13: =Y13-AA13 -> 633997.09 | AH13: =AE13+AF13 -> 37421.993 | AJ13: 8 | AK13: 45078 | AL13: =AT12 -> 634288.73 | AM13: =AM12 -> 4567.1281 | AN13: =AM13-AP13 -> 470.68001 | AO13: =(AN13/AL13)*12 -> 0.0089047145 | AP13: =AL13*($AK$1/12) -> 4096.4481 | AQ13: =(AP13/AL13)*12 -> 0.0775 | AR13: =AR12+AN13 -> 3681.9483 | AS13: =AS12+AP13 -> 32855.076 | AT13: =AL13-AN13 -> 633818.05 | AU13: =AR13+AS13 -> 36537.025 | AW13: 8 | AX13: 45078 | AY13: =BG12 -> 634125.43 | AZ13: =AZ12 -> 4457.4925 | BA13: =AZ13-BC13 -> 494.20855 | BB13: =(BA13/AY13)*12 -> 0.0093522549 | BC13: =AY13*($AX$1/12) -> 3963.2839 | BD13: =(BC13/AY13)*12 -> 0.075 | BE13: =BE12+BA13 -> 3868.7786 | BF13: =BF12+BC13 -> 31791.161 | BG13: =AY13-BA13 -> 633631.22 | BH13: =BE13+BF13 -> 35659.94 | BJ13: 8 | BK13: 45078 | BL13: =BT12 -> 633955.09 | BM13: =BM12 -> 4348.8738 | BN13: =BM13-BP13 -> 518.72848 | BO13: =(BN13/BL13)*12 -> 0.0098189002 | BP13: =BL13*($BK$1/12) -> 3830.1453 | BQ13: =(BP13/BL13)*12 -> 0.0725 | BR13: =BR12+BN13 -> 4063.643 | BS13: =BS12+BP13 -> 30727.347 | BT13: =BL13-BN13 -> 633436.36 | BU13: =BR13+BS13 -> 34790.99 | BW13: 8 | BX13: 45078 | BY13: =CG12 -> 633777.49 | BZ13: =BZ12 -> 4241.3034 | CA13: =BZ13-CC13 -> 544.26806 | CB13: =(CA13/BY13)*12 -> 0.010305221 | CC13: =BY13*($BX$1/12) -> 3697.0353 | CD13: =(CC13/BY13)*12 -> 0.07 | CE13: =CE12+CA13 -> 4266.7807 | CF13: =CF12+CC13 -> 29663.647 | CG13: =BY13-CA13 -> 633233.22 | CH13: =CE13+CF13 -> 33930.427
A14: =A13+1 -> 6 | B14: =VLOOKUP(A14*12,$J$5:$U$365,10) -> 307123.49 | C14: =VLOOKUP(A14*12,$W$5:$AH$365,10) -> 297434.18 | D14: =VLOOKUP(A14*12,$AJ$5:$AU$365,10) -> 287754.35 | E14: =VLOOKUP(A14*12,$AW$5:$BH$365,10) -> 278085.05 | F14: =VLOOKUP(A14*12,$BJ$5:$BU$365,10) -> 268427.38 | G14: =VLOOKUP(A14*12,$BW$5:$CH$365,10) -> 258782.49 | J14: 9 | K14: 45108 | L14: =T13 -> 634168.56 | M14: =$L$6/((($N$2)-1)/($N$1*$N$2)) -> 4789.3246 | N14: =M14-P14 -> 429.41572 | O14: =(N14/L14)*12 -> 0.008125582 | P14: =L14*($K$1/12) -> 4359.9089 | Q14: =(P14/L14)*12 -> 0.0825 | R14: =R13+N14 -> 3760.8514 | S14: =S13+P14 -> 39343.07 | T14: =L14-N14 -> 633739.15 | U14: =R14+S14 -> 43103.921 | W14: 9 | X14: 45108 | Y14: =AG13 -> 633997.09 | Z14: =Z13 -> 4677.7492 | AA14: =Z14-AC14 -> 451.10191 | AB14: =(AA14/Y14)*12 -> 0.0085382458 | AC14: =Y14*($X$1/12) -> 4226.6472 | AD14: =(AC14/Y14)*12 -> 0.08 | AE14: =AE13+AA14 -> 3954.0152 | AF14: =AF13+AC14 -> 38145.727 | AG14: =Y14-AA14 -> 633545.98 | AH14: =AE14+AF14 -> 42099.742 | AJ14: 9 | AK14: 45108 | AL14: =AT13 -> 633818.05 | AM14: =AM13 -> 4567.1281 | AN14: =AM14-AP14 -> 473.71981 | AO14: =(AN14/AL14)*12 -> 0.0089688796 | AP14: =AL14*($AK$1/12) -> 4093.4083 | AQ14: =(AP14/AL14)*12 -> 0.0775 | AR14: =AR13+AN14 -> 4155.6681 | AS14: =AS13+AP14 -> 36948.485 | AT14: =AL14-AN14 -> 633344.33 | AU14: =AR14+AS14 -> 41104.153 | AW14: 9 | AX14: 45108 | AY14: =BG13 -> 633631.22 | AZ14: =AZ13 -> 4457.4925 | BA14: =AZ14-BC14 -> 497.29736 | BB14: =(BA14/AY14)*12 -> 0.0094180465 | BC14: =AY14*($AX$1/12) -> 3960.1951 | BD14: =(BC14/AY14)*12 -> 0.075 | BE14: =BE13+BA14 -> 4366.0759 | BF14: =BF13+BC14 -> 35751.357 | BG14: =AY14-BA14 -> 633133.92 | BH14: =BE14+BF14 -> 40117.432 | BJ14: 9 | BK14: 45108 | BL14: =BT13 -> 633436.36 | BM14: =BM13 -> 4348.8738 | BN14: =BM14-BP14 -> 521.86246 | BO14: =(BN14/BL14)*12 -> 0.0098863121 | BP14: =BL14*($BK$1/12) -> 3827.0113 | BQ14: =(BP14/BL14)*12 -> 0.0725 | BR14: =BR13+BN14 -> 4585.5055 | BS14: =BS13+BP14 -> 34554.359 | BT14: =BL14-BN14 -> 632914.49 | BU14: =BR14+BS14 -> 39139.864 | BW14: 9 | BX14: 45108 | BY14: =CG13 -> 633233.22 | BZ14: =BZ13 -> 4241.3034 | CA14: =BZ14-CC14 -> 547.44296 | CB14: =(CA14/BY14)*12 -> 0.010374243 | CC14: =BY14*($BX$1/12) -> 3693.8604 | CD14: =(CC14/BY14)*12 -> 0.07 | CE14: =CE13+CA14 -> 4814.2237 | CF14: =CF13+CC14 -> 33357.507 | CG14: =BY14-CA14 -> 632685.78 | CH14: =CE14+CF14 -> 38171.731
A15: =A14+1 -> 7 | B15: =VLOOKUP(A15*12,$J$5:$U$365,10) -> 356297.22 | C15: =VLOOKUP(A15*12,$W$5:$AH$365,10) -> 344974.56 | D15: =VLOOKUP(A15*12,$AJ$5:$AU$365,10) -> 333665.46 | E15: =VLOOKUP(A15*12,$AW$5:$BH$365,10) -> 322371.37 | F15: =VLOOKUP(A15*12,$BJ$5:$BU$365,10) -> 311093.78 | G15: =VLOOKUP(A15*12,$BW$5:$CH$365,10) -> 299834.25 | J15: 10 | K15: 45139 | L15: =T14 -> 633739.15 | M15: =$L$6/((($N$2)-1)/($N$1*$N$2)) -> 4789.3246 | N15: =M15-P15 -> 432.36795 | O15: =(N15/L15)*12 -> 0.008186989 | P15: =L15*($K$1/12) -> 4356.9566 | Q15: =(P15/L15)*12 -> 0.0825 | R15: =R14+N15 -> 4193.2193 | S15: =S14+P15 -> 43700.027 | T15: =L15-N15 -> 633306.78 | U15: =R15+S15 -> 47893.246 | W15: 10 | X15: 45139 | Y15: =AG14 -> 633545.98 | Z15: =Z14 -> 4677.7492 | AA15: =Z15-AC15 -> 454.10926 | AB15: =(AA15/Y15)*12 -> 0.0086012874 | AC15: =Y15*($X$1/12) -> 4223.6399 | AD15: =(AC15/Y15)*12 -> 0.08 | AE15: =AE14+AA15 -> 4408.1245 | AF15: =AF14+AC15 -> 42369.367 | AG15: =Y15-AA15 -> 633091.88 | AH15: =AE15+AF15 -> 46777.492 | AJ15: 10 | AK15: 45139 | AL15: =AT14 -> 633344.33 | AM15: =AM14 -> 4567.1281 | AN15: =AM15-AP15 -> 476.77926 | AO15: =(AN15/AL15)*12 -> 0.0090335553 | AP15: =AL15*($AK$1/12) -> 4090.3488 | AQ15: =(AP15/AL15)*12 -> 0.0775 | AR15: =AR14+AN15 -> 4632.4473 | AS15: =AS14+AP15 -> 41038.833 | AT15: =AL15-AN15 -> 632867.55 | AU15: =AR15+AS15 -> 45671.281 | AW15: 10 | AX15: 45139 | AY15: =BG14 -> 633133.92 | AZ15: =AZ14 -> 4457.4925 | BA15: =AZ15-BC15 -> 500.40547 | BB15: =(BA15/AY15)*12 -> 0.0094843529 | BC15: =AY15*($AX$1/12) -> 3957.087 | BD15: =(BC15/AY15)*12 -> 0.075 | BE15: =BE14+BA15 -> 4866.4814 | BF15: =BF14+BC15 -> 39708.444 | BG15: =AY15-BA15 -> 632633.52 | BH15: =BE15+BF15 -> 44574.925 | BJ15: 10 | BK15: 45139 | BL15: =BT14 -> 632914.49 | BM15: =BM14 -> 4348.8738 | BN15: =BM15-BP15 -> 525.01538 | BO15: =(BN15/BL15)*12 -> 0.0099542428 | BP15: =BL15*($BK$1/12) -> 3823.8584 | BQ15: =(BP15/BL15)*12 -> 0.0725 | BR15: =BR14+BN15 -> 5110.5209 | BS15: =BS14+BP15 -> 38378.217 | BT15: =BL15-BN15 -> 632389.48 | BU15: =BR15+BS15 -> 43488.738 | BW15: 10 | BX15: 45139 | BY15: =CG14 -> 632685.78 | BZ15: =BZ14 -> 4241.3034 | CA15: =BZ15-CC15 -> 550.63638 | CB15: =(CA15/BY15)*12 -> 0.010443789 | CC15: =BY15*($BX$1/12) -> 3690.667 | CD15: =(CC15/BY15)*12 -> 0.07 | CE15: =CE14+CA15 -> 5364.86 | CF15: =CF14+CC15 -> 37048.174 | CG15: =BY15-CA15 -> 632135.14 | CH15: =CE15+CF15 -> 42413.034
A16: =A15+1 -> 8 | B16: =VLOOKUP(A16*12,$J$5:$U$365,10) -> 404759.87 | C16: =VLOOKUP(A16*12,$W$5:$AH$365,10) -> 391801.75 | D16: =VLOOKUP(A16*12,$AJ$5:$AU$365,10) -> 378862.23 | E16: =VLOOKUP(A16*12,$AW$5:$BH$365,10) -> 365943.18 | F16: =VLOOKUP(A16*12,$BJ$5:$BU$365,10) -> 353046.56 | G16: =VLOOKUP(A16*12,$BW$5:$CH$365,10) -> 340174.4 | J16: 11 | K16: 45170 | L16: =T15 -> 633306.78 | M16: =$L$6/((($N$2)-1)/($N$1*$N$2)) -> 4789.3246 | N16: =M16-P16 -> 435.34048 | O16: =(N16/L16)*12 -> 0.0082489024 | P16: =L16*($K$1/12) -> 4353.9841 | Q16: =(P16/L16)*12 -> 0.0825 | R16: =R15+N16 -> 4628.5598 | S16: =S15+P16 -> 48054.011 | T16: =L16-N16 -> 632871.44 | U16: =R16+S16 -> 52682.571 | W16: 11 | X16: 45170 | Y16: =AG15 -> 633091.88 | Z16: =Z15 -> 4677.7492 | AA16: =Z16-AC16 -> 457.13666 | AB16: =(AA16/Y16)*12 -> 0.0086648401 | AC16: =Y16*($X$1/12) -> 4220.6125 | AD16: =(AC16/Y16)*12 -> 0.08 | AE16: =AE15+AA16 -> 4865.2611 | AF16: =AF15+AC16 -> 46589.98 | AG16: =Y16-AA16 -> 632634.74 | AH16: =AE16+AF16 -> 51455.241 | AJ16: 11 | AK16: 45170 | AL16: =AT15 -> 632867.55 | AM16: =AM15 -> 4567.1281 | AN16: =AM16-AP16 -> 479.85845 | AO16: =(AN16/AL16)*12 -> 0.0090987465 | AP16: =AL16*($AK$1/12) -> 4087.2696 | AQ16: =(AP16/AL16)*12 -> 0.0775 | AR16: =AR15+AN16 -> 5112.3058 | AS16: =AS15+AP16 -> 45126.103 | AT16: =AL16-AN16 -> 632387.69 | AU16: =AR16+AS16 -> 50238.409 | AW16: 11 | AX16: 45170 | AY16: =BG15 -> 632633.52 | AZ16: =AZ15 -> 4457.4925 | BA16: =AZ16-BC16 -> 503.533 | BB16: =(BA16/AY16)*12 -> 0.009551179 | BC16: =AY16*($AX$1/12) -> 3953.9595 | BD16: =(BC16/AY16)*12 -> 0.075 | BE16: =BE15+BA16 -> 5370.0144 | BF16: =BF15+BC16 -> 43662.403 | BG16: =AY16-BA16 -> 632129.99 | BH16: =BE16+BF16 -> 49032.417 | BJ16: 11 | BK16: 45170 | BL16: =BT15 -> 632389.48 | BM16: =BM15 -> 4348.8738 | BN16: =BM16-BP16 -> 528.18735 | BO16: =(BN16/BL16)*12 -> 0.010022697 | BP16: =BL16*($BK$1/12) -> 3820.6864 | BQ16: =(BP16/BL16)*12 -> 0.0725 | BR16: =BR15+BN16 -> 5638.7082 | BS16: =BS15+BP16 -> 42198.903 | BT16: =BL16-BN16 -> 631861.29 | BU16: =BR16+BS16 -> 47837.612 | BW16: 11 | BX16: 45170 | BY16: =CG15 -> 632135.14 | BZ16: =BZ15 -> 4241.3034 | CA16: =BZ16-CC16 -> 553.84842 | CB16: =(CA16/BY16)*12 -> 0.010513861 | CC16: =BY16*($BX$1/12) -> 3687.455 | CD16: =(CC16/BY16)*12 -> 0.07 | CE16: =CE15+CA16 -> 5918.7085 | CF16: =CF15+CC16 -> 40735.629 | CG16: =BY16-CA16 -> 631581.29 | CH16: =CE16+CF16 -> 46654.337
A17: =A16+1 -> 9 | B17: =VLOOKUP(A17*12,$J$5:$U$365,10) -> 452450.49 | C17: =VLOOKUP(A17*12,$W$5:$AH$365,10) -> 437856.56 | D17: =VLOOKUP(A17*12,$AJ$5:$AU$365,10) -> 423287.29 | E17: =VLOOKUP(A17*12,$AW$5:$BH$365,10) -> 408745.03 | F17: =VLOOKUP(A17*12,$BJ$5:$BU$365,10) -> 394232.25 | G17: =VLOOKUP(A17*12,$BW$5:$CH$365,10) -> 379751.48 | J17: 12 | K17: 45200 | L17: =T16 -> 632871.44 | M17: =$L$6/((($N$2)-1)/($N$1*$N$2)) -> 4789.3246 | N17: =M17-P17 -> 438.33345 | O17: =(N17/L17)*12 -> 0.0083113269 | P17: =L17*($K$1/12) -> 4350.9912 | Q17: =(P17/L17)*12 -> 0.0825 | R17: =R16+N17 -> 5066.8933 | S17: =S16+P17 -> 52405.002 | T17: =L17-N17 -> 632433.11 | U17: =R17+S17 -> 57471.895 | W17: 12 | X17: 45200 | Y17: =AG16 -> 632634.74 | Z17: =Z16 -> 4677.7492 | AA17: =Z17-AC17 -> 460.18423 | AB17: =(AA17/Y17)*12 -> 0.0087289086 | AC17: =Y17*($X$1/12) -> 4217.5649 | AD17: =(AC17/Y17)*12 -> 0.08 | AE17: =AE16+AA17 -> 5325.4454 | AF17: =AF16+AC17 -> 50807.545 | AG17: =Y17-AA17 -> 632174.55 | AH17: =AE17+AF17 -> 56132.99 | AJ17: 12 | AK17: 45200 | AL17: =AT16 -> 632387.69 | AM17: =AM16 -> 4567.1281 | AN17: =AM17-AP17 -> 482.95754 | AO17: =(AN17/AL17)*12 -> 0.009164458 | AP17: =AL17*($AK$1/12) -> 4084.1705 | AQ17: =(AP17/AL17)*12 -> 0.0775 | AR17: =AR16+AN17 -> 5595.2633 | AS17: =AS16+AP17 -> 49210.273 | AT17: =AL17-AN17 -> 631904.74 | AU17: =AR17+AS17 -> 54805.537 | AW17: 12 | AX17: 45200 | AY17: =BG16 -> 632129.99 | AZ17: =AZ16 -> 4457.4925 | BA17: =AZ17-BC17 -> 506.68008 | BB17: =(BA17/AY17)*12 -> 0.0096185296 | BC17: =AY17*($AX$1/12) -> 3950.8124 | BD17: =(BC17/AY17)*12 -> 0.075 | BE17: =BE16+BA17 -> 5876.6945 | BF17: =BF16+BC17 -> 47613.215 | BG17: =AY17-BA17 -> 631623.31 | BH17: =BE17+BF17 -> 53489.91 | BJ17: 12 | BK17: 45200 | BL17: =BT16 -> 631861.29 | BM17: =BM16 -> 4348.8738 | BN17: =BM17-BP17 -> 531.37848 | BO17: =(BN17/BL17)*12 -> 0.01009168 | BP17: =BL17*($BK$1/12) -> 3817.4953 | BQ17: =(BP17/BL17)*12 -> 0.0725 | BR17: =BR16+BN17 -> 6170.0867 | BS17: =BS16+BP17 -> 46016.399 | BT17: =BL17-BN17 -> 631329.91 | BU17: =BR17+BS17 -> 52186.485 | BW17: 12 | BX17: 45200 | BY17: =CG16 -> 631581.29 | BZ17: =BZ16 -> 4241.3034 | CA17: =BZ17-CC17 -> 557.07921 | CB17: =(CA17/BY17)*12 -> 0.010584466 | CC17: =BY17*($BX$1/12) -> 3684.2242 | CD17: =(CC17/BY17)*12 -> 0.07 | CE17: =CE16+CA17 -> 6475.7877 | CF17: =CF16+CC17 -> 44419.853 | CG17: =BY17-CA17 -> 631024.21 | CH17: =CE17+CF17 -> 50895.641
A18: =A17+1 -> 10 | B18: =VLOOKUP(A18*12,$J$5:$U$365,10) -> 499302.94 | C18: =VLOOKUP(A18*12,$W$5:$AH$365,10) -> 483074.89 | D18: =VLOOKUP(A18*12,$AJ$5:$AU$365,10) -> 466878.66 | E18: =VLOOKUP(A18*12,$AW$5:$BH$365,10) -> 450717.14 | F18: =VLOOKUP(A18*12,$BJ$5:$BU$365,10) -> 434593.34 | G18: =VLOOKUP(A18*12,$BW$5:$CH$365,10) -> 418510.35 | J18: 13 | K18: 45231 | L18: =T17 -> 632433.11 | M18: =$L$6/((($N$2)-1)/($N$1*$N$2)) -> 4789.3246 | N18: =M18-P18 -> 441.34699 | O18: =(N18/L18)*12 -> 0.0083742673 | P18: =L18*($K$1/12) -> 4347.9776 | Q18: =(P18/L18)*12 -> 0.0825 | R18: =R17+N18 -> 5508.2403 | S18: =S17+P18 -> 56752.98 | T18: =L18-N18 -> 631991.76 | U18: =R18+S18 -> 62261.22 | W18: 13 | X18: 45231 | Y18: =AG17 -> 632174.55 | Z18: =Z17 -> 4677.7492 | AA18: =Z18-AC18 -> 463.25213 | AB18: =(AA18/Y18)*12 -> 0.0087934978 | AC18: =Y18*($X$1/12) -> 4214.497 | AD18: =(AC18/Y18)*12 -> 0.08 | AE18: =AE17+AA18 -> 5788.6975 | AF18: =AF17+AC18 -> 55022.042 | AG18: =Y18-AA18 -> 631711.3 | AH18: =AE18+AF18 -> 60810.739 | AJ18: 13 | AK18: 45231 | AL18: =AT17 -> 631904.74 | AM18: =AM17 -> 4567.1281 | AN18: =AM18-AP18 -> 486.07664 | AO18: =(AN18/AL18)*12 -> 0.0092306947 | AP18: =AL18*($AK$1/12) -> 4081.0514 | AQ18: =(AP18/AL18)*12 -> 0.0775 | AR18: =AR17+AN18 -> 6081.34 | AS18: =AS17+AP18 -> 53291.325 | AT18: =AL18-AN18 -> 631418.66 | AU18: =AR18+AS18 -> 59372.665 | AW18: 13 | AX18: 45231 | AY18: =BG17 -> 631623.31 | AZ18: =AZ17 -> 4457.4925 | BA18: =AZ18-BC18 -> 509.84683 | BB18: =(BA18/AY18)*12 -> 0.0096864095 | BC18: =AY18*($AX$1/12) -> 3947.6457 | BD18: =(BC18/AY18)*12 -> 0.075 | BE18: =BE17+BA18 -> 6386.5413 | BF18: =BF17+BC18 -> 51560.861 | BG18: =AY18-BA18 -> 631113.46 | BH18: =BE18+BF18 -> 57947.402 | BJ18: 13 | BK18: 45231 | BL18: =BT17 -> 631329.91 | BM18: =BM17 -> 4348.8738 | BN18: =BM18-BP18 -> 534.58889 | BO18: =(BN18/BL18)*12 -> 0.010161196 | BP18: =BL18*($BK$1/12) -> 3814.2849 | BQ18: =(BP18/BL18)*12 -> 0.0725 | BR18: =BR17+BN18 -> 6704.6756 | BS18: =BS17+BP18 -> 49830.684 | BT18: =BL18-BN18 -> 630795.32 | BU18: =BR18+BS18 -> 56535.359 | BW18: 13 | BX18: 45231 | BY18: =CG17 -> 631024.21 | BZ18: =BZ17 -> 4241.3034 | CA18: =BZ18-CC18 -> 560.32883 | CB18: =(CA18/BY18)*12 -> 0.010655607 | CC18: =BY18*($BX$1/12) -> 3680.9746 | CD18: =(CC18/BY18)*12 -> 0.07 | CE18: =CE17+CA18 -> 7036.1165 | CF18: =CF17+CC18 -> 48100.828 | CG18: =BY18-CA18 -> 630463.88 | CH18: =CE18+CF18 -> 55136.944
A19: =A18+1 -> 11 | B19: =VLOOKUP(A19*12,$J$5:$U$365,10) -> 545245.38 | C19: =VLOOKUP(A19*12,$W$5:$AH$365,10) -> 527387.3 | D19: =VLOOKUP(A19*12,$AJ$5:$AU$365,10) -> 509569.39 | E19: =VLOOKUP(A19*12,$AW$5:$BH$365,10) -> 491795.09 | F19: =VLOOKUP(A19*12,$BJ$5:$BU$365,10) -> 474068.01 | G19: =VLOOKUP(A19*12,$BW$5:$CH$365,10) -> 456391.85 | J19: 14 | K19: 45261 | L19: =T18 -> 631991.76 | M19: =$L$6/((($N$2)-1)/($N$1*$N$2)) -> 4789.3246 | N19: =M19-P19 -> 444.38125 | O19: =(N19/L19)*12 -> 0.0084377287 | P19: =L19*($K$1/12) -> 4344.9433 | Q19: =(P19/L19)*12 -> 0.0825 | R19: =R18+N19 -> 5952.6215 | S19: =S18+P19 -> 61097.923 | T19: =L19-N19 -> 631547.38 | U19: =R19+S19 -> 67050.544 | W19: 14 | X19: 45261 | Y19: =AG18 -> 631711.3 | Z19: =Z18 -> 4677.7492 | AA19: =Z19-AC19 -> 466.34048 | AB19: =(AA19/Y19)*12 -> 0.0088586126 | AC19: =Y19*($X$1/12) -> 4211.4087 | AD19: =(AC19/Y19)*12 -> 0.08 | AE19: =AE18+AA19 -> 6255.038 | AF19: =AF18+AC19 -> 59233.45 | AG19: =Y19-AA19 -> 631244.96 | AH19: =AE19+AF19 -> 65488.488 | AJ19: 14 | AK19: 45261 | AL19: =AT18 -> 631418.66 | AM19: =AM18 -> 4567.1281 | AN19: =AM19-AP19 -> 489.21589 | AO19: =(AN19/AL19)*12 -> 0.0092974614 | AP19: =AL19*($AK$1/12) -> 4077.9122 | AQ19: =(AP19/AL19)*12 -> 0.0775 | AR19: =AR18+AN19 -> 6570.5559 | AS19: =AS18+AP19 -> 57369.237 | AT19: =AL19-AN19 -> 630929.44 | AU19: =AR19+AS19 -> 63939.793 | AW19: 14 | AX19: 45261 | AY19: =BG18 -> 631113.46 | AZ19: =AZ18 -> 4457.4925 | BA19: =AZ19-BC19 -> 513.03338 | BB19: =(BA19/AY19)*12 -> 0.0097548237 | BC19: =AY19*($AX$1/12) -> 3944.4591 | BD19: =(BC19/AY19)*12 -> 0.075 | BE19: =BE18+BA19 -> 6899.5747 | BF19: =BF18+BC19 -> 55505.32 | BG19: =AY19-BA19 -> 630600.43 | BH19: =BE19+BF19 -> 62404.895 | BJ19: 14 | BK19: 45261 | BL19: =BT18 -> 630795.32 | BM19: =BM18 -> 4348.8738 | BN19: =BM19-BP19 -> 537.8187 | BO19: =(BN19/BL19)*12 -> 0.01023125 | BP19: =BL19*($BK$1/12) -> 3811.0551 | BQ19: =(BP19/BL19)*12 -> 0.0725 | BR19: =BR18+BN19 -> 7242.4943 | BS19: =BS18+BP19 -> 53641.739 | BT19: =BL19-BN19 -> 630257.51 | BU19: =BR19+BS19 -> 60884.233 | BW19: 14 | BX19: 45261 | BY19: =CG18 -> 630463.88 | BZ19: =BZ18 -> 4241.3034 | CA19: =BZ19-CC19 -> 563.59742 | CB19: =(CA19/BY19)*12 -> 0.01072729 | CC19: =BY19*($BX$1/12) -> 3677.706 | CD19: =(CC19/BY19)*12 -> 0.07 | CE19: =CE18+CA19 -> 7599.7139 | CF19: =CF18+CC19 -> 51778.534 | CG19: =BY19-CA19 -> 629900.29 | CH19: =CE19+CF19 -> 59378.248
A20: =A19+1 -> 12 | B20: =VLOOKUP(A20*12,$J$5:$U$365,10) -> 590199.84 | C20: =VLOOKUP(A20*12,$W$5:$AH$365,10) -> 570718.62 | D20: =VLOOKUP(A20*12,$AJ$5:$AU$365,10) -> 551287.14 | E20: =VLOOKUP(A20*12,$AW$5:$BH$365,10) -> 531909.47 | F20: =VLOOKUP(A20*12,$BJ$5:$BU$365,10) -> 512589.83 | G20: =VLOOKUP(A20*12,$BW$5:$CH$365,10) -> 493332.56 | J20: 15 | K20: 45292 | L20: =T19 -> 631547.38 | M20: =$L$6/((($N$2)-1)/($N$1*$N$2)) -> 4789.3246 | N20: =M20-P20 -> 447.43637 | O20: =(N20/L20)*12 -> 0.0085017161 | P20: =L20*($K$1/12) -> 4341.8882 | Q20: =(P20/L20)*12 -> 0.0825 | R20: =R19+N20 -> 6400.0579 | S20: =S19+P20 -> 65439.811 | T20: =L20-N20 -> 631099.94 | U20: =R20+S20 -> 71839.869 | W20: 15 | X20: 45292 | Y20: =AG19 -> 631244.96 | Z20: =Z19 -> 4677.7492 | AA20: =Z20-AC20 -> 469.44941 | AB20: =(AA20/Y20)*12 -> 0.0089242581 | AC20: =Y20*($X$1/12) -> 4208.2997 | AD20: =(AC20/Y20)*12 -> 0.08 | AE20: =AE19+AA20 -> 6724.4874 | AF20: =AF19+AC20 -> 63441.75 | AG20: =Y20-AA20 -> 630775.51 | AH20: =AE20+AF20 -> 70166.237 | AJ20: 15 | AK20: 45292 | AL20: =AT19 -> 630929.44 | AM20: =AM19 -> 4567.1281 | AN20: =AM20-AP20 -> 492.37541 | AO20: =(AN20/AL20)*12 -> 0.0093647632 | AP20: =AL20*($AK$1/12) -> 4074.7527 | AQ20: =(AP20/AL20)*12 -> 0.0775 | AR20: =AR19+AN20 -> 7062.9313 | AS20: =AS19+AP20 -> 61443.99 | AT20: =AL20-AN20 -> 630437.07 | AU20: =AR20+AS20 -> 68506.921 | AW20: 15 | AX20: 45292 | AY20: =BG19 -> 630600.43 | AZ20: =AZ19 -> 4457.4925 | BA20: =AZ20-BC20 -> 516.23983 | BB20: =(BA20/AY20)*12 -> 0.0098237771 | BC20: =AY20*($AX$1/12) -> 3941.2527 | BD20: =(BC20/AY20)*12 -> 0.075 | BE20: =BE19+BA20 -> 7415.8145 | BF20: =BF19+BC20 -> 59446.573 | BG20: =AY20-BA20 -> 630084.19 | BH20: =BE20+BF20 -> 66862.387 | BJ20: 15 | BK20: 45292 | BL20: =BT19 -> 630257.51 | BM20: =BM19 -> 4348.8738 | BN20: =BM20-BP20 -> 541.06802 | BO20: =(BN20/BL20)*12 -> 0.010301847 | BP20: =BL20*($BK$1/12) -> 3807.8058 | BQ20: =(BP20/BL20)*12 -> 0.0725 | BR20: =BR19+BN20 -> 7783.5623 | BS20: =BS19+BP20 -> 57449.544 | BT20: =BL20-BN20 -> 629716.44 | BU20: =BR20+BS20 -> 65233.107 | BW20: 15 | BX20: 45292 | BY20: =CG19 -> 629900.29 | BZ20: =BZ19 -> 4241.3034 | CA20: =BZ20-CC20 -> 566.88507 | CB20: =(CA20/BY20)*12 -> 0.01079952 | CC20: =BY20*($BX$1/12) -> 3674.4183 | CD20: =(CC20/BY20)*12 -> 0.07 | CE20: =CE19+CA20 -> 8166.599 | CF20: =CF19+CC20 -> 55452.952 | CG20: =BY20-CA20 -> 629333.4 | CH20: =CE20+CF20 -> 63619.551
A21: =A20+1 -> 13 | B21: =VLOOKUP(A21*12,$J$5:$U$365,10) -> 634081.66 | C21: =VLOOKUP(A21*12,$W$5:$AH$365,10) -> 612987.4 | D21: =VLOOKUP(A21*12,$AJ$5:$AU$365,10) -> 591953.77 | E21: =VLOOKUP(A21*12,$AW$5:$BH$365,10) -> 570985.47 | F21: =VLOOKUP(A21*12,$BJ$5:$BU$365,10) -> 550087.37 | G21: =VLOOKUP(A21*12,$BW$5:$CH$365,10) -> 529264.46 | J21: 16 | K21: 45323 | L21: =T20 -> 631099.94 | M21: =$L$6/((($N$2)-1)/($N$1*$N$2)) -> 4789.3246 | N21: =M21-P21 -> 450.5125 | O21: =(N21/L21)*12 -> 0.0085662343 | P21: =L21*($K$1/12) -> 4338.8121 | Q21: =(P21/L21)*12 -> 0.0825 | R21: =R20+N21 -> 6850.5704 | S21: =S20+P21 -> 69778.623 | T21: =L21-N21 -> 630649.43 | U21: =R21+S21 -> 76629.194 | W21: 16 | X21: 45323 | Y21: =AG20 -> 630775.51 | Z21: =Z20 -> 4677.7492 | AA21: =Z21-AC21 -> 472.57907 | AB21: =(AA21/Y21)*12 -> 0.0089904392 | AC21: =Y21*($X$1/12) -> 4205.1701 | AD21: =(AC21/Y21)*12 -> 0.08 | AE21: =AE20+AA21 -> 7197.0665 | AF21: =AF20+AC21 -> 67646.92 | AG21: =Y21-AA21 -> 630302.93 | AH21: =AE21+AF21 -> 74843.987 | AJ21: 16 | AK21: 45323 | AL21: =AT20 -> 630437.07 | AM21: =AM20 -> 4567.1281 | AN21: =AM21-AP21 -> 495.55533 | AO21: =(AN21/AL21)*12 -> 0.0094326052 | AP21: =AL21*($AK$1/12) -> 4071.5727 | AQ21: =(AP21/AL21)*12 -> 0.0775 | AR21: =AR20+AN21 -> 7558.4866 | AS21: =AS20+AP21 -> 65515.562 | AT21: =AL21-AN21 -> 629941.51 | AU21: =AR21+AS21 -> 73074.049 | AW21: 16 | AX21: 45323 | AY21: =BG20 -> 630084.19 | AZ21: =AZ20 -> 4457.4925 | BA21: =AZ21-BC21 -> 519.46633 | BB21: =(BA21/AY21)*12 -> 0.0098932748 | BC21: =AY21*($AX$1/12) -> 3938.0262 | BD21: =(BC21/AY21)*12 -> 0.075 | BE21: =BE20+BA21 -> 7935.2808 | BF21: =BF20+BC21 -> 63384.599 | BG21: =AY21-BA21 -> 629564.72 | BH21: =BE21+BF21 -> 71319.88 | BJ21: 16 | BK21: 45323 | BL21: =BT20 -> 629716.44 | BM21: =BM20 -> 4348.8738 | BN21: =BM21-BP21 -> 544.33697 | BO21: =(BN21/BL21)*12 -> 0.010372992 | BP21: =BL21*($BK$1/12) -> 3804.5368 | BQ21: =(BP21/BL21)*12 -> 0.0725 | BR21: =BR20+BN21 -> 8327.8993 | BS21: =BS20+BP21 -> 61254.081 | BT21: =BL21-BN21 -> 629172.1 | BU21: =BR21+BS21 -> 69581.981 | BW21: 16 | BX21: 45323 | BY21: =CG20 -> 629333.4 | BZ21: =BZ20 -> 4241.3034 | CA21: =BZ21-CC21 -> 570.1919 | CB21: =(CA21/BY21)*12 -> 0.010872302 | CC21: =BY21*($BX$1/12) -> 3671.1115 | CD21: =(CC21/BY21)*12 -> 0.07 | CE21: =CE20+CA21 -> 8736.7909 | CF21: =CF20+CC21 -> 59124.064 | CG21: =BY21-CA21 -> 628763.21 | CH21: =CE21+CF21 -> 67860.855
... A38: =A37+1 -> 30 | B38: =VLOOKUP(A38*12,$J$5:$U$365,10) -> 1086656.9 | C38: =VLOOKUP(A38*12,$W$5:$AH$365,10) -> 1046489.7 | D38: =VLOOKUP(A38*12,$AJ$5:$AU$365,10) -> 1006666.1 | E38: =VLOOKUP(A38*12,$AW$5:$BH$365,10) -> 967197.3 | F38: =VLOOKUP(A38*12,$BJ$5:$BU$365,10) -> 928094.56 | G38: =VLOOKUP(A38*12,$BW$5:$CH$365,10) -> 889369.23 | J38: 33 | K38: 45839 | L38: =T37 -> 623005.17 | M38: =$L$6/((($N$2)-1)/($N$1*$N$2)) -> 4789.3246 | N38: =M38-P38 -> 506.16408 | O38: =(N38/L38)*12 -> 0.0097494681 | P38: =L38*($K$1/12) -> 4283.1605 | Q38: =(P38/L38)*12 -> 0.0825 | R38: =R37+N38 -> 15000.998 | S38: =S37+P38 -> 143046.71 | T38: =L38-N38 -> 622499 | U38: =R38+S38 -> 158047.71 | W38: 33 | X38: 45839 | Y38: =AG37 -> 622298.58 | Z38: =Z37 -> 4677.7492 | AA38: =Z38-AC38 -> 529.09199 | AB38: =(AA38/Y38)*12 -> 0.010202665 | AC38: =Y38*($X$1/12) -> 4148.6572 | AD38: =(AC38/Y38)*12 -> 0.08 | AE38: =AE37+AA38 -> 15730.517 | AF38: =AF37+AC38 -> 138635.21 | AG38: =Y38-AA38 -> 621769.48 | AH38: =AE38+AF38 -> 154365.72 | AJ38: 33 | AK38: 45839 | AL38: =AT37 -> 621562.99 | AM38: =AM37 -> 4567.1281 | AN38: =AM38-AP38 -> 552.86711 | AO38: =(AN38/AL38)*12 -> 0.010673746 | AP38: =AL38*($AK$1/12) -> 4014.261 | AQ38: =(AP38/AL38)*12 -> 0.0775 | AR38: =AR37+AN38 -> 16489.88 | AS38: =AS37+AP38 -> 134225.35 | AT38: =AL38-AN38 -> 621010.12 | AU38: =AR38+AS38 -> 150715.23 | AW38: 33 | AX38: 45839 | AY38: =BG37 -> 620797.61 | AZ38: =AZ37 -> 4457.4925 | BA38: =AZ38-BC38 -> 577.50745 | BB38: =(BA38/AY38)*12 -> 0.011163203 | BC38: =AY38*($AX$1/12) -> 3879.985 | BD38: =(BC38/AY38)*12 -> 0.075 | BE38: =BE37+BA38 -> 17279.901 | BF38: =BF37+BC38 -> 129817.35 | BG38: =AY38-BA38 -> 620220.1 | BH38: =BE38+BF38 -> 147097.25 | BJ38: 33 | BK38: 45839 | BL38: =BT37 -> 620001.64 | BM38: =BM37 -> 4348.8738 | BN38: =BM38-BP38 -> 603.03052 | BO38: =(BN38/BL38)*12 -> 0.011671527 | BP38: =BL38*($BK$1/12) -> 3745.8433 | BQ38: =(BP38/BL38)*12 -> 0.0725 | BR38: =BR37+BN38 -> 18101.386 | BS38: =BS37+BP38 -> 125411.45 | BT38: =BL38-BN38 -> 619398.61 | BU38: =BR38+BS38 -> 143512.83 | BW38: 33 | BX38: 45839 | BY38: =CG37 -> 619174.32 | BZ38: =BZ37 -> 4241.3034 | CA38: =BZ38-CC38 -> 629.45321 | CB38: =(CA38/BY38)*12 -> 0.012199212 | CC38: =BY38*($BX$1/12) -> 3611.8502 | CD38: =(CC38/BY38)*12 -> 0.07 | CE38: =CE37+CA38 -> 18955.134 | CF38: =CF37+CC38 -> 121007.88 | CG38: =BY38-CA38 -> 618544.87 | CH38: =CE38+CF38 -> 139963.01
J39: 34 | K39: 45870 | L39: =T38 -> 622499 | M39: =$L$6/((($N$2)-1)/($N$1*$N$2)) -> 4789.3246 | N39: =M39-P39 -> 509.64396 | O39: =(N39/L39)*12 -> 0.0098244777 | P39: =L39*($K$1/12) -> 4279.6806 | Q39: =(P39/L39)*12 -> 0.0825 | R39: =R38+N39 -> 15510.642 | S39: =S38+P39 -> 147326.39 | T39: =L39-N39 -> 621989.36 | U39: =R39+S39 -> 162837.04 | W39: 34 | X39: 45870 | Y39: =AG38 -> 621769.48 | Z39: =Z38 -> 4677.7492 | AA39: =Z39-AC39 -> 532.61927 | AB39: =(AA39/Y39)*12 -> 0.010279423 | AC39: =Y39*($X$1/12) -> 4145.1299 | AD39: =(AC39/Y39)*12 -> 0.08 | AE39: =AE38+AA39 -> 16263.136 | AF39: =AF38+AC39 -> 142780.34 | AG39: =Y39-AA39 -> 621236.86 | AH39: =AE39+AF39 -> 159043.47 | AJ39: 34 | AK39: 45870 | AL39: =AT38 -> 621010.12 | AM39: =AM38 -> 4567.1281 | AN39: =AM39-AP39 -> 556.43771 | AO39: =(AN39/AL39)*12 -> 0.010752244 | AP39: =AL39*($AK$1/12) -> 4010.6904 | AQ39: =(AP39/AL39)*12 -> 0.0775 | AR39: =AR38+AN39 -> 17046.318 | AS39: =AS38+AP39 -> 138236.04 | AT39: =AL39-AN39 -> 620453.68 | AU39: =AR39+AS39 -> 155282.35 | AW39: 34 | AX39: 45870 | AY39: =BG38 -> 620220.1 | AZ39: =AZ38 -> 4457.4925 | BA39: =AZ39-BC39 -> 581.11687 | BB39: =(BA39/AY39)*12 -> 0.011243432 | BC39: =AY39*($AX$1/12) -> 3876.3756 | BD39: =(BC39/AY39)*12 -> 0.075 | BE39: =BE38+BA39 -> 17861.018 | BF39: =BF38+BC39 -> 133693.73 | BG39: =AY39-BA39 -> 619638.98 | BH39: =BE39+BF39 -> 151554.74 | BJ39: 34 | BK39: 45870 | BL39: =BT38 -> 619398.61 | BM39: =BM38 -> 4348.8738 | BN39: =BM39-BP39 -> 606.67383 | BO39: =(BN39/BL39)*12 -> 0.011753475 | BP39: =BL39*($BK$1/12) -> 3742.2 | BQ39: =(BP39/BL39)*12 -> 0.0725 | BR39: =BR38+BN39 -> 18708.06 | BS39: =BS38+BP39 -> 129153.65 | BT39: =BL39-BN39 -> 618791.94 | BU39: =BR39+BS39 -> 147861.71 | BW39: 34 | BX39: 45870 | BY39: =CG38 -> 618544.87 | BZ39: =BZ38 -> 4241.3034 | CA39: =BZ39-CC39 -> 633.12502 | CB39: =(CA39/BY39)*12 -> 0.01228286 | CC39: =BY39*($BX$1/12) -> 3608.1784 | CD39: =(CC39/BY39)*12 -> 0.07 | CE39: =CE38+CA39 -> 19588.259 | CF39: =CF38+CC39 -> 124616.06 | CG39: =BY39-CA39 -> 617911.74 | CH39: =CE39+CF39 -> 144204.32
J40: 35 | K40: 45901 | L40: =T39 -> 621989.36 | M40: =$L$6/((($N$2)-1)/($N$1*$N$2)) -> 4789.3246 | N40: =M40-P40 -> 513.14777 | O40: =(N40/L40)*12 -> 0.0099001263 | P40: =L40*($K$1/12) -> 4276.1768 | Q40: =(P40/L40)*12 -> 0.0825 | R40: =R39+N40 -> 16023.79 | S40: =S39+P40 -> 151602.57 | T40: =L40-N40 -> 621476.21 | U40: =R40+S40 -> 167626.36 | W40: 35 | X40: 45901 | Y40: =AG39 -> 621236.86 | Z40: =Z39 -> 4677.7492 | AA40: =Z40-AC40 -> 536.17007 | AB40: =(AA40/Y40)*12 -> 0.010356824 | AC40: =Y40*($X$1/12) -> 4141.5791 | AD40: =(AC40/Y40)*12 -> 0.08 | AE40: =AE39+AA40 -> 16799.306 | AF40: =AF39+AC40 -> 146921.91 | AG40: =Y40-AA40 -> 620700.69 | AH40: =AE40+AF40 -> 163721.22 | AJ40: 35 | AK40: 45901 | AL40: =AT39 -> 620453.68 | AM40: =AM39 -> 4567.1281 | AN40: =AM40-AP40 -> 560.03137 | AO40: =(AN40/AL40)*12 -> 0.010831391 | AP40: =AL40*($AK$1/12) -> 4007.0967 | AQ40: =(AP40/AL40)*12 -> 0.0775 | AR40: =AR39+AN40 -> 17606.349 | AS40: =AS39+AP40 -> 142243.13 | AT40: =AL40-AN40 -> 619893.65 | AU40: =AR40+AS40 -> 159849.48 | AW40: 35 | AX40: 45901 | AY40: =BG39 -> 619638.98 | AZ40: =AZ39 -> 4457.4925 | BA40: =AZ40-BC40 -> 584.74885 | BB40: =(BA40/AY40)*12 -> 0.011324314 | BC40: =AY40*($AX$1/12) -> 3872.7436 | BD40: =(BC40/AY40)*12 -> 0.075 | BE40: =BE39+BA40 -> 18445.767 | BF40: =BF39+BC40 -> 137566.47 | BG40: =AY40-BA40 -> 619054.23 | BH40: =BE40+BF40 -> 156012.24 | BJ40: 35 | BK40: 45901 | BL40: =BT39 -> 618791.94 | BM40: =BM39 -> 4348.8738 | BN40: =BM40-BP40 -> 610.33915 | BO40: =(BN40/BL40)*12 -> 0.011836078 | BP40: =BL40*($BK$1/12) -> 3738.5346 | BQ40: =(BP40/BL40)*12 -> 0.0725 | BR40: =BR39+BN40 -> 19318.399 | BS40: =BS39+BP40 -> 132892.18 | BT40: =BL40-BN40 -> 618181.6 | BU40: =BR40+BS40 -> 152210.58 | BW40: 35 | BX40: 45901 | BY40: =CG39 -> 617911.74 | BZ40: =BZ39 -> 4241.3034 | CA40: =BZ40-CC40 -> 636.81825 | CB40: =(CA40/BY40)*12 -> 0.012367169 | CC40: =BY40*($BX$1/12) -> 3604.4852 | CD40: =(CC40/BY40)*12 -> 0.07 | CE40: =CE39+CA40 -> 20225.077 | CF40: =CF39+CC40 -> 128220.54 | CG40: =BY40-CA40 -> 617274.92 | CH40: =CE40+CF40 -> 148445.62
J41: 36 | K41: 45931 | L41: =T40 -> 621476.21 | M41: =$L$6/((($N$2)-1)/($N$1*$N$2)) -> 4789.3246 | N41: =M41-P41 -> 516.67566 | O41: =(N41/L41)*12 -> 0.0099764203 | P41: =L41*($K$1/12) -> 4272.6489 | Q41: =(P41/L41)*12 -> 0.0825 | R41: =R40+N41 -> 16540.466 | S41: =S40+P41 -> 155875.22 | T41: =L41-N41 -> 620959.53 | U41: =R41+S41 -> 172415.69 | W41: 36 | X41: 45931 | Y41: =AG40 -> 620700.69 | Z41: =Z40 -> 4677.7492 | AA41: =Z41-AC41 -> 539.74453 | AB41: =(AA41/Y41)*12 -> 0.010434875 | AC41: =Y41*($X$1/12) -> 4138.0046 | AD41: =(AC41/Y41)*12 -> 0.08 | AE41: =AE40+AA41 -> 17339.051 | AF41: =AF40+AC41 -> 151059.92 | AG41: =Y41-AA41 -> 620160.95 | AH41: =AE41+AF41 -> 168398.97 | AJ41: 36 | AK41: 45931 | AL41: =AT40 -> 619893.65 | AM41: =AM40 -> 4567.1281 | AN41: =AM41-AP41 -> 563.64824 | AO41: =(AN41/AL41)*12 -> 0.010911192 | AP41: =AL41*($AK$1/12) -> 4003.4798 | AQ41: =(AP41/AL41)*12 -> 0.0775 | AR41: =AR40+AN41 -> 18169.998 | AS41: =AS40+AP41 -> 146246.61 | AT41: =AL41-AN41 -> 619330 | AU41: =AR41+AS41 -> 164416.61 | AW41: 36 | AX41: 45931 | AY41: =BG40 -> 619054.23 | AZ41: =AZ40 -> 4457.4925 | BA41: =AZ41-BC41 -> 588.40353 | BB41: =(BA41/AY41)*12 -> 0.011405854 | BC41: =AY41*($AX$1/12) -> 3869.089 | BD41: =(BC41/AY41)*12 -> 0.075 | BE41: =BE40+BA41 -> 19034.17 | BF41: =BF40+BC41 -> 141435.56 | BG41: =AY41-BA41 -> 618465.83 | BH41: =BE41+BF41 -> 160469.73 | BJ41: 36 | BK41: 45931 | BL41: =BT40 -> 618181.6 | BM41: =BM40 -> 4348.8738 | BN41: =BM41-BP41 -> 614.02661 | BO41: =(BN41/BL41)*12 -> 0.011919344 | BP41: =BL41*($BK$1/12) -> 3734.8472 | BQ41: =(BP41/BL41)*12 -> 0.0725 | BR41: =BR40+BN41 -> 19932.426 | BS41: =BS40+BP41 -> 136627.03 | BT41: =BL41-BN41 -> 617567.57 | BU41: =BR41+BS41 -> 156559.46 | BW41: 36 | BX41: 45931 | BY41: =CG40 -> 617274.92 | BZ41: =BZ40 -> 4241.3034 | CA41: =BZ41-CC41 -> 640.53302 | CB41: =(CA41/BY41)*12 -> 0.012452144 | CC41: =BY41*($BX$1/12) -> 3600.7704 | CD41: =(CC41/BY41)*12 -> 0.07 | CE41: =CE40+CA41 -> 20865.61 | CF41: =CF40+CC41 -> 131821.31 | CG41: =BY41-CA41 -> 616634.39 | CH41: =CE41+CF41 -> 152686.92
J42: 37 | K42: 45962 | L42: =T41 -> 620959.53 | M42: =$L$6/((($N$2)-1)/($N$1*$N$2)) -> 4789.3246 | N42: =M42-P42 -> 520.2278 | O42: =(N42/L42)*12 -> 0.010053366 | P42: =L42*($K$1/12) -> 4269.0968 | Q42: =(P42/L42)*12 -> 0.0825 | R42: =R41+N42 -> 17060.693 | S42: =S41+P42 -> 160144.32 | T42: =L42-N42 -> 620439.31 | U42: =R42+S42 -> 177205.01 | W42: 37 | X42: 45962 | Y42: =AG41 -> 620160.95 | Z42: =Z41 -> 4677.7492 | AA42: =Z42-AC42 -> 543.34283 | AB42: =(AA42/Y42)*12 -> 0.010513584 | AC42: =Y42*($X$1/12) -> 4134.4063 | AD42: =(AC42/Y42)*12 -> 0.08 | AE42: =AE41+AA42 -> 17882.394 | AF42: =AF41+AC42 -> 155194.33 | AG42: =Y42-AA42 -> 619617.61 | AH42: =AE42+AF42 -> 173076.72 | AJ42: 37 | AK42: 45962 | AL42: =AT41 -> 619330 | AM42: =AM41 -> 4567.1281 | AN42: =AM42-AP42 -> 567.28847 | AO42: =(AN42/AL42)*12 -> 0.010991655 | AP42: =AL42*($AK$1/12) -> 3999.8396 | AQ42: =(AP42/AL42)*12 -> 0.0775 | AR42: =AR41+AN42 -> 18737.286 | AS42: =AS41+AP42 -> 150246.45 | AT42: =AL42-AN42 -> 618762.71 | AU42: =AR42+AS42 -> 168983.74 | AW42: 37 | AX42: 45962 | AY42: =BG41 -> 618465.83 | AZ42: =AZ41 -> 4457.4925 | BA42: =AZ42-BC42 -> 592.08106 | BB42: =(BA42/AY42)*12 -> 0.01148806 | BC42: =AY42*($AX$1/12) -> 3865.4114 | BD42: =(BC42/AY42)*12 -> 0.075 | BE42: =BE41+BA42 -> 19626.251 | BF42: =BF41+BC42 -> 145300.97 | BG42: =AY42-BA42 -> 617873.75 | BH42: =BE42+BF42 -> 164927.22 | BJ42: 37 | BK42: 45962 | BL42: =BT41 -> 617567.57 | BM42: =BM41 -> 4348.8738 | BN42: =BM42-BP42 -> 617.73636 | BO42: =(BN42/BL42)*12 -> 0.01200328 | BP42: =BL42*($BK$1/12) -> 3731.1374 | BQ42: =(BP42/BL42)*12 -> 0.0725 | BR42: =BR41+BN42 -> 20550.162 | BS42: =BS41+BP42 -> 140358.17 | BT42: =BL42-BN42 -> 616949.84 | BU42: =BR42+BS42 -> 160908.33 | BW42: 37 | BX42: 45962 | BY42: =CG41 -> 616634.39 | BZ42: =BZ41 -> 4241.3034 | CA42: =BZ42-CC42 -> 644.26947 | CB42: =(CA42/BY42)*12 -> 0.012537792 | CC42: =BY42*($BX$1/12) -> 3597.0339 | CD42: =(CC42/BY42)*12 -> 0.07 | CE42: =CE41+CA42 -> 21509.88 | CF42: =CF41+CC42 -> 135418.35 | CG42: =BY42-CA42 -> 615990.12 | CH42: =CE42+CF42 -> 156928.23
J43: 38 | K43: 45992 | L43: =T42 -> 620439.31 | M43: =$L$6/((($N$2)-1)/($N$1*$N$2)) -> 4789.3246 | N43: =M43-P43 -> 523.80437 | O43: =(N43/L43)*12 -> 0.010130971 | P43: =L43*($K$1/12) -> 4265.5202 | Q43: =(P43/L43)*12 -> 0.0825 | R43: =R42+N43 -> 17584.498 | S43: =S42+P43 -> 164409.84 | T43: =L43-N43 -> 619915.5 | U43: =R43+S43 -> 181994.33 | W43: 38 | X43: 45992 | Y43: =AG42 -> 619617.61 | Z43: =Z42 -> 4677.7492 | AA43: =Z43-AC43 -> 546.96512 | AB43: =(AA43/Y43)*12 -> 0.010592955 | AC43: =Y43*($X$1/12) -> 4130.784 | AD43: =(AC43/Y43)*12 -> 0.08 | AE43: =AE42+AA43 -> 18429.359 | AF43: =AF42+AC43 -> 159325.11 | AG43: =Y43-AA43 -> 619070.64 | AH43: =AE43+AF43 -> 177754.47 | AJ43: 38 | AK43: 45992 | AL43: =AT42 -> 618762.71 | AM43: =AM42 -> 4567.1281 | AN43: =AM43-AP43 -> 570.9522 | AO43: =(AN43/AL43)*12 -> 0.011072785 | AP43: =AL43*($AK$1/12) -> 3996.1759 | AQ43: =(AP43/AL43)*12 -> 0.0775 | AR43: =AR42+AN43 -> 19308.238 | AS43: =AS42+AP43 -> 154242.63 | AT43: =AL43-AN43 -> 618191.76 | AU43: =AR43+AS43 -> 173550.87 | AW43: 38 | AX43: 45992 | AY43: =BG42 -> 617873.75 | AZ43: =AZ42 -> 4457.4925 | BA43: =AZ43-BC43 -> 595.78156 | BB43: =(BA43/AY43)*12 -> 0.011570938 | BC43: =AY43*($AX$1/12) -> 3861.7109 | BD43: =(BC43/AY43)*12 -> 0.075 | BE43: =BE42+BA43 -> 20222.033 | BF43: =BF42+BC43 -> 149162.68 | BG43: =AY43-BA43 -> 617277.97 | BH43: =BE43+BF43 -> 169384.71 | BJ43: 38 | BK43: 45992 | BL43: =BT42 -> 616949.84 | BM43: =BM42 -> 4348.8738 | BN43: =BM43-BP43 -> 621.46852 | BO43: =(BN43/BL43)*12 -> 0.012087891 | BP43: =BL43*($BK$1/12) -> 3727.4053 | BQ43: =(BP43/BL43)*12 -> 0.0725 | BR43: =BR42+BN43 -> 21171.631 | BS43: =BS42+BP43 -> 144085.57 | BT43: =BL43-BN43 -> 616328.37 | BU43: =BR43+BS43 -> 165257.2 | BW43: 38 | BX43: 45992 | BY43: =CG42 -> 615990.12 | BZ43: =BZ42 -> 4241.3034 | CA43: =BZ43-CC43 -> 648.0277 | CB43: =(CA43/BY43)*12 -> 0.012624119 | CC43: =BY43*($BX$1/12) -> 3593.2757 | CD43: =(CC43/BY43)*12 -> 0.07 | CE43: =CE42+CA43 -> 22157.907 | CF43: =CF42+CC43 -> 139011.62 | CG43: =BY43-CA43 -> 615342.09 | CH43: =CE43+CF43 -> 161169.53
