Workbook
Name If: #REF!
Name If: #REF!

Sheet Calculators
A3: Year | C3: Annual ROI | G3: Year | I3: Annual ROI | S3: IRR | T3: =XIRR(T4:T10,R4:R10) -> 0.21632629
A4: 0 | B4: 100000 | G4: 0 | H4: 100000 | M4: Present Value=Future Value /( 1+i)^n | R4: 45292 | S4: Initial Investment | T4: -8500000
A5: =A4+1 -> 1 | B5: 110000 | C5: =(B5/B4)-1 -> 0.1 | G5: =G4+1 -> 1 | H5: 110000 | I5: =(H5/H4)-1 -> 0.1 | M5: interest | N5: 0.08 | R5: =R4+365 -> 45657 | S5: Year 1 Cashflow | T5: =-$T$4*$U$5 -> 1360000 | U5: 0.16 | V5: Cash On Cash
A6: =A5+1 -> 2 | B6: 105000 | C6: =(B6/B5)-1 -> -0.045454545 | G6: =G5+1 -> 2 | H6: 105000 | I6: =(H6/H5)-1 -> -0.045454545 | M6: time (yrs) | N6: 5 | O6: =N6*12 -> 60 | R6: =R5+365 -> 46022 | S6: Year 2 Cashflow | T6: =-$T$4*$U$5 -> 1360000
A7: =A6+1 -> 3 | B7: 120000 | C7: =(B7/B6)-1 -> 0.14285714 | G7: =G6+1 -> 3 | H7: 120000 | I7: =(H7/H6)-1 -> 0.14285714 | R7: =R6+365 -> 46387 | S7: Year 3 Cashflow | T7: =-$T$4*$U$5 -> 1360000
A8: =A7+1 -> 4 | B8: =B7+5000 -> 125000 | C8: =(B8/B7)-1 -> 0.041666667 | G8: =G7+1 -> 4 | H8: =H7+5000 -> 125000 | I8: =(H8/H7)-1 -> 0.041666667 | R8: =R7+365 -> 46752 | S8: Year 4 Cashflow | T8: =-$T$4*$U$5 -> 1360000
A9: =A8+1 -> 5 | B9: =B8+5000 -> 130000 | C9: =(B9/B8)-1 -> 0.04 | G9: =G8+1 -> 5 | H9: =H8+5000 -> 130000 | I9: =(H9/H8)-1 -> 0.04 | R9: =R8+365 -> 47117 | S9: Year 5 Cashflow | T9: =-$T$4*$U$5 -> 1360000
A10: =A9+1 -> 6 | B10: =B9+5000 -> 135000 | C10: =(B10/B9)-1 -> 0.038461538 | R10: =R9+365 -> 47482 | S10: 6 | T10: =-T4*(1+U10)^S10 -> 14813534 | U10: 0.097 | V10: Assumed Appreciation
A11: =A10+1 -> 7 | B11: =B10+5000 -> 140000 | C11: =(B11/B10)-1 -> 0.037037037 | I11: =(H9-H4)/H4 -> 0.3 | J11: ROI
A12: =A11+1 -> 8 | B12: =B11+5000 -> 145000 | C12: =(B12/B11)-1 -> 0.035714286 | I12: =SUM(I5:I9)/COUNT(I5:I9) -> 0.055813853 | J12: AAR
A13: =A12+1 -> 9 | B13: =B12+5000 -> 150000 | C13: =(B13/B12)-1 -> 0.034482759 | I13: =(H9/H4)^(1/COUNT(I4:I9))-1 -> 0.053873952 | J13: CAGR | M13: 0.105 | N13: projected Cash On Cash Return
A14: =A13+1 -> 10 | B14: =B13+5000 -> 155000 | C14: =(B14/B13)-1 -> 0.033333333 | I14: =H9/H4 -> 1.3 | J14: Equity Multiplier | M14: 8500000 | N14: initial investment
M15: =O15*12 -> 60 | N15: hold period | O15: 5
C16: =(B14-B4)/B4 -> 0.55 | D16: ROI
C17: =SUM(C5:C14)/COUNT(C5:C14) -> 0.045809822 | D17: AAR | M17: Future | N17: =M14*(1+M13/12)^(M15) -> 14336125 | O17: =N17/M14 -> 1.686603 | P17: Equity Multiple
C18: =(B14/B4)^(1/COUNT(C4:C14))-1 -> 0.044800014 | D18: CAGR | M18: CAGR | N18: =(N17/M14)^(1/(O15*4))-1 -> 0.026480357
C19: =B14/B4 -> 1.55 | D19: Equity Multiplier

Sheet STR Calculator
A1: 2974 Ginas Way, Sevierville, TN 37862 | MLS #303878 | Zillow | B1: https://www.youtube.com/watch?v=htWCJ51RIyg | H1: Heloc Down Payment | I1: 0.0825
A2: 2974 Ginas Way - 3bd / 4bath - 1927 sqft | B2: 1927 | C2: sqft | D2: =A3/B2 -> 415.15309 | E2: per sqft | H2: Heloc Loan Terms | I2: 20 | J2: yrs
A3: =B5 -> 800000 | B3: asking price | H3: HELOC Amount | I3: =SUM(B7+B6-C5-C4) -> 105000
C4: 5000 | D4: earnest money | H4: HELOC P&I Payment | I4: =-PMT($I$1/12,$I$2*12,I3) -> 894.66893 | J4: =I4*12 -> 10736.027 | L4: IRR | M4: =IRR(M5:M11) -> 0.031714733
A5: Purchase Price | B5: 800000 | C5: 50000 | D5: cash | H5: HELOC Principle Payment | I5: =-PPMT($I$1/12,1,$I$2*12,I3) -> 172.79393 | J5: =I5*12 -> 2073.5272 | L5: Initial Investment | M5: =-B5 -> -800000
A6: Closing Costs (4%) | B6: 0 | C6: $B$5*0.04 | H6: HELOC Interest Only Payment | I6: =-IPMT($I$1/12,1,$I$2*12,I3) -> 721.875 | J6: =I6*12 -> 8662.5 | L6: Year 1 Cashflow | M6: ='STR 10 Year'!B39 -> 9539.7062
A7: Down Payment | B7: =B5*C7 -> 160000 | C7: 0.2 | D7: downpayment | L7: Year 2 Cashflow | M7: ='STR 10 Year'!C39 -> 10787.706
A8: Total Loan Amount | B8: =B5-B7 -> 640000 | H8: Conventional Loan Interest Rate | I8: =IF(C7=0.1,0.08062,0.0775) -> 0.0775 | J8: IF(C7=0.1,0.08062,0.0775) | L8: Year 3 Cashflow | M8: ='STR 10 Year'!D39 -> 11742.036
H9: Loan Term | I9: 30 | J9: yrs | L9: Year 4 Cashflow | M9: ='STR 10 Year'!E39 -> 12702.64
B10: Nightly | C10: Monthly | D10: Annually | H10: Monthly Payment on Purchase Price | I10: =-PMT($I$8/12,$I$9*12,$B$8) -> 4585.0384 | L10: Year 5 Cashflow | M10: ='STR 10 Year'!F39 -> 13669.457
A11: Average Rent | B11: 300 | C11: =B11*30.5 -> 9150 | D11: =C11*12 -> 109800 | H11: Monthly Interest Payment on Purchase Price | I11: =-IPMT($I$8/12,1,$I$9*12,$B$8) -> 4133.3333 | L11: 6 | M11: =$B$5*(1+0.02)^L11 -> 900929.94 | N11: assumes 2%/yr appreciation
A12: Occupancy Rate | B12: 1 | C12: =-C11*(1-B12) -> 0 | D12: =C12*12 -> 0 | H12: Monthly Principle Payment on Purchase Price | I12: =-PPMT($I$8/12,1,$I$9*12,$B$8) -> 451.70504 | J12: =I12*12 -> 5420.4605
A13: Additional Income (Laundry/Storage etc) | C13: 0 | D13: =C13*12 -> 0
H14: Financials
A15: Calculated Gross Revenue | C15: =SUM(C11:C13) -> 9150 | D15: =C15*12 -> 109800 | H15: Cash On Cash Return (CoC) | I15: =C45/SUM($B$6:$B$7,B60) -> 0.022032636 | L15: Desired Return | M15: 0.08
H16: ROE (Return on Equity) | I16: =C45/B7 -> 0.022810664
A17: Estimated Expenses | B17: Monthly | C17: Annually | H17: AAR | I17: ='STR 10 Year'!L50 -> 0.16578848 | L17: IRR | O17: NPV
A18: Management Fees | B18: =C11*D18 -> 0 | C18: =B18*12 -> 0 | D18: 0 | E18: =IF(D18=0,1,0) -> 1 | H18: Mortgage Pay Down yr 1 | I18: =PPMT($I$8/12,1,$I$9*12,$B$8)*12 -> -5420.4605 | L18: 45536 | M18: 0 | N18: =-SUM('STR Calculator'!B6:B7,B60) -> -165650 | O18: =N18 -> -165650
A19: Subscriptions (AirDnA/Pricelabs/Guesty) | B19: 50 | C19: =B19*12 -> 600 | H19: Tax Savings at 25% | I19: =C45*0.25 -> 912.42655 | L19: 45901 | M19: 1 | N19: ='STR 10 Year'!B39 -> 9539.7062 | O19: =N19/(1+$M$15)^M19 -> 8833.0613
A20: AirBnB / VRBO Fee (3% of nightly) | B20: 0 | C20: =B20*12 -> 0 | L20: 46266 | M20: 2 | N20: ='STR 10 Year'!C39 -> 10787.706 | O20: =N20/(1+$M$15)^M20 -> 9248.7193
A21: Property Taxes / Year | B21: 200 | C21: =B21*12 -> 2400 | D21: =C21/B5 -> 0.003 | H21: Rules of Thumb | L21: 46631 | M21: 3 | N21: ='STR 10 Year'!D39 -> 11742.036 | O21: =N21/(1+$M$15)^M21 -> 9321.2069
A22: Insurance / Year | B22: 300 | C22: =B22*12 -> 3600 | D22: =C22/B5 -> 0.0045 | H22: 2% Rule | I22: =$C$11/$B$5 -> 0.0114375 | L22: 46997 | M22: 4 | N22: ='STR 10 Year'!E39 -> 12702.64 | O22: =N22/(1+$M$15)^M22 -> 9336.8198
A23: Cleaners (per stay, average 6/month) - Trash included. Soap/Toilet Paper/Detergent etc. | B23: =D23*6 -> 1500 | C23: =B23*12 -> 18000 | D23: 250 | H23: DSCR | I23: =B40/(B42+B41+B43) -> 1.1460313 | L23: 47362 | M23: 5 | N23: ='STR 10 Year'!F39 -> 13669.457 | O23: =N23/(1+$M$15)^M23 -> 9303.2029
A24: Handyman | B24: 250 | C24: =B24*12 -> 3000 | L24: 47727 | M24: 6 | N24: ='STR 10 Year'!G39 -> 14642.42 | O24: =N24/(1+$M$15)^M24 -> 9227.2086
A25: HOA / year | B25: 0 | C25: =B25*12 -> 0 | D25: =C25/B5 -> 0 | L25: 48092 | M25: 7 | N25: ='STR 10 Year'!H39 -> 15621.457 | O25: =N25/(1+$M$15)^M25 -> 9114.9703
A26: Electricity | B26: 250 | C26: =B26*12 -> 3000 | L26: 48458 | M26: 8 | N26: ='STR 10 Year'!I39 -> 16606.49 | O26: =N26/(1+$M$15)^M26 -> 8971.9698
A27: Nat Gas(~$2k for large tank, for ~1.5yrs) | B27: =2000/18 -> 111.11111 | C27: =B27*12 -> 1333.3333 | H27: Emergency Fund Needed (6 months) | I27: =B38*$J$27+SUM(B41:B42)*$J$27 -> 50250.147 | J27: 6 | K27: months | L27: 48823 | M27: 9 | N27: ='STR 10 Year'!J39 -> 17597.433 | O27: =N27/(1+$M$15)^M27 -> 8803.0979
A28: WIFI / Cable | B28: 150 | C28: =B28*12 -> 1800 | I28: =I27/2 -> 25125.073 | J28: =J27/2 -> 3 | K28: months | L28: 49188 | M28: 10 | N28: ='STR 10 Year'!K39+'STR 10 Year'!K44-('STR Calculator'!B8-SUM('STR 10 Year'!B46:K46)) -> 651171.76 | O28: =N28/(1+$M$15)^M28 -> 301618.52
A29: Pool Service (bi-weekly = 2xmonth) | B29: 150 | C29: =B29*12 -> 1800
A30: Water/Sewer ($0 for well/septic) | B30: 0 | C30: =B30*12 -> 0 | N30: =XIRR(N18:N28,L18:L28) -> 0.19071521 | O30: =SUM(O18:O28) -> 218128.77
A31: Building Maintenance | B31: =C31/12 -> 0 | C31: =B5*D31 -> 0 | D31: 0
A32: Capex (Future Repairs) | B32: =C32/12 -> 0 | C32: =D32*B5 -> 0 | D32: 0
A33: Grounds Cleanup/Services Maintenance/Snow Removal | B33: 0 | C33: =B33*12 -> 0
A34: City Permit Fees | B34: 25 | C34: =B34*12 -> 300
A35: Fire Marshal Permit | B35: 20 | C35: =B35*12 -> 240
A36: Incidentals (Coffee/Creamer etc) | B36: 25 | C36: =B36*12 -> 300
A37: Umbrella Insurance (Allstate Anchorage) | B37: 37 | C37: =B37*12 -> 444 | H37: Ask cleaners what is included vs not - Linens/soaps/shampoos/coffee/creamer
A38: Totals | B38: =SUM(B18:B37) -> 3068.1111 | C38: =SUM(C18:C37) -> 36817.333
A40: Net Operating Income | B40: =C15-B38 -> 6081.8889 | C40: =D15-C38 -> 72982.667 | D40: DSCR | E40: =B40/(B42+B41+B43) -> 1.1460313
A41: HELOC Payment (Interest Only) | B41: =IF(I6<0,0,I6) -> 721.875 | C41: =B41*12 -> 8662.5 | D41: =IF(B41=I6,1,0) -> 1
A42: Conventional Loan Payment | B42: =-PMT($I$8/12,$I$9*12,$B$8) -> 4585.0384 | C42: =B42*12 -> 55020.46 | D42: Cap Rate | E42: =C40/$B$5 -> 0.091228333
A43: PMI if down payment less than 20% | B43: =IF(C7<0.2,300,0) -> 0 | C43: =B43*12 -> 0 | D43: =ROUND(C43/B8,4)&"% of loan" -> 0% of loan
A44: Upgrades | B44: =C44/12 -> 470.83333 | C44: =B60 -> 5650
A45: Cash Flow | B45: =B40-B42-B41-B44-B43 -> 304.14218 | C45: =B45*12 -> 3649.7062
A48: Estimated Short Term CapEx (Upgrades) | B48: Cost Estimate
A49: Putting Greens | B49: 1000
A50: Kids Playground (mulch/play set) | B50: 1000
A51: Climbing wall materials | B51: 100
A52: Ninja Warrior Slackline kit | B52: 250
A53: Air Hockey/Fooseball etc | B53: 500
A54: Custom Bunk Beds for 1 bedroom (increase to 10 occupancy) | B54: 2000
A55: Sitting Area (Fireplace/Seats/Gravel) | B55: 400
A56: String Lights / Poles | B56: 200
A57: Pool Games (Basketball goal/Diving Toys) | B57: 200
A60: Total Estimated Upgrades | B60: =SUM(B49:B58) -> 5650
A63: Estimated Long Term CapEx | B63: Timeline of Repair (yrs) | C63: Cost per Unit | D63: Total Cost | E63: Monthly Cost
A64: Roof | B64: 5 | C64: 7000 | D64: =C64 -> 7000 | E64: =D64/B64/12 -> 116.66667
A65: Master Bath | B65: 10 | D65: =C65 -> 0 | E65: =D65/B65/12 -> 0
A66: Kitchen | B66: 10 | D66: =C66 -> 0 | E66: =D66/B66/12 -> 0
A67: Flooring | B67: 10 | C67: 8000 | D67: =C67 -> 8000 | E67: =D67/B67/12 -> 66.666667
A68: Guest baths | B68: 10 | D68: =C68 -> 0 | E68: =D68/B68/12 -> 0
A69: Exterior Paint | B69: 1 | D69: =C69 -> 0 | E69: =D69/B69/12 -> 0
A70: Interior Paint | B70: 6 | C70: 2000 | D70: =C70 -> 2000 | E70: =D70/B70/12 -> 27.777778
A71: Cabinets | B71: 10 | D71: =C71 -> 0 | E71: =D71/B71/12 -> 0
A72: Concrete walkways | B72: 4 | D72: =C72 -> 0 | E72: =D72/B72/12 -> 0
A73: Driveway Re-Pave (Asphalt) | B73: 1 | D73: =C73 -> 0 | E73: =D73/B73/12 -> 0
A74: Miscellaneous (light fixtures/door knobs etc) | B74: 10 | C74: 500 | D74: =C74 -> 500 | E74: =D74/B74/12 -> 4.1666667
A75: Total Estimated Repairs | E75: =SUM(E64:E74) -> 215.27778

Sheet Interest Rate Comparison
A1: Purchase Price | C1: 0.1 | D1: 0.15 | E1: 0.2 | F1: 0.25 | H1: 5% Increase in Down Payment | I1: Time to recoup
A2: ='STR Calculator'!B5 -> 800000 | B2: Down Payment | C2: =$A$2*C1 -> 80000 | D2: =$A$2*D1 -> 120000 | E2: =$A$2*E1 -> 160000 | F2: =$A$2*F1 -> 200000 | H2: =D2-C2 -> 40000
A3: 30 | B3: 0.0825 | C3: =PMT($B$3/12,$A$3*12,($A$2-C2)) -> -5409.1195 | D3: =PMT($B$3/12,$A$3*12,($A$2-D2)) -> -5108.6129 | E3: =PMT($B$3/12,$A$3*12,($A$2-E2)) -> -4808.1063 | F3: =PMT($B$3/12,$A$3*12,($A$2-F2)) -> -4507.5996 | G3: =B3 -> 0.0825 | H3: =D3-C3 -> 300.50664 | I3: =$H$2/H3/12 -> 11.092378
B4: 0.08 | C4: =PMT($B$4/12,$A$3*12,($A$2-C2)) -> -5283.1049 | D4: =PMT($B$4/12,$A$3*12,($A$2-D2)) -> -4989.5991 | E4: =PMT($B$4/12,$A$3*12,($A$2-E2)) -> -4696.0933 | F4: =PMT($B$4/12,$A$3*12,($A$2-F2)) -> -4402.5874 | G4: =B4 -> 0.08 | H4: =D4-C4 -> 293.50583 | I4: =$H$2/H4/12 -> 11.356958
B5: 0.0775 | C5: =PMT($B$5/12,$A$3*12,($A$2-C2)) -> -5158.1682 | D5: =PMT($B$5/12,$A$3*12,($A$2-D2)) -> -4871.6033 | E5: =PMT($B$5/12,$A$3*12,($A$2-E2)) -> -4585.0384 | F5: =PMT($B$5/12,$A$3*12,($A$2-F2)) -> -4298.4735 | G5: =B5 -> 0.0775 | H5: =D5-C5 -> 286.5649 | I5: =$H$2/H5/12 -> 11.632036
B6: 0.075 | C6: =PMT($B$6/12,$A$3*12,($A$2-C2)) -> -5034.3445 | D6: =PMT($B$6/12,$A$3*12,($A$2-D2)) -> -4754.6587 | E6: =PMT($B$6/12,$A$3*12,($A$2-E2)) -> -4474.9729 | F6: =PMT($B$6/12,$A$3*12,($A$2-F2)) -> -4195.2871 | G6: =B6 -> 0.075 | H6: =D6-C6 -> 279.6858 | I6: =$H$2/H6/12 -> 11.918136
B7: 0.0725 | C7: =PMT($B$7/12,$A$3*12,($A$2-C2)) -> -4911.6692 | D7: =PMT($B$7/12,$A$3*12,($A$2-D2)) -> -4638.7987 | E7: =PMT($B$7/12,$A$3*12,($A$2-E2)) -> -4365.9282 | F7: =PMT($B$7/12,$A$3*12,($A$2-F2)) -> -4093.0577 | G7: =B7 -> 0.0725 | H7: =D7-C7 -> 272.87051 | I7: =$H$2/H7/12 -> 12.215806
B8: 0.07 | C8: =PMT($B$8/12,$A$3*12,($A$2-C2)) -> -4790.178 | D8: =PMT($B$8/12,$A$3*12,($A$2-D2)) -> -4524.057 | E8: =PMT($B$8/12,$A$3*12,($A$2-E2)) -> -4257.936 | F8: =PMT($B$8/12,$A$3*12,($A$2-F2)) -> -3991.815 | G8: =B8 -> 0.07 | H8: =D8-C8 -> 266.121 | I8: =$H$2/H8/12 -> 12.525631
G9: Higher delta between P&I payment at higher interest rate compared to lower = shorter payout, when factoring in increased down payment for lower rate
A12: Down Payment % | B12: Down Payment | C12: Interest Rate | D12: ="Interest Paid on Down Payment by Year "&ROUND(I4,0) -> Interest Paid on Down Payment by Year 11 | E12: Down Payment Difference | F12: ="Interest Paid Difference @ year "&ROUND(I4,0) -> Interest Paid Difference @ year 11 | G12: Down Payment vs Interest Paid | H12: =ROUND(I4,0)&"yr FV of down payment saved @ 8%" -> 11yr FV of down payment saved @ 8% | I12: NPV of Interest Saved/Lost | J12: ="Cum Interest Paid Year "&ROUND(I4,0) -> Cum Interest Paid Year 11 | K12: Interest Saved Compared to 10% Loan | L12: Total Interest Paid - Life of Loan
A13: =C1 -> 0.1 | B13: =$A$2*A13 -> 80000 | C13: =B4 -> 0.08 | D13: =B13*(1+C13)^$I$4 -> 191726.51 | E13: 0 | F13: 0 | G13: =F13-E13 -> 0 | H13: 0 | I13: 0 | J13: =VLOOKUP($I$4*12,'Amoritization Scenario 10% DP'!$W$8:$AH$367,10) -> 612077.9 | K13: 0 | L13: 1270301
A14: =D1 -> 0.15 | B14: =$A$2*A14 -> 120000 | C14: =B4 -> 0.08 | D14: =B14*(1+C14)^$I$4 -> 287589.77 | E14: =B14-B13 -> 40000 | F14: =D14-D13 -> 95863.255 | G14: =F14-E14 -> 55863.255 | H14: =E14*(1+0.08)^I4 -> 95863.255 | I14: =G14/(1+C14)^I4 -> 23309.559 | J14: =VLOOKUP($I$4*12,'Amoritization Scenario 15% DP'!$W$8:$AH$367,10) -> 578073.57 | K14: =J13-J14 -> 34004.328 | L14: 1199728 | M14: =L14+H14 -> 1295591.3
A15: =E1 -> 0.2 | B15: =$A$2*A15 -> 160000 | C15: =B5 -> 0.0775 | D15: =B15*(1+C15)^$I$4 -> 373492.3 | E15: =B15-B13 -> 80000 | F15: =D15-D13 -> 181765.79 | G15: =F15-E15 -> 101765.79 | H15: =E15*(1+0.08)^I4 -> 191726.51 | I15: =G15/(1+C15)^I4 -> 43595.346 | J15: =VLOOKUP($I$4*12,'Amoritization Scenario 20% DP'!$AJ$8:$AU$367,10) -> 525640.43 | K15: =J13-J15 -> 86437.47 | L15: 1034105 | M15: =L15+H15 -> 1225831.5
K17: Present Value=Future Value /( 1+i)^n

Sheet STR 10 Year
A1: Year | B1: 1 | C1: 2 | D1: 3 | E1: 4 | F1: 5 | G1: 6 | H1: 7 | I1: 8 | J1: 9 | K1: 10
A2: Property Income | L2: Desired Return | M2: 0.08 | N2: match stock market
A3: Yearly Revenue | B3: ='STR Calculator'!D11 -> 109800 | C3: =B3*(1+C5) -> 110898 | D3: =C3*(1+D5) -> 112006.98 | E3: =D3*(1+E5) -> 113127.05 | F3: =E3*(1+F5) -> 114258.32 | G3: =F3*(1+G5) -> 115400.9 | H3: =G3*(1+H5) -> 116554.91 | I3: =H3*(1+I5) -> 117720.46 | J3: =I3*(1+J5) -> 118897.67 | K3: =J3*(1+K5) -> 120086.64
A4: Monthly Revenue | B4: =B3/12 -> 9150 | C4: =C3/12 -> 9241.5 | D4: =D3/12 -> 9333.915 | E4: =E3/12 -> 9427.2541 | F4: =F3/12 -> 9521.5267 | G4: =G3/12 -> 9616.742 | H4: =H3/12 -> 9712.9094 | I4: =I3/12 -> 9810.0385 | ... K4: =K3/12 -> 10007.22 | M4: IRR | P4: NPV
A5: Rent Appreciation | B5: 0.01 | C5: =$B$5 -> 0.01 | D5: =$B$5 -> 0.01 | E5: =$B$5 -> 0.01 | F5: =$B$5 -> 0.01 | G5: =$B$5 -> 0.01 | H5: =$B$5 -> 0.01 | I5: =$B$5 -> 0.01 | J5: =$B$5 -> 0.01 | K5: =$B$5 -> 0.01 | M5: 45536 | N5: 0 | O5: =-SUM('STR Calculator'!B6:B7,'STR Calculator'!B60) -> -165650 | P5: =O5 -> -165650
A6: ="Vacancy Loss (Occupancy rate "&'STR Calculator'!$B$12&"%)" -> Vacancy Loss (Occupancy rate 1%) | B6: =B3*(1-'STR Calculator'!$B$12) -> 0 | C6: =C3*(1-'STR Calculator'!$B$12) -> 0 | D6: =D3*(1-'STR Calculator'!$B$12) -> 0 | E6: =E3*(1-'STR Calculator'!$B$12) -> 0 | F6: =F3*(1-'STR Calculator'!$B$12) -> 0 | G6: =G3*(1-'STR Calculator'!$B$12) -> 0 | H6: =H3*(1-'STR Calculator'!$B$12) -> 0 | I6: =I3*(1-'STR Calculator'!$B$12) -> 0 | ... K6: =K3*(1-'STR Calculator'!$B$12) -> 0 | M6: 45901 | N6: 1 | O6: =B39 -> 9539.7062 | P6: =O6/(1+$M$2)^N6 -> 8833.0613
M7: 46266 | N7: 2 | O7: =C39 -> 10787.706 | P7: =O7/(1+$M$2)^N7 -> 9248.7193
A8: Operating Income | B8: =B3-B6 -> 109800 | C8: =C3-C6 -> 110898 | D8: =D3-D6 -> 112006.98 | E8: =E3-E6 -> 113127.05 | F8: =F3-F6 -> 114258.32 | G8: =G3-G6 -> 115400.9 | H8: =H3-H6 -> 116554.91 | I8: =I3-I6 -> 117720.46 | ... K8: =K3-K6 -> 120086.64 | M8: 46631 | N8: 3 | O8: =D39 -> 11742.036 | P8: =O8/(1+$M$2)^N8 -> 9321.2069
M9: 46997 | N9: 4 | O9: =E39 -> 12702.64 | P9: =O9/(1+$M$2)^N9 -> 9336.8198
A10: Property Expenses | M10: 47362 | N10: 5 | O10: =F39 -> 13669.457 | P10: =O10/(1+$M$2)^N10 -> 9303.2029
A11: Management Fee | B11: ='STR Calculator'!$C$18 -> 0 | C11: =$B$11 -> 0 | D11: =$B$11 -> 0 | E11: =$B$11 -> 0 | F11: =$B$11 -> 0 | G11: =$B$11 -> 0 | H11: =$B$11 -> 0 | I11: =$B$11 -> 0 | J11: =$B$11 -> 0 | K11: =$B$11 -> 0 | M11: 47727 | N11: 6 | O11: =G39 -> 14642.42 | P11: =O11/(1+$M$2)^N11 -> 9227.2086
A12: Subscriptions | B12: ='STR Calculator'!$C$19 -> 600 | C12: ='STR Calculator'!$C$19 -> 600 | D12: ='STR Calculator'!$C$19 -> 600 | E12: ='STR Calculator'!$C$19 -> 600 | F12: ='STR Calculator'!$C$19 -> 600 | G12: ='STR Calculator'!$C$19 -> 600 | H12: ='STR Calculator'!$C$19 -> 600 | I12: ='STR Calculator'!$C$19 -> 600 | ... K12: ='STR Calculator'!$C$19 -> 600 | M12: 48092 | N12: 7 | O12: =H39 -> 15621.457 | P12: =O12/(1+$M$2)^N12 -> 9114.9703
A13: AirBnB/VRBO Fee (3% of nightly- Passed to guest) | B13: ='STR Calculator'!$C$20 -> 0 | C13: ='STR Calculator'!$C$20 -> 0 | D13: ='STR Calculator'!$C$20 -> 0 | E13: ='STR Calculator'!$C$20 -> 0 | F13: ='STR Calculator'!$C$20 -> 0 | G13: ='STR Calculator'!$C$20 -> 0 | H13: ='STR Calculator'!$C$20 -> 0 | I13: ='STR Calculator'!$C$20 -> 0 | ... K13: ='STR Calculator'!$C$20 -> 0 | M13: 48458 | N13: 8 | O13: =I39 -> 16606.49 | P13: =O13/(1+$M$2)^N13 -> 8971.9698
A14: Property Taxes (1.5%) | B14: ='STR Calculator'!$C$21 -> 2400 | C14: =B44*($B$14/'STR Calculator'!$B$5) -> 2496 | D14: =C44*($B$14/'STR Calculator'!$B$5) -> 2595.84 | E14: =D44*($B$14/'STR Calculator'!$B$5) -> 2699.6736 | F14: =E44*($B$14/'STR Calculator'!$B$5) -> 2807.6605 | G14: =F44*($B$14/'STR Calculator'!$B$5) -> 2919.967 | H14: =G44*($B$14/'STR Calculator'!$B$5) -> 3036.7656 | I14: =H44*($B$14/'STR Calculator'!$B$5) -> 3158.2363 | J14: =I44*($B$14/'STR Calculator'!$B$5) -> 3284.5657 | K14: =J44*($B$14/'STR Calculator'!$B$5) -> 3415.9483 | M14: 48823 | N14: 9 | O14: =J39 -> 17597.433 | P14: =O14/(1+$M$2)^N14 -> 8803.0979
A15: Insurance (1.5%) | B15: ='STR Calculator'!$C$22 -> 3600 | C15: =B15+(B15*0.015) -> 3654 | D15: =C15+(C15*0.015) -> 3708.81 | E15: =D15+(D15*0.015) -> 3764.4421 | F15: =E15+(E15*0.015) -> 3820.9088 | G15: =F15+(F15*0.015) -> 3878.2224 | H15: =G15+(G15*0.015) -> 3936.3958 | I15: =H15+(H15*0.015) -> 3995.4417 | J15: =I15+(I15*0.015) -> 4055.3733 | K15: =J15+(J15*0.015) -> 4116.2039 | M15: 49188 | N15: 10 | O15: =K39+K44-('STR Calculator'!B8-SUM('STR 10 Year'!B46:K46)) -> 651171.76 | P15: =O15/(1+$M$2)^N15 -> 301618.52
A16: Cleaners/Handyman | B16: =SUM('STR Calculator'!$C$23:$C$24) -> 21000 | C16: =SUM('STR Calculator'!$C$23:$C$24) -> 21000 | D16: =SUM('STR Calculator'!$C$23:$C$24) -> 21000 | E16: =SUM('STR Calculator'!$C$23:$C$24) -> 21000 | F16: =SUM('STR Calculator'!$C$23:$C$24) -> 21000 | G16: =SUM('STR Calculator'!$C$23:$C$24) -> 21000 | H16: =SUM('STR Calculator'!$C$23:$C$24) -> 21000 | I16: =SUM('STR Calculator'!$C$23:$C$24) -> 21000 | ... K16: =SUM('STR Calculator'!$C$23:$C$24) -> 21000
A17: HOA Fees | B17: ='STR Calculator'!$C$25 -> 0 | C17: ='STR Calculator'!$C$25 -> 0 | D17: ='STR Calculator'!$C$25 -> 0 | E17: ='STR Calculator'!$C$25 -> 0 | F17: ='STR Calculator'!$C$25 -> 0 | G17: ='STR Calculator'!$C$25 -> 0 | H17: ='STR Calculator'!$C$25 -> 0 | I17: ='STR Calculator'!$C$25 -> 0 | ... K17: ='STR Calculator'!$C$25 -> 0 | O17: =XIRR(O5:O15,M5:M15) -> 0.19071521 | P17: =SUM(P5:P15) -> 218128.77
A18: Electricity | B18: ='STR Calculator'!$C$26 -> 3000 | C18: ='STR Calculator'!$C$26 -> 3000 | D18: ='STR Calculator'!$C$26 -> 3000 | E18: ='STR Calculator'!$C$26 -> 3000 | F18: ='STR Calculator'!$C$26 -> 3000 | G18: ='STR Calculator'!$C$26 -> 3000 | H18: ='STR Calculator'!$C$26 -> 3000 | I18: ='STR Calculator'!$C$26 -> 3000 | ... K18: ='STR Calculator'!$C$26 -> 3000
A19: Natural Gas | B19: ='STR Calculator'!$C$27 -> 1333.3333 | C19: ='STR Calculator'!$C$27 -> 1333.3333 | D19: ='STR Calculator'!$C$27 -> 1333.3333 | E19: ='STR Calculator'!$C$27 -> 1333.3333 | F19: ='STR Calculator'!$C$27 -> 1333.3333 | G19: ='STR Calculator'!$C$27 -> 1333.3333 | H19: ='STR Calculator'!$C$27 -> 1333.3333 | I19: ='STR Calculator'!$C$27 -> 1333.3333 | ... K19: ='STR Calculator'!$C$27 -> 1333.3333
A20: WIFI/Cable | B20: ='STR Calculator'!$C$28 -> 1800 | C20: ='STR Calculator'!$C$28 -> 1800 | D20: ='STR Calculator'!$C$28 -> 1800 | E20: ='STR Calculator'!$C$28 -> 1800 | F20: ='STR Calculator'!$C$28 -> 1800 | G20: ='STR Calculator'!$C$28 -> 1800 | H20: ='STR Calculator'!$C$28 -> 1800 | I20: ='STR Calculator'!$C$28 -> 1800 | ... K20: ='STR Calculator'!$C$28 -> 1800
A21: Water/Sewer ($0 if septic/well) | B21: ='STR Calculator'!$C$30 -> 0 | C21: ='STR Calculator'!$C$30 -> 0 | D21: ='STR Calculator'!$C$30 -> 0 | E21: ='STR Calculator'!$C$30 -> 0 | F21: ='STR Calculator'!$C$30 -> 0 | G21: ='STR Calculator'!$C$30 -> 0 | H21: ='STR Calculator'!$C$30 -> 0 | I21: ='STR Calculator'!$C$30 -> 0 | ... K21: ='STR Calculator'!$C$30 -> 0
A22: Pool Service ($75/each x biweekly) | B22: ='STR Calculator'!$C$29 -> 1800 | C22: ='STR Calculator'!$C$29 -> 1800 | D22: ='STR Calculator'!$C$29 -> 1800 | E22: ='STR Calculator'!$C$29 -> 1800 | F22: ='STR Calculator'!$C$29 -> 1800 | G22: ='STR Calculator'!$C$29 -> 1800 | H22: ='STR Calculator'!$C$29 -> 1800 | I22: ='STR Calculator'!$C$29 -> 1800 | ... K22: ='STR Calculator'!$C$29 -> 1800
A23: Building Maintenance (1%) | B23: ='STR Calculator'!$C$31 -> 0 | C23: ='STR Calculator'!$B$5*'STR Calculator'!$D$32 -> 0 | D23: ='STR Calculator'!$B$5*'STR Calculator'!$D$32 -> 0 | E23: ='STR Calculator'!$B$5*'STR Calculator'!$D$32 -> 0 | F23: ='STR Calculator'!$B$5*'STR Calculator'!$D$32 -> 0 | G23: ='STR Calculator'!$B$5*'STR Calculator'!$D$32 -> 0 | H23: ='STR Calculator'!$B$5*'STR Calculator'!$D$32 -> 0 | I23: ='STR Calculator'!$B$5*'STR Calculator'!$D$32 -> 0 | J23: ='STR Calculator'!$B$5*'STR Calculator'!$D$32 -> 0 | K23: ='STR Calculator'!$B$5*'STR Calculator'!$D$32 -> 0
A24: Capex (1%) | B24: ='STR Calculator'!$C$32 -> 0 | C24: ='STR Calculator'!$C$32 -> 0 | D24: ='STR Calculator'!$C$32 -> 0 | E24: ='STR Calculator'!$C$32 -> 0 | F24: ='STR Calculator'!$C$32 -> 0 | G24: ='STR Calculator'!$C$32 -> 0 | H24: ='STR Calculator'!$C$32 -> 0 | I24: ='STR Calculator'!$C$32 -> 0 | ... K24: ='STR Calculator'!$C$32 -> 0
A25: Grounds Cleanup/Services/Snow Removal | B25: ='STR Calculator'!$C$33 -> 0 | C25: ='STR Calculator'!$C$33 -> 0 | D25: ='STR Calculator'!$C$33 -> 0 | E25: ='STR Calculator'!$C$33 -> 0 | F25: ='STR Calculator'!$C$33 -> 0 | G25: ='STR Calculator'!$C$33 -> 0 | H25: ='STR Calculator'!$C$33 -> 0 | I25: ='STR Calculator'!$C$33 -> 0 | ... K25: ='STR Calculator'!$C$33 -> 0
A26: City Permit Fee | B26: 300 | C26: 0 | D26: 0 | E26: 0 | F26: 0 | G26: 0 | H26: 0 | I26: 0 | J26: 0 | K26: 0
A27: Incidentals (Coffee/Creamer etc) | B27: ='STR Calculator'!$C$36 -> 300 | C27: ='STR Calculator'!$C$36 -> 300 | D27: ='STR Calculator'!$C$36 -> 300 | E27: ='STR Calculator'!$C$36 -> 300 | F27: ='STR Calculator'!$C$36 -> 300 | G27: ='STR Calculator'!$C$36 -> 300 | H27: ='STR Calculator'!$C$36 -> 300 | I27: ='STR Calculator'!$C$36 -> 300 | ... K27: ='STR Calculator'!$C$36 -> 300
A28: Umbrella Insurance | B28: ='STR Calculator'!$C$37 -> 444 | C28: ='STR Calculator'!$C$37 -> 444 | D28: ='STR Calculator'!$C$37 -> 444 | E28: ='STR Calculator'!$C$37 -> 444 | F28: ='STR Calculator'!$C$37 -> 444 | G28: ='STR Calculator'!$C$37 -> 444 | H28: ='STR Calculator'!$C$37 -> 444 | I28: ='STR Calculator'!$C$37 -> 444 | ... K28: ='STR Calculator'!$C$37 -> 444
A30: Operating Expenses | B30: =SUM(B12:B28) -> 36577.333 | C30: =SUM(C12:C28) -> 36427.333 | D30: =SUM(D12:D28) -> 36581.983 | E30: =SUM(E12:E28) -> 36741.449 | F30: =SUM(F12:F28) -> 36905.903 | G30: =SUM(G12:G28) -> 37075.523 | H30: =SUM(H12:H28) -> 37250.495 | I30: =SUM(I12:I28) -> 37431.011 | ... K30: =SUM(K12:K28) -> 37809.486
A32: Net Operating Income (NOI) | B32: =B8-B30 -> 73222.667 | C32: =C8-C30 -> 74470.667 | D32: =D8-D30 -> 75424.997 | E32: =E8-E30 -> 76385.601 | F32: =F8-F30 -> 77352.418 | G32: =G8-G30 -> 78325.381 | H32: =H8-H30 -> 79304.418 | I32: =I8-I30 -> 80289.45 | ... K32: =K8-K30 -> 82277.157
A33: Capitalization Rate (CAP Rate) | B33: =B32/'STR Calculator'!$B$5 -> 0.091528333 | C33: =C32/'STR Calculator'!$B$5 -> 0.093088333 | D33: =D32/'STR Calculator'!$B$5 -> 0.094281246 | E33: =E32/'STR Calculator'!$B$5 -> 0.095482001 | F33: =F32/'STR Calculator'!$B$5 -> 0.096690522 | G33: =G32/'STR Calculator'!$B$5 -> 0.097906726 | H33: =H32/'STR Calculator'!$B$5 -> 0.099130522 | I33: =I32/'STR Calculator'!$B$5 -> 0.10036181 | ... K33: =K32/'STR Calculator'!$B$5 -> 0.10284645
A35: Key Investment Indicators
A36: Mortgage Payment | B36: =PMT('STR Calculator'!$I$8/12, 'STR Calculator'!$I$9*12,'STR Calculator'!$B$8)*12 -> -55020.46 | C36: =PMT('STR Calculator'!$I$8/12, 'STR Calculator'!$I$9*12,'STR Calculator'!$B$8)*12 -> -55020.46 | D36: =PMT('STR Calculator'!$I$8/12, 'STR Calculator'!$I$9*12,'STR Calculator'!$B$8)*12 -> -55020.46 | E36: =PMT('STR Calculator'!$I$8/12, 'STR Calculator'!$I$9*12,'STR Calculator'!$B$8)*12 -> -55020.46 | F36: =PMT('STR Calculator'!$I$8/12, 'STR Calculator'!$I$9*12,'STR Calculator'!$B$8)*12 -> -55020.46 | G36: =PMT('STR Calculator'!$I$8/12, 'STR Calculator'!$I$9*12,'STR Calculator'!$B$8)*12 -> -55020.46 | H36: =PMT('STR Calculator'!$I$8/12, 'STR Calculator'!$I$9*12,'STR Calculator'!$B$8)*12 -> -55020.46 | I36: =PMT('STR Calculator'!$I$8/12, 'STR Calculator'!$I$9*12,'STR Calculator'!$B$8)*12 -> -55020.46 | ... K36: =PMT('STR Calculator'!$I$8/12, 'STR Calculator'!$I$9*12,'STR Calculator'!$B$8)*12 -> -55020.46
A37: ="HELOC Payment ($"& 'STR Calculator'!I3&")" -> HELOC Payment ($105000) | B37: =-'STR Calculator'!$C$41 -> -8662.5 | C37: =-'STR Calculator'!$C$41 -> -8662.5 | D37: =-'STR Calculator'!$C$41 -> -8662.5 | E37: =-'STR Calculator'!$C$41 -> -8662.5 | F37: =-'STR Calculator'!$C$41 -> -8662.5 | G37: =-'STR Calculator'!$C$41 -> -8662.5 | H37: =-'STR Calculator'!$C$41 -> -8662.5 | I37: =-'STR Calculator'!$C$41 -> -8662.5 | ... K37: =-'STR Calculator'!$C$41 -> -8662.5
A38: PMI if Down Payment less than 20% | B38: =-'STR Calculator'!$C$43 -> 0 | C38: =-'STR Calculator'!$C$43 -> 0 | D38: =-'STR Calculator'!$C$43 -> 0 | E38: =-'STR Calculator'!$C$43 -> 0 | F38: =-'STR Calculator'!$C$43 -> 0 | G38: =-'STR Calculator'!$C$43 -> 0 | H38: =-'STR Calculator'!$C$43 -> 0 | I38: =-'STR Calculator'!$C$43 -> 0 | ... K38: =-'STR Calculator'!$C$43 -> 0
A39: Net Cash Flow | B39: =B32+B36+B37+B38 -> 9539.7062 | C39: =C32+C36+C37+C38 -> 10787.706 | D39: =D32+D36+D37+D38 -> 11742.036 | E39: =E32+E36+E37+E38 -> 12702.64 | F39: =F32+F36+F37+F38 -> 13669.457 | G39: =G32+G36+G37+G38 -> 14642.42 | H39: =H32+H36+H37+H38 -> 15621.457 | I39: =I32+I36+I37+I38 -> 16606.49 | ... K39: =K32+K36+K37+K38 -> 18594.197 | L39: =SUM(B39:K39) -> 141503.54 | M39: FV of all cash flows
A40: Monthly Cash Flow | B40: =B39/12 -> 794.97552 | C40: =C39/12 -> 898.97552 | D40: =D39/12 -> 978.50302 | E40: =E39/12 -> 1058.5534 | F40: =F39/12 -> 1139.1214 | G40: =G39/12 -> 1220.2017 | H40: =H39/12 -> 1301.7881 | I40: =I39/12 -> 1383.8742 | ... K40: =K39/12 -> 1549.5164
A41: ="Discounted Cash Flow (DCF) @ "&M2&"% return" -> Discounted Cash Flow (DCF) @ 0.08% return | B41: =B39/(1+$M$2)^B1 -> 8833.0613 | C41: =C39/(1+$M$2)^C1 -> 9248.7193 | D41: =D39/(1+$M$2)^D1 -> 9321.2069 | E41: =E39/(1+$M$2)^E1 -> 9336.8198 | F41: =F39/(1+$M$2)^F1 -> 9303.2029 | G41: =G39/(1+$M$2)^G1 -> 9227.2086 | H41: =H39/(1+$M$2)^H1 -> 9114.9703 | I41: =I39/(1+$M$2)^I1 -> 8971.9698 | ... K41: =K39/(1+$M$2)^K1 -> 8612.7109 | L41: =SUM(B41:K41) -> 90772.968 | M41: PV of all cash flows
A42: Cash on Cash ROI | B42: =B39/(SUM('STR Calculator'!$B$7,'STR Calculator'!$B$6)) -> 0.059623164 | C42: =C39/(SUM('STR Calculator'!$B$7,'STR Calculator'!$B$6)) -> 0.067423164 | D42: =D39/(SUM('STR Calculator'!$B$7,'STR Calculator'!$B$6)) -> 0.073387726 | E42: =E39/(SUM('STR Calculator'!$B$7,'STR Calculator'!$B$6)) -> 0.079391502 | F42: =F39/(SUM('STR Calculator'!$B$7,'STR Calculator'!$B$6)) -> 0.085434107 | G42: =G39/(SUM('STR Calculator'!$B$7,'STR Calculator'!$B$6)) -> 0.091515127 | H42: =H39/(SUM('STR Calculator'!$B$7,'STR Calculator'!$B$6)) -> 0.097634108 | I42: =I39/(SUM('STR Calculator'!$B$7,'STR Calculator'!$B$6)) -> 0.10379056 | ... K42: =K39/(SUM('STR Calculator'!$B$7,'STR Calculator'!$B$6)) -> 0.11621373
A43: Property Appreciation | B43: 0.04 | C43: =$B$43 -> 0.04 | D43: =$B$43 -> 0.04 | E43: =$B$43 -> 0.04 | F43: =$B$43 -> 0.04 | G43: =$B$43 -> 0.04 | H43: =$B$43 -> 0.04 | I43: =$B$43 -> 0.04 | J43: =$B$43 -> 0.04 | K43: =$B$43 -> 0.04
A44: Property Value | B44: ='STR Calculator'!$B$5*(1+'STR 10 Year'!B43) -> 832000 | C44: =B44*(1+'STR 10 Year'!C43) -> 865280 | D44: =C44*(1+'STR 10 Year'!D43) -> 899891.2 | E44: =D44*(1+'STR 10 Year'!E43) -> 935886.85 | F44: =E44*(1+'STR 10 Year'!F43) -> 973322.32 | G44: =F44*(1+'STR 10 Year'!G43) -> 1012255.2 | H44: =G44*(1+'STR 10 Year'!H43) -> 1052745.4 | I44: =H44*(1+'STR 10 Year'!I43) -> 1094855.2 | J44: =I44*(1+'STR 10 Year'!J43) -> 1138649.4 | K44: =J44*(1+'STR 10 Year'!K43) -> 1184195.4
A45: Property Appreciation | B45: ='STR Calculator'!$B$5*B43 -> 32000 | C45: =B44*C43 -> 33280 | D45: =C44*D43 -> 34611.2 | E45: =D44*E43 -> 35995.648 | F45: =E44*F43 -> 37435.474 | G45: =F44*G43 -> 38932.893 | H45: =G44*H43 -> 40490.209 | I45: =H44*I43 -> 42109.817 | J45: =I44*J43 -> 43794.21 | K45: =J44*K43 -> 45545.978
A46: Mortgage Principle Reduction | B46: =VLOOKUP('STR 10 Year'!B1*12,'Amoritization Scenario 10% DP'!$W$8:$AH$367,9) -> 6014.6207 | C46: =VLOOKUP('STR 10 Year'!C1*12,'Amoritization Scenario 10% DP'!$W$8:$AH$367,9)-B46 -> 6513.8312 | D46: =VLOOKUP('STR 10 Year'!D1*12,'Amoritization Scenario 10% DP'!$W$8:$AH$367,9)-SUM(B46:C46) -> 7054.476 | E46: =VLOOKUP('STR 10 Year'!E1*12,'Amoritization Scenario 10% DP'!$W$8:$AH$367,9)-SUM(B46:D46) -> 7639.994 | F46: =VLOOKUP('STR 10 Year'!F1*12,'Amoritization Scenario 10% DP'!$W$8:$AH$367,9)-SUM(B46:E46) -> 8274.1098 | G46: =VLOOKUP('STR 10 Year'!G1*12,'Amoritization Scenario 10% DP'!$W$8:$AH$367,9)-SUM(B46:F46) -> 8960.8568 | H46: =VLOOKUP('STR 10 Year'!H1*12,'Amoritization Scenario 10% DP'!$W$8:$AH$367,9)-SUM(B46:G46) -> 9704.6035 | I46: =VLOOKUP('STR 10 Year'!I1*12,'Amoritization Scenario 10% DP'!$W$8:$AH$367,9)-SUM(B46:H46) -> 10510.081 | J46: =VLOOKUP('STR 10 Year'!J1*12,'Amoritization Scenario 10% DP'!$W$8:$AH$367,9)-SUM(B46:I46) -> 11382.412 | K46: =VLOOKUP('STR 10 Year'!K1*12,'Amoritization Scenario 10% DP'!$W$8:$AH$367,9)-SUM(B46:J46) -> 12327.147 | L46: =SUM(B46:K46) -> 88382.132 | M46: loan paid down
A47: Net Tax Savings (25% Bracket) | B47: =B39*0.25 -> 2384.9266 | C47: =C39*0.25 -> 2696.9266 | D47: =D39*0.25 -> 2935.5091 | E47: =E39*0.25 -> 3175.6601 | F47: =F39*0.25 -> 3417.3643 | G47: =G39*0.25 -> 3660.6051 | H47: =H39*0.25 -> 3905.3643 | I47: =I39*0.25 -> 4151.6225 | ... K47: =K39*0.25 -> 4648.5492
A48: Tax ROI | B48: =B47/SUM('STR Calculator'!$B$6:$B$7) -> 0.014905791 | C48: =C47/SUM('STR Calculator'!$B$6:$B$7) -> 0.016855791 | D48: =D47/SUM('STR Calculator'!$B$6:$B$7) -> 0.018346932 | E48: =E47/SUM('STR Calculator'!$B$6:$B$7) -> 0.019847875 | F48: =F47/SUM('STR Calculator'!$B$6:$B$7) -> 0.021358527 | G48: =G47/SUM('STR Calculator'!$B$6:$B$7) -> 0.022878782 | H48: =H47/SUM('STR Calculator'!$B$6:$B$7) -> 0.024408527 | I48: =I47/SUM('STR Calculator'!$B$6:$B$7) -> 0.02594764 | ... K48: =K47/SUM('STR Calculator'!$B$6:$B$7) -> 0.029053433
A49: Total Return (Not counting appreciation) | B49: =SUM(B39,B46,B47) -> 17939.253 | C49: =SUM(C39,C46,C47) -> 19998.464 | D49: =SUM(D39,D46,D47) -> 21732.021 | E49: =SUM(E39,E46,E47) -> 23518.294 | F49: =SUM(F39,F46,F47) -> 25360.931 | G49: =SUM(G39,G46,G47) -> 27263.882 | H49: =SUM(H39,H46,H47) -> 29231.425 | I49: =SUM(I39,I46,I47) -> 31268.193 | ... K49: =SUM(K39,K46,K47) -> 35569.893
A50: Total ROI | B50: =B49/SUM('STR Calculator'!$B$6:$B$7) -> 0.11212033 | C50: =C49/SUM('STR Calculator'!$B$6:$B$7) -> 0.1249904 | D50: =D49/SUM('STR Calculator'!$B$6:$B$7) -> 0.13582513 | E50: =E49/SUM('STR Calculator'!$B$6:$B$7) -> 0.14698934 | F50: =F49/SUM('STR Calculator'!$B$6:$B$7) -> 0.15850582 | G50: =G49/SUM('STR Calculator'!$B$6:$B$7) -> 0.17039926 | H50: =H49/SUM('STR Calculator'!$B$6:$B$7) -> 0.18269641 | I50: =I49/SUM('STR Calculator'!$B$6:$B$7) -> 0.19542621 | ... K50: =K49/SUM('STR Calculator'!$B$6:$B$7) -> 0.22231183 | L50: =SUM(B50:K50)/K1 -> 0.16578848 | M50: AAR
L51: =('STR 10 Year'!K44/'STR Calculator'!B5)^(1/'STR 10 Year'!K1)-1 -> 0.04 | M51: CAGR
A53: Total Property Equity (not counting appreciation) | B53: =SUM('STR Calculator'!$B$7,'STR 10 Year'!B46) -> 166014.62 | C53: =B53+C46 -> 172528.45 | D53: =C53+D46 -> 179582.93 | E53: =D53+E46 -> 187222.92 | F53: =E53+F46 -> 195497.03 | G53: =F53+G46 -> 204457.89 | H53: =G53+H46 -> 214162.49 | I53: =H53+I46 -> 224672.57 | J53: =I53+J46 -> 236054.98 | K53: =J53+K46 -> 248382.13
K54: =(K53-B53)/B53 -> 0.49614613 | L54: =(K53/B53)^(1/K1)-1 -> 0.041111878 | M54: CAGR
A55: Total Property Equity (counting appreciation) | B55: =SUM('STR Calculator'!$B$7,'STR 10 Year'!B46,B45) -> 198014.62 | C55: =B55+C46+C45 -> 237808.45 | D55: =C55+D46+D45 -> 279474.13 | E55: =D55+E46+E45 -> 323109.77 | F55: =E55+F46+F45 -> 368819.35 | G55: =F55+G46+G45 -> 416713.1 | H55: =G55+H46+H45 -> 466907.92 | I55: =H55+I46+I45 -> 519527.81 | J55: =I55+J46+J45 -> 574704.43 | K55: =J55+K46+K45 -> 632577.56
K56: =(K55-B55)/B55 -> 2.1946003 | L56: =(K55/B55)^(1/K1)-1 -> 0.12316006 | M56: CAGR w/ Appreciation

Sheet STR 7yr IRR Financing
A1: ='STR Calculator'!A2 &" - FINANCING CALCULATIONS" -> 2974 Ginas Way - 3bd / 4bath - 1927 sqft - FINANCING CALCULATIONS
B4: Year 1 | C4: Year 2 | D4: Year 3 | E4: Year 4 | F4: Year 5 | G4: Year 6 | H4: Year 7
A5: Maintenance | B5: 0.01 | C5: 0.01 | D5: 0.01 | E5: 0.01 | F5: 0.01 | G5: 0.01 | H5: 0.01
A6: Property Appreciation | B6: 0.02 | C6: 0.02 | D6: 0.02 | E6: 0.02 | F6: 0.02 | G6: 0.02 | H6: 0.02
A7: Rental Appreciation | B7: 0.01 | C7: 0.01 | D7: 0.01 | E7: 0.01 | F7: 0.01 | G7: 0.01 | H7: 0.01
A8: Tax/Insurance/HOA Appreciation | B8: 0.015 | C8: 0.015 | D8: 0.015 | E8: 0.015 | F8: 0.015 | G8: 0.015 | H8: 0.015
A9: Vacancy | B9: =1-'STR Calculator'!$B$12 -> 0 | C9: =1-'STR Calculator'!$B$12 -> 0 | D9: =1-'STR Calculator'!$B$12 -> 0 | E9: =1-'STR Calculator'!$B$12 -> 0 | F9: =1-'STR Calculator'!$B$12 -> 0 | G9: =1-'STR Calculator'!$B$12 -> 0 | H9: =1-'STR Calculator'!$B$12 -> 0
B11: Year 1 | C11: Year 2 | D11: Year 3 | E11: Year 4 | F11: Year 5 | G11: Year 6 | H11: Year 7
A12: Revenues
A13: Rental Income | B13: ='STR Calculator'!D11 -> 109800 | C13: =SUM(B$13+(C$7*B$13)) -> 110898 | D13: =SUM(C$13+(D$7*C$13)) -> 112006.98 | E13: =SUM(D$13+(E$7*D$13)) -> 113127.05 | F13: =SUM(E$13+(F$7*E$13)) -> 114258.32 | G13: =SUM(F$13+(G$7*F$13)) -> 115400.9 | H13: =SUM(G$13+(H$7*G$13)) -> 116554.91
A14: Monthly Revenue | B14: =B13/12 -> 9150 | C14: =C13/12 -> 9241.5 | D14: =D13/12 -> 9333.915 | E14: =E13/12 -> 9427.2541 | F14: =F13/12 -> 9521.5267 | G14: =G13/12 -> 9616.742 | H14: =H13/12 -> 9712.9094
A15: Vacancy Rate | B15: ='STR Calculator'!D12 -> 0 | C15: =-(C13*C9) -> 0 | D15: =-(D13*D9) -> 0 | E15: =-(E13*E9) -> 0 | F15: =-(F13*F9) -> 0 | G15: =-(G13*G9) -> 0 | H15: =-(H13*H9) -> 0
A16: Net Revenue | B16: =SUM(B13,B15) -> 109800 | C16: =SUM(C13,C15) -> 110898 | D16: =SUM(D13,D15) -> 112006.98 | E16: =SUM(E13,E15) -> 113127.05 | F16: =SUM(F13,F15) -> 114258.32 | G16: =SUM(G13,G15) -> 115400.9 | H16: =SUM(H13,H15) -> 116554.91
A18: Expenses
A19: Management Fees | B19: 0 | C19: 0 | D19: 0 | E19: 0 | F19: 0 | G19: 0 | H19: 0
A20: Subscriptions | B20: ='STR Calculator'!$C$19 -> 600 | C20: ='STR Calculator'!$C$19 -> 600 | D20: ='STR Calculator'!$C$19 -> 600 | E20: ='STR Calculator'!$C$19 -> 600 | F20: ='STR Calculator'!$C$19 -> 600 | G20: ='STR Calculator'!$C$19 -> 600 | H20: ='STR Calculator'!$C$19 -> 600
A21: Property Taxes | B21: ='STR Calculator'!$C$21 -> 2400 | C21: =B$21+(B$21*C$8) -> 2436 | D21: =C$21+(C$21*D$8) -> 2472.54 | E21: =D$21+(D$21*E$8) -> 2509.6281 | F21: =E$21+(E$21*F$8) -> 2547.2725 | G21: =F$21+(F$21*G$8) -> 2585.4816 | H21: =G$21+(G$21*H$8) -> 2624.2638
A22: Insurance | B22: =('STR Calculator'!$C$22) -> 3600 | C22: =('STR Calculator'!$B$5+B48)*($B$22/'STR Calculator'!$B$5) -> 3672 | D22: =('STR Calculator'!$B$5+C48)*($B$22/'STR Calculator'!$B$5) -> 3673.44 | E22: =('STR Calculator'!$B$5+D48)*($B$22/'STR Calculator'!$B$5) -> 3673.4688 | F22: =('STR Calculator'!$B$5+E48)*($B$22/'STR Calculator'!$B$5) -> 3673.4694 | G22: =('STR Calculator'!$B$5+F48)*($B$22/'STR Calculator'!$B$5) -> 3673.4694 | H22: =('STR Calculator'!$B$5+G48)*($B$22/'STR Calculator'!$B$5) -> 3673.4694
A23: Cleaners/Handyman | B23: =SUM('STR Calculator'!$C$23:$C$24) -> 21000 | C23: =SUM('STR Calculator'!$C$23:$C$24) -> 21000 | D23: =SUM('STR Calculator'!$C$23:$C$24) -> 21000 | E23: =SUM('STR Calculator'!$C$23:$C$24) -> 21000 | F23: =SUM('STR Calculator'!$C$23:$C$24) -> 21000 | G23: =SUM('STR Calculator'!$C$23:$C$24) -> 21000 | H23: =SUM('STR Calculator'!$C$23:$C$24) -> 21000
A24: Electricity | B24: ='STR Calculator'!$C$26 -> 3000 | C24: ='STR Calculator'!$C$26 -> 3000 | D24: ='STR Calculator'!$C$26 -> 3000 | E24: ='STR Calculator'!$C$26 -> 3000 | F24: ='STR Calculator'!$C$26 -> 3000 | G24: ='STR Calculator'!$C$26 -> 3000 | H24: ='STR Calculator'!$C$26 -> 3000
A25: Natural Gas | B25: ='STR Calculator'!$C$27 -> 1333.3333 | C25: ='STR Calculator'!$C$27 -> 1333.3333 | D25: ='STR Calculator'!$C$27 -> 1333.3333 | E25: ='STR Calculator'!$C$27 -> 1333.3333 | F25: ='STR Calculator'!$C$27 -> 1333.3333 | G25: ='STR Calculator'!$C$27 -> 1333.3333 | H25: ='STR Calculator'!$C$27 -> 1333.3333
A26: WIFI/Cable | B26: ='STR Calculator'!$C$28 -> 1800 | C26: ='STR Calculator'!$C$28 -> 1800 | D26: ='STR Calculator'!$C$28 -> 1800 | E26: ='STR Calculator'!$C$28 -> 1800 | F26: ='STR Calculator'!$C$28 -> 1800 | G26: ='STR Calculator'!$C$28 -> 1800 | H26: ='STR Calculator'!$C$28 -> 1800
A27: Water/Sewer | B27: ='STR Calculator'!$C$30 -> 0 | C27: ='STR Calculator'!$C$30 -> 0 | D27: ='STR Calculator'!$C$30 -> 0 | E27: ='STR Calculator'!$C$30 -> 0 | F27: ='STR Calculator'!$C$30 -> 0 | G27: ='STR Calculator'!$C$30 -> 0 | H27: ='STR Calculator'!$C$30 -> 0
A28: Pool Service | B28: ='STR Calculator'!$C$29 -> 1800 | C28: ='STR Calculator'!$C$29 -> 1800 | D28: ='STR Calculator'!$C$29 -> 1800 | E28: ='STR Calculator'!$C$29 -> 1800 | F28: ='STR Calculator'!$C$29 -> 1800 | G28: ='STR Calculator'!$C$29 -> 1800 | H28: ='STR Calculator'!$C$29 -> 1800
A29: HOA | B29: ='STR Calculator'!$C$25 -> 0 | C29: =B29+(B29*C8) -> 0 | D29: =C29+(C29*D8) -> 0 | E29: =D29+(D29*E8) -> 0 | F29: =E29+(E29*F8) -> 0 | G29: =F29+(F29*G8) -> 0 | H29: =G29+(G29*H8) -> 0
A30: Maintenance & Repairs | B30: ='STR Calculator'!$C$31 -> 0 | C30: ='STR Calculator'!$B$5*C5 -> 8000 | D30: ='STR Calculator'!$B$5*D5 -> 8000 | E30: ='STR Calculator'!$B$5*E5 -> 8000 | F30: ='STR Calculator'!$B$5*F5 -> 8000 | G30: ='STR Calculator'!$B$5*G5 -> 8000 | H30: ='STR Calculator'!$B$5*H5 -> 8000
A31: Capex | B31: ='STR Calculator'!$C$32 -> 0 | C31: ='STR Calculator'!$C$32 -> 0 | D31: ='STR Calculator'!$C$32 -> 0 | E31: ='STR Calculator'!$C$32 -> 0 | F31: ='STR Calculator'!$C$32 -> 0 | G31: ='STR Calculator'!$C$32 -> 0 | H31: ='STR Calculator'!$C$32 -> 0
A32: City Permit | B32: ='STR Calculator'!C34 -> 300 | C32: 0 | D32: 0 | E32: 0 | F32: 0 | G32: 0 | H32: 0
A33: Incidentals (Coffee, etc) | B33: ='STR Calculator'!$C$36 -> 300 | C33: ='STR Calculator'!$C$36 -> 300 | D33: ='STR Calculator'!$C$36 -> 300 | E33: ='STR Calculator'!$C$36 -> 300 | F33: ='STR Calculator'!$C$36 -> 300 | G33: ='STR Calculator'!$C$36 -> 300 | H33: ='STR Calculator'!$C$36 -> 300
A34: Umbrella Insurance | B34: ='STR Calculator'!$C$37 -> 444 | C34: ='STR Calculator'!$C$37 -> 444 | D34: ='STR Calculator'!$C$37 -> 444 | E34: ='STR Calculator'!$C$37 -> 444 | F34: ='STR Calculator'!$C$37 -> 444 | G34: ='STR Calculator'!$C$37 -> 444 | H34: ='STR Calculator'!$C$37 -> 444
A35: Total Expenses | B35: =SUM(B20:B34) -> 36577.333 | C35: =SUM(C20:C34) -> 44385.333 | D35: =SUM(D20:D34) -> 44423.313 | E35: =SUM(E20:E34) -> 44460.43 | F35: =SUM(F20:F34) -> 44498.075 | G35: =SUM(G20:G34) -> 44536.284 | H35: =SUM(H20:H34) -> 44575.067
A37: Net Operating Income (NOI) | B37: =SUM(B16-B35) -> 73222.667 | C37: =SUM(C16-C35) -> 66512.667 | D37: =SUM(D16-D35) -> 67583.667 | E37: =SUM(E16-E35) -> 68666.62 | F37: =SUM(F16-F35) -> 69760.245 | G37: =SUM(G16-G35) -> 70864.619 | H37: =SUM(H16-H35) -> 71979.846
A39: Cash Flow
A40: NOI (Cash Available) | B40: =B37 -> 73222.667 | C40: =C37 -> 66512.667 | D40: =D37 -> 67583.667 | E40: =E37 -> 68666.62 | F40: =F37 -> 69760.245 | G40: =G37 -> 70864.619 | H40: =H37 -> 71979.846
A41: Conventional Mortgage | B41: ='STR Calculator'!$C$42 -> 55020.46 | C41: ='STR Calculator'!$C$42 -> 55020.46 | D41: ='STR Calculator'!$C$42 -> 55020.46 | E41: ='STR Calculator'!$C$42 -> 55020.46 | F41: ='STR Calculator'!$C$42 -> 55020.46 | G41: ='STR Calculator'!$C$42 -> 55020.46 | H41: ='STR Calculator'!$C$42 -> 55020.46
A42: HELOC Mortgage | B42: ='STR Calculator'!$C$41 -> 8662.5 | C42: ='STR Calculator'!$C$41 -> 8662.5 | D42: ='STR Calculator'!$C$41 -> 8662.5 | E42: ='STR Calculator'!$C$41 -> 8662.5 | F42: ='STR Calculator'!$C$41 -> 8662.5 | G42: ='STR Calculator'!$C$41 -> 8662.5 | H42: ='STR Calculator'!$C$41 -> 8662.5
A43: PMI if Down Payment less than 20% | B43: ='STR Calculator'!$C$43 -> 0 | C43: ='STR Calculator'!$C$43 -> 0 | D43: ='STR Calculator'!$C$43 -> 0 | E43: ='STR Calculator'!$C$43 -> 0 | F43: ='STR Calculator'!$C$43 -> 0 | G43: ='STR Calculator'!$C$43 -> 0 | H43: ='STR Calculator'!$C$43 -> 0
A44: Total Cash Flow | B44: =SUM(B40-B41-B42-B43) -> 9539.7062 | C44: =SUM(C40-C41-C42-C43) -> 2829.7062 | D44: =SUM(D40-D41-D42-D43) -> 3900.7062 | E44: =SUM(E40-E41-E42-E43) -> 4983.6591 | F44: =SUM(F40-F41-F42-F43) -> 6077.2846 | G44: =SUM(G40-G41-G42-G43) -> 7181.6587 | H44: =SUM(H40-H41-H42-H43) -> 8296.8855
A45: Monthly Cash Flow | B45: =B44/12 -> 794.97552 | C45: =C44/12 -> 235.80885 | D45: =D44/12 -> 325.05885 | E45: =E44/12 -> 415.30493 | F45: =F44/12 -> 506.44038 | G45: =G44/12 -> 598.47156 | H45: =H44/12 -> 691.40713
A46: DSCR | B46: =B40/SUM(B41:B43) -> 1.1498 | C46: =C40/SUM(C41:C43) -> 1.0444343 | D46: =D40/SUM(D41:D43) -> 1.061252 | E46: =E40/SUM(E41:E43) -> 1.0782573 | F46: =F40/SUM(F41:F43) -> 1.0954303 | G46: =G40/SUM(G41:G43) -> 1.1127721 | H46: =H40/SUM(H41:H43) -> 1.1302842
A47: Equity Accrued | B47: =-CUMPRINC('STR Calculator'!$I$8/12,'STR Calculator'!$I$9*12,'STR Calculator'!$B$8,1,12,0) -> 5617.2055 | C47: =-CUMPRINC('STR Calculator'!$I$8/12,'STR Calculator'!$I$9*12,'STR Calculator'!$B$8,13,24,0) -> 6068.3401 | D47: =-CUMPRINC('STR Calculator'!$I$8/12,'STR Calculator'!$I$9*12,'STR Calculator'!$B$8,25,36,0) -> 6555.7067 | E47: =-CUMPRINC('STR Calculator'!$I$8/12,'STR Calculator'!$I$9*12,'STR Calculator'!$B$8,37,48,0) -> 7082.2152 | F47: =-CUMPRINC('STR Calculator'!$I$8/12,'STR Calculator'!$I$9*12,'STR Calculator'!$B$8,49,60,0) -> 7651.0091 | G47: =-CUMPRINC('STR Calculator'!$I$8/12,'STR Calculator'!$I$9*12,'STR Calculator'!$B$8,61,72,0) -> 8265.4846 | H47: =-CUMPRINC('STR Calculator'!$I$8/12,'STR Calculator'!$I$9*12,'STR Calculator'!$B$8,73,84,0) -> 8929.3105
A48: Appreciation | B48: =SUM(B6*'STR Calculator'!$B$5) -> 16000 | C48: =(SUM(B48)+'STR Calculator'!$B$5)*C$6 -> 16320 | D48: =(SUM(C48)+'STR Calculator'!$B$5)*D$6 -> 16326.4 | E48: =(SUM(D48)+'STR Calculator'!$B$5)*E$6 -> 16326.528 | F48: =(SUM(E48)+'STR Calculator'!$B$5)*F$6 -> 16326.531 | G48: =(SUM(F48)+'STR Calculator'!$B$5)*G$6 -> 16326.531 | H48: =(SUM(G48)+'STR Calculator'!$B$5)*H$6 -> 16326.531
A49: Total Return w/o Appreciation | B49: =SUM(B47+B44) -> 15156.912 | C49: =SUM(C47+C44) -> 8898.0464 | D49: =SUM(D47+D44) -> 10456.413 | E49: =SUM(E47+E44) -> 12065.874 | F49: =SUM(F47+F44) -> 13728.294 | G49: =SUM(G47+G44) -> 15447.143 | H49: =SUM(H47+H44) -> 17226.196
A50: ROI w/o appreciation | B50: =B49/SUM('STR Calculator'!$B$6:$B$7) -> 0.094730698 | C50: =C49/SUM('STR Calculator'!$B$6:$B$7) -> 0.05561279 | D50: =D49/SUM('STR Calculator'!$B$6:$B$7) -> 0.065352581 | E50: =E49/SUM('STR Calculator'!$B$6:$B$7) -> 0.075411714 | F50: =F49/SUM('STR Calculator'!$B$6:$B$7) -> 0.085801836 | G50: =G49/SUM('STR Calculator'!$B$6:$B$7) -> 0.096544646 | H50: =H49/SUM('STR Calculator'!$B$6:$B$7) -> 0.10766372
A51: Total Return w/ Appreciation | B51: =SUM(B44+B47+B48) -> 31156.912 | C51: =SUM(C44+C47+C48) -> 25218.046 | D51: =SUM(D44+D47+D48) -> 26782.813 | E51: =SUM(E44+E47+E48) -> 28392.402 | F51: =SUM(F44+F47+F48) -> 30054.824 | G51: =SUM(G44+G47+G48) -> 31773.674 | H51: =SUM(H44+H47+H48) -> 33552.727
A52: Total ROI | B52: =B51/SUM('STR Calculator'!$B$6:$B$7) -> 0.1947307 | C52: =C51/SUM('STR Calculator'!$B$6:$B$7) -> 0.15761279 | D52: =D51/SUM('STR Calculator'!$B$6:$B$7) -> 0.16739258 | E52: =E51/SUM('STR Calculator'!$B$6:$B$7) -> 0.17745251 | F52: =F51/SUM('STR Calculator'!$B$6:$B$7) -> 0.18784265 | G52: =G51/SUM('STR Calculator'!$B$6:$B$7) -> 0.19858546 | H52: =H51/SUM('STR Calculator'!$B$6:$B$7) -> 0.20970454
A53: Average ROI | G53: =AVERAGE(B50:H50) -> 0.083016856
A54: Estimated Value at Year 7 | G54: ='STR Calculator'!B5+(SUM('STR 7yr IRR Financing'!B48:H48)) -> 913952.52
A55: Loan Paid Down over 7 Years | G55: =SUM(B47:H47) -> 50169.272
A56: Total returns are based on calculations of external data and is subject to change. Estimated returns are estimated, and may not factor in all scenarios or costs. REI Nation, LLC and Premier Property Management Group, LLC have offered this estimator of returns in good faith. We realize that there are alternate methods to calculate return, and that some assumptions may not be applicable for your calculations. Data provided for the calculation is the user’s responsibility. We do not make any representations or warranties of any kind on the information provided. We also disclaim any liability or responsibility for the accuracy, correctness, or completeness of any information provided. *All calculations include estimated maintenance, estimated vacancy, estimated property management fees, estimated equity accrual, estimated property taxes, estimated insurance and estimated appreciation.

Sheet Amoritization Scenario 10% DP
A1: If deciding between different Down Payment % and Interest Rates, compare Cumulative Interest Payment over duration to recoup additional Down Payment Lump Sum, to see which is better. NPV / PV/FV money calculation
C3: sqft | J3: Interest | K3: ='Interest Rate Comparison'!B3 -> 0.0825 | N3: =K3/12 -> 0.006875 | O3: r | W3: Interest | X3: ='Interest Rate Comparison'!B4 -> 0.08 | AA3: =X3/12 -> 0.0066666667 | AB3: r | AJ3: Interest | AK3: ='Interest Rate Comparison'!B5 -> 0.0775 | AN3: =AK3/12 -> 0.0064583333 | AO3: r | AW3: Interest | AX3: ='Interest Rate Comparison'!B6 -> 0.075 | BA3: =AX3/12 -> 0.00625 | BB3: r | BJ3: Interest | BK3: ='Interest Rate Comparison'!B7 -> 0.0725 | BN3: =BK3/12 -> 0.0060416667 | BO3: r | BW3: Interest | BX3: ='Interest Rate Comparison'!B8 -> 0.07 | CA3: =BX3/12 -> 0.0058333333 | CB3: r
C4: $/sqft Market Estimate | J4: Term | K4: =$L$4*12 -> 360 | L4: ='STR Calculator'!I9 -> 30 | M4: years | N4: =(1+N3)^K4 -> 11.781506 | O4: (1+r)^n | W4: Term | X4: =$L$4*12 -> 360 | Y4: 30 | Z4: years | AA4: =(1+AA3)^X4 -> 10.93573 | AB4: (1+r)^n | AJ4: Term | AK4: =$L$4*12 -> 360 | AL4: 30 | AM4: years | AN4: =(1+AN3)^AK4 -> 10.150514 | AO4: (1+r)^n | AW4: Term | AX4: =$L$4*12 -> 360 | AY4: 30 | AZ4: years | BA4: =(1+BA3)^AX4 -> 9.4215339 | BB4: (1+r)^n | BJ4: Term | BK4: =$L$4*12 -> 360 | BL4: 30 | BM4: years | BN4: =(1+BN3)^BK4 -> 8.744772 | BO4: (1+r)^n | BW4: Term | BX4: =$L$4*12 -> 360 | BY4: 30 | BZ4: years | CA4: =(1+CA3)^BX4 -> 8.1164975 | CB4: (1+r)^n
A5: Original Purchase Price | B5: ='STR Calculator'!B5 -> 800000 | C5: =B5/B3 -> #DIV/0! | D5: sqft | J5: Monthly Payment | W5: Monthly Payment | AJ5: Monthly Payment | AW5: Monthly Payment | BJ5: Monthly Payment | BW5: Monthly Payment
A6: Down Payment | B6: 0.1
A7: Current Loan Balance | B7: =B5-(B5*B6) -> 720000 | C7: as of 11/13/22 | J7: paymentNumber | K7: paymentDate | L7: startingBalance | M7: Monthly Payment | N7: principalPayment | O7: Principle Pay Down | P7: interestPayment | Q7: Interest Percent | R7: cumulativePrincipal | S7: cumulativeInterest | T7: endingBalance | U7: Total Paid End of Loan | W7: paymentNumber | X7: paymentDate | Y7: startingBalance | Z7: Monthly Payment | AA7: principalPayment | AB7: Principle Pay Down | AC7: interestPayment | AD7: Interest Percent | AE7: cumulativePrincipal | AF7: cumulativeInterest | AG7: endingBalance | AH7: Total Paid End of Loan | AJ7: paymentNumber | AK7: paymentDate | AL7: startingBalance | AM7: Monthly Payment | AN7: principalPayment | AO7: Principle Pay Down | AP7: interestPayment | AQ7: Interest Percent | AR7: cumulativePrincipal | AS7: cumulativeInterest | AT7: endingBalance | AU7: Total Paid End of Loan | AW7: paymentNumber | AX7: paymentDate | AY7: startingBalance | AZ7: Monthly Payment | BA7: principalPayment | BB7: Principle Pay Down | BC7: interestPayment | BD7: Interest Percent | BE7: cumulativePrincipal | BF7: cumulativeInterest | BG7: endingBalance | BH7: Total Paid End of Loan | BJ7: paymentNumber | BK7: paymentDate | BL7: startingBalance | BM7: Monthly Payment | BN7: principalPayment | BO7: Principle Pay Down | BP7: interestPayment | BQ7: Interest Percent | BR7: cumulativePrincipal | BS7: cumulativeInterest | BT7: endingBalance | BU7: Total Paid End of Loan | BW7: paymentNumber | BX7: paymentDate | BY7: startingBalance | BZ7: Monthly Payment | CA7: principalPayment | CB7: Principle Pay Down | CC7: interestPayment | CD7: Interest Percent | CE7: cumulativePrincipal | CF7: cumulativeInterest | CG7: endingBalance | CH7: Total Paid End of Loan
A8: Current Equity | B8: =B5-B7 -> 80000 | J8: 1 | K8: 44866 | L8: ='Amoritization Scenario 10% DP'!$B$7 -> 720000 | M8: =$L$8/((($N$4)-1)/($N$3*$N$4)) -> 5409.1195 | N8: =M8-P8 -> 459.11955 | O8: =(N8/L8)*12 -> 0.0076519925 | P8: =L8*($K$3/12) -> 4950 | Q8: =(P8/L8)*12 -> 0.0825 | R8: =N8 -> 459.11955 | S8: =P8 -> 4950 | T8: =L8-N8 -> 719540.88 | U8: =R8+S8 -> 5409.1195 | W8: 1 | X8: 44866 | Y8: ='Amoritization Scenario 10% DP'!$B$7 -> 720000 | Z8: =$Y$8/((($AA$4)-1)/($AA$3*$AA$4)) -> 5283.1049 | AA8: =Z8-AC8 -> 483.10493 | AB8: =(AA8/Y8)*12 -> 0.0080517489 | AC8: =Y8*($X$3/12) -> 4800 | AD8: =(AC8/Y8)*12 -> 0.08 | AE8: =AA8 -> 483.10493 | AF8: =AC8 -> 4800 | AG8: =Y8-AA8 -> 719516.9 | AH8: =AE8+AF8 -> 5283.1049 | AJ8: 1 | AK8: 44866 | AL8: ='Amoritization Scenario 10% DP'!$B$7 -> 720000 | AM8: =$AL$8/((($AN$4)-1)/($AN$3*$AN$4)) -> 5158.1682 | AN8: =AM8-AP8 -> 508.16817 | AO8: =(AN8/AL8)*12 -> 0.0084694695 | AP8: =AL8*($AK$3/12) -> 4650 | AQ8: =(AP8/AL8)*12 -> 0.0775 | AR8: =AN8 -> 508.16817 | AS8: =AP8 -> 4650 | AT8: =AL8-AN8 -> 719491.83 | AU8: =AR8+AS8 -> 5158.1682 | AW8: 1 | AX8: 44866 | AY8: ='Amoritization Scenario 10% DP'!$B$7 -> 720000 | AZ8: =$AY$8/((($BA$4)-1)/($BA$3*$BA$4)) -> 5034.3445 | BA8: =AZ8-BC8 -> 534.34446 | BB8: =(BA8/AY8)*12 -> 0.008905741 | BC8: =AY8*($AX$3/12) -> 4500 | BD8: =(BC8/AY8)*12 -> 0.075 | BE8: =BA8 -> 534.34446 | BF8: =BC8 -> 4500 | BG8: =AY8-BA8 -> 719465.66 | BH8: =BE8+BF8 -> 5034.3445 | BJ8: 1 | BK8: 44866 | BL8: ='Amoritization Scenario 10% DP'!$B$7 -> 720000 | BM8: =$BL$8/((($BN$4)-1)/($BN$3*$BN$4)) -> 4911.6692 | BN8: =BM8-BP8 -> 561.66922 | BO8: =(BN8/BL8)*12 -> 0.0093611536 | BP8: =BL8*($BK$3/12) -> 4350 | BQ8: =(BP8/BL8)*12 -> 0.0725 | BR8: =BN8 -> 561.66922 | BS8: =BP8 -> 4350 | BT8: =BL8-BN8 -> 719438.33 | BU8: =BR8+BS8 -> 4911.6692 | BW8: 1 | BX8: 44866 | BY8: ='Amoritization Scenario 10% DP'!$B$7 -> 720000 | BZ8: =$BY$8/((($CA$4)-1)/($CA$3*$CA$4)) -> 4790.178 | CA8: =BZ8-CC8 -> 590.17797 | CB8: =(CA8/BY8)*12 -> 0.0098362994 | CC8: =BY8*($BX$3/12) -> 4200 | CD8: =(CC8/BY8)*12 -> 0.07 | CE8: =CA8 -> 590.17797 | CF8: =CC8 -> 4200 | CG8: =BY8-CA8 -> 719409.82 | CH8: =CE8+CF8 -> 4790.178
J9: 2 | K9: 44896 | L9: =T8 -> 719540.88 | M9: =$L$8/((($N$4)-1)/($N$3*$N$4)) -> 5409.1195 | N9: =M9-P9 -> 462.276 | O9: =(N9/L9)*12 -> 0.007709516 | P9: =L9*($K$3/12) -> 4946.8436 | Q9: =(P9/L9)*12 -> 0.0825 | R9: =R8+N9 -> 921.39555 | S9: =S8+P9 -> 9896.8436 | T9: =L9-N9 -> 719078.6 | U9: =R9+S9 -> 10818.239 | W9: 2 | X9: 44896 | Y9: =AG8 -> 719516.9 | Z9: =Z8 -> 5283.1049 | AA9: =Z9-AC9 -> 486.32563 | AB9: =(AA9/Y9)*12 -> 0.0081108694 | AC9: =Y9*($X$3/12) -> 4796.7793 | AD9: =(AC9/Y9)*12 -> 0.08 | AE9: =AE8+AA9 -> 969.43056 | AF9: =AF8+AC9 -> 9596.7793 | AG9: =Y9-AA9 -> 719030.57 | AH9: =AE9+AF9 -> 10566.21 | AJ9: 2 | AK9: 44896 | AL9: =AT8 -> 719491.83 | AM9: =AM8 -> 5158.1682 | AN9: =AM9-AP9 -> 511.45009 | AO9: =(AN9/AL9)*12 -> 0.0085301886 | AP9: =AL9*($AK$3/12) -> 4646.7181 | AQ9: =(AP9/AL9)*12 -> 0.0775 | AR9: =AR8+AN9 -> 1019.6183 | AS9: =AS8+AP9 -> 9296.7181 | AT9: =AL9-AN9 -> 718980.38 | AU9: =AR9+AS9 -> 10316.336 | AW9: 2 | AX9: 44896 | AY9: =BG8 -> 719465.66 | AZ9: =AZ8 -> 5034.3445 | BA9: =AZ9-BC9 -> 537.68411 | BB9: =(BA9/AY9)*12 -> 0.0089680575 | BC9: =AY9*($AX$3/12) -> 4496.6603 | BD9: =(BC9/AY9)*12 -> 0.075 | BE9: =BE8+BA9 -> 1072.0286 | BF9: =BF8+BC9 -> 8996.6603 | BG9: =AY9-BA9 -> 718927.97 | BH9: =BE9+BF9 -> 10068.689 | BJ9: 2 | BK9: 44896 | BL9: =BT8 -> 719438.33 | BM9: =BM8 -> 4911.6692 | BN9: =BM9-BP9 -> 565.06263 | BO9: =(BN9/BL9)*12 -> 0.009425063 | BP9: =BL9*($BK$3/12) -> 4346.6066 | BQ9: =(BP9/BL9)*12 -> 0.0725 | BR9: =BR8+BN9 -> 1126.7319 | BS9: =BS8+BP9 -> 8696.6066 | BT9: =BL9-BN9 -> 718873.27 | BU9: =BR9+BS9 -> 9823.3384 | BW9: 2 | BX9: 44896 | BY9: =CG8 -> 719409.82 | BZ9: =BZ8 -> 4790.178 | CA9: =BZ9-CC9 -> 593.62067 | CB9: =(CA9/BY9)*12 -> 0.0099017943 | CC9: =BY9*($BX$3/12) -> 4196.5573 | CD9: =(CC9/BY9)*12 -> 0.07 | CE9: =CE8+CA9 -> 1183.7986 | CF9: =CF8+CC9 -> 8396.5573 | CG9: =BY9-CA9 -> 718816.2 | CH9: =CE9+CF9 -> 9580.3559
A10: Year | B10: ="Cum Interest @ "&K3&"%" -> Cum Interest @ 0.0825% | C10: ="Cum Interest @ "&X3&"%" -> Cum Interest @ 0.08% | D10: ="Cum Interest @ "&AK3&"%" -> Cum Interest @ 0.0775% | E10: ="Cum Interest @ "&AX3&"%" -> Cum Interest @ 0.075% | F10: ="Cum Interest @ "&BK3&"%" -> Cum Interest @ 0.0725% | G10: ="Cum Interest @ "&BX3&"%" -> Cum Interest @ 0.07% | J10: 3 | K10: 44927 | L10: =T9 -> 719078.6 | M10: =$L$8/((($N$4)-1)/($N$3*$N$4)) -> 5409.1195 | N10: =M10-P10 -> 465.45414 | O10: =(N10/L10)*12 -> 0.0077675093 | P10: =L10*($K$3/12) -> 4943.6654 | Q10: =(P10/L10)*12 -> 0.0825 | R10: =R9+N10 -> 1386.8497 | S10: =S9+P10 -> 14840.509 | T10: =L10-N10 -> 718613.15 | U10: =R10+S10 -> 16227.359 | W10: 3 | X10: 44927 | Y10: =AG9 -> 719030.57 | Z10: =Z9 -> 5283.1049 | AA10: =Z10-AC10 -> 489.5678 | AB10: =(AA10/Y10)*12 -> 0.0081704643 | AC10: =Y10*($X$3/12) -> 4793.5371 | AD10: =(AC10/Y10)*12 -> 0.08 | AE10: =AE9+AA10 -> 1458.9984 | AF10: =AF9+AC10 -> 14390.316 | AG10: =Y10-AA10 -> 718541 | AH10: =AE10+AF10 -> 15849.315 | AJ10: 3 | AK10: 44927 | AL10: =AT9 -> 718980.38 | AM10: =AM9 -> 5158.1682 | AN10: =AM10-AP10 -> 514.7532 | AO10: =(AN10/AL10)*12 -> 0.0085913866 | AP10: =AL10*($AK$3/12) -> 4643.415 | AQ10: =(AP10/AL10)*12 -> 0.0775 | AR10: =AR9+AN10 -> 1534.3715 | AS10: =AS9+AP10 -> 13940.133 | AT10: =AL10-AN10 -> 718465.63 | AU10: =AR10+AS10 -> 15474.505 | AW10: 3 | AX10: 44927 | AY10: =BG9 -> 718927.97 | AZ10: =AZ9 -> 5034.3445 | BA10: =AZ10-BC10 -> 541.04464 | BB10: =(BA10/AY10)*12 -> 0.009030857 | BC10: =AY10*($AX$3/12) -> 4493.2998 | BD10: =(BC10/AY10)*12 -> 0.075 | BE10: =BE9+BA10 -> 1613.0732 | BF10: =BF9+BC10 -> 13489.96 | BG10: =AY10-BA10 -> 718386.93 | BH10: =BE10+BF10 -> 15103.033 | BJ10: 3 | BK10: 44927 | BL10: =BT9 -> 718873.27 | BM10: =BM9 -> 4911.6692 | BN10: =BM10-BP10 -> 568.47655 | BO10: =(BN10/BL10)*12 -> 0.0094894594 | BP10: =BL10*($BK$3/12) -> 4343.1927 | BQ10: =(BP10/BL10)*12 -> 0.0725 | BR10: =BR9+BN10 -> 1695.2084 | BS10: =BS9+BP10 -> 13039.799 | BT10: =BL10-BN10 -> 718304.79 | BU10: =BR10+BS10 -> 14735.008 | BW10: 3 | BX10: 44927 | BY10: =CG9 -> 718816.2 | BZ10: =BZ9 -> 4790.178 | CA10: =BZ10-CC10 -> 597.08346 | CB10: =(CA10/BY10)*12 -> 0.0099677796 | CC10: =BY10*($BX$3/12) -> 4193.0945 | CD10: =(CC10/BY10)*12 -> 0.07 | CE10: =CE9+CA10 -> 1780.8821 | CF10: =CF9+CC10 -> 12589.652 | CG10: =BY10-CA10 -> 718219.12 | CH10: =CE10+CF10 -> 14370.534
A11: 1 | B11: =VLOOKUP($A$11*12,$J$7:$U$367,10) -> 59186.826 | C11: =VLOOKUP(A11*12,$W$7:$AH$367,10) -> 57382.639 | D11: =VLOOKUP(A11*12,$AJ$7:$AU$367,10) -> 55578.662 | E11: =VLOOKUP(A11*12,$AW$7:$BH$367,10) -> 53774.926 | F11: =VLOOKUP(A11*12,$BJ$7:$BU$367,10) -> 51971.462 | G11: =VLOOKUP(A11*12,$BW$7:$CH$367,10) -> 50168.305 | J11: 4 | K11: 44958 | L11: =T10 -> 718613.15 | M11: =$L$8/((($N$4)-1)/($N$3*$N$4)) -> 5409.1195 | N11: =M11-P11 -> 468.65414 | O11: =(N11/L11)*12 -> 0.0078259766 | P11: =L11*($K$3/12) -> 4940.4654 | Q11: =(P11/L11)*12 -> 0.0825 | R11: =R10+N11 -> 1855.5038 | S11: =S10+P11 -> 19780.974 | T11: =L11-N11 -> 718144.5 | U11: =R11+S11 -> 21636.478 | W11: 4 | X11: 44958 | Y11: =AG10 -> 718541 | Z11: =Z10 -> 5283.1049 | AA11: =Z11-AC11 -> 492.83159 | AB11: =(AA11/Y11)*12 -> 0.008230538 | AC11: =Y11*($X$3/12) -> 4790.2733 | AD11: =(AC11/Y11)*12 -> 0.08 | AE11: =AE10+AA11 -> 1951.83 | AF11: =AF10+AC11 -> 19180.59 | AG11: =Y11-AA11 -> 718048.17 | AH11: =AE11+AF11 -> 21132.42 | AJ11: 4 | AK11: 44958 | AL11: =AT10 -> 718465.63 | AM11: =AM10 -> 5158.1682 | AN11: =AM11-AP11 -> 518.07765 | AO11: =(AN11/AL11)*12 -> 0.0086530678 | AP11: =AL11*($AK$3/12) -> 4640.0905 | AQ11: =(AP11/AL11)*12 -> 0.0775 | AR11: =AR10+AN11 -> 2052.4491 | AS11: =AS10+AP11 -> 18580.224 | AT11: =AL11-AN11 -> 717947.55 | AU11: =AR11+AS11 -> 20632.673 | AW11: 4 | AX11: 44958 | AY11: =BG10 -> 718386.93 | AZ11: =AZ10 -> 5034.3445 | BA11: =AZ11-BC11 -> 544.42617 | BB11: =(BA11/AY11)*12 -> 0.0090941438 | BC11: =AY11*($AX$3/12) -> 4489.9183 | BD11: =(BC11/AY11)*12 -> 0.075 | BE11: =BE10+BA11 -> 2157.4994 | BF11: =BF10+BC11 -> 17979.878 | BG11: =AY11-BA11 -> 717842.5 | BH11: =BE11+BF11 -> 20137.378 | BJ11: 4 | BK11: 44958 | BL11: =BT10 -> 718304.79 | BM11: =BM10 -> 4911.6692 | BN11: =BM11-BP11 -> 571.9111 | BO11: =(BN11/BL11)*12 -> 0.009554347 | BP11: =BL11*($BK$3/12) -> 4339.7581 | BQ11: =(BP11/BL11)*12 -> 0.0725 | BR11: =BR10+BN11 -> 2267.1195 | BS11: =BS10+BP11 -> 17379.557 | BT11: =BL11-BN11 -> 717732.88 | BU11: =BR11+BS11 -> 19646.677 | BW11: 4 | BX11: 44958 | BY11: =CG10 -> 718219.12 | BZ11: =BZ10 -> 4790.178 | CA11: =BZ11-CC11 -> 600.56644 | CB11: =(CA11/BY11)*12 -> 0.01003426 | CC11: =BY11*($BX$3/12) -> 4189.6115 | CD11: =(CC11/BY11)*12 -> 0.07 | CE11: =CE10+CA11 -> 2381.4485 | CF11: =CF10+CC11 -> 16779.263 | CG11: =BY11-CA11 -> 717618.55 | CH11: =CE11+CF11 -> 19160.712
A12: =A11+1 -> 2 | B12: =VLOOKUP(A12*12,$J$7:$U$367,10) -> 117883.27 | C12: =VLOOKUP(A12*12,$W$7:$AH$367,10) -> 114266.07 | D12: =VLOOKUP(A12*12,$AJ$7:$AU$367,10) -> 110649.8 | E12: =VLOOKUP(A12*12,$AW$7:$BH$367,10) -> 107034.59 | F12: =VLOOKUP(A12*12,$BJ$7:$BU$367,10) -> 103420.57 | G12: =VLOOKUP(A12*12,$BW$7:$CH$367,10) -> 99807.892 | J12: 5 | K12: 44986 | L12: =T11 -> 718144.5 | M12: =$L$8/((($N$4)-1)/($N$3*$N$4)) -> 5409.1195 | N12: =M12-P12 -> 471.87614 | O12: =(N12/L12)*12 -> 0.0078849224 | P12: =L12*($K$3/12) -> 4937.2434 | Q12: =(P12/L12)*12 -> 0.0825 | R12: =R11+N12 -> 2327.38 | S12: =S11+P12 -> 24718.218 | T12: =L12-N12 -> 717672.62 | U12: =R12+S12 -> 27045.598 | W12: 5 | X12: 44986 | Y12: =AG11 -> 718048.17 | Z12: =Z11 -> 5283.1049 | AA12: =Z12-AC12 -> 496.11713 | AB12: =(AA12/Y12)*12 -> 0.008291095 | AC12: =Y12*($X$3/12) -> 4786.9878 | AD12: =(AC12/Y12)*12 -> 0.08 | AE12: =AE11+AA12 -> 2447.9471 | AF12: =AF11+AC12 -> 23967.578 | AG12: =Y12-AA12 -> 717552.05 | AH12: =AE12+AF12 -> 26415.525 | AJ12: 5 | AK12: 44986 | AL12: =AT11 -> 717947.55 | AM12: =AM11 -> 5158.1682 | AN12: =AM12-AP12 -> 521.42357 | AO12: =(AN12/AL12)*12 -> 0.0087152367 | AP12: =AL12*($AK$3/12) -> 4636.7446 | AQ12: =(AP12/AL12)*12 -> 0.0775 | AR12: =AR11+AN12 -> 2573.8727 | AS12: =AS11+AP12 -> 23216.968 | AT12: =AL12-AN12 -> 717426.13 | AU12: =AR12+AS12 -> 25790.841 | AW12: 5 | AX12: 44986 | AY12: =BG11 -> 717842.5 | AZ12: =AZ11 -> 5034.3445 | BA12: =AZ12-BC12 -> 547.82883 | BB12: =(BA12/AY12)*12 -> 0.0091579225 | BC12: =AY12*($AX$3/12) -> 4486.5156 | BD12: =(BC12/AY12)*12 -> 0.075 | BE12: =BE11+BA12 -> 2705.3282 | BF12: =BF11+BC12 -> 22466.394 | BG12: =AY12-BA12 -> 717294.67 | BH12: =BE12+BF12 -> 25171.722 | BJ12: 5 | BK12: 44986 | BL12: =BT11 -> 717732.88 | BM12: =BM11 -> 4911.6692 | BN12: =BM12-BP12 -> 575.3664 | BO12: =(BN12/BL12)*12 -> 0.0096197303 | BP12: =BL12*($BK$3/12) -> 4336.3028 | BQ12: =(BP12/BL12)*12 -> 0.0725 | BR12: =BR11+BN12 -> 2842.4859 | BS12: =BS11+BP12 -> 21715.86 | BT12: =BL12-BN12 -> 717157.51 | BU12: =BR12+BS12 -> 24558.346 | BW12: 5 | BX12: 44986 | BY12: =CG11 -> 717618.55 | BZ12: =BZ11 -> 4790.178 | CA12: =BZ12-CC12 -> 604.06975 | CB12: =(CA12/BY12)*12 -> 0.01010124 | CC12: =BY12*($BX$3/12) -> 4186.1082 | CD12: =(CC12/BY12)*12 -> 0.07 | CE12: =CE11+CA12 -> 2985.5183 | CF12: =CF11+CC12 -> 20965.372 | CG12: =BY12-CA12 -> 717014.48 | CH12: =CE12+CF12 -> 23950.89
A13: =A12+1 -> 3 | B13: =VLOOKUP(A13*12,$J$7:$U$367,10) -> 176047.31 | C13: =VLOOKUP(A13*12,$W$7:$AH$367,10) -> 170608.85 | D13: =VLOOKUP(A13*12,$AJ$7:$AU$367,10) -> 165172.65 | E13: =VLOOKUP(A13*12,$AW$7:$BH$367,10) -> 159738.98 | F13: =VLOOKUP(A13*12,$BJ$7:$BU$367,10) -> 154308.18 | G13: =VLOOKUP(A13*12,$BW$7:$CH$367,10) -> 148880.54 | J13: 6 | K13: 45017 | L13: =T12 -> 717672.62 | M13: =$L$8/((($N$4)-1)/($N$3*$N$4)) -> 5409.1195 | N13: =M13-P13 -> 475.12029 | O13: =(N13/L13)*12 -> 0.0079443513 | P13: =L13*($K$3/12) -> 4933.9993 | Q13: =(P13/L13)*12 -> 0.0825 | R13: =R12+N13 -> 2802.5003 | S13: =S12+P13 -> 29652.217 | T13: =L13-N13 -> 717197.5 | U13: =R13+S13 -> 32454.717 | W13: 6 | X13: 45017 | Y13: =AG12 -> 717552.05 | Z13: =Z12 -> 5283.1049 | AA13: =Z13-AC13 -> 499.42458 | AB13: =(AA13/Y13)*12 -> 0.0083521396 | AC13: =Y13*($X$3/12) -> 4783.6804 | AD13: =(AC13/Y13)*12 -> 0.08 | AE13: =AE12+AA13 -> 2947.3717 | AF13: =AF12+AC13 -> 28751.258 | AG13: =Y13-AA13 -> 717052.63 | AH13: =AE13+AF13 -> 31698.63 | AJ13: 6 | AK13: 45017 | AL13: =AT12 -> 717426.13 | AM13: =AM12 -> 5158.1682 | AN13: =AM13-AP13 -> 524.7911 | AO13: =(AN13/AL13)*12 -> 0.0087778977 | AP13: =AL13*($AK$3/12) -> 4633.3771 | AQ13: =(AP13/AL13)*12 -> 0.0775 | AR13: =AR12+AN13 -> 3098.6638 | AS13: =AS12+AP13 -> 27850.345 | AT13: =AL13-AN13 -> 716901.34 | AU13: =AR13+AS13 -> 30949.009 | AW13: 6 | AX13: 45017 | AY13: =BG12 -> 717294.67 | AZ13: =AZ12 -> 5034.3445 | BA13: =AZ13-BC13 -> 551.25276 | BB13: =(BA13/AY13)*12 -> 0.0092221975 | BC13: =AY13*($AX$3/12) -> 4483.0917 | BD13: =(BC13/AY13)*12 -> 0.075 | BE13: =BE12+BA13 -> 3256.581 | BF13: =BF12+BC13 -> 26949.486 | BG13: =AY13-BA13 -> 716743.42 | BH13: =BE13+BF13 -> 30206.067 | BJ13: 6 | BK13: 45017 | BL13: =BT12 -> 717157.51 | BM13: =BM12 -> 4911.6692 | BN13: =BM13-BP13 -> 578.84257 | BO13: =(BN13/BL13)*12 -> 0.009685614 | BP13: =BL13*($BK$3/12) -> 4332.8266 | BQ13: =(BP13/BL13)*12 -> 0.0725 | BR13: =BR12+BN13 -> 3421.3285 | BS13: =BS12+BP13 -> 26048.687 | BT13: =BL13-BN13 -> 716578.67 | BU13: =BR13+BS13 -> 29470.015 | BW13: 6 | BX13: 45017 | BY13: =CG12 -> 717014.48 | BZ13: =BZ12 -> 4790.178 | CA13: =BZ13-CC13 -> 607.59349 | CB13: =(CA13/BY13)*12 -> 0.010168723 | CC13: =BY13*($BX$3/12) -> 4182.5845 | CD13: =(CC13/BY13)*12 -> 0.07 | CE13: =CE12+CA13 -> 3593.1118 | CF13: =CF12+CC13 -> 25147.956 | CG13: =BY13-CA13 -> 716406.89 | CH13: =CE13+CF13 -> 28741.068
A14: =A13+1 -> 4 | B14: =VLOOKUP(A14*12,$J$7:$U$367,10) -> 233633.32 | C14: =VLOOKUP(A14*12,$W$7:$AH$367,10) -> 226366.11 | D14: =VLOOKUP(A14*12,$AJ$7:$AU$367,10) -> 219103.17 | E14: =VLOOKUP(A14*12,$AW$7:$BH$367,10) -> 211845.01 | F14: =VLOOKUP(A14*12,$BJ$7:$BU$367,10) -> 204592.18 | G14: =VLOOKUP(A14*12,$BW$7:$CH$367,10) -> 197345.27 | J14: 7 | K14: 45047 | L14: =T13 -> 717197.5 | M14: =$L$8/((($N$4)-1)/($N$3*$N$4)) -> 5409.1195 | N14: =M14-P14 -> 478.38674 | O14: =(N14/L14)*12 -> 0.0080042678 | P14: =L14*($K$3/12) -> 4930.7328 | Q14: =(P14/L14)*12 -> 0.0825 | R14: =R13+N14 -> 3280.887 | S14: =S13+P14 -> 34582.95 | T14: =L14-N14 -> 716719.11 | U14: =R14+S14 -> 37863.837 | W14: 7 | X14: 45047 | Y14: =AG13 -> 717052.63 | Z14: =Z13 -> 5283.1049 | AA14: =Z14-AC14 -> 502.75408 | AB14: =(AA14/Y14)*12 -> 0.0084136766 | AC14: =Y14*($X$3/12) -> 4780.3509 | AD14: =(AC14/Y14)*12 -> 0.08 | AE14: =AE13+AA14 -> 3450.1257 | AF14: =AF13+AC14 -> 33531.609 | AG14: =Y14-AA14 -> 716549.87 | AH14: =AE14+AF14 -> 36981.735 | AJ14: 7 | AK14: 45047 | AL14: =AT13 -> 716901.34 | AM14: =AM13 -> 5158.1682 | AN14: =AM14-AP14 -> 528.18037 | AO14: =(AN14/AL14)*12 -> 0.0088410554 | AP14: =AL14*($AK$3/12) -> 4629.9878 | AQ14: =(AP14/AL14)*12 -> 0.0775 | AR14: =AR13+AN14 -> 3626.8441 | AS14: =AS13+AP14 -> 32480.333 | AT14: =AL14-AN14 -> 716373.16 | AU14: =AR14+AS14 -> 36107.177 | AW14: 7 | AX14: 45047 | AY14: =BG13 -> 716743.42 | AZ14: =AZ13 -> 5034.3445 | BA14: =AZ14-BC14 -> 554.69809 | BB14: =(BA14/AY14)*12 -> 0.0092869735 | BC14: =AY14*($AX$3/12) -> 4479.6464 | BD14: =(BC14/AY14)*12 -> 0.075 | BE14: =BE13+BA14 -> 3811.2791 | BF14: =BF13+BC14 -> 31429.132 | BG14: =AY14-BA14 -> 716188.72 | BH14: =BE14+BF14 -> 35240.411 | BJ14: 7 | BK14: 45047 | BL14: =BT13 -> 716578.67 | BM14: =BM13 -> 4911.6692 | BN14: =BM14-BP14 -> 582.33974 | BO14: =(BN14/BL14)*12 -> 0.0097520024 | BP14: =BL14*($BK$3/12) -> 4329.3295 | BQ14: =(BP14/BL14)*12 -> 0.0725 | BR14: =BR13+BN14 -> 4003.6682 | BS14: =BS13+BP14 -> 30378.016 | BT14: =BL14-BN14 -> 715996.33 | BU14: =BR14+BS14 -> 34381.685 | BW14: 7 | BX14: 45047 | BY14: =CG13 -> 716406.89 | BZ14: =BZ13 -> 4790.178 | CA14: =BZ14-CC14 -> 611.13778 | CB14: =(CA14/BY14)*12 -> 0.010236715 | CC14: =BY14*($BX$3/12) -> 4179.0402 | CD14: =(CC14/BY14)*12 -> 0.07 | CE14: =CE13+CA14 -> 4204.2496 | CF14: =CF13+CC14 -> 29326.996 | CG14: =BY14-CA14 -> 715795.75 | CH14: =CE14+CF14 -> 33531.246
A15: =A14+1 -> 5 | B15: =VLOOKUP(A15*12,$J$7:$U$367,10) -> 290591.77 | C15: =VLOOKUP(A15*12,$W$7:$AH$367,10) -> 281489.26 | D15: =VLOOKUP(A15*12,$AJ$7:$AU$367,10) -> 272393.8 | E15: =VLOOKUP(A15*12,$AW$7:$BH$367,10) -> 263306.21 | F15: =VLOOKUP(A15*12,$BJ$7:$BU$367,10) -> 254227.35 | G15: =VLOOKUP(A15*12,$BW$7:$CH$367,10) -> 245158.12 | J15: 8 | K15: 45078 | L15: =T14 -> 716719.11 | M15: =$L$8/((($N$4)-1)/($N$3*$N$4)) -> 5409.1195 | N15: =M15-P15 -> 481.67565 | O15: =(N15/L15)*12 -> 0.0080646765 | P15: =L15*($K$3/12) -> 4927.4439 | Q15: =(P15/L15)*12 -> 0.0825 | R15: =R14+N15 -> 3762.5626 | S15: =S14+P15 -> 39510.394 | T15: =L15-N15 -> 716237.44 | U15: =R15+S15 -> 43272.956 | W15: 8 | X15: 45078 | Y15: =AG14 -> 716549.87 | Z15: =Z14 -> 5283.1049 | AA15: =Z15-AC15 -> 506.10577 | AB15: =(AA15/Y15)*12 -> 0.0084757104 | AC15: =Y15*($X$3/12) -> 4776.9992 | AD15: =(AC15/Y15)*12 -> 0.08 | AE15: =AE14+AA15 -> 3956.2315 | AF15: =AF14+AC15 -> 38308.608 | AG15: =Y15-AA15 -> 716043.77 | AH15: =AE15+AF15 -> 42264.839 | AJ15: 8 | AK15: 45078 | AL15: =AT14 -> 716373.16 | AM15: =AM14 -> 5158.1682 | AN15: =AM15-AP15 -> 531.59154 | AO15: =(AN15/AL15)*12 -> 0.0089047145 | AP15: =AL15*($AK$3/12) -> 4626.5766 | AQ15: =(AP15/AL15)*12 -> 0.0775 | AR15: =AR14+AN15 -> 4158.4357 | AS15: =AS14+AP15 -> 37106.91 | AT15: =AL15-AN15 -> 715841.56 | AU15: =AR15+AS15 -> 41265.345 | AW15: 8 | AX15: 45078 | AY15: =BG14 -> 716188.72 | AZ15: =AZ14 -> 5034.3445 | BA15: =AZ15-BC15 -> 558.16496 | BB15: =(BA15/AY15)*12 -> 0.0093522549 | BC15: =AY15*($AX$3/12) -> 4476.1795 | BD15: =(BC15/AY15)*12 -> 0.075 | BE15: =BE14+BA15 -> 4369.444 | BF15: =BF14+BC15 -> 35905.312 | BG15: =AY15-BA15 -> 715630.56 | BH15: =BE15+BF15 -> 40274.756 | BJ15: 8 | BK15: 45078 | BL15: =BT14 -> 715996.33 | BM15: =BM14 -> 4911.6692 | BN15: =BM15-BP15 -> 585.85805 | BO15: =(BN15/BL15)*12 -> 0.0098189002 | BP15: =BL15*($BK$3/12) -> 4325.8112 | BQ15: =(BP15/BL15)*12 -> 0.0725 | BR15: =BR14+BN15 -> 4589.5263 | BS15: =BS14+BP15 -> 34703.827 | BT15: =BL15-BN15 -> 715410.47 | BU15: =BR15+BS15 -> 39293.354 | BW15: 8 | BX15: 45078 | BY15: =CG14 -> 715795.75 | BZ15: =BZ14 -> 4790.178 | CA15: =BZ15-CC15 -> 614.70275 | CB15: =(CA15/BY15)*12 -> 0.010305221 | CC15: =BY15*($BX$3/12) -> 4175.4752 | CD15: =(CC15/BY15)*12 -> 0.07 | CE15: =CE14+CA15 -> 4818.9523 | CF15: =CF14+CC15 -> 33502.471 | CG15: =BY15-CA15 -> 715181.05 | CH15: =CE15+CF15 -> 38321.424
A16: =A15+1 -> 6 | B16: =VLOOKUP(A16*12,$J$7:$U$367,10) -> 346868.88 | C16: =VLOOKUP(A16*12,$W$7:$AH$367,10) -> 335925.67 | D16: =VLOOKUP(A16*12,$AJ$7:$AU$367,10) -> 324993.15 | E16: =VLOOKUP(A16*12,$AW$7:$BH$367,10) -> 314072.53 | F16: =VLOOKUP(A16*12,$BJ$7:$BU$367,10) -> 303165.04 | G16: =VLOOKUP(A16*12,$BW$7:$CH$367,10) -> 292271.99 | J16: 9 | K16: 45108 | L16: =T15 -> 716237.44 | M16: =$L$8/((($N$4)-1)/($N$3*$N$4)) -> 5409.1195 | N16: =M16-P16 -> 484.98717 | O16: =(N16/L16)*12 -> 0.008125582 | P16: =L16*($K$3/12) -> 4924.1324 | Q16: =(P16/L16)*12 -> 0.0825 | R16: =R15+N16 -> 4247.5498 | S16: =S15+P16 -> 44434.526 | T16: =L16-N16 -> 715752.45 | U16: =R16+S16 -> 48682.076 | W16: 9 | X16: 45108 | Y16: =AG15 -> 716043.77 | Z16: =Z15 -> 5283.1049 | AA16: =Z16-AC16 -> 509.47981 | AB16: =(AA16/Y16)*12 -> 0.0085382458 | AC16: =Y16*($X$3/12) -> 4773.6251 | AD16: =(AC16/Y16)*12 -> 0.08 | AE16: =AE15+AA16 -> 4465.7113 | AF16: =AF15+AC16 -> 43082.233 | AG16: =Y16-AA16 -> 715534.29 | AH16: =AE16+AF16 -> 47547.944 | AJ16: 9 | AK16: 45108 | AL16: =AT15 -> 715841.56 | AM16: =AM15 -> 5158.1682 | AN16: =AM16-AP16 -> 535.02473 | AO16: =(AN16/AL16)*12 -> 0.0089688796 | AP16: =AL16*($AK$3/12) -> 4623.1434 | AQ16: =(AP16/AL16)*12 -> 0.0775 | AR16: =AR15+AN16 -> 4693.4604 | AS16: =AS15+AP16 -> 41730.053 | AT16: =AL16-AN16 -> 715306.54 | AU16: =AR16+AS16 -> 46423.514 | AW16: 9 | AX16: 45108 | AY16: =BG15 -> 715630.56 | AZ16: =AZ15 -> 5034.3445 | BA16: =AZ16-BC16 -> 561.65349 | BB16: =(BA16/AY16)*12 -> 0.0094180465 | BC16: =AY16*($AX$3/12) -> 4472.691 | BD16: =(BC16/AY16)*12 -> 0.075 | BE16: =BE15+BA16 -> 4931.0975 | BF16: =BF15+BC16 -> 40378.003 | BG16: =AY16-BA16 -> 715068.9 | BH16: =BE16+BF16 -> 45309.1 | BJ16: 9 | BK16: 45108 | BL16: =BT15 -> 715410.47 | BM16: =BM15 -> 4911.6692 | BN16: =BM16-BP16 -> 589.3976 | BO16: =(BN16/BL16)*12 -> 0.0098863121 | BP16: =BL16*($BK$3/12) -> 4322.2716 | BQ16: =(BP16/BL16)*12 -> 0.0725 | BR16: =BR15+BN16 -> 5178.9239 | BS16: =BS15+BP16 -> 39026.099 | BT16: =BL16-BN16 -> 714821.08 | BU16: =BR16+BS16 -> 44205.023 | BW16: 9 | BX16: 45108 | BY16: =CG15 -> 715181.05 | BZ16: =BZ15 -> 4790.178 | CA16: =BZ16-CC16 -> 618.28852 | CB16: =(CA16/BY16)*12 -> 0.010374243 | CC16: =BY16*($BX$3/12) -> 4171.8894 | CD16: =(CC16/BY16)*12 -> 0.07 | CE16: =CE15+CA16 -> 5437.2408 | CF16: =CF15+CC16 -> 37674.361 | CG16: =BY16-CA16 -> 714562.76 | CH16: =CE16+CF16 -> 43111.602
A17: =A16+1 -> 7 | B17: =VLOOKUP(A17*12,$J$7:$U$367,10) -> 402406.28 | C17: =VLOOKUP(A17*12,$W$7:$AH$367,10) -> 389618.32 | D17: =VLOOKUP(A17*12,$AJ$7:$AU$367,10) -> 376845.7 | E17: =VLOOKUP(A17*12,$AW$7:$BH$367,10) -> 364090.01 | F17: =VLOOKUP(A17*12,$BJ$7:$BU$367,10) -> 351352.97 | G17: =VLOOKUP(A17*12,$BW$7:$CH$367,10) -> 338636.33 | J17: 10 | K17: 45139 | L17: =T16 -> 715752.45 | M17: =$L$8/((($N$4)-1)/($N$3*$N$4)) -> 5409.1195 | N17: =M17-P17 -> 488.32145 | O17: =(N17/L17)*12 -> 0.008186989 | P17: =L17*($K$3/12) -> 4920.7981 | Q17: =(P17/L17)*12 -> 0.0825 | R17: =R16+N17 -> 4735.8713 | S17: =S16+P17 -> 49355.324 | T17: =L17-N17 -> 715264.13 | U17: =R17+S17 -> 54091.195 | W17: 10 | X17: 45139 | Y17: =AG16 -> 715534.29 | Z17: =Z16 -> 5283.1049 | AA17: =Z17-AC17 -> 512.87634 | AB17: =(AA17/Y17)*12 -> 0.0086012874 | AC17: =Y17*($X$3/12) -> 4770.2286 | AD17: =(AC17/Y17)*12 -> 0.08 | AE17: =AE16+AA17 -> 4978.5877 | AF17: =AF16+AC17 -> 47852.462 | AG17: =Y17-AA17 -> 715021.41 | AH17: =AE17+AF17 -> 52831.049 | AJ17: 10 | AK17: 45139 | AL17: =AT16 -> 715306.54 | AM17: =AM16 -> 5158.1682 | AN17: =AM17-AP17 -> 538.4801 | AO17: =(AN17/AL17)*12 -> 0.0090335553 | AP17: =AL17*($AK$3/12) -> 4619.6881 | AQ17: =(AP17/AL17)*12 -> 0.0775 | AR17: =AR16+AN17 -> 5231.9405 | AS17: =AS16+AP17 -> 46349.741 | AT17: =AL17-AN17 -> 714768.06 | AU17: =AR17+AS17 -> 51581.682 | AW17: 10 | AX17: 45139 | AY17: =BG16 -> 715068.9 | AZ17: =AZ16 -> 5034.3445 | BA17: =AZ17-BC17 -> 565.16382 | BB17: =(BA17/AY17)*12 -> 0.0094843529 | BC17: =AY17*($AX$3/12) -> 4469.1806 | BD17: =(BC17/AY17)*12 -> 0.075 | BE17: =BE16+BA17 -> 5496.2613 | BF17: =BF16+BC17 -> 44847.183 | BG17: =AY17-BA17 -> 714503.74 | BH17: =BE17+BF17 -> 50343.445 | BJ17: 10 | BK17: 45139 | BL17: =BT16 -> 714821.08 | BM17: =BM16 -> 4911.6692 | BN17: =BM17-BP17 -> 592.95855 | BO17: =(BN17/BL17)*12 -> 0.0099542428 | BP17: =BL17*($BK$3/12) -> 4318.7107 | BQ17: =(BP17/BL17)*12 -> 0.0725 | BR17: =BR16+BN17 -> 5771.8824 | BS17: =BS16+BP17 -> 43344.81 | BT17: =BL17-BN17 -> 714228.12 | BU17: =BR17+BS17 -> 49116.692 | BW17: 10 | BX17: 45139 | BY17: =CG16 -> 714562.76 | BZ17: =BZ16 -> 4790.178 | CA17: =BZ17-CC17 -> 621.8952 | CB17: =(CA17/BY17)*12 -> 0.010443789 | CC17: =BY17*($BX$3/12) -> 4168.2828 | CD17: =(CC17/BY17)*12 -> 0.07 | CE17: =CE16+CA17 -> 6059.136 | CF17: =CF16+CC17 -> 41842.644 | CG17: =BY17-CA17 -> 713940.86 | CH17: =CE17+CF17 -> 47901.78
A18: =A17+1 -> 8 | B18: =VLOOKUP(A18*12,$J$7:$U$367,10) -> 457140.56 | C18: =VLOOKUP(A18*12,$W$7:$AH$367,10) -> 442505.5 | D18: =VLOOKUP(A18*12,$AJ$7:$AU$367,10) -> 427891.46 | E18: =VLOOKUP(A18*12,$AW$7:$BH$367,10) -> 413300.54 | F18: =VLOOKUP(A18*12,$BJ$7:$BU$367,10) -> 398734.94 | G18: =VLOOKUP(A18*12,$BW$7:$CH$367,10) -> 384196.97 | J18: 11 | K18: 45170 | L18: =T17 -> 715264.13 | M18: =$L$8/((($N$4)-1)/($N$3*$N$4)) -> 5409.1195 | N18: =M18-P18 -> 491.67866 | O18: =(N18/L18)*12 -> 0.0082489024 | P18: =L18*($K$3/12) -> 4917.4409 | Q18: =(P18/L18)*12 -> 0.0825 | R18: =R17+N18 -> 5227.5499 | S18: =S17+P18 -> 54272.765 | T18: =L18-N18 -> 714772.45 | U18: =R18+S18 -> 59500.315 | W18: 11 | X18: 45170 | Y18: =AG17 -> 715021.41 | Z18: =Z17 -> 5283.1049 | AA18: =Z18-AC18 -> 516.29552 | AB18: =(AA18/Y18)*12 -> 0.0086648401 | AC18: =Y18*($X$3/12) -> 4766.8094 | AD18: =(AC18/Y18)*12 -> 0.08 | AE18: =AE17+AA18 -> 5494.8832 | AF18: =AF17+AC18 -> 52619.271 | AG18: =Y18-AA18 -> 714505.12 | AH18: =AE18+AF18 -> 58114.154 | AJ18: 11 | AK18: 45170 | AL18: =AT17 -> 714768.06 | AM18: =AM17 -> 5158.1682 | AN18: =AM18-AP18 -> 541.95778 | AO18: =(AN18/AL18)*12 -> 0.0090987465 | AP18: =AL18*($AK$3/12) -> 4616.2104 | AQ18: =(AP18/AL18)*12 -> 0.0775 | AR18: =AR17+AN18 -> 5773.8983 | AS18: =AS17+AP18 -> 50965.952 | AT18: =AL18-AN18 -> 714226.1 | AU18: =AR18+AS18 -> 56739.85 | AW18: 11 | AX18: 45170 | AY18: =BG17 -> 714503.74 | AZ18: =AZ17 -> 5034.3445 | BA18: =AZ18-BC18 -> 568.69609 | BB18: =(BA18/AY18)*12 -> 0.009551179 | BC18: =AY18*($AX$3/12) -> 4465.6484 | BD18: =(BC18/AY18)*12 -> 0.075 | BE18: =BE17+BA18 -> 6064.9574 | BF18: =BF17+BC18 -> 49312.832 | BG18: =AY18-BA18 -> 713935.04 | BH18: =BE18+BF18 -> 55377.789 | BJ18: 11 | BK18: 45170 | BL18: =BT17 -> 714228.12 | BM18: =BM17 -> 4911.6692 | BN18: =BM18-BP18 -> 596.54101 | BO18: =(BN18/BL18)*12 -> 0.010022697 | BP18: =BL18*($BK$3/12) -> 4315.1282 | BQ18: =(BP18/BL18)*12 -> 0.0725 | BR18: =BR17+BN18 -> 6368.4234 | BS18: =BS17+BP18 -> 47659.938 | BT18: =BL18-BN18 -> 713631.58 | BU18: =BR18+BS18 -> 54028.361 | BW18: 11 | BX18: 45170 | BY18: =CG17 -> 713940.86 | BZ18: =BZ17 -> 4790.178 | CA18: =BZ18-CC18 -> 625.52293 | CB18: =(CA18/BY18)*12 -> 0.010513861 | CC18: =BY18*($BX$3/12) -> 4164.655 | CD18: =(CC18/BY18)*12 -> 0.07 | CE18: =CE17+CA18 -> 6684.659 | CF18: =CF17+CC18 -> 46007.299 | CG18: =BY18-CA18 -> 713315.34 | CH18: =CE18+CF18 -> 52691.958
A19: =A18+1 -> 9 | B19: =VLOOKUP(A19*12,$J$7:$U$367,10) -> 511002.91 | C19: =VLOOKUP(A19*12,$W$7:$AH$367,10) -> 494520.35 | D19: =VLOOKUP(A19*12,$AJ$7:$AU$367,10) -> 478065.64 | E19: =VLOOKUP(A19*12,$AW$7:$BH$367,10) -> 461641.45 | F19: =VLOOKUP(A19*12,$BJ$7:$BU$367,10) -> 445250.54 | G19: =VLOOKUP(A19*12,$BW$7:$CH$367,10) -> 428895.79 | J19: 12 | K19: 45200 | L19: =T18 -> 714772.45 | M19: =$L$8/((($N$4)-1)/($N$3*$N$4)) -> 5409.1195 | N19: =M19-P19 -> 495.05895 | O19: =(N19/L19)*12 -> 0.0083113269 | P19: =L19*($K$3/12) -> 4914.0606 | Q19: =(P19/L19)*12 -> 0.0825 | R19: =R18+N19 -> 5722.6089 | S19: =S18+P19 -> 59186.826 | T19: =L19-N19 -> 714277.39 | U19: =R19+S19 -> 64909.435 | W19: 12 | X19: 45200 | Y19: =AG18 -> 714505.12 | Z19: =Z18 -> 5283.1049 | AA19: =Z19-AC19 -> 519.73749 | AB19: =(AA19/Y19)*12 -> 0.0087289086 | AC19: =Y19*($X$3/12) -> 4763.3674 | AD19: =(AC19/Y19)*12 -> 0.08 | AE19: =AE18+AA19 -> 6014.6207 | AF19: =AF18+AC19 -> 57382.639 | AG19: =Y19-AA19 -> 713985.38 | AH19: =AE19+AF19 -> 63397.259 | AJ19: 12 | AK19: 45200 | AL19: =AT18 -> 714226.1 | AM19: =AM18 -> 5158.1682 | AN19: =AM19-AP19 -> 545.45793 | AO19: =(AN19/AL19)*12 -> 0.009164458 | AP19: =AL19*($AK$3/12) -> 4612.7102 | AQ19: =(AP19/AL19)*12 -> 0.0775 | AR19: =AR18+AN19 -> 6319.3562 | AS19: =AS18+AP19 -> 55578.662 | AT19: =AL19-AN19 -> 713680.64 | AU19: =AR19+AS19 -> 61898.018 | AW19: 12 | AX19: 45200 | AY19: =BG18 -> 713935.04 | AZ19: =AZ18 -> 5034.3445 | BA19: =AZ19-BC19 -> 572.25045 | BB19: =(BA19/AY19)*12 -> 0.0096185296 | BC19: =AY19*($AX$3/12) -> 4462.094 | BD19: =(BC19/AY19)*12 -> 0.075 | BE19: =BE18+BA19 -> 6637.2079 | BF19: =BF18+BC19 -> 53774.926 | BG19: =AY19-BA19 -> 713362.79 | BH19: =BE19+BF19 -> 60412.134 | BJ19: 12 | BK19: 45200 | BL19: =BT18 -> 713631.58 | BM19: =BM18 -> 4911.6692 | BN19: =BM19-BP19 -> 600.14511 | BO19: =(BN19/BL19)*12 -> 0.01009168 | BP19: =BL19*($BK$3/12) -> 4311.5241 | BQ19: =(BP19/BL19)*12 -> 0.0725 | BR19: =BR18+BN19 -> 6968.5685 | BS19: =BS18+BP19 -> 51971.462 | BT19: =BL19-BN19 -> 713031.43 | BU19: =BR19+BS19 -> 58940.031 | BW19: 12 | BX19: 45200 | BY19: =CG18 -> 713315.34 | BZ19: =BZ18 -> 4790.178 | CA19: =BZ19-CC19 -> 629.17181 | CB19: =(CA19/BY19)*12 -> 0.010584466 | CC19: =BY19*($BX$3/12) -> 4161.0062 | CD19: =(CC19/BY19)*12 -> 0.07 | CE19: =CE18+CA19 -> 7313.8308 | CF19: =CF18+CC19 -> 50168.305 | CG19: =BY19-CA19 -> 712686.17 | CH19: =CE19+CF19 -> 57482.136
A20: =A19+1 -> 10 | B20: =VLOOKUP(A20*12,$J$7:$U$367,10) -> 563918.61 | C20: =VLOOKUP(A20*12,$W$7:$AH$367,10) -> 545590.46 | D20: =VLOOKUP(A20*12,$AJ$7:$AU$367,10) -> 527298.25 | E20: =VLOOKUP(A20*12,$AW$7:$BH$367,10) -> 509045.24 | F20: =VLOOKUP(A20*12,$BJ$7:$BU$367,10) -> 490834.83 | G20: =VLOOKUP(A20*12,$BW$7:$CH$367,10) -> 472670.52 | J20: 13 | K20: 45231 | L20: =T19 -> 714277.39 | M20: =$L$8/((($N$4)-1)/($N$3*$N$4)) -> 5409.1195 | N20: =M20-P20 -> 498.46249 | O20: =(N20/L20)*12 -> 0.0083742673 | P20: =L20*($K$3/12) -> 4910.6571 | Q20: =(P20/L20)*12 -> 0.0825 | R20: =R19+N20 -> 6221.0714 | S20: =S19+P20 -> 64097.483 | T20: =L20-N20 -> 713778.93 | U20: =R20+S20 -> 70318.554 | W20: 13 | X20: 45231 | Y20: =AG19 -> 713985.38 | Z20: =Z19 -> 5283.1049 | AA20: =Z20-AC20 -> 523.2024 | AB20: =(AA20/Y20)*12 -> 0.0087934978 | AC20: =Y20*($X$3/12) -> 4759.9025 | AD20: =(AC20/Y20)*12 -> 0.08 | AE20: =AE19+AA20 -> 6537.8231 | AF20: =AF19+AC20 -> 62142.541 | AG20: =Y20-AA20 -> 713462.18 | AH20: =AE20+AF20 -> 68680.364 | AJ20: 13 | AK20: 45231 | AL20: =AT19 -> 713680.64 | AM20: =AM19 -> 5158.1682 | AN20: =AM20-AP20 -> 548.98068 | AO20: =(AN20/AL20)*12 -> 0.0092306947 | AP20: =AL20*($AK$3/12) -> 4609.1875 | AQ20: =(AP20/AL20)*12 -> 0.0775 | AR20: =AR19+AN20 -> 6868.3369 | AS20: =AS19+AP20 -> 60187.849 | AT20: =AL20-AN20 -> 713131.66 | AU20: =AR20+AS20 -> 67056.186 | AW20: 13 | AX20: 45231 | AY20: =BG19 -> 713362.79 | AZ20: =AZ19 -> 5034.3445 | BA20: =AZ20-BC20 -> 575.82701 | BB20: =(BA20/AY20)*12 -> 0.0096864095 | BC20: =AY20*($AX$3/12) -> 4458.5175 | BD20: =(BC20/AY20)*12 -> 0.075 | BE20: =BE19+BA20 -> 7213.0349 | BF20: =BF19+BC20 -> 58233.443 | BG20: =AY20-BA20 -> 712786.97 | BH20: =BE20+BF20 -> 65446.478 | BJ20: 13 | BK20: 45231 | BL20: =BT19 -> 713031.43 | BM20: =BM19 -> 4911.6692 | BN20: =BM20-BP20 -> 603.77098 | BO20: =(BN20/BL20)*12 -> 0.010161196 | BP20: =BL20*($BK$3/12) -> 4307.8982 | BQ20: =(BP20/BL20)*12 -> 0.0725 | BR20: =BR19+BN20 -> 7572.3395 | BS20: =BS19+BP20 -> 56279.36 | BT20: =BL20-BN20 -> 712427.66 | BU20: =BR20+BS20 -> 63851.7 | BW20: 13 | BX20: 45231 | BY20: =CG19 -> 712686.17 | BZ20: =BZ19 -> 4790.178 | CA20: =BZ20-CC20 -> 632.84198 | CB20: =(CA20/BY20)*12 -> 0.010655607 | CC20: =BY20*($BX$3/12) -> 4157.336 | CD20: =(CC20/BY20)*12 -> 0.07 | CE20: =CE19+CA20 -> 7946.6727 | CF20: =CF19+CC20 -> 54325.641 | CG20: =BY20-CA20 -> 712053.33 | CH20: =CE20+CF20 -> 62272.314
A21: =A20+1 -> 11 | B21: =VLOOKUP(A21*12,$J$7:$U$367,10) -> 615806.55 | C21: =VLOOKUP(A21*12,$W$7:$AH$367,10) -> 595637.43 | D21: =VLOOKUP(A21*12,$AJ$7:$AU$367,10) -> 575513.66 | E21: =VLOOKUP(A21*12,$AW$7:$BH$367,10) -> 555439.16 | F21: =VLOOKUP(A21*12,$BJ$7:$BU$367,10) -> 535417.99 | G21: =VLOOKUP(A21*12,$BW$7:$CH$367,10) -> 515454.33 | J21: 14 | K21: 45261 | L21: =T20 -> 713778.93 | M21: =$L$8/((($N$4)-1)/($N$3*$N$4)) -> 5409.1195 | N21: =M21-P21 -> 501.88941 | O21: =(N21/L21)*12 -> 0.0084377287 | P21: =L21*($K$3/12) -> 4907.2301 | Q21: =(P21/L21)*12 -> 0.0825 | R21: =R20+N21 -> 6722.9608 | S21: =S20+P21 -> 69004.713 | T21: =L21-N21 -> 713277.04 | U21: =R21+S21 -> 75727.674 | W21: 14 | X21: 45261 | Y21: =AG20 -> 713462.18 | Z21: =Z20 -> 5283.1049 | AA21: =Z21-AC21 -> 526.69042 | AB21: =(AA21/Y21)*12 -> 0.0088586126 | AC21: =Y21*($X$3/12) -> 4756.4145 | AD21: =(AC21/Y21)*12 -> 0.08 | AE21: =AE20+AA21 -> 7064.5135 | AF21: =AF20+AC21 -> 66898.956 | AG21: =Y21-AA21 -> 712935.49 | AH21: =AE21+AF21 -> 73963.469 | AJ21: 14 | AK21: 45261 | AL21: =AT20 -> 713131.66 | AM21: =AM20 -> 5158.1682 | AN21: =AM21-AP21 -> 552.52618 | AO21: =(AN21/AL21)*12 -> 0.0092974614 | AP21: =AL21*($AK$3/12) -> 4605.642 | AQ21: =(AP21/AL21)*12 -> 0.0775 | AR21: =AR20+AN21 -> 7420.8631 | AS21: =AS20+AP21 -> 64793.491 | AT21: =AL21-AN21 -> 712579.14 | AU21: =AR21+AS21 -> 72214.354 | AW21: 14 | AX21: 45261 | AY21: =BG20 -> 712786.97 | AZ21: =AZ20 -> 5034.3445 | BA21: =AZ21-BC21 -> 579.42593 | BB21: =(BA21/AY21)*12 -> 0.0097548237 | BC21: =AY21*($AX$3/12) -> 4454.9185 | BD21: =(BC21/AY21)*12 -> 0.075 | BE21: =BE20+BA21 -> 7792.4608 | BF21: =BF20+BC21 -> 62688.362 | BG21: =AY21-BA21 -> 712207.54 | BH21: =BE21+BF21 -> 70480.822 | BJ21: 14 | BK21: 45261 | BL21: =BT20 -> 712427.66 | BM21: =BM20 -> 4911.6692 | BN21: =BM21-BP21 -> 607.41877 | BO21: =(BN21/BL21)*12 -> 0.01023125 | BP21: =BL21*($BK$3/12) -> 4304.2504 | BQ21: =(BP21/BL21)*12 -> 0.0725 | BR21: =BR20+BN21 -> 8179.7583 | BS21: =BS20+BP21 -> 60583.611 | BT21: =BL21-BN21 -> 711820.24 | BU21: =BR21+BS21 -> 68763.369 | BW21: 14 | BX21: 45261 | BY21: =CG20 -> 712053.33 | BZ21: =BZ20 -> 4790.178 | CA21: =BZ21-CC21 -> 636.53356 | CB21: =(CA21/BY21)*12 -> 0.01072729 | CC21: =BY21*($BX$3/12) -> 4153.6444 | CD21: =(CC21/BY21)*12 -> 0.07 | CE21: =CE20+CA21 -> 8583.2063 | CF21: =CF20+CC21 -> 58479.285 | CG21: =BY21-CA21 -> 711416.79 | CH21: =CE21+CF21 -> 67062.492
A22: =A21+1 -> 12 | B22: =VLOOKUP(A22*12,$J$7:$U$367,10) -> 666578.65 | C22: =VLOOKUP(A22*12,$W$7:$AH$367,10) -> 644576.32 | D22: =VLOOKUP(A22*12,$AJ$7:$AU$367,10) -> 622630.18 | E22: =VLOOKUP(A22*12,$AW$7:$BH$367,10) -> 600744.82 | F22: =VLOOKUP(A22*12,$BJ$7:$BU$367,10) -> 578924.98 | G22: =VLOOKUP(A22*12,$BW$7:$CH$367,10) -> 557175.6 | J22: 15 | K22: 45292 | L22: =T21 -> 713277.04 | M22: =$L$8/((($N$4)-1)/($N$3*$N$4)) -> 5409.1195 | N22: =M22-P22 -> 505.3399 | O22: =(N22/L22)*12 -> 0.0085017161 | P22: =L22*($K$3/12) -> 4903.7796 | Q22: =(P22/L22)*12 -> 0.0825 | R22: =R21+N22 -> 7228.3007 | S22: =S21+P22 -> 73908.493 | T22: =L22-N22 -> 712771.7 | U22: =R22+S22 -> 81136.793 | W22: 15 | X22: 45292 | Y22: =AG21 -> 712935.49 | Z22: =Z21 -> 5283.1049 | AA22: =Z22-AC22 -> 530.20169 | AB22: =(AA22/Y22)*12 -> 0.0089242581 | AC22: =Y22*($X$3/12) -> 4752.9032 | AD22: =(AC22/Y22)*12 -> 0.08 | AE22: =AE21+AA22 -> 7594.7152 | AF22: =AF21+AC22 -> 71651.859 | AG22: =Y22-AA22 -> 712405.28 | AH22: =AE22+AF22 -> 79246.574 | AJ22: 15 | AK22: 45292 | AL22: =AT21 -> 712579.14 | AM22: =AM21 -> 5158.1682 | AN22: =AM22-AP22 -> 556.09458 | AO22: =(AN22/AL22)*12 -> 0.0093647632 | AP22: =AL22*($AK$3/12) -> 4602.0736 | AQ22: =(AP22/AL22)*12 -> 0.0775 | AR22: =AR21+AN22 -> 7976.9577 | AS22: =AS21+AP22 -> 69395.565 | AT22: =AL22-AN22 -> 712023.04 | AU22: =AR22+AS22 -> 77372.523 | AW22: 15 | AX22: 45292 | AY22: =BG21 -> 712207.54 | AZ22: =AZ21 -> 5034.3445 | BA22: =AZ22-BC22 -> 583.04734 | BB22: =(BA22/AY22)*12 -> 0.0098237771 | BC22: =AY22*($AX$3/12) -> 4451.2971 | BD22: =(BC22/AY22)*12 -> 0.075 | BE22: =BE21+BA22 -> 8375.5082 | BF22: =BF21+BC22 -> 67139.659 | BG22: =AY22-BA22 -> 711624.49 | BH22: =BE22+BF22 -> 75515.167 | BJ22: 15 | BK22: 45292 | BL22: =BT21 -> 711820.24 | BM22: =BM21 -> 4911.6692 | BN22: =BM22-BP22 -> 611.08859 | BO22: =(BN22/BL22)*12 -> 0.010301847 | BP22: =BL22*($BK$3/12) -> 4300.5806 | BQ22: =(BP22/BL22)*12 -> 0.0725 | BR22: =BR21+BN22 -> 8790.8469 | BS22: =BS21+BP22 -> 64884.191 | BT22: =BL22-BN22 -> 711209.15 | BU22: =BR22+BS22 -> 73675.038 | BW22: 15 | BX22: 45292 | BY22: =CG21 -> 711416.79 | BZ22: =BZ21 -> 4790.178 | CA22: =BZ22-CC22 -> 640.24667 | CB22: =(CA22/BY22)*12 -> 0.01079952 | CC22: =BY22*($BX$3/12) -> 4149.9313 | CD22: =(CC22/BY22)*12 -> 0.07 | CE22: =CE21+CA22 -> 9223.453 | CF22: =CF21+CC22 -> 62629.217 | CG22: =BY22-CA22 -> 710776.55 | CH22: =CE22+CF22 -> 71852.669
A23: =A22+1 -> 13 | B23: =VLOOKUP(A23*12,$J$7:$U$367,10) -> 716139.28 | C23: =VLOOKUP(A23*12,$W$7:$AH$367,10) -> 692315.18 | D23: =VLOOKUP(A23*12,$AJ$7:$AU$367,10) -> 668559.55 | E23: =VLOOKUP(A23*12,$AW$7:$BH$367,10) -> 644877.71 | F23: =VLOOKUP(A23*12,$BJ$7:$BU$367,10) -> 621275.14 | G23: =VLOOKUP(A23*12,$BW$7:$CH$367,10) -> 597757.51 | J23: 16 | K23: 45323 | L23: =T22 -> 712771.7 | M23: =$L$8/((($N$4)-1)/($N$3*$N$4)) -> 5409.1195 | N23: =M23-P23 -> 508.81412 | O23: =(N23/L23)*12 -> 0.0085662343 | P23: =L23*($K$3/12) -> 4900.3054 | Q23: =(P23/L23)*12 -> 0.0825 | R23: =R22+N23 -> 7737.1148 | S23: =S22+P23 -> 78808.798 | T23: =L23-N23 -> 712262.89 | U23: =R23+S23 -> 86545.913 | W23: 16 | X23: 45323 | Y23: =AG22 -> 712405.28 | Z23: =Z22 -> 5283.1049 | AA23: =Z23-AC23 -> 533.73637 | AB23: =(AA23/Y23)*12 -> 0.0089904392 | AC23: =Y23*($X$3/12) -> 4749.3686 | AD23: =(AC23/Y23)*12 -> 0.08 | AE23: =AE22+AA23 -> 8128.4515 | AF23: =AF22+AC23 -> 76401.227 | AG23: =Y23-AA23 -> 711871.55 | AH23: =AE23+AF23 -> 84529.679 | AJ23: 16 | AK23: 45323 | AL23: =AT22 -> 712023.04 | AM23: =AM22 -> 5158.1682 | AN23: =AM23-AP23 -> 559.68602 | AO23: =(AN23/AL23)*12 -> 0.0094326052 | AP23: =AL23*($AK$3/12) -> 4598.4821 | AQ23: =(AP23/AL23)*12 -> 0.0775 | AR23: =AR22+AN23 -> 8536.6437 | AS23: =AS22+AP23 -> 73994.047 | AT23: =AL23-AN23 -> 711463.36 | AU23: =AR23+AS23 -> 82530.691 | AW23: 16 | AX23: 45323 | AY23: =BG22 -> 711624.49 | AZ23: =AZ22 -> 5034.3445 | BA23: =AZ23-BC23 -> 586.69139 | BB23: =(BA23/AY23)*12 -> 0.0098932748 | BC23: =AY23*($AX$3/12) -> 4447.6531 | BD23: =(BC23/AY23)*12 -> 0.075 | BE23: =BE22+BA23 -> 8962.1995 | BF23: =BF22+BC23 -> 71587.312 | BG23: =AY23-BA23 -> 711037.8 | BH23: =BE23+BF23 -> 80549.511 | BJ23: 16 | BK23: 45323 | BL23: =BT22 -> 711209.15 | BM23: =BM22 -> 4911.6692 | BN23: =BM23-BP23 -> 614.78058 | BO23: =(BN23/BL23)*12 -> 0.010372992 | BP23: =BL23*($BK$3/12) -> 4296.8886 | BQ23: =(BP23/BL23)*12 -> 0.0725 | BR23: =BR22+BN23 -> 9405.6275 | BS23: =BS22+BP23 -> 69181.08 | BT23: =BL23-BN23 -> 710594.37 | BU23: =BR23+BS23 -> 78586.707 | BW23: 16 | BX23: 45323 | BY23: =CG22 -> 710776.55 | BZ23: =BZ22 -> 4790.178 | CA23: =BZ23-CC23 -> 643.98144 | CB23: =(CA23/BY23)*12 -> 0.010872302 | CC23: =BY23*($BX$3/12) -> 4146.1965 | CD23: =(CC23/BY23)*12 -> 0.07 | CE23: =CE22+CA23 -> 9867.4344 | CF23: =CF22+CC23 -> 66775.413 | CG23: =BY23-CA23 -> 710132.57 | CH23: =CE23+CF23 -> 76642.847
... A40: =A39+1 -> 30 | B40: =VLOOKUP(A40*12,$J$7:$U$367,10) -> 1227283 | C40: =VLOOKUP(A40*12,$W$7:$AH$367,10) -> 1181917.8 | D40: =VLOOKUP(A40*12,$AJ$7:$AU$367,10) -> 1136940.5 | E40: =VLOOKUP(A40*12,$AW$7:$BH$367,10) -> 1092364 | F40: =VLOOKUP(A40*12,$BJ$7:$BU$367,10) -> 1048200.9 | G40: =VLOOKUP(A40*12,$BW$7:$CH$367,10) -> 1004464.1 | J40: 33 | K40: 45839 | L40: =T39 -> 703629.36 | M40: =$L$8/((($N$4)-1)/($N$3*$N$4)) -> 5409.1195 | N40: =M40-P40 -> 571.66767 | O40: =(N40/L40)*12 -> 0.0097494681 | P40: =L40*($K$3/12) -> 4837.4519 | Q40: =(P40/L40)*12 -> 0.0825 | R40: =R39+N40 -> 16942.304 | S40: =S39+P40 -> 161558.64 | T40: =L40-N40 -> 703057.7 | U40: =R40+S40 -> 178500.95 | W40: 33 | X40: 45839 | Y40: =AG39 -> 702831.33 | Z40: =Z39 -> 5283.1049 | AA40: =Z40-AC40 -> 597.56272 | AB40: =(AA40/Y40)*12 -> 0.010202665 | AC40: =Y40*($X$3/12) -> 4685.5422 | AD40: =(AC40/Y40)*12 -> 0.08 | AE40: =AE39+AA40 -> 17766.231 | AF40: =AF39+AC40 -> 156576.23 | AG40: =Y40-AA40 -> 702233.77 | AH40: =AE40+AF40 -> 174342.46 | AJ40: 33 | AK40: 45839 | AL40: =AT39 -> 702000.55 | AM40: =AM39 -> 5158.1682 | AN40: =AM40-AP40 -> 624.41462 | AO40: =(AN40/AL40)*12 -> 0.010673746 | AP40: =AL40*($AK$3/12) -> 4533.7536 | AQ40: =(AP40/AL40)*12 -> 0.0775 | AR40: =AR39+AN40 -> 18623.865 | AS40: =AS39+AP40 -> 151595.68 | AT40: =AL40-AN40 -> 701376.14 | AU40: =AR40+AS40 -> 170219.55 | AW40: 33 | AX40: 45839 | AY40: =BG39 -> 701136.12 | AZ40: =AZ39 -> 5034.3445 | BA40: =AZ40-BC40 -> 652.24371 | BB40: =(BA40/AY40)*12 -> 0.011163203 | BC40: =AY40*($AX$3/12) -> 4382.1008 | BD40: =(BC40/AY40)*12 -> 0.075 | BE40: =BE39+BA40 -> 19516.124 | BF40: =BF39+BC40 -> 146617.24 | BG40: =AY40-BA40 -> 700483.88 | BH40: =BE40+BF40 -> 166133.37 | BJ40: 33 | BK40: 45839 | BL40: =BT39 -> 700237.15 | BM40: =BM39 -> 4911.6692 | BN40: =BM40-BP40 -> 681.06976 | BO40: =(BN40/BL40)*12 -> 0.011671527 | BP40: =BL40*($BK$3/12) -> 4230.5995 | BQ40: =(BP40/BL40)*12 -> 0.0725 | BR40: =BR39+BN40 -> 20443.919 | BS40: =BS39+BP40 -> 141641.17 | BT40: =BL40-BN40 -> 699556.08 | BU40: =BR40+BS40 -> 162085.08 | BW40: 33 | BX40: 45839 | BY40: =CG39 -> 699302.76 | BZ40: =BZ39 -> 4790.178 | CA40: =BZ40-CC40 -> 710.91186 | CB40: =(CA40/BY40)*12 -> 0.012199212 | CC40: =BY40*($BX$3/12) -> 4079.2661 | CD40: =(CC40/BY40)*12 -> 0.07 | CE40: =CE39+CA40 -> 21408.151 | CF40: =CF39+CC40 -> 136667.72 | CG40: =BY40-CA40 -> 698591.85 | CH40: =CE40+CF40 -> 158075.87
J41: 34 | K41: 45870 | L41: =T40 -> 703057.7 | M41: =$L$8/((($N$4)-1)/($N$3*$N$4)) -> 5409.1195 | N41: =M41-P41 -> 575.59789 | O41: =(N41/L41)*12 -> 0.0098244777 | P41: =L41*($K$3/12) -> 4833.5217 | Q41: =(P41/L41)*12 -> 0.0825 | R41: =R40+N41 -> 17517.902 | S41: =S40+P41 -> 166392.16 | T41: =L41-N41 -> 702482.1 | U41: =R41+S41 -> 183910.06 | W41: 34 | X41: 45870 | Y41: =AG40 -> 702233.77 | Z41: =Z40 -> 5283.1049 | AA41: =Z41-AC41 -> 601.54647 | AB41: =(AA41/Y41)*12 -> 0.010279423 | AC41: =Y41*($X$3/12) -> 4681.5585 | AD41: =(AC41/Y41)*12 -> 0.08 | AE41: =AE40+AA41 -> 18367.777 | AF41: =AF40+AC41 -> 161257.79 | AG41: =Y41-AA41 -> 701632.22 | AH41: =AE41+AF41 -> 179625.57 | AJ41: 34 | AK41: 45870 | AL41: =AT40 -> 701376.14 | AM41: =AM40 -> 5158.1682 | AN41: =AM41-AP41 -> 628.44729 | AO41: =(AN41/AL41)*12 -> 0.010752244 | AP41: =AL41*($AK$3/12) -> 4529.7209 | AQ41: =(AP41/AL41)*12 -> 0.0775 | AR41: =AR40+AN41 -> 19252.312 | AS41: =AS40+AP41 -> 156125.41 | AT41: =AL41-AN41 -> 700747.69 | AU41: =AR41+AS41 -> 175377.72 | AW41: 34 | AX41: 45870 | AY41: =BG40 -> 700483.88 | AZ41: =AZ40 -> 5034.3445 | BA41: =AZ41-BC41 -> 656.32023 | BB41: =(BA41/AY41)*12 -> 0.011243432 | BC41: =AY41*($AX$3/12) -> 4378.0242 | BD41: =(BC41/AY41)*12 -> 0.075 | BE41: =BE40+BA41 -> 20172.444 | BF41: =BF40+BC41 -> 150995.27 | BG41: =AY41-BA41 -> 699827.56 | BH41: =BE41+BF41 -> 171167.71 | BJ41: 34 | BK41: 45870 | BL41: =BT40 -> 699556.08 | BM41: =BM40 -> 4911.6692 | BN41: =BM41-BP41 -> 685.18456 | BO41: =(BN41/BL41)*12 -> 0.011753475 | BP41: =BL41*($BK$3/12) -> 4226.4847 | BQ41: =(BP41/BL41)*12 -> 0.0725 | BR41: =BR40+BN41 -> 21129.103 | BS41: =BS40+BP41 -> 145867.65 | BT41: =BL41-BN41 -> 698870.9 | BU41: =BR41+BS41 -> 166996.75 | BW41: 34 | BX41: 45870 | BY41: =CG40 -> 698591.85 | BZ41: =BZ40 -> 4790.178 | CA41: =BZ41-CC41 -> 715.05885 | CB41: =(CA41/BY41)*12 -> 0.01228286 | CC41: =BY41*($BX$3/12) -> 4075.1191 | CD41: =(CC41/BY41)*12 -> 0.07 | CE41: =CE40+CA41 -> 22123.21 | CF41: =CF40+CC41 -> 140742.84 | CG41: =BY41-CA41 -> 697876.79 | CH41: =CE41+CF41 -> 162866.05
J42: 35 | K42: 45901 | L42: =T41 -> 702482.1 | M42: =$L$8/((($N$4)-1)/($N$3*$N$4)) -> 5409.1195 | N42: =M42-P42 -> 579.55512 | O42: =(N42/L42)*12 -> 0.0099001263 | P42: =L42*($K$3/12) -> 4829.5644 | Q42: =(P42/L42)*12 -> 0.0825 | R42: =R41+N42 -> 18097.457 | S42: =S41+P42 -> 171221.73 | T42: =L42-N42 -> 701902.54 | U42: =R42+S42 -> 189319.18 | W42: 35 | X42: 45901 | Y42: =AG41 -> 701632.22 | Z42: =Z41 -> 5283.1049 | AA42: =Z42-AC42 -> 605.55678 | AB42: =(AA42/Y42)*12 -> 0.010356824 | AC42: =Y42*($X$3/12) -> 4677.5482 | AD42: =(AC42/Y42)*12 -> 0.08 | AE42: =AE41+AA42 -> 18973.334 | AF42: =AF41+AC42 -> 165935.34 | AG42: =Y42-AA42 -> 701026.67 | AH42: =AE42+AF42 -> 184908.67 | AJ42: 35 | AK42: 45901 | AL42: =AT41 -> 700747.69 | AM42: =AM41 -> 5158.1682 | AN42: =AM42-AP42 -> 632.50602 | AO42: =(AN42/AL42)*12 -> 0.010831391 | AP42: =AL42*($AK$3/12) -> 4525.6622 | AQ42: =(AP42/AL42)*12 -> 0.0775 | AR42: =AR41+AN42 -> 19884.818 | AS42: =AS41+AP42 -> 160651.07 | AT42: =AL42-AN42 -> 700115.18 | AU42: =AR42+AS42 -> 180535.89 | AW42: 35 | AX42: 45901 | AY42: =BG41 -> 699827.56 | AZ42: =AZ41 -> 5034.3445 | BA42: =AZ42-BC42 -> 660.42224 | BB42: =(BA42/AY42)*12 -> 0.011324314 | BC42: =AY42*($AX$3/12) -> 4373.9222 | BD42: =(BC42/AY42)*12 -> 0.075 | BE42: =BE41+BA42 -> 20832.866 | BF42: =BF41+BC42 -> 155369.19 | BG42: =AY42-BA42 -> 699167.13 | BH42: =BE42+BF42 -> 176202.06 | BJ42: 35 | BK42: 45901 | BL42: =BT41 -> 698870.9 | BM42: =BM41 -> 4911.6692 | BN42: =BM42-BP42 -> 689.32421 | BO42: =(BN42/BL42)*12 -> 0.011836078 | BP42: =BL42*($BK$3/12) -> 4222.345 | BQ42: =(BP42/BL42)*12 -> 0.0725 | BR42: =BR41+BN42 -> 21818.427 | BS42: =BS41+BP42 -> 150090 | BT42: =BL42-BN42 -> 698181.57 | BU42: =BR42+BS42 -> 171908.42 | BW42: 35 | BX42: 45901 | BY42: =CG41 -> 697876.79 | BZ42: =BZ41 -> 4790.178 | CA42: =BZ42-CC42 -> 719.23002 | CB42: =(CA42/BY42)*12 -> 0.012367169 | CC42: =BY42*($BX$3/12) -> 4070.9479 | CD42: =(CC42/BY42)*12 -> 0.07 | CE42: =CE41+CA42 -> 22842.44 | CF42: =CF41+CC42 -> 144813.79 | CG42: =BY42-CA42 -> 697157.56 | CH42: =CE42+CF42 -> 167656.23
J43: 36 | K43: 45931 | L43: =T42 -> 701902.54 | M43: =$L$8/((($N$4)-1)/($N$3*$N$4)) -> 5409.1195 | N43: =M43-P43 -> 583.53956 | O43: =(N43/L43)*12 -> 0.0099764203 | P43: =L43*($K$3/12) -> 4825.58 | Q43: =(P43/L43)*12 -> 0.0825 | R43: =R42+N43 -> 18680.996 | S43: =S42+P43 -> 176047.31 | T43: =L43-N43 -> 701319 | U43: =R43+S43 -> 194728.3 | W43: 36 | X43: 45931 | Y43: =AG42 -> 701026.67 | Z43: =Z42 -> 5283.1049 | AA43: =Z43-AC43 -> 609.59383 | AB43: =(AA43/Y43)*12 -> 0.010434875 | AC43: =Y43*($X$3/12) -> 4673.5111 | AD43: =(AC43/Y43)*12 -> 0.08 | AE43: =AE42+AA43 -> 19582.928 | AF43: =AF42+AC43 -> 170608.85 | AG43: =Y43-AA43 -> 700417.07 | AH43: =AE43+AF43 -> 190191.78 | AJ43: 36 | AK43: 45931 | AL43: =AT42 -> 700115.18 | AM43: =AM42 -> 5158.1682 | AN43: =AM43-AP43 -> 636.59095 | AO43: =(AN43/AL43)*12 -> 0.010911192 | AP43: =AL43*($AK$3/12) -> 4521.5772 | AQ43: =(AP43/AL43)*12 -> 0.0775 | AR43: =AR42+AN43 -> 20521.409 | AS43: =AS42+AP43 -> 165172.65 | AT43: =AL43-AN43 -> 699478.59 | AU43: =AR43+AS43 -> 185694.05 | AW43: 36 | AX43: 45931 | AY43: =BG42 -> 699167.13 | AZ43: =AZ42 -> 5034.3445 | BA43: =AZ43-BC43 -> 664.54987 | BB43: =(BA43/AY43)*12 -> 0.011405854 | BC43: =AY43*($AX$3/12) -> 4369.7946 | BD43: =(BC43/AY43)*12 -> 0.075 | BE43: =BE42+BA43 -> 21497.416 | BF43: =BF42+BC43 -> 159738.98 | BG43: =AY43-BA43 -> 698502.58 | BH43: =BE43+BF43 -> 181236.4 | BJ43: 36 | BK43: 45931 | BL43: =BT42 -> 698181.57 | BM43: =BM42 -> 4911.6692 | BN43: =BM43-BP43 -> 693.48888 | BO43: =(BN43/BL43)*12 -> 0.011919344 | BP43: =BL43*($BK$3/12) -> 4218.1803 | BQ43: =(BP43/BL43)*12 -> 0.0725 | BR43: =BR42+BN43 -> 22511.916 | BS43: =BS42+BP43 -> 154308.18 | BT43: =BL43-BN43 -> 697488.08 | BU43: =BR43+BS43 -> 176820.09 | BW43: 36 | BX43: 45931 | BY43: =CG42 -> 697157.56 | BZ43: =BZ42 -> 4790.178 | CA43: =BZ43-CC43 -> 723.42553 | CB43: =(CA43/BY43)*12 -> 0.012452144 | CC43: =BY43*($BX$3/12) -> 4066.7524 | CD43: =(CC43/BY43)*12 -> 0.07 | CE43: =CE42+CA43 -> 23565.866 | CF43: =CF42+CC43 -> 148880.54 | CG43: =BY43-CA43 -> 696434.13 | CH43: =CE43+CF43 -> 172446.41
J44: 37 | K44: 45962 | L44: =T43 -> 701319 | M44: =$L$8/((($N$4)-1)/($N$3*$N$4)) -> 5409.1195 | N44: =M44-P44 -> 587.5514 | O44: =(N44/L44)*12 -> 0.010053366 | P44: =L44*($K$3/12) -> 4821.5682 | Q44: =(P44/L44)*12 -> 0.0825 | R44: =R43+N44 -> 19268.548 | S44: =S43+P44 -> 180868.88 | T44: =L44-N44 -> 700731.45 | U44: =R44+S44 -> 200137.42 | W44: 37 | X44: 45962 | Y44: =AG43 -> 700417.07 | Z44: =Z43 -> 5283.1049 | AA44: =Z44-AC44 -> 613.65778 | AB44: =(AA44/Y44)*12 -> 0.010513584 | AC44: =Y44*($X$3/12) -> 4669.4471 | AD44: =(AC44/Y44)*12 -> 0.08 | AE44: =AE43+AA44 -> 20196.586 | AF44: =AF43+AC44 -> 175278.3 | AG44: =Y44-AA44 -> 699803.41 | AH44: =AE44+AF44 -> 195474.88 | AJ44: 37 | AK44: 45962 | AL44: =AT43 -> 699478.59 | AM44: =AM43 -> 5158.1682 | AN44: =AM44-AP44 -> 640.70227 | AO44: =(AN44/AL44)*12 -> 0.010991655 | AP44: =AL44*($AK$3/12) -> 4517.4659 | AQ44: =(AP44/AL44)*12 -> 0.0775 | AR44: =AR43+AN44 -> 21162.111 | AS44: =AS43+AP44 -> 169690.11 | AT44: =AL44-AN44 -> 698837.89 | AU44: =AR44+AS44 -> 190852.22 | AW44: 37 | AX44: 45962 | AY44: =BG43 -> 698502.58 | AZ44: =AZ43 -> 5034.3445 | BA44: =AZ44-BC44 -> 668.70331 | BB44: =(BA44/AY44)*12 -> 0.01148806 | BC44: =AY44*($AX$3/12) -> 4365.6412 | BD44: =(BC44/AY44)*12 -> 0.075 | BE44: =BE43+BA44 -> 22166.119 | BF44: =BF43+BC44 -> 164104.63 | BG44: =AY44-BA44 -> 697833.88 | BH44: =BE44+BF44 -> 186270.75 | BJ44: 37 | BK44: 45962 | BL44: =BT43 -> 697488.08 | BM44: =BM43 -> 4911.6692 | BN44: =BM44-BP44 -> 697.67871 | BO44: =(BN44/BL44)*12 -> 0.01200328 | BP44: =BL44*($BK$3/12) -> 4213.9905 | BQ44: =(BP44/BL44)*12 -> 0.0725 | BR44: =BR43+BN44 -> 23209.595 | BS44: =BS43+BP44 -> 158522.17 | BT44: =BL44-BN44 -> 696790.4 | BU44: =BR44+BS44 -> 181731.76 | BW44: 37 | BX44: 45962 | BY44: =CG43 -> 696434.13 | BZ44: =BZ43 -> 4790.178 | CA44: =BZ44-CC44 -> 727.64551 | CB44: =(CA44/BY44)*12 -> 0.012537792 | CC44: =BY44*($BX$3/12) -> 4062.5325 | CD44: =(CC44/BY44)*12 -> 0.07 | CE44: =CE43+CA44 -> 24293.511 | CF44: =CF43+CC44 -> 152943.07 | CG44: =BY44-CA44 -> 695706.49 | CH44: =CE44+CF44 -> 177236.58
J45: 38 | K45: 45992 | L45: =T44 -> 700731.45 | M45: =$L$8/((($N$4)-1)/($N$3*$N$4)) -> 5409.1195 | N45: =M45-P45 -> 591.59081 | O45: =(N45/L45)*12 -> 0.010130971 | P45: =L45*($K$3/12) -> 4817.5287 | Q45: =(P45/L45)*12 -> 0.0825 | R45: =R44+N45 -> 19860.139 | S45: =S44+P45 -> 185686.4 | T45: =L45-N45 -> 700139.86 | U45: =R45+S45 -> 205546.54 | W45: 38 | X45: 45992 | Y45: =AG44 -> 699803.41 | Z45: =Z44 -> 5283.1049 | AA45: =Z45-AC45 -> 617.74884 | AB45: =(AA45/Y45)*12 -> 0.010592955 | AC45: =Y45*($X$3/12) -> 4665.3561 | AD45: =(AC45/Y45)*12 -> 0.08 | AE45: =AE44+AA45 -> 20814.334 | AF45: =AF44+AC45 -> 179943.65 | AG45: =Y45-AA45 -> 699185.67 | AH45: =AE45+AF45 -> 200757.99 | AJ45: 38 | AK45: 45992 | AL45: =AT44 -> 698837.89 | AM45: =AM44 -> 5158.1682 | AN45: =AM45-AP45 -> 644.84014 | AO45: =(AN45/AL45)*12 -> 0.011072785 | AP45: =AL45*($AK$3/12) -> 4513.328 | AQ45: =(AP45/AL45)*12 -> 0.0775 | AR45: =AR44+AN45 -> 21806.951 | AS45: =AS44+AP45 -> 174203.44 | AT45: =AL45-AN45 -> 698193.05 | AU45: =AR45+AS45 -> 196010.39 | AW45: 38 | AX45: 45992 | AY45: =BG44 -> 697833.88 | AZ45: =AZ44 -> 5034.3445 | BA45: =AZ45-BC45 -> 672.88271 | BB45: =(BA45/AY45)*12 -> 0.011570938 | BC45: =AY45*($AX$3/12) -> 4361.4618 | BD45: =(BC45/AY45)*12 -> 0.075 | BE45: =BE44+BA45 -> 22839.002 | BF45: =BF44+BC45 -> 168466.09 | BG45: =AY45-BA45 -> 697161 | BH45: =BE45+BF45 -> 191305.09 | BJ45: 38 | BK45: 45992 | BL45: =BT44 -> 696790.4 | BM45: =BM44 -> 4911.6692 | BN45: =BM45-BP45 -> 701.89385 | BO45: =(BN45/BL45)*12 -> 0.012087891 | BP45: =BL45*($BK$3/12) -> 4209.7754 | BQ45: =(BP45/BL45)*12 -> 0.0725 | BR45: =BR44+BN45 -> 23911.489 | BS45: =BS44+BP45 -> 162731.94 | BT45: =BL45-BN45 -> 696088.51 | BU45: =BR45+BS45 -> 186643.43 | BW45: 38 | BX45: 45992 | BY45: =CG44 -> 695706.49 | BZ45: =BZ44 -> 4790.178 | CA45: =BZ45-CC45 -> 731.89011 | CB45: =(CA45/BY45)*12 -> 0.012624119 | CC45: =BY45*($BX$3/12) -> 4058.2879 | CD45: =(CC45/BY45)*12 -> 0.07 | CE45: =CE44+CA45 -> 25025.401 | CF45: =CF44+CC45 -> 157001.36 | CG45: =BY45-CA45 -> 694974.6 | CH45: =CE45+CF45 -> 182026.76
J46: 39 | K46: 46023 | L46: =T45 -> 700139.86 | M46: =$L$8/((($N$4)-1)/($N$3*$N$4)) -> 5409.1195 | N46: =M46-P46 -> 595.658 | O46: =(N46/L46)*12 -> 0.01020924 | P46: =L46*($K$3/12) -> 4813.4615 | Q46: =(P46/L46)*12 -> 0.0825 | R46: =R45+N46 -> 20455.797 | S46: =S45+P46 -> 190499.87 | T46: =L46-N46 -> 699544.2 | U46: =R46+S46 -> 210955.66 | W46: 39 | X46: 46023 | Y46: =AG45 -> 699185.67 | Z46: =Z45 -> 5283.1049 | AA46: =Z46-AC46 -> 621.86716 | AB46: =(AA46/Y46)*12 -> 0.010672996 | AC46: =Y46*($X$3/12) -> 4661.2378 | AD46: =(AC46/Y46)*12 -> 0.08 | AE46: =AE45+AA46 -> 21436.202 | AF46: =AF45+AC46 -> 184604.89 | AG46: =Y46-AA46 -> 698563.8 | AH46: =AE46+AF46 -> 206041.09 | AJ46: 39 | AK46: 46023 | AL46: =AT45 -> 698193.05 | AM46: =AM45 -> 5158.1682 | AN46: =AM46-AP46 -> 649.00473 | AO46: =(AN46/AL46)*12 -> 0.011154589 | AP46: =AL46*($AK$3/12) -> 4509.1634 | AQ46: =(AP46/AL46)*12 -> 0.0775 | AR46: =AR45+AN46 -> 22455.956 | AS46: =AS45+AP46 -> 178712.6 | AT46: =AL46-AN46 -> 697544.04 | AU46: =AR46+AS46 -> 201168.56 | AW46: 39 | AX46: 46023 | AY46: =BG45 -> 697161 | AZ46: =AZ45 -> 5034.3445 | BA46: =AZ46-BC46 -> 677.08822 | BB46: =(BA46/AY46)*12 -> 0.011654494 | BC46: =AY46*($AX$3/12) -> 4357.2562 | BD46: =(BC46/AY46)*12 -> 0.075 | BE46: =BE45+BA46 -> 23516.09 | BF46: =BF45+BC46 -> 172823.34 | BG46: =AY46-BA46 -> 696483.91 | BH46: =BE46+BF46 -> 196339.43 | BJ46: 39 | BK46: 46023 | BL46: =BT45 -> 696088.51 | BM46: =BM45 -> 4911.6692 | BN46: =BM46-BP46 -> 706.13446 | BO46: =(BN46/BL46)*12 -> 0.012173184 | BP46: =BL46*($BK$3/12) -> 4205.5348 | BQ46: =(BP46/BL46)*12 -> 0.0725 | BR46: =BR45+BN46 -> 24617.623 | BS46: =BS45+BP46 -> 166937.48 | BT46: =BL46-BN46 -> 695382.38 | BU46: =BR46+BS46 -> 191555.1 | BW46: 39 | BX46: 46023 | BY46: =CG45 -> 694974.6 | BZ46: =BZ45 -> 4790.178 | CA46: =BZ46-CC46 -> 736.15947 | CB46: =(CA46/BY46)*12 -> 0.012711132 | CC46: =BY46*($BX$3/12) -> 4054.0185 | CD46: =(CC46/BY46)*12 -> 0.07 | CE46: =CE45+CA46 -> 25761.561 | CF46: =CF45+CC46 -> 161055.38 | CG46: =BY46-CA46 -> 694238.44 | CH46: =CE46+CF46 -> 186816.94
J47: 40 | K47: 46054 | L47: =T46 -> 699544.2 | M47: =$L$8/((($N$4)-1)/($N$3*$N$4)) -> 5409.1195 | N47: =M47-P47 -> 599.75315 | O47: =(N47/L47)*12 -> 0.010288182 | P47: =L47*($K$3/12) -> 4809.3664 | Q47: =(P47/L47)*12 -> 0.0825 | R47: =R46+N47 -> 21055.55 | S47: =S46+P47 -> 195309.23 | T47: =L47-N47 -> 698944.45 | U47: =R47+S47 -> 216364.78 | W47: 40 | X47: 46054 | Y47: =AG46 -> 698563.8 | Z47: =Z46 -> 5283.1049 | AA47: =Z47-AC47 -> 626.01294 | AB47: =(AA47/Y47)*12 -> 0.010753714 | AC47: =Y47*($X$3/12) -> 4657.092 | AD47: =(AC47/Y47)*12 -> 0.08 | AE47: =AE46+AA47 -> 22062.215 | AF47: =AF46+AC47 -> 189261.98 | AG47: =Y47-AA47 -> 697937.79 | AH47: =AE47+AF47 -> 211324.2 | AJ47: 40 | AK47: 46054 | AL47: =AT46 -> 697544.04 | AM47: =AM46 -> 5158.1682 | AN47: =AM47-AP47 -> 653.19622 | AO47: =(AN47/AL47)*12 -> 0.011237075 | AP47: =AL47*($AK$3/12) -> 4504.972 | AQ47: =(AP47/AL47)*12 -> 0.0775 | AR47: =AR46+AN47 -> 23109.152 | AS47: =AS46+AP47 -> 183217.57 | AT47: =AL47-AN47 -> 696890.85 | AU47: =AR47+AS47 -> 206326.73 | AW47: 40 | AX47: 46054 | AY47: =BG46 -> 696483.91 | AZ47: =AZ46 -> 5034.3445 | BA47: =AZ47-BC47 -> 681.32003 | BB47: =(BA47/AY47)*12 -> 0.011738735 | BC47: =AY47*($AX$3/12) -> 4353.0244 | BD47: =(BC47/AY47)*12 -> 0.075 | BE47: =BE46+BA47 -> 24197.41 | BF47: =BF46+BC47 -> 177176.37 | BG47: =AY47-BA47 -> 695802.59 | BH47: =BE47+BF47 -> 201373.78 | BJ47: 40 | BK47: 46054 | BL47: =BT46 -> 695382.38 | BM47: =BM46 -> 4911.6692 | BN47: =BM47-BP47 -> 710.40069 | BO47: =(BN47/BL47)*12 -> 0.012259166 | BP47: =BL47*($BK$3/12) -> 4201.2685 | BQ47: =(BP47/BL47)*12 -> 0.0725 | BR47: =BR46+BN47 -> 25328.024 | BS47: =BS46+BP47 -> 171138.74 | BT47: =BL47-BN47 -> 694671.98 | BU47: =BR47+BS47 -> 196466.77 | BW47: 40 | BX47: 46054 | BY47: =CG46 -> 694238.44 | BZ47: =BZ46 -> 4790.178 | CA47: =BZ47-CC47 -> 740.45374 | CB47: =(CA47/BY47)*12 -> 0.012798837 | CC47: =BY47*($BX$3/12) -> 4049.7242 | CD47: =(CC47/BY47)*12 -> 0.07 | CE47: =CE46+CA47 -> 26502.014 | CF47: =CF46+CC47 -> 165105.1 | CG47: =BY47-CA47 -> 693497.99 | CH47: =CE47+CF47 -> 191607.12
J48: 41 | K48: 46082 | L48: =T47 -> 698944.45 | M48: =$L$8/((($N$4)-1)/($N$3*$N$4)) -> 5409.1195 | N48: =M48-P48 -> 603.87645 | O48: =(N48/L48)*12 -> 0.010367802 | P48: =L48*($K$3/12) -> 4805.2431 | Q48: =(P48/L48)*12 -> 0.0825 | R48: =R47+N48 -> 21659.426 | S48: =S47+P48 -> 200114.48 | T48: =L48-N48 -> 698340.57 | U48: =R48+S48 -> 221773.9 | W48: 41 | X48: 46082 | Y48: =AG47 -> 697937.79 | Z48: =Z47 -> 5283.1049 | AA48: =Z48-AC48 -> 630.18636 | AB48: =(AA48/Y48)*12 -> 0.010835115 | AC48: =Y48*($X$3/12) -> 4652.9186 | AD48: =(AC48/Y48)*12 -> 0.08 | AE48: =AE47+AA48 -> 22692.401 | AF48: =AF47+AC48 -> 193914.9 | AG48: =Y48-AA48 -> 697307.6 | AH48: =AE48+AF48 -> 216607.3 | AJ48: 41 | AK48: 46082 | AL48: =AT47 -> 696890.85 | AM48: =AM47 -> 5158.1682 | AN48: =AM48-AP48 -> 657.41478 | AO48: =(AN48/AL48)*12 -> 0.011320248 | AP48: =AL48*($AK$3/12) -> 4500.7534 | AQ48: =(AP48/AL48)*12 -> 0.0775 | AR48: =AR47+AN48 -> 23766.567 | AS48: =AS47+AP48 -> 187718.33 | AT48: =AL48-AN48 -> 696233.43 | AU48: =AR48+AS48 -> 211484.89 | AW48: 41 | AX48: 46082 | AY48: =BG47 -> 695802.59 | AZ48: =AZ47 -> 5034.3445 | BA48: =AZ48-BC48 -> 685.57828 | BB48: =(BA48/AY48)*12 -> 0.011823669 | BC48: =AY48*($AX$3/12) -> 4348.7662 | BD48: =(BC48/AY48)*12 -> 0.075 | BE48: =BE47+BA48 -> 24882.989 | BF48: =BF47+BC48 -> 181525.13 | BG48: =AY48-BA48 -> 695117.01 | BH48: =BE48+BF48 -> 206408.12 | BJ48: 41 | BK48: 46082 | BL48: =BT47 -> 694671.98 | BM48: =BM47 -> 4911.6692 | BN48: =BM48-BP48 -> 714.69269 | BO48: =(BN48/BL48)*12 -> 0.012345845 | BP48: =BL48*($BK$3/12) -> 4196.9765 | BQ48: =(BP48/BL48)*12 -> 0.0725 | BR48: =BR47+BN48 -> 26042.717 | BS48: =BS47+BP48 -> 175335.72 | BT48: =BL48-BN48 -> 693957.28 | BU48: =BR48+BS48 -> 201378.44 | BW48: 41 | BX48: 46082 | BY48: =CG47 -> 693497.99 | BZ48: =BZ47 -> 4790.178 | CA48: =BZ48-CC48 -> 744.77305 | CB48: =(CA48/BY48)*12 -> 0.012887242 | CC48: =BY48*($BX$3/12) -> 4045.4049 | CD48: =(CC48/BY48)*12 -> 0.07 | CE48: =CE47+CA48 -> 27246.787 | CF48: =CF47+CC48 -> 169150.51 | CG48: =BY48-CA48 -> 692753.21 | CH48: =CE48+CF48 -> 196397.3
J49: 42 | K49: 46113 | L49: =T48 -> 698340.57 | M49: =$L$8/((($N$4)-1)/($N$3*$N$4)) -> 5409.1195 | N49: =M49-P49 -> 608.0281 | O49: =(N49/L49)*12 -> 0.010448107 | P49: =L49*($K$3/12) -> 4801.0914 | Q49: =(P49/L49)*12 -> 0.0825 | R49: =R48+N49 -> 22267.454 | S49: =S48+P49 -> 204915.57 | T49: =L49-N49 -> 697732.55 | U49: =R49+S49 -> 227183.02 | W49: 42 | X49: 46113 | Y49: =AG48 -> 697307.6 | Z49: =Z48 -> 5283.1049 | AA49: =Z49-AC49 -> 634.3876 | AB49: =(AA49/Y49)*12 -> 0.010917207 | AC49: =Y49*($X$3/12) -> 4648.7173 | AD49: =(AC49/Y49)*12 -> 0.08 | AE49: =AE48+AA49 -> 23326.789 | AF49: =AF48+AC49 -> 198563.62 | AG49: =Y49-AA49 -> 696673.21 | AH49: =AE49+AF49 -> 221890.41 | AJ49: 42 | AK49: 46113 | AL49: =AT48 -> 696233.43 | AM49: =AM48 -> 5158.1682 | AN49: =AM49-AP49 -> 661.66058 | AO49: =(AN49/AL49)*12 -> 0.011404116 | AP49: =AL49*($AK$3/12) -> 4496.5076 | AQ49: =(AP49/AL49)*12 -> 0.0775 | AR49: =AR48+AN49 -> 24428.228 | AS49: =AS48+AP49 -> 192214.84 | AT49: =AL49-AN49 -> 695571.77 | AU49: =AR49+AS49 -> 216643.06 | AW49: 42 | AX49: 46113 | AY49: =BG48 -> 695117.01 | AZ49: =AZ48 -> 5034.3445 | BA49: =AZ49-BC49 -> 689.86314 | BB49: =(BA49/AY49)*12 -> 0.011909301 | BC49: =AY49*($AX$3/12) -> 4344.4813 | BD49: =(BC49/AY49)*12 -> 0.075 | BE49: =BE48+BA49 -> 25572.852 | BF49: =BF48+BC49 -> 185869.62 | BG49: =AY49-BA49 -> 694427.15 | BH49: =BE49+BF49 -> 211442.47 | BJ49: 42 | BK49: 46113 | BL49: =BT48 -> 693957.28 | BM49: =BM48 -> 4911.6692 | BN49: =BM49-BP49 -> 719.01063 | BO49: =(BN49/BL49)*12 -> 0.012433226 | BP49: =BL49*($BK$3/12) -> 4192.6586 | BQ49: =(BP49/BL49)*12 -> 0.0725 | BR49: =BR48+BN49 -> 26761.727 | BS49: =BS48+BP49 -> 179528.38 | BT49: =BL49-BN49 -> 693238.27 | BU49: =BR49+BS49 -> 206290.11 | BW49: 42 | BX49: 46113 | BY49: =CG48 -> 692753.21 | BZ49: =BZ48 -> 4790.178 | CA49: =BZ49-CC49 -> 749.11756 | CB49: =(CA49/BY49)*12 -> 0.012976354 | CC49: =BY49*($BX$3/12) -> 4041.0604 | CD49: =(CC49/BY49)*12 -> 0.07 | CE49: =CE48+CA49 -> 27995.905 | CF49: =CF48+CC49 -> 173191.57 | CG49: =BY49-CA49 -> 692004.09 | CH49: =CE49+CF49 -> 201187.47
J50: 43 | K50: 46143 | L50: =T49 -> 697732.55 | M50: =$L$8/((($N$4)-1)/($N$3*$N$4)) -> 5409.1195 | N50: =M50-P50 -> 612.2083 | O50: =(N50/L50)*12 -> 0.010529105 | P50: =L50*($K$3/12) -> 4796.9113 | Q50: =(P50/L50)*12 -> 0.0825 | R50: =R49+N50 -> 22879.663 | S50: =S49+P50 -> 209712.48 | T50: =L50-N50 -> 697120.34 | U50: =R50+S50 -> 232592.14 | W50: 43 | X50: 46143 | Y50: =AG49 -> 696673.21 | Z50: =Z49 -> 5283.1049 | AA50: =Z50-AC50 -> 638.61686 | AB50: =(AA50/Y50)*12 -> 0.010999996 | AC50: =Y50*($X$3/12) -> 4644.4881 | AD50: =(AC50/Y50)*12 -> 0.08 | AE50: =AE49+AA50 -> 23965.405 | AF50: =AF49+AC50 -> 203208.11 | AG50: =Y50-AA50 -> 696034.59 | AH50: =AE50+AF50 -> 227173.51 | AJ50: 43 | AK50: 46143 | AL50: =AT49 -> 695571.77 | AM50: =AM49 -> 5158.1682 | AN50: =AM50-AP50 -> 665.93381 | AO50: =(AN50/AL50)*12 -> 0.011488686 | AP50: =AL50*($AK$3/12) -> 4492.2344 | AQ50: =(AP50/AL50)*12 -> 0.0775 | AR50: =AR49+AN50 -> 25094.161 | AS50: =AS49+AP50 -> 196707.07 | AT50: =AL50-AN50 -> 694905.84 | AU50: =AR50+AS50 -> 221801.23 | AW50: 43 | AX50: 46143 | AY50: =BG49 -> 694427.15 | AZ50: =AZ49 -> 5034.3445 | BA50: =AZ50-BC50 -> 694.17478 | BB50: =(BA50/AY50)*12 -> 0.011995639 | BC50: =AY50*($AX$3/12) -> 4340.1697 | BD50: =(BC50/AY50)*12 -> 0.075 | BE50: =BE49+BA50 -> 26267.026 | BF50: =BF49+BC50 -> 190209.79 | BG50: =AY50-BA50 -> 693732.97 | BH50: =BE50+BF50 -> 216476.81 | BJ50: 43 | BK50: 46143 | BL50: =BT49 -> 693238.27 | BM50: =BM49 -> 4911.6692 | BN50: =BM50-BP50 -> 723.35465 | BO50: =(BN50/BL50)*12 -> 0.012521317 | BP50: =BL50*($BK$3/12) -> 4188.3146 | BQ50: =(BP50/BL50)*12 -> 0.0725 | BR50: =BR49+BN50 -> 27485.082 | BS50: =BS49+BP50 -> 183716.69 | BT50: =BL50-BN50 -> 692514.92 | BU50: =BR50+BS50 -> 211201.78 | BW50: 43 | BX50: 46143 | BY50: =CG49 -> 692004.09 | BZ50: =BZ49 -> 4790.178 | CA50: =BZ50-CC50 -> 753.48741 | CB50: =(CA50/BY50)*12 -> 0.013066178 | CC50: =BY50*($BX$3/12) -> 4036.6906 | CD50: =(CC50/BY50)*12 -> 0.07 | CE50: =CE49+CA50 -> 28749.392 | CF50: =CF49+CC50 -> 177228.26 | CG50: =BY50-CA50 -> 691250.61 | CH50: =CE50+CF50 -> 205977.65
J51: 44 | K51: 46174 | L51: =T50 -> 697120.34 | M51: =$L$8/((($N$4)-1)/($N$3*$N$4)) -> 5409.1195 | N51: =M51-P51 -> 616.41723 | O51: =(N51/L51)*12 -> 0.010610803 | P51: =L51*($K$3/12) -> 4792.7023 | Q51: =(P51/L51)*12 -> 0.0825 | R51: =R50+N51 -> 23496.08 | S51: =S50+P51 -> 214505.18 | T51: =L51-N51 -> 696503.92 | U51: =R51+S51 -> 238001.26 | W51: 44 | X51: 46174 | Y51: =AG50 -> 696034.59 | Z51: =Z50 -> 5283.1049 | AA51: =Z51-AC51 -> 642.8743 | AB51: =(AA51/Y51)*12 -> 0.011083489 | AC51: =Y51*($X$3/12) -> 4640.2306 | AD51: =(AC51/Y51)*12 -> 0.08 | AE51: =AE50+AA51 -> 24608.28 | AF51: =AF50+AC51 -> 207848.34 | AG51: =Y51-AA51 -> 695391.72 | AH51: =AE51+AF51 -> 232456.62 | AJ51: 44 | AK51: 46174 | AL51: =AT50 -> 694905.84 | AM51: =AM50 -> 5158.1682 | AN51: =AM51-AP51 -> 670.23463 | AO51: =(AN51/AL51)*12 -> 0.011573965 | AP51: =AL51*($AK$3/12) -> 4487.9335 | AQ51: =(AP51/AL51)*12 -> 0.0775 | AR51: =AR50+AN51 -> 25764.396 | AS51: =AS50+AP51 -> 201195 | AT51: =AL51-AN51 -> 694235.6 | AU51: =AR51+AS51 -> 226959.4 | AW51: 44 | AX51: 46174 | AY51: =BG50 -> 693732.97 | AZ51: =AZ50 -> 5034.3445 | BA51: =AZ51-BC51 -> 698.51338 | BB51: =(BA51/AY51)*12 -> 0.01208269 | BC51: =AY51*($AX$3/12) -> 4335.8311 | BD51: =(BC51/AY51)*12 -> 0.075 | BE51: =BE50+BA51 -> 26965.54 | BF51: =BF50+BC51 -> 194545.62 | BG51: =AY51-BA51 -> 693034.46 | BH51: =BE51+BF51 -> 221511.16 | BJ51: 44 | BK51: 46174 | BL51: =BT50 -> 692514.92 | BM51: =BM50 -> 4911.6692 | BN51: =BM51-BP51 -> 727.72492 | BO51: =(BN51/BL51)*12 -> 0.012610124 | BP51: =BL51*($BK$3/12) -> 4183.9443 | BQ51: =(BP51/BL51)*12 -> 0.0725 | BR51: =BR50+BN51 -> 28212.807 | BS51: =BS50+BP51 -> 187900.64 | BT51: =BL51-BN51 -> 691787.19 | BU51: =BR51+BS51 -> 216113.45 | BW51: 44 | BX51: 46174 | BY51: =CG50 -> 691250.61 | BZ51: =BZ50 -> 4790.178 | CA51: =BZ51-CC51 -> 757.88275 | CB51: =(CA51/BY51)*12 -> 0.013156723 | CC51: =BY51*($BX$3/12) -> 4032.2952 | CD51: =(CC51/BY51)*12 -> 0.07 | CE51: =CE50+CA51 -> 29507.275 | CF51: =CF50+CC51 -> 181260.56 | CG51: =BY51-CA51 -> 690492.72 | CH51: =CE51+CF51 -> 210767.83
J52: 45 | K52: 46204 | L52: =T51 -> 696503.92 | M52: =$L$8/((($N$4)-1)/($N$3*$N$4)) -> 5409.1195 | N52: =M52-P52 -> 620.6551 | O52: =(N52/L52)*12 -> 0.010693208 | P52: =L52*($K$3/12) -> 4788.4645 | Q52: =(P52/L52)*12 -> 0.0825 | R52: =R51+N52 -> 24116.735 | S52: =S51+P52 -> 219293.64 | T52: =L52-N52 -> 695883.27 | U52: =R52+S52 -> 243410.38 | W52: 45 | X52: 46204 | Y52: =AG51 -> 695391.72 | Z52: =Z51 -> 5283.1049 | AA52: =Z52-AC52 -> 647.16013 | AB52: =(AA52/Y52)*12 -> 0.011167693 | AC52: =Y52*($X$3/12) -> 4635.9448 | AD52: =(AC52/Y52)*12 -> 0.08 | AE52: =AE51+AA52 -> 25255.44 | AF52: =AF51+AC52 -> 212484.28 | AG52: =Y52-AA52 -> 694744.56 | AH52: =AE52+AF52 -> 237739.72 | AJ52: 45 | AK52: 46204 | AL52: =AT51 -> 694235.6 | AM52: =AM51 -> 5158.1682 | AN52: =AM52-AP52 -> 674.56323 | AO52: =(AN52/AL52)*12 -> 0.011659959 | AP52: =AL52*($AK$3/12) -> 4483.6049 | AQ52: =(AP52/AL52)*12 -> 0.0775 | AR52: =AR51+AN52 -> 26438.959 | AS52: =AS51+AP52 -> 205678.61 | AT52: =AL52-AN52 -> 693561.04 | AU52: =AR52+AS52 -> 232117.57 | AW52: 45 | AX52: 46204 | AY52: =BG51 -> 693034.46 | AZ52: =AZ51 -> 5034.3445 | BA52: =AZ52-BC52 -> 702.87909 | BB52: =(BA52/AY52)*12 -> 0.012170461 | BC52: =AY52*($AX$3/12) -> 4331.4654 | BD52: =(BC52/AY52)*12 -> 0.075 | BE52: =BE51+BA52 -> 27668.419 | BF52: =BF51+BC52 -> 198877.08 | BG52: =AY52-BA52 -> 692331.58 | BH52: =BE52+BF52 -> 226545.5 | BJ52: 45 | BK52: 46204 | BL52: =BT51 -> 691787.19 | BM52: =BM51 -> 4911.6692 | BN52: =BM52-BP52 -> 732.12159 | BO52: =(BN52/BL52)*12 -> 0.012699656 | BP52: =BL52*($BK$3/12) -> 4179.5476 | BQ52: =(BP52/BL52)*12 -> 0.0725 | BR52: =BR51+BN52 -> 28944.928 | BS52: =BS51+BP52 -> 192080.19 | BT52: =BL52-BN52 -> 691055.07 | BU52: =BR52+BS52 -> 221025.11 | BW52: 45 | BX52: 46204 | BY52: =CG51 -> 690492.72 | BZ52: =BZ51 -> 4790.178 | CA52: =BZ52-CC52 -> 762.30374 | CB52: =(CA52/BY52)*12 -> 0.013247996 | CC52: =BY52*($BX$3/12) -> 4027.8742 | CD52: =(CC52/BY52)*12 -> 0.07 | CE52: =CE51+CA52 -> 30269.579 | CF52: =CF51+CC52 -> 185288.43 | CG52: =BY52-CA52 -> 689730.42 | CH52: =CE52+CF52 -> 215558.01
... J342: 335 | K342: 55032 | L342: =T341 -> 128381.7 | M342: =$L$8/((($N$4)-1)/($N$3*$N$4)) -> 5409.1195 | N342: =M342-P342 -> 4526.4953 | O342: =(N342/L342)*12 -> 0.42309724 | P342: =L342*($K$3/12) -> 882.6242 | Q342: =(P342/L342)*12 -> 0.0825 | R342: =R341+N342 -> 596144.79 | S342: =S341+P342 -> 1215910.3 | T342: =L342-N342 -> 123855.21 | U342: =R342+S342 -> 1812055 | W342: 335 | X342: 55032 | Y342: =AG341 -> 125731.74 | Z342: =Z341 -> 5283.1049 | AA342: =Z342-AC342 -> 4444.8933 | AB342: =(AA342/Y342)*12 -> 0.42422637 | AC342: =Y342*($X$3/12) -> 838.21161 | AD342: =(AC342/Y342)*12 -> 0.08 | AE342: =AE341+AA342 -> 598713.15 | AF342: =AF341+AC342 -> 1171127 | AG342: =Y342-AA342 -> 121286.85 | AH342: =AE342+AF342 -> 1769840.2 | AJ342: 335 | AK342: 55032 | AL342: =AT341 -> 123092.51 | AM342: =AM341 -> 5158.1682 | AN342: =AM342-AP342 -> 4363.1957 | AO342: =(AN342/AL342)*12 -> 0.42535772 | AP342: =AL342*($AK$3/12) -> 794.97245 | AQ342: =(AP342/AL342)*12 -> 0.0775 | AR342: =AR341+AN342 -> 601270.69 | AS342: =AS341+AP342 -> 1126715.6 | AT342: =AL342-AN342 -> 118729.31 | AU342: =AR342+AS342 -> 1727986.3 | AW342: 335 | AX342: 55032 | AY342: =BG341 -> 120464.97 | AZ342: =AZ341 -> 5034.3445 | BA342: =AZ342-BC342 -> 4281.4384 | BB342: =(BA342/AY342)*12 -> 0.42649129 | BC342: =AY342*($AX$3/12) -> 752.90606 | BD342: =(BC342/AY342)*12 -> 0.075 | BE342: =BE341+BA342 -> 603816.47 | BF342: =BF341+BC342 -> 1082688.9 | BG342: =AY342-BA342 -> 116183.53 | BH342: =BE342+BF342 -> 1686505.4 | BJ342: 335 | BK342: 55032 | BL342: =BT341 -> 117850.1 | BM342: =BM341 -> 4911.6692 | BN342: =BM342-BP342 -> 4199.6582 | BO342: =(BN342/BL342)*12 -> 0.4276271 | BP342: =BL342*($BK$3/12) -> 712.01105 | BQ342: =(BP342/BL342)*12 -> 0.0725 | BR342: =BR341+BN342 -> 606349.55 | BS342: =BS341+BP342 -> 1039059.6 | BT342: =BL342-BN342 -> 113650.45 | BU342: =BR342+BS342 -> 1645409.2 | BW342: 335 | BX342: 55032 | BY342: =CG341 -> 115248.91 | BZ342: =BZ341 -> 4790.178 | CA342: =BZ342-CC342 -> 4117.8927 | CB342: =(CA342/BY342)*12 -> 0.42876513 | CC342: =BY342*($BX$3/12) -> 672.28529 | CD342: =(CC342/BY342)*12 -> 0.07 | CE342: =CE341+CA342 -> 608868.99 | CF342: =CF341+CC342 -> 995840.63 | CG342: =BY342-CA342 -> 111131.01 | CH342: =CE342+CF342 -> 1604709.6
J343: =J342+1 -> 336 | L343: =T342 -> 123855.21 | M343: =$L$8/((($N$4)-1)/($N$3*$N$4)) -> 5409.1195 | N343: =M343-P343 -> 4557.615 | O343: =(N343/L343)*12 -> 0.44157514 | P343: =L343*($K$3/12) -> 851.50455 | Q343: =(P343/L343)*12 -> 0.0825 | R343: =R342+N343 -> 600702.41 | S343: =S342+P343 -> 1216761.8 | T343: =L343-N343 -> 119297.59 | U343: =R343+S343 -> 1817464.2 | W343: =W342+1 -> 336 | Y343: =AG342 -> 121286.85 | Z343: =Z342 -> 5283.1049 | AA343: =Z343-AC343 -> 4474.5259 | AB343: =(AA343/Y343)*12 -> 0.44270514 | AC343: =Y343*($X$3/12) -> 808.57899 | AD343: =(AC343/Y343)*12 -> 0.08 | AE343: =AE342+AA343 -> 603187.68 | AF343: =AF342+AC343 -> 1171935.6 | AG343: =Y343-AA343 -> 116812.32 | AH343: =AE343+AF343 -> 1775123.3 | AJ343: =AJ342+1 -> 336 | AL343: =AT342 -> 118729.31 | AM343: =AM342 -> 5158.1682 | AN343: =AM343-AP343 -> 4391.3747 | AO343: =(AN343/AL343)*12 -> 0.44383729 | AP343: =AL343*($AK$3/12) -> 766.79348 | AQ343: =(AP343/AL343)*12 -> 0.0775 | AR343: =AR342+AN343 -> 605662.06 | AS343: =AS342+AP343 -> 1127482.4 | AT343: =AL343-AN343 -> 114337.94 | AU343: =AR343+AS343 -> 1733144.5 | AW343: =AW342+1 -> 336 | AY343: =BG342 -> 116183.53 | AZ343: =AZ342 -> 5034.3445 | BA343: =AZ343-BC343 -> 4308.1974 | BB343: =(BA343/AY343)*12 -> 0.44497157 | BC343: =AY343*($AX$3/12) -> 726.14707 | BD343: =(BC343/AY343)*12 -> 0.075 | BE343: =BE342+BA343 -> 608124.67 | BF343: =BF342+BC343 -> 1083415.1 | BG343: =AY343-BA343 -> 111875.33 | BH343: =BE343+BF343 -> 1691539.7 | BJ343: =BJ342+1 -> 336 | BL343: =BT342 -> 113650.45 | BM343: =BM342 -> 4911.6692 | BN343: =BM343-BP343 -> 4225.0311 | BO343: =(BN343/BL343)*12 -> 0.446108 | BP343: =BL343*($BK$3/12) -> 686.63811 | BQ343: =(BP343/BL343)*12 -> 0.0725 | BR343: =BR342+BN343 -> 610574.58 | BS343: =BS342+BP343 -> 1039746.3 | BT343: =BL343-BN343 -> 109425.42 | BU343: =BR343+BS343 -> 1650320.9 | BW343: =BW342+1 -> 336 | BY343: =CG342 -> 111131.01 | BZ343: =BZ342 -> 4790.178 | CA343: =BZ343-CC343 -> 4141.9137 | CB343: =(CA343/BY343)*12 -> 0.44724657 | CC343: =BY343*($BX$3/12) -> 648.26425 | CD343: =(CC343/BY343)*12 -> 0.07 | CE343: =CE342+CA343 -> 613010.9 | CF343: =CF342+CC343 -> 996488.9 | CG343: =BY343-CA343 -> 106989.1 | CH343: =CE343+CF343 -> 1609499.8
J344: =J343+1 -> 337 | L344: =T343 -> 119297.59 | M344: =$L$8/((($N$4)-1)/($N$3*$N$4)) -> 5409.1195 | N344: =M344-P344 -> 4588.9486 | O344: =(N344/L344)*12 -> 0.46159677 | P344: =L344*($K$3/12) -> 820.17094 | Q344: =(P344/L344)*12 -> 0.0825 | R344: =R343+N344 -> 605291.36 | S344: =S343+P344 -> 1217581.9 | T344: =L344-N344 -> 114708.64 | U344: =R344+S344 -> 1822873.3 | W344: =W343+1 -> 337 | Y344: =AG343 -> 116812.32 | Z344: =Z343 -> 5283.1049 | AA344: =Z344-AC344 -> 4504.3561 | AB344: =(AA344/Y344)*12 -> 0.4627275 | AC344: =Y344*($X$3/12) -> 778.74881 | AD344: =(AC344/Y344)*12 -> 0.08 | AE344: =AE343+AA344 -> 607692.03 | AF344: =AF343+AC344 -> 1172714.3 | AG344: =Y344-AA344 -> 112307.97 | AH344: =AE344+AF344 -> 1780406.4 | AJ344: =AJ343+1 -> 337 | AL344: =AT343 -> 114337.94 | AM344: =AM343 -> 5158.1682 | AN344: =AM344-AP344 -> 4419.7356 | AO344: =(AN344/AL344)*12 -> 0.46386028 | AP344: =AL344*($AK$3/12) -> 738.43252 | AQ344: =(AP344/AL344)*12 -> 0.0775 | AR344: =AR343+AN344 -> 610081.8 | AS344: =AS343+AP344 -> 1128220.9 | AT344: =AL344-AN344 -> 109918.2 | AU344: =AR344+AS344 -> 1738302.7 | AW344: =AW343+1 -> 337 | AY344: =BG343 -> 111875.33 | AZ344: =AZ343 -> 5034.3445 | BA344: =AZ344-BC344 -> 4335.1236 | BB344: =(BA344/AY344)*12 -> 0.46499511 | BC344: =AY344*($AX$3/12) -> 699.22084 | BD344: =(BC344/AY344)*12 -> 0.075 | BE344: =BE343+BA344 -> 612459.79 | BF344: =BF343+BC344 -> 1084114.3 | BG344: =AY344-BA344 -> 107540.21 | BH344: =BE344+BF344 -> 1696574.1 | BJ344: =BJ343+1 -> 337 | BL344: =BT343 -> 109425.42 | BM344: =BM343 -> 4911.6692 | BN344: =BM344-BP344 -> 4250.5573 | BO344: =(BN344/BL344)*12 -> 0.466132 | BP344: =BL344*($BK$3/12) -> 661.11188 | BQ344: =(BP344/BL344)*12 -> 0.0725 | BR344: =BR343+BN344 -> 614825.14 | BS344: =BS343+BP344 -> 1040407.4 | BT344: =BL344-BN344 -> 105174.86 | BU344: =BR344+BS344 -> 1655232.5 | BW344: =BW343+1 -> 337 | BY344: =CG343 -> 106989.1 | BZ344: =BZ343 -> 4790.178 | CA344: =BZ344-CC344 -> 4166.0749 | CB344: =(CA344/BY344)*12 -> 0.46727095 | CC344: =BY344*($BX$3/12) -> 624.10309 | CD344: =(CC344/BY344)*12 -> 0.07 | CE344: =CE343+CA344 -> 617176.97 | CF344: =CF343+CC344 -> 997113 | CG344: =BY344-CA344 -> 102823.03 | CH344: =CE344+CF344 -> 1614290
J345: =J344+1 -> 338 | L345: =T344 -> 114708.64 | M345: =$L$8/((($N$4)-1)/($N$3*$N$4)) -> 5409.1195 | N345: =M345-P345 -> 4620.4976 | O345: =(N345/L345)*12 -> 0.4833635 | P345: =L345*($K$3/12) -> 788.62192 | Q345: =(P345/L345)*12 -> 0.0825 | R345: =R344+N345 -> 609911.85 | S345: =S344+P345 -> 1218370.6 | T345: =L345-N345 -> 110088.15 | U345: =R345+S345 -> 1828282.4 | W345: =W344+1 -> 338 | Y345: =AG344 -> 112307.97 | Z345: =Z344 -> 5283.1049 | AA345: =Z345-AC345 -> 4534.3852 | AB345: =(AA345/Y345)*12 -> 0.48449477 | AC345: =Y345*($X$3/12) -> 748.71977 | AD345: =(AC345/Y345)*12 -> 0.08 | AE345: =AE344+AA345 -> 612226.42 | AF345: =AF344+AC345 -> 1173463 | AG345: =Y345-AA345 -> 107773.58 | AH345: =AE345+AF345 -> 1785689.5 | AJ345: =AJ344+1 -> 338 | AL345: =AT344 -> 109918.2 | AM345: =AM344 -> 5158.1682 | AN345: =AM345-AP345 -> 4448.2798 | AO345: =(AN345/AL345)*12 -> 0.485628 | AP345: =AL345*($AK$3/12) -> 709.88839 | AQ345: =(AP345/AL345)*12 -> 0.0775 | AR345: =AR344+AN345 -> 614530.08 | AS345: =AS344+AP345 -> 1128930.8 | AT345: =AL345-AN345 -> 105469.92 | AU345: =AR345+AS345 -> 1743460.8 | AW345: =AW344+1 -> 338 | AY345: =BG344 -> 107540.21 | AZ345: =AZ344 -> 5034.3445 | BA345: =AZ345-BC345 -> 4362.2181 | BB345: =(BA345/AY345)*12 -> 0.48676321 | BC345: =AY345*($AX$3/12) -> 672.12632 | BD345: =(BC345/AY345)*12 -> 0.075 | BE345: =BE344+BA345 -> 616822.01 | BF345: =BF344+BC345 -> 1084786.4 | BG345: =AY345-BA345 -> 103177.99 | BH345: =BE345+BF345 -> 1701608.4 | BJ345: =BJ344+1 -> 338 | BL345: =BT344 -> 105174.86 | BM345: =BM344 -> 4911.6692 | BN345: =BM345-BP345 -> 4276.2378 | BO345: =(BN345/BL345)*12 -> 0.48790038 | BP345: =BL345*($BK$3/12) -> 635.43143 | BQ345: =(BP345/BL345)*12 -> 0.0725 | BR345: =BR344+BN345 -> 619101.38 | BS345: =BS344+BP345 -> 1041042.8 | BT345: =BL345-BN345 -> 100898.62 | BU345: =BR345+BS345 -> 1660144.2 | BW345: =BW344+1 -> 338 | BY345: =CG344 -> 102823.03 | BZ345: =BZ344 -> 4790.178 | CA345: =BZ345-CC345 -> 4190.377 | CB345: =(CA345/BY345)*12 -> 0.48903953 | CC345: =BY345*($BX$3/12) -> 599.80098 | CD345: =(CC345/BY345)*12 -> 0.07 | CE345: =CE344+CA345 -> 621367.35 | CF345: =CF344+CC345 -> 997712.8 | CG345: =BY345-CA345 -> 98632.649 | CH345: =CE345+CF345 -> 1619080.2
J346: =J345+1 -> 339 | L346: =T345 -> 110088.15 | M346: =$L$8/((($N$4)-1)/($N$3*$N$4)) -> 5409.1195 | N346: =M346-P346 -> 4652.2635 | O346: =(N346/L346)*12 -> 0.5071133 | P346: =L346*($K$3/12) -> 756.856 | Q346: =(P346/L346)*12 -> 0.0825 | R346: =R345+N346 -> 614564.12 | S346: =S345+P346 -> 1219127.4 | T346: =L346-N346 -> 105435.88 | U346: =R346+S346 -> 1833691.5 | W346: =W345+1 -> 339 | Y346: =AG345 -> 107773.58 | Z346: =Z345 -> 5283.1049 | AA346: =Z346-AC346 -> 4564.6144 | AB346: =(AA346/Y346)*12 -> 0.5082449 | AC346: =Y346*($X$3/12) -> 718.49054 | AD346: =(AC346/Y346)*12 -> 0.08 | AE346: =AE345+AA346 -> 616791.03 | AF346: =AF345+AC346 -> 1174181.5 | AG346: =Y346-AA346 -> 103208.97 | AH346: =AE346+AF346 -> 1790972.6 | AJ346: =AJ345+1 -> 339 | AL346: =AT345 -> 105469.92 | AM346: =AM345 -> 5158.1682 | AN346: =AM346-AP346 -> 4477.0082 | AO346: =(AN346/AL346)*12 -> 0.50937838 | AP346: =AL346*($AK$3/12) -> 681.15992 | AQ346: =(AP346/AL346)*12 -> 0.0775 | AR346: =AR345+AN346 -> 619007.09 | AS346: =AS345+AP346 -> 1129611.9 | AT346: =AL346-AN346 -> 100992.91 | AU346: =AR346+AS346 -> 1748619 | AW346: =AW345+1 -> 339 | AY346: =BG345 -> 103177.99 | AZ346: =AZ345 -> 5034.3445 | BA346: =AZ346-BC346 -> 4389.482 | BB346: =(BA346/AY346)*12 -> 0.51051375 | BC346: =AY346*($AX$3/12) -> 644.86245 | BD346: =(BC346/AY346)*12 -> 0.075 | BE346: =BE345+BA346 -> 621211.49 | BF346: =BF345+BC346 -> 1085431.3 | BG346: =AY346-BA346 -> 98788.51 | BH346: =BE346+BF346 -> 1706642.8 | BJ346: =BJ345+1 -> 339 | BL346: =BT345 -> 100898.62 | BM346: =BM345 -> 4911.6692 | BN346: =BM346-BP346 -> 4302.0734 | BO346: =(BN346/BL346)*12 -> 0.51165101 | BP346: =BL346*($BK$3/12) -> 609.59583 | BQ346: =(BP346/BL346)*12 -> 0.0725 | BR346: =BR345+BN346 -> 623403.45 | BS346: =BS345+BP346 -> 1041652.4 | BT346: =BL346-BN346 -> 96596.547 | BU346: =BR346+BS346 -> 1665055.9 | BW346: =BW345+1 -> 339 | BY346: =CG345 -> 98632.649 | BZ346: =BZ345 -> 4790.178 | CA346: =BZ346-CC346 -> 4214.8208 | CB346: =(CA346/BY346)*12 -> 0.51279014 | CC346: =BY346*($BX$3/12) -> 575.35712 | CD346: =(CC346/BY346)*12 -> 0.07 | CE346: =CE345+CA346 -> 625582.17 | CF346: =CF345+CC346 -> 998288.16 | CG346: =BY346-CA346 -> 94417.828 | CH346: =CE346+CF346 -> 1623870.3
J347: =J346+1 -> 340 | L347: =T346 -> 105435.88 | M347: =$L$8/((($N$4)-1)/($N$3*$N$4)) -> 5409.1195 | N347: =M347-P347 -> 4684.2479 | O347: =(N347/L347)*12 -> 0.53312945 | P347: =L347*($K$3/12) -> 724.87169 | Q347: =(P347/L347)*12 -> 0.0825 | R347: =R346+N347 -> 619248.37 | S347: =S346+P347 -> 1219852.3 | T347: =L347-N347 -> 100751.63 | U347: =R347+S347 -> 1839100.6 | W347: =W346+1 -> 340 | Y347: =AG346 -> 103208.97 | Z347: =Z346 -> 5283.1049 | AA347: =Z347-AC347 -> 4595.0452 | AB347: =(AA347/Y347)*12 -> 0.53426116 | AC347: =Y347*($X$3/12) -> 688.05978 | AD347: =(AC347/Y347)*12 -> 0.08 | AE347: =AE346+AA347 -> 621386.08 | AF347: =AF346+AC347 -> 1174869.6 | AG347: =Y347-AA347 -> 98613.921 | AH347: =AE347+AF347 -> 1796255.7 | AJ347: =AJ346+1 -> 340 | AL347: =AT346 -> 100992.91 | AM347: =AM346 -> 5158.1682 | AN347: =AM347-AP347 -> 4505.9223 | AO347: =(AN347/AL347)*12 -> 0.53539466 | AP347: =AL347*($AK$3/12) -> 652.24591 | AQ347: =(AP347/AL347)*12 -> 0.0775 | AR347: =AR346+AN347 -> 623513.01 | AS347: =AS346+AP347 -> 1130264.2 | AT347: =AL347-AN347 -> 96486.992 | AU347: =AR347+AS347 -> 1753777.2 | AW347: =AW346+1 -> 340 | AY347: =BG346 -> 98788.51 | AZ347: =AZ346 -> 5034.3445 | BA347: =AZ347-BC347 -> 4416.9163 | BB347: =(BA347/AY347)*12 -> 0.53652996 | BC347: =AY347*($AX$3/12) -> 617.42819 | BD347: =(BC347/AY347)*12 -> 0.075 | BE347: =BE346+BA347 -> 625628.41 | BF347: =BF346+BC347 -> 1086048.7 | BG347: =AY347-BA347 -> 94371.594 | BH347: =BE347+BF347 -> 1711677.1 | BJ347: =BJ346+1 -> 340 | BL347: =BT346 -> 96596.547 | BM347: =BM346 -> 4911.6692 | BN347: =BM347-BP347 -> 4328.0651 | BO347: =(BN347/BL347)*12 -> 0.53766706 | BP347: =BL347*($BK$3/12) -> 583.60414 | BQ347: =(BP347/BL347)*12 -> 0.0725 | BR347: =BR346+BN347 -> 627731.52 | BS347: =BS346+BP347 -> 1042236 | BT347: =BL347-BN347 -> 92268.482 | BU347: =BR347+BS347 -> 1669967.5 | BW347: =BW346+1 -> 340 | BY347: =CG346 -> 94417.828 | BZ347: =BZ346 -> 4790.178 | CA347: =BZ347-CC347 -> 4239.4073 | CB347: =(CA347/BY347)*12 -> 0.53880595 | CC347: =BY347*($BX$3/12) -> 550.77066 | CD347: =(CC347/BY347)*12 -> 0.07 | CE347: =CE346+CA347 -> 629821.58 | CF347: =CF346+CC347 -> 998838.93 | CG347: =BY347-CA347 -> 90178.42 | CH347: =CE347+CF347 -> 1628660.5
J348: =J347+1 -> 341 | L348: =T347 -> 100751.63 | M348: =$L$8/((($N$4)-1)/($N$3*$N$4)) -> 5409.1195 | N348: =M348-P348 -> 4716.4521 | O348: =(N348/L348)*12 -> 0.56175193 | P348: =L348*($K$3/12) -> 692.66749 | Q348: =(P348/L348)*12 -> 0.0825 | R348: =R347+N348 -> 623964.82 | S348: =S347+P348 -> 1220544.9 | T348: =L348-N348 -> 96035.182 | U348: =R348+S348 -> 1844509.8 | W348: =W347+1 -> 341 | Y348: =AG347 -> 98613.921 | Z348: =Z347 -> 5283.1049 | AA348: =Z348-AC348 -> 4625.6788 | AB348: =(AA348/Y348)*12 -> 0.56288346 | AC348: =Y348*($X$3/12) -> 657.42614 | AD348: =(AC348/Y348)*12 -> 0.08 | AE348: =AE347+AA348 -> 626011.76 | AF348: =AF347+AC348 -> 1175527 | AG348: =Y348-AA348 -> 93988.242 | AH348: =AE348+AF348 -> 1801538.8 | AJ348: =AJ347+1 -> 341 | AL348: =AT347 -> 96486.992 | AM348: =AM347 -> 5158.1682 | AN348: =AM348-AP348 -> 4535.023 | AO348: =(AN348/AL348)*12 -> 0.56401671 | AP348: =AL348*($AK$3/12) -> 623.14516 | AQ348: =(AP348/AL348)*12 -> 0.0775 | AR348: =AR347+AN348 -> 628048.03 | AS348: =AS347+AP348 -> 1130887.3 | AT348: =AL348-AN348 -> 91951.969 | AU348: =AR348+AS348 -> 1758935.3 | AW348: =AW347+1 -> 341 | AY348: =BG347 -> 94371.594 | AZ348: =AZ347 -> 5034.3445 | BA348: =AZ348-BC348 -> 4444.522 | BB348: =(BA348/AY348)*12 -> 0.56515167 | BC348: =AY348*($AX$3/12) -> 589.82246 | BD348: =(BC348/AY348)*12 -> 0.075 | BE348: =BE347+BA348 -> 630072.93 | BF348: =BF347+BC348 -> 1086638.5 | BG348: =AY348-BA348 -> 89927.072 | BH348: =BE348+BF348 -> 1716711.5 | BJ348: =BJ347+1 -> 341 | BL348: =BT347 -> 92268.482 | BM348: =BM347 -> 4911.6692 | BN348: =BM348-BP348 -> 4354.2138 | BO348: =(BN348/BL348)*12 -> 0.56628834 | BP348: =BL348*($BK$3/12) -> 557.45541 | BQ348: =(BP348/BL348)*12 -> 0.0725 | BR348: =BR347+BN348 -> 632085.73 | BS348: =BS347+BP348 -> 1042793.5 | BT348: =BL348-BN348 -> 87914.268 | BU348: =BR348+BS348 -> 1674879.2 | BW348: =BW347+1 -> 341 | BY348: =CG347 -> 90178.42 | BZ348: =BZ347 -> 4790.178 | CA348: =BZ348-CC348 -> 4264.1372 | CB348: =(CA348/BY348)*12 -> 0.56742673 | CC348: =BY348*($BX$3/12) -> 526.04079 | CD348: =(CC348/BY348)*12 -> 0.07 | CE348: =CE347+CA348 -> 634085.72 | CF348: =CF347+CC348 -> 999364.97 | CG348: =BY348-CA348 -> 85914.283 | CH348: =CE348+CF348 -> 1633450.7
J349: =J348+1 -> 342 | L349: =T348 -> 96035.182 | M349: =$L$8/((($N$4)-1)/($N$3*$N$4)) -> 5409.1195 | N349: =M349-P349 -> 4748.8777 | O349: =(N349/L349)*12 -> 0.59339224 | P349: =L349*($K$3/12) -> 660.24188 | Q349: =(P349/L349)*12 -> 0.0825 | R349: =R348+N349 -> 628713.7 | S349: =S348+P349 -> 1221205.2 | T349: =L349-N349 -> 91286.304 | U349: =R349+S349 -> 1849918.9 | W349: =W348+1 -> 342 | Y349: =AG348 -> 93988.242 | Z349: =Z348 -> 5283.1049 | AA349: =Z349-AC349 -> 4656.5166 | AB349: =(AA349/Y349)*12 -> 0.5945233 | AC349: =Y349*($X$3/12) -> 626.58828 | AD349: =(AC349/Y349)*12 -> 0.08 | AE349: =AE348+AA349 -> 630668.27 | AF349: =AF348+AC349 -> 1176153.6 | AG349: =Y349-AA349 -> 89331.726 | AH349: =AE349+AF349 -> 1806821.9 | AJ349: =AJ348+1 -> 342 | AL349: =AT348 -> 91951.969 | AM349: =AM348 -> 5158.1682 | AN349: =AM349-AP349 -> 4564.3117 | AO349: =(AN349/AL349)*12 -> 0.59565598 | AP349: =AL349*($AK$3/12) -> 593.85647 | AQ349: =(AP349/AL349)*12 -> 0.0775 | AR349: =AR348+AN349 -> 632612.34 | AS349: =AS348+AP349 -> 1131481.2 | AT349: =AL349-AN349 -> 87387.658 | AU349: =AR349+AS349 -> 1764093.5 | AW349: =AW348+1 -> 342 | AY349: =BG348 -> 89927.072 | AZ349: =AZ348 -> 5034.3445 | BA349: =AZ349-BC349 -> 4472.3003 | BB349: =(BA349/AY349)*12 -> 0.59679029 | BC349: =AY349*($AX$3/12) -> 562.0442 | BD349: =(BC349/AY349)*12 -> 0.075 | BE349: =BE348+BA349 -> 634545.23 | BF349: =BF348+BC349 -> 1087200.6 | BG349: =AY349-BA349 -> 85454.772 | BH349: =BE349+BF349 -> 1721745.8 | BJ349: =BJ348+1 -> 342 | BL349: =BT348 -> 87914.268 | BM349: =BM348 -> 4911.6692 | BN349: =BM349-BP349 -> 4380.5205 | BO349: =(BN349/BL349)*12 -> 0.59792622 | BP349: =BL349*($BK$3/12) -> 531.1487 | BQ349: =(BP349/BL349)*12 -> 0.0725 | BR349: =BR348+BN349 -> 636466.25 | BS349: =BS348+BP349 -> 1043324.6 | BT349: =BL349-BN349 -> 83533.748 | BU349: =BR349+BS349 -> 1679790.9 | BW349: =BW348+1 -> 342 | BY349: =CG348 -> 85914.283 | BZ349: =BZ348 -> 4790.178 | CA349: =BZ349-CC349 -> 4289.0113 | CB349: =(CA349/BY349)*12 -> 0.59906379 | CC349: =BY349*($BX$3/12) -> 501.16665 | CD349: =(CC349/BY349)*12 -> 0.07 | CE349: =CE348+CA349 -> 638374.73 | CF349: =CF348+CC349 -> 999866.14 | CG349: =BY349-CA349 -> 81625.272 | CH349: =CE349+CF349 -> 1638240.9
J350: =J349+1 -> 343 | L350: =T349 -> 91286.304 | M350: =$L$8/((($N$4)-1)/($N$3*$N$4)) -> 5409.1195 | N350: =M350-P350 -> 4781.5262 | O350: =(N350/L350)*12 -> 0.62855337 | P350: =L350*($K$3/12) -> 627.59334 | Q350: =(P350/L350)*12 -> 0.0825 | R350: =R349+N350 -> 633495.22 | S350: =S349+P350 -> 1221832.8 | T350: =L350-N350 -> 86504.778 | U350: =R350+S350 -> 1855328 | W350: =W349+1 -> 343 | Y350: =AG349 -> 89331.726 | Z350: =Z349 -> 5283.1049 | AA350: =Z350-AC350 -> 4687.5601 | AB350: =(AA350/Y350)*12 -> 0.62968358 | AC350: =Y350*($X$3/12) -> 595.54484 | AD350: =(AC350/Y350)*12 -> 0.08 | AE350: =AE349+AA350 -> 635355.83 | AF350: =AF349+AC350 -> 1176749.2 | AG350: =Y350-AA350 -> 84644.166 | AH350: =AE350+AF350 -> 1812105 | AJ350: =AJ349+1 -> 343 | AL350: =AT349 -> 87387.658 | AM350: =AM349 -> 5158.1682 | AN350: =AM350-AP350 -> 4593.7895 | AO350: =(AN350/AL350)*12 -> 0.63081533 | AP350: =AL350*($AK$3/12) -> 564.37862 | AQ350: =(AP350/AL350)*12 -> 0.0775 | AR350: =AR349+AN350 -> 637206.13 | AS350: =AS349+AP350 -> 1132045.5 | AT350: =AL350-AN350 -> 82793.868 | AU350: =AR350+AS350 -> 1769251.7 | AW350: =AW349+1 -> 343 | AY350: =BG349 -> 85454.772 | AZ350: =AZ349 -> 5034.3445 | BA350: =AZ350-BC350 -> 4500.2521 | BB350: =(BA350/AY350)*12 -> 0.63194863 | BC350: =AY350*($AX$3/12) -> 534.09232 | BD350: =(BC350/AY350)*12 -> 0.075 | BE350: =BE349+BA350 -> 639045.48 | BF350: =BF349+BC350 -> 1087734.7 | BG350: =AY350-BA350 -> 80954.52 | BH350: =BE350+BF350 -> 1726780.2 | BJ350: =BJ349+1 -> 343 | BL350: =BT349 -> 83533.748 | BM350: =BM349 -> 4911.6692 | BN350: =BM350-BP350 -> 4406.9862 | BO350: =(BN350/BL350)*12 -> 0.63308346 | BP350: =BL350*($BK$3/12) -> 504.68306 | BQ350: =(BP350/BL350)*12 -> 0.0725 | BR350: =BR349+BN350 -> 640873.24 | BS350: =BS349+BP350 -> 1043829.3 | BT350: =BL350-BN350 -> 79126.761 | BU350: =BR350+BS350 -> 1684702.5 | BW350: =BW349+1 -> 343 | BY350: =CG349 -> 81625.272 | BZ350: =BZ349 -> 4790.178 | CA350: =BZ350-CC350 -> 4314.0305 | CB350: =(CA350/BY350)*12 -> 0.63421984 | CC350: =BY350*($BX$3/12) -> 476.14742 | CD350: =(CC350/BY350)*12 -> 0.07 | CE350: =CE349+CA350 -> 642688.76 | CF350: =CF349+CC350 -> 1000342.3 | CG350: =BY350-CA350 -> 77311.241 | CH350: =CE350+CF350 -> 1643031
J351: =J350+1 -> 344 | L351: =T350 -> 86504.778 | M351: =$L$8/((($N$4)-1)/($N$3*$N$4)) -> 5409.1195 | N351: =M351-P351 -> 4814.3992 | O351: =(N351/L351)*12 -> 0.66785664 | P351: =L351*($K$3/12) -> 594.72035 | Q351: =(P351/L351)*12 -> 0.0825 | R351: =R350+N351 -> 638309.62 | S351: =S350+P351 -> 1222427.5 | T351: =L351-N351 -> 81690.379 | U351: =R351+S351 -> 1860737.1 | W351: =W350+1 -> 344 | Y351: =AG350 -> 84644.166 | Z351: =Z350 -> 5283.1049 | AA351: =Z351-AC351 -> 4718.8105 | AB351: =(AA351/Y351)*12 -> 0.66898558 | AC351: =Y351*($X$3/12) -> 564.29444 | AD351: =(AC351/Y351)*12 -> 0.08 | AE351: =AE350+AA351 -> 640074.64 | AF351: =AF350+AC351 -> 1177313.5 | AG351: =Y351-AA351 -> 79925.355 | AH351: =AE351+AF351 -> 1817388.1 | AJ351: =AJ350+1 -> 344 | AL351: =AT350 -> 82793.868 | AM351: =AM350 -> 5158.1682 | AN351: =AM351-AP351 -> 4623.4578 | AO351: =(AN351/AL351)*12 -> 0.67011597 | AP351: =AL351*($AK$3/12) -> 534.7104 | AQ351: =(AP351/AL351)*12 -> 0.0775 | AR351: =AR350+AN351 -> 641829.59 | AS351: =AS350+AP351 -> 1132580.3 | AT351: =AL351-AN351 -> 78170.41 | AU351: =AR351+AS351 -> 1774409.8 | AW351: =AW350+1 -> 344 | AY351: =BG350 -> 80954.52 | AZ351: =AZ350 -> 5034.3445 | BA351: =AZ351-BC351 -> 4528.3787 | BB351: =(BA351/AY351)*12 -> 0.67124782 | BC351: =AY351*($AX$3/12) -> 505.96575 | BD351: =(BC351/AY351)*12 -> 0.075 | BE351: =BE350+BA351 -> 643573.86 | BF351: =BF350+BC351 -> 1088240.6 | BG351: =AY351-BA351 -> 76426.141 | BH351: =BE351+BF351 -> 1731814.5 | BJ351: =BJ350+1 -> 344 | BL351: =BT350 -> 79126.761 | BM351: =BM350 -> 4911.6692 | BN351: =BM351-BP351 -> 4433.6117 | BO351: =(BN351/BL351)*12 -> 0.67238112 | BP351: =BL351*($BK$3/12) -> 478.05752 | BQ351: =(BP351/BL351)*12 -> 0.0725 | BR351: =BR350+BN351 -> 645306.85 | BS351: =BS350+BP351 -> 1044307.4 | BT351: =BL351-BN351 -> 74693.15 | BU351: =BR351+BS351 -> 1689614.2 | BW351: =BW350+1 -> 344 | BY351: =CG350 -> 77311.241 | BZ351: =BZ350 -> 4790.178 | CA351: =BZ351-CC351 -> 4339.1957 | CB351: =(CA351/BY351)*12 -> 0.67351588 | CC351: =BY351*($BX$3/12) -> 450.98224 | CD351: =(CC351/BY351)*12 -> 0.07 | CE351: =CE350+CA351 -> 647027.95 | CF351: =CF350+CC351 -> 1000793.3 | CG351: =BY351-CA351 -> 72972.046 | CH351: =CE351+CF351 -> 1647821.2
J352: =J351+1 -> 345 | L352: =T351 -> 81690.379 | M352: =$L$8/((($N$4)-1)/($N$3*$N$4)) -> 5409.1195 | N352: =M352-P352 -> 4847.4982 | O352: =(N352/L352)*12 -> 0.71207869 | P352: =L352*($K$3/12) -> 561.62136 | Q352: =(P352/L352)*12 -> 0.0825 | R352: =R351+N352 -> 643157.12 | S352: =S351+P352 -> 1222989.1 | T352: =L352-N352 -> 76842.881 | U352: =R352+S352 -> 1866146.2 | W352: =W351+1 -> 345 | Y352: =AG351 -> 79925.355 | Z352: =Z351 -> 5283.1049 | AA352: =Z352-AC352 -> 4750.2692 | AB352: =(AA352/Y352)*12 -> 0.71320585 | AC352: =Y352*($X$3/12) -> 532.8357 | AD352: =(AC352/Y352)*12 -> 0.08 | AE352: =AE351+AA352 -> 644824.91 | AF352: =AF351+AC352 -> 1177846.3 | AG352: =Y352-AA352 -> 75175.086 | AH352: =AE352+AF352 -> 1822671.2 | AJ352: =AJ351+1 -> 345 | AL352: =AT351 -> 78170.41 | AM352: =AM351 -> 5158.1682 | AN352: =AM352-AP352 -> 4653.3176 | AO352: =(AN352/AL352)*12 -> 0.71433437 | AP352: =AL352*($AK$3/12) -> 504.85057 | AQ352: =(AP352/AL352)*12 -> 0.0775 | AR352: =AR351+AN352 -> 646482.91 | AS352: =AS351+AP352 -> 1133085.1 | AT352: =AL352-AN352 -> 73517.093 | AU352: =AR352+AS352 -> 1779568 | AW352: =AW351+1 -> 345 | AY352: =BG351 -> 76426.141 | AZ352: =AZ351 -> 5034.3445 | BA352: =AZ352-BC352 -> 4556.6811 | BB352: =(BA352/AY352)*12 -> 0.71546427 | BC352: =AY352*($AX$3/12) -> 477.66338 | BD352: =(BC352/AY352)*12 -> 0.075 | BE352: =BE351+BA352 -> 648130.54 | BF352: =BF351+BC352 -> 1088718.3 | BG352: =AY352-BA352 -> 71869.46 | BH352: =BE352+BF352 -> 1736848.8 | BJ352: =BJ351+1 -> 345 | BL352: =BT351 -> 74693.15 | BM352: =BM351 -> 4911.6692 | BN352: =BM352-BP352 -> 4460.3981 | BO352: =(BN352/BL352)*12 -> 0.71659553 | BP352: =BL352*($BK$3/12) -> 451.27111 | BQ352: =(BP352/BL352)*12 -> 0.0725 | BR352: =BR351+BN352 -> 649767.25 | BS352: =BS351+BP352 -> 1044758.6 | BT352: =BL352-BN352 -> 70232.752 | BU352: =BR352+BS352 -> 1694525.9 | BW352: =BW351+1 -> 345 | BY352: =CG351 -> 72972.046 | BZ352: =BZ351 -> 4790.178 | CA352: =BZ352-CC352 -> 4364.5077 | CB352: =(CA352/BY352)*12 -> 0.71772816 | CC352: =BY352*($BX$3/12) -> 425.67027 | CD352: =(CC352/BY352)*12 -> 0.07 | CE352: =CE351+CA352 -> 651392.46 | CF352: =CF351+CC352 -> 1001218.9 | CG352: =BY352-CA352 -> 68607.538 | CH352: =CE352+CF352 -> 1652611.4
J353: =J352+1 -> 346 | L353: =T352 -> 76842.881 | M353: =$L$8/((($N$4)-1)/($N$3*$N$4)) -> 5409.1195 | N353: =M353-P353 -> 4880.8247 | O353: =(N353/L353)*12 -> 0.76220329 | P353: =L353*($K$3/12) -> 528.29481 | Q353: =(P353/L353)*12 -> 0.0825 | R353: =R352+N353 -> 648037.94 | S353: =S352+P353 -> 1223517.4 | T353: =L353-N353 -> 71962.056 | U353: =R353+S353 -> 1871555.4 | W353: =W352+1 -> 346 | Y353: =AG352 -> 75175.086 | Z353: =Z352 -> 5283.1049 | AA353: =Z353-AC353 -> 4781.9377 | AB353: =(AA353/Y353)*12 -> 0.76332806 | AC353: =Y353*($X$3/12) -> 501.16724 | AD353: =(AC353/Y353)*12 -> 0.08 | AE353: =AE352+AA353 -> 649606.85 | AF353: =AF352+AC353 -> 1178347.5 | AG353: =Y353-AA353 -> 70393.148 | AH353: =AE353+AF353 -> 1827954.3 | AJ353: =AJ352+1 -> 346 | AL353: =AT352 -> 73517.093 | AM353: =AM352 -> 5158.1682 | AN353: =AM353-AP353 -> 4683.3703 | AO353: =(AN353/AL353)*12 -> 0.7644541 | AP353: =AL353*($AK$3/12) -> 474.79789 | AQ353: =(AP353/AL353)*12 -> 0.0775 | AR353: =AR352+AN353 -> 651166.28 | AS353: =AS352+AP353 -> 1133559.9 | AT353: =AL353-AN353 -> 68833.723 | AU353: =AR353+AS353 -> 1784726.2 | AW353: =AW352+1 -> 346 | AY353: =BG352 -> 71869.46 | AZ353: =AZ352 -> 5034.3445 | BA353: =AZ353-BC353 -> 4585.1603 | BB353: =(BA353/AY353)*12 -> 0.76558143 | BC353: =AY353*($AX$3/12) -> 449.18412 | BD353: =(BC353/AY353)*12 -> 0.075 | BE353: =BE352+BA353 -> 652715.7 | BF353: =BF352+BC353 -> 1089167.5 | BG353: =AY353-BA353 -> 67284.3 | BH353: =BE353+BF353 -> 1741883.2 | BJ353: =BJ352+1 -> 346 | BL353: =BT352 -> 70232.752 | BM353: =BM352 -> 4911.6692 | BN353: =BM353-BP353 -> 4487.3463 | BO353: =(BN353/BL353)*12 -> 0.76671004 | BP353: =BL353*($BK$3/12) -> 424.32287 | BQ353: =(BP353/BL353)*12 -> 0.0725 | BR353: =BR352+BN353 -> 654254.59 | BS353: =BS352+BP353 -> 1045183 | BT353: =BL353-BN353 -> 65745.405 | BU353: =BR353+BS353 -> 1699437.5 | BW353: =BW352+1 -> 346 | BY353: =CG352 -> 68607.538 | BZ353: =BZ352 -> 4790.178 | CA353: =BZ353-CC353 -> 4389.9673 | CB353: =(CA353/BY353)*12 -> 0.76783994 | CC353: =BY353*($BX$3/12) -> 400.21064 | CD353: =(CC353/BY353)*12 -> 0.07 | CE353: =CE352+CA353 -> 655782.43 | CF353: =CF352+CC353 -> 1001619.1 | CG353: =BY353-CA353 -> 64217.571 | CH353: =CE353+CF353 -> 1657401.6
J354: =J353+1 -> 347 | L354: =T353 -> 71962.056 | M354: =$L$8/((($N$4)-1)/($N$3*$N$4)) -> 5409.1195 | N354: =M354-P354 -> 4914.3804 | O354: =(N354/L354)*12 -> 0.81949527 | P354: =L354*($K$3/12) -> 494.73914 | Q354: =(P354/L354)*12 -> 0.0825 | R354: =R353+N354 -> 652952.32 | S354: =S353+P354 -> 1224012.2 | T354: =L354-N354 -> 67047.676 | U354: =R354+S354 -> 1876964.5 | W354: =W353+1 -> 347 | Y354: =AG353 -> 70393.148 | Z354: =Z353 -> 5283.1049 | AA354: =Z354-AC354 -> 4813.8173 | AB354: =(AA354/Y354)*12 -> 0.8206169 | AC354: =Y354*($X$3/12) -> 469.28765 | AD354: =(AC354/Y354)*12 -> 0.08 | AE354: =AE353+AA354 -> 654420.67 | AF354: =AF353+AC354 -> 1178816.7 | AG354: =Y354-AA354 -> 65579.331 | AH354: =AE354+AF354 -> 1833237.4 | AJ354: =AJ353+1 -> 347 | AL354: =AT353 -> 68833.723 | AM354: =AM353 -> 5158.1682 | AN354: =AM354-AP354 -> 4713.617 | AO354: =(AN354/AL354)*12 -> 0.82173973 | AP354: =AL354*($AK$3/12) -> 444.55112 | AQ354: =(AP354/AL354)*12 -> 0.0775 | AR354: =AR353+AN354 -> 655879.89 | AS354: =AS353+AP354 -> 1134004.5 | AT354: =AL354-AN354 -> 64120.105 | AU354: =AR354+AS354 -> 1789884.4 | AW354: =AW353+1 -> 347 | AY354: =BG353 -> 67284.3 | AZ354: =AZ353 -> 5034.3445 | BA354: =AZ354-BC354 -> 4613.8176 | BB354: =(BA354/AY354)*12 -> 0.82286375 | BC354: =AY354*($AX$3/12) -> 420.52687 | BD354: =(BC354/AY354)*12 -> 0.075 | BE354: =BE353+BA354 -> 657329.52 | BF354: =BF353+BC354 -> 1089588 | BG354: =AY354-BA354 -> 62670.482 | BH354: =BE354+BF354 -> 1746917.5 | BJ354: =BJ353+1 -> 347 | BL354: =BT353 -> 65745.405 | BM354: =BM353 -> 4911.6692 | BN354: =BM354-BP354 -> 4514.4574 | BO354: =(BN354/BL354)*12 -> 0.82398897 | BP354: =BL354*($BK$3/12) -> 397.21182 | BQ354: =(BP354/BL354)*12 -> 0.0725 | BR354: =BR353+BN354 -> 658769.05 | BS354: =BS353+BP354 -> 1045580.2 | BT354: =BL354-BN354 -> 61230.948 | BU354: =BR354+BS354 -> 1704349.2 | BW354: =BW353+1 -> 347 | BY354: =CG353 -> 64217.571 | BZ354: =BZ353 -> 4790.178 | CA354: =BZ354-CC354 -> 4415.5755 | CB354: =(CA354/BY354)*12 -> 0.82511539 | CC354: =BY354*($BX$3/12) -> 374.6025 | CD354: =(CC354/BY354)*12 -> 0.07 | CE354: =CE353+CA354 -> 660198 | CF354: =CF353+CC354 -> 1001993.7 | CG354: =BY354-CA354 -> 59801.995 | CH354: =CE354+CF354 -> 1662191.8
... J367: =J366+1 -> 360 | L367: =T366 -> 5372.1858 | M367: =$L$8/((($N$4)-1)/($N$3*$N$4)) -> 5409.1195 | N367: =M367-P367 -> 5372.1858 | O367: =(N367/L367)*12 -> 12 | P367: =L367*($K$3/12) -> 36.933777 | Q367: =(P367/L367)*12 -> 0.0825 | R367: =R366+N367 -> 720000 | S367: =S366+P367 -> 1227283 | T367: =L367-N367 -> -1.6320882e-08 | U367: =R367+S367 -> 1947283 | W367: =W366+1 -> 360 | Y367: =AG366 -> 5248.1175 | Z367: =Z366 -> 5283.1049 | AA367: =Z367-AC367 -> 5248.1175 | AB367: =(AA367/Y367)*12 -> 12 | AC367: =Y367*($X$3/12) -> 34.98745 | AD367: =(AC367/Y367)*12 -> 0.08 | AE367: =AE366+AA367 -> 720000 | AF367: =AF366+AC367 -> 1181917.8 | AG367: =Y367-AA367 -> -1.6204467e-08 | AH367: =AE367+AF367 -> 1901917.8 | AJ367: =AJ366+1 -> 360 | AL367: =AT366 -> 5125.0688 | AM367: =AM366 -> 5158.1682 | AN367: =AM367-AP367 -> 5125.0688 | AO367: =(AN367/AL367)*12 -> 12 | AP367: =AL367*($AK$3/12) -> 33.099402 | AQ367: =(AP367/AL367)*12 -> 0.0775 | AR367: =AR366+AN367 -> 720000 | AS367: =AS366+AP367 -> 1136940.5 | AT367: =AL367-AN367 -> -1.1276825e-08 | AU367: =AR367+AS367 -> 1856940.5 | AW367: =AW366+1 -> 360 | AY367: =BG366 -> 5003.0752 | AZ367: =AZ366 -> 5034.3445 | BA367: =AZ367-BC367 -> 5003.0752 | BB367: =(BA367/AY367)*12 -> 12 | BC367: =AY367*($AX$3/12) -> 31.26922 | BD367: =(BC367/AY367)*12 -> 0.075 | BE367: =BE366+BA367 -> 720000 | BF367: =BF366+BC367 -> 1092364 | BG367: =AY367-BA367 -> 1.5185833e-08 | BH367: =BE367+BF367 -> 1812364 | BJ367: =BJ366+1 -> 360 | BL367: =BT366 -> 4882.1728 | BM367: =BM366 -> 4911.6692 | BN367: =BM367-BP367 -> 4882.1728 | BO367: =(BN367/BL367)*12 -> 12 | BP367: =BL367*($BK$3/12) -> 29.49646 | BQ367: =(BP367/BL367)*12 -> 0.0725 | BR367: =BR366+BN367 -> 720000 | BS367: =BS366+BP367 -> 1048200.9 | BT367: =BL367-BN367 -> 7.7816367e-09 | BU367: =BR367+BS367 -> 1768200.9 | BW367: =BW366+1 -> 360 | BY367: =CG366 -> 4762.3973 | BZ367: =BZ366 -> 4790.178 | CA367: =BZ367-CC367 -> 4762.3973 | CB367: =(CA367/BY367)*12 -> 12 | CC367: =BY367*($BX$3/12) -> 27.780651 | CD367: =(CC367/BY367)*12 -> 0.07 | CE367: =CE366+CA367 -> 720000 | CF367: =CF366+CC367 -> 1004464.1 | CG367: =BY367-CA367 -> 9.0731191e-09 | CH367: =CE367+CF367 -> 1724464.1

Sheet Amoritization Scenario 15% DP
J1: Interest | K1: ='Interest Rate Comparison'!B3 -> 0.0825 | N1: =K1/12 -> 0.006875 | O1: r | W1: Interest | X1: ='Interest Rate Comparison'!B4 -> 0.08 | AA1: =X1/12 -> 0.0066666667 | AB1: r | AJ1: Interest | AK1: ='Interest Rate Comparison'!B5 -> 0.0775 | AN1: =AK1/12 -> 0.0064583333 | AO1: r | AW1: Interest | AX1: ='Interest Rate Comparison'!B6 -> 0.075 | BA1: =AX1/12 -> 0.00625 | BB1: r | BJ1: Interest | BK1: ='Interest Rate Comparison'!B7 -> 0.0725 | BN1: =BK1/12 -> 0.0060416667 | BO1: r | BW1: Interest | BX1: ='Interest Rate Comparison'!B8 -> 0.07 | CA1: =BX1/12 -> 0.0058333333 | CB1: r
J2: Term | K2: =$L$2*12 -> 360 | L2: ='STR Calculator'!I9 -> 30 | M2: years | N2: =(1+N1)^K2 -> 11.781506 | O2: (1+r)^n | W2: Term | X2: =$L$2*12 -> 360 | Y2: 30 | Z2: years | AA2: =(1+AA1)^X2 -> 10.93573 | AB2: (1+r)^n | AJ2: Term | AK2: =$L$2*12 -> 360 | AL2: 30 | AM2: years | AN2: =(1+AN1)^AK2 -> 10.150514 | AO2: (1+r)^n | AW2: Term | AX2: =$L$2*12 -> 360 | AY2: 30 | AZ2: years | BA2: =(1+BA1)^AX2 -> 9.4215339 | BB2: (1+r)^n | BJ2: Term | BK2: =$L$2*12 -> 360 | BL2: 30 | BM2: years | BN2: =(1+BN1)^BK2 -> 8.744772 | BO2: (1+r)^n | BW2: Term | BX2: =$L$2*12 -> 360 | BY2: 30 | BZ2: years | CA2: =(1+CA1)^BX2 -> 8.1164975 | CB2: (1+r)^n
A3: Original Purchase Price | B3: ='STR Calculator'!B5 -> 800000 | C3: =B3/B1 -> #DIV/0! | D3: sqft | J3: Monthly Payment | W3: Monthly Payment | AJ3: Monthly Payment | AW3: Monthly Payment | BJ3: Monthly Payment | BW3: Monthly Payment
A4: Down Payment | B4: 0.15
A5: Current Loan Balance | B5: =B3-(B3*B4) -> 680000 | C5: as of 11/13/22 | J5: paymentNumber | K5: paymentDate | L5: startingBalance | M5: Monthly Payment | N5: principalPayment | O5: Principle Pay Down | P5: interestPayment | Q5: Interest Percent | R5: cumulativePrincipal | S5: cumulativeInterest | T5: endingBalance | U5: Total Paid End of Loan | W5: paymentNumber | X5: paymentDate | Y5: startingBalance | Z5: Monthly Payment | AA5: principalPayment | AB5: Principle Pay Down | AC5: interestPayment | AD5: Interest Percent | AE5: cumulativePrincipal | AF5: cumulativeInterest | AG5: endingBalance | AH5: Total Paid End of Loan | AJ5: paymentNumber | AK5: paymentDate | AL5: startingBalance | AM5: Monthly Payment | AN5: principalPayment | AO5: Principle Pay Down | AP5: interestPayment | AQ5: Interest Percent | AR5: cumulativePrincipal | AS5: cumulativeInterest | AT5: endingBalance | AU5: Total Paid End of Loan | AW5: paymentNumber | AX5: paymentDate | AY5: startingBalance | AZ5: Monthly Payment | BA5: principalPayment | BB5: Principle Pay Down | BC5: interestPayment | BD5: Interest Percent | BE5: cumulativePrincipal | BF5: cumulativeInterest | BG5: endingBalance | BH5: Total Paid End of Loan | BJ5: paymentNumber | BK5: paymentDate | BL5: startingBalance | BM5: Monthly Payment | BN5: principalPayment | BO5: Principle Pay Down | BP5: interestPayment | BQ5: Interest Percent | BR5: cumulativePrincipal | BS5: cumulativeInterest | BT5: endingBalance | BU5: Total Paid End of Loan | BW5: paymentNumber | BX5: paymentDate | BY5: startingBalance | BZ5: Monthly Payment | CA5: principalPayment | CB5: Principle Pay Down | CC5: interestPayment | CD5: Interest Percent | CE5: cumulativePrincipal | CF5: cumulativeInterest | CG5: endingBalance | CH5: Total Paid End of Loan
A6: Current Equity | B6: =B3-B5 -> 120000 | J6: 1 | K6: 44866 | L6: ='Amoritization Scenario 15% DP'!$B$5 -> 680000 | M6: =$L$6/((($N$2)-1)/($N$1*$N$2)) -> 5108.6129 | N6: =M6-P6 -> 433.61291 | O6: =(N6/L6)*12 -> 0.0076519925 | P6: =L6*($K$1/12) -> 4675 | Q6: =(P6/L6)*12 -> 0.0825 | R6: =N6 -> 433.61291 | S6: =P6 -> 4675 | T6: =L6-N6 -> 679566.39 | U6: =R6+S6 -> 5108.6129 | W6: 1 | X6: 44866 | Y6: ='Amoritization Scenario 15% DP'!$B$5 -> 680000 | Z6: =$Y$6/((($AA$2)-1)/($AA$1*$AA$2)) -> 4989.5991 | AA6: =Z6-AC6 -> 456.26577 | AB6: =(AA6/Y6)*12 -> 0.0080517489 | AC6: =Y6*($X$1/12) -> 4533.3333 | AD6: =(AC6/Y6)*12 -> 0.08 | AE6: =AA6 -> 456.26577 | AF6: =AC6 -> 4533.3333 | AG6: =Y6-AA6 -> 679543.73 | AH6: =AE6+AF6 -> 4989.5991 | AJ6: 1 | AK6: 44866 | AL6: ='Amoritization Scenario 15% DP'!$B$5 -> 680000 | AM6: =$AL$6/((($AN$2)-1)/($AN$1*$AN$2)) -> 4871.6033 | AN6: =AM6-AP6 -> 479.9366 | AO6: =(AN6/AL6)*12 -> 0.0084694695 | AP6: =AL6*($AK$1/12) -> 4391.6667 | AQ6: =(AP6/AL6)*12 -> 0.0775 | AR6: =AN6 -> 479.9366 | AS6: =AP6 -> 4391.6667 | AT6: =AL6-AN6 -> 679520.06 | AU6: =AR6+AS6 -> 4871.6033 | AW6: 1 | AX6: 44866 | AY6: ='Amoritization Scenario 15% DP'!$B$5 -> 680000 | AZ6: =$AY$6/((($BA$2)-1)/($BA$1*$BA$2)) -> 4754.6587 | BA6: =AZ6-BC6 -> 504.65866 | BB6: =(BA6/AY6)*12 -> 0.008905741 | BC6: =AY6*($AX$1/12) -> 4250 | BD6: =(BC6/AY6)*12 -> 0.075 | BE6: =BA6 -> 504.65866 | BF6: =BC6 -> 4250 | BG6: =AY6-BA6 -> 679495.34 | BH6: =BE6+BF6 -> 4754.6587 | BJ6: 1 | BK6: 44866 | BL6: ='Amoritization Scenario 15% DP'!$B$5 -> 680000 | BM6: =$BL$6/((($BN$2)-1)/($BN$1*$BN$2)) -> 4638.7987 | BN6: =BM6-BP6 -> 530.46537 | BO6: =(BN6/BL6)*12 -> 0.0093611536 | BP6: =BL6*($BK$1/12) -> 4108.3333 | BQ6: =(BP6/BL6)*12 -> 0.0725 | BR6: =BN6 -> 530.46537 | BS6: =BP6 -> 4108.3333 | BT6: =BL6-BN6 -> 679469.53 | BU6: =BR6+BS6 -> 4638.7987 | BW6: 1 | BX6: 44866 | BY6: ='Amoritization Scenario 15% DP'!$B$5 -> 680000 | BZ6: =$BY$6/((($CA$2)-1)/($CA$1*$CA$2)) -> 4524.057 | CA6: =BZ6-CC6 -> 557.3903 | CB6: =(CA6/BY6)*12 -> 0.0098362994 | CC6: =BY6*($BX$1/12) -> 3966.6667 | CD6: =(CC6/BY6)*12 -> 0.07 | CE6: =CA6 -> 557.3903 | CF6: =CC6 -> 3966.6667 | CG6: =BY6-CA6 -> 679442.61 | CH6: =CE6+CF6 -> 4524.057
J7: 2 | K7: 44896 | L7: =T6 -> 679566.39 | M7: =$L$6/((($N$2)-1)/($N$1*$N$2)) -> 5108.6129 | N7: =M7-P7 -> 436.594 | O7: =(N7/L7)*12 -> 0.007709516 | P7: =L7*($K$1/12) -> 4672.0189 | Q7: =(P7/L7)*12 -> 0.0825 | R7: =R6+N7 -> 870.2069 | S7: =S6+P7 -> 9347.0189 | T7: =L7-N7 -> 679129.79 | U7: =R7+S7 -> 10217.226 | W7: 2 | X7: 44896 | Y7: =AG6 -> 679543.73 | Z7: =Z6 -> 4989.5991 | AA7: =Z7-AC7 -> 459.30754 | AB7: =(AA7/Y7)*12 -> 0.0081108694 | AC7: =Y7*($X$1/12) -> 4530.2916 | AD7: =(AC7/Y7)*12 -> 0.08 | AE7: =AE6+AA7 -> 915.57331 | AF7: =AF6+AC7 -> 9063.6249 | AG7: =Y7-AA7 -> 679084.43 | AH7: =AE7+AF7 -> 9979.1982 | AJ7: 2 | AK7: 44896 | AL7: =AT6 -> 679520.06 | AM7: =AM6 -> 4871.6033 | AN7: =AM7-AP7 -> 483.03619 | AO7: =(AN7/AL7)*12 -> 0.0085301886 | AP7: =AL7*($AK$1/12) -> 4388.5671 | AQ7: =(AP7/AL7)*12 -> 0.0775 | AR7: =AR6+AN7 -> 962.9728 | AS7: =AS6+AP7 -> 8780.2337 | AT7: =AL7-AN7 -> 679037.03 | AU7: =AR7+AS7 -> 9743.2065 | AW7: 2 | AX7: 44896 | AY7: =BG6 -> 679495.34 | AZ7: =AZ6 -> 4754.6587 | BA7: =AZ7-BC7 -> 507.81277 | BB7: =(BA7/AY7)*12 -> 0.0089680575 | BC7: =AY7*($AX$1/12) -> 4246.8459 | BD7: =(BC7/AY7)*12 -> 0.075 | BE7: =BE6+BA7 -> 1012.4714 | BF7: =BF6+BC7 -> 8496.8459 | BG7: =AY7-BA7 -> 678987.53 | BH7: =BE7+BF7 -> 9509.3173 | BJ7: 2 | BK7: 44896 | BL7: =BT6 -> 679469.53 | BM7: =BM6 -> 4638.7987 | BN7: =BM7-BP7 -> 533.67027 | BO7: =(BN7/BL7)*12 -> 0.009425063 | BP7: =BL7*($BK$1/12) -> 4105.1284 | BQ7: =(BP7/BL7)*12 -> 0.0725 | BR7: =BR6+BN7 -> 1064.1356 | BS7: =BS6+BP7 -> 8213.4618 | BT7: =BL7-BN7 -> 678935.86 | BU7: =BR7+BS7 -> 9277.5974 | BW7: 2 | BX7: 44896 | BY7: =CG6 -> 679442.61 | BZ7: =BZ6 -> 4524.057 | CA7: =BZ7-CC7 -> 560.64174 | CB7: =(CA7/BY7)*12 -> 0.0099017943 | CC7: =BY7*($BX$1/12) -> 3963.4152 | CD7: =(CC7/BY7)*12 -> 0.07 | CE7: =CE6+CA7 -> 1118.032 | CF7: =CF6+CC7 -> 7930.0819 | CG7: =BY7-CA7 -> 678881.97 | CH7: =CE7+CF7 -> 9048.1139
A8: Year | B8: ="Cum Interest @ "&K1&"%" -> Cum Interest @ 0.0825% | C8: ="Cum Interest @ "&X1&"%" -> Cum Interest @ 0.08% | D8: ="Cum Interest @ "&AK1&"%" -> Cum Interest @ 0.0775% | E8: ="Cum Interest @ "&AX1&"%" -> Cum Interest @ 0.075% | F8: ="Cum Interest @ "&BK1&"%" -> Cum Interest @ 0.0725% | G8: ="Cum Interest @ "&BX1&"%" -> Cum Interest @ 0.07% | J8: 3 | K8: 44927 | L8: =T7 -> 679129.79 | M8: =$L$6/((($N$2)-1)/($N$1*$N$2)) -> 5108.6129 | N8: =M8-P8 -> 439.59558 | O8: =(N8/L8)*12 -> 0.0077675093 | P8: =L8*($K$1/12) -> 4669.0173 | Q8: =(P8/L8)*12 -> 0.0825 | R8: =R7+N8 -> 1309.8025 | S8: =S7+P8 -> 14016.036 | T8: =L8-N8 -> 678690.2 | U8: =R8+S8 -> 15325.839 | W8: 3 | X8: 44927 | Y8: =AG7 -> 679084.43 | Z8: =Z7 -> 4989.5991 | AA8: =Z8-AC8 -> 462.36959 | AB8: =(AA8/Y8)*12 -> 0.0081704643 | AC8: =Y8*($X$1/12) -> 4527.2295 | AD8: =(AC8/Y8)*12 -> 0.08 | AE8: =AE7+AA8 -> 1377.9429 | AF8: =AF7+AC8 -> 13590.854 | AG8: =Y8-AA8 -> 678622.06 | AH8: =AE8+AF8 -> 14968.797 | AJ8: 3 | AK8: 44927 | AL8: =AT7 -> 679037.03 | AM8: =AM7 -> 4871.6033 | AN8: =AM8-AP8 -> 486.1558 | AO8: =(AN8/AL8)*12 -> 0.0085913866 | AP8: =AL8*($AK$1/12) -> 4385.4475 | AQ8: =(AP8/AL8)*12 -> 0.0775 | AR8: =AR7+AN8 -> 1449.1286 | AS8: =AS7+AP8 -> 13165.681 | AT8: =AL8-AN8 -> 678550.87 | AU8: =AR8+AS8 -> 14614.81 | AW8: 3 | AX8: 44927 | AY8: =BG7 -> 678987.53 | AZ8: =AZ7 -> 4754.6587 | BA8: =AZ8-BC8 -> 510.9866 | BB8: =(BA8/AY8)*12 -> 0.009030857 | BC8: =AY8*($AX$1/12) -> 4243.6721 | BD8: =(BC8/AY8)*12 -> 0.075 | BE8: =BE7+BA8 -> 1523.458 | BF8: =BF7+BC8 -> 12740.518 | BG8: =AY8-BA8 -> 678476.54 | BH8: =BE8+BF8 -> 14263.976 | BJ8: 3 | BK8: 44927 | BL8: =BT7 -> 678935.86 | BM8: =BM7 -> 4638.7987 | BN8: =BM8-BP8 -> 536.89452 | BO8: =(BN8/BL8)*12 -> 0.0094894594 | BP8: =BL8*($BK$1/12) -> 4101.9042 | BQ8: =(BP8/BL8)*12 -> 0.0725 | BR8: =BR7+BN8 -> 1601.0302 | BS8: =BS7+BP8 -> 12315.366 | BT8: =BL8-BN8 -> 678398.97 | BU8: =BR8+BS8 -> 13916.396 | BW8: 3 | BX8: 44927 | BY8: =CG7 -> 678881.97 | BZ8: =BZ7 -> 4524.057 | CA8: =BZ8-CC8 -> 563.91215 | CB8: =(CA8/BY8)*12 -> 0.0099677796 | CC8: =BY8*($BX$1/12) -> 3960.1448 | CD8: =(CC8/BY8)*12 -> 0.07 | CE8: =CE7+CA8 -> 1681.9442 | CF8: =CF7+CC8 -> 11890.227 | CG8: =BY8-CA8 -> 678318.06 | CH8: =CE8+CF8 -> 13572.171
A9: 1 | B9: =VLOOKUP($A$9*12,$J$5:$U$365,10) -> 55898.669 | C9: =VLOOKUP(A9*12,$W$5:$AH$365,10) -> 54194.714 | D9: =VLOOKUP(A9*12,$AJ$5:$AU$365,10) -> 52490.958 | E9: =VLOOKUP(A9*12,$AW$5:$BH$365,10) -> 50787.43 | F9: =VLOOKUP(A9*12,$BJ$5:$BU$365,10) -> 49084.159 | G9: =VLOOKUP(A9*12,$BW$5:$CH$365,10) -> 47381.177 | J9: 4 | K9: 44958 | L9: =T8 -> 678690.2 | M9: =$L$6/((($N$2)-1)/($N$1*$N$2)) -> 5108.6129 | N9: =M9-P9 -> 442.6178 | O9: =(N9/L9)*12 -> 0.0078259766 | P9: =L9*($K$1/12) -> 4665.9951 | Q9: =(P9/L9)*12 -> 0.0825 | R9: =R8+N9 -> 1752.4203 | S9: =S8+P9 -> 18682.031 | T9: =L9-N9 -> 678247.58 | U9: =R9+S9 -> 20434.452 | W9: 4 | X9: 44958 | Y9: =AG8 -> 678622.06 | Z9: =Z8 -> 4989.5991 | AA9: =Z9-AC9 -> 465.45206 | AB9: =(AA9/Y9)*12 -> 0.008230538 | AC9: =Y9*($X$1/12) -> 4524.147 | AD9: =(AC9/Y9)*12 -> 0.08 | AE9: =AE8+AA9 -> 1843.395 | AF9: =AF8+AC9 -> 18115.001 | AG9: =Y9-AA9 -> 678156.61 | AH9: =AE9+AF9 -> 19958.396 | AJ9: 4 | AK9: 44958 | AL9: =AT8 -> 678550.87 | AM9: =AM8 -> 4871.6033 | AN9: =AM9-AP9 -> 489.29556 | AO9: =(AN9/AL9)*12 -> 0.0086530678 | AP9: =AL9*($AK$1/12) -> 4382.3077 | AQ9: =(AP9/AL9)*12 -> 0.0775 | AR9: =AR8+AN9 -> 1938.4242 | AS9: =AS8+AP9 -> 17547.989 | AT9: =AL9-AN9 -> 678061.58 | AU9: =AR9+AS9 -> 19486.413 | AW9: 4 | AX9: 44958 | AY9: =BG8 -> 678476.54 | AZ9: =AZ8 -> 4754.6587 | BA9: =AZ9-BC9 -> 514.18027 | BB9: =(BA9/AY9)*12 -> 0.0090941438 | BC9: =AY9*($AX$1/12) -> 4240.4784 | BD9: =(BC9/AY9)*12 -> 0.075 | BE9: =BE8+BA9 -> 2037.6383 | BF9: =BF8+BC9 -> 16980.996 | BG9: =AY9-BA9 -> 677962.36 | BH9: =BE9+BF9 -> 19018.635 | BJ9: 4 | BK9: 44958 | BL9: =BT8 -> 678398.97 | BM9: =BM8 -> 4638.7987 | BN9: =BM9-BP9 -> 540.13826 | BO9: =(BN9/BL9)*12 -> 0.009554347 | BP9: =BL9*($BK$1/12) -> 4098.6604 | BQ9: =(BP9/BL9)*12 -> 0.0725 | BR9: =BR8+BN9 -> 2141.1684 | BS9: =BS8+BP9 -> 16414.026 | BT9: =BL9-BN9 -> 677858.83 | BU9: =BR9+BS9 -> 18555.195 | BW9: 4 | BX9: 44958 | BY9: =CG8 -> 678318.06 | BZ9: =BZ8 -> 4524.057 | CA9: =BZ9-CC9 -> 567.20164 | CB9: =(CA9/BY9)*12 -> 0.01003426 | CC9: =BY9*($BX$1/12) -> 3956.8553 | CD9: =(CC9/BY9)*12 -> 0.07 | CE9: =CE8+CA9 -> 2249.1458 | CF9: =CF8+CC9 -> 15847.082 | CG9: =BY9-CA9 -> 677750.85 | CH9: =CE9+CF9 -> 18096.228
A10: =A9+1 -> 2 | B10: =VLOOKUP(A10*12,$J$5:$U$365,10) -> 111334.2 | C10: =VLOOKUP(A10*12,$W$5:$AH$365,10) -> 107917.95 | D10: =VLOOKUP(A10*12,$AJ$5:$AU$365,10) -> 104502.59 | E10: =VLOOKUP(A10*12,$AW$5:$BH$365,10) -> 101088.22 | F10: =VLOOKUP(A10*12,$BJ$5:$BU$365,10) -> 97674.985 | G10: =VLOOKUP(A10*12,$BW$5:$CH$365,10) -> 94263.009 | J10: 5 | K10: 44986 | L10: =T9 -> 678247.58 | M10: =$L$6/((($N$2)-1)/($N$1*$N$2)) -> 5108.6129 | N10: =M10-P10 -> 445.6608 | O10: =(N10/L10)*12 -> 0.0078849224 | P10: =L10*($K$1/12) -> 4662.9521 | Q10: =(P10/L10)*12 -> 0.0825 | R10: =R9+N10 -> 2198.0811 | S10: =S9+P10 -> 23344.983 | T10: =L10-N10 -> 677801.92 | U10: =R10+S10 -> 25543.065 | W10: 5 | X10: 44986 | Y10: =AG9 -> 678156.61 | Z10: =Z9 -> 4989.5991 | AA10: =Z10-AC10 -> 468.55507 | AB10: =(AA10/Y10)*12 -> 0.008291095 | AC10: =Y10*($X$1/12) -> 4521.044 | AD10: =(AC10/Y10)*12 -> 0.08 | AE10: =AE9+AA10 -> 2311.95 | AF10: =AF9+AC10 -> 22636.045 | AG10: =Y10-AA10 -> 677688.05 | AH10: =AE10+AF10 -> 24947.996 | AJ10: 5 | AK10: 44986 | AL10: =AT9 -> 678061.58 | AM10: =AM9 -> 4871.6033 | AN10: =AM10-AP10 -> 492.45559 | AO10: =(AN10/AL10)*12 -> 0.0087152367 | AP10: =AL10*($AK$1/12) -> 4379.1477 | AQ10: =(AP10/AL10)*12 -> 0.0775 | AR10: =AR9+AN10 -> 2430.8798 | AS10: =AS9+AP10 -> 21927.137 | AT10: =AL10-AN10 -> 677569.12 | AU10: =AR10+AS10 -> 24358.016 | AW10: 5 | AX10: 44986 | AY10: =BG9 -> 677962.36 | AZ10: =AZ9 -> 4754.6587 | BA10: =AZ10-BC10 -> 517.3939 | BB10: =(BA10/AY10)*12 -> 0.0091579225 | BC10: =AY10*($AX$1/12) -> 4237.2648 | BD10: =(BC10/AY10)*12 -> 0.075 | BE10: =BE9+BA10 -> 2555.0322 | BF10: =BF9+BC10 -> 21218.261 | BG10: =AY10-BA10 -> 677444.97 | BH10: =BE10+BF10 -> 23773.293 | BJ10: 5 | BK10: 44986 | BL10: =BT9 -> 677858.83 | BM10: =BM9 -> 4638.7987 | BN10: =BM10-BP10 -> 543.4016 | BO10: =(BN10/BL10)*12 -> 0.0096197303 | BP10: =BL10*($BK$1/12) -> 4095.3971 | BQ10: =(BP10/BL10)*12 -> 0.0725 | BR10: =BR9+BN10 -> 2684.57 | BS10: =BS9+BP10 -> 20509.424 | BT10: =BL10-BN10 -> 677315.43 | BU10: =BR10+BS10 -> 23193.994 | BW10: 5 | BX10: 44986 | BY10: =CG9 -> 677750.85 | BZ10: =BZ9 -> 4524.057 | CA10: =BZ10-CC10 -> 570.51032 | CB10: =(CA10/BY10)*12 -> 0.01010124 | CC10: =BY10*($BX$1/12) -> 3953.5466 | CD10: =(CC10/BY10)*12 -> 0.07 | CE10: =CE9+CA10 -> 2819.6562 | CF10: =CF9+CC10 -> 19800.629 | CG10: =BY10-CA10 -> 677180.34 | CH10: =CE10+CF10 -> 22620.285
A11: =A10+1 -> 3 | B11: =VLOOKUP(A11*12,$J$5:$U$365,10) -> 166266.9 | C11: =VLOOKUP(A11*12,$W$5:$AH$365,10) -> 161130.58 | D11: =VLOOKUP(A11*12,$AJ$5:$AU$365,10) -> 155996.39 | E11: =VLOOKUP(A11*12,$AW$5:$BH$365,10) -> 150864.6 | F11: =VLOOKUP(A11*12,$BJ$5:$BU$365,10) -> 145735.5 | G11: =VLOOKUP(A11*12,$BW$5:$CH$365,10) -> 140609.4 | J11: 6 | K11: 45017 | L11: =T10 -> 677801.92 | M11: =$L$6/((($N$2)-1)/($N$1*$N$2)) -> 5108.6129 | N11: =M11-P11 -> 448.72471 | O11: =(N11/L11)*12 -> 0.0079443513 | P11: =L11*($K$1/12) -> 4659.8882 | Q11: =(P11/L11)*12 -> 0.0825 | R11: =R10+N11 -> 2646.8058 | S11: =S10+P11 -> 28004.872 | T11: =L11-N11 -> 677353.19 | U11: =R11+S11 -> 30651.677 | W11: 6 | X11: 45017 | Y11: =AG10 -> 677688.05 | Z11: =Z10 -> 4989.5991 | AA11: =Z11-AC11 -> 471.67877 | AB11: =(AA11/Y11)*12 -> 0.0083521396 | AC11: =Y11*($X$1/12) -> 4517.9203 | AD11: =(AC11/Y11)*12 -> 0.08 | AE11: =AE10+AA11 -> 2783.6288 | AF11: =AF10+AC11 -> 27153.966 | AG11: =Y11-AA11 -> 677216.37 | AH11: =AE11+AF11 -> 29937.595 | AJ11: 6 | AK11: 45017 | AL11: =AT10 -> 677569.12 | AM11: =AM10 -> 4871.6033 | AN11: =AM11-AP11 -> 495.63603 | AO11: =(AN11/AL11)*12 -> 0.0087778977 | AP11: =AL11*($AK$1/12) -> 4375.9672 | AQ11: =(AP11/AL11)*12 -> 0.0775 | AR11: =AR10+AN11 -> 2926.5158 | AS11: =AS10+AP11 -> 26303.104 | AT11: =AL11-AN11 -> 677073.48 | AU11: =AR11+AS11 -> 29229.62 | AW11: 6 | AX11: 45017 | AY11: =BG10 -> 677444.97 | AZ11: =AZ10 -> 4754.6587 | BA11: =AZ11-BC11 -> 520.62761 | BB11: =(BA11/AY11)*12 -> 0.0092221975 | BC11: =AY11*($AX$1/12) -> 4234.031 | BD11: =(BC11/AY11)*12 -> 0.075 | BE11: =BE10+BA11 -> 3075.6598 | BF11: =BF10+BC11 -> 25452.292 | BG11: =AY11-BA11 -> 676924.34 | BH11: =BE11+BF11 -> 28527.952 | BJ11: 6 | BK11: 45017 | BL11: =BT10 -> 677315.43 | BM11: =BM10 -> 4638.7987 | BN11: =BM11-BP11 -> 546.68465 | BO11: =(BN11/BL11)*12 -> 0.009685614 | BP11: =BL11*($BK$1/12) -> 4092.1141 | BQ11: =(BP11/BL11)*12 -> 0.0725 | BR11: =BR10+BN11 -> 3231.2547 | BS11: =BS10+BP11 -> 24601.538 | BT11: =BL11-BN11 -> 676768.75 | BU11: =BR11+BS11 -> 27832.792 | BW11: 6 | BX11: 45017 | BY11: =CG10 -> 677180.34 | BZ11: =BZ10 -> 4524.057 | CA11: =BZ11-CC11 -> 573.83829 | CB11: =(CA11/BY11)*12 -> 0.010168723 | CC11: =BY11*($BX$1/12) -> 3950.2187 | CD11: =(CC11/BY11)*12 -> 0.07 | CE11: =CE10+CA11 -> 3393.4945 | CF11: =CF10+CC11 -> 23750.847 | CG11: =BY11-CA11 -> 676606.51 | CH11: =CE11+CF11 -> 27144.342
A12: =A11+1 -> 4 | B12: =VLOOKUP(A12*12,$J$5:$U$365,10) -> 220653.69 | C12: =VLOOKUP(A12*12,$W$5:$AH$365,10) -> 213790.22 | D12: =VLOOKUP(A12*12,$AJ$5:$AU$365,10) -> 206930.77 | E12: =VLOOKUP(A12*12,$AW$5:$BH$365,10) -> 200075.84 | F12: =VLOOKUP(A12*12,$BJ$5:$BU$365,10) -> 193225.95 | G12: =VLOOKUP(A12*12,$BW$5:$CH$365,10) -> 186381.64 | J12: 7 | K12: 45047 | L12: =T11 -> 677353.19 | M12: =$L$6/((($N$2)-1)/($N$1*$N$2)) -> 5108.6129 | N12: =M12-P12 -> 451.8097 | O12: =(N12/L12)*12 -> 0.0080042678 | P12: =L12*($K$1/12) -> 4656.8032 | Q12: =(P12/L12)*12 -> 0.0825 | R12: =R11+N12 -> 3098.6155 | S12: =S11+P12 -> 32661.675 | T12: =L12-N12 -> 676901.38 | U12: =R12+S12 -> 35760.29 | W12: 7 | X12: 45047 | Y12: =AG11 -> 677216.37 | Z12: =Z11 -> 4989.5991 | AA12: =Z12-AC12 -> 474.82329 | AB12: =(AA12/Y12)*12 -> 0.0084136766 | AC12: =Y12*($X$1/12) -> 4514.7758 | AD12: =(AC12/Y12)*12 -> 0.08 | AE12: =AE11+AA12 -> 3258.4521 | AF12: =AF11+AC12 -> 31668.742 | AG12: =Y12-AA12 -> 676741.55 | AH12: =AE12+AF12 -> 34927.194 | AJ12: 7 | AK12: 45047 | AL12: =AT11 -> 677073.48 | AM12: =AM11 -> 4871.6033 | AN12: =AM12-AP12 -> 498.83702 | AO12: =(AN12/AL12)*12 -> 0.0088410554 | AP12: =AL12*($AK$1/12) -> 4372.7663 | AQ12: =(AP12/AL12)*12 -> 0.0775 | AR12: =AR11+AN12 -> 3425.3528 | AS12: =AS11+AP12 -> 30675.87 | AT12: =AL12-AN12 -> 676574.65 | AU12: =AR12+AS12 -> 34101.223 | AW12: 7 | AX12: 45047 | AY12: =BG11 -> 676924.34 | AZ12: =AZ11 -> 4754.6587 | BA12: =AZ12-BC12 -> 523.88153 | BB12: =(BA12/AY12)*12 -> 0.0092869735 | BC12: =AY12*($AX$1/12) -> 4230.7771 | BD12: =(BC12/AY12)*12 -> 0.075 | BE12: =BE11+BA12 -> 3599.5413 | BF12: =BF11+BC12 -> 29683.069 | BG12: =AY12-BA12 -> 676400.46 | BH12: =BE12+BF12 -> 33282.611 | BJ12: 7 | BK12: 45047 | BL12: =BT11 -> 676768.75 | BM12: =BM11 -> 4638.7987 | BN12: =BM12-BP12 -> 549.98753 | BO12: =(BN12/BL12)*12 -> 0.0097520024 | BP12: =BL12*($BK$1/12) -> 4088.8112 | BQ12: =(BP12/BL12)*12 -> 0.0725 | BR12: =BR11+BN12 -> 3781.2422 | BS12: =BS11+BP12 -> 28690.349 | BT12: =BL12-BN12 -> 676218.76 | BU12: =BR12+BS12 -> 32471.591 | BW12: 7 | BX12: 45047 | BY12: =CG11 -> 676606.51 | BZ12: =BZ11 -> 4524.057 | CA12: =BZ12-CC12 -> 577.18568 | CB12: =(CA12/BY12)*12 -> 0.010236715 | CC12: =BY12*($BX$1/12) -> 3946.8713 | CD12: =(CC12/BY12)*12 -> 0.07 | CE12: =CE11+CA12 -> 3970.6801 | CF12: =CF11+CC12 -> 27697.719 | CG12: =BY12-CA12 -> 676029.32 | CH12: =CE12+CF12 -> 31668.399
A13: =A12+1 -> 5 | B13: =VLOOKUP(A13*12,$J$5:$U$365,10) -> 274447.78 | C13: =VLOOKUP(A13*12,$W$5:$AH$365,10) -> 265850.97 | D13: =VLOOKUP(A13*12,$AJ$5:$AU$365,10) -> 257260.81 | E13: =VLOOKUP(A13*12,$AW$5:$BH$365,10) -> 248678.09 | F13: =VLOOKUP(A13*12,$BJ$5:$BU$365,10) -> 240103.61 | G13: =VLOOKUP(A13*12,$BW$5:$CH$365,10) -> 231538.23 | J13: 8 | K13: 45078 | L13: =T12 -> 676901.38 | M13: =$L$6/((($N$2)-1)/($N$1*$N$2)) -> 5108.6129 | N13: =M13-P13 -> 454.91589 | O13: =(N13/L13)*12 -> 0.0080646765 | P13: =L13*($K$1/12) -> 4653.697 | Q13: =(P13/L13)*12 -> 0.0825 | R13: =R12+N13 -> 3553.5314 | S13: =S12+P13 -> 37315.372 | T13: =L13-N13 -> 676446.47 | U13: =R13+S13 -> 40868.903 | W13: 8 | X13: 45078 | Y13: =AG12 -> 676741.55 | Z13: =Z12 -> 4989.5991 | AA13: =Z13-AC13 -> 477.98878 | AB13: =(AA13/Y13)*12 -> 0.0084757104 | AC13: =Y13*($X$1/12) -> 4511.6103 | AD13: =(AC13/Y13)*12 -> 0.08 | AE13: =AE12+AA13 -> 3736.4409 | AF13: =AF12+AC13 -> 36180.352 | AG13: =Y13-AA13 -> 676263.56 | AH13: =AE13+AF13 -> 39916.793 | AJ13: 8 | AK13: 45078 | AL13: =AT12 -> 676574.65 | AM13: =AM12 -> 4871.6033 | AN13: =AM13-AP13 -> 502.05867 | AO13: =(AN13/AL13)*12 -> 0.0089047145 | AP13: =AL13*($AK$1/12) -> 4369.5446 | AQ13: =(AP13/AL13)*12 -> 0.0775 | AR13: =AR12+AN13 -> 3927.4115 | AS13: =AS12+AP13 -> 35045.415 | AT13: =AL13-AN13 -> 676072.59 | AU13: =AR13+AS13 -> 38972.826 | AW13: 8 | AX13: 45078 | AY13: =BG12 -> 676400.46 | AZ13: =AZ12 -> 4754.6587 | BA13: =AZ13-BC13 -> 527.15579 | BB13: =(BA13/AY13)*12 -> 0.0093522549 | BC13: =AY13*($AX$1/12) -> 4227.5029 | BD13: =(BC13/AY13)*12 -> 0.075 | BE13: =BE12+BA13 -> 4126.6971 | BF13: =BF12+BC13 -> 33910.572 | BG13: =AY13-BA13 -> 675873.3 | BH13: =BE13+BF13 -> 38037.269 | BJ13: 8 | BK13: 45078 | BL13: =BT12 -> 676218.76 | BM13: =BM12 -> 4638.7987 | BN13: =BM13-BP13 -> 553.31038 | BO13: =(BN13/BL13)*12 -> 0.0098189002 | BP13: =BL13*($BK$1/12) -> 4085.4883 | BQ13: =(BP13/BL13)*12 -> 0.0725 | BR13: =BR12+BN13 -> 4334.5526 | BS13: =BS12+BP13 -> 32775.837 | BT13: =BL13-BN13 -> 675665.45 | BU13: =BR13+BS13 -> 37110.39 | BW13: 8 | BX13: 45078 | BY13: =CG12 -> 676029.32 | BZ13: =BZ12 -> 4524.057 | CA13: =BZ13-CC13 -> 580.5526 | CB13: =(CA13/BY13)*12 -> 0.010305221 | CC13: =BY13*($BX$1/12) -> 3943.5044 | CD13: =(CC13/BY13)*12 -> 0.07 | CE13: =CE12+CA13 -> 4551.2327 | CF13: =CF12+CC13 -> 31641.223 | CG13: =BY13-CA13 -> 675448.77 | CH13: =CE13+CF13 -> 36192.456
A14: =A13+1 -> 6 | B14: =VLOOKUP(A14*12,$J$5:$U$365,10) -> 327598.39 | C14: =VLOOKUP(A14*12,$W$5:$AH$365,10) -> 317263.13 | D14: =VLOOKUP(A14*12,$AJ$5:$AU$365,10) -> 306937.98 | E14: =VLOOKUP(A14*12,$AW$5:$BH$365,10) -> 296624.05 | F14: =VLOOKUP(A14*12,$BJ$5:$BU$365,10) -> 286322.54 | G14: =VLOOKUP(A14*12,$BW$5:$CH$365,10) -> 276034.66 | J14: 9 | K14: 45108 | L14: =T13 -> 676446.47 | M14: =$L$6/((($N$2)-1)/($N$1*$N$2)) -> 5108.6129 | N14: =M14-P14 -> 458.04344 | O14: =(N14/L14)*12 -> 0.008125582 | P14: =L14*($K$1/12) -> 4650.5695 | Q14: =(P14/L14)*12 -> 0.0825 | R14: =R13+N14 -> 4011.5748 | S14: =S13+P14 -> 41965.941 | T14: =L14-N14 -> 675988.43 | U14: =R14+S14 -> 45977.516 | W14: 9 | X14: 45108 | Y14: =AG13 -> 676263.56 | Z14: =Z13 -> 4989.5991 | AA14: =Z14-AC14 -> 481.17537 | AB14: =(AA14/Y14)*12 -> 0.0085382458 | AC14: =Y14*($X$1/12) -> 4508.4237 | AD14: =(AC14/Y14)*12 -> 0.08 | AE14: =AE13+AA14 -> 4217.6162 | AF14: =AF13+AC14 -> 40688.776 | AG14: =Y14-AA14 -> 675782.38 | AH14: =AE14+AF14 -> 44906.392 | AJ14: 9 | AK14: 45108 | AL14: =AT13 -> 676072.59 | AM14: =AM13 -> 4871.6033 | AN14: =AM14-AP14 -> 505.30114 | AO14: =(AN14/AL14)*12 -> 0.0089688796 | AP14: =AL14*($AK$1/12) -> 4366.3021 | AQ14: =(AP14/AL14)*12 -> 0.0775 | AR14: =AR13+AN14 -> 4432.7126 | AS14: =AS13+AP14 -> 39411.717 | AT14: =AL14-AN14 -> 675567.29 | AU14: =AR14+AS14 -> 43844.429 | AW14: 9 | AX14: 45108 | AY14: =BG13 -> 675873.3 | AZ14: =AZ13 -> 4754.6587 | BA14: =AZ14-BC14 -> 530.45052 | BB14: =(BA14/AY14)*12 -> 0.0094180465 | BC14: =AY14*($AX$1/12) -> 4224.2081 | BD14: =(BC14/AY14)*12 -> 0.075 | BE14: =BE13+BA14 -> 4657.1477 | BF14: =BF13+BC14 -> 38134.78 | BG14: =AY14-BA14 -> 675342.85 | BH14: =BE14+BF14 -> 42791.928 | BJ14: 9 | BK14: 45108 | BL14: =BT13 -> 675665.45 | BM14: =BM13 -> 4638.7987 | BN14: =BM14-BP14 -> 556.65329 | BO14: =(BN14/BL14)*12 -> 0.0098863121 | BP14: =BL14*($BK$1/12) -> 4082.1454 | BQ14: =(BP14/BL14)*12 -> 0.0725 | BR14: =BR13+BN14 -> 4891.2059 | BS14: =BS13+BP14 -> 36857.982 | BT14: =BL14-BN14 -> 675108.79 | BU14: =BR14+BS14 -> 41749.188 | BW14: 9 | BX14: 45108 | BY14: =CG13 -> 675448.77 | BZ14: =BZ13 -> 4524.057 | CA14: =BZ14-CC14 -> 583.93916 | CB14: =(CA14/BY14)*12 -> 0.010374243 | CC14: =BY14*($BX$1/12) -> 3940.1178 | CD14: =(CC14/BY14)*12 -> 0.07 | CE14: =CE13+CA14 -> 5135.1719 | CF14: =CF13+CC14 -> 35581.341 | CG14: =BY14-CA14 -> 674864.83 | CH14: =CE14+CF14 -> 40716.513
A15: =A14+1 -> 7 | B15: =VLOOKUP(A15*12,$J$5:$U$365,10) -> 380050.37 | C15: =VLOOKUP(A15*12,$W$5:$AH$365,10) -> 367972.86 | D15: =VLOOKUP(A15*12,$AJ$5:$AU$365,10) -> 355909.82 | E15: =VLOOKUP(A15*12,$AW$5:$BH$365,10) -> 343862.79 | F15: =VLOOKUP(A15*12,$BJ$5:$BU$365,10) -> 331833.36 | G15: =VLOOKUP(A15*12,$BW$5:$CH$365,10) -> 319823.2 | J15: 10 | K15: 45139 | L15: =T14 -> 675988.43 | M15: =$L$6/((($N$2)-1)/($N$1*$N$2)) -> 5108.6129 | N15: =M15-P15 -> 461.19248 | O15: =(N15/L15)*12 -> 0.008186989 | P15: =L15*($K$1/12) -> 4647.4204 | Q15: =(P15/L15)*12 -> 0.0825 | R15: =R14+N15 -> 4472.7673 | S15: =S14+P15 -> 46613.362 | T15: =L15-N15 -> 675527.23 | U15: =R15+S15 -> 51086.129 | W15: 10 | X15: 45139 | Y15: =AG14 -> 675782.38 | Z15: =Z14 -> 4989.5991 | AA15: =Z15-AC15 -> 484.38321 | AB15: =(AA15/Y15)*12 -> 0.0086012874 | AC15: =Y15*($X$1/12) -> 4505.2159 | AD15: =(AC15/Y15)*12 -> 0.08 | AE15: =AE14+AA15 -> 4701.9995 | AF15: =AF14+AC15 -> 45193.992 | AG15: =Y15-AA15 -> 675298 | AH15: =AE15+AF15 -> 49895.991 | AJ15: 10 | AK15: 45139 | AL15: =AT14 -> 675567.29 | AM15: =AM14 -> 4871.6033 | AN15: =AM15-AP15 -> 508.56454 | AO15: =(AN15/AL15)*12 -> 0.0090335553 | AP15: =AL15*($AK$1/12) -> 4363.0387 | AQ15: =(AP15/AL15)*12 -> 0.0775 | AR15: =AR14+AN15 -> 4941.2772 | AS15: =AS14+AP15 -> 43774.756 | AT15: =AL15-AN15 -> 675058.72 | AU15: =AR15+AS15 -> 48716.033 | AW15: 10 | AX15: 45139 | AY15: =BG14 -> 675342.85 | AZ15: =AZ14 -> 4754.6587 | BA15: =AZ15-BC15 -> 533.76583 | BB15: =(BA15/AY15)*12 -> 0.0094843529 | BC15: =AY15*($AX$1/12) -> 4220.8928 | BD15: =(BC15/AY15)*12 -> 0.075 | BE15: =BE14+BA15 -> 5190.9135 | BF15: =BF14+BC15 -> 42355.673 | BG15: =AY15-BA15 -> 674809.09 | BH15: =BE15+BF15 -> 47546.587 | BJ15: 10 | BK15: 45139 | BL15: =BT14 -> 675108.79 | BM15: =BM14 -> 4638.7987 | BN15: =BM15-BP15 -> 560.01641 | BO15: =(BN15/BL15)*12 -> 0.0099542428 | BP15: =BL15*($BK$1/12) -> 4078.7823 | BQ15: =(BP15/BL15)*12 -> 0.0725 | BR15: =BR14+BN15 -> 5451.2223 | BS15: =BS14+BP15 -> 40936.765 | BT15: =BL15-BN15 -> 674548.78 | BU15: =BR15+BS15 -> 46387.987 | BW15: 10 | BX15: 45139 | BY15: =CG14 -> 674864.83 | BZ15: =BZ14 -> 4524.057 | CA15: =BZ15-CC15 -> 587.34547 | CB15: =(CA15/BY15)*12 -> 0.010443789 | CC15: =BY15*($BX$1/12) -> 3936.7115 | CD15: =(CC15/BY15)*12 -> 0.07 | CE15: =CE14+CA15 -> 5722.5174 | CF15: =CF14+CC15 -> 39518.052 | CG15: =BY15-CA15 -> 674277.48 | CH15: =CE15+CF15 -> 45240.57
A16: =A15+1 -> 8 | B16: =VLOOKUP(A16*12,$J$5:$U$365,10) -> 431743.86 | C16: =VLOOKUP(A16*12,$W$5:$AH$365,10) -> 417921.86 | D16: =VLOOKUP(A16*12,$AJ$5:$AU$365,10) -> 404119.71 | E16: =VLOOKUP(A16*12,$AW$5:$BH$365,10) -> 390339.4 | F16: =VLOOKUP(A16*12,$BJ$5:$BU$365,10) -> 376583 | G16: =VLOOKUP(A16*12,$BW$5:$CH$365,10) -> 362852.69 | J16: 11 | K16: 45170 | L16: =T15 -> 675527.23 | M16: =$L$6/((($N$2)-1)/($N$1*$N$2)) -> 5108.6129 | N16: =M16-P16 -> 464.36318 | O16: =(N16/L16)*12 -> 0.0082489024 | P16: =L16*($K$1/12) -> 4644.2497 | Q16: =(P16/L16)*12 -> 0.0825 | R16: =R15+N16 -> 4937.1305 | S16: =S15+P16 -> 51257.611 | T16: =L16-N16 -> 675062.87 | U16: =R16+S16 -> 56194.742 | W16: 11 | X16: 45170 | Y16: =AG15 -> 675298 | Z16: =Z15 -> 4989.5991 | AA16: =Z16-AC16 -> 487.61243 | AB16: =(AA16/Y16)*12 -> 0.0086648401 | AC16: =Y16*($X$1/12) -> 4501.9867 | AD16: =(AC16/Y16)*12 -> 0.08 | AE16: =AE15+AA16 -> 5189.6119 | AF16: =AF15+AC16 -> 49695.978 | AG16: =Y16-AA16 -> 674810.39 | AH16: =AE16+AF16 -> 54885.59 | AJ16: 11 | AK16: 45170 | AL16: =AT15 -> 675058.72 | AM16: =AM15 -> 4871.6033 | AN16: =AM16-AP16 -> 511.84902 | AO16: =(AN16/AL16)*12 -> 0.0090987465 | AP16: =AL16*($AK$1/12) -> 4359.7543 | AQ16: =(AP16/AL16)*12 -> 0.0775 | AR16: =AR15+AN16 -> 5453.1262 | AS16: =AS15+AP16 -> 48134.51 | AT16: =AL16-AN16 -> 674546.87 | AU16: =AR16+AS16 -> 53587.636 | AW16: 11 | AX16: 45170 | AY16: =BG15 -> 674809.09 | AZ16: =AZ15 -> 4754.6587 | BA16: =AZ16-BC16 -> 537.10187 | BB16: =(BA16/AY16)*12 -> 0.009551179 | BC16: =AY16*($AX$1/12) -> 4217.5568 | BD16: =(BC16/AY16)*12 -> 0.075 | BE16: =BE15+BA16 -> 5728.0154 | BF16: =BF15+BC16 -> 46573.23 | BG16: =AY16-BA16 -> 674271.98 | BH16: =BE16+BF16 -> 52301.245 | BJ16: 11 | BK16: 45170 | BL16: =BT15 -> 674548.78 | BM16: =BM15 -> 4638.7987 | BN16: =BM16-BP16 -> 563.39984 | BO16: =(BN16/BL16)*12 -> 0.010022697 | BP16: =BL16*($BK$1/12) -> 4075.3989 | BQ16: =(BP16/BL16)*12 -> 0.0725 | BR16: =BR15+BN16 -> 6014.6221 | BS16: =BS15+BP16 -> 45012.164 | BT16: =BL16-BN16 -> 673985.38 | BU16: =BR16+BS16 -> 51026.786 | BW16: 11 | BX16: 45170 | BY16: =CG15 -> 674277.48 | BZ16: =BZ15 -> 4524.057 | CA16: =BZ16-CC16 -> 590.77165 | CB16: =(CA16/BY16)*12 -> 0.010513861 | CC16: =BY16*($BX$1/12) -> 3933.2853 | CD16: =(CC16/BY16)*12 -> 0.07 | CE16: =CE15+CA16 -> 6313.289 | CF16: =CF15+CC16 -> 43451.338 | CG16: =BY16-CA16 -> 673686.71 | CH16: =CE16+CF16 -> 49764.627
A17: =A16+1 -> 9 | B17: =VLOOKUP(A17*12,$J$5:$U$365,10) -> 482613.86 | C17: =VLOOKUP(A17*12,$W$5:$AH$365,10) -> 467047 | D17: =VLOOKUP(A17*12,$AJ$5:$AU$365,10) -> 451506.44 | E17: =VLOOKUP(A17*12,$AW$5:$BH$365,10) -> 435994.7 | F17: =VLOOKUP(A17*12,$BJ$5:$BU$365,10) -> 420514.4 | G17: =VLOOKUP(A17*12,$BW$5:$CH$365,10) -> 405068.25 | J17: 12 | K17: 45200 | L17: =T16 -> 675062.87 | M17: =$L$6/((($N$2)-1)/($N$1*$N$2)) -> 5108.6129 | N17: =M17-P17 -> 467.55568 | O17: =(N17/L17)*12 -> 0.0083113269 | P17: =L17*($K$1/12) -> 4641.0572 | Q17: =(P17/L17)*12 -> 0.0825 | R17: =R16+N17 -> 5404.6862 | S17: =S16+P17 -> 55898.669 | T17: =L17-N17 -> 674595.31 | U17: =R17+S17 -> 61303.355 | W17: 12 | X17: 45200 | Y17: =AG16 -> 674810.39 | Z17: =Z16 -> 4989.5991 | AA17: =Z17-AC17 -> 490.86318 | AB17: =(AA17/Y17)*12 -> 0.0087289086 | AC17: =Y17*($X$1/12) -> 4498.7359 | AD17: =(AC17/Y17)*12 -> 0.08 | AE17: =AE16+AA17 -> 5680.4751 | AF17: =AF16+AC17 -> 54194.714 | AG17: =Y17-AA17 -> 674319.52 | AH17: =AE17+AF17 -> 59875.189 | AJ17: 12 | AK17: 45200 | AL17: =AT16 -> 674546.87 | AM17: =AM16 -> 4871.6033 | AN17: =AM17-AP17 -> 515.15471 | AO17: =(AN17/AL17)*12 -> 0.009164458 | AP17: =AL17*($AK$1/12) -> 4356.4486 | AQ17: =(AP17/AL17)*12 -> 0.0775 | AR17: =AR16+AN17 -> 5968.2809 | AS17: =AS16+AP17 -> 52490.958 | AT17: =AL17-AN17 -> 674031.72 | AU17: =AR17+AS17 -> 58459.239 | AW17: 12 | AX17: 45200 | AY17: =BG16 -> 674271.98 | AZ17: =AZ16 -> 4754.6587 | BA17: =AZ17-BC17 -> 540.45875 | BB17: =(BA17/AY17)*12 -> 0.0096185296 | BC17: =AY17*($AX$1/12) -> 4214.1999 | BD17: =(BC17/AY17)*12 -> 0.075 | BE17: =BE16+BA17 -> 6268.4741 | BF17: =BF16+BC17 -> 50787.43 | BG17: =AY17-BA17 -> 673731.53 | BH17: =BE17+BF17 -> 57055.904 | BJ17: 12 | BK17: 45200 | BL17: =BT16 -> 673985.38 | BM17: =BM16 -> 4638.7987 | BN17: =BM17-BP17 -> 566.80371 | BO17: =(BN17/BL17)*12 -> 0.01009168 | BP17: =BL17*($BK$1/12) -> 4071.995 | BQ17: =(BP17/BL17)*12 -> 0.0725 | BR17: =BR16+BN17 -> 6581.4258 | BS17: =BS16+BP17 -> 49084.159 | BT17: =BL17-BN17 -> 673418.57 | BU17: =BR17+BS17 -> 55665.584 | BW17: 12 | BX17: 45200 | BY17: =CG16 -> 673686.71 | BZ17: =BZ16 -> 4524.057 | CA17: =BZ17-CC17 -> 594.21782 | CB17: =(CA17/BY17)*12 -> 0.010584466 | CC17: =BY17*($BX$1/12) -> 3929.8391 | CD17: =(CC17/BY17)*12 -> 0.07 | CE17: =CE16+CA17 -> 6907.5068 | CF17: =CF16+CC17 -> 47381.177 | CG17: =BY17-CA17 -> 673092.49 | CH17: =CE17+CF17 -> 54288.684
A18: =A17+1 -> 10 | B18: =VLOOKUP(A18*12,$J$5:$U$365,10) -> 532589.8 | C18: =VLOOKUP(A18*12,$W$5:$AH$365,10) -> 515279.88 | D18: =VLOOKUP(A18*12,$AJ$5:$AU$365,10) -> 498003.9 | E18: =VLOOKUP(A18*12,$AW$5:$BH$365,10) -> 480764.95 | F18: =VLOOKUP(A18*12,$BJ$5:$BU$365,10) -> 463566.23 | G18: =VLOOKUP(A18*12,$BW$5:$CH$365,10) -> 446411.04 | J18: 13 | K18: 45231 | L18: =T17 -> 674595.31 | M18: =$L$6/((($N$2)-1)/($N$1*$N$2)) -> 5108.6129 | N18: =M18-P18 -> 470.77012 | O18: =(N18/L18)*12 -> 0.0083742673 | P18: =L18*($K$1/12) -> 4637.8428 | Q18: =(P18/L18)*12 -> 0.0825 | R18: =R17+N18 -> 5875.4563 | S18: =S17+P18 -> 60536.512 | T18: =L18-N18 -> 674124.54 | U18: =R18+S18 -> 66411.968 | W18: 13 | X18: 45231 | Y18: =AG17 -> 674319.52 | Z18: =Z17 -> 4989.5991 | AA18: =Z18-AC18 -> 494.1356 | AB18: =(AA18/Y18)*12 -> 0.0087934978 | AC18: =Y18*($X$1/12) -> 4495.4635 | AD18: =(AC18/Y18)*12 -> 0.08 | AE18: =AE17+AA18 -> 6174.6107 | AF18: =AF17+AC18 -> 58690.178 | AG18: =Y18-AA18 -> 673825.39 | AH18: =AE18+AF18 -> 64864.788 | AJ18: 13 | AK18: 45231 | AL18: =AT17 -> 674031.72 | AM18: =AM17 -> 4871.6033 | AN18: =AM18-AP18 -> 518.48175 | AO18: =(AN18/AL18)*12 -> 0.0092306947 | AP18: =AL18*($AK$1/12) -> 4353.1215 | AQ18: =(AP18/AL18)*12 -> 0.0775 | AR18: =AR17+AN18 -> 6486.7626 | AS18: =AS17+AP18 -> 56844.08 | AT18: =AL18-AN18 -> 673513.24 | AU18: =AR18+AS18 -> 63330.843 | AW18: 13 | AX18: 45231 | AY18: =BG17 -> 673731.53 | AZ18: =AZ17 -> 4754.6587 | BA18: =AZ18-BC18 -> 543.83662 | BB18: =(BA18/AY18)*12 -> 0.0096864095 | BC18: =AY18*($AX$1/12) -> 4210.822 | BD18: =(BC18/AY18)*12 -> 0.075 | BE18: =BE17+BA18 -> 6812.3107 | BF18: =BF17+BC18 -> 54998.252 | BG18: =AY18-BA18 -> 673187.69 | BH18: =BE18+BF18 -> 61810.563 | BJ18: 13 | BK18: 45231 | BL18: =BT17 -> 673418.57 | BM18: =BM17 -> 4638.7987 | BN18: =BM18-BP18 -> 570.22815 | BO18: =(BN18/BL18)*12 -> 0.010161196 | BP18: =BL18*($BK$1/12) -> 4068.5706 | BQ18: =(BP18/BL18)*12 -> 0.0725 | BR18: =BR17+BN18 -> 7151.654 | BS18: =BS17+BP18 -> 53152.729 | BT18: =BL18-BN18 -> 672848.35 | BU18: =BR18+BS18 -> 60304.383 | BW18: 13 | BX18: 45231 | BY18: =CG17 -> 673092.49 | BZ18: =BZ17 -> 4524.057 | CA18: =BZ18-CC18 -> 597.68409 | CB18: =(CA18/BY18)*12 -> 0.010655607 | CC18: =BY18*($BX$1/12) -> 3926.3729 | CD18: =(CC18/BY18)*12 -> 0.07 | CE18: =CE17+CA18 -> 7505.1909 | CF18: =CF17+CC18 -> 51307.55 | CG18: =BY18-CA18 -> 672494.81 | CH18: =CE18+CF18 -> 58812.741
A19: =A18+1 -> 11 | B19: =VLOOKUP(A19*12,$J$5:$U$365,10) -> 581595.08 | C19: =VLOOKUP(A19*12,$W$5:$AH$365,10) -> 562546.46 | D19: =VLOOKUP(A19*12,$AJ$5:$AU$365,10) -> 543540.68 | E19: =VLOOKUP(A19*12,$AW$5:$BH$365,10) -> 524581.43 | F19: =VLOOKUP(A19*12,$BJ$5:$BU$365,10) -> 505672.54 | G19: =VLOOKUP(A19*12,$BW$5:$CH$365,10) -> 486817.98 | J19: 14 | K19: 45261 | L19: =T18 -> 674124.54 | M19: =$L$6/((($N$2)-1)/($N$1*$N$2)) -> 5108.6129 | N19: =M19-P19 -> 474.00667 | O19: =(N19/L19)*12 -> 0.0084377287 | P19: =L19*($K$1/12) -> 4634.6062 | Q19: =(P19/L19)*12 -> 0.0825 | R19: =R18+N19 -> 6349.463 | S19: =S18+P19 -> 65171.118 | T19: =L19-N19 -> 673650.54 | U19: =R19+S19 -> 71520.581 | W19: 14 | X19: 45261 | Y19: =AG18 -> 673825.39 | Z19: =Z18 -> 4989.5991 | AA19: =Z19-AC19 -> 497.42984 | AB19: =(AA19/Y19)*12 -> 0.0088586126 | AC19: =Y19*($X$1/12) -> 4492.1693 | AD19: =(AC19/Y19)*12 -> 0.08 | AE19: =AE18+AA19 -> 6672.0405 | AF19: =AF18+AC19 -> 63182.347 | AG19: =Y19-AA19 -> 673327.96 | AH19: =AE19+AF19 -> 69854.387 | AJ19: 14 | AK19: 45261 | AL19: =AT18 -> 673513.24 | AM19: =AM18 -> 4871.6033 | AN19: =AM19-AP19 -> 521.83028 | AO19: =(AN19/AL19)*12 -> 0.0092974614 | AP19: =AL19*($AK$1/12) -> 4349.773 | AQ19: =(AP19/AL19)*12 -> 0.0775 | AR19: =AR18+AN19 -> 7008.5929 | AS19: =AS18+AP19 -> 61193.853 | AT19: =AL19-AN19 -> 672991.41 | AU19: =AR19+AS19 -> 68202.446 | AW19: 14 | AX19: 45261 | AY19: =BG18 -> 673187.69 | AZ19: =AZ18 -> 4754.6587 | BA19: =AZ19-BC19 -> 547.2356 | BB19: =(BA19/AY19)*12 -> 0.0097548237 | BC19: =AY19*($AX$1/12) -> 4207.4231 | BD19: =(BC19/AY19)*12 -> 0.075 | BE19: =BE18+BA19 -> 7359.5463 | BF19: =BF18+BC19 -> 59205.675 | BG19: =AY19-BA19 -> 672640.45 | BH19: =BE19+BF19 -> 66565.221 | BJ19: 14 | BK19: 45261 | BL19: =BT18 -> 672848.35 | BM19: =BM18 -> 4638.7987 | BN19: =BM19-BP19 -> 573.67328 | BO19: =(BN19/BL19)*12 -> 0.01023125 | BP19: =BL19*($BK$1/12) -> 4065.1254 | BQ19: =(BP19/BL19)*12 -> 0.0725 | BR19: =BR18+BN19 -> 7725.3273 | BS19: =BS18+BP19 -> 57217.855 | BT19: =BL19-BN19 -> 672274.67 | BU19: =BR19+BS19 -> 64943.182 | BW19: 14 | BX19: 45261 | BY19: =CG18 -> 672494.81 | BZ19: =BZ18 -> 4524.057 | CA19: =BZ19-CC19 -> 601.17058 | CB19: =(CA19/BY19)*12 -> 0.01072729 | CC19: =BY19*($BX$1/12) -> 3922.8864 | CD19: =(CC19/BY19)*12 -> 0.07 | CE19: =CE18+CA19 -> 8106.3615 | CF19: =CF18+CC19 -> 55230.436 | CG19: =BY19-CA19 -> 671893.64 | CH19: =CE19+CF19 -> 63336.798
A20: =A19+1 -> 12 | B20: =VLOOKUP(A20*12,$J$5:$U$365,10) -> 629546.5 | C20: =VLOOKUP(A20*12,$W$5:$AH$365,10) -> 608766.53 | D20: =VLOOKUP(A20*12,$AJ$5:$AU$365,10) -> 588039.61 | E20: =VLOOKUP(A20*12,$AW$5:$BH$365,10) -> 567370.1 | F20: =VLOOKUP(A20*12,$BJ$5:$BU$365,10) -> 546762.48 | G20: =VLOOKUP(A20*12,$BW$5:$CH$365,10) -> 526221.4 | J20: 15 | K20: 45292 | L20: =T19 -> 673650.54 | M20: =$L$6/((($N$2)-1)/($N$1*$N$2)) -> 5108.6129 | N20: =M20-P20 -> 477.26547 | O20: =(N20/L20)*12 -> 0.0085017161 | P20: =L20*($K$1/12) -> 4631.3474 | Q20: =(P20/L20)*12 -> 0.0825 | R20: =R19+N20 -> 6826.7284 | S20: =S19+P20 -> 69802.465 | T20: =L20-N20 -> 673173.27 | U20: =R20+S20 -> 76629.194 | W20: 15 | X20: 45292 | Y20: =AG19 -> 673327.96 | Z20: =Z19 -> 4989.5991 | AA20: =Z20-AC20 -> 500.74604 | AB20: =(AA20/Y20)*12 -> 0.0089242581 | AC20: =Y20*($X$1/12) -> 4488.8531 | AD20: =(AC20/Y20)*12 -> 0.08 | AE20: =AE19+AA20 -> 7172.7866 | AF20: =AF19+AC20 -> 67671.2 | AG20: =Y20-AA20 -> 672827.21 | AH20: =AE20+AF20 -> 74843.987 | AJ20: 15 | AK20: 45292 | AL20: =AT19 -> 672991.41 | AM20: =AM19 -> 4871.6033 | AN20: =AM20-AP20 -> 525.20043 | AO20: =(AN20/AL20)*12 -> 0.0093647632 | AP20: =AL20*($AK$1/12) -> 4346.4028 | AQ20: =(AP20/AL20)*12 -> 0.0775 | AR20: =AR19+AN20 -> 7533.7933 | AS20: =AS19+AP20 -> 65540.256 | AT20: =AL20-AN20 -> 672466.21 | AU20: =AR20+AS20 -> 73074.049 | AW20: 15 | AX20: 45292 | AY20: =BG19 -> 672640.45 | AZ20: =AZ19 -> 4754.6587 | BA20: =AZ20-BC20 -> 550.65582 | BB20: =(BA20/AY20)*12 -> 0.0098237771 | BC20: =AY20*($AX$1/12) -> 4204.0028 | BD20: =(BC20/AY20)*12 -> 0.075 | BE20: =BE19+BA20 -> 7910.2022 | BF20: =BF19+BC20 -> 63409.678 | BG20: =AY20-BA20 -> 672089.8 | BH20: =BE20+BF20 -> 71319.88 | BJ20: 15 | BK20: 45292 | BL20: =BT19 -> 672274.67 | BM20: =BM19 -> 4638.7987 | BN20: =BM20-BP20 -> 577.13922 | BO20: =(BN20/BL20)*12 -> 0.010301847 | BP20: =BL20*($BK$1/12) -> 4061.6595 | BQ20: =(BP20/BL20)*12 -> 0.0725 | BR20: =BR19+BN20 -> 8302.4665 | BS20: =BS19+BP20 -> 61279.514 | BT20: =BL20-BN20 -> 671697.53 | BU20: =BR20+BS20 -> 69581.981 | BW20: 15 | BX20: 45292 | BY20: =CG19 -> 671893.64 | BZ20: =BZ19 -> 4524.057 | CA20: =BZ20-CC20 -> 604.67741 | CB20: =(CA20/BY20)*12 -> 0.01079952 | CC20: =BY20*($BX$1/12) -> 3919.3796 | CD20: =(CC20/BY20)*12 -> 0.07 | CE20: =CE19+CA20 -> 8711.0389 | CF20: =CF19+CC20 -> 59149.816 | CG20: =BY20-CA20 -> 671288.96 | CH20: =CE20+CF20 -> 67860.855
A21: =A20+1 -> 13 | B21: =VLOOKUP(A21*12,$J$5:$U$365,10) -> 676353.77 | C21: =VLOOKUP(A21*12,$W$5:$AH$365,10) -> 653853.23 | D21: =VLOOKUP(A21*12,$AJ$5:$AU$365,10) -> 631417.36 | E21: =VLOOKUP(A21*12,$AW$5:$BH$365,10) -> 609051.17 | F21: =VLOOKUP(A21*12,$BJ$5:$BU$365,10) -> 586759.86 | G21: =VLOOKUP(A21*12,$BW$5:$CH$365,10) -> 564548.76 | J21: 16 | K21: 45323 | L21: =T20 -> 673173.27 | M21: =$L$6/((($N$2)-1)/($N$1*$N$2)) -> 5108.6129 | N21: =M21-P21 -> 480.54667 | O21: =(N21/L21)*12 -> 0.0085662343 | P21: =L21*($K$1/12) -> 4628.0662 | Q21: =(P21/L21)*12 -> 0.0825 | R21: =R20+N21 -> 7307.2751 | S21: =S20+P21 -> 74430.531 | T21: =L21-N21 -> 672692.72 | U21: =R21+S21 -> 81737.807 | W21: 16 | X21: 45323 | Y21: =AG20 -> 672827.21 | Z21: =Z20 -> 4989.5991 | AA21: =Z21-AC21 -> 504.08435 | AB21: =(AA21/Y21)*12 -> 0.0089904392 | AC21: =Y21*($X$1/12) -> 4485.5148 | AD21: =(AC21/Y21)*12 -> 0.08 | AE21: =AE20+AA21 -> 7676.8709 | AF21: =AF20+AC21 -> 72156.715 | AG21: =Y21-AA21 -> 672323.13 | AH21: =AE21+AF21 -> 79833.586 | AJ21: 16 | AK21: 45323 | AL21: =AT20 -> 672466.21 | AM21: =AM20 -> 4871.6033 | AN21: =AM21-AP21 -> 528.59235 | AO21: =(AN21/AL21)*12 -> 0.0094326052 | AP21: =AL21*($AK$1/12) -> 4343.0109 | AQ21: =(AP21/AL21)*12 -> 0.0775 | AR21: =AR20+AN21 -> 8062.3857 | AS21: =AS20+AP21 -> 69883.267 | AT21: =AL21-AN21 -> 671937.61 | AU21: =AR21+AS21 -> 77945.652 | AW21: 16 | AX21: 45323 | AY21: =BG20 -> 672089.8 | AZ21: =AZ20 -> 4754.6587 | BA21: =AZ21-BC21 -> 554.09742 | BB21: =(BA21/AY21)*12 -> 0.0098932748 | BC21: =AY21*($AX$1/12) -> 4200.5612 | BD21: =(BC21/AY21)*12 -> 0.075 | BE21: =BE20+BA21 -> 8464.2996 | BF21: =BF20+BC21 -> 67610.239 | BG21: =AY21-BA21 -> 671535.7 | BH21: =BE21+BF21 -> 76074.539 | BJ21: 16 | BK21: 45323 | BL21: =BT20 -> 671697.53 | BM21: =BM20 -> 4638.7987 | BN21: =BM21-BP21 -> 580.62611 | BO21: =(BN21/BL21)*12 -> 0.010372992 | BP21: =BL21*($BK$1/12) -> 4058.1726 | BQ21: =(BP21/BL21)*12 -> 0.0725 | BR21: =BR20+BN21 -> 8883.0926 | BS21: =BS20+BP21 -> 65337.687 | BT21: =BL21-BN21 -> 671116.91 | BU21: =BR21+BS21 -> 74220.779 | BW21: 16 | BX21: 45323 | BY21: =CG20 -> 671288.96 | BZ21: =BZ20 -> 4524.057 | CA21: =BZ21-CC21 -> 608.20469 | CB21: =(CA21/BY21)*12 -> 0.010872302 | CC21: =BY21*($BX$1/12) -> 3915.8523 | CD21: =(CC21/BY21)*12 -> 0.07 | CE21: =CE20+CA21 -> 9319.2436 | CF21: =CF20+CC21 -> 63065.668 | CG21: =BY21-CA21 -> 670680.76 | CH21: =CE21+CF21 -> 72384.911
... A38: =A37+1 -> 30 | B38: =VLOOKUP(A38*12,$J$5:$U$365,10) -> 1159100.6 | C38: =VLOOKUP(A38*12,$W$5:$AH$365,10) -> 1116255.7 | D38: =VLOOKUP(A38*12,$AJ$5:$AU$365,10) -> 1073777.2 | E38: =VLOOKUP(A38*12,$AW$5:$BH$365,10) -> 1031677.1 | F38: =VLOOKUP(A38*12,$BJ$5:$BU$365,10) -> 989967.53 | G38: =VLOOKUP(A38*12,$BW$5:$CH$365,10) -> 948660.51 | J38: 33 | K38: 45839 | L38: =T37 -> 664538.84 | M38: =$L$6/((($N$2)-1)/($N$1*$N$2)) -> 5108.6129 | N38: =M38-P38 -> 539.90836 | O38: =(N38/L38)*12 -> 0.0097494681 | P38: =L38*($K$1/12) -> 4568.7046 | Q38: =(P38/L38)*12 -> 0.0825 | R38: =R37+N38 -> 16001.065 | S38: =S37+P38 -> 152583.16 | T38: =L38-N38 -> 663998.94 | U38: =R38+S38 -> 168584.23 | W38: 33 | X38: 45839 | Y38: =AG37 -> 663785.15 | Z38: =Z37 -> 4989.5991 | AA38: =Z38-AC38 -> 564.36479 | AB38: =(AA38/Y38)*12 -> 0.010202665 | AC38: =Y38*($X$1/12) -> 4425.2343 | AD38: =(AC38/Y38)*12 -> 0.08 | AE38: =AE37+AA38 -> 16779.218 | AF38: =AF37+AC38 -> 147877.55 | AG38: =Y38-AA38 -> 663220.78 | AH38: =AE38+AF38 -> 164656.77 | AJ38: 33 | AK38: 45839 | AL38: =AT37 -> 663000.52 | AM38: =AM37 -> 4871.6033 | AN38: =AM38-AP38 -> 589.72492 | AO38: =(AN38/AL38)*12 -> 0.010673746 | AP38: =AL38*($AK$1/12) -> 4281.8784 | AQ38: =(AP38/AL38)*12 -> 0.0775 | AR38: =AR37+AN38 -> 17589.206 | AS38: =AS37+AP38 -> 143173.7 | AT38: =AL38-AN38 -> 662410.79 | AU38: =AR38+AS38 -> 160762.91 | AW38: 33 | AX38: 45839 | AY38: =BG37 -> 662184.11 | AZ38: =AZ37 -> 4754.6587 | BA38: =AZ38-BC38 -> 616.00795 | BB38: =(BA38/AY38)*12 -> 0.011163203 | BC38: =AY38*($AX$1/12) -> 4138.6507 | BD38: =(BC38/AY38)*12 -> 0.075 | BE38: =BE37+BA38 -> 18431.895 | BF38: =BF37+BC38 -> 138471.84 | BG38: =AY38-BA38 -> 661568.11 | BH38: =BE38+BF38 -> 156903.74 | BJ38: 33 | BK38: 45839 | BL38: =BT37 -> 661335.09 | BM38: =BM37 -> 4638.7987 | BN38: =BM38-BP38 -> 643.23255 | BO38: =(BN38/BL38)*12 -> 0.011671527 | BP38: =BL38*($BK$1/12) -> 3995.5662 | BQ38: =(BP38/BL38)*12 -> 0.0725 | BR38: =BR37+BN38 -> 19308.145 | BS38: =BS37+BP38 -> 133772.21 | BT38: =BL38-BN38 -> 660691.85 | BU38: =BR38+BS38 -> 153080.36 | BW38: 33 | BX38: 45839 | BY38: =CG37 -> 660452.61 | BZ38: =BZ37 -> 4524.057 | CA38: =BZ38-CC38 -> 671.41676 | CB38: =(CA38/BY38)*12 -> 0.012199212 | CC38: =BY38*($BX$1/12) -> 3852.6402 | CD38: =(CC38/BY38)*12 -> 0.07 | CE38: =CE37+CA38 -> 20218.809 | CF38: =CF37+CC38 -> 129075.07 | CG38: =BY38-CA38 -> 659781.19 | CH38: =CE38+CF38 -> 149293.88
J39: 34 | K39: 45870 | L39: =T38 -> 663998.94 | M39: =$L$6/((($N$2)-1)/($N$1*$N$2)) -> 5108.6129 | N39: =M39-P39 -> 543.62023 | O39: =(N39/L39)*12 -> 0.0098244777 | P39: =L39*($K$1/12) -> 4564.9927 | Q39: =(P39/L39)*12 -> 0.0825 | R39: =R38+N39 -> 16544.685 | S39: =S38+P39 -> 157148.15 | T39: =L39-N39 -> 663455.32 | U39: =R39+S39 -> 173692.84 | W39: 34 | X39: 45870 | Y39: =AG38 -> 663220.78 | Z39: =Z38 -> 4989.5991 | AA39: =Z39-AC39 -> 568.12722 | AB39: =(AA39/Y39)*12 -> 0.010279423 | AC39: =Y39*($X$1/12) -> 4421.4719 | AD39: =(AC39/Y39)*12 -> 0.08 | AE39: =AE38+AA39 -> 17347.345 | AF39: =AF38+AC39 -> 152299.02 | AG39: =Y39-AA39 -> 662652.65 | AH39: =AE39+AF39 -> 169646.37 | AJ39: 34 | AK39: 45870 | AL39: =AT38 -> 662410.79 | AM39: =AM38 -> 4871.6033 | AN39: =AM39-AP39 -> 593.53356 | AO39: =(AN39/AL39)*12 -> 0.010752244 | AP39: =AL39*($AK$1/12) -> 4278.0697 | AQ39: =(AP39/AL39)*12 -> 0.0775 | AR39: =AR38+AN39 -> 18182.739 | AS39: =AS38+AP39 -> 147451.77 | AT39: =AL39-AN39 -> 661817.26 | AU39: =AR39+AS39 -> 165634.51 | AW39: 34 | AX39: 45870 | AY39: =BG38 -> 661568.11 | AZ39: =AZ38 -> 4754.6587 | BA39: =AZ39-BC39 -> 619.858 | BB39: =(BA39/AY39)*12 -> 0.011243432 | BC39: =AY39*($AX$1/12) -> 4134.8007 | BD39: =(BC39/AY39)*12 -> 0.075 | BE39: =BE38+BA39 -> 19051.753 | BF39: =BF38+BC39 -> 142606.64 | BG39: =AY39-BA39 -> 660948.25 | BH39: =BE39+BF39 -> 161658.39 | BJ39: 34 | BK39: 45870 | BL39: =BT38 -> 660691.85 | BM39: =BM38 -> 4638.7987 | BN39: =BM39-BP39 -> 647.11875 | BO39: =(BN39/BL39)*12 -> 0.011753475 | BP39: =BL39*($BK$1/12) -> 3991.68 | BQ39: =(BP39/BL39)*12 -> 0.0725 | BR39: =BR38+BN39 -> 19955.264 | BS39: =BS38+BP39 -> 137763.89 | BT39: =BL39-BN39 -> 660044.74 | BU39: =BR39+BS39 -> 157719.16 | BW39: 34 | BX39: 45870 | BY39: =CG38 -> 659781.19 | BZ39: =BZ38 -> 4524.057 | CA39: =BZ39-CC39 -> 675.33336 | CB39: =(CA39/BY39)*12 -> 0.01228286 | CC39: =BY39*($BX$1/12) -> 3848.7236 | CD39: =(CC39/BY39)*12 -> 0.07 | CE39: =CE38+CA39 -> 20894.143 | CF39: =CF38+CC39 -> 132923.79 | CG39: =BY39-CA39 -> 659105.86 | CH39: =CE39+CF39 -> 153817.94
J40: 35 | K40: 45901 | L40: =T39 -> 663455.32 | M40: =$L$6/((($N$2)-1)/($N$1*$N$2)) -> 5108.6129 | N40: =M40-P40 -> 547.35762 | O40: =(N40/L40)*12 -> 0.0099001263 | P40: =L40*($K$1/12) -> 4561.2553 | Q40: =(P40/L40)*12 -> 0.0825 | R40: =R39+N40 -> 17092.043 | S40: =S39+P40 -> 161709.41 | T40: =L40-N40 -> 662907.96 | U40: =R40+S40 -> 178801.45 | W40: 35 | X40: 45901 | Y40: =AG39 -> 662652.65 | Z40: =Z39 -> 4989.5991 | AA40: =Z40-AC40 -> 571.91474 | AB40: =(AA40/Y40)*12 -> 0.010356824 | AC40: =Y40*($X$1/12) -> 4417.6844 | AD40: =(AC40/Y40)*12 -> 0.08 | AE40: =AE39+AA40 -> 17919.26 | AF40: =AF39+AC40 -> 156716.71 | AG40: =Y40-AA40 -> 662080.74 | AH40: =AE40+AF40 -> 174635.97 | AJ40: 35 | AK40: 45901 | AL40: =AT39 -> 661817.26 | AM40: =AM39 -> 4871.6033 | AN40: =AM40-AP40 -> 597.36679 | AO40: =(AN40/AL40)*12 -> 0.010831391 | AP40: =AL40*($AK$1/12) -> 4274.2365 | AQ40: =(AP40/AL40)*12 -> 0.0775 | AR40: =AR39+AN40 -> 18780.106 | AS40: =AS39+AP40 -> 151726.01 | AT40: =AL40-AN40 -> 661219.89 | AU40: =AR40+AS40 -> 170506.11 | AW40: 35 | AX40: 45901 | AY40: =BG39 -> 660948.25 | AZ40: =AZ39 -> 4754.6587 | BA40: =AZ40-BC40 -> 623.73211 | BB40: =(BA40/AY40)*12 -> 0.011324314 | BC40: =AY40*($AX$1/12) -> 4130.9265 | BD40: =(BC40/AY40)*12 -> 0.075 | BE40: =BE39+BA40 -> 19675.485 | BF40: =BF39+BC40 -> 146737.57 | BG40: =AY40-BA40 -> 660324.52 | BH40: =BE40+BF40 -> 166413.05 | BJ40: 35 | BK40: 45901 | BL40: =BT39 -> 660044.74 | BM40: =BM39 -> 4638.7987 | BN40: =BM40-BP40 -> 651.02843 | BO40: =(BN40/BL40)*12 -> 0.011836078 | BP40: =BL40*($BK$1/12) -> 3987.7703 | BQ40: =(BP40/BL40)*12 -> 0.0725 | BR40: =BR39+BN40 -> 20606.293 | BS40: =BS39+BP40 -> 141751.66 | BT40: =BL40-BN40 -> 659393.71 | BU40: =BR40+BS40 -> 162357.95 | BW40: 35 | BX40: 45901 | BY40: =CG39 -> 659105.86 | BZ40: =BZ39 -> 4524.057 | CA40: =BZ40-CC40 -> 679.2728 | CB40: =(CA40/BY40)*12 -> 0.012367169 | CC40: =BY40*($BX$1/12) -> 3844.7842 | CD40: =(CC40/BY40)*12 -> 0.07 | CE40: =CE39+CA40 -> 21573.416 | CF40: =CF39+CC40 -> 136768.58 | CG40: =BY40-CA40 -> 658426.58 | CH40: =CE40+CF40 -> 158341.99
J41: 36 | K41: 45931 | L41: =T40 -> 662907.96 | M41: =$L$6/((($N$2)-1)/($N$1*$N$2)) -> 5108.6129 | N41: =M41-P41 -> 551.1207 | O41: =(N41/L41)*12 -> 0.0099764203 | P41: =L41*($K$1/12) -> 4557.4922 | Q41: =(P41/L41)*12 -> 0.0825 | R41: =R40+N41 -> 17643.163 | S41: =S40+P41 -> 166266.9 | T41: =L41-N41 -> 662356.84 | U41: =R41+S41 -> 183910.06 | W41: 36 | X41: 45931 | Y41: =AG40 -> 662080.74 | Z41: =Z40 -> 4989.5991 | AA41: =Z41-AC41 -> 575.7275 | AB41: =(AA41/Y41)*12 -> 0.010434875 | AC41: =Y41*($X$1/12) -> 4413.8716 | AD41: =(AC41/Y41)*12 -> 0.08 | AE41: =AE40+AA41 -> 18494.987 | AF41: =AF40+AC41 -> 161130.58 | AG41: =Y41-AA41 -> 661505.01 | AH41: =AE41+AF41 -> 179625.57 | AJ41: 36 | AK41: 45931 | AL41: =AT40 -> 661219.89 | AM41: =AM40 -> 4871.6033 | AN41: =AM41-AP41 -> 601.22479 | AO41: =(AN41/AL41)*12 -> 0.010911192 | AP41: =AL41*($AK$1/12) -> 4270.3785 | AQ41: =(AP41/AL41)*12 -> 0.0775 | AR41: =AR40+AN41 -> 19381.331 | AS41: =AS40+AP41 -> 155996.39 | AT41: =AL41-AN41 -> 660618.67 | AU41: =AR41+AS41 -> 175377.72 | AW41: 36 | AX41: 45931 | AY41: =BG40 -> 660324.52 | AZ41: =AZ40 -> 4754.6587 | BA41: =AZ41-BC41 -> 627.63044 | BB41: =(BA41/AY41)*12 -> 0.011405854 | BC41: =AY41*($AX$1/12) -> 4127.0282 | BD41: =(BC41/AY41)*12 -> 0.075 | BE41: =BE40+BA41 -> 20303.115 | BF41: =BF40+BC41 -> 150864.6 | BG41: =AY41-BA41 -> 659696.88 | BH41: =BE41+BF41 -> 171167.71 | BJ41: 36 | BK41: 45931 | BL41: =BT40 -> 659393.71 | BM41: =BM40 -> 4638.7987 | BN41: =BM41-BP41 -> 654.96172 | BO41: =(BN41/BL41)*12 -> 0.011919344 | BP41: =BL41*($BK$1/12) -> 3983.837 | BQ41: =(BP41/BL41)*12 -> 0.0725 | BR41: =BR40+BN41 -> 21261.254 | BS41: =BS40+BP41 -> 145735.5 | BT41: =BL41-BN41 -> 658738.75 | BU41: =BR41+BS41 -> 166996.75 | BW41: 36 | BX41: 45931 | BY41: =CG40 -> 658426.58 | BZ41: =BZ40 -> 4524.057 | CA41: =BZ41-CC41 -> 683.23522 | CB41: =(CA41/BY41)*12 -> 0.012452144 | CC41: =BY41*($BX$1/12) -> 3840.8217 | CD41: =(CC41/BY41)*12 -> 0.07 | CE41: =CE40+CA41 -> 22256.651 | CF41: =CF40+CC41 -> 140609.4 | CG41: =BY41-CA41 -> 657743.35 | CH41: =CE41+CF41 -> 162866.05
J42: 37 | K42: 45962 | L42: =T41 -> 662356.84 | M42: =$L$6/((($N$2)-1)/($N$1*$N$2)) -> 5108.6129 | N42: =M42-P42 -> 554.90965 | O42: =(N42/L42)*12 -> 0.010053366 | P42: =L42*($K$1/12) -> 4553.7033 | Q42: =(P42/L42)*12 -> 0.0825 | R42: =R41+N42 -> 18198.073 | S42: =S41+P42 -> 170820.6 | T42: =L42-N42 -> 661801.93 | U42: =R42+S42 -> 189018.68 | W42: 37 | X42: 45962 | Y42: =AG41 -> 661505.01 | Z42: =Z41 -> 4989.5991 | AA42: =Z42-AC42 -> 579.56569 | AB42: =(AA42/Y42)*12 -> 0.010513584 | AC42: =Y42*($X$1/12) -> 4410.0334 | AD42: =(AC42/Y42)*12 -> 0.08 | AE42: =AE41+AA42 -> 19074.553 | AF42: =AF41+AC42 -> 165540.61 | AG42: =Y42-AA42 -> 660925.45 | AH42: =AE42+AF42 -> 184615.17 | AJ42: 37 | AK42: 45962 | AL42: =AT41 -> 660618.67 | AM42: =AM41 -> 4871.6033 | AN42: =AM42-AP42 -> 605.1077 | AO42: =(AN42/AL42)*12 -> 0.010991655 | AP42: =AL42*($AK$1/12) -> 4266.4956 | AQ42: =(AP42/AL42)*12 -> 0.0775 | AR42: =AR41+AN42 -> 19986.438 | AS42: =AS41+AP42 -> 160262.88 | AT42: =AL42-AN42 -> 660013.56 | AU42: =AR42+AS42 -> 180249.32 | AW42: 37 | AX42: 45962 | AY42: =BG41 -> 659696.88 | AZ42: =AZ41 -> 4754.6587 | BA42: =AZ42-BC42 -> 631.55313 | BB42: =(BA42/AY42)*12 -> 0.01148806 | BC42: =AY42*($AX$1/12) -> 4123.1055 | BD42: =(BC42/AY42)*12 -> 0.075 | BE42: =BE41+BA42 -> 20934.668 | BF42: =BF41+BC42 -> 154987.7 | BG42: =AY42-BA42 -> 659065.33 | BH42: =BE42+BF42 -> 175922.37 | BJ42: 37 | BK42: 45962 | BL42: =BT41 -> 658738.75 | BM42: =BM41 -> 4638.7987 | BN42: =BM42-BP42 -> 658.91878 | BO42: =(BN42/BL42)*12 -> 0.01200328 | BP42: =BL42*($BK$1/12) -> 3979.8799 | BQ42: =(BP42/BL42)*12 -> 0.0725 | BR42: =BR41+BN42 -> 21920.173 | BS42: =BS41+BP42 -> 149715.38 | BT42: =BL42-BN42 -> 658079.83 | BU42: =BR42+BS42 -> 171635.55 | BW42: 37 | BX42: 45962 | BY42: =CG41 -> 657743.35 | BZ42: =BZ41 -> 4524.057 | CA42: =BZ42-CC42 -> 687.22076 | CB42: =(CA42/BY42)*12 -> 0.012537792 | CC42: =BY42*($BX$1/12) -> 3836.8362 | CD42: =(CC42/BY42)*12 -> 0.07 | CE42: =CE41+CA42 -> 22943.872 | CF42: =CF41+CC42 -> 144446.24 | CG42: =BY42-CA42 -> 657056.13 | CH42: =CE42+CF42 -> 167390.11
