Workbook
Name If: #REF!
Name If: #REF!
Name If: #REF!

Sheet Quick HELOC Loan Calc
G1: Heloc Down Payment | H1: 0.08
G2: Heloc Loan Terms | H2: 20 | I2: yrs
A3: =B5 -> 1000000 | B3: asking price | G3: HELOC Amount | H3: =SUM(B7+B6-C5-C4) -> 87974
C4: 5000 | D4: earnest money | G4: HELOC P&I Payment | H4: =-PMT($H$1/12,$H$2*12,H3) -> 735.84979 | I4: =H4*12 -> 8830.1974 | K4: IRR | L4: =IRR(L5:L11) -> -0.025857971
A5: Purchase Price | B5: 1000000 | C5: 47026 | D5: cash | G5: HELOC Interest Only Payment | H5: =-IPMT($H$1/12,1,$H$2*12,H3) -> 586.49333 | I5: =H5*12 -> 7037.92 | K5: Initial Investment | L5: =-B5 -> -1000000
A6: Closing Costs (4%) | B6: =B5*0.04 -> 40000 | I6: =H4-H5 -> 149.35645 | K6: Year 1 Cashflow | L6: ='10 Year'!B30 -> -64027.504
A7: Down Payment (20%) - HELOC | B7: =B5*C7 -> 100000 | C7: 0.1 | D7: downpayment | G7: Conventional Loan Interest Rate | H7: 0.06625 | K7: Year 2 Cashflow | L7: ='10 Year'!C30 -> -57861.456
A8: Total Loan Amount | B8: =B5-B7 -> 900000 | G8: Loan Term | H8: 30 | I8: yrs | K8: Year 3 Cashflow | L8: ='10 Year'!D30 -> -57919.908
A9: Down Payment - Cash | B9: =B5 -> 1000000 | G9: Monthly Interest Payment on Purchase Price | H9: =-PMT($H$7/12,$H$8*12,$B$8) -> 5762.7986 | K9: Year 4 Cashflow | L9: ='10 Year'!E30 -> -57212.363
G10: Monthly Interest Payment on Purchase Price | H10: =-IPMT($H$7/12,1,$H$8*12,$B$8) -> 4968.75 | K10: Year 5 Cashflow | L10: ='10 Year'!F30 -> -56988.166
A11: All In Price (Purchase+Repairs) | B11: =SUM(B5) -> 1000000 | K11: 6 | L11: =B5*(1+0.02)^K11 -> 1126162.4 | M11: assumes 2%/yr appreciation
A12: Estimated ARV (After Repair Value) | B12: =B5 -> 1000000 | G12: Financials
G13: Cash On Cash Return (CoC) | H13: =C38/SUM(B6:B7) -> -0.4576536
B14: Monthly | C14: Annually | G14: ROI (Return on Investment) | H14: =(SUM($B$6:$B$7)/B5) -> 0.14
A15: Average Rent | B15: 1350 | C15: =B15*12 -> 16200 | G15: ROE (Return on Equity) | H15: =C38/B7 -> -0.64071504
A16: Less 4% Vacancy | B16: =B15*-0.04 -> -54 | C16: =B16*12 -> -648 | G16: Mortgage Pay Down yr 1 | H16: =PPMT(H7/12,1,H8*12,B8)*12 -> -9528.5838
A17: Additional Income (Laundry) | B17: 0 | C17: =B17*12 -> 0 | G17: Tax Savings at 33% | H17: =C38*0.33 -> -21143.596
A18: Calculated Gross Revenue | B18: =SUM(B15:B17) -> 1296 | C18: =B18*12 -> 15552
G19: Rules of Thumb
G20: 50% Rule
A21: Estimated Expenses | B21: Monthly | C21: Annually | G21: 2% Rule | H21: =$B$15/$B$5 -> 0.00135
A22: Management Fees | B22: =B15*D22 -> 0 | C22: =B22*12 -> 0 | D22: 0 | E22: =IF(D22=0,1,0) -> 1 | G22: DSCR | H22: =B35/(B37+B36) -> 0.15907285
A23: Property Taxes / Year | B23: 107 | C23: =B23*12 -> 1284 | D23: 0.0108
A24: Insurance / Year | B24: 80 | C24: =B24*12 -> 960 | D24: =C24/B5 -> 0.00096
A25: HOA / year
A26: Electricity | C26: =B26*12 -> 0 | G26: Emergency Fund Needed (6 months) | H26: =B33*$I$26+SUM(B36:B37)*$I$26 -> 39811.752 | I26: 6 | J26: months
A27: Nat Gas | C27: =B27*12 -> 0 | H27: =H26/2 -> 19905.876 | I27: =I26/2 -> 3 | J27: months
A28: Water/Sewer | C28: =B28*12 -> 0
A29: Building Maintenance | B29: 54 | C29: =B29*12 -> 648 | D29: =C29/C15 -> 0.04
A30: Grounds Cleanup/Services Maintenance/Snow Removal | C30: =B30*12 -> 0
A31: Yearly Safety Inspection | B31: 8 | C31: =B31*12 -> 96
A32: Umbrella Insurance (Allstate Anchorage) | B32: 37 | C32: =B32*12 -> 444
A33: Totals | B33: =SUM(B22:B32) -> 286 | C33: =SUM(C22:C32) -> 3432
A35: Net Operating Income | B35: =B18-B33 -> 1010 | C35: =C18-C33 -> 12120 | D35: DSCR | E35: =B35/(B37+B36) -> 0.15907285
A36: HELOC Payment | B36: =H5 -> 586.49333 | C36: =B36*12 -> 7037.92 | D36: =IF(B36=H5,1,0) -> 1
A37: Conventional Loan Payment | B37: =-PMT($H$7/12,$H$8*12,$B$8) -> 5762.7986 | C37: =B37*12 -> 69153.584 | D37: Cap Rate | E37: =C35/B5 -> 0.01212
A38: Cash Flow | B38: =B35-B37-B36 -> -5339.292 | C38: =B38*12 -> -64071.504 | G38: NOI/value
A41: Estimated CapEx | B41: Timeline of Repair (yrs) | C41: Cost per Unit | D41: Total Cost | E41: Monthly Cost
A42: Roof | B42: 5 | C42: 7000 | D42: =C42 -> 7000 | E42: =D42/B42/12 -> 116.66667
A43: Master Bath | B43: 10 | D43: =C43 -> 0 | E43: =D43/B43/12 -> 0
A44: Kitchen | B44: 10 | D44: =C44 -> 0 | E44: =D44/B44/12 -> 0
A45: Flooring | B45: 10 | C45: 8000 | D45: =C45 -> 8000 | E45: =D45/B45/12 -> 66.666667
A46: Guest baths | B46: 10 | D46: =C46 -> 0 | E46: =D46/B46/12 -> 0
A47: Exterior Paint | B47: 1 | D47: =C47 -> 0 | E47: =D47/B47/12 -> 0
A48: Interior Paint | B48: 6 | C48: 2000 | D48: =C48 -> 2000 | E48: =D48/B48/12 -> 27.777778
A49: Cabinets | B49: 10 | D49: =C49 -> 0 | E49: =D49/B49/12 -> 0
A50: Concrete walkways | B50: 4 | D50: =C50 -> 0 | E50: =D50/B50/12 -> 0
A51: Driveway Re-Pave (Asphalt) | B51: 1 | D51: =C51 -> 0 | E51: =D51/B51/12 -> 0
A52: Miscellaneous (light fixtures/door knobs etc) | B52: 10 | C52: 500 | D52: =C52 -> 500 | E52: =D52/B52/12 -> 4.1666667
A53: Total Estimated Repairs | E53: =SUM(E42:E52) -> 215.27778

Sheet 7yr IRR Financing
A1: ='Quick HELOC Loan Calc'!$A$1 &" FINANCING CALCULATIONS" -> FINANCING CALCULATIONS
B4: Year 1 | C4: Year 2 | D4: Year 3 | E4: Year 4 | F4: Year 5 | G4: Year 6 | H4: Year 7
A5: Maintenance | B5: 0.04 | C5: 0.04 | D5: 0.04 | E5: 0.04 | F5: 0.04 | G5: 0.04 | H5: 0.04
A6: Property Appreciation | B6: 0.04 | C6: 0.04 | D6: 0.04 | E6: 0.04 | F6: 0.04 | G6: 0.04 | H6: 0.04
A7: Rental Appreciation | B7: 0.03 | C7: 0.03 | D7: 0.03 | E7: 0.03 | F7: 0.03 | G7: 0.03 | H7: 0.03
A8: Tax/Insurance/HOA Appreciation | B8: 0.015 | C8: 0.015 | D8: 0.015 | E8: 0.015 | F8: 0.015 | G8: 0.015 | H8: 0.015
A9: Vacancy | B9: 0.04 | C9: 0.04 | D9: 0.04 | E9: 0.04 | F9: 0.04 | G9: 0.04 | H9: 0.04
B11: Year 1 | C11: Year 2 | D11: Year 3 | E11: Year 4 | F11: Year 5 | G11: Year 6 | H11: Year 7
A12: Revenues
A13: Rental Income | B13: ='Quick HELOC Loan Calc'!C15 -> 16200 | C13: =SUM(B$13+(C$7*B$13)) -> 16686 | D13: =SUM(C$13+(D$7*C$13)) -> 17186.58 | E13: =SUM(D$13+(E$7*D$13)) -> 17702.177 | F13: =SUM(E$13+(F$7*E$13)) -> 18233.243 | G13: =SUM(F$13+(G$7*F$13)) -> 18780.24 | H13: =SUM(G$13+(H$7*G$13)) -> 19343.647
B14: =B13/12 -> 1350 | C14: =C13/12 -> 1390.5 | D14: =D13/12 -> 1432.215 | E14: =E13/12 -> 1475.1815 | F14: =F13/12 -> 1519.4369 | G14: =G13/12 -> 1565.02 | H14: =H13/12 -> 1611.9706
A15: Vacancy Rate | B15: =-(B13*B9) -> -648 | C15: =-(C13*C9) -> -667.44 | D15: =-(D13*D9) -> -687.4632 | E15: =-(E13*E9) -> -708.0871 | F15: =-(F13*F9) -> -729.32971 | G15: =-(G13*G9) -> -751.2096 | H15: =-(H13*H9) -> -773.74589
A16: Net Rental Income | B16: =SUM(B13,B15) -> 15552 | C16: =SUM(C13,C15) -> 16018.56 | D16: =SUM(D13,D15) -> 16499.117 | E16: =SUM(E13,E15) -> 16994.09 | F16: =SUM(F13,F15) -> 17503.913 | G16: =SUM(G13,G15) -> 18029.03 | H16: =SUM(H13,H15) -> 18569.901
A18: Expenses
A19: Property Taxes | B19: ='Quick HELOC Loan Calc'!C23 -> 1284 | C19: =B$19+(B$19*C$8) -> 1303.26 | D19: =C$19+(C$19*D$8) -> 1322.8089 | E19: =D$19+(D$19*E$8) -> 1342.651 | F19: =E$19+(E$19*F$8) -> 1362.7908 | G19: =F$19+(F$19*G$8) -> 1383.2327 | H19: =G$19+(G$19*H$8) -> 1403.9812
A20: Insurance | B20: ='Quick HELOC Loan Calc'!C24 -> 960 | C20: =B20+(B20*C8) -> 974.4 | D20: =C20+(C20*D8) -> 989.016 | E20: =D20+(D20*E8) -> 1003.8512 | F20: =E20+(E20*F8) -> 1018.909 | G20: =F20+(F20*G8) -> 1034.1926 | H20: =G20+(G20*H8) -> 1049.7055
A21: Property Mgmt | C21: =C13*0.08 -> 1334.88 | D21: =D13*0.08 -> 1374.9264 | E21: =E13*0.08 -> 1416.1742 | F21: =F13*0.08 -> 1458.6594 | G21: =G13*0.08 -> 1502.4192 | H21: =H13*0.08 -> 1547.4918 | I21: $5000 management credit
A22: Lease Fee | B22: 0 | C22: 0 | D22: 250 | E22: 0 | F22: 250 | G22: 0 | H22: 250
A23: Management Renewal Fee | D23: 250 | E23: 250 | F23: 250 | H23: 250
A24: HOA | B24: ='[1]Input Info'!B14 -> 0 | C24: =B24+(B24*C8) -> 0 | D24: =C24+(C24*D8) -> 0 | E24: =D24+(D24*E8) -> 0 | F24: =E24+(E24*F8) -> 0 | G24: =F24+(F24*G8) -> 0 | H24: =G24+(G24*H8) -> 0
A25: Maintenance & Repairs | B25: =B13*B5 -> 648 | C25: =C13*C5 -> 667.44 | D25: =D13*D5 -> 687.4632 | E25: =E13*E5 -> 708.0871 | F25: =F13*F5 -> 729.32971 | G25: =G13*G5 -> 751.2096 | H25: =H13*H5 -> 773.74589
A26: Yearly Inspection | B26: 100 | C26: 100 | D26: 100 | E26: 100 | F26: 100 | G26: 100 | H26: 100
A27: Umbrella Insurance | B27: =33*12 -> 396 | C27: =33*12 -> 396 | D27: =33*12 -> 396 | E27: =33*12 -> 396 | F27: =33*12 -> 396 | G27: =33*12 -> 396 | H27: =33*12 -> 396
A28: Total Expenses | B28: =SUM(B19:B27) -> 3388 | C28: =SUM(C19:C27) -> 4775.98 | D28: =SUM(D19:D27) -> 5370.2145 | E28: =SUM(E19:E27) -> 5216.7636 | F28: =SUM(F19:F27) -> 5565.6889 | G28: =SUM(G19:G27) -> 5167.0541 | H28: =SUM(H19:H27) -> 5770.9243
A30: Net Operating Income (NOI) | B30: =SUM(B16-B28) -> 12164 | C30: =SUM(C16-C28) -> 11242.58 | D30: =SUM(D16-D28) -> 11128.902 | E30: =SUM(E16-E28) -> 11777.327 | F30: =SUM(F16-F28) -> 11938.224 | G30: =SUM(G16-G28) -> 12861.976 | H30: =SUM(H16-H28) -> 12798.977
A32: Cash Flow
A33: NOI (Cash Available) | B33: =B30 -> 12164 | C33: =C30 -> 11242.58 | D33: =D30 -> 11128.902 | E33: =E30 -> 11777.327 | F33: =F30 -> 11938.224 | G33: =G30 -> 12861.976 | H33: =H30 -> 12798.977
A34: Conventional Mortgage | B34: =SUM('Quick HELOC Loan Calc'!$B$37*12) -> 69153.584 | C34: =SUM('Quick HELOC Loan Calc'!$B$37*12) -> 69153.584 | D34: =SUM('Quick HELOC Loan Calc'!$B$37*12) -> 69153.584 | E34: =SUM('Quick HELOC Loan Calc'!$B$37*12) -> 69153.584 | F34: =SUM('Quick HELOC Loan Calc'!$B$37*12) -> 69153.584 | G34: =SUM('Quick HELOC Loan Calc'!$B$37*12) -> 69153.584 | H34: =SUM('Quick HELOC Loan Calc'!$B$37*12) -> 69153.584
A35: HELOC Mortgage | B35: ='Quick HELOC Loan Calc'!C36 -> 7037.92 | I35: Interest Only - Pay off on 1 year anniversary
A36: Total Cash Flow | B36: =SUM(B33-B34-B35) -> -64027.504 | C36: =SUM(C33-C34-C35) -> -57911.004 | D36: =SUM(D33-D34-D35) -> -58024.681 | E36: =SUM(E33-E34-E35) -> -57376.257 | F36: =SUM(F33-F34-F35) -> -57215.36 | G36: =SUM(G33-G34-G35) -> -56291.607 | H36: =SUM(H33-H34-H35) -> -56354.607
A37: Monthly Cash Flow | B37: =B36/12 -> -5335.6253 | C37: =C36/12 -> -4825.917 | D37: =D36/12 -> -4835.3901 | E37: =E36/12 -> -4781.3548 | F37: =F36/12 -> -4767.9466 | G37: =G36/12 -> -4690.9673 | H37: =H36/12 -> -4696.2172
A38: DSCR | B38: =B33/SUM(B34:B35) -> 0.15965035 | C38: =C33/SUM(C34:C35) -> 0.16257408 | D38: =D33/SUM(D34:D35) -> 0.16093023 | E38: =E33/SUM(E34:E35) -> 0.17030682 | F38: =F33/SUM(F34:F35) -> 0.17263348 | G38: =G33/SUM(G34:G35) -> 0.18599146 | H38: =H33/SUM(H34:H35) -> 0.18508046
A39: Equity Accrued | B39: =-CUMPRINC('Quick HELOC Loan Calc'!$H$7/12,'Quick HELOC Loan Calc'!$H$8*12,'Quick HELOC Loan Calc'!$B$8,1,12,0) -> 9823.3065 | C39: =-CUMPRINC('Quick HELOC Loan Calc'!$H$7/12,'Quick HELOC Loan Calc'!$H$8*12,'Quick HELOC Loan Calc'!$B$8,13,24,0) -> 10494.23 | D39: =-CUMPRINC('Quick HELOC Loan Calc'!$H$7/12,'Quick HELOC Loan Calc'!$H$8*12,'Quick HELOC Loan Calc'!$B$8,25,36,0) -> 11210.977 | E39: =-CUMPRINC('Quick HELOC Loan Calc'!$H$7/12,'Quick HELOC Loan Calc'!$H$8*12,'Quick HELOC Loan Calc'!$B$8,37,48,0) -> 11976.677 | F39: =-CUMPRINC('Quick HELOC Loan Calc'!$H$7/12,'Quick HELOC Loan Calc'!$H$8*12,'Quick HELOC Loan Calc'!$B$8,49,60,0) -> 12794.673 | G39: =-CUMPRINC('Quick HELOC Loan Calc'!$H$7/12,'Quick HELOC Loan Calc'!$H$8*12,'Quick HELOC Loan Calc'!$B$8,61,72,0) -> 13668.539 | H39: =-CUMPRINC('Quick HELOC Loan Calc'!$H$7/12,'Quick HELOC Loan Calc'!$H$8*12,'Quick HELOC Loan Calc'!$B$8,73,84,0) -> 14602.088
A40: Appreciation | B40: =SUM(B6*'Quick HELOC Loan Calc'!$B$5) -> 40000 | C40: =(SUM(B40)+'Quick HELOC Loan Calc'!$B$5)*C$6 -> 41600 | D40: =('Quick HELOC Loan Calc'!$B$5+C40+B40)*D$6 -> 43264 | E40: =('Quick HELOC Loan Calc'!$B$5+D40+C40+B40)*E$6 -> 44994.56 | F40: =('Quick HELOC Loan Calc'!$B$5+E40+D40+C40+B40)*F$6 -> 46794.342 | G40: =('Quick HELOC Loan Calc'!$B$5+F40+E40+D40+C40+B40)*G$6 -> 48666.116 | H40: =('Quick HELOC Loan Calc'!$B$5+G40+F40+E40+D40+C40+B40)*H$6 -> 50612.761
A41: Total Return | B41: =SUM(B36+B39+B40) -> -14204.197 | C41: =SUM(C36+C39+C40) -> -5816.7739 | D41: =SUM(D36+D39+D40) -> -3549.7048 | E41: =SUM(E36+E39+E40) -> -405.0203 | F41: =SUM(F36+F39+F40) -> 2373.6561 | G41: =SUM(G36+G39+G40) -> 6043.0472 | H41: =SUM(H36+H39+H40) -> 8860.2419
A42: Total ROI | B42: =SUM(B41/'[1]Input Info'!$B$18) -> -0.33819517 | C42: =SUM(C41/'[1]Input Info'!$B$18) -> -0.13849462 | D42: =SUM(D41/'[1]Input Info'!$B$18) -> -0.08451678 | E42: =SUM(E41/'[1]Input Info'!$B$18) -> -0.0096433404 | F42: =SUM(F41/'[1]Input Info'!$B$18) -> 0.056515622 | G42: =SUM(G41/'[1]Input Info'!$B$18) -> 0.14388208 | H42: =SUM(H41/'[1]Input Info'!$B$18) -> 0.21095814
A43: Average ROI | G43: =AVERAGE(B42:H42) -> -0.022784867
A44: Estimated Value at Year 7 | G44: ='[1]Input Info'!B5+(SUM('7yr IRR Financing'!B40:H40)) -> 455931.78
A45: Loan Paid Down over 7 Years | G45: =SUM(B39:H39) -> 84570.49
A46: Total returns are based on calculations of external data and is subject to change. Estimated returns are estimated, and may not factor in all scenarios or costs. REI Nation, LLC and Premier Property Management Group, LLC have offered this estimator of returns in good faith. We realize that there are alternate methods to calculate return, and that some assumptions may not be applicable for your calculations. Data provided for the calculation is the user’s responsibility. We do not make any representations or warranties of any kind on the information provided. We also disclaim any liability or responsibility for the accuracy, correctness, or completeness of any information provided. *All calculations include estimated maintenance, estimated vacancy, estimated property management fees, estimated equity accrual, estimated property taxes, estimated insurance and estimated appreciation.

Sheet 10 Year
A1: Year | B1: 1 | C1: 2 | D1: 3 | E1: 4 | F1: 5 | G1: 6 | H1: 7 | I1: 8 | J1: 9 | K1: 10
A2: Property Income | L2: Desired Return | M2: 0.08 | N2: match stock market
A3: Rent | B3: ='Quick HELOC Loan Calc'!C15 -> 16200 | C3: =B3*(1+C5) -> 16783.2 | D3: =C3*(1+D5) -> 17387.395 | E3: =D3*(1+E5) -> 18013.341 | F3: =E3*(1+F5) -> 18661.822 | G3: =F3*(1+G5) -> 19333.647 | H3: =G3*(1+H5) -> 20029.659 | I3: =H3*(1+I5) -> 20750.726 | J3: =I3*(1+J5) -> 21497.752 | K3: =J3*(1+K5) -> 22271.672
A4: Monthly Rent | B4: =B3/12 -> 1350 | C4: =C3/12 -> 1398.6 | D4: =D3/12 -> 1448.9496 | E4: =E3/12 -> 1501.1118 | F4: =F3/12 -> 1555.1518 | G4: =G3/12 -> 1611.1373 | H4: =H3/12 -> 1669.1382 | I4: =I3/12 -> 1729.2272 | ... K4: =K3/12 -> 1855.9726 | M4: IRR | P4: NPV
A5: Rent Appreciation | B5: 0.036 | C5: =$B$5 -> 0.036 | D5: =$B$5 -> 0.036 | E5: =$B$5 -> 0.036 | F5: =$B$5 -> 0.036 | G5: =$B$5 -> 0.036 | H5: =$B$5 -> 0.036 | I5: =$B$5 -> 0.036 | J5: =$B$5 -> 0.036 | K5: =$B$5 -> 0.036 | M5: 45536 | N5: 0 | O5: =-SUM('Quick HELOC Loan Calc'!B6:B7) -> -140000 | P5: =O5 -> -140000
A6: Vacancy Loss | B6: 0.04 | C6: =$B$6 -> 0.04 | D6: =$B$6 -> 0.04 | E6: =$B$6 -> 0.04 | F6: =$B$6 -> 0.04 | G6: =$B$6 -> 0.04 | H6: =$B$6 -> 0.04 | I6: =$B$6 -> 0.04 | J6: =$B$6 -> 0.04 | K6: =$B$6 -> 0.04 | M6: 45901 | N6: 1 | O6: =B30 -> -64027.504 | P6: =O6/(1+$M$2)^N6 -> -59284.726
M7: 46266 | N7: 2 | O7: =C30 -> -57861.456 | P7: =O7/(1+$M$2)^N7 -> -49606.872
A8: Operating Income | B8: =B3*(1-B6) -> 15552 | C8: =C3*(1-C6) -> 16111.872 | D8: =D3*(1-D6) -> 16691.899 | E8: =E3*(1-E6) -> 17292.808 | F8: =F3*(1-F6) -> 17915.349 | G8: =G3*(1-G6) -> 18560.301 | H8: =H3*(1-H6) -> 19228.472 | I8: =I3*(1-I6) -> 19920.697 | ... K8: =K3*(1-K6) -> 21380.805 | M8: 46631 | N8: 3 | O8: =D30 -> -57919.908 | P8: =O8/(1+$M$2)^N8 -> -45978.69
M9: 46997 | N9: 4 | O9: =E30 -> -57212.363 | P9: =O9/(1+$M$2)^N9 -> -42052.794
A10: Property Expenses | M10: 47362 | N10: 5 | O10: =F30 -> -56988.166 | P10: =O10/(1+$M$2)^N10 -> -38785.188
A11: Management Fee | B11: =0.08 -> 0.08 | C11: =$B$11 -> 0.08 | D11: =$B$11 -> 0.08 | E11: =$B$11 -> 0.08 | F11: =$B$11 -> 0.08 | G11: =$B$11 -> 0.08 | H11: =$B$11 -> 0.08 | I11: =$B$11 -> 0.08 | J11: =$B$11 -> 0.08 | K11: =$B$11 -> 0.08 | M11: 47727 | N11: 6 | O11: =G30 -> -55996.721 | P11: =O11/(1+$M$2)^N11 -> -35287.433
A12: Management Fees | B12: =IF('Quick HELOC Loan Calc'!$E$22=1,"Waived",'Quick HELOC Loan Calc'!$C$22) -> Waived | C12: =C3*C11 -> 1342.656 | D12: =D3*D11 -> 1390.9916 | E12: =E3*E11 -> 1441.0673 | F12: =F3*F11 -> 1492.9457 | G12: =G3*G11 -> 1546.6918 | H12: =H3*H11 -> 1602.3727 | I12: =I3*I11 -> 1660.0581 | J12: =J3*J11 -> 1719.8202 | K12: =K3*K11 -> 1781.7337 | M12: 48092 | N12: 7 | O12: =H30 -> -55987.409 | P12: =O12/(1+$M$2)^N12 -> -32668.115
A13: Property Taxes (1.5%) | B13: ='Quick HELOC Loan Calc'!C23 -> 1284 | C13: =B36*($B$13/'Quick HELOC Loan Calc'!$B$5) -> 1335.36 | D13: =C36*($B$13/'Quick HELOC Loan Calc'!$B$5) -> 1386.72 | E13: =D36*($B$13/'Quick HELOC Loan Calc'!$B$5) -> 1440.1344 | F13: =E36*($B$13/'Quick HELOC Loan Calc'!$B$5) -> 1495.6032 | G13: =F36*($B$13/'Quick HELOC Loan Calc'!$B$5) -> 1553.2086 | H13: =G36*($B$13/'Quick HELOC Loan Calc'!$B$5) -> 1613.0327 | I13: =H36*($B$13/'Quick HELOC Loan Calc'!$B$5) -> 1675.161 | J13: =I36*($B$13/'Quick HELOC Loan Calc'!$B$5) -> 1739.6824 | K13: =J36*($B$13/'Quick HELOC Loan Calc'!$B$5) -> 1806.6888 | M13: 48458 | N13: 8 | O13: =I30 -> -54959.586 | P13: =O13/(1+$M$2)^N13 -> -29692.954
A14: Insurance (1.5%) | B14: ='Quick HELOC Loan Calc'!C24 -> 960 | C14: =B14+(B14*0.015) -> 974.4 | D14: =C14+(C14*0.015) -> 989.016 | E14: =D14+(D14*0.015) -> 1003.8512 | F14: =E14+(E14*0.015) -> 1018.909 | G14: =F14+(F14*0.015) -> 1034.1926 | H14: =G14+(G14*0.015) -> 1049.7055 | I14: =H14+(H14*0.015) -> 1065.4511 | J14: =I14+(I14*0.015) -> 1081.4329 | K14: =J14+(J14*0.015) -> 1097.6544 | M14: 48823 | N14: 9 | O14: =J30 -> -54912.587 | P14: =O14/(1+$M$2)^N14 -> -27469.965
A15: Maintenance/Repairs (4%) | B15: =IF('Quick HELOC Loan Calc'!$C$29=0,"Seller Covered",'Quick HELOC Loan Calc'!$C$29) -> 648 | C15: =C3*0.04 -> 671.328 | D15: =D3*0.04 -> 695.49581 | E15: =E3*0.04 -> 720.53366 | F15: =F3*0.04 -> 746.47287 | G15: =G3*0.04 -> 773.34589 | H15: =H3*0.04 -> 801.18634 | I15: =I3*0.04 -> 830.02905 | J15: =J3*0.04 -> 859.9101 | K15: =K3*0.04 -> 890.86686 | M15: 49188 | N15: 10 | O15: =K30+K36-('Quick HELOC Loan Calc'!B8-SUM('10 Year'!B38:K38)) -> 641816.22 | P15: =O15/(1+$M$2)^N15 -> 297285.09
A16: Leasing Fee | B16: 0 | C16: 0 | D16: 250 | E16: 0 | F16: 250 | G16: 0 | H16: 250 | I16: 0 | J16: 250 | K16: 0 | O16: =XIRR(O5:O15,M5:M15) -> -0.0035256736 | P16: =SUM(P5:P15) -> -203541.64
A17: Annual Safety Inspection | B17: 100 | C17: 100 | D17: 100 | E17: 100 | F17: 100 | G17: 100 | H17: 100 | I17: 100 | J17: 100 | K17: 100
A18: Management Renewal Fee | D18: 250 | E18: 250 | F18: 250 | H18: 250 | J18: 250 | K18: 250
A19: HOA Fees | B19: 0 | C19: 0 | D19: 0 | E19: 0 | F19: 0 | G19: 0 | H19: 0 | I19: 0 | J19: 0 | K19: 0
A20: Umbrella Insurance | B20: =33*12 -> 396 | C20: =33*12 -> 396 | D20: =33*12 -> 396 | E20: =33*12 -> 396 | F20: =33*12 -> 396 | G20: =33*12 -> 396 | H20: =33*12 -> 396 | I20: =33*12 -> 396 | ... K20: =33*12 -> 396
A22: Operating Expenses | B22: =SUM(B12:B20) -> 3388 | C22: =SUM(C12:C20) -> 4819.744 | D22: =SUM(D12:D20) -> 5458.2234 | E22: =SUM(E12:E20) -> 5351.5866 | F22: =SUM(F12:F20) -> 5749.9308 | G22: =SUM(G12:G20) -> 5403.4389 | H22: =SUM(H12:H20) -> 6062.2973 | I22: =SUM(I12:I20) -> 5726.6993 | ... K22: =SUM(K12:K20) -> 6322.9438
A24: Net Operating Income (NOI) | B24: =B8-B22 -> 12164 | C24: =C8-C22 -> 11292.128 | D24: =D8-D22 -> 11233.676 | E24: =E8-E22 -> 11941.221 | F24: =F8-F22 -> 12165.418 | G24: =G8-G22 -> 13156.863 | H24: =H8-H22 -> 13166.175 | I24: =I8-I22 -> 14193.998 | ... K24: =K8-K22 -> 15057.861
A25: Capitalization Rate (CAP Rate) | B25: =B24/'Quick HELOC Loan Calc'!$B$5 -> 0.012164 | C25: =C24/'Quick HELOC Loan Calc'!$B$5 -> 0.011292128 | D25: =D24/'Quick HELOC Loan Calc'!$B$5 -> 0.011233676 | E25: =E24/'Quick HELOC Loan Calc'!$B$5 -> 0.011941221 | F25: =F24/'Quick HELOC Loan Calc'!$B$5 -> 0.012165418 | G25: =G24/'Quick HELOC Loan Calc'!$B$5 -> 0.013156863 | H25: =H24/'Quick HELOC Loan Calc'!$B$5 -> 0.013166175 | I25: =I24/'Quick HELOC Loan Calc'!$B$5 -> 0.014193998 | ... K25: =K24/'Quick HELOC Loan Calc'!$B$5 -> 0.015057861
A27: Key Investment Indicators
A28: Mortgage Payment | B28: =PMT('Quick HELOC Loan Calc'!$H$7/12, 'Quick HELOC Loan Calc'!$H$8*12,'Quick HELOC Loan Calc'!$B$8)*12 -> -69153.584 | C28: =PMT('Quick HELOC Loan Calc'!$H$7/12, 'Quick HELOC Loan Calc'!$H$8*12,'Quick HELOC Loan Calc'!$B$8)*12 -> -69153.584 | D28: =PMT('Quick HELOC Loan Calc'!$H$7/12, 'Quick HELOC Loan Calc'!$H$8*12,'Quick HELOC Loan Calc'!$B$8)*12 -> -69153.584 | E28: =PMT('Quick HELOC Loan Calc'!$H$7/12, 'Quick HELOC Loan Calc'!$H$8*12,'Quick HELOC Loan Calc'!$B$8)*12 -> -69153.584 | F28: =PMT('Quick HELOC Loan Calc'!$H$7/12, 'Quick HELOC Loan Calc'!$H$8*12,'Quick HELOC Loan Calc'!$B$8)*12 -> -69153.584 | G28: =PMT('Quick HELOC Loan Calc'!$H$7/12, 'Quick HELOC Loan Calc'!$H$8*12,'Quick HELOC Loan Calc'!$B$8)*12 -> -69153.584 | H28: =PMT('Quick HELOC Loan Calc'!$H$7/12, 'Quick HELOC Loan Calc'!$H$8*12,'Quick HELOC Loan Calc'!$B$8)*12 -> -69153.584 | I28: =PMT('Quick HELOC Loan Calc'!$H$7/12, 'Quick HELOC Loan Calc'!$H$8*12,'Quick HELOC Loan Calc'!$B$8)*12 -> -69153.584 | ... K28: =PMT('Quick HELOC Loan Calc'!$H$7/12, 'Quick HELOC Loan Calc'!$H$8*12,'Quick HELOC Loan Calc'!$B$8)*12 -> -69153.584
A29: ="HELOC Payment ($"& SUM('Quick HELOC Loan Calc'!B6,'Quick HELOC Loan Calc'!B7)-('Quick HELOC Loan Calc'!$C$5)&")" -> HELOC Payment ($92974) | B29: =-'Quick HELOC Loan Calc'!$C$36 -> -7037.92
A30: Net Cash Flow | B30: =B24+B28+B29 -> -64027.504 | C30: =C24+C28+C29 -> -57861.456 | D30: =D24+D28+D29 -> -57919.908 | E30: =E24+E28+E29 -> -57212.363 | F30: =F24+F28+F29 -> -56988.166 | G30: =G24+G28+G29 -> -55996.721 | H30: =H24+H28+H29 -> -55987.409 | I30: =I24+I28+I29 -> -54959.586 | ... K30: =K24+K28+K29 -> -54095.723 | L30: =SUM(B30:K30) -> -569961.42 | M30: FV of all cash flows
A31: Monthly Cash Flow | B31: =B30/12 -> -5335.6253 | C31: =C30/12 -> -4821.788 | D31: =D30/12 -> -4826.659 | E31: =E30/12 -> -4767.6969 | F31: =F30/12 -> -4749.0138 | G31: =G30/12 -> -4666.3934 | H31: =H30/12 -> -4665.6174 | I31: =I30/12 -> -4579.9655 | ... K31: =K30/12 -> -4507.9769
A32: ="Discounted Cash Flow (DCF) @"&M2&"% return" -> Discounted Cash Flow (DCF) @0.08% return | B32: =B30/(1+$M$2)^B1 -> -59284.726 | C32: =C30/(1+$M$2)^C1 -> -49606.872 | D32: =D30/(1+$M$2)^D1 -> -45978.69 | E32: =E30/(1+$M$2)^E1 -> -42052.794 | F32: =F30/(1+$M$2)^F1 -> -38785.188 | G32: =G30/(1+$M$2)^G1 -> -35287.433 | H32: =H30/(1+$M$2)^H1 -> -32668.115 | I32: =I30/(1+$M$2)^I1 -> -29692.954 | ... K32: =K30/(1+$M$2)^K1 -> -25056.787 | L32: =SUM(B32:K32) -> -385883.52 | M32: PV of all cash flows
A33: Cash on Cash ROI | B33: =B30/(SUM('Quick HELOC Loan Calc'!$B$7,'Quick HELOC Loan Calc'!$B$6)) -> -0.45733931 | C33: =C30/(SUM('Quick HELOC Loan Calc'!$B$7,'Quick HELOC Loan Calc'!$B$6)) -> -0.41329611 | D33: =D30/(SUM('Quick HELOC Loan Calc'!$B$7,'Quick HELOC Loan Calc'!$B$6)) -> -0.41371363 | E33: =E30/(SUM('Quick HELOC Loan Calc'!$B$7,'Quick HELOC Loan Calc'!$B$6)) -> -0.40865973 | F33: =F30/(SUM('Quick HELOC Loan Calc'!$B$7,'Quick HELOC Loan Calc'!$B$6)) -> -0.40705833 | G33: =G30/(SUM('Quick HELOC Loan Calc'!$B$7,'Quick HELOC Loan Calc'!$B$6)) -> -0.39997658 | H33: =H30/(SUM('Quick HELOC Loan Calc'!$B$7,'Quick HELOC Loan Calc'!$B$6)) -> -0.39991006 | I33: =I30/(SUM('Quick HELOC Loan Calc'!$B$7,'Quick HELOC Loan Calc'!$B$6)) -> -0.39256847 | ... K33: =K30/(SUM('Quick HELOC Loan Calc'!$B$7,'Quick HELOC Loan Calc'!$B$6)) -> -0.38639802
A35: Property Appreciation | B35: 0.04 | C35: =$B$35 -> 0.04 | D35: =$B$35 -> 0.04 | E35: =$B$35 -> 0.04 | F35: =$B$35 -> 0.04 | G35: =$B$35 -> 0.04 | H35: =$B$35 -> 0.04 | I35: =$B$35 -> 0.04 | J35: =$B$35 -> 0.04 | K35: =$B$35 -> 0.04
A36: Property Value | B36: ='Quick HELOC Loan Calc'!$B$5*(1+'10 Year'!B35) -> 1040000 | C36: =B36+B37 -> 1080000 | D36: =C36+C37 -> 1121600 | E36: =D36+D37 -> 1164800 | F36: =E36+E37 -> 1209664 | G36: =F36+F37 -> 1256256 | H36: =G36+G37 -> 1304642.6 | I36: =H36+H37 -> 1354892.8 | J36: =I36+I37 -> 1407078.5 | K36: =J36+J37 -> 1461274.2
A37: Property Appreciation | B37: ='Quick HELOC Loan Calc'!$B$5*B35 -> 40000 | C37: =B36*C35 -> 41600 | D37: =C36*D35 -> 43200 | E37: =D36*E35 -> 44864 | F37: =E36*F35 -> 46592 | G37: =F36*G35 -> 48386.56 | H37: =G36*H35 -> 50250.24 | I37: =H36*I35 -> 52185.702 | J37: =I36*J35 -> 54195.712 | K37: =J36*K35 -> 56283.14
A38: Mortgage Principle Reduction | B38: =-CUMPRINC('Quick HELOC Loan Calc'!$H$7/12,'Quick HELOC Loan Calc'!$H$8*12,'Quick HELOC Loan Calc'!$B$8,1,12,0) -> 9823.3065 | C38: =-CUMPRINC('Quick HELOC Loan Calc'!$H$7/12,'Quick HELOC Loan Calc'!$H$8*12,'Quick HELOC Loan Calc'!$B$8,13,24,0) -> 10494.23 | D38: =-CUMPRINC('Quick HELOC Loan Calc'!$H$7/12,'Quick HELOC Loan Calc'!$H$8*12,'Quick HELOC Loan Calc'!$B$8,25,36,0) -> 11210.977 | E38: =-CUMPRINC('Quick HELOC Loan Calc'!$H$7/12,'Quick HELOC Loan Calc'!$H$8*12,'Quick HELOC Loan Calc'!$B$8,37,48,0) -> 11976.677 | F38: =-CUMPRINC('Quick HELOC Loan Calc'!$H$7/12,'Quick HELOC Loan Calc'!$H$8*12,'Quick HELOC Loan Calc'!$B$8,49,60,0) -> 12794.673 | G38: =-CUMPRINC('Quick HELOC Loan Calc'!$H$7/12,'Quick HELOC Loan Calc'!$H$8*12,'Quick HELOC Loan Calc'!$B$8,61,72,0) -> 13668.539 | H38: =-CUMPRINC('Quick HELOC Loan Calc'!$H$7/12,'Quick HELOC Loan Calc'!$H$8*12,'Quick HELOC Loan Calc'!$B$8,73,84,0) -> 14602.088 | I38: =-CUMPRINC('Quick HELOC Loan Calc'!$H$7/12,'Quick HELOC Loan Calc'!$H$8*12,'Quick HELOC Loan Calc'!$B$8,85,96,0) -> 15599.398 | J38: =-CUMPRINC('Quick HELOC Loan Calc'!$H$7/12,'Quick HELOC Loan Calc'!$H$8*12,'Quick HELOC Loan Calc'!$B$8,97,108,0) -> 16664.823 | K38: =-CUMPRINC('Quick HELOC Loan Calc'!$H$7/12,'Quick HELOC Loan Calc'!$H$8*12,'Quick HELOC Loan Calc'!$B$8,109,120,0) -> 17803.017
A39: Net Tax Savings (33% Bracket) | B39: =B30*0.25 -> -16006.876 | C39: =C30*0.25 -> -14465.364 | D39: =D30*0.25 -> -14479.977 | E39: =E30*0.25 -> -14303.091 | F39: =F30*0.25 -> -14247.041 | G39: =G30*0.25 -> -13999.18 | H39: =H30*0.25 -> -13996.852 | I39: =I30*0.25 -> -13739.896 | ... K39: =K30*0.25 -> -13523.931
A40: Tax ROI | B40: =B39/SUM('Quick HELOC Loan Calc'!$B$6:$B$7) -> -0.11433483 | C40: =C39/SUM('Quick HELOC Loan Calc'!$B$6:$B$7) -> -0.10332403 | D40: =D39/SUM('Quick HELOC Loan Calc'!$B$6:$B$7) -> -0.10342841 | E40: =E39/SUM('Quick HELOC Loan Calc'!$B$6:$B$7) -> -0.10216493 | F40: =F39/SUM('Quick HELOC Loan Calc'!$B$6:$B$7) -> -0.10176458 | G40: =G39/SUM('Quick HELOC Loan Calc'!$B$6:$B$7) -> -0.099994145 | H40: =H39/SUM('Quick HELOC Loan Calc'!$B$6:$B$7) -> -0.099977516 | I40: =I39/SUM('Quick HELOC Loan Calc'!$B$6:$B$7) -> -0.098142118 | ... K40: =K39/SUM('Quick HELOC Loan Calc'!$B$6:$B$7) -> -0.096599505
A41: Total Return (Not counting appreciation) | B41: =SUM(B30,B38,B39) -> -70211.073 | C41: =SUM(C30,C38,C39) -> -61832.59 | D41: =SUM(D30,D38,D39) -> -61188.908 | E41: =SUM(E30,E38,E39) -> -59538.777 | F41: =SUM(F30,F38,F39) -> -58440.534 | G41: =SUM(G30,G38,G39) -> -56327.363 | H41: =SUM(H30,H38,H39) -> -55382.173 | I41: =SUM(I30,I38,I39) -> -53100.084 | ... K41: =SUM(K30,K38,K39) -> -49816.637
A42: Total ROI | B42: =B41/SUM('Quick HELOC Loan Calc'!$B$6:$B$7) -> -0.50150767 | C42: =C41/SUM('Quick HELOC Loan Calc'!$B$6:$B$7) -> -0.44166136 | D42: =D41/SUM('Quick HELOC Loan Calc'!$B$6:$B$7) -> -0.43706363 | E42: =E41/SUM('Quick HELOC Loan Calc'!$B$6:$B$7) -> -0.42527698 | F42: =F41/SUM('Quick HELOC Loan Calc'!$B$6:$B$7) -> -0.41743238 | G42: =G41/SUM('Quick HELOC Loan Calc'!$B$6:$B$7) -> -0.40233831 | H42: =H41/SUM('Quick HELOC Loan Calc'!$B$6:$B$7) -> -0.39558695 | I42: =I41/SUM('Quick HELOC Loan Calc'!$B$6:$B$7) -> -0.37928632 | ... K42: =K41/SUM('Quick HELOC Loan Calc'!$B$6:$B$7) -> -0.35583312 | L42: =SUM(B42:K42)/K1 -> -0.41272432 | M42: AAR
L43: =('10 Year'!K36/'Quick HELOC Loan Calc'!B5)^(1/'10 Year'!K1)-1 -> 0.038659439 | M43: CAGR
A45: Total Property Equity (not counting appreciation) | B45: =SUM('Quick HELOC Loan Calc'!$B$7,'10 Year'!B38) -> 109823.31 | C45: =B45+C38 -> 120317.54 | D45: =C45+D38 -> 131528.51 | E45: =D45+E38 -> 143505.19 | F45: =E45+F38 -> 156299.86 | G45: =F45+G38 -> 169968.4 | H45: =G45+H38 -> 184570.49 | I45: =H45+I38 -> 200169.89 | J45: =I45+J38 -> 216834.71 | K45: =J45+K38 -> 234637.73
K46: =(K45-B45)/B45 -> 1.1365021 | L46: =(K45/B45)^(1/K1)-1 -> 0.078873021 | M46: Appreciation CAGR

Sheet Calculators
A3: Year | C3: Annual ROI | G3: Year | I3: Annual ROI | S3: IRR | T3: =XIRR(T4:T10,R4:R10) -> 0.21632629
A4: 0 | B4: 100000 | G4: 0 | H4: 100000 | M4: Present Value=Future Value /( 1+i)^n | R4: 45292 | S4: Initial Investment | T4: -8500000
A5: =A4+1 -> 1 | B5: 110000 | C5: =(B5/B4)-1 -> 0.1 | G5: =G4+1 -> 1 | H5: 110000 | I5: =(H5/H4)-1 -> 0.1 | M5: interest | N5: 0.08 | R5: =R4+365 -> 45657 | S5: Year 1 Cashflow | T5: =-$T$4*$U$5 -> 1360000 | U5: 0.16 | V5: Cash On Cash
A6: =A5+1 -> 2 | B6: 105000 | C6: =(B6/B5)-1 -> -0.045454545 | G6: =G5+1 -> 2 | H6: 105000 | I6: =(H6/H5)-1 -> -0.045454545 | M6: time (yrs) | N6: 5 | O6: =N6*12 -> 60 | R6: =R5+365 -> 46022 | S6: Year 2 Cashflow | T6: =-$T$4*$U$5 -> 1360000
A7: =A6+1 -> 3 | B7: 120000 | C7: =(B7/B6)-1 -> 0.14285714 | G7: =G6+1 -> 3 | H7: 120000 | I7: =(H7/H6)-1 -> 0.14285714 | R7: =R6+365 -> 46387 | S7: Year 3 Cashflow | T7: =-$T$4*$U$5 -> 1360000
A8: =A7+1 -> 4 | B8: =B7+5000 -> 125000 | C8: =(B8/B7)-1 -> 0.041666667 | G8: =G7+1 -> 4 | H8: =H7+5000 -> 125000 | I8: =(H8/H7)-1 -> 0.041666667 | R8: =R7+365 -> 46752 | S8: Year 4 Cashflow | T8: =-$T$4*$U$5 -> 1360000
A9: =A8+1 -> 5 | B9: =B8+5000 -> 130000 | C9: =(B9/B8)-1 -> 0.04 | G9: =G8+1 -> 5 | H9: =H8+5000 -> 130000 | I9: =(H9/H8)-1 -> 0.04 | R9: =R8+365 -> 47117 | S9: Year 5 Cashflow | T9: =-$T$4*$U$5 -> 1360000
A10: =A9+1 -> 6 | B10: =B9+5000 -> 135000 | C10: =(B10/B9)-1 -> 0.038461538 | R10: =R9+365 -> 47482 | S10: 6 | T10: =-T4*(1+U10)^S10 -> 14813534 | U10: 0.097 | V10: Assumed Appreciation
A11: =A10+1 -> 7 | B11: =B10+5000 -> 140000 | C11: =(B11/B10)-1 -> 0.037037037 | I11: =(H9-H4)/H4 -> 0.3 | J11: ROI
A12: =A11+1 -> 8 | B12: =B11+5000 -> 145000 | C12: =(B12/B11)-1 -> 0.035714286 | I12: =SUM(I5:I9)/COUNT(I5:I9) -> 0.055813853 | J12: AAR
A13: =A12+1 -> 9 | B13: =B12+5000 -> 150000 | C13: =(B13/B12)-1 -> 0.034482759 | I13: =(H9/H4)^(1/COUNT(I4:I9))-1 -> 0.053873952 | J13: CAGR | M13: 0.105 | N13: projected Cash On Cash Return
A14: =A13+1 -> 10 | B14: =B13+5000 -> 155000 | C14: =(B14/B13)-1 -> 0.033333333 | I14: =H9/H4 -> 1.3 | J14: Equity Multiplier | M14: 8500000 | N14: initial investment
M15: =O15*12 -> 60 | N15: hold period | O15: 5
C16: =(B14-B4)/B4 -> 0.55 | D16: ROI
C17: =SUM(C5:C14)/COUNT(C5:C14) -> 0.045809822 | D17: AAR | M17: Future | N17: =M14*(1+M13/12)^(M15) -> 14336125 | O17: =N17/M14 -> 1.686603 | P17: Equity Multiple
C18: =(B14/B4)^(1/COUNT(C4:C14))-1 -> 0.044800014 | D18: CAGR | M18: CAGR | N18: =(N17/M14)^(1/(M15))-1 -> 0.00875
C19: =B14/B4 -> 1.55 | D19: Equity Multiplier

Sheet STR Calculator
H1: Heloc Down Payment | I1: 0.0825
H2: Heloc Loan Terms | I2: 20 | J2: yrs
A3: =B5 -> 852000 | B3: asking price | H3: HELOC Amount | I3: =SUM(B7+B6-C5-C4) -> 64280
C4: 5000 | D4: earnest money | H4: HELOC P&I Payment | I4: =-PMT($I$1/12,$I$2*12,I3) -> 547.7078 | J4: =I4*12 -> 6572.4936 | L4: IRR | M4: =IRR(M5:M11) -> -0.022363608
A5: Purchase Price | B5: 852000 | C5: 50000 | D5: cash | H5: HELOC Principle Payment | I5: =-PPMT($I$1/12,1,$I$2*12,I3) -> 105.7828 | J5: =I5*12 -> 1269.3936 | L5: Initial Investment | M5: =-B5 -> -852000
A6: Closing Costs (4%) | B6: =B5*0.04 -> 34080 | H6: HELOC Interest Only Payment | I6: =-IPMT($I$1/12,1,$I$2*12,I3) -> 441.925 | J6: =I6*12 -> 5303.1 | L6: Year 1 Cashflow | M6: ='STR 10 Year'!B32 -> 1974.819
A7: Down Payment | B7: =B5*C7 -> 85200 | C7: 0.1 | D7: downpayment | L7: Year 2 Cashflow | M7: ='10 Year'!C30 -> -57861.456
A8: Total Loan Amount | B8: =B5-B7 -> 766800 | H8: Conventional Loan Interest Rate | I8: 0.08 | L8: Year 3 Cashflow | M8: ='10 Year'!D30 -> -57919.908
H9: Loan Term | I9: 30 | J9: yrs | L9: Year 4 Cashflow | M9: ='10 Year'!E30 -> -57212.363
H10: Monthly Payment on Purchase Price | I10: =-PMT($I$8/12,$I$9*12,$B$8) -> 5626.5068 | L10: Year 5 Cashflow | M10: ='10 Year'!F30 -> -56988.166
A11: All In Price (Purchase+Repairs) | B11: =SUM(B5) -> 852000 | H11: Monthly Interest Payment on Purchase Price | I11: =-IPMT($I$8/12,1,$I$9*12,$B$8) -> 5112 | L11: 6 | M11: =B5*(1+0.02)^L11 -> 959490.38 | N11: assumes 2%/yr appreciation
A12: Estimated ARV (After Repair Value) | B12: =B5 -> 852000 | H12: Monthly Principle Payment on Purchase Price | I12: =-PPMT($I$8/12,1,$I$9*12,$B$8) -> 514.50675 | J12: =I12*12 -> 6174.081
B14: Nightly | C14: Monthly | D14: Annually | H14: Financials
A15: Average Rent | B15: 400 | C15: =B15*30.5 -> 12200 | D15: =C15*12 -> 146400 | H15: Cash On Cash Return (CoC) | I15: =C45/SUM(B6:B7) -> -0.029832168
A16: Occupancy Rate | B16: 0.85 | C16: =-C15*(1-B16) -> -1830 | D16: =C16*12 -> -21960 | H16: ROI (Return on Investment) | I16: =(SUM($B$6:$B$7)/B5) -> 0.14
A17: Additional Income (Laundry/Storage etc) | C17: 0 | D17: =C17*12 -> 0 | H17: ROE (Return on Equity) | I17: =C45/B7 -> -0.041765036
A18: Calculated Gross Revenue | C18: =SUM(C15:C17) -> 10370 | D18: =C18*12 -> 124440 | H18: Mortgage Pay Down yr 1 | I18: =PPMT(I8/12,1,I9*12,B8)*12 -> -6174.081
H19: Tax Savings at 33% | I19: =C45*0.33 -> -1174.2657
A21: Estimated Expenses | B21: Nightly/per stay | C21: Monthly | D21: Annually | H21: Rules of Thumb
A22: Management Fees | C22: =C15*E22 -> 0 | D22: =C22*12 -> 0 | E22: 0 | F22: =IF(E22=0,1,0) -> 1 | H22: 50% Rule
A23: Subscriptions (AirDnA/Pricelabs/Guesty/Hospitable) | C23: =20+40+40+40 -> 140 | D23: =C23*12 -> 1680 | H23: 2% Rule | I23: =$C$15/$B$5 -> 0.014319249
A24: AirBnB / VRBO Fee (3% of nightly) | C24: =C18*0.03 -> 311.1 | D24: =C24*12 -> 3733.2 | H24: DSCR | I24: =B41/(B43+B42) -> 1.0005715
A25: Property Taxes / Year | C25: 200 | D25: =C25*12 -> 2400 | E25: =D25/B5 -> 0.0028169014
A26: Insurance / Year | C26: 320 | D26: =C26*12 -> 3840 | E26: =D26/B5 -> 0.0045070423
A27: Cleaners (per stay, average 6/month) | B27: =E27*6/30.5 -> 29.508197 | C27: =B27*30.5 -> 900 | D27: =C27*12 -> 10800 | E27: 150 | K27: months
A28: Handyman | C28: 250 | D28: =C28*12 -> 3000 | H28: Emergency Fund Needed (6 months) | I28: =C39*$J$28+SUM(B42:B43)*$J$28 -> 62199.191 | J28: 6 | K28: months
A29: HOA / year | C29: 40 | D29: =C29*12 -> 480 | E29: =D29/B5 -> 0.00056338028 | I29: =I28/2 -> 31099.595 | J29: =J28/2 -> 3
A30: Electricity | C30: 1000 | D30: =C30*12 -> 12000
A31: Nat Gas | C31: 500 | D31: =C31*12 -> 6000
A32: WIFI / Cable | C32: 150 | D32: =C32*12 -> 1800
A33: Water/Sewer | C33: 350 | D33: =C33*12 -> 4200
A34: Building Maintenance (future Repairs) | C34: 100 | D34: =C34*12 -> 1200 | E34: =D34/D15 -> 0.0081967213
A35: Grounds Cleanup/Services Maintenance/Snow Removal | D35: =C35*12 -> 0
A36: City Permit Fees | C36: 0 | D36: =C36*12 -> 0
A37: Incidentals (Soap/Toilet Paper/Coffee/Creamer etc)
A38: Umbrella Insurance (Allstate Anchorage) | C38: 37 | D38: =C38*12 -> 444
A39: Totals | C39: =SUM(C22:C38) -> 4298.1 | D39: =SUM(D22:D38) -> 51577.2
A41: Net Operating Income | B41: =C18-C39 -> 6071.9 | C41: =D18-D39 -> 72862.8 | D41: DSCR | E41: =B41/(B43+B42) -> 1.0005715
A42: HELOC Payment (Interest Only) | B42: =I6 -> 441.925 | C42: =B42*12 -> 5303.1 | D42: =IF(B42=I6,1,0) -> 1
A43: Conventional Loan Payment | B43: =-PMT($I$8/12,$I$9*12,$B$8) -> 5626.5068 | C43: =B43*12 -> 67518.081 | D43: Cap Rate | E43: =C41/B5 -> 0.085519718
A44: PMI if down payment less than 20% | B44: =IF(C7<0.2,300,0) -> 300 | C44: =B44*12 -> 3600 | D44: =ROUND(C44/B8,4)&"% of loan" -> 0.0047% of loan
A45: Cash Flow | B45: =B41-B43-B42-B44 -> -296.53175 | C45: =B45*12 -> -3558.381
A48: Estimated CapEx | B48: Timeline of Repair (yrs) | C48: Cost per Unit | D48: Total Cost | E48: Monthly Cost
A49: Roof | B49: 5 | C49: 7000 | D49: =C49 -> 7000 | E49: =D49/B49/12 -> 116.66667
A50: Master Bath | B50: 10 | D50: =C50 -> 0 | E50: =D50/B50/12 -> 0
A51: Kitchen | B51: 10 | D51: =C51 -> 0 | E51: =D51/B51/12 -> 0
A52: Flooring | B52: 10 | C52: 8000 | D52: =C52 -> 8000 | E52: =D52/B52/12 -> 66.666667
A53: Guest baths | B53: 10 | D53: =C53 -> 0 | E53: =D53/B53/12 -> 0
A54: Exterior Paint | B54: 1 | D54: =C54 -> 0 | E54: =D54/B54/12 -> 0
A55: Interior Paint | B55: 6 | C55: 2000 | D55: =C55 -> 2000 | E55: =D55/B55/12 -> 27.777778
A56: Cabinets | B56: 10 | D56: =C56 -> 0 | E56: =D56/B56/12 -> 0
A57: Concrete walkways | B57: 4 | D57: =C57 -> 0 | E57: =D57/B57/12 -> 0
A58: Driveway Re-Pave (Asphalt) | B58: 1 | D58: =C58 -> 0 | E58: =D58/B58/12 -> 0
A59: Miscellaneous (light fixtures/door knobs etc) | B59: 10 | C59: 500 | D59: =C59 -> 500 | E59: =D59/B59/12 -> 4.1666667
A60: Total Estimated Repairs | E60: =SUM(E49:E59) -> 215.27778

Sheet Interest Rate Comparison
A1: Purchase Price | C1: 0.1 | D1: 0.15 | E1: 0.2 | F1: 0.25 | H1: 5% Increase in Down Payment | I1: Time to recoup
A2: ='STR Calculator'!B5 -> 852000 | B2: Down Payment | C2: =$A$2*C1 -> 85200 | D2: =$A$2*D1 -> 127800 | E2: =$A$2*E1 -> 170400 | F2: =$A$2*F1 -> 213000 | H2: =D2-C2 -> 42600
A3: 30 | B3: 0.0825 | C3: =PMT($B$3/12,$A$3*12,($A$2-C2)) -> -5760.7123 | D3: =PMT($B$3/12,$A$3*12,($A$2-D2)) -> -5440.6727 | E3: =PMT($B$3/12,$A$3*12,($A$2-E2)) -> -5120.6332 | F3: =PMT($B$3/12,$A$3*12,($A$2-F2)) -> -4800.5936 | G3: =B3 -> 0.0825 | H3: =D3-C3 -> 320.03957 | I3: =$H$2/H3/12 -> 11.092378
B4: 0.08 | C4: =PMT($B$4/12,$A$3*12,($A$2-C2)) -> -5626.5068 | D4: =PMT($B$4/12,$A$3*12,($A$2-D2)) -> -5313.923 | E4: =PMT($B$4/12,$A$3*12,($A$2-E2)) -> -5001.3393 | F4: =PMT($B$4/12,$A$3*12,($A$2-F2)) -> -4688.7556 | G4: =B4 -> 0.08 | H4: =D4-C4 -> 312.58371 | I4: =$H$2/H4/12 -> 11.356958
B5: 0.0775 | C5: =PMT($B$5/12,$A$3*12,($A$2-C2)) -> -5493.4491 | D5: =PMT($B$5/12,$A$3*12,($A$2-D2)) -> -5188.2575 | E5: =PMT($B$5/12,$A$3*12,($A$2-E2)) -> -4883.0659 | F5: =PMT($B$5/12,$A$3*12,($A$2-F2)) -> -4577.8742 | G5: =B5 -> 0.0775 | H5: =D5-C5 -> 305.19162 | I5: =$H$2/H5/12 -> 11.632036
B6: 0.075 | C6: =PMT($B$6/12,$A$3*12,($A$2-C2)) -> -5361.5769 | D6: =PMT($B$6/12,$A$3*12,($A$2-D2)) -> -5063.7115 | E6: =PMT($B$6/12,$A$3*12,($A$2-E2)) -> -4765.8461 | F6: =PMT($B$6/12,$A$3*12,($A$2-F2)) -> -4467.9807 | G6: =B6 -> 0.075 | H6: =D6-C6 -> 297.86538 | I6: =$H$2/H6/12 -> 11.918136
B7: 0.0725 | C7: =PMT($B$7/12,$A$3*12,($A$2-C2)) -> -5230.9277 | D7: =PMT($B$7/12,$A$3*12,($A$2-D2)) -> -4940.3206 | E7: =PMT($B$7/12,$A$3*12,($A$2-E2)) -> -4649.7135 | F7: =PMT($B$7/12,$A$3*12,($A$2-F2)) -> -4359.1064 | G7: =B7 -> 0.0725 | H7: =D7-C7 -> 290.6071 | I7: =$H$2/H7/12 -> 12.215806
B8: 0.07 | C8: =PMT($B$8/12,$A$3*12,($A$2-C2)) -> -5101.5395 | D8: =PMT($B$8/12,$A$3*12,($A$2-D2)) -> -4818.1207 | E8: =PMT($B$8/12,$A$3*12,($A$2-E2)) -> -4534.7018 | F8: =PMT($B$8/12,$A$3*12,($A$2-F2)) -> -4251.2829 | G8: =B8 -> 0.07 | H8: =D8-C8 -> 283.41886 | I8: =$H$2/H8/12 -> 12.525631
G9: Higher delta between P&I payment at higher interest rate compared to lower = shorter payout, when factoring in increased down payment for lower rate
A12: Down Payment % | B12: Down Payment | C12: Interest Rate | D12: ="Interest Paid on Down Payment by Year "&ROUND(I4,0) -> Interest Paid on Down Payment by Year 11 | E12: Down Payment Difference | F12: ="Interest Saved by Larger DownPayment @ year "&ROUND(I4,0) -> Interest Saved by Larger DownPayment @ year 11 | G12: Down Payment vs Interest Saved | H12: =ROUND(I4,0)&"yr FV of down payment saved @ 8%" -> 11yr FV of down payment saved @ 8% | I12: PV of Interest Saved/Lost | J12: ="Cum Interest Paid Year "&ROUND(I4,0) -> Cum Interest Paid Year 11 | K12: Interest Saved Compared to 10% Loan | L12: Total Interest Paid - Life of Loan
A13: =C1 -> 0.1 | B13: =$A$2*A13 -> 85200 | C13: =B4 -> 0.08 | D13: 71056 | E13: 0 | F13: 0 | G13: =F13-E13 -> 0 | H13: 0 | I13: 0 | J13: 639505 | K13: 0 | L13: 1270301
A14: =D1 -> 0.15 | B14: =$A$2*A14 -> 127800 | C14: =B4 -> 0.08 | D14: 106584 | E14: =B14-B13 -> 42600 | F14: =D14-D13 -> 35528 | G14: =F14-E14 -> -7072 | H14: =E14*(1+0.08)^I4 -> 102094.37 | I14: =G14/(1+C14)^I4 -> -2950.87 | J14: 603997 | K14: =J13-J14 -> 35508 | L14: 1199728 | M14: =L14+H14 -> 1301822.4
A15: =E1 -> 0.2 | B15: =$A$2*A15 -> 170400 | C15: =B5 -> 0.0775 | D15: 131454 | E15: =B15-B13 -> 85200 | F15: =D15-D13 -> 60398 | G15: =F15-E15 -> -24802 | H15: =E15*(1+0.08)^I4 -> 204188.73 | I15: =G15/(1+C15)^I4 -> -10624.904 | J15: 525816 | K15: =J13-J15 -> 113689 | L15: 1034105 | M15: =L15+H15 -> 1238293.7
K17: Present Value=Future Value /( 1+i)^n

Sheet Amoritization Scenario 10
A1: If deciding between different Down Payment % and Interest Rates, compare Cumulative Interest Payment over duration to recoup additional Down Payment Lump Sum, to see which is better. NPV / PV/FV money calculation
C3: sqft | J3: Interest | K3: ='Interest Rate Comparison'!B3 -> 0.0825 | N3: =K3/12 -> 0.006875 | O3: r | W3: Interest | X3: ='Interest Rate Comparison'!B4 -> 0.08 | AA3: =X3/12 -> 0.0066666667 | AB3: r | AJ3: Interest | AK3: ='Interest Rate Comparison'!B5 -> 0.0775 | AN3: =AK3/12 -> 0.0064583333 | AO3: r | AW3: Interest | AX3: ='Interest Rate Comparison'!B6 -> 0.075 | BA3: =AX3/12 -> 0.00625 | BB3: r | BJ3: Interest | BK3: ='Interest Rate Comparison'!B7 -> 0.0725 | BN3: =BK3/12 -> 0.0060416667 | BO3: r | BW3: Interest | BX3: ='Interest Rate Comparison'!B8 -> 0.07 | CA3: =BX3/12 -> 0.0058333333 | CB3: r
C4: $/sqft Market Estimate | J4: Term | K4: =$L$4*12 -> 360 | L4: ='STR Calculator'!I9 -> 30 | M4: years | N4: =(1+N3)^K4 -> 11.781506 | O4: (1+r)^n | W4: Term | X4: =$L$4*12 -> 360 | Y4: 30 | Z4: years | AA4: =(1+AA3)^X4 -> 10.93573 | AB4: (1+r)^n | AJ4: Term | AK4: =$L$4*12 -> 360 | AL4: 30 | AM4: years | AN4: =(1+AN3)^AK4 -> 10.150514 | AO4: (1+r)^n | AW4: Term | AX4: =$L$4*12 -> 360 | AY4: 30 | AZ4: years | BA4: =(1+BA3)^AX4 -> 9.4215339 | BB4: (1+r)^n | BJ4: Term | BK4: =$L$4*12 -> 360 | BL4: 30 | BM4: years | BN4: =(1+BN3)^BK4 -> 8.744772 | BO4: (1+r)^n | BW4: Term | BX4: =$L$4*12 -> 360 | BY4: 30 | BZ4: years | CA4: =(1+CA3)^BX4 -> 8.1164975 | CB4: (1+r)^n
A5: Original Purchase Price | B5: ='STR Calculator'!B5 -> 852000 | C5: =B5/B3 -> #DIV/0! | D5: sqft | J5: Monthly Payment | W5: Monthly Payment | AJ5: Monthly Payment | AW5: Monthly Payment | BJ5: Monthly Payment | BW5: Monthly Payment
A6: Down Payment | B6: 0.1
A7: Current Loan Balance | B7: =B5-(B5*B6) -> 766800 | C7: as of 11/13/22 | J7: paymentNumber | K7: paymentDate | L7: startingBalance | M7: Monthly Payment | N7: principalPayment | O7: Principle Pay Down | P7: interestPayment | Q7: Interest Percent | R7: cumulativePrincipal | S7: cumulativeInterest | T7: endingBalance | U7: Total Paid End of Loan | W7: paymentNumber | X7: paymentDate | Y7: startingBalance | Z7: Monthly Payment | AA7: principalPayment | AB7: Principle Pay Down | AC7: interestPayment | AD7: Interest Percent | AE7: cumulativePrincipal | AF7: cumulativeInterest | AG7: endingBalance | AH7: Total Paid End of Loan | AJ7: paymentNumber | AK7: paymentDate | AL7: startingBalance | AM7: Monthly Payment | AN7: principalPayment | AO7: Principle Pay Down | AP7: interestPayment | AQ7: Interest Percent | AR7: cumulativePrincipal | AS7: cumulativeInterest | AT7: endingBalance | AU7: Total Paid End of Loan | AW7: paymentNumber | AX7: paymentDate | AY7: startingBalance | AZ7: Monthly Payment | BA7: principalPayment | BB7: Principle Pay Down | BC7: interestPayment | BD7: Interest Percent | BE7: cumulativePrincipal | BF7: cumulativeInterest | BG7: endingBalance | BH7: Total Paid End of Loan | BJ7: paymentNumber | BK7: paymentDate | BL7: startingBalance | BM7: Monthly Payment | BN7: principalPayment | BO7: Principle Pay Down | BP7: interestPayment | BQ7: Interest Percent | BR7: cumulativePrincipal | BS7: cumulativeInterest | BT7: endingBalance | BU7: Total Paid End of Loan | BW7: paymentNumber | BX7: paymentDate | BY7: startingBalance | BZ7: Monthly Payment | CA7: principalPayment | CB7: Principle Pay Down | CC7: interestPayment | CD7: Interest Percent | CE7: cumulativePrincipal | CF7: cumulativeInterest | CG7: endingBalance | CH7: Total Paid End of Loan
A8: Current Equity | B8: =B5-B7 -> 85200 | J8: 1 | K8: 44866 | L8: ='Amoritization Scenario 10'!$B$7 -> 766800 | M8: =$L$8/((($N$4)-1)/($N$3*$N$4)) -> 5760.7123 | N8: =M8-P8 -> 488.96232 | O8: =(N8/L8)*12 -> 0.0076519925 | P8: =L8*($K$3/12) -> 5271.75 | Q8: =(P8/L8)*12 -> 0.0825 | R8: =N8 -> 488.96232 | S8: =P8 -> 5271.75 | T8: =L8-N8 -> 766311.04 | U8: =R8+S8 -> 5760.7123 | W8: 1 | X8: 44866 | Y8: ='Amoritization Scenario 10'!$B$7 -> 766800 | Z8: =$Y$8/((($AA$4)-1)/($AA$3*$AA$4)) -> 5626.5068 | AA8: =Z8-AC8 -> 514.50675 | AB8: =(AA8/Y8)*12 -> 0.0080517489 | AC8: =Y8*($X$3/12) -> 5112 | AD8: =(AC8/Y8)*12 -> 0.08 | AE8: =AA8 -> 514.50675 | AF8: =AC8 -> 5112 | AG8: =Y8-AA8 -> 766285.49 | AH8: =AE8+AF8 -> 5626.5068 | AJ8: 1 | AK8: 44866 | AL8: ='Amoritization Scenario 10'!$B$7 -> 766800 | AM8: =$AL$8/((($AN$4)-1)/($AN$3*$AN$4)) -> 5493.4491 | AN8: =AM8-AP8 -> 541.1991 | AO8: =(AN8/AL8)*12 -> 0.0084694695 | AP8: =AL8*($AK$3/12) -> 4952.25 | AQ8: =(AP8/AL8)*12 -> 0.0775 | AR8: =AN8 -> 541.1991 | AS8: =AP8 -> 4952.25 | AT8: =AL8-AN8 -> 766258.8 | AU8: =AR8+AS8 -> 5493.4491 | AW8: 1 | AX8: 44866 | AY8: ='Amoritization Scenario 10'!$B$7 -> 766800 | AZ8: =$AY$8/((($BA$4)-1)/($BA$3*$BA$4)) -> 5361.5769 | BA8: =AZ8-BC8 -> 569.07685 | BB8: =(BA8/AY8)*12 -> 0.008905741 | BC8: =AY8*($AX$3/12) -> 4792.5 | BD8: =(BC8/AY8)*12 -> 0.075 | BE8: =BA8 -> 569.07685 | BF8: =BC8 -> 4792.5 | BG8: =AY8-BA8 -> 766230.92 | BH8: =BE8+BF8 -> 5361.5769 | BJ8: 1 | BK8: 44866 | BL8: ='Amoritization Scenario 10'!$B$7 -> 766800 | BM8: =$BL$8/((($BN$4)-1)/($BN$3*$BN$4)) -> 5230.9277 | BN8: =BM8-BP8 -> 598.17772 | BO8: =(BN8/BL8)*12 -> 0.0093611536 | BP8: =BL8*($BK$3/12) -> 4632.75 | BQ8: =(BP8/BL8)*12 -> 0.0725 | BR8: =BN8 -> 598.17772 | BS8: =BP8 -> 4632.75 | BT8: =BL8-BN8 -> 766201.82 | BU8: =BR8+BS8 -> 5230.9277 | BW8: 1 | BX8: 44866 | BY8: ='Amoritization Scenario 10'!$B$7 -> 766800 | BZ8: =$BY$8/((($CA$4)-1)/($CA$3*$CA$4)) -> 5101.5395 | CA8: =BZ8-CC8 -> 628.53953 | CB8: =(CA8/BY8)*12 -> 0.0098362994 | CC8: =BY8*($BX$3/12) -> 4473 | CD8: =(CC8/BY8)*12 -> 0.07 | CE8: =CA8 -> 628.53953 | CF8: =CC8 -> 4473 | CG8: =BY8-CA8 -> 766171.46 | CH8: =CE8+CF8 -> 5101.5395
J9: 2 | K9: 44896 | L9: =T8 -> 766311.04 | M9: =$L$8/((($N$4)-1)/($N$3*$N$4)) -> 5760.7123 | N9: =M9-P9 -> 492.32394 | O9: =(N9/L9)*12 -> 0.007709516 | P9: =L9*($K$3/12) -> 5268.3884 | Q9: =(P9/L9)*12 -> 0.0825 | R9: =R8+N9 -> 981.28626 | S9: =S8+P9 -> 10540.138 | T9: =L9-N9 -> 765818.71 | U9: =R9+S9 -> 11521.425 | W9: 2 | X9: 44896 | Y9: =AG8 -> 766285.49 | Z9: =Z8 -> 5626.5068 | AA9: =Z9-AC9 -> 517.9368 | AB9: =(AA9/Y9)*12 -> 0.0081108694 | AC9: =Y9*($X$3/12) -> 5108.57 | AD9: =(AC9/Y9)*12 -> 0.08 | AE9: =AE8+AA9 -> 1032.4436 | AF9: =AF8+AC9 -> 10220.57 | AG9: =Y9-AA9 -> 765767.56 | AH9: =AE9+AF9 -> 11253.014 | AJ9: 2 | AK9: 44896 | AL9: =AT8 -> 766258.8 | AM9: =AM8 -> 5493.4491 | AN9: =AM9-AP9 -> 544.69434 | AO9: =(AN9/AL9)*12 -> 0.0085301886 | AP9: =AL9*($AK$3/12) -> 4948.7548 | AQ9: =(AP9/AL9)*12 -> 0.0775 | AR9: =AR8+AN9 -> 1085.8934 | AS9: =AS8+AP9 -> 9901.0048 | AT9: =AL9-AN9 -> 765714.11 | AU9: =AR9+AS9 -> 10986.898 | AW9: 2 | AX9: 44896 | AY9: =BG8 -> 766230.92 | AZ9: =AZ8 -> 5361.5769 | BA9: =AZ9-BC9 -> 572.63358 | BB9: =(BA9/AY9)*12 -> 0.0089680575 | BC9: =AY9*($AX$3/12) -> 4788.9433 | BD9: =(BC9/AY9)*12 -> 0.075 | BE9: =BE8+BA9 -> 1141.7104 | BF9: =BF8+BC9 -> 9581.4433 | BG9: =AY9-BA9 -> 765658.29 | BH9: =BE9+BF9 -> 10723.154 | BJ9: 2 | BK9: 44896 | BL9: =BT8 -> 766201.82 | BM9: =BM8 -> 5230.9277 | BN9: =BM9-BP9 -> 601.79171 | BO9: =(BN9/BL9)*12 -> 0.009425063 | BP9: =BL9*($BK$3/12) -> 4629.136 | BQ9: =(BP9/BL9)*12 -> 0.0725 | BR9: =BR8+BN9 -> 1199.9694 | BS9: =BS8+BP9 -> 9261.886 | BT9: =BL9-BN9 -> 765600.03 | BU9: =BR9+BS9 -> 10461.855 | BW9: 2 | BX9: 44896 | BY9: =CG8 -> 766171.46 | BZ9: =BZ8 -> 5101.5395 | CA9: =BZ9-CC9 -> 632.20601 | CB9: =(CA9/BY9)*12 -> 0.0099017943 | CC9: =BY9*($BX$3/12) -> 4469.3335 | CD9: =(CC9/BY9)*12 -> 0.07 | CE9: =CE8+CA9 -> 1260.7455 | CF9: =CF8+CC9 -> 8942.3335 | CG9: =BY9-CA9 -> 765539.25 | CH9: =CE9+CF9 -> 10203.079
A10: Year | B10: ="Cum Interest @ "&K3&"%" -> Cum Interest @ 0.0825% | C10: ="Cum Interest @ "&X3&"%" -> Cum Interest @ 0.08% | D10: ="Cum Interest @ "&AK3&"%" -> Cum Interest @ 0.0775% | E10: ="Cum Interest @ "&AX3&"%" -> Cum Interest @ 0.075% | F10: ="Cum Interest @ "&BK3&"%" -> Cum Interest @ 0.0725% | G10: ="Cum Interest @ "&BX3&"%" -> Cum Interest @ 0.07% | J10: 3 | K10: 44927 | L10: =T9 -> 765818.71 | M10: =$L$8/((($N$4)-1)/($N$3*$N$4)) -> 5760.7123 | N10: =M10-P10 -> 495.70866 | O10: =(N10/L10)*12 -> 0.0077675093 | P10: =L10*($K$3/12) -> 5265.0037 | Q10: =(P10/L10)*12 -> 0.0825 | R10: =R9+N10 -> 1476.9949 | S10: =S9+P10 -> 15805.142 | T10: =L10-N10 -> 765323.01 | U10: =R10+S10 -> 17282.137 | W10: 3 | X10: 44927 | Y10: =AG9 -> 765767.56 | Z10: =Z9 -> 5626.5068 | AA10: =Z10-AC10 -> 521.38971 | AB10: =(AA10/Y10)*12 -> 0.0081704643 | AC10: =Y10*($X$3/12) -> 5105.117 | AD10: =(AC10/Y10)*12 -> 0.08 | AE10: =AE9+AA10 -> 1553.8333 | AF10: =AF9+AC10 -> 15325.687 | AG10: =Y10-AA10 -> 765246.17 | AH10: =AE10+AF10 -> 16879.52 | AJ10: 3 | AK10: 44927 | AL10: =AT9 -> 765714.11 | AM10: =AM9 -> 5493.4491 | AN10: =AM10-AP10 -> 548.21216 | AO10: =(AN10/AL10)*12 -> 0.0085913866 | AP10: =AL10*($AK$3/12) -> 4945.2369 | AQ10: =(AP10/AL10)*12 -> 0.0775 | AR10: =AR9+AN10 -> 1634.1056 | AS10: =AS9+AP10 -> 14846.242 | AT10: =AL10-AN10 -> 765165.89 | AU10: =AR10+AS10 -> 16480.347 | AW10: 3 | AX10: 44927 | AY10: =BG9 -> 765658.29 | AZ10: =AZ9 -> 5361.5769 | BA10: =AZ10-BC10 -> 576.21254 | BB10: =(BA10/AY10)*12 -> 0.009030857 | BC10: =AY10*($AX$3/12) -> 4785.3643 | BD10: =(BC10/AY10)*12 -> 0.075 | BE10: =BE9+BA10 -> 1717.923 | BF10: =BF9+BC10 -> 14366.808 | BG10: =AY10-BA10 -> 765082.08 | BH10: =BE10+BF10 -> 16084.731 | BJ10: 3 | BK10: 44927 | BL10: =BT9 -> 765600.03 | BM10: =BM9 -> 5230.9277 | BN10: =BM10-BP10 -> 605.42753 | BO10: =(BN10/BL10)*12 -> 0.0094894594 | BP10: =BL10*($BK$3/12) -> 4625.5002 | BQ10: =(BP10/BL10)*12 -> 0.0725 | BR10: =BR9+BN10 -> 1805.397 | BS10: =BS9+BP10 -> 13887.386 | BT10: =BL10-BN10 -> 764994.6 | BU10: =BR10+BS10 -> 15692.783 | BW10: 3 | BX10: 44927 | BY10: =CG9 -> 765539.25 | BZ10: =BZ9 -> 5101.5395 | CA10: =BZ10-CC10 -> 635.89388 | CB10: =(CA10/BY10)*12 -> 0.0099677796 | CC10: =BY10*($BX$3/12) -> 4465.6457 | CD10: =(CC10/BY10)*12 -> 0.07 | CE10: =CE9+CA10 -> 1896.6394 | CF10: =CF9+CC10 -> 13407.979 | CG10: =BY10-CA10 -> 764903.36 | CH10: =CE10+CF10 -> 15304.619
A11: 1 | B11: =VLOOKUP($A$11*12,$J$7:$U$367,10) -> 63033.969 | C11: =VLOOKUP(A11*12,$W$7:$AH$367,10) -> 61112.51 | D11: =VLOOKUP(A11*12,$AJ$7:$AU$367,10) -> 59191.275 | E11: =VLOOKUP(A11*12,$AW$7:$BH$367,10) -> 57270.296 | F11: =VLOOKUP(A11*12,$BJ$7:$BU$367,10) -> 55349.607 | G11: =VLOOKUP(A11*12,$BW$7:$CH$367,10) -> 53429.245 | J11: 4 | K11: 44958 | L11: =T10 -> 765323.01 | M11: =$L$8/((($N$4)-1)/($N$3*$N$4)) -> 5760.7123 | N11: =M11-P11 -> 499.11666 | O11: =(N11/L11)*12 -> 0.0078259766 | P11: =L11*($K$3/12) -> 5261.5957 | Q11: =(P11/L11)*12 -> 0.0825 | R11: =R10+N11 -> 1976.1116 | S11: =S10+P11 -> 21066.738 | T11: =L11-N11 -> 764823.89 | U11: =R11+S11 -> 23042.849 | W11: 4 | X11: 44958 | Y11: =AG10 -> 765246.17 | Z11: =Z10 -> 5626.5068 | AA11: =Z11-AC11 -> 524.86564 | AB11: =(AA11/Y11)*12 -> 0.008230538 | AC11: =Y11*($X$3/12) -> 5101.6411 | AD11: =(AC11/Y11)*12 -> 0.08 | AE11: =AE10+AA11 -> 2078.6989 | AF11: =AF10+AC11 -> 20427.328 | AG11: =Y11-AA11 -> 764721.3 | AH11: =AE11+AF11 -> 22506.027 | AJ11: 4 | AK11: 44958 | AL11: =AT10 -> 765165.89 | AM11: =AM10 -> 5493.4491 | AN11: =AM11-AP11 -> 551.7527 | AO11: =(AN11/AL11)*12 -> 0.0086530678 | AP11: =AL11*($AK$3/12) -> 4941.6964 | AQ11: =(AP11/AL11)*12 -> 0.0775 | AR11: =AR10+AN11 -> 2185.8583 | AS11: =AS10+AP11 -> 19787.938 | AT11: =AL11-AN11 -> 764614.14 | AU11: =AR11+AS11 -> 21973.796 | AW11: 4 | AX11: 44958 | AY11: =BG10 -> 765082.08 | AZ11: =AZ10 -> 5361.5769 | BA11: =AZ11-BC11 -> 579.81387 | BB11: =(BA11/AY11)*12 -> 0.0090941438 | BC11: =AY11*($AX$3/12) -> 4781.763 | BD11: =(BC11/AY11)*12 -> 0.075 | BE11: =BE10+BA11 -> 2297.7368 | BF11: =BF10+BC11 -> 19148.571 | BG11: =AY11-BA11 -> 764502.26 | BH11: =BE11+BF11 -> 21446.307 | BJ11: 4 | BK11: 44958 | BL11: =BT10 -> 764994.6 | BM11: =BM10 -> 5230.9277 | BN11: =BM11-BP11 -> 609.08532 | BO11: =(BN11/BL11)*12 -> 0.009554347 | BP11: =BL11*($BK$3/12) -> 4621.8424 | BQ11: =(BP11/BL11)*12 -> 0.0725 | BR11: =BR10+BN11 -> 2414.4823 | BS11: =BS10+BP11 -> 18509.229 | BT11: =BL11-BN11 -> 764385.52 | BU11: =BR11+BS11 -> 20923.711 | BW11: 4 | BX11: 44958 | BY11: =CG10 -> 764903.36 | BZ11: =BZ10 -> 5101.5395 | CA11: =BZ11-CC11 -> 639.60326 | CB11: =(CA11/BY11)*12 -> 0.01003426 | CC11: =BY11*($BX$3/12) -> 4461.9363 | CD11: =(CC11/BY11)*12 -> 0.07 | CE11: =CE10+CA11 -> 2536.2427 | CF11: =CF10+CC11 -> 17869.915 | CG11: =BY11-CA11 -> 764263.76 | CH11: =CE11+CF11 -> 20406.158
A12: =A11+1 -> 2 | B12: =VLOOKUP(A12*12,$J$7:$U$367,10) -> 125545.68 | C12: =VLOOKUP(A12*12,$W$7:$AH$367,10) -> 121693.36 | D12: =VLOOKUP(A12*12,$AJ$7:$AU$367,10) -> 117842.03 | E12: =VLOOKUP(A12*12,$AW$7:$BH$367,10) -> 113991.84 | F12: =VLOOKUP(A12*12,$BJ$7:$BU$367,10) -> 110142.91 | G12: =VLOOKUP(A12*12,$BW$7:$CH$367,10) -> 106295.41 | J12: 5 | K12: 44986 | L12: =T11 -> 764823.89 | M12: =$L$8/((($N$4)-1)/($N$3*$N$4)) -> 5760.7123 | N12: =M12-P12 -> 502.54809 | O12: =(N12/L12)*12 -> 0.0078849224 | P12: =L12*($K$3/12) -> 5258.1642 | Q12: =(P12/L12)*12 -> 0.0825 | R12: =R11+N12 -> 2478.6597 | S12: =S11+P12 -> 26324.902 | T12: =L12-N12 -> 764321.34 | U12: =R12+S12 -> 28803.562 | W12: 5 | X12: 44986 | Y12: =AG11 -> 764721.3 | Z12: =Z11 -> 5626.5068 | AA12: =Z12-AC12 -> 528.36475 | AB12: =(AA12/Y12)*12 -> 0.008291095 | AC12: =Y12*($X$3/12) -> 5098.142 | AD12: =(AC12/Y12)*12 -> 0.08 | AE12: =AE11+AA12 -> 2607.0636 | AF12: =AF11+AC12 -> 25525.47 | AG12: =Y12-AA12 -> 764192.94 | AH12: =AE12+AF12 -> 28132.534 | AJ12: 5 | AK12: 44986 | AL12: =AT11 -> 764614.14 | AM12: =AM11 -> 5493.4491 | AN12: =AM12-AP12 -> 555.3161 | AO12: =(AN12/AL12)*12 -> 0.0087152367 | AP12: =AL12*($AK$3/12) -> 4938.133 | AQ12: =(AP12/AL12)*12 -> 0.0775 | AR12: =AR11+AN12 -> 2741.1744 | AS12: =AS11+AP12 -> 24726.071 | AT12: =AL12-AN12 -> 764058.83 | AU12: =AR12+AS12 -> 27467.245 | AW12: 5 | AX12: 44986 | AY12: =BG11 -> 764502.26 | AZ12: =AZ11 -> 5361.5769 | BA12: =AZ12-BC12 -> 583.43771 | BB12: =(BA12/AY12)*12 -> 0.0091579225 | BC12: =AY12*($AX$3/12) -> 4778.1391 | BD12: =(BC12/AY12)*12 -> 0.075 | BE12: =BE11+BA12 -> 2881.1746 | BF12: =BF11+BC12 -> 23926.71 | BG12: =AY12-BA12 -> 763918.83 | BH12: =BE12+BF12 -> 26807.884 | BJ12: 5 | BK12: 44986 | BL12: =BT11 -> 764385.52 | BM12: =BM11 -> 5230.9277 | BN12: =BM12-BP12 -> 612.76521 | BO12: =(BN12/BL12)*12 -> 0.0096197303 | BP12: =BL12*($BK$3/12) -> 4618.1625 | BQ12: =(BP12/BL12)*12 -> 0.0725 | BR12: =BR11+BN12 -> 3027.2475 | BS12: =BS11+BP12 -> 23127.391 | BT12: =BL12-BN12 -> 763772.75 | BU12: =BR12+BS12 -> 26154.639 | BW12: 5 | BX12: 44986 | BY12: =CG11 -> 764263.76 | BZ12: =BZ11 -> 5101.5395 | CA12: =BZ12-CC12 -> 643.33428 | CB12: =(CA12/BY12)*12 -> 0.01010124 | CC12: =BY12*($BX$3/12) -> 4458.2053 | CD12: =(CC12/BY12)*12 -> 0.07 | CE12: =CE11+CA12 -> 3179.577 | CF12: =CF11+CC12 -> 22328.121 | CG12: =BY12-CA12 -> 763620.42 | CH12: =CE12+CF12 -> 25507.698
A13: =A12+1 -> 3 | B13: =VLOOKUP(A13*12,$J$7:$U$367,10) -> 187490.38 | C13: =VLOOKUP(A13*12,$W$7:$AH$367,10) -> 181698.42 | D13: =VLOOKUP(A13*12,$AJ$7:$AU$367,10) -> 175908.87 | E13: =VLOOKUP(A13*12,$AW$7:$BH$367,10) -> 170122.02 | F13: =VLOOKUP(A13*12,$BJ$7:$BU$367,10) -> 164338.21 | G13: =VLOOKUP(A13*12,$BW$7:$CH$367,10) -> 158557.78 | J13: 6 | K13: 45017 | L13: =T12 -> 764321.34 | M13: =$L$8/((($N$4)-1)/($N$3*$N$4)) -> 5760.7123 | N13: =M13-P13 -> 506.00311 | O13: =(N13/L13)*12 -> 0.0079443513 | P13: =L13*($K$3/12) -> 5254.7092 | Q13: =(P13/L13)*12 -> 0.0825 | R13: =R12+N13 -> 2984.6628 | S13: =S12+P13 -> 31579.611 | T13: =L13-N13 -> 763815.34 | U13: =R13+S13 -> 34564.274 | W13: 6 | X13: 45017 | Y13: =AG12 -> 764192.94 | Z13: =Z12 -> 5626.5068 | AA13: =Z13-AC13 -> 531.88718 | AB13: =(AA13/Y13)*12 -> 0.0083521396 | AC13: =Y13*($X$3/12) -> 5094.6196 | AD13: =(AC13/Y13)*12 -> 0.08 | AE13: =AE12+AA13 -> 3138.9508 | AF13: =AF12+AC13 -> 30620.09 | AG13: =Y13-AA13 -> 763661.05 | AH13: =AE13+AF13 -> 33759.041 | AJ13: 6 | AK13: 45017 | AL13: =AT12 -> 764058.83 | AM13: =AM12 -> 5493.4491 | AN13: =AM13-AP13 -> 558.90252 | AO13: =(AN13/AL13)*12 -> 0.0087778977 | AP13: =AL13*($AK$3/12) -> 4934.5466 | AQ13: =(AP13/AL13)*12 -> 0.0775 | AR13: =AR12+AN13 -> 3300.0769 | AS13: =AS12+AP13 -> 29660.618 | AT13: =AL13-AN13 -> 763499.92 | AU13: =AR13+AS13 -> 32960.695 | AW13: 6 | AX13: 45017 | AY13: =BG12 -> 763918.83 | AZ13: =AZ12 -> 5361.5769 | BA13: =AZ13-BC13 -> 587.08419 | BB13: =(BA13/AY13)*12 -> 0.0092221975 | BC13: =AY13*($AX$3/12) -> 4774.4927 | BD13: =(BC13/AY13)*12 -> 0.075 | BE13: =BE12+BA13 -> 3468.2587 | BF13: =BF12+BC13 -> 28701.202 | BG13: =AY13-BA13 -> 763331.74 | BH13: =BE13+BF13 -> 32169.461 | BJ13: 6 | BK13: 45017 | BL13: =BT12 -> 763772.75 | BM13: =BM12 -> 5230.9277 | BN13: =BM13-BP13 -> 616.46734 | BO13: =(BN13/BL13)*12 -> 0.009685614 | BP13: =BL13*($BK$3/12) -> 4614.4604 | BQ13: =(BP13/BL13)*12 -> 0.0725 | BR13: =BR12+BN13 -> 3643.7148 | BS13: =BS12+BP13 -> 27741.851 | BT13: =BL13-BN13 -> 763156.29 | BU13: =BR13+BS13 -> 31385.566 | BW13: 6 | BX13: 45017 | BY13: =CG12 -> 763620.42 | BZ13: =BZ12 -> 5101.5395 | CA13: =BZ13-CC13 -> 647.08707 | CB13: =(CA13/BY13)*12 -> 0.010168723 | CC13: =BY13*($BX$3/12) -> 4454.4525 | CD13: =(CC13/BY13)*12 -> 0.07 | CE13: =CE12+CA13 -> 3826.664 | CF13: =CF12+CC13 -> 26782.573 | CG13: =BY13-CA13 -> 762973.34 | CH13: =CE13+CF13 -> 30609.237
A14: =A13+1 -> 4 | B14: =VLOOKUP(A14*12,$J$7:$U$367,10) -> 248819.48 | C14: =VLOOKUP(A14*12,$W$7:$AH$367,10) -> 241079.91 | D14: =VLOOKUP(A14*12,$AJ$7:$AU$367,10) -> 233344.88 | E14: =VLOOKUP(A14*12,$AW$7:$BH$367,10) -> 225614.94 | F14: =VLOOKUP(A14*12,$BJ$7:$BU$367,10) -> 217890.67 | G14: =VLOOKUP(A14*12,$BW$7:$CH$367,10) -> 210172.71 | J14: 7 | K14: 45047 | L14: =T13 -> 763815.34 | M14: =$L$8/((($N$4)-1)/($N$3*$N$4)) -> 5760.7123 | N14: =M14-P14 -> 509.48188 | O14: =(N14/L14)*12 -> 0.0080042678 | P14: =L14*($K$3/12) -> 5251.2304 | Q14: =(P14/L14)*12 -> 0.0825 | R14: =R13+N14 -> 3494.1446 | S14: =S13+P14 -> 36830.842 | T14: =L14-N14 -> 763305.86 | U14: =R14+S14 -> 40324.986 | W14: 7 | X14: 45047 | Y14: =AG13 -> 763661.05 | Z14: =Z13 -> 5626.5068 | AA14: =Z14-AC14 -> 535.43309 | AB14: =(AA14/Y14)*12 -> 0.0084136766 | AC14: =Y14*($X$3/12) -> 5091.0737 | AD14: =(AC14/Y14)*12 -> 0.08 | AE14: =AE13+AA14 -> 3674.3839 | AF14: =AF13+AC14 -> 35711.163 | AG14: =Y14-AA14 -> 763125.62 | AH14: =AE14+AF14 -> 39385.547 | AJ14: 7 | AK14: 45047 | AL14: =AT13 -> 763499.92 | AM14: =AM13 -> 5493.4491 | AN14: =AM14-AP14 -> 562.5121 | AO14: =(AN14/AL14)*12 -> 0.0088410554 | AP14: =AL14*($AK$3/12) -> 4930.937 | AQ14: =(AP14/AL14)*12 -> 0.0775 | AR14: =AR13+AN14 -> 3862.589 | AS14: =AS13+AP14 -> 34591.555 | AT14: =AL14-AN14 -> 762937.41 | AU14: =AR14+AS14 -> 38454.144 | AW14: 7 | AX14: 45047 | AY14: =BG13 -> 763331.74 | AZ14: =AZ13 -> 5361.5769 | BA14: =AZ14-BC14 -> 590.75347 | BB14: =(BA14/AY14)*12 -> 0.0092869735 | BC14: =AY14*($AX$3/12) -> 4770.8234 | BD14: =(BC14/AY14)*12 -> 0.075 | BE14: =BE13+BA14 -> 4059.0122 | BF14: =BF13+BC14 -> 33472.026 | BG14: =AY14-BA14 -> 762740.99 | BH14: =BE14+BF14 -> 37531.038 | BJ14: 7 | BK14: 45047 | BL14: =BT13 -> 763156.29 | BM14: =BM13 -> 5230.9277 | BN14: =BM14-BP14 -> 620.19183 | BO14: =(BN14/BL14)*12 -> 0.0097520024 | BP14: =BL14*($BK$3/12) -> 4610.7359 | BQ14: =(BP14/BL14)*12 -> 0.0725 | BR14: =BR13+BN14 -> 4263.9066 | BS14: =BS13+BP14 -> 32352.587 | BT14: =BL14-BN14 -> 762536.09 | BU14: =BR14+BS14 -> 36616.494 | BW14: 7 | BX14: 45047 | BY14: =CG13 -> 762973.34 | BZ14: =BZ13 -> 5101.5395 | CA14: =BZ14-CC14 -> 650.86174 | CB14: =(CA14/BY14)*12 -> 0.010236715 | CC14: =BY14*($BX$3/12) -> 4450.6778 | CD14: =(CC14/BY14)*12 -> 0.07 | CE14: =CE13+CA14 -> 4477.5258 | CF14: =CF13+CC14 -> 31233.251 | CG14: =BY14-CA14 -> 762322.47 | CH14: =CE14+CF14 -> 35710.777
A15: =A14+1 -> 5 | B15: =VLOOKUP(A15*12,$J$7:$U$367,10) -> 309480.24 | C15: =VLOOKUP(A15*12,$W$7:$AH$367,10) -> 299786.07 | D15: =VLOOKUP(A15*12,$AJ$7:$AU$367,10) -> 290099.4 | E15: =VLOOKUP(A15*12,$AW$7:$BH$367,10) -> 280421.11 | F15: =VLOOKUP(A15*12,$BJ$7:$BU$367,10) -> 270752.13 | G15: =VLOOKUP(A15*12,$BW$7:$CH$367,10) -> 261093.4 | J15: 8 | K15: 45078 | L15: =T14 -> 763305.86 | M15: =$L$8/((($N$4)-1)/($N$3*$N$4)) -> 5760.7123 | N15: =M15-P15 -> 512.98456 | O15: =(N15/L15)*12 -> 0.0080646765 | P15: =L15*($K$3/12) -> 5247.7278 | Q15: =(P15/L15)*12 -> 0.0825 | R15: =R14+N15 -> 4007.1292 | S15: =S14+P15 -> 42078.569 | T15: =L15-N15 -> 762792.87 | U15: =R15+S15 -> 46085.699 | W15: 8 | X15: 45078 | Y15: =AG14 -> 763125.62 | Z15: =Z14 -> 5626.5068 | AA15: =Z15-AC15 -> 539.00265 | AB15: =(AA15/Y15)*12 -> 0.0084757104 | AC15: =Y15*($X$3/12) -> 5087.5041 | AD15: =(AC15/Y15)*12 -> 0.08 | AE15: =AE14+AA15 -> 4213.3866 | AF15: =AF14+AC15 -> 40798.667 | AG15: =Y15-AA15 -> 762586.61 | AH15: =AE15+AF15 -> 45012.054 | AJ15: 8 | AK15: 45078 | AL15: =AT14 -> 762937.41 | AM15: =AM14 -> 5493.4491 | AN15: =AM15-AP15 -> 566.14499 | AO15: =(AN15/AL15)*12 -> 0.0089047145 | AP15: =AL15*($AK$3/12) -> 4927.3041 | AQ15: =(AP15/AL15)*12 -> 0.0775 | AR15: =AR14+AN15 -> 4428.734 | AS15: =AS14+AP15 -> 39518.859 | AT15: =AL15-AN15 -> 762371.27 | AU15: =AR15+AS15 -> 43947.593 | AW15: 8 | AX15: 45078 | AY15: =BG14 -> 762740.99 | AZ15: =AZ14 -> 5361.5769 | BA15: =AZ15-BC15 -> 594.44568 | BB15: =(BA15/AY15)*12 -> 0.0093522549 | BC15: =AY15*($AX$3/12) -> 4767.1312 | BD15: =(BC15/AY15)*12 -> 0.075 | BE15: =BE14+BA15 -> 4653.4579 | BF15: =BF14+BC15 -> 38239.157 | BG15: =AY15-BA15 -> 762146.54 | BH15: =BE15+BF15 -> 42892.615 | BJ15: 8 | BK15: 45078 | BL15: =BT14 -> 762536.09 | BM15: =BM14 -> 5230.9277 | BN15: =BM15-BP15 -> 623.93882 | BO15: =(BN15/BL15)*12 -> 0.0098189002 | BP15: =BL15*($BK$3/12) -> 4606.9889 | BQ15: =(BP15/BL15)*12 -> 0.0725 | BR15: =BR14+BN15 -> 4887.8455 | BS15: =BS14+BP15 -> 36959.576 | BT15: =BL15-BN15 -> 761912.15 | BU15: =BR15+BS15 -> 41847.422 | BW15: 8 | BX15: 45078 | BY15: =CG14 -> 762322.47 | BZ15: =BZ14 -> 5101.5395 | CA15: =BZ15-CC15 -> 654.65843 | CB15: =(CA15/BY15)*12 -> 0.010305221 | CC15: =BY15*($BX$3/12) -> 4446.8811 | CD15: =(CC15/BY15)*12 -> 0.07 | CE15: =CE14+CA15 -> 5132.1842 | CF15: =CF14+CC15 -> 35680.132 | CG15: =BY15-CA15 -> 761667.82 | CH15: =CE15+CF15 -> 40812.316
A16: =A15+1 -> 6 | B16: =VLOOKUP(A16*12,$J$7:$U$367,10) -> 369415.36 | C16: =VLOOKUP(A16*12,$W$7:$AH$367,10) -> 357760.84 | D16: =VLOOKUP(A16*12,$AJ$7:$AU$367,10) -> 346117.71 | E16: =VLOOKUP(A16*12,$AW$7:$BH$367,10) -> 334487.24 | F16: =VLOOKUP(A16*12,$BJ$7:$BU$367,10) -> 322870.77 | G16: =VLOOKUP(A16*12,$BW$7:$CH$367,10) -> 311269.67 | J16: 9 | K16: 45108 | L16: =T15 -> 762792.87 | M16: =$L$8/((($N$4)-1)/($N$3*$N$4)) -> 5760.7123 | N16: =M16-P16 -> 516.51133 | O16: =(N16/L16)*12 -> 0.008125582 | P16: =L16*($K$3/12) -> 5244.201 | Q16: =(P16/L16)*12 -> 0.0825 | R16: =R15+N16 -> 4523.6405 | S16: =S15+P16 -> 47322.77 | T16: =L16-N16 -> 762276.36 | U16: =R16+S16 -> 51846.411 | W16: 9 | X16: 45108 | Y16: =AG15 -> 762586.61 | Z16: =Z15 -> 5626.5068 | AA16: =Z16-AC16 -> 542.596 | AB16: =(AA16/Y16)*12 -> 0.0085382458 | AC16: =Y16*($X$3/12) -> 5083.9108 | AD16: =(AC16/Y16)*12 -> 0.08 | AE16: =AE15+AA16 -> 4755.9826 | AF16: =AF15+AC16 -> 45882.578 | AG16: =Y16-AA16 -> 762044.02 | AH16: =AE16+AF16 -> 50638.561 | AJ16: 9 | AK16: 45108 | AL16: =AT15 -> 762371.27 | AM16: =AM15 -> 5493.4491 | AN16: =AM16-AP16 -> 569.80134 | AO16: =(AN16/AL16)*12 -> 0.0089688796 | AP16: =AL16*($AK$3/12) -> 4923.6478 | AQ16: =(AP16/AL16)*12 -> 0.0775 | AR16: =AR15+AN16 -> 4998.5353 | AS16: =AS15+AP16 -> 44442.507 | AT16: =AL16-AN16 -> 761801.46 | AU16: =AR16+AS16 -> 49441.042 | AW16: 9 | AX16: 45108 | AY16: =BG15 -> 762146.54 | AZ16: =AZ15 -> 5361.5769 | BA16: =AZ16-BC16 -> 598.16096 | BB16: =(BA16/AY16)*12 -> 0.0094180465 | BC16: =AY16*($AX$3/12) -> 4763.4159 | BD16: =(BC16/AY16)*12 -> 0.075 | BE16: =BE15+BA16 -> 5251.6189 | BF16: =BF15+BC16 -> 43002.573 | BG16: =AY16-BA16 -> 761548.38 | BH16: =BE16+BF16 -> 48254.192 | BJ16: 9 | BK16: 45108 | BL16: =BT15 -> 761912.15 | BM16: =BM15 -> 5230.9277 | BN16: =BM16-BP16 -> 627.70845 | BO16: =(BN16/BL16)*12 -> 0.0098863121 | BP16: =BL16*($BK$3/12) -> 4603.2193 | BQ16: =(BP16/BL16)*12 -> 0.0725 | BR16: =BR15+BN16 -> 5515.5539 | BS16: =BS15+BP16 -> 41562.796 | BT16: =BL16-BN16 -> 761284.45 | BU16: =BR16+BS16 -> 47078.349 | BW16: 9 | BX16: 45108 | BY16: =CG15 -> 761667.82 | BZ16: =BZ15 -> 5101.5395 | CA16: =BZ16-CC16 -> 658.47727 | CB16: =(CA16/BY16)*12 -> 0.010374243 | CC16: =BY16*($BX$3/12) -> 4443.0623 | CD16: =(CC16/BY16)*12 -> 0.07 | CE16: =CE15+CA16 -> 5790.6615 | CF16: =CF15+CC16 -> 40123.194 | CG16: =BY16-CA16 -> 761009.34 | CH16: =CE16+CF16 -> 45913.856
A17: =A16+1 -> 7 | B17: =VLOOKUP(A17*12,$J$7:$U$367,10) -> 428562.69 | C17: =VLOOKUP(A17*12,$W$7:$AH$367,10) -> 414943.51 | D17: =VLOOKUP(A17*12,$AJ$7:$AU$367,10) -> 401340.67 | E17: =VLOOKUP(A17*12,$AW$7:$BH$367,10) -> 387755.86 | F17: =VLOOKUP(A17*12,$BJ$7:$BU$367,10) -> 374190.91 | G17: =VLOOKUP(A17*12,$BW$7:$CH$367,10) -> 360647.69 | J17: 10 | K17: 45139 | L17: =T16 -> 762276.36 | M17: =$L$8/((($N$4)-1)/($N$3*$N$4)) -> 5760.7123 | N17: =M17-P17 -> 520.06235 | O17: =(N17/L17)*12 -> 0.008186989 | P17: =L17*($K$3/12) -> 5240.65 | Q17: =(P17/L17)*12 -> 0.0825 | R17: =R16+N17 -> 5043.7029 | S17: =S16+P17 -> 52563.42 | T17: =L17-N17 -> 761756.3 | U17: =R17+S17 -> 57607.123 | W17: 10 | X17: 45139 | Y17: =AG16 -> 762044.02 | Z17: =Z16 -> 5626.5068 | AA17: =Z17-AC17 -> 546.2133 | AB17: =(AA17/Y17)*12 -> 0.0086012874 | AC17: =Y17*($X$3/12) -> 5080.2934 | AD17: =(AC17/Y17)*12 -> 0.08 | AE17: =AE16+AA17 -> 5302.1959 | AF17: =AF16+AC17 -> 50962.872 | AG17: =Y17-AA17 -> 761497.8 | AH17: =AE17+AF17 -> 56265.068 | AJ17: 10 | AK17: 45139 | AL17: =AT16 -> 761801.46 | AM17: =AM16 -> 5493.4491 | AN17: =AM17-AP17 -> 573.48131 | AO17: =(AN17/AL17)*12 -> 0.0090335553 | AP17: =AL17*($AK$3/12) -> 4919.9678 | AQ17: =(AP17/AL17)*12 -> 0.0775 | AR17: =AR16+AN17 -> 5572.0166 | AS17: =AS16+AP17 -> 49362.474 | AT17: =AL17-AN17 -> 761227.98 | AU17: =AR17+AS17 -> 54934.491 | AW17: 10 | AX17: 45139 | AY17: =BG16 -> 761548.38 | AZ17: =AZ16 -> 5361.5769 | BA17: =AZ17-BC17 -> 601.89947 | BB17: =(BA17/AY17)*12 -> 0.0094843529 | BC17: =AY17*($AX$3/12) -> 4759.6774 | BD17: =(BC17/AY17)*12 -> 0.075 | BE17: =BE16+BA17 -> 5853.5183 | BF17: =BF16+BC17 -> 47762.25 | BG17: =AY17-BA17 -> 760946.48 | BH17: =BE17+BF17 -> 53615.769 | BJ17: 10 | BK17: 45139 | BL17: =BT16 -> 761284.45 | BM17: =BM16 -> 5230.9277 | BN17: =BM17-BP17 -> 631.50085 | BO17: =(BN17/BL17)*12 -> 0.0099542428 | BP17: =BL17*($BK$3/12) -> 4599.4269 | BQ17: =(BP17/BL17)*12 -> 0.0725 | BR17: =BR16+BN17 -> 6147.0548 | BS17: =BS16+BP17 -> 46162.222 | BT17: =BL17-BN17 -> 760652.95 | BU17: =BR17+BS17 -> 52309.277 | BW17: 10 | BX17: 45139 | BY17: =CG16 -> 761009.34 | BZ17: =BZ16 -> 5101.5395 | CA17: =BZ17-CC17 -> 662.31839 | CB17: =(CA17/BY17)*12 -> 0.010443789 | CC17: =BY17*($BX$3/12) -> 4439.2211 | CD17: =(CC17/BY17)*12 -> 0.07 | CE17: =CE16+CA17 -> 6452.9799 | CF17: =CF16+CC17 -> 44562.415 | CG17: =BY17-CA17 -> 760347.02 | CH17: =CE17+CF17 -> 51015.395
A18: =A17+1 -> 8 | B18: =VLOOKUP(A18*12,$J$7:$U$367,10) -> 486854.7 | C18: =VLOOKUP(A18*12,$W$7:$AH$367,10) -> 471268.36 | D18: =VLOOKUP(A18*12,$AJ$7:$AU$367,10) -> 455704.4 | E18: =VLOOKUP(A18*12,$AW$7:$BH$367,10) -> 440165.07 | F18: =VLOOKUP(A18*12,$BJ$7:$BU$367,10) -> 424652.71 | G18: =VLOOKUP(A18*12,$BW$7:$CH$367,10) -> 409169.77 | J18: 11 | K18: 45170 | L18: =T17 -> 761756.3 | M18: =$L$8/((($N$4)-1)/($N$3*$N$4)) -> 5760.7123 | N18: =M18-P18 -> 523.63778 | O18: =(N18/L18)*12 -> 0.0082489024 | P18: =L18*($K$3/12) -> 5237.0745 | Q18: =(P18/L18)*12 -> 0.0825 | R18: =R17+N18 -> 5567.3407 | S18: =S17+P18 -> 57800.495 | T18: =L18-N18 -> 761232.66 | U18: =R18+S18 -> 63367.836 | W18: 11 | X18: 45170 | Y18: =AG17 -> 761497.8 | Z18: =Z17 -> 5626.5068 | AA18: =Z18-AC18 -> 549.85472 | AB18: =(AA18/Y18)*12 -> 0.0086648401 | AC18: =Y18*($X$3/12) -> 5076.652 | AD18: =(AC18/Y18)*12 -> 0.08 | AE18: =AE17+AA18 -> 5852.0506 | AF18: =AF17+AC18 -> 56039.524 | AG18: =Y18-AA18 -> 760947.95 | AH18: =AE18+AF18 -> 61891.574 | AJ18: 11 | AK18: 45170 | AL18: =AT17 -> 761227.98 | AM18: =AM17 -> 5493.4491 | AN18: =AM18-AP18 -> 577.18504 | AO18: =(AN18/AL18)*12 -> 0.0090987465 | AP18: =AL18*($AK$3/12) -> 4916.2641 | AQ18: =(AP18/AL18)*12 -> 0.0775 | AR18: =AR17+AN18 -> 6149.2017 | AS18: =AS17+AP18 -> 54278.738 | AT18: =AL18-AN18 -> 760650.8 | AU18: =AR18+AS18 -> 60427.94 | AW18: 11 | AX18: 45170 | AY18: =BG17 -> 760946.48 | AZ18: =AZ17 -> 5361.5769 | BA18: =AZ18-BC18 -> 605.66134 | BB18: =(BA18/AY18)*12 -> 0.009551179 | BC18: =AY18*($AX$3/12) -> 4755.9155 | BD18: =(BC18/AY18)*12 -> 0.075 | BE18: =BE17+BA18 -> 6459.1797 | BF18: =BF17+BC18 -> 52518.166 | BG18: =AY18-BA18 -> 760340.82 | BH18: =BE18+BF18 -> 58977.345 | BJ18: 11 | BK18: 45170 | BL18: =BT17 -> 760652.95 | BM18: =BM17 -> 5230.9277 | BN18: =BM18-BP18 -> 635.31617 | BO18: =(BN18/BL18)*12 -> 0.010022697 | BP18: =BL18*($BK$3/12) -> 4595.6115 | BQ18: =(BP18/BL18)*12 -> 0.0725 | BR18: =BR17+BN18 -> 6782.3709 | BS18: =BS17+BP18 -> 50757.834 | BT18: =BL18-BN18 -> 760017.63 | BU18: =BR18+BS18 -> 57540.205 | BW18: 11 | BX18: 45170 | BY18: =CG17 -> 760347.02 | BZ18: =BZ17 -> 5101.5395 | CA18: =BZ18-CC18 -> 666.18192 | CB18: =(CA18/BY18)*12 -> 0.010513861 | CC18: =BY18*($BX$3/12) -> 4435.3576 | CD18: =(CC18/BY18)*12 -> 0.07 | CE18: =CE17+CA18 -> 7119.1618 | CF18: =CF17+CC18 -> 48997.773 | CG18: =BY18-CA18 -> 759680.84 | CH18: =CE18+CF18 -> 56116.935
A19: =A18+1 -> 9 | B19: =VLOOKUP(A19*12,$J$7:$U$367,10) -> 544218.1 | C19: =VLOOKUP(A19*12,$W$7:$AH$367,10) -> 526664.17 | D19: =VLOOKUP(A19*12,$AJ$7:$AU$367,10) -> 509139.91 | E19: =VLOOKUP(A19*12,$AW$7:$BH$367,10) -> 491648.14 | F19: =VLOOKUP(A19*12,$BJ$7:$BU$367,10) -> 474191.83 | G19: =VLOOKUP(A19*12,$BW$7:$CH$367,10) -> 456774.02 | J19: 12 | K19: 45200 | L19: =T18 -> 761232.66 | M19: =$L$8/((($N$4)-1)/($N$3*$N$4)) -> 5760.7123 | N19: =M19-P19 -> 527.23779 | O19: =(N19/L19)*12 -> 0.0083113269 | P19: =L19*($K$3/12) -> 5233.4745 | Q19: =(P19/L19)*12 -> 0.0825 | R19: =R18+N19 -> 6094.5785 | S19: =S18+P19 -> 63033.969 | T19: =L19-N19 -> 760705.42 | U19: =R19+S19 -> 69128.548 | W19: 12 | X19: 45200 | Y19: =AG18 -> 760947.95 | Z19: =Z18 -> 5626.5068 | AA19: =Z19-AC19 -> 553.52042 | AB19: =(AA19/Y19)*12 -> 0.0087289086 | AC19: =Y19*($X$3/12) -> 5072.9863 | AD19: =(AC19/Y19)*12 -> 0.08 | AE19: =AE18+AA19 -> 6405.571 | AF19: =AF18+AC19 -> 61112.51 | AG19: =Y19-AA19 -> 760394.43 | AH19: =AE19+AF19 -> 67518.081 | AJ19: 12 | AK19: 45200 | AL19: =AT18 -> 760650.8 | AM19: =AM18 -> 5493.4491 | AN19: =AM19-AP19 -> 580.91269 | AO19: =(AN19/AL19)*12 -> 0.009164458 | AP19: =AL19*($AK$3/12) -> 4912.5364 | AQ19: =(AP19/AL19)*12 -> 0.0775 | AR19: =AR18+AN19 -> 6730.1144 | AS19: =AS18+AP19 -> 59191.275 | AT19: =AL19-AN19 -> 760069.89 | AU19: =AR19+AS19 -> 65921.389 | AW19: 12 | AX19: 45200 | AY19: =BG18 -> 760340.82 | AZ19: =AZ18 -> 5361.5769 | BA19: =AZ19-BC19 -> 609.44672 | BB19: =(BA19/AY19)*12 -> 0.0096185296 | BC19: =AY19*($AX$3/12) -> 4752.1301 | BD19: =(BC19/AY19)*12 -> 0.075 | BE19: =BE18+BA19 -> 7068.6264 | BF19: =BF18+BC19 -> 57270.296 | BG19: =AY19-BA19 -> 759731.37 | BH19: =BE19+BF19 -> 64338.922 | BJ19: 12 | BK19: 45200 | BL19: =BT18 -> 760017.63 | BM19: =BM18 -> 5230.9277 | BN19: =BM19-BP19 -> 639.15454 | BO19: =(BN19/BL19)*12 -> 0.01009168 | BP19: =BL19*($BK$3/12) -> 4591.7732 | BQ19: =(BP19/BL19)*12 -> 0.0725 | BR19: =BR18+BN19 -> 7421.5255 | BS19: =BS18+BP19 -> 55349.607 | BT19: =BL19-BN19 -> 759378.47 | BU19: =BR19+BS19 -> 62771.133 | BW19: 12 | BX19: 45200 | BY19: =CG18 -> 759680.84 | BZ19: =BZ18 -> 5101.5395 | CA19: =BZ19-CC19 -> 670.06798 | CB19: =(CA19/BY19)*12 -> 0.010584466 | CC19: =BY19*($BX$3/12) -> 4431.4716 | CD19: =(CC19/BY19)*12 -> 0.07 | CE19: =CE18+CA19 -> 7789.2298 | CF19: =CF18+CC19 -> 53429.245 | CG19: =BY19-CA19 -> 759010.77 | CH19: =CE19+CF19 -> 61218.474
A20: =A19+1 -> 10 | B20: =VLOOKUP(A20*12,$J$7:$U$367,10) -> 600573.32 | C20: =VLOOKUP(A20*12,$W$7:$AH$367,10) -> 581053.84 | D20: =VLOOKUP(A20*12,$AJ$7:$AU$367,10) -> 561572.64 | E20: =VLOOKUP(A20*12,$AW$7:$BH$367,10) -> 542133.18 | F20: =VLOOKUP(A20*12,$BJ$7:$BU$367,10) -> 522739.09 | G20: =VLOOKUP(A20*12,$BW$7:$CH$367,10) -> 503394.1 | J20: 13 | K20: 45231 | L20: =T19 -> 760705.42 | M20: =$L$8/((($N$4)-1)/($N$3*$N$4)) -> 5760.7123 | N20: =M20-P20 -> 530.86255 | O20: =(N20/L20)*12 -> 0.0083742673 | P20: =L20*($K$3/12) -> 5229.8498 | Q20: =(P20/L20)*12 -> 0.0825 | R20: =R19+N20 -> 6625.441 | S20: =S19+P20 -> 68263.819 | T20: =L20-N20 -> 760174.56 | U20: =R20+S20 -> 74889.26 | W20: 13 | X20: 45231 | Y20: =AG19 -> 760394.43 | Z20: =Z19 -> 5626.5068 | AA20: =Z20-AC20 -> 557.21056 | AB20: =(AA20/Y20)*12 -> 0.0087934978 | AC20: =Y20*($X$3/12) -> 5069.2962 | AD20: =(AC20/Y20)*12 -> 0.08 | AE20: =AE19+AA20 -> 6962.7816 | AF20: =AF19+AC20 -> 66181.806 | AG20: =Y20-AA20 -> 759837.22 | AH20: =AE20+AF20 -> 73144.588 | AJ20: 13 | AK20: 45231 | AL20: =AT19 -> 760069.89 | AM20: =AM19 -> 5493.4491 | AN20: =AM20-AP20 -> 584.66442 | AO20: =(AN20/AL20)*12 -> 0.0092306947 | AP20: =AL20*($AK$3/12) -> 4908.7847 | AQ20: =(AP20/AL20)*12 -> 0.0775 | AR20: =AR19+AN20 -> 7314.7788 | AS20: =AS19+AP20 -> 64100.059 | AT20: =AL20-AN20 -> 759485.22 | AU20: =AR20+AS20 -> 71414.838 | AW20: 13 | AX20: 45231 | AY20: =BG19 -> 759731.37 | AZ20: =AZ19 -> 5361.5769 | BA20: =AZ20-BC20 -> 613.25577 | BB20: =(BA20/AY20)*12 -> 0.0096864095 | BC20: =AY20*($AX$3/12) -> 4748.3211 | BD20: =(BC20/AY20)*12 -> 0.075 | BE20: =BE19+BA20 -> 7681.8822 | BF20: =BF19+BC20 -> 62018.617 | BG20: =AY20-BA20 -> 759118.12 | BH20: =BE20+BF20 -> 69700.499 | BJ20: 13 | BK20: 45231 | BL20: =BT19 -> 759378.47 | BM20: =BM19 -> 5230.9277 | BN20: =BM20-BP20 -> 643.0161 | BO20: =(BN20/BL20)*12 -> 0.010161196 | BP20: =BL20*($BK$3/12) -> 4587.9116 | BQ20: =(BP20/BL20)*12 -> 0.0725 | BR20: =BR19+BN20 -> 8064.5416 | BS20: =BS19+BP20 -> 59937.519 | BT20: =BL20-BN20 -> 758735.46 | BU20: =BR20+BS20 -> 68002.06 | BW20: 13 | BX20: 45231 | BY20: =CG19 -> 759010.77 | BZ20: =BZ19 -> 5101.5395 | CA20: =BZ20-CC20 -> 673.97671 | CB20: =(CA20/BY20)*12 -> 0.010655607 | CC20: =BY20*($BX$3/12) -> 4427.5628 | CD20: =(CC20/BY20)*12 -> 0.07 | CE20: =CE19+CA20 -> 8463.2065 | CF20: =CF19+CC20 -> 57856.807 | CG20: =BY20-CA20 -> 758336.79 | CH20: =CE20+CF20 -> 66320.014
A21: =A20+1 -> 11 | B21: =VLOOKUP(A21*12,$J$7:$U$367,10) -> 655833.98 | C21: =VLOOKUP(A21*12,$W$7:$AH$367,10) -> 634353.86 | D21: =VLOOKUP(A21*12,$AJ$7:$AU$367,10) -> 612922.05 | E21: =VLOOKUP(A21*12,$AW$7:$BH$367,10) -> 591542.71 | F21: =VLOOKUP(A21*12,$BJ$7:$BU$367,10) -> 570220.16 | G21: =VLOOKUP(A21*12,$BW$7:$CH$367,10) -> 548958.86 | J21: 14 | K21: 45261 | L21: =T20 -> 760174.56 | M21: =$L$8/((($N$4)-1)/($N$3*$N$4)) -> 5760.7123 | N21: =M21-P21 -> 534.51223 | O21: =(N21/L21)*12 -> 0.0084377287 | P21: =L21*($K$3/12) -> 5226.2001 | Q21: =(P21/L21)*12 -> 0.0825 | R21: =R20+N21 -> 7159.9532 | S21: =S20+P21 -> 73490.019 | T21: =L21-N21 -> 759640.05 | U21: =R21+S21 -> 80649.972 | W21: 14 | X21: 45261 | Y21: =AG20 -> 759837.22 | Z21: =Z20 -> 5626.5068 | AA21: =Z21-AC21 -> 560.9253 | AB21: =(AA21/Y21)*12 -> 0.0088586126 | AC21: =Y21*($X$3/12) -> 5065.5815 | AD21: =(AC21/Y21)*12 -> 0.08 | AE21: =AE20+AA21 -> 7523.7069 | AF21: =AF20+AC21 -> 71247.388 | AG21: =Y21-AA21 -> 759276.29 | AH21: =AE21+AF21 -> 78771.095 | AJ21: 14 | AK21: 45261 | AL21: =AT20 -> 759485.22 | AM21: =AM20 -> 5493.4491 | AN21: =AM21-AP21 -> 588.44038 | AO21: =(AN21/AL21)*12 -> 0.0092974614 | AP21: =AL21*($AK$3/12) -> 4905.0087 | AQ21: =(AP21/AL21)*12 -> 0.0775 | AR21: =AR20+AN21 -> 7903.2192 | AS21: =AS20+AP21 -> 69005.068 | AT21: =AL21-AN21 -> 758896.78 | AU21: =AR21+AS21 -> 76908.287 | AW21: 14 | AX21: 45261 | AY21: =BG20 -> 759118.12 | AZ21: =AZ20 -> 5361.5769 | BA21: =AZ21-BC21 -> 617.08862 | BB21: =(BA21/AY21)*12 -> 0.0097548237 | BC21: =AY21*($AX$3/12) -> 4744.4882 | BD21: =(BC21/AY21)*12 -> 0.075 | BE21: =BE20+BA21 -> 8298.9708 | BF21: =BF20+BC21 -> 66763.105 | BG21: =AY21-BA21 -> 758501.03 | BH21: =BE21+BF21 -> 75062.076 | BJ21: 14 | BK21: 45261 | BL21: =BT20 -> 758735.46 | BM21: =BM20 -> 5230.9277 | BN21: =BM21-BP21 -> 646.90099 | BO21: =(BN21/BL21)*12 -> 0.01023125 | BP21: =BL21*($BK$3/12) -> 4584.0267 | BQ21: =(BP21/BL21)*12 -> 0.0725 | BR21: =BR20+BN21 -> 8711.4426 | BS21: =BS20+BP21 -> 64521.545 | BT21: =BL21-BN21 -> 758088.56 | BU21: =BR21+BS21 -> 73232.988 | BW21: 14 | BX21: 45261 | BY21: =CG20 -> 758336.79 | BZ21: =BZ20 -> 5101.5395 | CA21: =BZ21-CC21 -> 677.90824 | CB21: =(CA21/BY21)*12 -> 0.01072729 | CC21: =BY21*($BX$3/12) -> 4423.6313 | CD21: =(CC21/BY21)*12 -> 0.07 | CE21: =CE20+CA21 -> 9141.1147 | CF21: =CF20+CC21 -> 62280.439 | CG21: =BY21-CA21 -> 757658.89 | CH21: =CE21+CF21 -> 71421.553
A22: =A21+1 -> 12 | B22: =VLOOKUP(A22*12,$J$7:$U$367,10) -> 709906.26 | C22: =VLOOKUP(A22*12,$W$7:$AH$367,10) -> 686473.78 | D22: =VLOOKUP(A22*12,$AJ$7:$AU$367,10) -> 663101.14 | E22: =VLOOKUP(A22*12,$AW$7:$BH$367,10) -> 639793.23 | F22: =VLOOKUP(A22*12,$BJ$7:$BU$367,10) -> 616555.11 | G22: =VLOOKUP(A22*12,$BW$7:$CH$367,10) -> 593392.01 | J22: 15 | K22: 45292 | L22: =T21 -> 759640.05 | M22: =$L$8/((($N$4)-1)/($N$3*$N$4)) -> 5760.7123 | N22: =M22-P22 -> 538.187 | O22: =(N22/L22)*12 -> 0.0085017161 | P22: =L22*($K$3/12) -> 5222.5253 | Q22: =(P22/L22)*12 -> 0.0825 | R22: =R21+N22 -> 7698.1402 | S22: =S21+P22 -> 78712.545 | T22: =L22-N22 -> 759101.86 | U22: =R22+S22 -> 86410.685 | W22: 15 | X22: 45292 | Y22: =AG21 -> 759276.29 | Z22: =Z21 -> 5626.5068 | AA22: =Z22-AC22 -> 564.6648 | AB22: =(AA22/Y22)*12 -> 0.0089242581 | AC22: =Y22*($X$3/12) -> 5061.842 | AD22: =(AC22/Y22)*12 -> 0.08 | AE22: =AE21+AA22 -> 8088.3717 | AF22: =AF21+AC22 -> 76309.23 | AG22: =Y22-AA22 -> 758711.63 | AH22: =AE22+AF22 -> 84397.601 | AJ22: 15 | AK22: 45292 | AL22: =AT21 -> 758896.78 | AM22: =AM21 -> 5493.4491 | AN22: =AM22-AP22 -> 592.24072 | AO22: =(AN22/AL22)*12 -> 0.0093647632 | AP22: =AL22*($AK$3/12) -> 4901.2084 | AQ22: =(AP22/AL22)*12 -> 0.0775 | AR22: =AR21+AN22 -> 8495.4599 | AS22: =AS21+AP22 -> 73906.277 | AT22: =AL22-AN22 -> 758304.54 | AU22: =AR22+AS22 -> 82401.736 | AW22: 15 | AX22: 45292 | AY22: =BG21 -> 758501.03 | AZ22: =AZ21 -> 5361.5769 | BA22: =AZ22-BC22 -> 620.94542 | BB22: =(BA22/AY22)*12 -> 0.0098237771 | BC22: =AY22*($AX$3/12) -> 4740.6314 | BD22: =(BC22/AY22)*12 -> 0.075 | BE22: =BE21+BA22 -> 8919.9162 | BF22: =BF21+BC22 -> 71503.737 | BG22: =AY22-BA22 -> 757880.08 | BH22: =BE22+BF22 -> 80423.653 | BJ22: 15 | BK22: 45292 | BL22: =BT21 -> 758088.56 | BM22: =BM21 -> 5230.9277 | BN22: =BM22-BP22 -> 650.80935 | BO22: =(BN22/BL22)*12 -> 0.010301847 | BP22: =BL22*($BK$3/12) -> 4580.1184 | BQ22: =(BP22/BL22)*12 -> 0.0725 | BR22: =BR21+BN22 -> 9362.2519 | BS22: =BS21+BP22 -> 69101.664 | BT22: =BL22-BN22 -> 757437.75 | BU22: =BR22+BS22 -> 78463.916 | BW22: 15 | BX22: 45292 | BY22: =CG21 -> 757658.89 | BZ22: =BZ21 -> 5101.5395 | CA22: =BZ22-CC22 -> 681.8627 | CB22: =(CA22/BY22)*12 -> 0.01079952 | CC22: =BY22*($BX$3/12) -> 4419.6768 | CD22: =(CC22/BY22)*12 -> 0.07 | CE22: =CE21+CA22 -> 9822.9774 | CF22: =CF21+CC22 -> 66700.116 | CG22: =BY22-CA22 -> 756977.02 | CH22: =CE22+CF22 -> 76523.093
A23: =A22+1 -> 13 | B23: =VLOOKUP(A23*12,$J$7:$U$367,10) -> 762688.33 | C23: =VLOOKUP(A23*12,$W$7:$AH$367,10) -> 737315.67 | D23: =VLOOKUP(A23*12,$AJ$7:$AU$367,10) -> 712015.92 | E23: =VLOOKUP(A23*12,$AW$7:$BH$367,10) -> 686794.76 | F23: =VLOOKUP(A23*12,$BJ$7:$BU$367,10) -> 661658.03 | G23: =VLOOKUP(A23*12,$BW$7:$CH$367,10) -> 636611.75 | J23: 16 | K23: 45323 | L23: =T22 -> 759101.86 | M23: =$L$8/((($N$4)-1)/($N$3*$N$4)) -> 5760.7123 | N23: =M23-P23 -> 541.88703 | O23: =(N23/L23)*12 -> 0.0085662343 | P23: =L23*($K$3/12) -> 5218.8253 | Q23: =(P23/L23)*12 -> 0.0825 | R23: =R22+N23 -> 8240.0273 | S23: =S22+P23 -> 83931.37 | T23: =L23-N23 -> 758559.97 | U23: =R23+S23 -> 92171.397 | W23: 16 | X23: 45323 | Y23: =AG22 -> 758711.63 | Z23: =Z22 -> 5626.5068 | AA23: =Z23-AC23 -> 568.42923 | AB23: =(AA23/Y23)*12 -> 0.0089904392 | AC23: =Y23*($X$3/12) -> 5058.0775 | AD23: =(AC23/Y23)*12 -> 0.08 | AE23: =AE22+AA23 -> 8656.8009 | AF23: =AF22+AC23 -> 81367.307 | AG23: =Y23-AA23 -> 758143.2 | AH23: =AE23+AF23 -> 90024.108 | AJ23: 16 | AK23: 45323 | AL23: =AT22 -> 758304.54 | AM23: =AM22 -> 5493.4491 | AN23: =AM23-AP23 -> 596.06561 | AO23: =(AN23/AL23)*12 -> 0.0094326052 | AP23: =AL23*($AK$3/12) -> 4897.3835 | AQ23: =(AP23/AL23)*12 -> 0.0775 | AR23: =AR22+AN23 -> 9091.5255 | AS23: =AS22+AP23 -> 78803.66 | AT23: =AL23-AN23 -> 757708.47 | AU23: =AR23+AS23 -> 87895.186 | AW23: 16 | AX23: 45323 | AY23: =BG22 -> 757880.08 | AZ23: =AZ22 -> 5361.5769 | BA23: =AZ23-BC23 -> 624.82633 | BB23: =(BA23/AY23)*12 -> 0.0098932748 | BC23: =AY23*($AX$3/12) -> 4736.7505 | BD23: =(BC23/AY23)*12 -> 0.075 | BE23: =BE22+BA23 -> 9544.7425 | BF23: =BF22+BC23 -> 76240.487 | BG23: =AY23-BA23 -> 757255.26 | BH23: =BE23+BF23 -> 85785.23 | BJ23: 16 | BK23: 45323 | BL23: =BT22 -> 757437.75 | BM23: =BM22 -> 5230.9277 | BN23: =BM23-BP23 -> 654.74132 | BO23: =(BN23/BL23)*12 -> 0.010372992 | BP23: =BL23*($BK$3/12) -> 4576.1864 | BQ23: =(BP23/BL23)*12 -> 0.0725 | BR23: =BR22+BN23 -> 10016.993 | BS23: =BS22+BP23 -> 73677.85 | BT23: =BL23-BN23 -> 756783.01 | BU23: =BR23+BS23 -> 83694.843 | BW23: 16 | BX23: 45323 | BY23: =CG22 -> 756977.02 | BZ23: =BZ22 -> 5101.5395 | CA23: =BZ23-CC23 -> 685.84023 | CB23: =(CA23/BY23)*12 -> 0.010872302 | CC23: =BY23*($BX$3/12) -> 4415.6993 | CD23: =(CC23/BY23)*12 -> 0.07 | CE23: =CE22+CA23 -> 10508.818 | CF23: =CF22+CC23 -> 71115.815 | CG23: =BY23-CA23 -> 756291.18 | CH23: =CE23+CF23 -> 81624.633
... A40: =A39+1 -> 30 | B40: =VLOOKUP(A40*12,$J$7:$U$367,10) -> 1307056.4 | C40: =VLOOKUP(A40*12,$W$7:$AH$367,10) -> 1258742.4 | D40: =VLOOKUP(A40*12,$AJ$7:$AU$367,10) -> 1210841.7 | E40: =VLOOKUP(A40*12,$AW$7:$BH$367,10) -> 1163367.7 | F40: =VLOOKUP(A40*12,$BJ$7:$BU$367,10) -> 1116334 | G40: =VLOOKUP(A40*12,$BW$7:$CH$367,10) -> 1069754.2 | J40: 33 | K40: 45839 | L40: =T39 -> 749365.27 | M40: =$L$8/((($N$4)-1)/($N$3*$N$4)) -> 5760.7123 | N40: =M40-P40 -> 608.82607 | O40: =(N40/L40)*12 -> 0.0097494681 | P40: =L40*($K$3/12) -> 5151.8862 | Q40: =(P40/L40)*12 -> 0.0825 | R40: =R39+N40 -> 18043.554 | S40: =S39+P40 -> 172059.95 | T40: =L40-N40 -> 748756.45 | U40: =R40+S40 -> 190103.51 | W40: 33 | X40: 45839 | Y40: =AG39 -> 748515.37 | Z40: =Z39 -> 5626.5068 | AA40: =Z40-AC40 -> 636.4043 | AB40: =(AA40/Y40)*12 -> 0.010202665 | AC40: =Y40*($X$3/12) -> 4990.1025 | AD40: =(AC40/Y40)*12 -> 0.08 | AE40: =AE39+AA40 -> 18921.036 | AF40: =AF39+AC40 -> 166753.69 | AG40: =Y40-AA40 -> 747878.96 | AH40: =AE40+AF40 -> 185674.72 | AJ40: 33 | AK40: 45839 | AL40: =AT39 -> 747630.59 | AM40: =AM39 -> 5493.4491 | AN40: =AM40-AP40 -> 665.00157 | AO40: =(AN40/AL40)*12 -> 0.010673746 | AP40: =AL40*($AK$3/12) -> 4828.4475 | AQ40: =(AP40/AL40)*12 -> 0.0775 | AR40: =AR39+AN40 -> 19834.416 | AS40: =AS39+AP40 -> 161449.4 | AT40: =AL40-AN40 -> 746965.58 | AU40: =AR40+AS40 -> 181283.82 | AW40: 33 | AX40: 45839 | AY40: =BG39 -> 746709.97 | AZ40: =AZ39 -> 5361.5769 | BA40: =AZ40-BC40 -> 694.63955 | BB40: =(BA40/AY40)*12 -> 0.011163203 | BC40: =AY40*($AX$3/12) -> 4666.9373 | BD40: =(BC40/AY40)*12 -> 0.075 | BE40: =BE39+BA40 -> 20784.672 | BF40: =BF39+BC40 -> 156147.36 | BG40: =AY40-BA40 -> 746015.33 | BH40: =BE40+BF40 -> 176932.04 | BJ40: 33 | BK40: 45839 | BL40: =BT39 -> 745752.57 | BM40: =BM39 -> 5230.9277 | BN40: =BM40-BP40 -> 725.3393 | BO40: =(BN40/BL40)*12 -> 0.011671527 | BP40: =BL40*($BK$3/12) -> 4505.5884 | BQ40: =(BP40/BL40)*12 -> 0.0725 | BR40: =BR39+BN40 -> 21772.773 | BS40: =BS39+BP40 -> 150847.84 | BT40: =BL40-BN40 -> 745027.23 | BU40: =BR40+BS40 -> 172620.61 | BW40: 33 | BX40: 45839 | BY40: =CG39 -> 744757.44 | BZ40: =BZ39 -> 5101.5395 | CA40: =BZ40-CC40 -> 757.12113 | CB40: =(CA40/BY40)*12 -> 0.012199212 | CC40: =BY40*($BX$3/12) -> 4344.4184 | CD40: =(CC40/BY40)*12 -> 0.07 | CE40: =CE39+CA40 -> 22799.681 | CF40: =CF39+CC40 -> 145551.12 | CG40: =BY40-CA40 -> 744000.32 | CH40: =CE40+CF40 -> 168350.8
J41: 34 | K41: 45870 | L41: =T40 -> 748756.45 | M41: =$L$8/((($N$4)-1)/($N$3*$N$4)) -> 5760.7123 | N41: =M41-P41 -> 613.01175 | O41: =(N41/L41)*12 -> 0.0098244777 | P41: =L41*($K$3/12) -> 5147.7006 | Q41: =(P41/L41)*12 -> 0.0825 | R41: =R40+N41 -> 18656.565 | S41: =S40+P41 -> 177207.65 | T41: =L41-N41 -> 748143.43 | U41: =R41+S41 -> 195864.22 | W41: 34 | X41: 45870 | Y41: =AG40 -> 747878.96 | Z41: =Z40 -> 5626.5068 | AA41: =Z41-AC41 -> 640.64699 | AB41: =(AA41/Y41)*12 -> 0.010279423 | AC41: =Y41*($X$3/12) -> 4985.8598 | AD41: =(AC41/Y41)*12 -> 0.08 | AE41: =AE40+AA41 -> 19561.683 | AF41: =AF40+AC41 -> 171739.55 | AG41: =Y41-AA41 -> 747238.32 | AH41: =AE41+AF41 -> 191301.23 | AJ41: 34 | AK41: 45870 | AL41: =AT40 -> 746965.58 | AM41: =AM40 -> 5493.4491 | AN41: =AM41-AP41 -> 669.29637 | AO41: =(AN41/AL41)*12 -> 0.010752244 | AP41: =AL41*($AK$3/12) -> 4824.1527 | AQ41: =(AP41/AL41)*12 -> 0.0775 | AR41: =AR40+AN41 -> 20503.712 | AS41: =AS40+AP41 -> 166273.56 | AT41: =AL41-AN41 -> 746296.29 | AU41: =AR41+AS41 -> 186777.27 | AW41: 34 | AX41: 45870 | AY41: =BG40 -> 746015.33 | AZ41: =AZ40 -> 5361.5769 | BA41: =AZ41-BC41 -> 698.98105 | BB41: =(BA41/AY41)*12 -> 0.011243432 | BC41: =AY41*($AX$3/12) -> 4662.5958 | BD41: =(BC41/AY41)*12 -> 0.075 | BE41: =BE40+BA41 -> 21483.653 | BF41: =BF40+BC41 -> 160809.96 | BG41: =AY41-BA41 -> 745316.35 | BH41: =BE41+BF41 -> 182293.61 | BJ41: 34 | BK41: 45870 | BL41: =BT40 -> 745027.23 | BM41: =BM40 -> 5230.9277 | BN41: =BM41-BP41 -> 729.72155 | BO41: =(BN41/BL41)*12 -> 0.011753475 | BP41: =BL41*($BK$3/12) -> 4501.2062 | BQ41: =(BP41/BL41)*12 -> 0.0725 | BR41: =BR40+BN41 -> 22502.495 | BS41: =BS40+BP41 -> 155349.05 | BT41: =BL41-BN41 -> 744297.51 | BU41: =BR41+BS41 -> 177851.54 | BW41: 34 | BX41: 45870 | BY41: =CG40 -> 744000.32 | BZ41: =BZ40 -> 5101.5395 | CA41: =BZ41-CC41 -> 761.53767 | CB41: =(CA41/BY41)*12 -> 0.01228286 | CC41: =BY41*($BX$3/12) -> 4340.0019 | CD41: =(CC41/BY41)*12 -> 0.07 | CE41: =CE40+CA41 -> 23561.219 | CF41: =CF40+CC41 -> 149891.13 | CG41: =BY41-CA41 -> 743238.78 | CH41: =CE41+CF41 -> 173452.34
J42: 35 | K42: 45901 | L42: =T41 -> 748143.43 | M42: =$L$8/((($N$4)-1)/($N$3*$N$4)) -> 5760.7123 | N42: =M42-P42 -> 617.22621 | O42: =(N42/L42)*12 -> 0.0099001263 | P42: =L42*($K$3/12) -> 5143.4861 | Q42: =(P42/L42)*12 -> 0.0825 | R42: =R41+N42 -> 19273.791 | S42: =S41+P42 -> 182351.14 | T42: =L42-N42 -> 747526.21 | U42: =R42+S42 -> 201624.93 | W42: 35 | X42: 45901 | Y42: =AG41 -> 747238.32 | Z42: =Z41 -> 5626.5068 | AA42: =Z42-AC42 -> 644.91797 | AB42: =(AA42/Y42)*12 -> 0.010356824 | AC42: =Y42*($X$3/12) -> 4981.5888 | AD42: =(AC42/Y42)*12 -> 0.08 | AE42: =AE41+AA42 -> 20206.601 | AF42: =AF41+AC42 -> 176721.14 | AG42: =Y42-AA42 -> 746593.4 | AH42: =AE42+AF42 -> 196927.74 | AJ42: 35 | AK42: 45901 | AL42: =AT41 -> 746296.29 | AM42: =AM41 -> 5493.4491 | AN42: =AM42-AP42 -> 673.61891 | AO42: =(AN42/AL42)*12 -> 0.010831391 | AP42: =AL42*($AK$3/12) -> 4819.8302 | AQ42: =(AP42/AL42)*12 -> 0.0775 | AR42: =AR41+AN42 -> 21177.331 | AS42: =AS41+AP42 -> 171093.39 | AT42: =AL42-AN42 -> 745622.67 | AU42: =AR42+AS42 -> 192270.72 | AW42: 35 | AX42: 45901 | AY42: =BG41 -> 745316.35 | AZ42: =AZ41 -> 5361.5769 | BA42: =AZ42-BC42 -> 703.34968 | BB42: =(BA42/AY42)*12 -> 0.011324314 | BC42: =AY42*($AX$3/12) -> 4658.2272 | BD42: =(BC42/AY42)*12 -> 0.075 | BE42: =BE41+BA42 -> 22187.002 | BF42: =BF41+BC42 -> 165468.19 | BG42: =AY42-BA42 -> 744613 | BH42: =BE42+BF42 -> 187655.19 | BJ42: 35 | BK42: 45901 | BL42: =BT41 -> 744297.51 | BM42: =BM41 -> 5230.9277 | BN42: =BM42-BP42 -> 734.13029 | BO42: =(BN42/BL42)*12 -> 0.011836078 | BP42: =BL42*($BK$3/12) -> 4496.7974 | BQ42: =(BP42/BL42)*12 -> 0.0725 | BR42: =BR41+BN42 -> 23236.625 | BS42: =BS41+BP42 -> 159845.84 | BT42: =BL42-BN42 -> 743563.37 | BU42: =BR42+BS42 -> 183082.47 | BW42: 35 | BX42: 45901 | BY42: =CG41 -> 743238.78 | BZ42: =BZ41 -> 5101.5395 | CA42: =BZ42-CC42 -> 765.97998 | CB42: =(CA42/BY42)*12 -> 0.012367169 | CC42: =BY42*($BX$3/12) -> 4335.5596 | CD42: =(CC42/BY42)*12 -> 0.07 | CE42: =CE41+CA42 -> 24327.199 | CF42: =CF41+CC42 -> 154226.68 | CG42: =BY42-CA42 -> 742472.8 | CH42: =CE42+CF42 -> 178553.88
J43: 36 | K43: 45931 | L43: =T42 -> 747526.21 | M43: =$L$8/((($N$4)-1)/($N$3*$N$4)) -> 5760.7123 | N43: =M43-P43 -> 621.46964 | O43: =(N43/L43)*12 -> 0.0099764203 | P43: =L43*($K$3/12) -> 5139.2427 | Q43: =(P43/L43)*12 -> 0.0825 | R43: =R42+N43 -> 19895.261 | S43: =S42+P43 -> 187490.38 | T43: =L43-N43 -> 746904.74 | U43: =R43+S43 -> 207385.64 | W43: 36 | X43: 45931 | Y43: =AG42 -> 746593.4 | Z43: =Z42 -> 5626.5068 | AA43: =Z43-AC43 -> 649.21742 | AB43: =(AA43/Y43)*12 -> 0.010434875 | AC43: =Y43*($X$3/12) -> 4977.2893 | AD43: =(AC43/Y43)*12 -> 0.08 | AE43: =AE42+AA43 -> 20855.818 | AF43: =AF42+AC43 -> 181698.42 | AG43: =Y43-AA43 -> 745944.18 | AH43: =AE43+AF43 -> 202554.24 | AJ43: 36 | AK43: 45931 | AL43: =AT42 -> 745622.67 | AM43: =AM42 -> 5493.4491 | AN43: =AM43-AP43 -> 677.96936 | AO43: =(AN43/AL43)*12 -> 0.010911192 | AP43: =AL43*($AK$3/12) -> 4815.4797 | AQ43: =(AP43/AL43)*12 -> 0.0775 | AR43: =AR42+AN43 -> 21855.301 | AS43: =AS42+AP43 -> 175908.87 | AT43: =AL43-AN43 -> 744944.7 | AU43: =AR43+AS43 -> 197764.17 | AW43: 36 | AX43: 45931 | AY43: =BG42 -> 744613 | AZ43: =AZ42 -> 5361.5769 | BA43: =AZ43-BC43 -> 707.74562 | BB43: =(BA43/AY43)*12 -> 0.011405854 | BC43: =AY43*($AX$3/12) -> 4653.8312 | BD43: =(BC43/AY43)*12 -> 0.075 | BE43: =BE42+BA43 -> 22894.748 | BF43: =BF42+BC43 -> 170122.02 | BG43: =AY43-BA43 -> 743905.25 | BH43: =BE43+BF43 -> 193016.77 | BJ43: 36 | BK43: 45931 | BL43: =BT42 -> 743563.37 | BM43: =BM42 -> 5230.9277 | BN43: =BM43-BP43 -> 738.56566 | BO43: =(BN43/BL43)*12 -> 0.011919344 | BP43: =BL43*($BK$3/12) -> 4492.3621 | BQ43: =(BP43/BL43)*12 -> 0.0725 | BR43: =BR42+BN43 -> 23975.191 | BS43: =BS42+BP43 -> 164338.21 | BT43: =BL43-BN43 -> 742824.81 | BU43: =BR43+BS43 -> 188313.4 | BW43: 36 | BX43: 45931 | BY43: =CG42 -> 742472.8 | BZ43: =BZ42 -> 5101.5395 | CA43: =BZ43-CC43 -> 770.44819 | CB43: =(CA43/BY43)*12 -> 0.012452144 | CC43: =BY43*($BX$3/12) -> 4331.0913 | CD43: =(CC43/BY43)*12 -> 0.07 | CE43: =CE42+CA43 -> 25097.647 | CF43: =CF42+CC43 -> 158557.78 | CG43: =BY43-CA43 -> 741702.35 | CH43: =CE43+CF43 -> 183655.42
J44: 37 | K44: 45962 | L44: =T43 -> 746904.74 | M44: =$L$8/((($N$4)-1)/($N$3*$N$4)) -> 5760.7123 | N44: =M44-P44 -> 625.74224 | O44: =(N44/L44)*12 -> 0.010053366 | P44: =L44*($K$3/12) -> 5134.9701 | Q44: =(P44/L44)*12 -> 0.0825 | R44: =R43+N44 -> 20521.003 | S44: =S43+P44 -> 192625.35 | T44: =L44-N44 -> 746279 | U44: =R44+S44 -> 213146.36 | W44: 37 | X44: 45962 | Y44: =AG43 -> 745944.18 | Z44: =Z43 -> 5626.5068 | AA44: =Z44-AC44 -> 653.54554 | AB44: =(AA44/Y44)*12 -> 0.010513584 | AC44: =Y44*($X$3/12) -> 4972.9612 | AD44: =(AC44/Y44)*12 -> 0.08 | AE44: =AE43+AA44 -> 21509.364 | AF44: =AF43+AC44 -> 186671.39 | AG44: =Y44-AA44 -> 745290.64 | AH44: =AE44+AF44 -> 208180.75 | AJ44: 37 | AK44: 45962 | AL44: =AT43 -> 744944.7 | AM44: =AM43 -> 5493.4491 | AN44: =AM44-AP44 -> 682.34792 | AO44: =(AN44/AL44)*12 -> 0.010991655 | AP44: =AL44*($AK$3/12) -> 4811.1012 | AQ44: =(AP44/AL44)*12 -> 0.0775 | AR44: =AR43+AN44 -> 22537.648 | AS44: =AS43+AP44 -> 180719.97 | AT44: =AL44-AN44 -> 744262.35 | AU44: =AR44+AS44 -> 203257.62 | AW44: 37 | AX44: 45962 | AY44: =BG43 -> 743905.25 | AZ44: =AZ43 -> 5361.5769 | BA44: =AZ44-BC44 -> 712.16903 | BB44: =(BA44/AY44)*12 -> 0.01148806 | BC44: =AY44*($AX$3/12) -> 4649.4078 | BD44: =(BC44/AY44)*12 -> 0.075 | BE44: =BE43+BA44 -> 23606.917 | BF44: =BF43+BC44 -> 174771.43 | BG44: =AY44-BA44 -> 743193.08 | BH44: =BE44+BF44 -> 198378.34 | BJ44: 37 | BK44: 45962 | BL44: =BT43 -> 742824.81 | BM44: =BM43 -> 5230.9277 | BN44: =BM44-BP44 -> 743.02783 | BO44: =(BN44/BL44)*12 -> 0.01200328 | BP44: =BL44*($BK$3/12) -> 4487.8999 | BQ44: =(BP44/BL44)*12 -> 0.0725 | BR44: =BR43+BN44 -> 24718.219 | BS44: =BS43+BP44 -> 168826.11 | BT44: =BL44-BN44 -> 742081.78 | BU44: =BR44+BS44 -> 193544.33 | BW44: 37 | BX44: 45962 | BY44: =CG43 -> 741702.35 | BZ44: =BZ43 -> 5101.5395 | CA44: =BZ44-CC44 -> 774.94247 | CB44: =(CA44/BY44)*12 -> 0.012537792 | CC44: =BY44*($BX$3/12) -> 4326.5971 | CD44: =(CC44/BY44)*12 -> 0.07 | CE44: =CE43+CA44 -> 25872.589 | CF44: =CF43+CC44 -> 162884.37 | CG44: =BY44-CA44 -> 740927.41 | CH44: =CE44+CF44 -> 188756.96
J45: 38 | K45: 45992 | L45: =T44 -> 746279 | M45: =$L$8/((($N$4)-1)/($N$3*$N$4)) -> 5760.7123 | N45: =M45-P45 -> 630.04422 | O45: =(N45/L45)*12 -> 0.010130971 | P45: =L45*($K$3/12) -> 5130.6681 | Q45: =(P45/L45)*12 -> 0.0825 | R45: =R44+N45 -> 21151.048 | S45: =S44+P45 -> 197756.02 | T45: =L45-N45 -> 745648.95 | U45: =R45+S45 -> 218907.07 | W45: 38 | X45: 45992 | Y45: =AG44 -> 745290.64 | Z45: =Z44 -> 5626.5068 | AA45: =Z45-AC45 -> 657.90251 | AB45: =(AA45/Y45)*12 -> 0.010592955 | AC45: =Y45*($X$3/12) -> 4968.6042 | AD45: =(AC45/Y45)*12 -> 0.08 | AE45: =AE44+AA45 -> 22167.266 | AF45: =AF44+AC45 -> 191639.99 | AG45: =Y45-AA45 -> 744632.73 | AH45: =AE45+AF45 -> 213807.26 | AJ45: 38 | AK45: 45992 | AL45: =AT44 -> 744262.35 | AM45: =AM44 -> 5493.4491 | AN45: =AM45-AP45 -> 686.75475 | AO45: =(AN45/AL45)*12 -> 0.011072785 | AP45: =AL45*($AK$3/12) -> 4806.6944 | AQ45: =(AP45/AL45)*12 -> 0.0775 | AR45: =AR44+AN45 -> 23224.403 | AS45: =AS44+AP45 -> 185526.66 | AT45: =AL45-AN45 -> 743575.6 | AU45: =AR45+AS45 -> 208751.07 | AW45: 38 | AX45: 45992 | AY45: =BG44 -> 743193.08 | AZ45: =AZ44 -> 5361.5769 | BA45: =AZ45-BC45 -> 716.62008 | BB45: =(BA45/AY45)*12 -> 0.011570938 | BC45: =AY45*($AX$3/12) -> 4644.9568 | BD45: =(BC45/AY45)*12 -> 0.075 | BE45: =BE44+BA45 -> 24323.537 | BF45: =BF44+BC45 -> 179416.38 | BG45: =AY45-BA45 -> 742476.46 | BH45: =BE45+BF45 -> 203739.92 | BJ45: 38 | BK45: 45992 | BL45: =BT44 -> 742081.78 | BM45: =BM44 -> 5230.9277 | BN45: =BM45-BP45 -> 747.51695 | BO45: =(BN45/BL45)*12 -> 0.012087891 | BP45: =BL45*($BK$3/12) -> 4483.4108 | BQ45: =(BP45/BL45)*12 -> 0.0725 | BR45: =BR44+BN45 -> 25465.736 | BS45: =BS44+BP45 -> 173309.52 | BT45: =BL45-BN45 -> 741334.26 | BU45: =BR45+BS45 -> 198775.25 | BW45: 38 | BX45: 45992 | BY45: =CG44 -> 740927.41 | BZ45: =BZ44 -> 5101.5395 | CA45: =BZ45-CC45 -> 779.46297 | CB45: =(CA45/BY45)*12 -> 0.012624119 | CC45: =BY45*($BX$3/12) -> 4322.0766 | CD45: =(CC45/BY45)*12 -> 0.07 | CE45: =CE44+CA45 -> 26652.052 | CF45: =CF44+CC45 -> 167206.45 | CG45: =BY45-CA45 -> 740147.95 | CH45: =CE45+CF45 -> 193858.5
J46: 39 | K46: 46023 | L46: =T45 -> 745648.95 | M46: =$L$8/((($N$4)-1)/($N$3*$N$4)) -> 5760.7123 | N46: =M46-P46 -> 634.37577 | O46: =(N46/L46)*12 -> 0.01020924 | P46: =L46*($K$3/12) -> 5126.3365 | Q46: =(P46/L46)*12 -> 0.0825 | R46: =R45+N46 -> 21785.423 | S46: =S45+P46 -> 202882.36 | T46: =L46-N46 -> 745014.58 | U46: =R46+S46 -> 224667.78 | W46: 39 | X46: 46023 | Y46: =AG45 -> 744632.73 | Z46: =Z45 -> 5626.5068 | AA46: =Z46-AC46 -> 662.28853 | AB46: =(AA46/Y46)*12 -> 0.010672996 | AC46: =Y46*($X$3/12) -> 4964.2182 | AD46: =(AC46/Y46)*12 -> 0.08 | AE46: =AE45+AA46 -> 22829.555 | AF46: =AF45+AC46 -> 196604.21 | AG46: =Y46-AA46 -> 743970.45 | AH46: =AE46+AF46 -> 219433.76 | AJ46: 39 | AK46: 46023 | AL46: =AT45 -> 743575.6 | AM46: =AM45 -> 5493.4491 | AN46: =AM46-AP46 -> 691.19004 | AO46: =(AN46/AL46)*12 -> 0.011154589 | AP46: =AL46*($AK$3/12) -> 4802.2591 | AQ46: =(AP46/AL46)*12 -> 0.0775 | AR46: =AR45+AN46 -> 23915.593 | AS46: =AS45+AP46 -> 190328.92 | AT46: =AL46-AN46 -> 742884.41 | AU46: =AR46+AS46 -> 214244.51 | AW46: 39 | AX46: 46023 | AY46: =BG45 -> 742476.46 | AZ46: =AZ45 -> 5361.5769 | BA46: =AZ46-BC46 -> 721.09896 | BB46: =(BA46/AY46)*12 -> 0.011654494 | BC46: =AY46*($AX$3/12) -> 4640.4779 | BD46: =(BC46/AY46)*12 -> 0.075 | BE46: =BE45+BA46 -> 25044.636 | BF46: =BF45+BC46 -> 184056.86 | BG46: =AY46-BA46 -> 741755.36 | BH46: =BE46+BF46 -> 209101.5 | BJ46: 39 | BK46: 46023 | BL46: =BT45 -> 741334.26 | BM46: =BM45 -> 5230.9277 | BN46: =BM46-BP46 -> 752.0332 | BO46: =(BN46/BL46)*12 -> 0.012173184 | BP46: =BL46*($BK$3/12) -> 4478.8945 | BQ46: =(BP46/BL46)*12 -> 0.0725 | BR46: =BR45+BN46 -> 26217.769 | BS46: =BS45+BP46 -> 177788.41 | BT46: =BL46-BN46 -> 740582.23 | BU46: =BR46+BS46 -> 204006.18 | BW46: 39 | BX46: 46023 | BY46: =CG45 -> 740147.95 | BZ46: =BZ45 -> 5101.5395 | CA46: =BZ46-CC46 -> 784.00984 | CB46: =(CA46/BY46)*12 -> 0.012711132 | CC46: =BY46*($BX$3/12) -> 4317.5297 | CD46: =(CC46/BY46)*12 -> 0.07 | CE46: =CE45+CA46 -> 27436.062 | CF46: =CF45+CC46 -> 171523.98 | CG46: =BY46-CA46 -> 739363.94 | CH46: =CE46+CF46 -> 198960.04
J47: 40 | K47: 46054 | L47: =T46 -> 745014.58 | M47: =$L$8/((($N$4)-1)/($N$3*$N$4)) -> 5760.7123 | N47: =M47-P47 -> 638.73711 | O47: =(N47/L47)*12 -> 0.010288182 | P47: =L47*($K$3/12) -> 5121.9752 | Q47: =(P47/L47)*12 -> 0.0825 | R47: =R46+N47 -> 22424.16 | S47: =S46+P47 -> 208004.33 | T47: =L47-N47 -> 744375.84 | U47: =R47+S47 -> 230428.49 | W47: 40 | X47: 46054 | Y47: =AG46 -> 743970.45 | Z47: =Z46 -> 5626.5068 | AA47: =Z47-AC47 -> 666.70378 | AB47: =(AA47/Y47)*12 -> 0.010753714 | AC47: =Y47*($X$3/12) -> 4959.803 | AD47: =(AC47/Y47)*12 -> 0.08 | AE47: =AE46+AA47 -> 23496.259 | AF47: =AF46+AC47 -> 201564.01 | AG47: =Y47-AA47 -> 743303.74 | AH47: =AE47+AF47 -> 225060.27 | AJ47: 40 | AK47: 46054 | AL47: =AT46 -> 742884.41 | AM47: =AM46 -> 5493.4491 | AN47: =AM47-AP47 -> 695.65397 | AO47: =(AN47/AL47)*12 -> 0.011237075 | AP47: =AL47*($AK$3/12) -> 4797.7951 | AQ47: =(AP47/AL47)*12 -> 0.0775 | AR47: =AR46+AN47 -> 24611.247 | AS47: =AS46+AP47 -> 195126.72 | AT47: =AL47-AN47 -> 742188.75 | AU47: =AR47+AS47 -> 219737.96 | AW47: 40 | AX47: 46054 | AY47: =BG46 -> 741755.36 | AZ47: =AZ46 -> 5361.5769 | BA47: =AZ47-BC47 -> 725.60583 | BB47: =(BA47/AY47)*12 -> 0.011738735 | BC47: =AY47*($AX$3/12) -> 4635.971 | BD47: =(BC47/AY47)*12 -> 0.075 | BE47: =BE46+BA47 -> 25770.242 | BF47: =BF46+BC47 -> 188692.83 | BG47: =AY47-BA47 -> 741029.76 | BH47: =BE47+BF47 -> 214463.07 | BJ47: 40 | BK47: 46054 | BL47: =BT46 -> 740582.23 | BM47: =BM46 -> 5230.9277 | BN47: =BM47-BP47 -> 756.57674 | BO47: =(BN47/BL47)*12 -> 0.012259166 | BP47: =BL47*($BK$3/12) -> 4474.351 | BQ47: =(BP47/BL47)*12 -> 0.0725 | BR47: =BR46+BN47 -> 26974.346 | BS47: =BS46+BP47 -> 182262.76 | BT47: =BL47-BN47 -> 739825.65 | BU47: =BR47+BS47 -> 209237.11 | BW47: 40 | BX47: 46054 | BY47: =CG46 -> 739363.94 | BZ47: =BZ46 -> 5101.5395 | CA47: =BZ47-CC47 -> 788.58323 | CB47: =(CA47/BY47)*12 -> 0.012798837 | CC47: =BY47*($BX$3/12) -> 4312.9563 | CD47: =(CC47/BY47)*12 -> 0.07 | CE47: =CE46+CA47 -> 28224.645 | CF47: =CF46+CC47 -> 175836.94 | CG47: =BY47-CA47 -> 738575.35 | CH47: =CE47+CF47 -> 204061.58
J48: 41 | K48: 46082 | L48: =T47 -> 744375.84 | M48: =$L$8/((($N$4)-1)/($N$3*$N$4)) -> 5760.7123 | N48: =M48-P48 -> 643.12842 | O48: =(N48/L48)*12 -> 0.010367802 | P48: =L48*($K$3/12) -> 5117.5839 | Q48: =(P48/L48)*12 -> 0.0825 | R48: =R47+N48 -> 23067.289 | S48: =S47+P48 -> 213121.92 | T48: =L48-N48 -> 743732.71 | U48: =R48+S48 -> 236189.21 | W48: 41 | X48: 46082 | Y48: =AG47 -> 743303.74 | Z48: =Z47 -> 5626.5068 | AA48: =Z48-AC48 -> 671.14848 | AB48: =(AA48/Y48)*12 -> 0.010835115 | AC48: =Y48*($X$3/12) -> 4955.3583 | AD48: =(AC48/Y48)*12 -> 0.08 | AE48: =AE47+AA48 -> 24167.407 | AF48: =AF47+AC48 -> 206519.37 | AG48: =Y48-AA48 -> 742632.59 | AH48: =AE48+AF48 -> 230686.78 | AJ48: 41 | AK48: 46082 | AL48: =AT47 -> 742188.75 | AM48: =AM47 -> 5493.4491 | AN48: =AM48-AP48 -> 700.14674 | AO48: =(AN48/AL48)*12 -> 0.011320248 | AP48: =AL48*($AK$3/12) -> 4793.3024 | AQ48: =(AP48/AL48)*12 -> 0.0775 | AR48: =AR47+AN48 -> 25311.394 | AS48: =AS47+AP48 -> 199920.02 | AT48: =AL48-AN48 -> 741488.61 | AU48: =AR48+AS48 -> 225231.41 | AW48: 41 | AX48: 46082 | AY48: =BG47 -> 741029.76 | AZ48: =AZ47 -> 5361.5769 | BA48: =AZ48-BC48 -> 730.14086 | BB48: =(BA48/AY48)*12 -> 0.011823669 | BC48: =AY48*($AX$3/12) -> 4631.436 | BD48: =(BC48/AY48)*12 -> 0.075 | BE48: =BE47+BA48 -> 26500.383 | BF48: =BF47+BC48 -> 193324.27 | BG48: =AY48-BA48 -> 740299.62 | BH48: =BE48+BF48 -> 219824.65 | BJ48: 41 | BK48: 46082 | BL48: =BT47 -> 739825.65 | BM48: =BM47 -> 5230.9277 | BN48: =BM48-BP48 -> 761.14772 | BO48: =(BN48/BL48)*12 -> 0.012345845 | BP48: =BL48*($BK$3/12) -> 4469.78 | BQ48: =(BP48/BL48)*12 -> 0.0725 | BR48: =BR47+BN48 -> 27735.493 | BS48: =BS47+BP48 -> 186732.54 | BT48: =BL48-BN48 -> 739064.51 | BU48: =BR48+BS48 -> 214468.04 | BW48: 41 | BX48: 46082 | BY48: =CG47 -> 738575.35 | BZ48: =BZ47 -> 5101.5395 | CA48: =BZ48-CC48 -> 793.1833 | CB48: =(CA48/BY48)*12 -> 0.012887242 | CC48: =BY48*($BX$3/12) -> 4308.3562 | CD48: =(CC48/BY48)*12 -> 0.07 | CE48: =CE47+CA48 -> 29017.829 | CF48: =CF47+CC48 -> 180145.29 | CG48: =BY48-CA48 -> 737782.17 | CH48: =CE48+CF48 -> 209163.12
J49: 42 | K49: 46113 | L49: =T48 -> 743732.71 | M49: =$L$8/((($N$4)-1)/($N$3*$N$4)) -> 5760.7123 | N49: =M49-P49 -> 647.54993 | O49: =(N49/L49)*12 -> 0.010448107 | P49: =L49*($K$3/12) -> 5113.1624 | Q49: =(P49/L49)*12 -> 0.0825 | R49: =R48+N49 -> 23714.839 | S49: =S48+P49 -> 218235.08 | T49: =L49-N49 -> 743085.16 | U49: =R49+S49 -> 241949.92 | W49: 42 | X49: 46113 | Y49: =AG48 -> 742632.59 | Z49: =Z48 -> 5626.5068 | AA49: =Z49-AC49 -> 675.6228 | AB49: =(AA49/Y49)*12 -> 0.010917207 | AC49: =Y49*($X$3/12) -> 4950.884 | AD49: =(AC49/Y49)*12 -> 0.08 | AE49: =AE48+AA49 -> 24843.03 | AF49: =AF48+AC49 -> 211470.25 | AG49: =Y49-AA49 -> 741956.97 | AH49: =AE49+AF49 -> 236313.28 | AJ49: 42 | AK49: 46113 | AL49: =AT48 -> 741488.61 | AM49: =AM48 -> 5493.4491 | AN49: =AM49-AP49 -> 704.66852 | AO49: =(AN49/AL49)*12 -> 0.011404116 | AP49: =AL49*($AK$3/12) -> 4788.7806 | AQ49: =(AP49/AL49)*12 -> 0.0775 | AR49: =AR48+AN49 -> 26016.062 | AS49: =AS48+AP49 -> 204708.8 | AT49: =AL49-AN49 -> 740783.94 | AU49: =AR49+AS49 -> 230724.86 | AW49: 42 | AX49: 46113 | AY49: =BG48 -> 740299.62 | AZ49: =AZ48 -> 5361.5769 | BA49: =AZ49-BC49 -> 734.70424 | BB49: =(BA49/AY49)*12 -> 0.011909301 | BC49: =AY49*($AX$3/12) -> 4626.8726 | BD49: =(BC49/AY49)*12 -> 0.075 | BE49: =BE48+BA49 -> 27235.087 | BF49: =BF48+BC49 -> 197951.14 | BG49: =AY49-BA49 -> 739564.91 | BH49: =BE49+BF49 -> 225186.23 | BJ49: 42 | BK49: 46113 | BL49: =BT48 -> 739064.51 | BM49: =BM48 -> 5230.9277 | BN49: =BM49-BP49 -> 765.74632 | BO49: =(BN49/BL49)*12 -> 0.012433226 | BP49: =BL49*($BK$3/12) -> 4465.1814 | BQ49: =(BP49/BL49)*12 -> 0.0725 | BR49: =BR48+BN49 -> 28501.24 | BS49: =BS48+BP49 -> 191197.72 | BT49: =BL49-BN49 -> 738298.76 | BU49: =BR49+BS49 -> 219698.96 | BW49: 42 | BX49: 46113 | BY49: =CG48 -> 737782.17 | BZ49: =BZ48 -> 5101.5395 | CA49: =BZ49-CC49 -> 797.8102 | CB49: =(CA49/BY49)*12 -> 0.012976354 | CC49: =BY49*($BX$3/12) -> 4303.7293 | CD49: =(CC49/BY49)*12 -> 0.07 | CE49: =CE48+CA49 -> 29815.639 | CF49: =CF48+CC49 -> 184449.02 | CG49: =BY49-CA49 -> 736984.36 | CH49: =CE49+CF49 -> 214264.66
J50: 43 | K50: 46143 | L50: =T49 -> 743085.16 | M50: =$L$8/((($N$4)-1)/($N$3*$N$4)) -> 5760.7123 | N50: =M50-P50 -> 652.00184 | O50: =(N50/L50)*12 -> 0.010529105 | P50: =L50*($K$3/12) -> 5108.7105 | Q50: =(P50/L50)*12 -> 0.0825 | R50: =R49+N50 -> 24366.841 | S50: =S49+P50 -> 223343.79 | T50: =L50-N50 -> 742433.16 | U50: =R50+S50 -> 247710.63 | W50: 43 | X50: 46143 | Y50: =AG49 -> 741956.97 | Z50: =Z49 -> 5626.5068 | AA50: =Z50-AC50 -> 680.12695 | AB50: =(AA50/Y50)*12 -> 0.010999996 | AC50: =Y50*($X$3/12) -> 4946.3798 | AD50: =(AC50/Y50)*12 -> 0.08 | AE50: =AE49+AA50 -> 25523.157 | AF50: =AF49+AC50 -> 216416.63 | AG50: =Y50-AA50 -> 741276.84 | AH50: =AE50+AF50 -> 241939.79 | AJ50: 43 | AK50: 46143 | AL50: =AT49 -> 740783.94 | AM50: =AM49 -> 5493.4491 | AN50: =AM50-AP50 -> 709.2195 | AO50: =(AN50/AL50)*12 -> 0.011488686 | AP50: =AL50*($AK$3/12) -> 4784.2296 | AQ50: =(AP50/AL50)*12 -> 0.0775 | AR50: =AR49+AN50 -> 26725.282 | AS50: =AS49+AP50 -> 209493.03 | AT50: =AL50-AN50 -> 740074.72 | AU50: =AR50+AS50 -> 236218.31 | AW50: 43 | AX50: 46143 | AY50: =BG49 -> 739564.91 | AZ50: =AZ49 -> 5361.5769 | BA50: =AZ50-BC50 -> 739.29615 | BB50: =(BA50/AY50)*12 -> 0.011995639 | BC50: =AY50*($AX$3/12) -> 4622.2807 | BD50: =(BC50/AY50)*12 -> 0.075 | BE50: =BE49+BA50 -> 27974.383 | BF50: =BF49+BC50 -> 202573.42 | BG50: =AY50-BA50 -> 738825.62 | BH50: =BE50+BF50 -> 230547.8 | BJ50: 43 | BK50: 46143 | BL50: =BT49 -> 738298.76 | BM50: =BM49 -> 5230.9277 | BN50: =BM50-BP50 -> 770.3727 | BO50: =(BN50/BL50)*12 -> 0.012521317 | BP50: =BL50*($BK$3/12) -> 4460.555 | BQ50: =(BP50/BL50)*12 -> 0.0725 | BR50: =BR49+BN50 -> 29271.612 | BS50: =BS49+BP50 -> 195658.28 | BT50: =BL50-BN50 -> 737528.39 | BU50: =BR50+BS50 -> 224929.89 | BW50: 43 | BX50: 46143 | BY50: =CG49 -> 736984.36 | BZ50: =BZ49 -> 5101.5395 | CA50: =BZ50-CC50 -> 802.46409 | CB50: =(CA50/BY50)*12 -> 0.013066178 | CC50: =BY50*($BX$3/12) -> 4299.0754 | CD50: =(CC50/BY50)*12 -> 0.07 | CE50: =CE49+CA50 -> 30618.103 | CF50: =CF49+CC50 -> 188748.1 | CG50: =BY50-CA50 -> 736181.9 | CH50: =CE50+CF50 -> 219366.2
J51: 44 | K51: 46174 | L51: =T50 -> 742433.16 | M51: =$L$8/((($N$4)-1)/($N$3*$N$4)) -> 5760.7123 | N51: =M51-P51 -> 656.48435 | O51: =(N51/L51)*12 -> 0.010610803 | P51: =L51*($K$3/12) -> 5104.228 | Q51: =(P51/L51)*12 -> 0.0825 | R51: =R50+N51 -> 25023.325 | S51: =S50+P51 -> 228448.02 | T51: =L51-N51 -> 741776.68 | U51: =R51+S51 -> 253471.34 | W51: 44 | X51: 46174 | Y51: =AG50 -> 741276.84 | Z51: =Z50 -> 5626.5068 | AA51: =Z51-AC51 -> 684.66113 | AB51: =(AA51/Y51)*12 -> 0.011083489 | AC51: =Y51*($X$3/12) -> 4941.8456 | AD51: =(AC51/Y51)*12 -> 0.08 | AE51: =AE50+AA51 -> 26207.818 | AF51: =AF50+AC51 -> 221358.48 | AG51: =Y51-AA51 -> 740592.18 | AH51: =AE51+AF51 -> 247566.3 | AJ51: 44 | AK51: 46174 | AL51: =AT50 -> 740074.72 | AM51: =AM50 -> 5493.4491 | AN51: =AM51-AP51 -> 713.79988 | AO51: =(AN51/AL51)*12 -> 0.011573965 | AP51: =AL51*($AK$3/12) -> 4779.6492 | AQ51: =(AP51/AL51)*12 -> 0.0775 | AR51: =AR50+AN51 -> 27439.082 | AS51: =AS50+AP51 -> 214272.68 | AT51: =AL51-AN51 -> 739360.92 | AU51: =AR51+AS51 -> 241711.76 | AW51: 44 | AX51: 46174 | AY51: =BG50 -> 738825.62 | AZ51: =AZ50 -> 5361.5769 | BA51: =AZ51-BC51 -> 743.91675 | BB51: =(BA51/AY51)*12 -> 0.01208269 | BC51: =AY51*($AX$3/12) -> 4617.6601 | BD51: =(BC51/AY51)*12 -> 0.075 | BE51: =BE50+BA51 -> 28718.3 | BF51: =BF50+BC51 -> 207191.08 | BG51: =AY51-BA51 -> 738081.7 | BH51: =BE51+BF51 -> 235909.38 | BJ51: 44 | BK51: 46174 | BL51: =BT50 -> 737528.39 | BM51: =BM50 -> 5230.9277 | BN51: =BM51-BP51 -> 775.02704 | BO51: =(BN51/BL51)*12 -> 0.012610124 | BP51: =BL51*($BK$3/12) -> 4455.9007 | BQ51: =(BP51/BL51)*12 -> 0.0725 | BR51: =BR50+BN51 -> 30046.639 | BS51: =BS50+BP51 -> 200114.18 | BT51: =BL51-BN51 -> 736753.36 | BU51: =BR51+BS51 -> 230160.82 | BW51: 44 | BX51: 46174 | BY51: =CG50 -> 736181.9 | BZ51: =BZ50 -> 5101.5395 | CA51: =BZ51-CC51 -> 807.14513 | CB51: =(CA51/BY51)*12 -> 0.013156723 | CC51: =BY51*($BX$3/12) -> 4294.3944 | CD51: =(CC51/BY51)*12 -> 0.07 | CE51: =CE50+CA51 -> 31425.248 | CF51: =CF50+CC51 -> 193042.49 | CG51: =BY51-CA51 -> 735374.75 | CH51: =CE51+CF51 -> 224467.74
J52: 45 | K52: 46204 | L52: =T51 -> 741776.68 | M52: =$L$8/((($N$4)-1)/($N$3*$N$4)) -> 5760.7123 | N52: =M52-P52 -> 660.99768 | O52: =(N52/L52)*12 -> 0.010693208 | P52: =L52*($K$3/12) -> 5099.7146 | Q52: =(P52/L52)*12 -> 0.0825 | R52: =R51+N52 -> 25684.323 | S52: =S51+P52 -> 233547.73 | T52: =L52-N52 -> 741115.68 | U52: =R52+S52 -> 259232.05 | W52: 45 | X52: 46204 | Y52: =AG51 -> 740592.18 | Z52: =Z51 -> 5626.5068 | AA52: =Z52-AC52 -> 689.22554 | AB52: =(AA52/Y52)*12 -> 0.011167693 | AC52: =Y52*($X$3/12) -> 4937.2812 | AD52: =(AC52/Y52)*12 -> 0.08 | AE52: =AE51+AA52 -> 26897.043 | AF52: =AF51+AC52 -> 226295.76 | AG52: =Y52-AA52 -> 739902.96 | AH52: =AE52+AF52 -> 253192.8 | AJ52: 45 | AK52: 46204 | AL52: =AT51 -> 739360.92 | AM52: =AM51 -> 5493.4491 | AN52: =AM52-AP52 -> 718.40984 | AO52: =(AN52/AL52)*12 -> 0.011659959 | AP52: =AL52*($AK$3/12) -> 4775.0393 | AQ52: =(AP52/AL52)*12 -> 0.0775 | AR52: =AR51+AN52 -> 28157.492 | AS52: =AS51+AP52 -> 219047.72 | AT52: =AL52-AN52 -> 738642.51 | AU52: =AR52+AS52 -> 247205.21 | AW52: 45 | AX52: 46204 | AY52: =BG51 -> 738081.7 | AZ52: =AZ51 -> 5361.5769 | BA52: =AZ52-BC52 -> 748.56623 | BB52: =(BA52/AY52)*12 -> 0.012170461 | BC52: =AY52*($AX$3/12) -> 4613.0106 | BD52: =(BC52/AY52)*12 -> 0.075 | BE52: =BE51+BA52 -> 29466.866 | BF52: =BF51+BC52 -> 211804.09 | BG52: =AY52-BA52 -> 737333.13 | BH52: =BE52+BF52 -> 241270.96 | BJ52: 45 | BK52: 46204 | BL52: =BT51 -> 736753.36 | BM52: =BM51 -> 5230.9277 | BN52: =BM52-BP52 -> 779.70949 | BO52: =(BN52/BL52)*12 -> 0.012699656 | BP52: =BL52*($BK$3/12) -> 4451.2182 | BQ52: =(BP52/BL52)*12 -> 0.0725 | BR52: =BR51+BN52 -> 30826.349 | BS52: =BS51+BP52 -> 204565.4 | BT52: =BL52-BN52 -> 735973.65 | BU52: =BR52+BS52 -> 235391.75 | BW52: 45 | BX52: 46204 | BY52: =CG51 -> 735374.75 | BZ52: =BZ51 -> 5101.5395 | CA52: =BZ52-CC52 -> 811.85348 | CB52: =(CA52/BY52)*12 -> 0.013247996 | CC52: =BY52*($BX$3/12) -> 4289.6861 | CD52: =(CC52/BY52)*12 -> 0.07 | CE52: =CE51+CA52 -> 32237.102 | CF52: =CF51+CC52 -> 197332.18 | CG52: =BY52-CA52 -> 734562.9 | CH52: =CE52+CF52 -> 229569.28
... J342: 335 | K342: 55032 | L342: =T341 -> 136726.51 | M342: =$L$8/((($N$4)-1)/($N$3*$N$4)) -> 5760.7123 | N342: =M342-P342 -> 4820.7175 | O342: =(N342/L342)*12 -> 0.42309724 | P342: =L342*($K$3/12) -> 939.99478 | Q342: =(P342/L342)*12 -> 0.0825 | R342: =R341+N342 -> 634894.2 | S342: =S341+P342 -> 1294944.4 | T342: =L342-N342 -> 131905.8 | U342: =R342+S342 -> 1929838.6 | W342: 335 | X342: 55032 | Y342: =AG341 -> 133904.3 | Z342: =Z341 -> 5626.5068 | AA342: =Z342-AC342 -> 4733.8114 | AB342: =(AA342/Y342)*12 -> 0.42422637 | AC342: =Y342*($X$3/12) -> 892.69536 | AD342: =(AC342/Y342)*12 -> 0.08 | AE342: =AE341+AA342 -> 637629.51 | AF342: =AF341+AC342 -> 1247250.3 | AG342: =Y342-AA342 -> 129170.49 | AH342: =AE342+AF342 -> 1884879.8 | AJ342: 335 | AK342: 55032 | AL342: =AT341 -> 131093.52 | AM342: =AM341 -> 5493.4491 | AN342: =AM342-AP342 -> 4646.8034 | AO342: =(AN342/AL342)*12 -> 0.42535772 | AP342: =AL342*($AK$3/12) -> 846.64566 | AQ342: =(AP342/AL342)*12 -> 0.0775 | AR342: =AR341+AN342 -> 640353.28 | AS342: =AS341+AP342 -> 1199952.2 | AT342: =AL342-AN342 -> 126446.72 | AU342: =AR342+AS342 -> 1840305.4 | AW342: 335 | AX342: 55032 | AY342: =BG341 -> 128295.19 | AZ342: =AZ341 -> 5361.5769 | BA342: =AZ342-BC342 -> 4559.7319 | BB342: =(BA342/AY342)*12 -> 0.42649129 | BC342: =AY342*($AX$3/12) -> 801.84496 | BD342: =(BC342/AY342)*12 -> 0.075 | BE342: =BE341+BA342 -> 643064.54 | BF342: =BF341+BC342 -> 1153063.7 | BG342: =AY342-BA342 -> 123735.46 | BH342: =BE342+BF342 -> 1796128.2 | BJ342: 335 | BK342: 55032 | BL342: =BT341 -> 125510.36 | BM342: =BM341 -> 5230.9277 | BN342: =BM342-BP342 -> 4472.6359 | BO342: =(BN342/BL342)*12 -> 0.4276271 | BP342: =BL342*($BK$3/12) -> 758.29177 | BQ342: =(BP342/BL342)*12 -> 0.0725 | BR342: =BR341+BN342 -> 645762.27 | BS342: =BS341+BP342 -> 1106598.5 | BT342: =BL342-BN342 -> 121037.73 | BU342: =BR342+BS342 -> 1752360.8 | BW342: 335 | BX342: 55032 | BY342: =CG341 -> 122740.09 | BZ342: =BZ341 -> 5101.5395 | CA342: =BZ342-CC342 -> 4385.5557 | CB342: =(CA342/BY342)*12 -> 0.42876513 | CC342: =BY342*($BX$3/12) -> 715.98383 | CD342: =(CC342/BY342)*12 -> 0.07 | CE342: =CE341+CA342 -> 648445.47 | CF342: =CF341+CC342 -> 1060570.3 | CG342: =BY342-CA342 -> 118354.53 | CH342: =CE342+CF342 -> 1709015.7
J343: =J342+1 -> 336 | L343: =T342 -> 131905.8 | M343: =$L$8/((($N$4)-1)/($N$3*$N$4)) -> 5760.7123 | N343: =M343-P343 -> 4853.86 | O343: =(N343/L343)*12 -> 0.44157514 | P343: =L343*($K$3/12) -> 906.85234 | Q343: =(P343/L343)*12 -> 0.0825 | R343: =R342+N343 -> 639748.06 | S343: =S342+P343 -> 1295851.3 | T343: =L343-N343 -> 127051.94 | U343: =R343+S343 -> 1935599.3 | W343: =W342+1 -> 336 | Y343: =AG342 -> 129170.49 | Z343: =Z342 -> 5626.5068 | AA343: =Z343-AC343 -> 4765.3701 | AB343: =(AA343/Y343)*12 -> 0.44270514 | AC343: =Y343*($X$3/12) -> 861.13662 | AD343: =(AC343/Y343)*12 -> 0.08 | AE343: =AE342+AA343 -> 642394.88 | AF343: =AF342+AC343 -> 1248111.4 | AG343: =Y343-AA343 -> 124405.12 | AH343: =AE343+AF343 -> 1890506.3 | AJ343: =AJ342+1 -> 336 | AL343: =AT342 -> 126446.72 | AM343: =AM342 -> 5493.4491 | AN343: =AM343-AP343 -> 4676.814 | AO343: =(AN343/AL343)*12 -> 0.44383729 | AP343: =AL343*($AK$3/12) -> 816.63506 | AQ343: =(AP343/AL343)*12 -> 0.0775 | AR343: =AR342+AN343 -> 645030.1 | AS343: =AS342+AP343 -> 1200768.8 | AT343: =AL343-AN343 -> 121769.9 | AU343: =AR343+AS343 -> 1845798.9 | AW343: =AW342+1 -> 336 | AY343: =BG342 -> 123735.46 | AZ343: =AZ342 -> 5361.5769 | BA343: =AZ343-BC343 -> 4588.2302 | BB343: =(BA343/AY343)*12 -> 0.44497157 | BC343: =AY343*($AX$3/12) -> 773.34663 | BD343: =(BC343/AY343)*12 -> 0.075 | BE343: =BE342+BA343 -> 647652.77 | BF343: =BF342+BC343 -> 1153837.1 | BG343: =AY343-BA343 -> 119147.23 | BH343: =BE343+BF343 -> 1801489.8 | BJ343: =BJ342+1 -> 336 | BL343: =BT342 -> 121037.73 | BM343: =BM342 -> 5230.9277 | BN343: =BM343-BP343 -> 4499.6581 | BO343: =(BN343/BL343)*12 -> 0.446108 | BP343: =BL343*($BK$3/12) -> 731.26959 | BQ343: =(BP343/BL343)*12 -> 0.0725 | BR343: =BR342+BN343 -> 650261.93 | BS343: =BS342+BP343 -> 1107329.8 | BT343: =BL343-BN343 -> 116538.07 | BU343: =BR343+BS343 -> 1757591.7 | BW343: =BW342+1 -> 336 | BY343: =CG342 -> 118354.53 | BZ343: =BZ342 -> 5101.5395 | CA343: =BZ343-CC343 -> 4411.1381 | CB343: =(CA343/BY343)*12 -> 0.44724657 | CC343: =BY343*($BX$3/12) -> 690.40143 | CD343: =(CC343/BY343)*12 -> 0.07 | CE343: =CE342+CA343 -> 652856.61 | CF343: =CF342+CC343 -> 1061260.7 | CG343: =BY343-CA343 -> 113943.39 | CH343: =CE343+CF343 -> 1714117.3
J344: =J343+1 -> 337 | L344: =T343 -> 127051.94 | M344: =$L$8/((($N$4)-1)/($N$3*$N$4)) -> 5760.7123 | N344: =M344-P344 -> 4887.2303 | O344: =(N344/L344)*12 -> 0.46159677 | P344: =L344*($K$3/12) -> 873.48206 | Q344: =(P344/L344)*12 -> 0.0825 | R344: =R343+N344 -> 644635.29 | S344: =S343+P344 -> 1296724.8 | T344: =L344-N344 -> 122164.71 | U344: =R344+S344 -> 1941360.1 | W344: =W343+1 -> 337 | Y344: =AG343 -> 124405.12 | Z344: =Z343 -> 5626.5068 | AA344: =Z344-AC344 -> 4797.1393 | AB344: =(AA344/Y344)*12 -> 0.4627275 | AC344: =Y344*($X$3/12) -> 829.36749 | AD344: =(AC344/Y344)*12 -> 0.08 | AE344: =AE343+AA344 -> 647192.02 | AF344: =AF343+AC344 -> 1248940.8 | AG344: =Y344-AA344 -> 119607.98 | AH344: =AE344+AF344 -> 1896132.8 | AJ344: =AJ343+1 -> 337 | AL344: =AT343 -> 121769.9 | AM344: =AM343 -> 5493.4491 | AN344: =AM344-AP344 -> 4707.0185 | AO344: =(AN344/AL344)*12 -> 0.46386028 | AP344: =AL344*($AK$3/12) -> 786.43063 | AQ344: =(AP344/AL344)*12 -> 0.0775 | AR344: =AR343+AN344 -> 649737.11 | AS344: =AS343+AP344 -> 1201555.2 | AT344: =AL344-AN344 -> 117062.89 | AU344: =AR344+AS344 -> 1851292.3 | AW344: =AW343+1 -> 337 | AY344: =BG343 -> 119147.23 | AZ344: =AZ343 -> 5361.5769 | BA344: =AZ344-BC344 -> 4616.9067 | BB344: =(BA344/AY344)*12 -> 0.46499511 | BC344: =AY344*($AX$3/12) -> 744.67019 | BD344: =(BC344/AY344)*12 -> 0.075 | BE344: =BE343+BA344 -> 652269.68 | BF344: =BF343+BC344 -> 1154581.7 | BG344: =AY344-BA344 -> 114530.32 | BH344: =BE344+BF344 -> 1806851.4 | BJ344: =BJ343+1 -> 337 | BL344: =BT343 -> 116538.07 | BM344: =BM343 -> 5230.9277 | BN344: =BM344-BP344 -> 4526.8436 | BO344: =(BN344/BL344)*12 -> 0.466132 | BP344: =BL344*($BK$3/12) -> 704.08416 | BQ344: =(BP344/BL344)*12 -> 0.0725 | BR344: =BR343+BN344 -> 654788.78 | BS344: =BS343+BP344 -> 1108033.9 | BT344: =BL344-BN344 -> 112011.22 | BU344: =BR344+BS344 -> 1762822.6 | BW344: =BW343+1 -> 337 | BY344: =CG343 -> 113943.39 | BZ344: =BZ343 -> 5101.5395 | CA344: =BZ344-CC344 -> 4436.8697 | CB344: =(CA344/BY344)*12 -> 0.46727095 | CC344: =BY344*($BX$3/12) -> 664.66979 | CD344: =(CC344/BY344)*12 -> 0.07 | CE344: =CE343+CA344 -> 657293.48 | CF344: =CF343+CC344 -> 1061925.3 | CG344: =BY344-CA344 -> 109506.52 | CH344: =CE344+CF344 -> 1719218.8
J345: =J344+1 -> 338 | L345: =T344 -> 122164.71 | M345: =$L$8/((($N$4)-1)/($N$3*$N$4)) -> 5760.7123 | N345: =M345-P345 -> 4920.83 | O345: =(N345/L345)*12 -> 0.4833635 | P345: =L345*($K$3/12) -> 839.88235 | Q345: =(P345/L345)*12 -> 0.0825 | R345: =R344+N345 -> 649556.12 | S345: =S344+P345 -> 1297564.6 | T345: =L345-N345 -> 117243.88 | U345: =R345+S345 -> 1947120.8 | W345: =W344+1 -> 338 | Y345: =AG344 -> 119607.98 | Z345: =Z344 -> 5626.5068 | AA345: =Z345-AC345 -> 4829.1202 | AB345: =(AA345/Y345)*12 -> 0.48449477 | AC345: =Y345*($X$3/12) -> 797.38656 | AD345: =(AC345/Y345)*12 -> 0.08 | AE345: =AE344+AA345 -> 652021.14 | AF345: =AF344+AC345 -> 1249738.1 | AG345: =Y345-AA345 -> 114778.86 | AH345: =AE345+AF345 -> 1901759.3 | AJ345: =AJ344+1 -> 338 | AL345: =AT344 -> 117062.89 | AM345: =AM344 -> 5493.4491 | AN345: =AM345-AP345 -> 4737.418 | AO345: =(AN345/AL345)*12 -> 0.485628 | AP345: =AL345*($AK$3/12) -> 756.03114 | AQ345: =(AP345/AL345)*12 -> 0.0775 | AR345: =AR344+AN345 -> 654474.53 | AS345: =AS344+AP345 -> 1202311.3 | AT345: =AL345-AN345 -> 112325.47 | AU345: =AR345+AS345 -> 1856785.8 | AW345: =AW344+1 -> 338 | AY345: =BG344 -> 114530.32 | AZ345: =AZ344 -> 5361.5769 | BA345: =AZ345-BC345 -> 4645.7623 | BB345: =(BA345/AY345)*12 -> 0.48676321 | BC345: =AY345*($AX$3/12) -> 715.81453 | BD345: =(BC345/AY345)*12 -> 0.075 | BE345: =BE344+BA345 -> 656915.44 | BF345: =BF344+BC345 -> 1155297.5 | BG345: =AY345-BA345 -> 109884.56 | BH345: =BE345+BF345 -> 1812213 | BJ345: =BJ344+1 -> 338 | BL345: =BT344 -> 112011.22 | BM345: =BM344 -> 5230.9277 | BN345: =BM345-BP345 -> 4554.1932 | BO345: =(BN345/BL345)*12 -> 0.48790038 | BP345: =BL345*($BK$3/12) -> 676.73448 | BQ345: =(BP345/BL345)*12 -> 0.0725 | BR345: =BR344+BN345 -> 659342.97 | BS345: =BS344+BP345 -> 1108710.6 | BT345: =BL345-BN345 -> 107457.03 | BU345: =BR345+BS345 -> 1768053.6 | BW345: =BW344+1 -> 338 | BY345: =CG344 -> 109506.52 | BZ345: =BZ344 -> 5101.5395 | CA345: =BZ345-CC345 -> 4462.7515 | CB345: =(CA345/BY345)*12 -> 0.48903953 | CC345: =BY345*($BX$3/12) -> 638.78805 | CD345: =(CC345/BY345)*12 -> 0.07 | CE345: =CE344+CA345 -> 661756.23 | CF345: =CF344+CC345 -> 1062564.1 | CG345: =BY345-CA345 -> 105043.77 | CH345: =CE345+CF345 -> 1724320.4
J346: =J345+1 -> 339 | L346: =T345 -> 117243.88 | M346: =$L$8/((($N$4)-1)/($N$3*$N$4)) -> 5760.7123 | N346: =M346-P346 -> 4954.6607 | O346: =(N346/L346)*12 -> 0.5071133 | P346: =L346*($K$3/12) -> 806.05164 | Q346: =(P346/L346)*12 -> 0.0825 | R346: =R345+N346 -> 654510.79 | S346: =S345+P346 -> 1298370.7 | T346: =L346-N346 -> 112289.21 | U346: =R346+S346 -> 1952881.5 | W346: =W345+1 -> 339 | Y346: =AG345 -> 114778.86 | Z346: =Z345 -> 5626.5068 | AA346: =Z346-AC346 -> 4861.3143 | AB346: =(AA346/Y346)*12 -> 0.5082449 | AC346: =Y346*($X$3/12) -> 765.19242 | AD346: =(AC346/Y346)*12 -> 0.08 | AE346: =AE345+AA346 -> 656882.45 | AF346: =AF345+AC346 -> 1250503.3 | AG346: =Y346-AA346 -> 109917.55 | AH346: =AE346+AF346 -> 1907385.8 | AJ346: =AJ345+1 -> 339 | AL346: =AT345 -> 112325.47 | AM346: =AM345 -> 5493.4491 | AN346: =AM346-AP346 -> 4768.0138 | AO346: =(AN346/AL346)*12 -> 0.50937838 | AP346: =AL346*($AK$3/12) -> 725.43531 | AQ346: =(AP346/AL346)*12 -> 0.0775 | AR346: =AR345+AN346 -> 659242.55 | AS346: =AS345+AP346 -> 1203036.7 | AT346: =AL346-AN346 -> 107557.45 | AU346: =AR346+AS346 -> 1862279.2 | AW346: =AW345+1 -> 339 | AY346: =BG345 -> 109884.56 | AZ346: =AZ345 -> 5361.5769 | BA346: =AZ346-BC346 -> 4674.7983 | BB346: =(BA346/AY346)*12 -> 0.51051375 | BC346: =AY346*($AX$3/12) -> 686.77851 | BD346: =(BC346/AY346)*12 -> 0.075 | BE346: =BE345+BA346 -> 661590.24 | BF346: =BF345+BC346 -> 1155984.3 | BG346: =AY346-BA346 -> 105209.76 | BH346: =BE346+BF346 -> 1817574.6 | BJ346: =BJ345+1 -> 339 | BL346: =BT345 -> 107457.03 | BM346: =BM345 -> 5230.9277 | BN346: =BM346-BP346 -> 4581.7082 | BO346: =(BN346/BL346)*12 -> 0.51165101 | BP346: =BL346*($BK$3/12) -> 649.21956 | BQ346: =(BP346/BL346)*12 -> 0.0725 | BR346: =BR345+BN346 -> 663924.68 | BS346: =BS345+BP346 -> 1109359.8 | BT346: =BL346-BN346 -> 102875.32 | BU346: =BR346+BS346 -> 1773284.5 | BW346: =BW345+1 -> 339 | BY346: =CG345 -> 105043.77 | BZ346: =BZ345 -> 5101.5395 | CA346: =BZ346-CC346 -> 4488.7842 | CB346: =(CA346/BY346)*12 -> 0.51279014 | CC346: =BY346*($BX$3/12) -> 612.75533 | CD346: =(CC346/BY346)*12 -> 0.07 | CE346: =CE345+CA346 -> 666245.01 | CF346: =CF345+CC346 -> 1063176.9 | CG346: =BY346-CA346 -> 100554.99 | CH346: =CE346+CF346 -> 1729421.9
J347: =J346+1 -> 340 | L347: =T346 -> 112289.21 | M347: =$L$8/((($N$4)-1)/($N$3*$N$4)) -> 5760.7123 | N347: =M347-P347 -> 4988.724 | O347: =(N347/L347)*12 -> 0.53312945 | P347: =L347*($K$3/12) -> 771.98835 | Q347: =(P347/L347)*12 -> 0.0825 | R347: =R346+N347 -> 659499.51 | S347: =S346+P347 -> 1299142.7 | T347: =L347-N347 -> 107300.49 | U347: =R347+S347 -> 1958642.2 | W347: =W346+1 -> 340 | Y347: =AG346 -> 109917.55 | Z347: =Z346 -> 5626.5068 | AA347: =Z347-AC347 -> 4893.7231 | AB347: =(AA347/Y347)*12 -> 0.53426116 | AC347: =Y347*($X$3/12) -> 732.78366 | AD347: =(AC347/Y347)*12 -> 0.08 | AE347: =AE346+AA347 -> 661776.17 | AF347: =AF346+AC347 -> 1251236.1 | AG347: =Y347-AA347 -> 105023.83 | AH347: =AE347+AF347 -> 1913012.3 | AJ347: =AJ346+1 -> 340 | AL347: =AT346 -> 107557.45 | AM347: =AM346 -> 5493.4491 | AN347: =AM347-AP347 -> 4798.8072 | AO347: =(AN347/AL347)*12 -> 0.53539466 | AP347: =AL347*($AK$3/12) -> 694.64189 | AQ347: =(AP347/AL347)*12 -> 0.0775 | AR347: =AR346+AN347 -> 664041.35 | AS347: =AS346+AP347 -> 1203731.3 | AT347: =AL347-AN347 -> 102758.65 | AU347: =AR347+AS347 -> 1867772.7 | AW347: =AW346+1 -> 340 | AY347: =BG346 -> 105209.76 | AZ347: =AZ346 -> 5361.5769 | BA347: =AZ347-BC347 -> 4704.0158 | BB347: =(BA347/AY347)*12 -> 0.53652996 | BC347: =AY347*($AX$3/12) -> 657.56102 | BD347: =(BC347/AY347)*12 -> 0.075 | BE347: =BE346+BA347 -> 666294.25 | BF347: =BF346+BC347 -> 1156641.9 | BG347: =AY347-BA347 -> 100505.75 | BH347: =BE347+BF347 -> 1822936.1 | BJ347: =BJ346+1 -> 340 | BL347: =BT346 -> 102875.32 | BM347: =BM346 -> 5230.9277 | BN347: =BM347-BP347 -> 4609.3893 | BO347: =(BN347/BL347)*12 -> 0.53766706 | BP347: =BL347*($BK$3/12) -> 621.53841 | BQ347: =(BP347/BL347)*12 -> 0.0725 | BR347: =BR346+BN347 -> 668534.07 | BS347: =BS346+BP347 -> 1109981.4 | BT347: =BL347-BN347 -> 98265.933 | BU347: =BR347+BS347 -> 1778515.4 | BW347: =BW346+1 -> 340 | BY347: =CG346 -> 100554.99 | BZ347: =BZ346 -> 5101.5395 | CA347: =BZ347-CC347 -> 4514.9688 | CB347: =(CA347/BY347)*12 -> 0.53880595 | CC347: =BY347*($BX$3/12) -> 586.57076 | CD347: =(CC347/BY347)*12 -> 0.07 | CE347: =CE346+CA347 -> 670759.98 | CF347: =CF346+CC347 -> 1063763.5 | CG347: =BY347-CA347 -> 96040.018 | CH347: =CE347+CF347 -> 1734523.4
J348: =J347+1 -> 341 | L348: =T347 -> 107300.49 | M348: =$L$8/((($N$4)-1)/($N$3*$N$4)) -> 5760.7123 | N348: =M348-P348 -> 5023.0214 | O348: =(N348/L348)*12 -> 0.56175193 | P348: =L348*($K$3/12) -> 737.69087 | Q348: =(P348/L348)*12 -> 0.0825 | R348: =R347+N348 -> 664522.53 | S348: =S347+P348 -> 1299880.4 | T348: =L348-N348 -> 102277.47 | U348: =R348+S348 -> 1964402.9 | W348: =W347+1 -> 341 | Y348: =AG347 -> 105023.83 | Z348: =Z347 -> 5626.5068 | AA348: =Z348-AC348 -> 4926.3479 | AB348: =(AA348/Y348)*12 -> 0.56288346 | AC348: =Y348*($X$3/12) -> 700.15884 | AD348: =(AC348/Y348)*12 -> 0.08 | AE348: =AE347+AA348 -> 666702.52 | AF348: =AF347+AC348 -> 1251936.3 | AG348: =Y348-AA348 -> 100097.48 | AH348: =AE348+AF348 -> 1918638.8 | AJ348: =AJ347+1 -> 341 | AL348: =AT347 -> 102758.65 | AM348: =AM347 -> 5493.4491 | AN348: =AM348-AP348 -> 4829.7995 | AO348: =(AN348/AL348)*12 -> 0.56401671 | AP348: =AL348*($AK$3/12) -> 663.64959 | AQ348: =(AP348/AL348)*12 -> 0.0775 | AR348: =AR347+AN348 -> 668871.15 | AS348: =AS347+AP348 -> 1204395 | AT348: =AL348-AN348 -> 97928.847 | AU348: =AR348+AS348 -> 1873266.1 | AW348: =AW347+1 -> 341 | AY348: =BG347 -> 100505.75 | AZ348: =AZ347 -> 5361.5769 | BA348: =AZ348-BC348 -> 4733.4159 | BB348: =(BA348/AY348)*12 -> 0.56515167 | BC348: =AY348*($AX$3/12) -> 628.16092 | BD348: =(BC348/AY348)*12 -> 0.075 | BE348: =BE347+BA348 -> 671027.67 | BF348: =BF347+BC348 -> 1157270 | BG348: =AY348-BA348 -> 95772.332 | BH348: =BE348+BF348 -> 1828297.7 | BJ348: =BJ347+1 -> 341 | BL348: =BT347 -> 98265.933 | BM348: =BM347 -> 5230.9277 | BN348: =BM348-BP348 -> 4637.2377 | BO348: =(BN348/BL348)*12 -> 0.56628834 | BP348: =BL348*($BK$3/12) -> 593.69001 | BQ348: =(BP348/BL348)*12 -> 0.0725 | BR348: =BR347+BN348 -> 673171.3 | BS348: =BS347+BP348 -> 1110575 | BT348: =BL348-BN348 -> 93628.695 | BU348: =BR348+BS348 -> 1783746.4 | BW348: =BW347+1 -> 341 | BY348: =CG347 -> 96040.018 | BZ348: =BZ347 -> 5101.5395 | CA348: =BZ348-CC348 -> 4541.3061 | CB348: =(CA348/BY348)*12 -> 0.56742673 | CC348: =BY348*($BX$3/12) -> 560.23344 | CD348: =(CC348/BY348)*12 -> 0.07 | CE348: =CE347+CA348 -> 675301.29 | CF348: =CF347+CC348 -> 1064323.7 | CG348: =BY348-CA348 -> 91498.712 | CH348: =CE348+CF348 -> 1739625
J349: =J348+1 -> 342 | L349: =T348 -> 102277.47 | M349: =$L$8/((($N$4)-1)/($N$3*$N$4)) -> 5760.7123 | N349: =M349-P349 -> 5057.5547 | O349: =(N349/L349)*12 -> 0.59339224 | P349: =L349*($K$3/12) -> 703.1576 | Q349: =(P349/L349)*12 -> 0.0825 | R349: =R348+N349 -> 669580.09 | S349: =S348+P349 -> 1300583.5 | T349: =L349-N349 -> 97219.914 | U349: =R349+S349 -> 1970163.6 | W349: =W348+1 -> 342 | Y349: =AG348 -> 100097.48 | Z349: =Z348 -> 5626.5068 | AA349: =Z349-AC349 -> 4959.1902 | AB349: =(AA349/Y349)*12 -> 0.5945233 | AC349: =Y349*($X$3/12) -> 667.31652 | AD349: =(AC349/Y349)*12 -> 0.08 | AE349: =AE348+AA349 -> 671661.71 | AF349: =AF348+AC349 -> 1252603.6 | AG349: =Y349-AA349 -> 95138.288 | AH349: =AE349+AF349 -> 1924265.3 | AJ349: =AJ348+1 -> 342 | AL349: =AT348 -> 97928.847 | AM349: =AM348 -> 5493.4491 | AN349: =AM349-AP349 -> 4860.992 | AO349: =(AN349/AL349)*12 -> 0.59565598 | AP349: =AL349*($AK$3/12) -> 632.45714 | AQ349: =(AP349/AL349)*12 -> 0.0775 | AR349: =AR348+AN349 -> 673732.14 | AS349: =AS348+AP349 -> 1205027.4 | AT349: =AL349-AN349 -> 93067.855 | AU349: =AR349+AS349 -> 1878759.6 | AW349: =AW348+1 -> 342 | AY349: =BG348 -> 95772.332 | AZ349: =AZ348 -> 5361.5769 | BA349: =AZ349-BC349 -> 4762.9998 | BB349: =(BA349/AY349)*12 -> 0.59679029 | BC349: =AY349*($AX$3/12) -> 598.57707 | BD349: =(BC349/AY349)*12 -> 0.075 | BE349: =BE348+BA349 -> 675790.67 | BF349: =BF348+BC349 -> 1157868.6 | BG349: =AY349-BA349 -> 91009.332 | BH349: =BE349+BF349 -> 1833659.3 | BJ349: =BJ348+1 -> 342 | BL349: =BT348 -> 93628.695 | BM349: =BM348 -> 5230.9277 | BN349: =BM349-BP349 -> 4665.2543 | BO349: =(BN349/BL349)*12 -> 0.59792622 | BP349: =BL349*($BK$3/12) -> 565.67337 | BQ349: =(BP349/BL349)*12 -> 0.0725 | BR349: =BR348+BN349 -> 677836.56 | BS349: =BS348+BP349 -> 1111140.7 | BT349: =BL349-BN349 -> 88963.441 | BU349: =BR349+BS349 -> 1788977.3 | BW349: =BW348+1 -> 342 | BY349: =CG348 -> 91498.712 | BZ349: =BZ348 -> 5101.5395 | CA349: =BZ349-CC349 -> 4567.797 | CB349: =(CA349/BY349)*12 -> 0.59906379 | CC349: =BY349*($BX$3/12) -> 533.74249 | CD349: =(CC349/BY349)*12 -> 0.07 | CE349: =CE348+CA349 -> 679869.09 | CF349: =CF348+CC349 -> 1064857.4 | CG349: =BY349-CA349 -> 86930.915 | CH349: =CE349+CF349 -> 1744726.5
J350: =J349+1 -> 343 | L350: =T349 -> 97219.914 | M350: =$L$8/((($N$4)-1)/($N$3*$N$4)) -> 5760.7123 | N350: =M350-P350 -> 5092.3254 | O350: =(N350/L350)*12 -> 0.62855337 | P350: =L350*($K$3/12) -> 668.38691 | Q350: =(P350/L350)*12 -> 0.0825 | R350: =R349+N350 -> 674672.41 | S350: =S349+P350 -> 1301251.9 | T350: =L350-N350 -> 92127.589 | U350: =R350+S350 -> 1975924.3 | W350: =W349+1 -> 343 | Y350: =AG349 -> 95138.288 | Z350: =Z349 -> 5626.5068 | AA350: =Z350-AC350 -> 4992.2515 | AB350: =(AA350/Y350)*12 -> 0.62968358 | AC350: =Y350*($X$3/12) -> 634.25525 | AD350: =(AC350/Y350)*12 -> 0.08 | AE350: =AE349+AA350 -> 676653.96 | AF350: =AF349+AC350 -> 1253237.9 | AG350: =Y350-AA350 -> 90146.036 | AH350: =AE350+AF350 -> 1929891.8 | AJ350: =AJ349+1 -> 343 | AL350: =AT349 -> 93067.855 | AM350: =AM349 -> 5493.4491 | AN350: =AM350-AP350 -> 4892.3859 | AO350: =(AN350/AL350)*12 -> 0.63081533 | AP350: =AL350*($AK$3/12) -> 601.06323 | AQ350: =(AP350/AL350)*12 -> 0.0775 | AR350: =AR349+AN350 -> 678624.53 | AS350: =AS349+AP350 -> 1205628.5 | AT350: =AL350-AN350 -> 88175.47 | AU350: =AR350+AS350 -> 1884253 | AW350: =AW349+1 -> 343 | AY350: =BG349 -> 91009.332 | AZ350: =AZ349 -> 5361.5769 | BA350: =AZ350-BC350 -> 4792.7685 | BB350: =(BA350/AY350)*12 -> 0.63194863 | BC350: =AY350*($AX$3/12) -> 568.80832 | BD350: =(BC350/AY350)*12 -> 0.075 | BE350: =BE349+BA350 -> 680583.44 | BF350: =BF349+BC350 -> 1158437.4 | BG350: =AY350-BA350 -> 86216.563 | BH350: =BE350+BF350 -> 1839020.9 | BJ350: =BJ349+1 -> 343 | BL350: =BT349 -> 88963.441 | BM350: =BM349 -> 5230.9277 | BN350: =BM350-BP350 -> 4693.4403 | BO350: =(BN350/BL350)*12 -> 0.63308346 | BP350: =BL350*($BK$3/12) -> 537.48746 | BQ350: =(BP350/BL350)*12 -> 0.0725 | BR350: =BR349+BN350 -> 682530 | BS350: =BS349+BP350 -> 1111678.2 | BT350: =BL350-BN350 -> 84270.001 | BU350: =BR350+BS350 -> 1794208.2 | BW350: =BW349+1 -> 343 | BY350: =CG349 -> 86930.915 | BZ350: =BZ349 -> 5101.5395 | CA350: =BZ350-CC350 -> 4594.4425 | CB350: =(CA350/BY350)*12 -> 0.63421984 | CC350: =BY350*($BX$3/12) -> 507.097 | CD350: =(CC350/BY350)*12 -> 0.07 | CE350: =CE349+CA350 -> 684463.53 | CF350: =CF349+CC350 -> 1065364.5 | CG350: =BY350-CA350 -> 82336.472 | CH350: =CE350+CF350 -> 1749828.1
J351: =J350+1 -> 344 | L351: =T350 -> 92127.589 | M351: =$L$8/((($N$4)-1)/($N$3*$N$4)) -> 5760.7123 | N351: =M351-P351 -> 5127.3351 | O351: =(N351/L351)*12 -> 0.66785664 | P351: =L351*($K$3/12) -> 633.37717 | Q351: =(P351/L351)*12 -> 0.0825 | R351: =R350+N351 -> 679799.75 | S351: =S350+P351 -> 1301885.3 | T351: =L351-N351 -> 87000.254 | U351: =R351+S351 -> 1981685 | W351: =W350+1 -> 344 | Y351: =AG350 -> 90146.036 | Z351: =Z350 -> 5626.5068 | AA351: =Z351-AC351 -> 5025.5332 | AB351: =(AA351/Y351)*12 -> 0.66898558 | AC351: =Y351*($X$3/12) -> 600.97358 | AD351: =(AC351/Y351)*12 -> 0.08 | AE351: =AE350+AA351 -> 681679.5 | AF351: =AF350+AC351 -> 1253838.8 | AG351: =Y351-AA351 -> 85120.503 | AH351: =AE351+AF351 -> 1935518.3 | AJ351: =AJ350+1 -> 344 | AL351: =AT350 -> 88175.47 | AM351: =AM350 -> 5493.4491 | AN351: =AM351-AP351 -> 4923.9825 | AO351: =(AN351/AL351)*12 -> 0.67011597 | AP351: =AL351*($AK$3/12) -> 569.46657 | AQ351: =(AP351/AL351)*12 -> 0.0775 | AR351: =AR350+AN351 -> 683548.51 | AS351: =AS350+AP351 -> 1206198 | AT351: =AL351-AN351 -> 83251.487 | AU351: =AR351+AS351 -> 1889746.5 | AW351: =AW350+1 -> 344 | AY351: =BG350 -> 86216.563 | AZ351: =AZ350 -> 5361.5769 | BA351: =AZ351-BC351 -> 4822.7233 | BB351: =(BA351/AY351)*12 -> 0.67124782 | BC351: =AY351*($AX$3/12) -> 538.85352 | BD351: =(BC351/AY351)*12 -> 0.075 | BE351: =BE350+BA351 -> 685406.16 | BF351: =BF350+BC351 -> 1158976.3 | BG351: =AY351-BA351 -> 81393.84 | BH351: =BE351+BF351 -> 1844382.4 | BJ351: =BJ350+1 -> 344 | BL351: =BT350 -> 84270.001 | BM351: =BM350 -> 5230.9277 | BN351: =BM351-BP351 -> 4721.7965 | BO351: =(BN351/BL351)*12 -> 0.67238112 | BP351: =BL351*($BK$3/12) -> 509.13126 | BQ351: =(BP351/BL351)*12 -> 0.0725 | BR351: =BR350+BN351 -> 687251.8 | BS351: =BS350+BP351 -> 1112187.3 | BT351: =BL351-BN351 -> 79548.204 | BU351: =BR351+BS351 -> 1799439.1 | BW351: =BW350+1 -> 344 | BY351: =CG350 -> 82336.472 | BZ351: =BZ350 -> 5101.5395 | CA351: =BZ351-CC351 -> 4621.2434 | CB351: =(CA351/BY351)*12 -> 0.67351588 | CC351: =BY351*($BX$3/12) -> 480.29609 | CD351: =(CC351/BY351)*12 -> 0.07 | CE351: =CE350+CA351 -> 689084.77 | CF351: =CF350+CC351 -> 1065844.8 | CG351: =BY351-CA351 -> 77715.229 | CH351: =CE351+CF351 -> 1754929.6
J352: =J351+1 -> 345 | L352: =T351 -> 87000.254 | M352: =$L$8/((($N$4)-1)/($N$3*$N$4)) -> 5760.7123 | N352: =M352-P352 -> 5162.5856 | O352: =(N352/L352)*12 -> 0.71207869 | P352: =L352*($K$3/12) -> 598.12674 | Q352: =(P352/L352)*12 -> 0.0825 | R352: =R351+N352 -> 684962.33 | S352: =S351+P352 -> 1302483.4 | T352: =L352-N352 -> 81837.668 | U352: =R352+S352 -> 1987445.8 | W352: =W351+1 -> 345 | Y352: =AG351 -> 85120.503 | Z352: =Z351 -> 5626.5068 | AA352: =Z352-AC352 -> 5059.0367 | AB352: =(AA352/Y352)*12 -> 0.71320585 | AC352: =Y352*($X$3/12) -> 567.47002 | AD352: =(AC352/Y352)*12 -> 0.08 | AE352: =AE351+AA352 -> 686738.53 | AF352: =AF351+AC352 -> 1254406.3 | AG352: =Y352-AA352 -> 80061.466 | AH352: =AE352+AF352 -> 1941144.8 | AJ352: =AJ351+1 -> 345 | AL352: =AT351 -> 83251.487 | AM352: =AM351 -> 5493.4491 | AN352: =AM352-AP352 -> 4955.7832 | AO352: =(AN352/AL352)*12 -> 0.71433437 | AP352: =AL352*($AK$3/12) -> 537.66585 | AQ352: =(AP352/AL352)*12 -> 0.0775 | AR352: =AR351+AN352 -> 688504.3 | AS352: =AS351+AP352 -> 1206735.6 | AT352: =AL352-AN352 -> 78295.704 | AU352: =AR352+AS352 -> 1895239.9 | AW352: =AW351+1 -> 345 | AY352: =BG351 -> 81393.84 | AZ352: =AZ351 -> 5361.5769 | BA352: =AZ352-BC352 -> 4852.8654 | BB352: =(BA352/AY352)*12 -> 0.71546427 | BC352: =AY352*($AX$3/12) -> 508.7115 | BD352: =(BC352/AY352)*12 -> 0.075 | BE352: =BE351+BA352 -> 690259.03 | BF352: =BF351+BC352 -> 1159485 | BG352: =AY352-BA352 -> 76540.975 | BH352: =BE352+BF352 -> 1849744 | BJ352: =BJ351+1 -> 345 | BL352: =BT351 -> 79548.204 | BM352: =BM351 -> 5230.9277 | BN352: =BM352-BP352 -> 4750.324 | BO352: =(BN352/BL352)*12 -> 0.71659553 | BP352: =BL352*($BK$3/12) -> 480.60373 | BQ352: =(BP352/BL352)*12 -> 0.0725 | BR352: =BR351+BN352 -> 692002.12 | BS352: =BS351+BP352 -> 1112667.9 | BT352: =BL352-BN352 -> 74797.88 | BU352: =BR352+BS352 -> 1804670.1 | BW352: =BW351+1 -> 345 | BY352: =CG351 -> 77715.229 | BZ352: =BZ351 -> 5101.5395 | CA352: =BZ352-CC352 -> 4648.2007 | CB352: =(CA352/BY352)*12 -> 0.71772816 | CC352: =BY352*($BX$3/12) -> 453.33883 | CD352: =(CC352/BY352)*12 -> 0.07 | CE352: =CE351+CA352 -> 693732.97 | CF352: =CF351+CC352 -> 1066298.2 | CG352: =BY352-CA352 -> 73067.028 | CH352: =CE352+CF352 -> 1760031.1
J353: =J352+1 -> 346 | L353: =T352 -> 81837.668 | M353: =$L$8/((($N$4)-1)/($N$3*$N$4)) -> 5760.7123 | N353: =M353-P353 -> 5198.0784 | O353: =(N353/L353)*12 -> 0.76220329 | P353: =L353*($K$3/12) -> 562.63397 | Q353: =(P353/L353)*12 -> 0.0825 | R353: =R352+N353 -> 690160.41 | S353: =S352+P353 -> 1303046.1 | T353: =L353-N353 -> 76639.59 | U353: =R353+S353 -> 1993206.5 | W353: =W352+1 -> 346 | Y353: =AG352 -> 80061.466 | Z353: =Z352 -> 5626.5068 | AA353: =Z353-AC353 -> 5092.7636 | AB353: =(AA353/Y353)*12 -> 0.76332806 | AC353: =Y353*($X$3/12) -> 533.74311 | AD353: =(AC353/Y353)*12 -> 0.08 | AE353: =AE352+AA353 -> 691831.3 | AF353: =AF352+AC353 -> 1254940 | AG353: =Y353-AA353 -> 74968.703 | AH353: =AE353+AF353 -> 1946771.3 | AJ353: =AJ352+1 -> 346 | AL353: =AT352 -> 78295.704 | AM353: =AM352 -> 5493.4491 | AN353: =AM353-AP353 -> 4987.7893 | AO353: =(AN353/AL353)*12 -> 0.7644541 | AP353: =AL353*($AK$3/12) -> 505.65975 | AQ353: =(AP353/AL353)*12 -> 0.0775 | AR353: =AR352+AN353 -> 693492.09 | AS353: =AS352+AP353 -> 1207241.3 | AT353: =AL353-AN353 -> 73307.915 | AU353: =AR353+AS353 -> 1900733.4 | AW353: =AW352+1 -> 346 | AY353: =BG352 -> 76540.975 | AZ353: =AZ352 -> 5361.5769 | BA353: =AZ353-BC353 -> 4883.1958 | BB353: =(BA353/AY353)*12 -> 0.76558143 | BC353: =AY353*($AX$3/12) -> 478.38109 | BD353: =(BC353/AY353)*12 -> 0.075 | BE353: =BE352+BA353 -> 695142.22 | BF353: =BF352+BC353 -> 1159963.4 | BG353: =AY353-BA353 -> 71657.779 | BH353: =BE353+BF353 -> 1855105.6 | BJ353: =BJ352+1 -> 346 | BL353: =BT352 -> 74797.88 | BM353: =BM352 -> 5230.9277 | BN353: =BM353-BP353 -> 4779.0239 | BO353: =(BN353/BL353)*12 -> 0.76671004 | BP353: =BL353*($BK$3/12) -> 451.90386 | BQ353: =(BP353/BL353)*12 -> 0.0725 | BR353: =BR352+BN353 -> 696781.14 | BS353: =BS352+BP353 -> 1113119.8 | BT353: =BL353-BN353 -> 70018.857 | BU353: =BR353+BS353 -> 1809901 | BW353: =BW352+1 -> 346 | BY353: =CG352 -> 73067.028 | BZ353: =BZ352 -> 5101.5395 | CA353: =BZ353-CC353 -> 4675.3152 | CB353: =(CA353/BY353)*12 -> 0.76783994 | CC353: =BY353*($BX$3/12) -> 426.22433 | CD353: =(CC353/BY353)*12 -> 0.07 | CE353: =CE352+CA353 -> 698408.29 | CF353: =CF352+CC353 -> 1066724.4 | CG353: =BY353-CA353 -> 68391.713 | CH353: =CE353+CF353 -> 1765132.7
J354: =J353+1 -> 347 | L354: =T353 -> 76639.59 | M354: =$L$8/((($N$4)-1)/($N$3*$N$4)) -> 5760.7123 | N354: =M354-P354 -> 5233.8151 | O354: =(N354/L354)*12 -> 0.81949527 | P354: =L354*($K$3/12) -> 526.89718 | Q354: =(P354/L354)*12 -> 0.0825 | R354: =R353+N354 -> 695394.23 | S354: =S353+P354 -> 1303572.9 | T354: =L354-N354 -> 71405.775 | U354: =R354+S354 -> 1998967.2 | W354: =W353+1 -> 347 | Y354: =AG353 -> 74968.703 | Z354: =Z353 -> 5626.5068 | AA354: =Z354-AC354 -> 5126.7154 | AB354: =(AA354/Y354)*12 -> 0.8206169 | AC354: =Y354*($X$3/12) -> 499.79135 | AD354: =(AC354/Y354)*12 -> 0.08 | AE354: =AE353+AA354 -> 696958.01 | AF354: =AF353+AC354 -> 1255439.8 | AG354: =Y354-AA354 -> 69841.987 | AH354: =AE354+AF354 -> 1952397.8 | AJ354: =AJ353+1 -> 347 | AL354: =AT353 -> 73307.915 | AM354: =AM353 -> 5493.4491 | AN354: =AM354-AP354 -> 5020.0022 | AO354: =(AN354/AL354)*12 -> 0.82173973 | AP354: =AL354*($AK$3/12) -> 473.44695 | AQ354: =(AP354/AL354)*12 -> 0.0775 | AR354: =AR353+AN354 -> 698512.09 | AS354: =AS353+AP354 -> 1207714.7 | AT354: =AL354-AN354 -> 68287.912 | AU354: =AR354+AS354 -> 1906226.8 | AW354: =AW353+1 -> 347 | AY354: =BG353 -> 71657.779 | AZ354: =AZ353 -> 5361.5769 | BA354: =AZ354-BC354 -> 4913.7157 | BB354: =(BA354/AY354)*12 -> 0.82286375 | BC354: =AY354*($AX$3/12) -> 447.86112 | BD354: =(BC354/AY354)*12 -> 0.075 | BE354: =BE353+BA354 -> 700055.94 | BF354: =BF353+BC354 -> 1160411.2 | BG354: =AY354-BA354 -> 66744.063 | BH354: =BE354+BF354 -> 1860467.2 | BJ354: =BJ353+1 -> 347 | BL354: =BT353 -> 70018.857 | BM354: =BM353 -> 5230.9277 | BN354: =BM354-BP354 -> 4807.8971 | BO354: =(BN354/BL354)*12 -> 0.82398897 | BP354: =BL354*($BK$3/12) -> 423.03059 | BQ354: =(BP354/BL354)*12 -> 0.0725 | BR354: =BR353+BN354 -> 701589.04 | BS354: =BS353+BP354 -> 1113542.9 | BT354: =BL354-BN354 -> 65210.959 | BU354: =BR354+BS354 -> 1815131.9 | BW354: =BW353+1 -> 347 | BY354: =CG353 -> 68391.713 | BZ354: =BZ353 -> 5101.5395 | CA354: =BZ354-CC354 -> 4702.5879 | CB354: =(CA354/BY354)*12 -> 0.82511539 | CC354: =BY354*($BX$3/12) -> 398.95166 | CD354: =(CC354/BY354)*12 -> 0.07 | CE354: =CE353+CA354 -> 703110.88 | CF354: =CF353+CC354 -> 1067123.3 | CG354: =BY354-CA354 -> 63689.125 | CH354: =CE354+CF354 -> 1770234.2
... J367: =J366+1 -> 360 | L367: =T366 -> 5721.3778 | M367: =$L$8/((($N$4)-1)/($N$3*$N$4)) -> 5760.7123 | N367: =M367-P367 -> 5721.3778 | O367: =(N367/L367)*12 -> 12 | P367: =L367*($K$3/12) -> 39.334473 | Q367: =(P367/L367)*12 -> 0.0825 | R367: =R366+N367 -> 766800 | S367: =S366+P367 -> 1307056.4 | T367: =L367-N367 -> -2.325578e-08 | U367: =R367+S367 -> 2073856.4 | W367: =W366+1 -> 360 | Y367: =AG366 -> 5589.2451 | Z367: =Z366 -> 5626.5068 | AA367: =Z367-AC367 -> 5589.2451 | AB367: =(AA367/Y367)*12 -> 12 | AC367: =Y367*($X$3/12) -> 37.261634 | AD367: =(AC367/Y367)*12 -> 0.08 | AE367: =AE366+AA367 -> 766800 | AF367: =AF366+AC367 -> 1258742.4 | AG367: =Y367-AA367 -> -1.4485522e-08 | AH367: =AE367+AF367 -> 2025542.4 | AJ367: =AJ366+1 -> 360 | AL367: =AT366 -> 5458.1982 | AM367: =AM366 -> 5493.4491 | AN367: =AM367-AP367 -> 5458.1982 | AO367: =(AN367/AL367)*12 -> 12 | AP367: =AL367*($AK$3/12) -> 35.250864 | AQ367: =(AP367/AL367)*12 -> 0.0775 | AR367: =AR366+AN367 -> 766800 | AS367: =AS366+AP367 -> 1210841.7 | AT367: =AL367-AN367 -> -1.8096216e-08 | AU367: =AR367+AS367 -> 1977641.7 | AW367: =AW366+1 -> 360 | AY367: =BG366 -> 5328.2751 | AZ367: =AZ366 -> 5361.5769 | BA367: =AZ367-BC367 -> 5328.2751 | BB367: =(BA367/AY367)*12 -> 12 | BC367: =AY367*($AX$3/12) -> 33.30172 | BD367: =(BC367/AY367)*12 -> 0.075 | BE367: =BE366+BA367 -> 766800 | BF367: =BF366+BC367 -> 1163367.7 | BG367: =AY367-BA367 -> 1.6524609e-08 | BH367: =BE367+BF367 -> 1930167.7 | BJ367: =BJ366+1 -> 360 | BL367: =BT366 -> 5199.514 | BM367: =BM366 -> 5230.9277 | BN367: =BM367-BP367 -> 5199.514 | BO367: =(BN367/BL367)*12 -> 12 | BP367: =BL367*($BK$3/12) -> 31.41373 | BQ367: =(BP367/BL367)*12 -> 0.0725 | BR367: =BR366+BN367 -> 766800 | BS367: =BS366+BP367 -> 1116334 | BT367: =BL367-BN367 -> 2.3874236e-09 | BU367: =BR367+BS367 -> 1883134 | BW367: =BW366+1 -> 360 | BY367: =CG366 -> 5071.9531 | BZ367: =BZ366 -> 5101.5395 | CA367: =BZ367-CC367 -> 5071.9531 | CB367: =(CA367/BY367)*12 -> 12 | CC367: =BY367*($BX$3/12) -> 29.586393 | CD367: =(CC367/BY367)*12 -> 0.07 | CE367: =CE366+CA367 -> 766800 | CF367: =CF366+CC367 -> 1069754.2 | CG367: =BY367-CA367 -> 8.2554834e-09 | CH367: =CE367+CF367 -> 1836554.2

Sheet Amoritization Scenario 15
A1: 2950 Admiralty Bay Drive | B1: 2646 | C1: sqft | J1: Interest | K1: ='Interest Rate Comparison'!B3 -> 0.0825 | N1: =K1/12 -> 0.006875 | O1: r | W1: Interest | X1: ='Interest Rate Comparison'!B4 -> 0.08 | AA1: =X1/12 -> 0.0066666667 | AB1: r | AJ1: Interest | AK1: ='Interest Rate Comparison'!B5 -> 0.0775 | AN1: =AK1/12 -> 0.0064583333 | AO1: r | AW1: Interest | AX1: ='Interest Rate Comparison'!B6 -> 0.075 | BA1: =AX1/12 -> 0.00625 | BB1: r | BJ1: Interest | BK1: ='Interest Rate Comparison'!B7 -> 0.0725 | BN1: =BK1/12 -> 0.0060416667 | BO1: r | BW1: Interest | BX1: ='Interest Rate Comparison'!B8 -> 0.07 | CA1: =BX1/12 -> 0.0058333333 | CB1: r
B2: 246 | C2: $/sqft Market Estimate | J2: Term | K2: =$L$2*12 -> 360 | L2: ='STR Calculator'!I9 -> 30 | M2: years | N2: =(1+N1)^K2 -> 11.781506 | O2: (1+r)^n | W2: Term | X2: =$L$2*12 -> 360 | Y2: 30 | Z2: years | AA2: =(1+AA1)^X2 -> 10.93573 | AB2: (1+r)^n | AJ2: Term | AK2: =$L$2*12 -> 360 | AL2: 30 | AM2: years | AN2: =(1+AN1)^AK2 -> 10.150514 | AO2: (1+r)^n | AW2: Term | AX2: =$L$2*12 -> 360 | AY2: 30 | AZ2: years | BA2: =(1+BA1)^AX2 -> 9.4215339 | BB2: (1+r)^n | BJ2: Term | BK2: =$L$2*12 -> 360 | BL2: 30 | BM2: years | BN2: =(1+BN1)^BK2 -> 8.744772 | BO2: (1+r)^n | BW2: Term | BX2: =$L$2*12 -> 360 | BY2: 30 | BZ2: years | CA2: =(1+CA1)^BX2 -> 8.1164975 | CB2: (1+r)^n
A3: Original Purchase Price | B3: ='STR Calculator'!B5 -> 852000 | C3: =B3/B1 -> 321.99546 | D3: sqft | J3: Monthly Payment | W3: Monthly Payment | AJ3: Monthly Payment | AW3: Monthly Payment | BJ3: Monthly Payment | BW3: Monthly Payment
A4: Down Payment | B4: 0.15
A5: Current Loan Balance | B5: =B3-(B3*B4) -> 724200 | C5: as of 11/13/22 | J5: paymentNumber | K5: paymentDate | L5: startingBalance | M5: Monthly Payment | N5: principalPayment | O5: Principle Pay Down | P5: interestPayment | Q5: Interest Percent | R5: cumulativePrincipal | S5: cumulativeInterest | T5: endingBalance | U5: Total Paid End of Loan | W5: paymentNumber | X5: paymentDate | Y5: startingBalance | Z5: Monthly Payment | AA5: principalPayment | AB5: Principle Pay Down | AC5: interestPayment | AD5: Interest Percent | AE5: cumulativePrincipal | AF5: cumulativeInterest | AG5: endingBalance | AH5: Total Paid End of Loan | AJ5: paymentNumber | AK5: paymentDate | AL5: startingBalance | AM5: Monthly Payment | AN5: principalPayment | AO5: Principle Pay Down | AP5: interestPayment | AQ5: Interest Percent | AR5: cumulativePrincipal | AS5: cumulativeInterest | AT5: endingBalance | AU5: Total Paid End of Loan | AW5: paymentNumber | AX5: paymentDate | AY5: startingBalance | AZ5: Monthly Payment | BA5: principalPayment | BB5: Principle Pay Down | BC5: interestPayment | BD5: Interest Percent | BE5: cumulativePrincipal | BF5: cumulativeInterest | BG5: endingBalance | BH5: Total Paid End of Loan | BJ5: paymentNumber | BK5: paymentDate | BL5: startingBalance | BM5: Monthly Payment | BN5: principalPayment | BO5: Principle Pay Down | BP5: interestPayment | BQ5: Interest Percent | BR5: cumulativePrincipal | BS5: cumulativeInterest | BT5: endingBalance | BU5: Total Paid End of Loan | BW5: paymentNumber | BX5: paymentDate | BY5: startingBalance | BZ5: Monthly Payment | CA5: principalPayment | CB5: Principle Pay Down | CC5: interestPayment | CD5: Interest Percent | CE5: cumulativePrincipal | CF5: cumulativeInterest | CG5: endingBalance | CH5: Total Paid End of Loan
A6: Current Equity | B6: =B3-B5 -> 127800 | J6: 1 | K6: 44866 | L6: ='Amoritization Scenario 15'!$B$5 -> 724200 | M6: =$L$6/((($N$2)-1)/($N$1*$N$2)) -> 5440.6727 | N6: =M6-P6 -> 461.79775 | O6: =(N6/L6)*12 -> 0.0076519925 | P6: =L6*($K$1/12) -> 4978.875 | Q6: =(P6/L6)*12 -> 0.0825 | R6: =N6 -> 461.79775 | S6: =P6 -> 4978.875 | T6: =L6-N6 -> 723738.2 | U6: =R6+S6 -> 5440.6727 | W6: 1 | X6: 44866 | Y6: ='Amoritization Scenario 15'!$B$5 -> 724200 | Z6: =$Y$6/((($AA$2)-1)/($AA$1*$AA$2)) -> 5313.923 | AA6: =Z6-AC6 -> 485.92304 | AB6: =(AA6/Y6)*12 -> 0.0080517489 | AC6: =Y6*($X$1/12) -> 4828 | AD6: =(AC6/Y6)*12 -> 0.08 | AE6: =AA6 -> 485.92304 | AF6: =AC6 -> 4828 | AG6: =Y6-AA6 -> 723714.08 | AH6: =AE6+AF6 -> 5313.923 | AJ6: 1 | AK6: 44866 | AL6: ='Amoritization Scenario 15'!$B$5 -> 724200 | AM6: =$AL$6/((($AN$2)-1)/($AN$1*$AN$2)) -> 5188.2575 | AN6: =AM6-AP6 -> 511.13248 | AO6: =(AN6/AL6)*12 -> 0.0084694695 | AP6: =AL6*($AK$1/12) -> 4677.125 | AQ6: =(AP6/AL6)*12 -> 0.0775 | AR6: =AN6 -> 511.13248 | AS6: =AP6 -> 4677.125 | AT6: =AL6-AN6 -> 723688.87 | AU6: =AR6+AS6 -> 5188.2575 | AW6: 1 | AX6: 44866 | AY6: ='Amoritization Scenario 15'!$B$5 -> 724200 | AZ6: =$AY$6/((($BA$2)-1)/($BA$1*$BA$2)) -> 5063.7115 | BA6: =AZ6-BC6 -> 537.46147 | BB6: =(BA6/AY6)*12 -> 0.008905741 | BC6: =AY6*($AX$1/12) -> 4526.25 | BD6: =(BC6/AY6)*12 -> 0.075 | BE6: =BA6 -> 537.46147 | BF6: =BC6 -> 4526.25 | BG6: =AY6-BA6 -> 723662.54 | BH6: =BE6+BF6 -> 5063.7115 | BJ6: 1 | BK6: 44866 | BL6: ='Amoritization Scenario 15'!$B$5 -> 724200 | BM6: =$BL$6/((($BN$2)-1)/($BN$1*$BN$2)) -> 4940.3206 | BN6: =BM6-BP6 -> 564.94562 | BO6: =(BN6/BL6)*12 -> 0.0093611536 | BP6: =BL6*($BK$1/12) -> 4375.375 | BQ6: =(BP6/BL6)*12 -> 0.0725 | BR6: =BN6 -> 564.94562 | BS6: =BP6 -> 4375.375 | BT6: =BL6-BN6 -> 723635.05 | BU6: =BR6+BS6 -> 4940.3206 | BW6: 1 | BX6: 44866 | BY6: ='Amoritization Scenario 15'!$B$5 -> 724200 | BZ6: =$BY$6/((($CA$2)-1)/($CA$1*$CA$2)) -> 4818.1207 | CA6: =BZ6-CC6 -> 593.62067 | CB6: =(CA6/BY6)*12 -> 0.0098362994 | CC6: =BY6*($BX$1/12) -> 4224.5 | CD6: =(CC6/BY6)*12 -> 0.07 | CE6: =CA6 -> 593.62067 | CF6: =CC6 -> 4224.5 | CG6: =BY6-CA6 -> 723606.38 | CH6: =CE6+CF6 -> 4818.1207
J7: 2 | K7: 44896 | L7: =T6 -> 723738.2 | M7: =$L$6/((($N$2)-1)/($N$1*$N$2)) -> 5440.6727 | N7: =M7-P7 -> 464.97261 | O7: =(N7/L7)*12 -> 0.007709516 | P7: =L7*($K$1/12) -> 4975.7001 | Q7: =(P7/L7)*12 -> 0.0825 | R7: =R6+N7 -> 926.77035 | S7: =S6+P7 -> 9954.5751 | T7: =L7-N7 -> 723273.23 | U7: =R7+S7 -> 10881.345 | W7: 2 | X7: 44896 | Y7: =AG6 -> 723714.08 | Z7: =Z6 -> 5313.923 | AA7: =Z7-AC7 -> 489.16253 | AB7: =(AA7/Y7)*12 -> 0.0081108694 | AC7: =Y7*($X$1/12) -> 4824.7605 | AD7: =(AC7/Y7)*12 -> 0.08 | AE7: =AE6+AA7 -> 975.08558 | AF7: =AF6+AC7 -> 9652.7605 | AG7: =Y7-AA7 -> 723224.91 | AH7: =AE7+AF7 -> 10627.846 | AJ7: 2 | AK7: 44896 | AL7: =AT6 -> 723688.87 | AM7: =AM6 -> 5188.2575 | AN7: =AM7-AP7 -> 514.43355 | AO7: =(AN7/AL7)*12 -> 0.0085301886 | AP7: =AL7*($AK$1/12) -> 4673.8239 | AQ7: =(AP7/AL7)*12 -> 0.0775 | AR7: =AR6+AN7 -> 1025.566 | AS7: =AS6+AP7 -> 9350.9489 | AT7: =AL7-AN7 -> 723174.43 | AU7: =AR7+AS7 -> 10376.515 | AW7: 2 | AX7: 44896 | AY7: =BG6 -> 723662.54 | AZ7: =AZ6 -> 5063.7115 | BA7: =AZ7-BC7 -> 540.82061 | BB7: =(BA7/AY7)*12 -> 0.0089680575 | BC7: =AY7*($AX$1/12) -> 4522.8909 | BD7: =(BC7/AY7)*12 -> 0.075 | BE7: =BE6+BA7 -> 1078.2821 | BF7: =BF6+BC7 -> 9049.1409 | BG7: =AY7-BA7 -> 723121.72 | BH7: =BE7+BF7 -> 10127.423 | BJ7: 2 | BK7: 44896 | BL7: =BT6 -> 723635.05 | BM7: =BM6 -> 4940.3206 | BN7: =BM7-BP7 -> 568.35883 | BO7: =(BN7/BL7)*12 -> 0.009425063 | BP7: =BL7*($BK$1/12) -> 4371.9618 | BQ7: =(BP7/BL7)*12 -> 0.0725 | BR7: =BR6+BN7 -> 1133.3045 | BS7: =BS6+BP7 -> 8747.3368 | BT7: =BL7-BN7 -> 723066.7 | BU7: =BR7+BS7 -> 9880.6412 | BW7: 2 | BX7: 44896 | BY7: =CG6 -> 723606.38 | BZ7: =BZ6 -> 4818.1207 | CA7: =BZ7-CC7 -> 597.08346 | CB7: =(CA7/BY7)*12 -> 0.0099017943 | CC7: =BY7*($BX$1/12) -> 4221.0372 | CD7: =(CC7/BY7)*12 -> 0.07 | CE7: =CE6+CA7 -> 1190.7041 | CF7: =CF6+CC7 -> 8445.5372 | CG7: =BY7-CA7 -> 723009.3 | CH7: =CE7+CF7 -> 9636.2413
A8: Year | B8: ="Cum Interest @ "&K1&"%" -> Cum Interest @ 0.0825% | C8: ="Cum Interest @ "&X1&"%" -> Cum Interest @ 0.08% | D8: ="Cum Interest @ "&AK1&"%" -> Cum Interest @ 0.0775% | E8: ="Cum Interest @ "&AX1&"%" -> Cum Interest @ 0.075% | F8: ="Cum Interest @ "&BK1&"%" -> Cum Interest @ 0.0725% | G8: ="Cum Interest @ "&BX1&"%" -> Cum Interest @ 0.07% | J8: 3 | K8: 44927 | L8: =T7 -> 723273.23 | M8: =$L$6/((($N$2)-1)/($N$1*$N$2)) -> 5440.6727 | N8: =M8-P8 -> 468.16929 | O8: =(N8/L8)*12 -> 0.0077675093 | P8: =L8*($K$1/12) -> 4972.5035 | Q8: =(P8/L8)*12 -> 0.0825 | R8: =R7+N8 -> 1394.9396 | S8: =S7+P8 -> 14927.079 | T8: =L8-N8 -> 722805.06 | U8: =R8+S8 -> 16322.018 | W8: 3 | X8: 44927 | Y8: =AG7 -> 723224.91 | Z8: =Z7 -> 5313.923 | AA8: =Z8-AC8 -> 492.42361 | AB8: =(AA8/Y8)*12 -> 0.0081704643 | AC8: =Y8*($X$1/12) -> 4821.4994 | AD8: =(AC8/Y8)*12 -> 0.08 | AE8: =AE7+AA8 -> 1467.5092 | AF8: =AF7+AC8 -> 14474.26 | AG8: =Y8-AA8 -> 722732.49 | AH8: =AE8+AF8 -> 15941.769 | AJ8: 3 | AK8: 44927 | AL8: =AT7 -> 723174.43 | AM8: =AM7 -> 5188.2575 | AN8: =AM8-AP8 -> 517.75593 | AO8: =(AN8/AL8)*12 -> 0.0085913866 | AP8: =AL8*($AK$1/12) -> 4670.5016 | AQ8: =(AP8/AL8)*12 -> 0.0775 | AR8: =AR7+AN8 -> 1543.322 | AS8: =AS7+AP8 -> 14021.45 | AT8: =AL8-AN8 -> 722656.68 | AU8: =AR8+AS8 -> 15564.772 | AW8: 3 | AX8: 44927 | AY8: =BG7 -> 723121.72 | AZ8: =AZ7 -> 5063.7115 | BA8: =AZ8-BC8 -> 544.20073 | BB8: =(BA8/AY8)*12 -> 0.009030857 | BC8: =AY8*($AX$1/12) -> 4519.5107 | BD8: =(BC8/AY8)*12 -> 0.075 | BE8: =BE7+BA8 -> 1622.4828 | BF8: =BF7+BC8 -> 13568.652 | BG8: =AY8-BA8 -> 722577.52 | BH8: =BE8+BF8 -> 15191.134 | BJ8: 3 | BK8: 44927 | BL8: =BT7 -> 723066.7 | BM8: =BM7 -> 4940.3206 | BN8: =BM8-BP8 -> 571.79267 | BO8: =(BN8/BL8)*12 -> 0.0094894594 | BP8: =BL8*($BK$1/12) -> 4368.528 | BQ8: =(BP8/BL8)*12 -> 0.0725 | BR8: =BR7+BN8 -> 1705.0971 | BS8: =BS7+BP8 -> 13115.865 | BT8: =BL8-BN8 -> 722494.9 | BU8: =BR8+BS8 -> 14820.962 | BW8: 3 | BX8: 44927 | BY8: =CG7 -> 723009.3 | BZ8: =BZ7 -> 4818.1207 | CA8: =BZ8-CC8 -> 600.56644 | CB8: =(CA8/BY8)*12 -> 0.0099677796 | CC8: =BY8*($BX$1/12) -> 4217.5542 | CD8: =(CC8/BY8)*12 -> 0.07 | CE8: =CE7+CA8 -> 1791.2706 | CF8: =CF7+CC8 -> 12663.091 | CG8: =BY8-CA8 -> 722408.73 | CH8: =CE8+CF8 -> 14454.362
A9: 1 | B9: =VLOOKUP($A$9*12,$J$5:$U$365,10) -> 59532.082 | C9: =VLOOKUP(A9*12,$W$5:$AH$365,10) -> 57717.371 | D9: =VLOOKUP(A9*12,$AJ$5:$AU$365,10) -> 55902.871 | E9: =VLOOKUP(A9*12,$AW$5:$BH$365,10) -> 54088.613 | F9: =VLOOKUP(A9*12,$BJ$5:$BU$365,10) -> 52274.629 | G9: =VLOOKUP(A9*12,$BW$5:$CH$365,10) -> 50460.953 | J9: 4 | K9: 44958 | L9: =T8 -> 722805.06 | M9: =$L$6/((($N$2)-1)/($N$1*$N$2)) -> 5440.6727 | N9: =M9-P9 -> 471.38796 | O9: =(N9/L9)*12 -> 0.0078259766 | P9: =L9*($K$1/12) -> 4969.2848 | Q9: =(P9/L9)*12 -> 0.0825 | R9: =R8+N9 -> 1866.3276 | S9: =S8+P9 -> 19896.363 | T9: =L9-N9 -> 722333.67 | U9: =R9+S9 -> 21762.691 | W9: 4 | X9: 44958 | Y9: =AG8 -> 722732.49 | Z9: =Z8 -> 5313.923 | AA9: =Z9-AC9 -> 495.70644 | AB9: =(AA9/Y9)*12 -> 0.008230538 | AC9: =Y9*($X$1/12) -> 4818.2166 | AD9: =(AC9/Y9)*12 -> 0.08 | AE9: =AE8+AA9 -> 1963.2156 | AF9: =AF8+AC9 -> 19292.477 | AG9: =Y9-AA9 -> 722236.78 | AH9: =AE9+AF9 -> 21255.692 | AJ9: 4 | AK9: 44958 | AL9: =AT8 -> 722656.68 | AM9: =AM8 -> 5188.2575 | AN9: =AM9-AP9 -> 521.09977 | AO9: =(AN9/AL9)*12 -> 0.0086530678 | AP9: =AL9*($AK$1/12) -> 4667.1577 | AQ9: =(AP9/AL9)*12 -> 0.0775 | AR9: =AR8+AN9 -> 2064.4217 | AS9: =AS8+AP9 -> 18688.608 | AT9: =AL9-AN9 -> 722135.58 | AU9: =AR9+AS9 -> 20753.03 | AW9: 4 | AX9: 44958 | AY9: =BG8 -> 722577.52 | AZ9: =AZ8 -> 5063.7115 | BA9: =AZ9-BC9 -> 547.60199 | BB9: =(BA9/AY9)*12 -> 0.0090941438 | BC9: =AY9*($AX$1/12) -> 4516.1095 | BD9: =(BC9/AY9)*12 -> 0.075 | BE9: =BE8+BA9 -> 2170.0848 | BF9: =BF8+BC9 -> 18084.761 | BG9: =AY9-BA9 -> 722029.92 | BH9: =BE9+BF9 -> 20254.846 | BJ9: 4 | BK9: 44958 | BL9: =BT8 -> 722494.9 | BM9: =BM8 -> 4940.3206 | BN9: =BM9-BP9 -> 575.24725 | BO9: =(BN9/BL9)*12 -> 0.009554347 | BP9: =BL9*($BK$1/12) -> 4365.0734 | BQ9: =(BP9/BL9)*12 -> 0.0725 | BR9: =BR8+BN9 -> 2280.3444 | BS9: =BS8+BP9 -> 17480.938 | BT9: =BL9-BN9 -> 721919.66 | BU9: =BR9+BS9 -> 19761.282 | BW9: 4 | BX9: 44958 | BY9: =CG8 -> 722408.73 | BZ9: =BZ8 -> 4818.1207 | CA9: =BZ9-CC9 -> 604.06975 | CB9: =(CA9/BY9)*12 -> 0.01003426 | CC9: =BY9*($BX$1/12) -> 4214.0509 | CD9: =(CC9/BY9)*12 -> 0.07 | CE9: =CE8+CA9 -> 2395.3403 | CF9: =CF8+CC9 -> 16877.142 | CG9: =BY9-CA9 -> 721804.66 | CH9: =CE9+CF9 -> 19272.483
A10: =A9+1 -> 2 | B10: =VLOOKUP(A10*12,$J$5:$U$365,10) -> 118570.92 | C10: =VLOOKUP(A10*12,$W$5:$AH$365,10) -> 114932.62 | D10: =VLOOKUP(A10*12,$AJ$5:$AU$365,10) -> 111295.25 | E10: =VLOOKUP(A10*12,$AW$5:$BH$365,10) -> 107658.96 | F10: =VLOOKUP(A10*12,$BJ$5:$BU$365,10) -> 104023.86 | G10: =VLOOKUP(A10*12,$BW$5:$CH$365,10) -> 100390.1 | J10: 5 | K10: 44986 | L10: =T9 -> 722333.67 | M10: =$L$6/((($N$2)-1)/($N$1*$N$2)) -> 5440.6727 | N10: =M10-P10 -> 474.62875 | O10: =(N10/L10)*12 -> 0.0078849224 | P10: =L10*($K$1/12) -> 4966.044 | Q10: =(P10/L10)*12 -> 0.0825 | R10: =R9+N10 -> 2340.9564 | S10: =S9+P10 -> 24862.407 | T10: =L10-N10 -> 721859.04 | U10: =R10+S10 -> 27203.364 | W10: 5 | X10: 44986 | Y10: =AG9 -> 722236.78 | Z10: =Z9 -> 5313.923 | AA10: =Z10-AC10 -> 499.01115 | AB10: =(AA10/Y10)*12 -> 0.008291095 | AC10: =Y10*($X$1/12) -> 4814.9119 | AD10: =(AC10/Y10)*12 -> 0.08 | AE10: =AE9+AA10 -> 2462.2268 | AF10: =AF9+AC10 -> 24107.388 | AG10: =Y10-AA10 -> 721737.77 | AH10: =AE10+AF10 -> 26569.615 | AJ10: 5 | AK10: 44986 | AL10: =AT9 -> 722135.58 | AM10: =AM9 -> 5188.2575 | AN10: =AM10-AP10 -> 524.46521 | AO10: =(AN10/AL10)*12 -> 0.0087152367 | AP10: =AL10*($AK$1/12) -> 4663.7923 | AQ10: =(AP10/AL10)*12 -> 0.0775 | AR10: =AR9+AN10 -> 2588.8869 | AS10: =AS9+AP10 -> 23352.4 | AT10: =AL10-AN10 -> 721611.11 | AU10: =AR10+AS10 -> 25941.287 | AW10: 5 | AX10: 44986 | AY10: =BG9 -> 722029.92 | AZ10: =AZ9 -> 5063.7115 | BA10: =AZ10-BC10 -> 551.0245 | BB10: =(BA10/AY10)*12 -> 0.0091579225 | BC10: =AY10*($AX$1/12) -> 4512.687 | BD10: =(BC10/AY10)*12 -> 0.075 | BE10: =BE9+BA10 -> 2721.1093 | BF10: =BF9+BC10 -> 22597.448 | BG10: =AY10-BA10 -> 721478.89 | BH10: =BE10+BF10 -> 25318.557 | BJ10: 5 | BK10: 44986 | BL10: =BT9 -> 721919.66 | BM10: =BM9 -> 4940.3206 | BN10: =BM10-BP10 -> 578.7227 | BO10: =(BN10/BL10)*12 -> 0.0096197303 | BP10: =BL10*($BK$1/12) -> 4361.5979 | BQ10: =(BP10/BL10)*12 -> 0.0725 | BR10: =BR9+BN10 -> 2859.0671 | BS10: =BS9+BP10 -> 21842.536 | BT10: =BL10-BN10 -> 721340.93 | BU10: =BR10+BS10 -> 24701.603 | BW10: 5 | BX10: 44986 | BY10: =CG9 -> 721804.66 | BZ10: =BZ9 -> 4818.1207 | CA10: =BZ10-CC10 -> 607.59349 | CB10: =(CA10/BY10)*12 -> 0.01010124 | CC10: =BY10*($BX$1/12) -> 4210.5272 | CD10: =(CC10/BY10)*12 -> 0.07 | CE10: =CE9+CA10 -> 3002.9338 | CF10: =CF9+CC10 -> 21087.67 | CG10: =BY10-CA10 -> 721197.07 | CH10: =CE10+CF10 -> 24090.603
A11: =A10+1 -> 3 | B11: =VLOOKUP(A11*12,$J$5:$U$365,10) -> 177074.25 | C11: =VLOOKUP(A11*12,$W$5:$AH$365,10) -> 171604.07 | D11: =VLOOKUP(A11*12,$AJ$5:$AU$365,10) -> 166136.15 | E11: =VLOOKUP(A11*12,$AW$5:$BH$365,10) -> 160670.8 | F11: =VLOOKUP(A11*12,$BJ$5:$BU$365,10) -> 155208.31 | G11: =VLOOKUP(A11*12,$BW$5:$CH$365,10) -> 149749.01 | J11: 6 | K11: 45017 | L11: =T10 -> 721859.04 | M11: =$L$6/((($N$2)-1)/($N$1*$N$2)) -> 5440.6727 | N11: =M11-P11 -> 477.89182 | O11: =(N11/L11)*12 -> 0.0079443513 | P11: =L11*($K$1/12) -> 4962.7809 | Q11: =(P11/L11)*12 -> 0.0825 | R11: =R10+N11 -> 2818.8482 | S11: =S10+P11 -> 29825.188 | T11: =L11-N11 -> 721381.15 | U11: =R11+S11 -> 32644.036 | W11: 6 | X11: 45017 | Y11: =AG10 -> 721737.77 | Z11: =Z10 -> 5313.923 | AA11: =Z11-AC11 -> 502.33789 | AB11: =(AA11/Y11)*12 -> 0.0083521396 | AC11: =Y11*($X$1/12) -> 4811.5852 | AD11: =(AC11/Y11)*12 -> 0.08 | AE11: =AE10+AA11 -> 2964.5647 | AF11: =AF10+AC11 -> 28918.974 | AG11: =Y11-AA11 -> 721235.44 | AH11: =AE11+AF11 -> 31883.538 | AJ11: 6 | AK11: 45017 | AL11: =AT10 -> 721611.11 | AM11: =AM10 -> 5188.2575 | AN11: =AM11-AP11 -> 527.85238 | AO11: =(AN11/AL11)*12 -> 0.0087778977 | AP11: =AL11*($AK$1/12) -> 4660.4051 | AQ11: =(AP11/AL11)*12 -> 0.0775 | AR11: =AR10+AN11 -> 3116.7393 | AS11: =AS10+AP11 -> 28012.806 | AT11: =AL11-AN11 -> 721083.26 | AU11: =AR11+AS11 -> 31129.545 | AW11: 6 | AX11: 45017 | AY11: =BG10 -> 721478.89 | AZ11: =AZ10 -> 5063.7115 | BA11: =AZ11-BC11 -> 554.4684 | BB11: =(BA11/AY11)*12 -> 0.0092221975 | BC11: =AY11*($AX$1/12) -> 4509.2431 | BD11: =(BC11/AY11)*12 -> 0.075 | BE11: =BE10+BA11 -> 3275.5777 | BF11: =BF10+BC11 -> 27106.691 | BG11: =AY11-BA11 -> 720924.42 | BH11: =BE11+BF11 -> 30382.269 | BJ11: 6 | BK11: 45017 | BL11: =BT10 -> 721340.93 | BM11: =BM10 -> 4940.3206 | BN11: =BM11-BP11 -> 582.21915 | BO11: =(BN11/BL11)*12 -> 0.009685614 | BP11: =BL11*($BK$1/12) -> 4358.1015 | BQ11: =(BP11/BL11)*12 -> 0.0725 | BR11: =BR10+BN11 -> 3441.2862 | BS11: =BS10+BP11 -> 26200.637 | BT11: =BL11-BN11 -> 720758.71 | BU11: =BR11+BS11 -> 29641.924 | BW11: 6 | BX11: 45017 | BY11: =CG10 -> 721197.07 | BZ11: =BZ10 -> 4818.1207 | CA11: =BZ11-CC11 -> 611.13778 | CB11: =(CA11/BY11)*12 -> 0.010168723 | CC11: =BY11*($BX$1/12) -> 4206.9829 | CD11: =(CC11/BY11)*12 -> 0.07 | CE11: =CE10+CA11 -> 3614.0716 | CF11: =CF10+CC11 -> 25294.652 | CG11: =BY11-CA11 -> 720585.93 | CH11: =CE11+CF11 -> 28908.724
A12: =A11+1 -> 4 | B12: =VLOOKUP(A12*12,$J$5:$U$365,10) -> 234996.18 | C12: =VLOOKUP(A12*12,$W$5:$AH$365,10) -> 227686.58 | D12: =VLOOKUP(A12*12,$AJ$5:$AU$365,10) -> 220381.27 | E12: =VLOOKUP(A12*12,$AW$5:$BH$365,10) -> 213080.77 | F12: =VLOOKUP(A12*12,$BJ$5:$BU$365,10) -> 205785.64 | G12: =VLOOKUP(A12*12,$BW$5:$CH$365,10) -> 198496.45 | J12: 7 | K12: 45047 | L12: =T11 -> 721381.15 | M12: =$L$6/((($N$2)-1)/($N$1*$N$2)) -> 5440.6727 | N12: =M12-P12 -> 481.17733 | O12: =(N12/L12)*12 -> 0.0080042678 | P12: =L12*($K$1/12) -> 4959.4954 | Q12: =(P12/L12)*12 -> 0.0825 | R12: =R11+N12 -> 3300.0255 | S12: =S11+P12 -> 34784.684 | T12: =L12-N12 -> 720899.97 | U12: =R12+S12 -> 38084.709 | W12: 7 | X12: 45047 | Y12: =AG11 -> 721235.44 | Z12: =Z11 -> 5313.923 | AA12: =Z12-AC12 -> 505.68681 | AB12: =(AA12/Y12)*12 -> 0.0084136766 | AC12: =Y12*($X$1/12) -> 4808.2362 | AD12: =(AC12/Y12)*12 -> 0.08 | AE12: =AE11+AA12 -> 3470.2515 | AF12: =AF11+AC12 -> 33727.21 | AG12: =Y12-AA12 -> 720729.75 | AH12: =AE12+AF12 -> 37197.461 | AJ12: 7 | AK12: 45047 | AL12: =AT11 -> 721083.26 | AM12: =AM11 -> 5188.2575 | AN12: =AM12-AP12 -> 531.26142 | AO12: =(AN12/AL12)*12 -> 0.0088410554 | AP12: =AL12*($AK$1/12) -> 4656.9961 | AQ12: =(AP12/AL12)*12 -> 0.0775 | AR12: =AR11+AN12 -> 3648.0007 | AS12: =AS11+AP12 -> 32669.802 | AT12: =AL12-AN12 -> 720552 | AU12: =AR12+AS12 -> 36317.802 | AW12: 7 | AX12: 45047 | AY12: =BG11 -> 720924.42 | AZ12: =AZ11 -> 5063.7115 | BA12: =AZ12-BC12 -> 557.93383 | BB12: =(BA12/AY12)*12 -> 0.0092869735 | BC12: =AY12*($AX$1/12) -> 4505.7776 | BD12: =(BC12/AY12)*12 -> 0.075 | BE12: =BE11+BA12 -> 3833.5115 | BF12: =BF11+BC12 -> 31612.469 | BG12: =AY12-BA12 -> 720366.49 | BH12: =BE12+BF12 -> 35445.98 | BJ12: 7 | BK12: 45047 | BL12: =BT11 -> 720758.71 | BM12: =BM11 -> 4940.3206 | BN12: =BM12-BP12 -> 585.73672 | BO12: =(BN12/BL12)*12 -> 0.0097520024 | BP12: =BL12*($BK$1/12) -> 4354.5839 | BQ12: =(BP12/BL12)*12 -> 0.0725 | BR12: =BR11+BN12 -> 4027.0229 | BS12: =BS11+BP12 -> 30555.221 | BT12: =BL12-BN12 -> 720172.98 | BU12: =BR12+BS12 -> 34582.244 | BW12: 7 | BX12: 45047 | BY12: =CG11 -> 720585.93 | BZ12: =BZ11 -> 4818.1207 | CA12: =BZ12-CC12 -> 614.70275 | CB12: =(CA12/BY12)*12 -> 0.010236715 | CC12: =BY12*($BX$1/12) -> 4203.4179 | CD12: =(CC12/BY12)*12 -> 0.07 | CE12: =CE11+CA12 -> 4228.7743 | CF12: =CF11+CC12 -> 29498.07 | CG12: =BY12-CA12 -> 719971.23 | CH12: =CE12+CF12 -> 33726.845
A13: =A12+1 -> 5 | B13: =VLOOKUP(A13*12,$J$5:$U$365,10) -> 292286.89 | C13: =VLOOKUP(A13*12,$W$5:$AH$365,10) -> 283131.28 | D13: =VLOOKUP(A13*12,$AJ$5:$AU$365,10) -> 273982.77 | E13: =VLOOKUP(A13*12,$AW$5:$BH$365,10) -> 264842.16 | F13: =VLOOKUP(A13*12,$BJ$5:$BU$365,10) -> 255710.34 | G13: =VLOOKUP(A13*12,$BW$5:$CH$365,10) -> 246588.21 | J13: 8 | K13: 45078 | L13: =T12 -> 720899.97 | M13: =$L$6/((($N$2)-1)/($N$1*$N$2)) -> 5440.6727 | N13: =M13-P13 -> 484.48542 | O13: =(N13/L13)*12 -> 0.0080646765 | P13: =L13*($K$1/12) -> 4956.1873 | Q13: =(P13/L13)*12 -> 0.0825 | R13: =R12+N13 -> 3784.5109 | S13: =S12+P13 -> 39740.871 | T13: =L13-N13 -> 720415.49 | U13: =R13+S13 -> 43525.382 | W13: 8 | X13: 45078 | Y13: =AG12 -> 720729.75 | Z13: =Z12 -> 5313.923 | AA13: =Z13-AC13 -> 509.05805 | AB13: =(AA13/Y13)*12 -> 0.0084757104 | AC13: =Y13*($X$1/12) -> 4804.865 | AD13: =(AC13/Y13)*12 -> 0.08 | AE13: =AE12+AA13 -> 3979.3095 | AF13: =AF12+AC13 -> 38532.075 | AG13: =Y13-AA13 -> 720220.69 | AH13: =AE13+AF13 -> 42511.384 | AJ13: 8 | AK13: 45078 | AL13: =AT12 -> 720552 | AM13: =AM12 -> 5188.2575 | AN13: =AM13-AP13 -> 534.69249 | AO13: =(AN13/AL13)*12 -> 0.0089047145 | AP13: =AL13*($AK$1/12) -> 4653.565 | AQ13: =(AP13/AL13)*12 -> 0.0775 | AR13: =AR12+AN13 -> 4182.6932 | AS13: =AS12+AP13 -> 37323.367 | AT13: =AL13-AN13 -> 720017.31 | AU13: =AR13+AS13 -> 41506.06 | AW13: 8 | AX13: 45078 | AY13: =BG12 -> 720366.49 | AZ13: =AZ12 -> 5063.7115 | BA13: =AZ13-BC13 -> 561.42092 | BB13: =(BA13/AY13)*12 -> 0.0093522549 | BC13: =AY13*($AX$1/12) -> 4502.2906 | BD13: =(BC13/AY13)*12 -> 0.075 | BE13: =BE12+BA13 -> 4394.9325 | BF13: =BF12+BC13 -> 36114.759 | BG13: =AY13-BA13 -> 719805.07 | BH13: =BE13+BF13 -> 40509.692 | BJ13: 8 | BK13: 45078 | BL13: =BT12 -> 720172.98 | BM13: =BM12 -> 4940.3206 | BN13: =BM13-BP13 -> 589.27555 | BO13: =(BN13/BL13)*12 -> 0.0098189002 | BP13: =BL13*($BK$1/12) -> 4351.0451 | BQ13: =(BP13/BL13)*12 -> 0.0725 | BR13: =BR12+BN13 -> 4616.2985 | BS13: =BS12+BP13 -> 34906.266 | BT13: =BL13-BN13 -> 719583.7 | BU13: =BR13+BS13 -> 39522.565 | BW13: 8 | BX13: 45078 | BY13: =CG12 -> 719971.23 | BZ13: =BZ12 -> 4818.1207 | CA13: =BZ13-CC13 -> 618.28852 | CB13: =(CA13/BY13)*12 -> 0.010305221 | CC13: =BY13*($BX$1/12) -> 4199.8321 | CD13: =(CC13/BY13)*12 -> 0.07 | CE13: =CE12+CA13 -> 4847.0629 | CF13: =CF12+CC13 -> 33697.902 | CG13: =BY13-CA13 -> 719352.94 | CH13: =CE13+CF13 -> 38544.965
A14: =A13+1 -> 6 | B14: =VLOOKUP(A14*12,$J$5:$U$365,10) -> 348892.29 | C14: =VLOOKUP(A14*12,$W$5:$AH$365,10) -> 337885.23 | D14: =VLOOKUP(A14*12,$AJ$5:$AU$365,10) -> 326888.94 | E14: =VLOOKUP(A14*12,$AW$5:$BH$365,10) -> 315904.62 | F14: =VLOOKUP(A14*12,$BJ$5:$BU$365,10) -> 304933.5 | G14: =VLOOKUP(A14*12,$BW$5:$CH$365,10) -> 293976.91 | J14: 9 | K14: 45108 | L14: =T13 -> 720415.49 | M14: =$L$6/((($N$2)-1)/($N$1*$N$2)) -> 5440.6727 | N14: =M14-P14 -> 487.81626 | O14: =(N14/L14)*12 -> 0.008125582 | P14: =L14*($K$1/12) -> 4952.8565 | Q14: =(P14/L14)*12 -> 0.0825 | R14: =R13+N14 -> 4272.3272 | S14: =S13+P14 -> 44693.728 | T14: =L14-N14 -> 719927.67 | U14: =R14+S14 -> 48966.055 | W14: 9 | X14: 45108 | Y14: =AG13 -> 720220.69 | Z14: =Z13 -> 5313.923 | AA14: =Z14-AC14 -> 512.45177 | AB14: =(AA14/Y14)*12 -> 0.0085382458 | AC14: =Y14*($X$1/12) -> 4801.4713 | AD14: =(AC14/Y14)*12 -> 0.08 | AE14: =AE13+AA14 -> 4491.7613 | AF14: =AF13+AC14 -> 43333.546 | AG14: =Y14-AA14 -> 719708.24 | AH14: =AE14+AF14 -> 47825.307 | AJ14: 9 | AK14: 45108 | AL14: =AT13 -> 720017.31 | AM14: =AM13 -> 5188.2575 | AN14: =AM14-AP14 -> 538.14571 | AO14: =(AN14/AL14)*12 -> 0.0089688796 | AP14: =AL14*($AK$1/12) -> 4650.1118 | AQ14: =(AP14/AL14)*12 -> 0.0775 | AR14: =AR13+AN14 -> 4720.8389 | AS14: =AS13+AP14 -> 41973.478 | AT14: =AL14-AN14 -> 719479.16 | AU14: =AR14+AS14 -> 46694.317 | AW14: 9 | AX14: 45108 | AY14: =BG13 -> 719805.07 | AZ14: =AZ13 -> 5063.7115 | BA14: =AZ14-BC14 -> 564.9298 | BB14: =(BA14/AY14)*12 -> 0.0094180465 | BC14: =AY14*($AX$1/12) -> 4498.7817 | BD14: =(BC14/AY14)*12 -> 0.075 | BE14: =BE13+BA14 -> 4959.8623 | BF14: =BF13+BC14 -> 40613.541 | BG14: =AY14-BA14 -> 719240.14 | BH14: =BE14+BF14 -> 45573.403 | BJ14: 9 | BK14: 45108 | BL14: =BT13 -> 719583.7 | BM14: =BM13 -> 4940.3206 | BN14: =BM14-BP14 -> 592.83576 | BO14: =(BN14/BL14)*12 -> 0.0098863121 | BP14: =BL14*($BK$1/12) -> 4347.4849 | BQ14: =(BP14/BL14)*12 -> 0.0725 | BR14: =BR13+BN14 -> 5209.1343 | BS14: =BS13+BP14 -> 39253.751 | BT14: =BL14-BN14 -> 718990.87 | BU14: =BR14+BS14 -> 44462.886 | BW14: 9 | BX14: 45108 | BY14: =CG13 -> 719352.94 | BZ14: =BZ13 -> 4818.1207 | CA14: =BZ14-CC14 -> 621.8952 | CB14: =(CA14/BY14)*12 -> 0.010374243 | CC14: =BY14*($BX$1/12) -> 4196.2255 | CD14: =(CC14/BY14)*12 -> 0.07 | CE14: =CE13+CA14 -> 5468.9581 | CF14: =CF13+CC14 -> 37894.128 | CG14: =BY14-CA14 -> 718731.04 | CH14: =CE14+CF14 -> 43363.086
A15: =A14+1 -> 7 | B15: =VLOOKUP(A15*12,$J$5:$U$365,10) -> 404753.65 | C15: =VLOOKUP(A15*12,$W$5:$AH$365,10) -> 391891.1 | D15: =VLOOKUP(A15*12,$AJ$5:$AU$365,10) -> 379043.96 | E15: =VLOOKUP(A15*12,$AW$5:$BH$365,10) -> 366213.87 | F15: =VLOOKUP(A15*12,$BJ$5:$BU$365,10) -> 353402.53 | G15: =VLOOKUP(A15*12,$BW$5:$CH$365,10) -> 340611.71 | J15: 10 | K15: 45139 | L15: =T14 -> 719927.67 | M15: =$L$6/((($N$2)-1)/($N$1*$N$2)) -> 5440.6727 | N15: =M15-P15 -> 491.17 | O15: =(N15/L15)*12 -> 0.008186989 | P15: =L15*($K$1/12) -> 4949.5028 | Q15: =(P15/L15)*12 -> 0.0825 | R15: =R14+N15 -> 4763.4972 | S15: =S14+P15 -> 49643.23 | T15: =L15-N15 -> 719436.5 | U15: =R15+S15 -> 54406.727 | W15: 10 | X15: 45139 | Y15: =AG14 -> 719708.24 | Z15: =Z14 -> 5313.923 | AA15: =Z15-AC15 -> 515.86812 | AB15: =(AA15/Y15)*12 -> 0.0086012874 | AC15: =Y15*($X$1/12) -> 4798.0549 | AD15: =(AC15/Y15)*12 -> 0.08 | AE15: =AE14+AA15 -> 5007.6294 | AF15: =AF14+AC15 -> 48131.601 | AG15: =Y15-AA15 -> 719192.37 | AH15: =AE15+AF15 -> 53139.23 | AJ15: 10 | AK15: 45139 | AL15: =AT14 -> 719479.16 | AM15: =AM14 -> 5188.2575 | AN15: =AM15-AP15 -> 541.62123 | AO15: =(AN15/AL15)*12 -> 0.0090335553 | AP15: =AL15*($AK$1/12) -> 4646.6362 | AQ15: =(AP15/AL15)*12 -> 0.0775 | AR15: =AR14+AN15 -> 5262.4602 | AS15: =AS14+AP15 -> 46620.115 | AT15: =AL15-AN15 -> 718937.54 | AU15: =AR15+AS15 -> 51882.575 | AW15: 10 | AX15: 45139 | AY15: =BG14 -> 719240.14 | AZ15: =AZ14 -> 5063.7115 | BA15: =AZ15-BC15 -> 568.46061 | BB15: =(BA15/AY15)*12 -> 0.0094843529 | BC15: =AY15*($AX$1/12) -> 4495.2509 | BD15: =(BC15/AY15)*12 -> 0.075 | BE15: =BE14+BA15 -> 5528.3229 | BF15: =BF14+BC15 -> 45108.792 | BG15: =AY15-BA15 -> 718671.68 | BH15: =BE15+BF15 -> 50637.115 | BJ15: 10 | BK15: 45139 | BL15: =BT14 -> 718990.87 | BM15: =BM14 -> 4940.3206 | BN15: =BM15-BP15 -> 596.41747 | BO15: =(BN15/BL15)*12 -> 0.0099542428 | BP15: =BL15*($BK$1/12) -> 4343.9031 | BQ15: =(BP15/BL15)*12 -> 0.0725 | BR15: =BR14+BN15 -> 5805.5517 | BS15: =BS14+BP15 -> 43597.654 | BT15: =BL15-BN15 -> 718394.45 | BU15: =BR15+BS15 -> 49403.206 | BW15: 10 | BX15: 45139 | BY15: =CG14 -> 718731.04 | BZ15: =BZ14 -> 4818.1207 | CA15: =BZ15-CC15 -> 625.52293 | CB15: =(CA15/BY15)*12 -> 0.010443789 | CC15: =BY15*($BX$1/12) -> 4192.5977 | CD15: =(CC15/BY15)*12 -> 0.07 | CE15: =CE14+CA15 -> 6094.481 | CF15: =CF14+CC15 -> 42086.726 | CG15: =BY15-CA15 -> 718105.52 | CH15: =CE15+CF15 -> 48181.207
A16: =A15+1 -> 8 | B16: =VLOOKUP(A16*12,$J$5:$U$365,10) -> 459807.21 | C16: =VLOOKUP(A16*12,$W$5:$AH$365,10) -> 445086.78 | D16: =VLOOKUP(A16*12,$AJ$5:$AU$365,10) -> 430387.49 | E16: =VLOOKUP(A16*12,$AW$5:$BH$365,10) -> 415711.46 | F16: =VLOOKUP(A16*12,$BJ$5:$BU$365,10) -> 401060.9 | G16: =VLOOKUP(A16*12,$BW$5:$CH$365,10) -> 386438.11 | J16: 11 | K16: 45170 | L16: =T15 -> 719436.5 | M16: =$L$6/((($N$2)-1)/($N$1*$N$2)) -> 5440.6727 | N16: =M16-P16 -> 494.54679 | O16: =(N16/L16)*12 -> 0.0082489024 | P16: =L16*($K$1/12) -> 4946.126 | Q16: =(P16/L16)*12 -> 0.0825 | R16: =R15+N16 -> 5258.044 | S16: =S15+P16 -> 54589.356 | T16: =L16-N16 -> 718941.96 | U16: =R16+S16 -> 59847.4 | W16: 11 | X16: 45170 | Y16: =AG15 -> 719192.37 | Z16: =Z15 -> 5313.923 | AA16: =Z16-AC16 -> 519.30724 | AB16: =(AA16/Y16)*12 -> 0.0086648401 | AC16: =Y16*($X$1/12) -> 4794.6158 | AD16: =(AC16/Y16)*12 -> 0.08 | AE16: =AE15+AA16 -> 5526.9367 | AF16: =AF15+AC16 -> 52926.217 | AG16: =Y16-AA16 -> 718673.06 | AH16: =AE16+AF16 -> 58453.153 | AJ16: 11 | AK16: 45170 | AL16: =AT15 -> 718937.54 | AM16: =AM15 -> 5188.2575 | AN16: =AM16-AP16 -> 545.1192 | AO16: =(AN16/AL16)*12 -> 0.0090987465 | AP16: =AL16*($AK$1/12) -> 4643.1383 | AQ16: =(AP16/AL16)*12 -> 0.0775 | AR16: =AR15+AN16 -> 5807.5794 | AS16: =AS15+AP16 -> 51263.253 | AT16: =AL16-AN16 -> 718392.42 | AU16: =AR16+AS16 -> 57070.832 | AW16: 11 | AX16: 45170 | AY16: =BG15 -> 718671.68 | AZ16: =AZ15 -> 5063.7115 | BA16: =AZ16-BC16 -> 572.01349 | BB16: =(BA16/AY16)*12 -> 0.009551179 | BC16: =AY16*($AX$1/12) -> 4491.698 | BD16: =(BC16/AY16)*12 -> 0.075 | BE16: =BE15+BA16 -> 6100.3364 | BF16: =BF15+BC16 -> 49600.49 | BG16: =AY16-BA16 -> 718099.66 | BH16: =BE16+BF16 -> 55700.826 | BJ16: 11 | BK16: 45170 | BL16: =BT15 -> 718394.45 | BM16: =BM15 -> 4940.3206 | BN16: =BM16-BP16 -> 600.02083 | BO16: =(BN16/BL16)*12 -> 0.010022697 | BP16: =BL16*($BK$1/12) -> 4340.2998 | BQ16: =(BP16/BL16)*12 -> 0.0725 | BR16: =BR15+BN16 -> 6405.5726 | BS16: =BS15+BP16 -> 47937.954 | BT16: =BL16-BN16 -> 717794.43 | BU16: =BR16+BS16 -> 54343.527 | BW16: 11 | BX16: 45170 | BY16: =CG15 -> 718105.52 | BZ16: =BZ15 -> 4818.1207 | CA16: =BZ16-CC16 -> 629.17181 | CB16: =(CA16/BY16)*12 -> 0.010513861 | CC16: =BY16*($BX$1/12) -> 4188.9489 | CD16: =(CC16/BY16)*12 -> 0.07 | CE16: =CE15+CA16 -> 6723.6528 | CF16: =CF15+CC16 -> 46275.675 | CG16: =BY16-CA16 -> 717476.35 | CH16: =CE16+CF16 -> 52999.327
A17: =A16+1 -> 9 | B17: =VLOOKUP(A17*12,$J$5:$U$365,10) -> 513983.76 | C17: =VLOOKUP(A17*12,$W$5:$AH$365,10) -> 497405.05 | D17: =VLOOKUP(A17*12,$AJ$5:$AU$365,10) -> 480854.36 | E17: =VLOOKUP(A17*12,$AW$5:$BH$365,10) -> 464334.36 | F17: =VLOOKUP(A17*12,$BJ$5:$BU$365,10) -> 447847.84 | G17: =VLOOKUP(A17*12,$BW$5:$CH$365,10) -> 431397.69 | J17: 12 | K17: 45200 | L17: =T16 -> 718941.96 | M17: =$L$6/((($N$2)-1)/($N$1*$N$2)) -> 5440.6727 | N17: =M17-P17 -> 497.9468 | O17: =(N17/L17)*12 -> 0.0083113269 | P17: =L17*($K$1/12) -> 4942.7259 | Q17: =(P17/L17)*12 -> 0.0825 | R17: =R16+N17 -> 5755.9908 | S17: =S16+P17 -> 59532.082 | T17: =L17-N17 -> 718444.01 | U17: =R17+S17 -> 65288.073 | W17: 12 | X17: 45200 | Y17: =AG16 -> 718673.06 | Z17: =Z16 -> 5313.923 | AA17: =Z17-AC17 -> 522.76929 | AB17: =(AA17/Y17)*12 -> 0.0087289086 | AC17: =Y17*($X$1/12) -> 4791.1538 | AD17: =(AC17/Y17)*12 -> 0.08 | AE17: =AE16+AA17 -> 6049.706 | AF17: =AF16+AC17 -> 57717.371 | AG17: =Y17-AA17 -> 718150.29 | AH17: =AE17+AF17 -> 63767.077 | AJ17: 12 | AK17: 45200 | AL17: =AT16 -> 718392.42 | AM17: =AM16 -> 5188.2575 | AN17: =AM17-AP17 -> 548.63977 | AO17: =(AN17/AL17)*12 -> 0.009164458 | AP17: =AL17*($AK$1/12) -> 4639.6177 | AQ17: =(AP17/AL17)*12 -> 0.0775 | AR17: =AR16+AN17 -> 6356.2191 | AS17: =AS16+AP17 -> 55902.871 | AT17: =AL17-AN17 -> 717843.78 | AU17: =AR17+AS17 -> 62259.09 | AW17: 12 | AX17: 45200 | AY17: =BG16 -> 718099.66 | AZ17: =AZ16 -> 5063.7115 | BA17: =AZ17-BC17 -> 575.58857 | BB17: =(BA17/AY17)*12 -> 0.0096185296 | BC17: =AY17*($AX$1/12) -> 4488.1229 | BD17: =(BC17/AY17)*12 -> 0.075 | BE17: =BE16+BA17 -> 6675.9249 | BF17: =BF16+BC17 -> 54088.613 | BG17: =AY17-BA17 -> 717524.08 | BH17: =BE17+BF17 -> 60764.538 | BJ17: 12 | BK17: 45200 | BL17: =BT16 -> 717794.43 | BM17: =BM16 -> 4940.3206 | BN17: =BM17-BP17 -> 603.64595 | BO17: =(BN17/BL17)*12 -> 0.01009168 | BP17: =BL17*($BK$1/12) -> 4336.6747 | BQ17: =(BP17/BL17)*12 -> 0.0725 | BR17: =BR16+BN17 -> 7009.2185 | BS17: =BS16+BP17 -> 52274.629 | BT17: =BL17-BN17 -> 717190.78 | BU17: =BR17+BS17 -> 59283.847 | BW17: 12 | BX17: 45200 | BY17: =CG16 -> 717476.35 | BZ17: =BZ16 -> 4818.1207 | CA17: =BZ17-CC17 -> 632.84198 | CB17: =(CA17/BY17)*12 -> 0.010584466 | CC17: =BY17*($BX$1/12) -> 4185.2787 | CD17: =(CC17/BY17)*12 -> 0.07 | CE17: =CE16+CA17 -> 7356.4948 | CF17: =CF16+CC17 -> 50460.953 | CG17: =BY17-CA17 -> 716843.51 | CH17: =CE17+CF17 -> 57817.448
A18: =A17+1 -> 10 | B18: =VLOOKUP(A18*12,$J$5:$U$365,10) -> 567208.14 | C18: =VLOOKUP(A18*12,$W$5:$AH$365,10) -> 548773.07 | D18: =VLOOKUP(A18*12,$AJ$5:$AU$365,10) -> 530374.16 | E18: =VLOOKUP(A18*12,$AW$5:$BH$365,10) -> 512014.67 | F18: =VLOOKUP(A18*12,$BJ$5:$BU$365,10) -> 493698.03 | G18: =VLOOKUP(A18*12,$BW$5:$CH$365,10) -> 475427.76 | J18: 13 | K18: 45231 | L18: =T17 -> 718444.01 | M18: =$L$6/((($N$2)-1)/($N$1*$N$2)) -> 5440.6727 | N18: =M18-P18 -> 501.37018 | O18: =(N18/L18)*12 -> 0.0083742673 | P18: =L18*($K$1/12) -> 4939.3026 | Q18: =(P18/L18)*12 -> 0.0825 | R18: =R17+N18 -> 6257.3609 | S18: =S17+P18 -> 64471.385 | T18: =L18-N18 -> 717942.64 | U18: =R18+S18 -> 70728.746 | W18: 13 | X18: 45231 | Y18: =AG17 -> 718150.29 | Z18: =Z17 -> 5313.923 | AA18: =Z18-AC18 -> 526.25442 | AB18: =(AA18/Y18)*12 -> 0.0087934978 | AC18: =Y18*($X$1/12) -> 4787.6686 | AD18: =(AC18/Y18)*12 -> 0.08 | AE18: =AE17+AA18 -> 6575.9604 | AF18: =AF17+AC18 -> 62505.039 | AG18: =Y18-AA18 -> 717624.04 | AH18: =AE18+AF18 -> 69081 | AJ18: 13 | AK18: 45231 | AL18: =AT17 -> 717843.78 | AM18: =AM17 -> 5188.2575 | AN18: =AM18-AP18 -> 552.18306 | AO18: =(AN18/AL18)*12 -> 0.0092306947 | AP18: =AL18*($AK$1/12) -> 4636.0744 | AQ18: =(AP18/AL18)*12 -> 0.0775 | AR18: =AR17+AN18 -> 6908.4022 | AS18: =AS17+AP18 -> 60538.945 | AT18: =AL18-AN18 -> 717291.6 | AU18: =AR18+AS18 -> 67447.347 | AW18: 13 | AX18: 45231 | AY18: =BG17 -> 717524.08 | AZ18: =AZ17 -> 5063.7115 | BA18: =AZ18-BC18 -> 579.186 | BB18: =(BA18/AY18)*12 -> 0.0096864095 | BC18: =AY18*($AX$1/12) -> 4484.5255 | BD18: =(BC18/AY18)*12 -> 0.075 | BE18: =BE17+BA18 -> 7255.1109 | BF18: =BF17+BC18 -> 58573.138 | BG18: =AY18-BA18 -> 716944.89 | BH18: =BE18+BF18 -> 65828.249 | BJ18: 13 | BK18: 45231 | BL18: =BT17 -> 717190.78 | BM18: =BM17 -> 4940.3206 | BN18: =BM18-BP18 -> 607.29298 | BO18: =(BN18/BL18)*12 -> 0.010161196 | BP18: =BL18*($BK$1/12) -> 4333.0276 | BQ18: =(BP18/BL18)*12 -> 0.0725 | BR18: =BR17+BN18 -> 7616.5115 | BS18: =BS17+BP18 -> 56607.657 | BT18: =BL18-BN18 -> 716583.49 | BU18: =BR18+BS18 -> 64224.168 | BW18: 13 | BX18: 45231 | BY18: =CG17 -> 716843.51 | BZ18: =BZ17 -> 4818.1207 | CA18: =BZ18-CC18 -> 636.53356 | CB18: =(CA18/BY18)*12 -> 0.010655607 | CC18: =BY18*($BX$1/12) -> 4181.5871 | CD18: =(CC18/BY18)*12 -> 0.07 | CE18: =CE17+CA18 -> 7993.0283 | CF18: =CF17+CC18 -> 54642.54 | CG18: =BY18-CA18 -> 716206.97 | CH18: =CE18+CF18 -> 62635.569
A19: =A18+1 -> 11 | B19: =VLOOKUP(A19*12,$J$5:$U$365,10) -> 619398.75 | C19: =VLOOKUP(A19*12,$W$5:$AH$365,10) -> 599111.98 | D19: =VLOOKUP(A19*12,$AJ$5:$AU$365,10) -> 578870.82 | E19: =VLOOKUP(A19*12,$AW$5:$BH$365,10) -> 558679.23 | F19: =VLOOKUP(A19*12,$BJ$5:$BU$365,10) -> 538541.26 | G19: =VLOOKUP(A19*12,$BW$5:$CH$365,10) -> 518461.15 | J19: 14 | K19: 45261 | L19: =T18 -> 717942.64 | M19: =$L$6/((($N$2)-1)/($N$1*$N$2)) -> 5440.6727 | N19: =M19-P19 -> 504.8171 | O19: =(N19/L19)*12 -> 0.0084377287 | P19: =L19*($K$1/12) -> 4935.8556 | Q19: =(P19/L19)*12 -> 0.0825 | R19: =R18+N19 -> 6762.1781 | S19: =S18+P19 -> 69407.24 | T19: =L19-N19 -> 717437.82 | U19: =R19+S19 -> 76169.418 | W19: 14 | X19: 45261 | Y19: =AG18 -> 717624.04 | Z19: =Z18 -> 5313.923 | AA19: =Z19-AC19 -> 529.76278 | AB19: =(AA19/Y19)*12 -> 0.0088586126 | AC19: =Y19*($X$1/12) -> 4784.1603 | AD19: =(AC19/Y19)*12 -> 0.08 | AE19: =AE18+AA19 -> 7105.7231 | AF19: =AF18+AC19 -> 67289.199 | AG19: =Y19-AA19 -> 717094.28 | AH19: =AE19+AF19 -> 74394.923 | AJ19: 14 | AK19: 45261 | AL19: =AT18 -> 717291.6 | AM19: =AM18 -> 5188.2575 | AN19: =AM19-AP19 -> 555.74925 | AO19: =(AN19/AL19)*12 -> 0.0092974614 | AP19: =AL19*($AK$1/12) -> 4632.5082 | AQ19: =(AP19/AL19)*12 -> 0.0775 | AR19: =AR18+AN19 -> 7464.1514 | AS19: =AS18+AP19 -> 65171.453 | AT19: =AL19-AN19 -> 716735.85 | AU19: =AR19+AS19 -> 72635.605 | AW19: 14 | AX19: 45261 | AY19: =BG18 -> 716944.89 | AZ19: =AZ18 -> 5063.7115 | BA19: =AZ19-BC19 -> 582.80591 | BB19: =(BA19/AY19)*12 -> 0.0097548237 | BC19: =AY19*($AX$1/12) -> 4480.9056 | BD19: =(BC19/AY19)*12 -> 0.075 | BE19: =BE18+BA19 -> 7837.9168 | BF19: =BF18+BC19 -> 63054.044 | BG19: =AY19-BA19 -> 716362.08 | BH19: =BE19+BF19 -> 70891.961 | BJ19: 14 | BK19: 45261 | BL19: =BT18 -> 716583.49 | BM19: =BM18 -> 4940.3206 | BN19: =BM19-BP19 -> 610.96204 | BO19: =(BN19/BL19)*12 -> 0.01023125 | BP19: =BL19*($BK$1/12) -> 4329.3586 | BQ19: =(BP19/BL19)*12 -> 0.0725 | BR19: =BR18+BN19 -> 8227.4735 | BS19: =BS18+BP19 -> 60937.015 | BT19: =BL19-BN19 -> 715972.53 | BU19: =BR19+BS19 -> 69164.489 | BW19: 14 | BX19: 45261 | BY19: =CG18 -> 716206.97 | BZ19: =BZ18 -> 4818.1207 | CA19: =BZ19-CC19 -> 640.24667 | CB19: =(CA19/BY19)*12 -> 0.01072729 | CC19: =BY19*($BX$1/12) -> 4177.874 | CD19: =(CC19/BY19)*12 -> 0.07 | CE19: =CE18+CA19 -> 8633.275 | CF19: =CF18+CC19 -> 58820.414 | CG19: =BY19-CA19 -> 715566.72 | CH19: =CE19+CF19 -> 67453.689
A20: =A19+1 -> 12 | B20: =VLOOKUP(A20*12,$J$5:$U$365,10) -> 670467.02 | C20: =VLOOKUP(A20*12,$W$5:$AH$365,10) -> 648336.35 | D20: =VLOOKUP(A20*12,$AJ$5:$AU$365,10) -> 626262.19 | E20: =VLOOKUP(A20*12,$AW$5:$BH$365,10) -> 604249.16 | F20: =VLOOKUP(A20*12,$BJ$5:$BU$365,10) -> 582302.05 | G20: =VLOOKUP(A20*12,$BW$5:$CH$365,10) -> 560425.79 | J20: 15 | K20: 45292 | L20: =T19 -> 717437.82 | M20: =$L$6/((($N$2)-1)/($N$1*$N$2)) -> 5440.6727 | N20: =M20-P20 -> 508.28772 | O20: =(N20/L20)*12 -> 0.0085017161 | P20: =L20*($K$1/12) -> 4932.385 | Q20: =(P20/L20)*12 -> 0.0825 | R20: =R19+N20 -> 7270.4658 | S20: =S19+P20 -> 74339.625 | T20: =L20-N20 -> 716929.53 | U20: =R20+S20 -> 81610.091 | W20: 15 | X20: 45292 | Y20: =AG19 -> 717094.28 | Z20: =Z19 -> 5313.923 | AA20: =Z20-AC20 -> 533.29453 | AB20: =(AA20/Y20)*12 -> 0.0089242581 | AC20: =Y20*($X$1/12) -> 4780.6285 | AD20: =(AC20/Y20)*12 -> 0.08 | AE20: =AE19+AA20 -> 7639.0177 | AF20: =AF19+AC20 -> 72069.828 | AG20: =Y20-AA20 -> 716560.98 | AH20: =AE20+AF20 -> 79708.846 | AJ20: 15 | AK20: 45292 | AL20: =AT19 -> 716735.85 | AM20: =AM19 -> 5188.2575 | AN20: =AM20-AP20 -> 559.33846 | AO20: =(AN20/AL20)*12 -> 0.0093647632 | AP20: =AL20*($AK$1/12) -> 4628.919 | AQ20: =(AP20/AL20)*12 -> 0.0775 | AR20: =AR19+AN20 -> 8023.4899 | AS20: =AS19+AP20 -> 69800.372 | AT20: =AL20-AN20 -> 716176.51 | AU20: =AR20+AS20 -> 77823.862 | AW20: 15 | AX20: 45292 | AY20: =BG19 -> 716362.08 | AZ20: =AZ19 -> 5063.7115 | BA20: =AZ20-BC20 -> 586.44845 | BB20: =(BA20/AY20)*12 -> 0.0098237771 | BC20: =AY20*($AX$1/12) -> 4477.263 | BD20: =(BC20/AY20)*12 -> 0.075 | BE20: =BE19+BA20 -> 8424.3653 | BF20: =BF19+BC20 -> 67531.307 | BG20: =AY20-BA20 -> 715775.63 | BH20: =BE20+BF20 -> 75955.672 | BJ20: 15 | BK20: 45292 | BL20: =BT19 -> 715972.53 | BM20: =BM19 -> 4940.3206 | BN20: =BM20-BP20 -> 614.65327 | BO20: =(BN20/BL20)*12 -> 0.010301847 | BP20: =BL20*($BK$1/12) -> 4325.6673 | BQ20: =(BP20/BL20)*12 -> 0.0725 | BR20: =BR19+BN20 -> 8842.1268 | BS20: =BS19+BP20 -> 65262.682 | BT20: =BL20-BN20 -> 715357.87 | BU20: =BR20+BS20 -> 74104.809 | BW20: 15 | BX20: 45292 | BY20: =CG19 -> 715566.72 | BZ20: =BZ19 -> 4818.1207 | CA20: =BZ20-CC20 -> 643.98144 | CB20: =(CA20/BY20)*12 -> 0.01079952 | CC20: =BY20*($BX$1/12) -> 4174.1392 | CD20: =(CC20/BY20)*12 -> 0.07 | CE20: =CE19+CA20 -> 9277.2564 | CF20: =CF19+CC20 -> 62994.554 | CG20: =BY20-CA20 -> 714922.74 | CH20: =CE20+CF20 -> 72271.81
A21: =A20+1 -> 13 | B21: =VLOOKUP(A21*12,$J$5:$U$365,10) -> 720316.76 | C21: =VLOOKUP(A21*12,$W$5:$AH$365,10) -> 696353.69 | D21: =VLOOKUP(A21*12,$AJ$5:$AU$365,10) -> 672459.48 | E21: =VLOOKUP(A21*12,$AW$5:$BH$365,10) -> 648639.5 | F21: =VLOOKUP(A21*12,$BJ$5:$BU$365,10) -> 624899.25 | G21: =VLOOKUP(A21*12,$BW$5:$CH$365,10) -> 601244.43 | J21: 16 | K21: 45323 | L21: =T20 -> 716929.53 | M21: =$L$6/((($N$2)-1)/($N$1*$N$2)) -> 5440.6727 | N21: =M21-P21 -> 511.7822 | O21: =(N21/L21)*12 -> 0.0085662343 | P21: =L21*($K$1/12) -> 4928.8905 | Q21: =(P21/L21)*12 -> 0.0825 | R21: =R20+N21 -> 7782.248 | S21: =S20+P21 -> 79268.516 | T21: =L21-N21 -> 716417.75 | U21: =R21+S21 -> 87050.764 | W21: 16 | X21: 45323 | Y21: =AG20 -> 716560.98 | Z21: =Z20 -> 5313.923 | AA21: =Z21-AC21 -> 536.84983 | AB21: =(AA21/Y21)*12 -> 0.0089904392 | AC21: =Y21*($X$1/12) -> 4777.0732 | AD21: =(AC21/Y21)*12 -> 0.08 | AE21: =AE20+AA21 -> 8175.8675 | AF21: =AF20+AC21 -> 76846.901 | AG21: =Y21-AA21 -> 716024.13 | AH21: =AE21+AF21 -> 85022.769 | AJ21: 16 | AK21: 45323 | AL21: =AT20 -> 716176.51 | AM21: =AM20 -> 5188.2575 | AN21: =AM21-AP21 -> 562.95085 | AO21: =(AN21/AL21)*12 -> 0.0094326052 | AP21: =AL21*($AK$1/12) -> 4625.3066 | AQ21: =(AP21/AL21)*12 -> 0.0775 | AR21: =AR20+AN21 -> 8586.4408 | AS21: =AS20+AP21 -> 74425.679 | AT21: =AL21-AN21 -> 715613.56 | AU21: =AR21+AS21 -> 83012.12 | AW21: 16 | AX21: 45323 | AY21: =BG20 -> 715775.63 | AZ21: =AZ20 -> 5063.7115 | BA21: =AZ21-BC21 -> 590.11375 | BB21: =(BA21/AY21)*12 -> 0.0098932748 | BC21: =AY21*($AX$1/12) -> 4473.5977 | BD21: =(BC21/AY21)*12 -> 0.075 | BE21: =BE20+BA21 -> 9014.479 | BF21: =BF20+BC21 -> 72004.904 | BG21: =AY21-BA21 -> 715185.52 | BH21: =BE21+BF21 -> 81019.384 | BJ21: 16 | BK21: 45323 | BL21: =BT20 -> 715357.87 | BM21: =BM20 -> 4940.3206 | BN21: =BM21-BP21 -> 618.3668 | BO21: =(BN21/BL21)*12 -> 0.010372992 | BP21: =BL21*($BK$1/12) -> 4321.9538 | BQ21: =(BP21/BL21)*12 -> 0.0725 | BR21: =BR20+BN21 -> 9460.4936 | BS21: =BS20+BP21 -> 69584.636 | BT21: =BL21-BN21 -> 714739.51 | BU21: =BR21+BS21 -> 79045.13 | BW21: 16 | BX21: 45323 | BY21: =CG20 -> 714922.74 | BZ21: =BZ20 -> 4818.1207 | CA21: =BZ21-CC21 -> 647.738 | CB21: =(CA21/BY21)*12 -> 0.010872302 | CC21: =BY21*($BX$1/12) -> 4170.3827 | CD21: =(CC21/BY21)*12 -> 0.07 | CE21: =CE20+CA21 -> 9924.9944 | CF21: =CF20+CC21 -> 67164.936 | CG21: =BY21-CA21 -> 714275.01 | CH21: =CE21+CF21 -> 77089.931
... A38: =A37+1 -> 30 | B38: =VLOOKUP(A38*12,$J$5:$U$365,10) -> 1234442.2 | C38: =VLOOKUP(A38*12,$W$5:$AH$365,10) -> 1188812.3 | D38: =VLOOKUP(A38*12,$AJ$5:$AU$365,10) -> 1143572.7 | E38: =VLOOKUP(A38*12,$AW$5:$BH$365,10) -> 1098736.1 | F38: =VLOOKUP(A38*12,$BJ$5:$BU$365,10) -> 1054315.4 | G38: =VLOOKUP(A38*12,$BW$5:$CH$365,10) -> 1010323.4 | J38: 33 | K38: 45839 | L38: =T37 -> 707733.87 | M38: =$L$6/((($N$2)-1)/($N$1*$N$2)) -> 5440.6727 | N38: =M38-P38 -> 575.0024 | O38: =(N38/L38)*12 -> 0.0097494681 | P38: =L38*($K$1/12) -> 4865.6703 | Q38: =(P38/L38)*12 -> 0.0825 | R38: =R37+N38 -> 17041.134 | S38: =S37+P38 -> 162501.07 | T38: =L38-N38 -> 707158.87 | U38: =R38+S38 -> 179542.2 | W38: 33 | X38: 45839 | Y38: =AG37 -> 706931.18 | Z38: =Z37 -> 5313.923 | AA38: =Z38-AC38 -> 601.0485 | AB38: =(AA38/Y38)*12 -> 0.010202665 | AC38: =Y38*($X$1/12) -> 4712.8745 | AD38: =(AC38/Y38)*12 -> 0.08 | AE38: =AE37+AA38 -> 17869.867 | AF38: =AF37+AC38 -> 157489.59 | AG38: =Y38-AA38 -> 706330.13 | AH38: =AE38+AF38 -> 175359.46 | AJ38: 33 | AK38: 45839 | AL38: =AT37 -> 706095.55 | AM38: =AM37 -> 5188.2575 | AN38: =AM38-AP38 -> 628.05704 | AO38: =(AN38/AL38)*12 -> 0.010673746 | AP38: =AL38*($AK$1/12) -> 4560.2004 | AQ38: =(AP38/AL38)*12 -> 0.0775 | AR38: =AR37+AN38 -> 18732.504 | AS38: =AS37+AP38 -> 152479.99 | AT38: =AL38-AN38 -> 705467.5 | AU38: =AR38+AS38 -> 171212.5 | AW38: 33 | AX38: 45839 | AY38: =BG37 -> 705226.08 | AZ38: =AZ37 -> 5063.7115 | BA38: =AZ38-BC38 -> 656.04847 | BB38: =(BA38/AY38)*12 -> 0.011163203 | BC38: =AY38*($AX$1/12) -> 4407.663 | BD38: =(BC38/AY38)*12 -> 0.075 | BE38: =BE37+BA38 -> 19629.968 | BF38: =BF37+BC38 -> 147472.51 | BG38: =AY38-BA38 -> 704570.03 | BH38: =BE38+BF38 -> 167102.48 | BJ38: 33 | BK38: 45839 | BL38: =BT37 -> 704321.87 | BM38: =BM37 -> 4940.3206 | BN38: =BM38-BP38 -> 685.04267 | BO38: =(BN38/BL38)*12 -> 0.011671527 | BP38: =BL38*($BK$1/12) -> 4255.278 | BQ38: =(BP38/BL38)*12 -> 0.0725 | BR38: =BR37+BN38 -> 20563.175 | BS38: =BS37+BP38 -> 142467.41 | BT38: =BL38-BN38 -> 703636.83 | BU38: =BR38+BS38 -> 163030.58 | BW38: 33 | BX38: 45839 | BY38: =CG37 -> 703382.03 | BZ38: =BZ37 -> 4818.1207 | CA38: =BZ38-CC38 -> 715.05885 | CB38: =(CA38/BY38)*12 -> 0.012199212 | CC38: =BY38*($BX$1/12) -> 4103.0618 | CD38: =(CC38/BY38)*12 -> 0.07 | CE38: =CE37+CA38 -> 21533.032 | CF38: =CF37+CC38 -> 137464.95 | CG38: =BY38-CA38 -> 702666.97 | CH38: =CE38+CF38 -> 158997.98
J39: 34 | K39: 45870 | L39: =T38 -> 707158.87 | M39: =$L$6/((($N$2)-1)/($N$1*$N$2)) -> 5440.6727 | N39: =M39-P39 -> 578.95554 | O39: =(N39/L39)*12 -> 0.0098244777 | P39: =L39*($K$1/12) -> 4861.7172 | Q39: =(P39/L39)*12 -> 0.0825 | R39: =R38+N39 -> 17620.089 | S39: =S38+P39 -> 167362.78 | T39: =L39-N39 -> 706579.91 | U39: =R39+S39 -> 184982.87 | W39: 34 | X39: 45870 | Y39: =AG38 -> 706330.13 | Z39: =Z38 -> 5313.923 | AA39: =Z39-AC39 -> 605.05549 | AB39: =(AA39/Y39)*12 -> 0.010279423 | AC39: =Y39*($X$1/12) -> 4708.8676 | AD39: =(AC39/Y39)*12 -> 0.08 | AE39: =AE38+AA39 -> 18474.923 | AF39: =AF38+AC39 -> 162198.46 | AG39: =Y39-AA39 -> 705725.08 | AH39: =AE39+AF39 -> 180673.38 | AJ39: 34 | AK39: 45870 | AL39: =AT38 -> 705467.5 | AM39: =AM38 -> 5188.2575 | AN39: =AM39-AP39 -> 632.11324 | AO39: =(AN39/AL39)*12 -> 0.010752244 | AP39: =AL39*($AK$1/12) -> 4556.1442 | AQ39: =(AP39/AL39)*12 -> 0.0775 | AR39: =AR38+AN39 -> 19364.617 | AS39: =AS38+AP39 -> 157036.14 | AT39: =AL39-AN39 -> 704835.38 | AU39: =AR39+AS39 -> 176400.75 | AW39: 34 | AX39: 45870 | AY39: =BG38 -> 704570.03 | AZ39: =AZ38 -> 5063.7115 | BA39: =AZ39-BC39 -> 660.14877 | BB39: =(BA39/AY39)*12 -> 0.011243432 | BC39: =AY39*($AX$1/12) -> 4403.5627 | BD39: =(BC39/AY39)*12 -> 0.075 | BE39: =BE38+BA39 -> 20290.116 | BF39: =BF38+BC39 -> 151876.07 | BG39: =AY39-BA39 -> 703909.88 | BH39: =BE39+BF39 -> 172166.19 | BJ39: 34 | BK39: 45870 | BL39: =BT38 -> 703636.83 | BM39: =BM38 -> 4940.3206 | BN39: =BM39-BP39 -> 689.18147 | BO39: =(BN39/BL39)*12 -> 0.011753475 | BP39: =BL39*($BK$1/12) -> 4251.1392 | BQ39: =(BP39/BL39)*12 -> 0.0725 | BR39: =BR38+BN39 -> 21252.356 | BS39: =BS38+BP39 -> 146718.54 | BT39: =BL39-BN39 -> 702947.64 | BU39: =BR39+BS39 -> 167970.9 | BW39: 34 | BX39: 45870 | BY39: =CG38 -> 702666.97 | BZ39: =BZ38 -> 4818.1207 | CA39: =BZ39-CC39 -> 719.23002 | CB39: =(CA39/BY39)*12 -> 0.01228286 | CC39: =BY39*($BX$1/12) -> 4098.8906 | CD39: =(CC39/BY39)*12 -> 0.07 | CE39: =CE38+CA39 -> 22252.262 | CF39: =CF38+CC39 -> 141563.84 | CG39: =BY39-CA39 -> 701947.74 | CH39: =CE39+CF39 -> 163816.1
J40: 35 | K40: 45901 | L40: =T39 -> 706579.91 | M40: =$L$6/((($N$2)-1)/($N$1*$N$2)) -> 5440.6727 | N40: =M40-P40 -> 582.93586 | O40: =(N40/L40)*12 -> 0.0099001263 | P40: =L40*($K$1/12) -> 4857.7369 | Q40: =(P40/L40)*12 -> 0.0825 | R40: =R39+N40 -> 18203.025 | S40: =S39+P40 -> 172220.52 | T40: =L40-N40 -> 705996.97 | U40: =R40+S40 -> 190423.55 | W40: 35 | X40: 45901 | Y40: =AG39 -> 705725.08 | Z40: =Z39 -> 5313.923 | AA40: =Z40-AC40 -> 609.08919 | AB40: =(AA40/Y40)*12 -> 0.010356824 | AC40: =Y40*($X$1/12) -> 4704.8338 | AD40: =(AC40/Y40)*12 -> 0.08 | AE40: =AE39+AA40 -> 19084.012 | AF40: =AF39+AC40 -> 166903.29 | AG40: =Y40-AA40 -> 705115.99 | AH40: =AE40+AF40 -> 185987.31 | AJ40: 35 | AK40: 45901 | AL40: =AT39 -> 704835.38 | AM40: =AM39 -> 5188.2575 | AN40: =AM40-AP40 -> 636.19563 | AO40: =(AN40/AL40)*12 -> 0.010831391 | AP40: =AL40*($AK$1/12) -> 4552.0618 | AQ40: =(AP40/AL40)*12 -> 0.0775 | AR40: =AR39+AN40 -> 20000.813 | AS40: =AS39+AP40 -> 161588.2 | AT40: =AL40-AN40 -> 704199.19 | AU40: =AR40+AS40 -> 181589.01 | AW40: 35 | AX40: 45901 | AY40: =BG39 -> 703909.88 | AZ40: =AZ39 -> 5063.7115 | BA40: =AZ40-BC40 -> 664.2747 | BB40: =(BA40/AY40)*12 -> 0.011324314 | BC40: =AY40*($AX$1/12) -> 4399.4368 | BD40: =(BC40/AY40)*12 -> 0.075 | BE40: =BE39+BA40 -> 20954.391 | BF40: =BF39+BC40 -> 156275.51 | BG40: =AY40-BA40 -> 703245.61 | BH40: =BE40+BF40 -> 177229.9 | BJ40: 35 | BK40: 45901 | BL40: =BT39 -> 702947.64 | BM40: =BM39 -> 4940.3206 | BN40: =BM40-BP40 -> 693.34527 | BO40: =(BN40/BL40)*12 -> 0.011836078 | BP40: =BL40*($BK$1/12) -> 4246.9753 | BQ40: =(BP40/BL40)*12 -> 0.0725 | BR40: =BR39+BN40 -> 21945.702 | BS40: =BS39+BP40 -> 150965.52 | BT40: =BL40-BN40 -> 702254.3 | BU40: =BR40+BS40 -> 172911.22 | BW40: 35 | BX40: 45901 | BY40: =CG39 -> 701947.74 | BZ40: =BZ39 -> 4818.1207 | CA40: =BZ40-CC40 -> 723.42553 | CB40: =(CA40/BY40)*12 -> 0.012367169 | CC40: =BY40*($BX$1/12) -> 4094.6951 | CD40: =(CC40/BY40)*12 -> 0.07 | CE40: =CE39+CA40 -> 22975.688 | CF40: =CF39+CC40 -> 145658.54 | CG40: =BY40-CA40 -> 701224.31 | CH40: =CE40+CF40 -> 168634.22
J41: 36 | K41: 45931 | L41: =T40 -> 705996.97 | M41: =$L$6/((($N$2)-1)/($N$1*$N$2)) -> 5440.6727 | N41: =M41-P41 -> 586.94355 | O41: =(N41/L41)*12 -> 0.0099764203 | P41: =L41*($K$1/12) -> 4853.7292 | Q41: =(P41/L41)*12 -> 0.0825 | R41: =R40+N41 -> 18789.969 | S41: =S40+P41 -> 177074.25 | T41: =L41-N41 -> 705410.03 | U41: =R41+S41 -> 195864.22 | W41: 36 | X41: 45931 | Y41: =AG40 -> 705115.99 | Z41: =Z40 -> 5313.923 | AA41: =Z41-AC41 -> 613.14979 | AB41: =(AA41/Y41)*12 -> 0.010434875 | AC41: =Y41*($X$1/12) -> 4700.7733 | AD41: =(AC41/Y41)*12 -> 0.08 | AE41: =AE40+AA41 -> 19697.162 | AF41: =AF40+AC41 -> 171604.07 | AG41: =Y41-AA41 -> 704502.84 | AH41: =AE41+AF41 -> 191301.23 | AJ41: 36 | AK41: 45931 | AL41: =AT40 -> 704199.19 | AM41: =AM40 -> 5188.2575 | AN41: =AM41-AP41 -> 640.3044 | AO41: =(AN41/AL41)*12 -> 0.010911192 | AP41: =AL41*($AK$1/12) -> 4547.9531 | AQ41: =(AP41/AL41)*12 -> 0.0775 | AR41: =AR40+AN41 -> 20641.117 | AS41: =AS40+AP41 -> 166136.15 | AT41: =AL41-AN41 -> 703558.88 | AU41: =AR41+AS41 -> 186777.27 | AW41: 36 | AX41: 45931 | AY41: =BG40 -> 703245.61 | AZ41: =AZ40 -> 5063.7115 | BA41: =AZ41-BC41 -> 668.42642 | BB41: =(BA41/AY41)*12 -> 0.011405854 | BC41: =AY41*($AX$1/12) -> 4395.2851 | BD41: =(BC41/AY41)*12 -> 0.075 | BE41: =BE40+BA41 -> 21622.818 | BF41: =BF40+BC41 -> 160670.8 | BG41: =AY41-BA41 -> 702577.18 | BH41: =BE41+BF41 -> 182293.61 | BJ41: 36 | BK41: 45931 | BL41: =BT40 -> 702254.3 | BM41: =BM40 -> 4940.3206 | BN41: =BM41-BP41 -> 697.53423 | BO41: =(BN41/BL41)*12 -> 0.011919344 | BP41: =BL41*($BK$1/12) -> 4242.7864 | BQ41: =(BP41/BL41)*12 -> 0.0725 | BR41: =BR40+BN41 -> 22643.236 | BS41: =BS40+BP41 -> 155208.31 | BT41: =BL41-BN41 -> 701556.76 | BU41: =BR41+BS41 -> 177851.54 | BW41: 36 | BX41: 45931 | BY41: =CG40 -> 701224.31 | BZ41: =BZ40 -> 4818.1207 | CA41: =BZ41-CC41 -> 727.64551 | CB41: =(CA41/BY41)*12 -> 0.012452144 | CC41: =BY41*($BX$1/12) -> 4090.4752 | CD41: =(CC41/BY41)*12 -> 0.07 | CE41: =CE40+CA41 -> 23703.333 | CF41: =CF40+CC41 -> 149749.01 | CG41: =BY41-CA41 -> 700496.67 | CH41: =CE41+CF41 -> 173452.34
J42: 37 | K42: 45962 | L42: =T41 -> 705410.03 | M42: =$L$6/((($N$2)-1)/($N$1*$N$2)) -> 5440.6727 | N42: =M42-P42 -> 590.97878 | O42: =(N42/L42)*12 -> 0.010053366 | P42: =L42*($K$1/12) -> 4849.694 | Q42: =(P42/L42)*12 -> 0.0825 | R42: =R41+N42 -> 19380.948 | S42: =S41+P42 -> 181923.94 | T42: =L42-N42 -> 704819.05 | U42: =R42+S42 -> 201304.89 | W42: 37 | X42: 45962 | Y42: =AG41 -> 704502.84 | Z42: =Z41 -> 5313.923 | AA42: =Z42-AC42 -> 617.23745 | AB42: =(AA42/Y42)*12 -> 0.010513584 | AC42: =Y42*($X$1/12) -> 4696.6856 | AD42: =(AC42/Y42)*12 -> 0.08 | AE42: =AE41+AA42 -> 20314.399 | AF42: =AF41+AC42 -> 176300.75 | AG42: =Y42-AA42 -> 703885.6 | AH42: =AE42+AF42 -> 196615.15 | AJ42: 37 | AK42: 45962 | AL42: =AT41 -> 703558.88 | AM42: =AM41 -> 5188.2575 | AN42: =AM42-AP42 -> 644.4397 | AO42: =(AN42/AL42)*12 -> 0.010991655 | AP42: =AL42*($AK$1/12) -> 4543.8178 | AQ42: =(AP42/AL42)*12 -> 0.0775 | AR42: =AR41+AN42 -> 21285.557 | AS42: =AS41+AP42 -> 170679.97 | AT42: =AL42-AN42 -> 702914.44 | AU42: =AR42+AS42 -> 191965.53 | AW42: 37 | AX42: 45962 | AY42: =BG41 -> 702577.18 | AZ42: =AZ41 -> 5063.7115 | BA42: =AZ42-BC42 -> 672.60408 | BB42: =(BA42/AY42)*12 -> 0.01148806 | BC42: =AY42*($AX$1/12) -> 4391.1074 | BD42: =(BC42/AY42)*12 -> 0.075 | BE42: =BE41+BA42 -> 22295.422 | BF42: =BF41+BC42 -> 165061.9 | BG42: =AY42-BA42 -> 701904.58 | BH42: =BE42+BF42 -> 187357.32 | BJ42: 37 | BK42: 45962 | BL42: =BT41 -> 701556.76 | BM42: =BM41 -> 4940.3206 | BN42: =BM42-BP42 -> 701.7485 | BO42: =(BN42/BL42)*12 -> 0.01200328 | BP42: =BL42*($BK$1/12) -> 4238.5721 | BQ42: =(BP42/BL42)*12 -> 0.0725 | BR42: =BR41+BN42 -> 23344.984 | BS42: =BS41+BP42 -> 159446.88 | BT42: =BL42-BN42 -> 700855.02 | BU42: =BR42+BS42 -> 182791.86 | BW42: 37 | BX42: 45962 | BY42: =CG41 -> 700496.67 | BZ42: =BZ41 -> 4818.1207 | CA42: =BZ42-CC42 -> 731.89011 | CB42: =(CA42/BY42)*12 -> 0.012537792 | CC42: =BY42*($BX$1/12) -> 4086.2306 | CD42: =(CC42/BY42)*12 -> 0.07 | CE42: =CE41+CA42 -> 24435.223 | CF42: =CF41+CC42 -> 153835.24 | CG42: =BY42-CA42 -> 699764.78 | CH42: =CE42+CF42 -> 178270.46
J43: 38 | K43: 45992 | L43: =T42 -> 704819.05 | M43: =$L$6/((($N$2)-1)/($N$1*$N$2)) -> 5440.6727 | N43: =M43-P43 -> 595.04176 | O43: =(N43/L43)*12 -> 0.010130971 | P43: =L43*($K$1/12) -> 4845.631 | Q43: =(P43/L43)*12 -> 0.0825 | R43: =R42+N43 -> 19975.989 | S43: =S42+P43 -> 186769.57 | T43: =L43-N43 -> 704224.01 | U43: =R43+S43 -> 206745.56 | W43: 38 | X43: 45992 | Y43: =AG42 -> 703885.6 | Z43: =Z42 -> 5313.923 | AA43: =Z43-AC43 -> 621.35237 | AB43: =(AA43/Y43)*12 -> 0.010592955 | AC43: =Y43*($X$1/12) -> 4692.5707 | AD43: =(AC43/Y43)*12 -> 0.08 | AE43: =AE42+AA43 -> 20935.751 | AF43: =AF42+AC43 -> 180993.32 | AG43: =Y43-AA43 -> 703264.25 | AH43: =AE43+AF43 -> 201929.08 | AJ43: 38 | AK43: 45992 | AL43: =AT42 -> 702914.44 | AM43: =AM42 -> 5188.2575 | AN43: =AM43-AP43 -> 648.6017 | AO43: =(AN43/AL43)*12 -> 0.011072785 | AP43: =AL43*($AK$1/12) -> 4539.6558 | AQ43: =(AP43/AL43)*12 -> 0.0775 | AR43: =AR42+AN43 -> 21934.159 | AS43: =AS42+AP43 -> 175219.63 | AT43: =AL43-AN43 -> 702265.84 | AU43: =AR43+AS43 -> 197153.78 | AW43: 38 | AX43: 45992 | AY43: =BG42 -> 701904.58 | AZ43: =AZ42 -> 5063.7115 | BA43: =AZ43-BC43 -> 676.80786 | BB43: =(BA43/AY43)*12 -> 0.011570938 | BC43: =AY43*($AX$1/12) -> 4386.9036 | BD43: =(BC43/AY43)*12 -> 0.075 | BE43: =BE42+BA43 -> 22972.23 | BF43: =BF42+BC43 -> 169448.81 | BG43: =AY43-BA43 -> 701227.77 | BH43: =BE43+BF43 -> 192421.04 | BJ43: 38 | BK43: 45992 | BL43: =BT42 -> 700855.02 | BM43: =BM42 -> 4940.3206 | BN43: =BM43-BP43 -> 705.98823 | BO43: =(BN43/BL43)*12 -> 0.012087891 | BP43: =BL43*($BK$1/12) -> 4234.3324 | BQ43: =(BP43/BL43)*12 -> 0.0725 | BR43: =BR42+BN43 -> 24050.973 | BS43: =BS42+BP43 -> 163681.21 | BT43: =BL43-BN43 -> 700149.03 | BU43: =BR43+BS43 -> 187732.18 | BW43: 38 | BX43: 45992 | BY43: =CG42 -> 699764.78 | BZ43: =BZ42 -> 4818.1207 | CA43: =BZ43-CC43 -> 736.15947 | CB43: =(CA43/BY43)*12 -> 0.012624119 | CC43: =BY43*($BX$1/12) -> 4081.9612 | CD43: =(CC43/BY43)*12 -> 0.07 | CE43: =CE42+CA43 -> 25171.383 | CF43: =CF42+CC43 -> 157917.2 | CG43: =BY43-CA43 -> 699028.62 | CH43: =CE43+CF43 -> 183088.59
J44: 39 | K44: 46023 | L44: =T43 -> 704224.01 | M44: =$L$6/((($N$2)-1)/($N$1*$N$2)) -> 5440.6727 | N44: =M44-P44 -> 599.13267 | O44: =(N44/L44)*12 -> 0.01020924 | P44: =L44*($K$1/12) -> 4841.5401 | Q44: =(P44/L44)*12 -> 0.0825 | R44: =R43+N44 -> 20575.122 | S44: =S43+P44 -> 191611.12 | T44: =L44-N44 -> 703624.88 | U44: =R44+S44 -> 212186.24 | W44: 39 | X44: 46023 | Y44: =AG43 -> 703264.25 | Z44: =Z43 -> 5313.923 | AA44: =Z44-AC44 -> 625.49472 | AB44: =(AA44/Y44)*12 -> 0.010672996 | AC44: =Y44*($X$1/12) -> 4688.4283 | AD44: =(AC44/Y44)*12 -> 0.08 | AE44: =AE43+AA44 -> 21561.246 | AF44: =AF43+AC44 -> 185681.75 | AG44: =Y44-AA44 -> 702638.75 | AH44: =AE44+AF44 -> 207243 | AJ44: 39 | AK44: 46023 | AL44: =AT43 -> 702265.84 | AM44: =AM43 -> 5188.2575 | AN44: =AM44-AP44 -> 652.79059 | AO44: =(AN44/AL44)*12 -> 0.011154589 | AP44: =AL44*($AK$1/12) -> 4535.4669 | AQ44: =(AP44/AL44)*12 -> 0.0775 | AR44: =AR43+AN44 -> 22586.949 | AS44: =AS43+AP44 -> 179755.09 | AT44: =AL44-AN44 -> 701613.05 | AU44: =AR44+AS44 -> 202342.04 | AW44: 39 | AX44: 46023 | AY44: =BG43 -> 701227.77 | AZ44: =AZ43 -> 5063.7115 | BA44: =AZ44-BC44 -> 681.03791 | BB44: =(BA44/AY44)*12 -> 0.011654494 | BC44: =AY44*($AX$1/12) -> 4382.6736 | BD44: =(BC44/AY44)*12 -> 0.075 | BE44: =BE43+BA44 -> 23653.267 | BF44: =BF43+BC44 -> 173831.48 | BG44: =AY44-BA44 -> 700546.73 | BH44: =BE44+BF44 -> 197484.75 | BJ44: 39 | BK44: 46023 | BL44: =BT43 -> 700149.03 | BM44: =BM43 -> 4940.3206 | BN44: =BM44-BP44 -> 710.25358 | BO44: =(BN44/BL44)*12 -> 0.012173184 | BP44: =BL44*($BK$1/12) -> 4230.067 | BQ44: =(BP44/BL44)*12 -> 0.0725 | BR44: =BR43+BN44 -> 24761.226 | BS44: =BS43+BP44 -> 167911.28 | BT44: =BL44-BN44 -> 699438.77 | BU44: =BR44+BS44 -> 192672.5 | BW44: 39 | BX44: 46023 | BY44: =CG43 -> 699028.62 | BZ44: =BZ43 -> 4818.1207 | CA44: =BZ44-CC44 -> 740.45374 | CB44: =(CA44/BY44)*12 -> 0.012711132 | CC44: =BY44*($BX$1/12) -> 4077.6669 | CD44: =(CC44/BY44)*12 -> 0.07 | CE44: =CE43+CA44 -> 25911.836 | CF44: =CF43+CC44 -> 161994.87 | CG44: =BY44-CA44 -> 698288.16 | CH44: =CE44+CF44 -> 187906.71
J45: 40 | K45: 46054 | L45: =T44 -> 703624.88 | M45: =$L$6/((($N$2)-1)/($N$1*$N$2)) -> 5440.6727 | N45: =M45-P45 -> 603.25171 | O45: =(N45/L45)*12 -> 0.010288182 | P45: =L45*($K$1/12) -> 4837.421 | Q45: =(P45/L45)*12 -> 0.0825 | R45: =R44+N45 -> 21178.374 | S45: =S44+P45 -> 196448.54 | T45: =L45-N45 -> 703021.63 | U45: =R45+S45 -> 217626.91 | W45: 40 | X45: 46054 | Y45: =AG44 -> 702638.75 | Z45: =Z44 -> 5313.923 | AA45: =Z45-AC45 -> 629.66469 | AB45: =(AA45/Y45)*12 -> 0.010753714 | AC45: =Y45*($X$1/12) -> 4684.2584 | AD45: =(AC45/Y45)*12 -> 0.08 | AE45: =AE44+AA45 -> 22190.911 | AF45: =AF44+AC45 -> 190366.01 | AG45: =Y45-AA45 -> 702009.09 | AH45: =AE45+AF45 -> 212556.92 | AJ45: 40 | AK45: 46054 | AL45: =AT44 -> 701613.05 | AM45: =AM44 -> 5188.2575 | AN45: =AM45-AP45 -> 657.00653 | AO45: =(AN45/AL45)*12 -> 0.011237075 | AP45: =AL45*($AK$1/12) -> 4531.251 | AQ45: =(AP45/AL45)*12 -> 0.0775 | AR45: =AR44+AN45 -> 23243.956 | AS45: =AS44+AP45 -> 184286.34 | AT45: =AL45-AN45 -> 700956.04 | AU45: =AR45+AS45 -> 207530.3 | AW45: 40 | AX45: 46054 | AY45: =BG44 -> 700546.73 | AZ45: =AZ44 -> 5063.7115 | BA45: =AZ45-BC45 -> 685.29439 | BB45: =(BA45/AY45)*12 -> 0.011738735 | BC45: =AY45*($AX$1/12) -> 4378.4171 | BD45: =(BC45/AY45)*12 -> 0.075 | BE45: =BE44+BA45 -> 24338.562 | BF45: =BF44+BC45 -> 178209.9 | BG45: =AY45-BA45 -> 699861.44 | BH45: =BE45+BF45 -> 202548.46 | BJ45: 40 | BK45: 46054 | BL45: =BT44 -> 699438.77 | BM45: =BM44 -> 4940.3206 | BN45: =BM45-BP45 -> 714.54469 | BO45: =(BN45/BL45)*12 -> 0.012259166 | BP45: =BL45*($BK$1/12) -> 4225.7759 | BQ45: =(BP45/BL45)*12 -> 0.0725 | BR45: =BR44+BN45 -> 25475.771 | BS45: =BS44+BP45 -> 172137.05 | BT45: =BL45-BN45 -> 698724.23 | BU45: =BR45+BS45 -> 197612.82 | BW45: 40 | BX45: 46054 | BY45: =CG44 -> 698288.16 | BZ45: =BZ44 -> 4818.1207 | CA45: =BZ45-CC45 -> 744.77305 | CB45: =(CA45/BY45)*12 -> 0.012798837 | CC45: =BY45*($BX$1/12) -> 4073.3476 | CD45: =(CC45/BY45)*12 -> 0.07 | CE45: =CE44+CA45 -> 26656.61 | CF45: =CF44+CC45 -> 166068.22 | CG45: =BY45-CA45 -> 697543.39 | CH45: =CE45+CF45 -> 192724.83
